{
  "type": "Feature",
  "properties": {
    "gn:admin1_code":"5.0",
    "gn:admin2_code":"42250.0",
    "gn:asciiname":"Blackfellows Caves",
    "gn:country_code":"AU",
    "gn:dem":5,
    "gn:feature_class":"P",
    "gn:feature_code":"PPL",
    "gn:name":"Blackfellows Caves",
    "gn:population":0,
    "gn:timezone":"Australia/Adelaide",
    "iso:country":"AU",
    "name:eng_x_preferred":[
        "Blackfellows Caves"
    ],
    "wof:name":"Blackfellows Caves",
    "wof:placetype":"locality"
},
  "geometry": {"coordinates":[140.46850000000001,-37.94667000000001],"type":"Point"}
}