{
  "type": "Feature",
  "properties": {
    "gn:admin1_code":"5.0",
    "gn:admin2_code":"47490.0",
    "gn:asciiname":"Bairds Bay",
    "gn:country_code":"AU",
    "gn:dem":6,
    "gn:feature_class":"P",
    "gn:feature_code":"PPL",
    "gn:name":"Bairds Bay",
    "gn:population":0,
    "gn:timezone":"Australia/Adelaide",
    "iso:country":"AU",
    "name:eng_x_preferred":[
        "Bairds Bay"
    ],
    "name:und_x_variant":[
        "Baird Bay"
    ],
    "wof:name":"Bairds Bay",
    "wof:placetype":"locality"
},
  "geometry": {"coordinates":[134.36382,-33.15018],"type":"Point"}
}