{
  "type": "Feature",
  "properties": {
    "gn:admin1_code":"7",
    "gn:admin2_code":"25620",
    "gn:asciiname":"Upper Plenty",
    "gn:country_code":"AU",
    "gn:dem":526,
    "gn:feature_class":"P",
    "gn:feature_code":"PPL",
    "gn:name":"Upper Plenty",
    "gn:population":0,
    "gn:timezone":"Australia/Melbourne",
    "iso:country":"AU",
    "wof:name":"Upper Plenty",
    "wof:placetype":"locality"
},
  "geometry": {"coordinates":[145.73333,-37.43333],"type":"Point"}
}