{
  "type": "Feature",
  "properties": {
    "gn:admin1_code":"4.0",
    "gn:admin2_code":"32270.0",
    "gn:asciiname":"Karin",
    "gn:country_code":"AU",
    "gn:dem":257,
    "gn:feature_class":"P",
    "gn:feature_code":"PPL",
    "gn:name":"Karin",
    "gn:population":0,
    "gn:timezone":"Australia/Brisbane",
    "iso:country":"AU",
    "name:eng_x_preferred":[
        "Karin"
    ],
    "wof:name":"Karin",
    "wof:placetype":"locality"
},
  "geometry": {"coordinates":[147.77316999999999,-22.90562000000001],"type":"Point"}
}