{
  "type": "Feature",
  "properties": {
    "gn:admin1_code":"4.0",
    "gn:admin2_code":"32270.0",
    "gn:asciiname":"Karin",
    "gn:country_code":"AU",
    "gn:dem":257,
    "gn:feature_class":"P",
    "gn:feature_code":"PPL",
    "gn:name":"Karin",
    "gn:population":0,
    "gn:timezone":"Australia/Brisbane",
    "iso:country":"AU",
    "name:bos_x_preferred":[
        "Karin"
    ],
    "name:ceb_x_preferred":[
        "Karin"
    ],
    "name:deu_x_preferred":[
        "Karin"
    ],
    "name:eng_x_preferred":[
        "Karin"
    ],
    "name:fra_x_preferred":[
        "Karin"
    ],
    "name:hrv_x_preferred":[
        "Karin"
    ],
    "name:ita_x_preferred":[
        "Karin"
    ],
    "name:jpn_x_preferred":[
        "\u30ab\u30ea\u30f3"
    ],
    "name:kor_x_preferred":[
        "\uce74\ub9b0"
    ],
    "name:nld_x_preferred":[
        "Karin"
    ],
    "name:pol_x_preferred":[
        "Karin"
    ],
    "name:rus_x_preferred":[
        "\u041a\u0430\u0440\u0438\u043d"
    ],
    "name:spa_x_preferred":[
        "Karin"
    ],
    "name:srp_x_preferred":[
        "\u041a\u0430\u0440\u0438\u043d"
    ],
    "name:ukr_x_preferred":[
        "\u041a\u0430\u0440\u0456\u043d"
    ],
    "name:wuu_x_preferred":[
        "\u6b27\u6942"
    ],
    "wof:name":"Karin",
    "wof:placetype":"locality"
},
  "geometry": {"coordinates":[147.77316999999999,-22.90562000000001],"type":"Point"}
}