{
  "type": "Feature",
  "properties": {
    "gn:admin1_code":"8",
    "gn:admin2_code":"51960",
    "gn:asciiname":"Kurrawang",
    "gn:country_code":"AU",
    "gn:dem":364,
    "gn:feature_class":"P",
    "gn:feature_code":"PPL",
    "gn:name":"Kurrawang",
    "gn:population":0,
    "gn:timezone":"Australia/Perth",
    "iso:country":"AU",
    "name:eng_x_preferred":[
        "Kurrawang"
    ],
    "wof:name":"Kurrawang",
    "wof:placetype":"locality"
},
  "geometry": {"coordinates":[121.32503,-30.82485],"type":"Point"}
}