{
  "type": "Feature",
  "properties": {
    "gn:admin1_code":"2.0",
    "gn:admin2_code":"10550.0",
    "gn:asciiname":"Robs Parlor",
    "gn:country_code":"AU",
    "gn:dem":267,
    "gn:feature_class":"P",
    "gn:feature_code":"PPL",
    "gn:name":"Robs Parlor",
    "gn:population":0,
    "gn:timezone":"Australia/Sydney",
    "iso:country":"AU",
    "name:eng_x_preferred":[
        "Robs Parlor"
    ],
    "wof:name":"Robs Parlor",
    "wof:placetype":"locality"
},
  "geometry": {"coordinates":[149.73164,-36.33397],"type":"Point"}
}