{
  "type": "Feature",
  "properties": {
    "gn:admin1_code":"2.0",
    "gn:admin2_code":"11000.0",
    "gn:asciiname":"Wenonah",
    "gn:country_code":"AU",
    "gn:dem":807,
    "gn:feature_class":"P",
    "gn:feature_code":"PPL",
    "gn:name":"Wenonah",
    "gn:population":0,
    "gn:timezone":"Australia/Sydney",
    "iso:country":"AU",
    "name:deu_x_preferred":[
        "Wenonah"
    ],
    "name:eng_x_preferred":[
        "Wenonah"
    ],
    "name:ita_x_preferred":[
        "Wenonah"
    ],
    "name:nld_x_preferred":[
        "Wenonah"
    ],
    "name:por_x_preferred":[
        "Wenonah"
    ],
    "name:srp_x_preferred":[
        "\u0412\u0435\u043d\u043e\u043d\u0430"
    ],
    "name:vol_x_preferred":[
        "Wenonah"
    ],
    "wof:name":"Wenonah",
    "wof:placetype":"locality"
},
  "geometry": {"coordinates":[148.96806999999995,-37.08469],"type":"Point"}
}