{
  "type": "Feature",
  "properties": {
    "iso:country":"AU",
    "name:eng_x_preferred":[
        "Redbank"
    ],
    "name:ita_x_preferred":[
        "Redbank"
    ],
    "name:kor_x_preferred":[
        "\ub808\ub4dc\ubc45\ud06c"
    ],
    "name:unk_x_variant":[
        "Redbank"
    ],
    "qs:gn_adm0_cc":"AU",
    "qs:gn_local":2063042,
    "qs:gn_nam_loc":"port hedland",
    "qs:gn_namadm1":"08",
    "qs:local_max":93,
    "qs:local_sum":113,
    "qs:localhoods":2,
    "qs:name":"Redbank",
    "qs:name_adm0":"Australia",
    "qs:name_adm1":"Western Australia",
    "qs:name_adm2":"Port Hedland",
    "qs:name_local":"Port Hedland",
    "qs:photo_max":11,
    "qs:photo_sum":20,
    "qs:placetype":"Suburb",
    "qs:quad_count":7,
    "qs:woe_adm0":23424748,
    "qs:woe_adm1":2344706,
    "qs:woe_adm2":55864371,
    "qs:woe_lau":0,
    "qs:woe_local":1105126,
    "qs:woe_ver":"7.10.0",
    "wd:wordcount":57,
    "wof:lang":[
        "eng"
    ],
    "wof:name":"Redbank",
    "wof:placetype":"neighbourhood"
},
  "geometry": {"coordinates":[118.63284299999999,-20.340249],"type":"Point"}
}