{
  "type": "Feature",
  "properties": {
    "iso:country":"AU",
    "name:ara_x_preferred":[
        "\u0645\u0627\u0648\u0646\u062a \u0645\u0627\u063a\u0646\u064a\u062a"
    ],
    "name:dut_x_preferred":[
        "Mount Magnet"
    ],
    "name:eng_x_preferred":[
        "Mount Magnet"
    ],
    "name:fre_x_preferred":[
        "Mount Magnet"
    ],
    "name:ger_x_preferred":[
        "Mount Magnet"
    ],
    "name:ita_x_preferred":[
        "Mount Magnet"
    ],
    "name:por_x_preferred":[
        "Mount Magnet"
    ],
    "name:swe_x_preferred":[
        "Mount Magnet"
    ],
    "ne:ADM0CAP":0.0,
    "ne:ADM0NAME":"Australia",
    "ne:ADM0_A3":"AUS",
    "ne:ADM1NAME":"Western Australia",
    "ne:ADMIN1_COD":0,
    "ne:CAPALT":0,
    "ne:CHANGED":0,
    "ne:CHECKME":0,
    "ne:COMPARE":0,
    "ne:DIFFASCII":0,
    "ne:ELEVATION":0.0,
    "ne:FEATURECLA":"Populated place",
    "ne:GEONAMEID":-1,
    "ne:GEONAMESNO":"No GeoNames match due to small population, not in GeoNames, or poor NEV placement.",
    "ne:GN_POP":0,
    "ne:GTOPO30":0.0,
    "ne:ISO_A2":"AU",
    "ne:LABELRANK":3,
    "ne:LATITUDE":-28.066208,
    "ne:LONGITUDE":117.816674,
    "ne:LS_MATCH":0,
    "ne:LS_NAME":"Mount Magnet",
    "ne:MAX_AREAKM":0.0,
    "ne:MAX_AREAMI":0.0,
    "ne:MAX_BBXMAX":0.0,
    "ne:MAX_BBXMIN":0.0,
    "ne:MAX_BBYMAX":0.0,
    "ne:MAX_BBYMIN":0.0,
    "ne:MAX_NATSCA":0.0,
    "ne:MAX_PERKM":0.0,
    "ne:MAX_PERMI":0.0,
    "ne:MAX_POP10":0,
    "ne:MAX_POP20":0,
    "ne:MAX_POP300":0,
    "ne:MAX_POP310":0,
    "ne:MAX_POP50":0,
    "ne:MEAN_BBXC":0.0,
    "ne:MEAN_BBYC":0.0,
    "ne:MEGACITY":0,
    "ne:MIN_AREAKM":0.0,
    "ne:MIN_AREAMI":0.0,
    "ne:MIN_BBXMAX":0.0,
    "ne:MIN_BBXMIN":0.0,
    "ne:MIN_BBYMAX":0.0,
    "ne:MIN_BBYMIN":0.0,
    "ne:MIN_PERKM":0.0,
    "ne:MIN_PERMI":0.0,
    "ne:NAME":"Mount Magnet",
    "ne:NAMEASCII":"Mount Magnet",
    "ne:NAMEDIFF":0,
    "ne:NATSCALE":20,
    "ne:POP1950":0,
    "ne:POP1955":0,
    "ne:POP1960":0,
    "ne:POP1965":0,
    "ne:POP1970":0,
    "ne:POP1975":0,
    "ne:POP1980":0,
    "ne:POP1985":0,
    "ne:POP1990":0,
    "ne:POP1995":0,
    "ne:POP2000":0,
    "ne:POP2005":0,
    "ne:POP2010":0,
    "ne:POP2015":0,
    "ne:POP2020":0,
    "ne:POP2025":0,
    "ne:POP2050":0,
    "ne:POP_MAX":424,
    "ne:POP_MIN":424,
    "ne:POP_OTHER":0,
    "ne:RANK_MAX":2,
    "ne:RANK_MIN":2,
    "ne:SCALERANK":7,
    "ne:SOV0NAME":"Australia",
    "ne:SOV_A3":"AUS",
    "ne:UN_FID":0,
    "ne:UN_LAT":0.0,
    "ne:UN_LONG":0.0,
    "ne:WORLDCITY":0,
    "ne:min_zoom":6.7,
    "wof:name":"Mount Magnet",
    "wof:placetype":"locality"
},
  "geometry": {"coordinates":[117.81667394925194,-28.06620807008284],"type":"Point"}
}