{
  "type": "Feature",
  "properties": {
    "gn:admin1_code":"8",
    "gn:admin2_code":"55880",
    "gn:asciiname":"Welbungin",
    "gn:country_code":"AU",
    "gn:dem":348,
    "gn:feature_class":"P",
    "gn:feature_code":"PPL",
    "gn:name":"Welbungin",
    "gn:population":0,
    "gn:timezone":"Australia/Perth",
    "iso:country":"AU",
    "name:eng_x_preferred":[
        "Welbungin"
    ],
    "wof:name":"Welbungin",
    "wof:placetype":"locality"
},
  "geometry": {"coordinates":[117.98865000000001,-30.82853],"type":"Point"}
}