{
  "type": "Feature",
  "properties": {
    "iso:country":"AU",
    "name:ceb_x_preferred":[
        "Miles Airport"
    ],
    "name:eng_x_preferred":[
        "Miles Airport"
    ],
    "name:jpn_x_preferred":[
        "\u30de\u30a4\u30eb\u30ba\u7a7a\u6e2f"
    ],
    "name:ron_x_preferred":[
        "Aeroportul Miles"
    ],
    "name:swe_x_preferred":[
        "Miles Airport"
    ],
    "name:zho_x_preferred":[
        "Miles\u6a5f\u5834"
    ],
    "oa:elevation_ft":"304",
    "oa:type":"small_airport",
    "woe:hierarchy":{
        "country_id":23424748,
        "county_id":56072966,
        "planet_id":1,
        "state_id":2344702
    },
    "wof:name":"Miles Aerodrome",
    "wof:placetype":"campus"
},
  "geometry": {"coordinates":[150.16499999999999,-26.80916667],"type":"Point"}
}