{
  "type": "Feature",
  "properties": {
    "gn:admin1_code":"4",
    "gn:admin2_code":"35800",
    "gn:asciiname":"Tego",
    "gn:country_code":"AU",
    "gn:dem":141,
    "gn:feature_class":"P",
    "gn:feature_code":"PPL",
    "gn:name":"Tego",
    "gn:population":0,
    "gn:timezone":"Australia/Brisbane",
    "iso:country":"AU",
    "wof:name":"Tego",
    "wof:placetype":"locality"
},
  "geometry": {"coordinates":[146.78333000000001,-28.85],"type":"Point"}
}