{
  "type": "Feature",
  "properties": {
    "gn:country":"AU",
    "gn:fcode":"PPL",
    "gn:population":114,
    "iso:country":"AU",
    "name:ceb_x_preferred":[
        "Cranbrook"
    ],
    "name:deu_x_preferred":[
        "Cranbrook"
    ],
    "name:fra_x_preferred":[
        "Cranbrook"
    ],
    "name:heb_x_preferred":[
        "\u05e7\u05e8\u05d0\u05e0\u05d1\u05e8\u05d5\u05e7"
    ],
    "name:hun_x_preferred":[
        "Cranbrook"
    ],
    "name:ita_x_preferred":[
        "Cranbrook"
    ],
    "name:nld_x_preferred":[
        "Cranbrook"
    ],
    "name:pol_x_preferred":[
        "Cranbrook"
    ],
    "name:spa_x_preferred":[
        "Cranbrook"
    ],
    "name:swe_x_preferred":[
        "Cranbrook"
    ],
    "name:vol_x_preferred":[
        "Cranbrook"
    ],
    "qs_pg:aaroncc":"AU",
    "qs_pg:gn_country":"AU",
    "qs_pg:gn_fcode":"PPL",
    "qs_pg:gn_pop":114,
    "qs_pg:name":"Cranbrook",
    "qs_pg:name_adm0":"Australia",
    "qs_pg:name_adm1":"Tasmania",
    "qs_pg:photos":31,
    "qs_pg:photos_1k":6,
    "qs_pg:photos_9k":1,
    "qs_pg:photos_9r":2,
    "qs_pg:photos_all":31,
    "qs_pg:photos_sr":2,
    "qs_pg:pop_sr":1,
    "qs_pg:qs_pg_placetype":"locality",
    "qs_pg:qs_pg_placetype_gp":"Town",
    "qs_pg:woe_adm0":23424748,
    "woe:adm0_id":23424748,
    "woe:name_adm0":"Australia",
    "woe:name_adm1":"Tasmania",
    "woe:placetype":"Town",
    "wof:name":"Cranbrook",
    "wof:placetype":"locality",
    "wof:population":114
},
  "geometry": {"coordinates":[148.07639,-42.00806],"type":"Point"}
}