{
  "type": "Feature",
  "properties": {
    "iso:country":"AU",
    "name:eng_x_preferred":[
        "Bakery Hill"
    ],
    "qs:gn_adm0_cc":"AU",
    "qs:gn_fcode":"PPLX",
    "qs:gn_local":2177091,
    "qs:gn_nam_loc":"ballarat",
    "qs:gn_namadm1":"07",
    "qs:gn_name":"Bakery Hill",
    "qs:local_max":2722,
    "qs:local_sum":9720,
    "qs:localhoods":15,
    "qs:name":"Bakery Hill",
    "qs:name_adm0":"Australia",
    "qs:name_adm1":"Victoria",
    "qs:name_adm2":"City of Ballarat",
    "qs:name_local":"Ballarat",
    "qs:photo_max":203,
    "qs:photo_sum":565,
    "qs:placetype":"Suburb",
    "qs:quad_count":18,
    "qs:woe_adm0":23424748,
    "qs:woe_adm1":2344705,
    "qs:woe_adm2":55864013,
    "qs:woe_lau":0,
    "qs:woe_local":1100071,
    "qs:woe_ver":"7.10.0",
    "wof:lang":[
        "eng"
    ],
    "wof:name":"Bakery Hill",
    "wof:placetype":"neighbourhood"
},
  "geometry": {"coordinates":[143.86213100000001,-37.563278],"type":"Point"}
}