{
  "type": "Feature",
  "properties": {
    "gn:admin1_code":"8.0",
    "gn:admin2_code":"50250.0",
    "gn:asciiname":"Nyang",
    "gn:country_code":"AU",
    "gn:dem":110,
    "gn:feature_class":"P",
    "gn:feature_code":"PPL",
    "gn:name":"Nyang",
    "gn:population":0,
    "gn:timezone":"Australia/Perth",
    "iso:country":"AU",
    "wof:name":"Nyang",
    "wof:placetype":"locality"
},
  "geometry": {"coordinates":[115.04003,-23.03173],"type":"Point"}
}