{
  "type": "Feature",
  "properties": {
    "gn:admin1_code":"4.0",
    "gn:admin2_code":"32250.0",
    "gn:asciiname":"Leichards Yard",
    "gn:country_code":"AU",
    "gn:dem":23,
    "gn:feature_class":"P",
    "gn:feature_code":"PPL",
    "gn:name":"Leichards Yard",
    "gn:population":0,
    "gn:timezone":"Australia/Brisbane",
    "iso:country":"AU",
    "wof:name":"Leichards Yard",
    "wof:placetype":"locality"
},
  "geometry": {"coordinates":[141.95266000000001,-15.62847],"type":"Point"}
}