{
  "type": "Feature",
  "properties": {
    "gn:admin1_code":"4.0",
    "gn:admin2_code":"33200.0",
    "gn:asciiname":"Tarvano",
    "gn:country_code":"AU",
    "gn:dem":268,
    "gn:feature_class":"P",
    "gn:feature_code":"PPL",
    "gn:name":"Tarvano",
    "gn:population":0,
    "gn:timezone":"Australia/Brisbane",
    "iso:country":"AU",
    "name:eng_x_preferred":[
        "Tarvano"
    ],
    "wof:name":"Tarvano",
    "wof:placetype":"locality"
},
  "geometry": {"coordinates":[143.47311000000005,-21.61026],"type":"Point"}
}