{
  "type": "Feature",
  "properties": {
    "gn:admin1_code":"4.0",
    "gn:admin2_code":"30410.0",
    "gn:asciiname":"Cavendish",
    "gn:country_code":"AU",
    "gn:dem":395,
    "gn:feature_class":"P",
    "gn:feature_code":"PPL",
    "gn:name":"Cavendish",
    "gn:population":0,
    "gn:timezone":"Australia/Brisbane",
    "iso:country":"AU",
    "name:eng_x_preferred":[
        "Cavendish"
    ],
    "wof:name":"Cavendish",
    "wof:placetype":"locality"
},
  "geometry": {"coordinates":[146.28666999999999,-23.43558],"type":"Point"}
}