{
  "type": "Feature",
  "properties": {
    "gn:admin1_code":"4.0",
    "gn:admin2_code":"30410.0",
    "gn:asciiname":"Cavendish",
    "gn:country_code":"AU",
    "gn:dem":395,
    "gn:feature_class":"P",
    "gn:feature_code":"PPL",
    "gn:name":"Cavendish",
    "gn:population":0,
    "gn:timezone":"Australia/Brisbane",
    "iso:country":"AU",
    "name:bel_x_preferred":[
        "\u041a\u0430\u0432\u0435\u043d\u0434\u044b\u0448"
    ],
    "name:cat_x_preferred":[
        "Cavendish"
    ],
    "name:ceb_x_preferred":[
        "Cavendish"
    ],
    "name:deu_x_preferred":[
        "Cavendish"
    ],
    "name:eng_x_preferred":[
        "Cavendish"
    ],
    "name:epo_x_preferred":[
        "Cavendish"
    ],
    "name:fas_x_preferred":[
        "\u06a9\u0627\u0648\u0646\u062f\u06cc\u0634"
    ],
    "name:fin_x_preferred":[
        "Cavendish"
    ],
    "name:fra_x_preferred":[
        "Cavendish"
    ],
    "name:heb_x_preferred":[
        "\u05e7\u05d5\u05d5\u05e0\u05d3\u05d9\u05e9"
    ],
    "name:hun_x_preferred":[
        "Cavendish"
    ],
    "name:ita_x_preferred":[
        "Cavendish"
    ],
    "name:jpn_x_preferred":[
        "\u30ad\u30e3\u30f4\u30a7\u30f3\u30c7\u30a3\u30c3\u30b7\u30e5"
    ],
    "name:kor_x_preferred":[
        "\uce90\ubc88\ub514\uc2dc"
    ],
    "name:lav_x_preferred":[
        "Kevendi\u0161s"
    ],
    "name:mal_x_preferred":[
        "\u0d15\u0d3e\u0d35\u0d7b\u0d21\u0d3f\u0d37\u0d4d\u200c"
    ],
    "name:nld_x_preferred":[
        "Cavendish"
    ],
    "name:pol_x_preferred":[
        "Cavendish"
    ],
    "name:por_x_preferred":[
        "Cavendish"
    ],
    "name:ron_x_preferred":[
        "Cavendish"
    ],
    "name:rus_x_preferred":[
        "\u041a\u0430\u0432\u0435\u043d\u0434\u0438\u0448"
    ],
    "name:spa_x_preferred":[
        "Cavendish"
    ],
    "name:swe_x_preferred":[
        "Cavendish"
    ],
    "name:ukr_x_preferred":[
        "\u041a\u0435\u0432\u0435\u043d\u0434\u0456\u0448"
    ],
    "wof:name":"Cavendish",
    "wof:placetype":"locality"
},
  "geometry": {"coordinates":[146.28666999999999,-23.43558],"type":"Point"}
}