{
  "type": "Feature",
  "properties": {
    "gn:admin1_code":"4.0",
    "gn:admin2_code":"32310.0",
    "gn:asciiname":"Old Glenroy",
    "gn:country_code":"AU",
    "gn:dem":141,
    "gn:feature_class":"P",
    "gn:feature_code":"PPL",
    "gn:name":"Old Glenroy",
    "gn:population":0,
    "gn:timezone":"Australia/Brisbane",
    "iso:country":"AU",
    "wof:name":"Old Glenroy",
    "wof:placetype":"locality"
},
  "geometry": {"coordinates":[147.13333,-20.53333],"type":"Point"}
}