{
  "type": "Feature",
  "properties": {
    "gn:admin1_code":"3.0",
    "gn:admin2_code":"71300.0",
    "gn:asciiname":"Baniyala",
    "gn:country_code":"AU",
    "gn:dem":8,
    "gn:feature_class":"P",
    "gn:feature_code":"PPL",
    "gn:name":"Baniyala",
    "gn:population":0,
    "gn:timezone":"Australia/Darwin",
    "iso:country":"AU",
    "wof:name":"Baniyala",
    "wof:placetype":"locality"
},
  "geometry": {"coordinates":[136.22556,-13.2006],"type":"Point"}
}