{
  "type": "Feature",
  "properties": {
    "iso:country":"AU",
    "name:eng_x_preferred":[
        "Everton Hills"
    ],
    "qs:gn_adm0_cc":"AU",
    "qs:gn_fcode":"PPLX",
    "qs:gn_local":2174003,
    "qs:gn_nam_loc":"Brisbane, Brisbane, Queensland, AU",
    "qs:gn_namadm1":"04",
    "qs:gn_name":"Everton Hills",
    "qs:local_max":15217,
    "qs:local_sum":137917,
    "qs:localhoods":252,
    "qs:name":"Everton Hills",
    "qs:name_adm0":"Australia",
    "qs:name_adm1":"Queensland",
    "qs:name_adm2":"Moreton Bay Regional",
    "qs:name_local":"Brisbane",
    "qs:photo_max":3,
    "qs:photo_sum":7,
    "qs:placetype":"Suburb",
    "qs:quad_count":4,
    "qs:woe_adm0":23424748,
    "qs:woe_adm1":2344702,
    "qs:woe_adm2":56072967,
    "qs:woe_lau":0,
    "qs:woe_local":1100661,
    "qs:woe_ver":"7.10.0",
    "wof:lang":[
        "eng"
    ],
    "wof:name":"Everton Hills",
    "wof:placetype":"neighbourhood"
},
  "geometry": {"coordinates":[152.98181400000001,-27.372779],"type":"Point"}
}