{
  "type": "Feature",
  "properties": {
    "gn:admin1_code":"2",
    "gn:admin2_code":"18710",
    "gn:asciiname":"Tangmanjaroo",
    "gn:cc2":"AU",
    "gn:country_code":"AU",
    "gn:dem":609,
    "gn:feature_class":"P",
    "gn:feature_code":"PPL",
    "gn:name":"Tangmanjaroo",
    "gn:population":0,
    "gn:timezone":"Australia/Sydney",
    "iso:country":"AU",
    "name:und_x_variant":[
        "Tangmangaroo",
        "Tangmanjaroo"
    ],
    "wof:name":"Tangmanjaroo",
    "wof:placetype":"locality"
},
  "geometry": {"coordinates":[148.81666999999999,-34.65],"type":"Point"}
}