{
  "type": "Feature",
  "properties": {
    "gn:admin1_code":"7.0",
    "gn:admin2_code":"20740.0",
    "gn:asciiname":"Burndale",
    "gn:country_code":"AU",
    "gn:dem":186,
    "gn:feature_class":"P",
    "gn:feature_code":"PPL",
    "gn:name":"Burndale",
    "gn:population":0,
    "gn:timezone":"Australia/Melbourne",
    "iso:country":"AU",
    "wof:name":"Burndale",
    "wof:placetype":"locality"
},
  "geometry": {"coordinates":[145.66666999999995,-38.48333],"type":"Point"}
}