{
  "type": "Feature",
  "properties": {
    "gn:admin1_code":"04",
    "gn:admin2_code":"32260.0",
    "gn:asciiname":"Number 5 Branch",
    "gn:country_code":"AU",
    "gn:dem":17,
    "gn:feature_class":"P",
    "gn:feature_code":"PPL",
    "gn:name":"Number 5 Branch",
    "gn:population":0,
    "gn:timezone":"Australia/Brisbane",
    "iso:country":"AU",
    "wof:name":"Number 5 Branch",
    "wof:placetype":"locality"
},
  "geometry": {"coordinates":[146.01182,-17.72772],"type":"Point"}
}