{
  "type": "Feature",
  "properties": {
    "gn:admin1_code":"2.0",
    "gn:admin2_code":"11730.0",
    "gn:asciiname":"Lionsville",
    "gn:country_code":"AU",
    "gn:dem":167,
    "gn:feature_class":"P",
    "gn:feature_code":"PPL",
    "gn:name":"Lionsville",
    "gn:population":0,
    "gn:timezone":"Australia/Sydney",
    "iso:country":"AU",
    "name:eng_x_preferred":[
        "Lionsville"
    ],
    "wof:name":"Lionsville",
    "wof:placetype":"locality"
},
  "geometry": {"coordinates":[152.49069,-29.19193],"type":"Point"}
}