{
  "type": "Feature",
  "properties": {
    "gn:admin1_code":"2",
    "gn:admin2_code":"18020",
    "gn:asciiname":"Ulinda",
    "gn:country_code":"AU",
    "gn:dem":429,
    "gn:feature_class":"P",
    "gn:feature_code":"PPL",
    "gn:name":"Ulinda",
    "gn:population":0,
    "gn:timezone":"Australia/Sydney",
    "iso:country":"AU",
    "wof:name":"Ulinda",
    "wof:placetype":"locality"
},
  "geometry": {"coordinates":[149.48333,-31.58333],"type":"Point"}
}