{
  "type": "Feature",
  "properties": {
    "gn:admin1_code":"2",
    "gn:admin2_code":"10470",
    "gn:asciiname":"Wattle Flat",
    "gn:country_code":"AU",
    "gn:dem":926,
    "gn:feature_class":"P",
    "gn:feature_code":"PPL",
    "gn:name":"Wattle Flat",
    "gn:population":0,
    "gn:timezone":"Australia/Sydney",
    "iso:country":"AU",
    "wof:name":"Wattle Flat",
    "wof:placetype":"locality",
    "wof:population":257
},
  "geometry": {"coordinates":[149.69999999999999,-33.15],"type":"Point"}
}