{
  "type": "Feature",
  "properties": {
    "gn:admin1_code":"3.0",
    "gn:admin2_code":"70620.0",
    "gn:asciiname":"Tilmouth Crossing",
    "gn:country_code":"AU",
    "gn:dem":567,
    "gn:feature_class":"P",
    "gn:feature_code":"PPL",
    "gn:name":"Tilmouth Crossing",
    "gn:population":0,
    "gn:timezone":"Australia/Darwin",
    "iso:country":"AU",
    "wof:name":"Tilmouth Crossing",
    "wof:placetype":"locality"
},
  "geometry": {"coordinates":[132.59549999999999,-22.81888],"type":"Point"}
}