{
  "type": "Feature",
  "properties": {
    "gn:admin1_code":"8",
    "gn:admin2_code":"59250",
    "gn:asciiname":"Ives",
    "gn:cc2":"AU",
    "gn:country_code":"AU",
    "gn:dem":530,
    "gn:feature_class":"P",
    "gn:feature_code":"PPL",
    "gn:name":"Ives",
    "gn:population":0,
    "gn:timezone":"Australia/Perth",
    "iso:country":"AU",
    "name:und_x_variant":[
        "Ives Find",
        "Ives"
    ],
    "wof:name":"Ives",
    "wof:placetype":"locality"
},
  "geometry": {"coordinates":[120.76667,-26.91667],"type":"Point"}
}