{
  "type": "Feature",
  "properties": {
    "gn:admin1_code":"4.0",
    "gn:admin2_code":"34710.0",
    "gn:asciiname":"Marmboo",
    "gn:country_code":"AU",
    "gn:dem":215,
    "gn:feature_class":"P",
    "gn:feature_code":"PPL",
    "gn:name":"Marmboo",
    "gn:population":0,
    "gn:timezone":"Australia/Brisbane",
    "iso:country":"AU",
    "name:eng_x_preferred":[
        "Marmboo"
    ],
    "wof:name":"Marmboo",
    "wof:placetype":"locality"
},
  "geometry": {"coordinates":[143.44058999999999,-23.31425],"type":"Point"}
}