{
  "type": "Feature",
  "properties": {
    "iso:country":"AU",
    "name:eng_x_preferred":[
        "Prospect East"
    ],
    "name:unk_x_variant":[
        "Prospect East"
    ],
    "qs:gn_adm0_cc":"AU",
    "qs:gn_local":2078025,
    "qs:local_max":18505,
    "qs:local_sum":99726,
    "qs:localhoods":191,
    "qs:name":"Prospect East",
    "qs:name_adm0":"Australia",
    "qs:name_adm1":"South Australia",
    "qs:name_adm2":"City of Prospect",
    "qs:name_local":"Adelaide",
    "qs:photo_max":130,
    "qs:photo_sum":388,
    "qs:placetype":"Suburb",
    "qs:quad_count":22,
    "qs:woe_adm0":23424748,
    "qs:woe_adm1":2344703,
    "qs:woe_adm2":55864108,
    "qs:woe_lau":0,
    "qs:woe_local":1099805,
    "qs:woe_ver":"7.10.0",
    "wof:lang":[
        "eng"
    ],
    "wof:name":"Prospect East",
    "wof:placetype":"neighbourhood"
},
  "geometry": {"coordinates":[138.59862100000001,-34.890186],"type":"Point"}
}