{
  "type": "Feature",
  "properties": {
    "gn:admin1_code":"4.0",
    "gn:admin2_code":"32250.0",
    "gn:asciiname":"Mutton Yard",
    "gn:country_code":"AU",
    "gn:dem":40,
    "gn:feature_class":"P",
    "gn:feature_code":"PPL",
    "gn:name":"Mutton Yard",
    "gn:population":0,
    "gn:timezone":"Australia/Brisbane",
    "iso:country":"AU",
    "wof:name":"Mutton Yard",
    "wof:placetype":"locality"
},
  "geometry": {"coordinates":[142.28953000000001,-15.78564],"type":"Point"}
}