{
  "type": "Feature",
  "properties": {
    "gn:admin1_code":"4.0",
    "gn:admin2_code":"32250.0",
    "gn:asciiname":"Killarney Yards",
    "gn:country_code":"AU",
    "gn:dem":12,
    "gn:feature_class":"P",
    "gn:feature_code":"PPL",
    "gn:name":"Killarney Yards",
    "gn:population":0,
    "gn:timezone":"Australia/Brisbane",
    "iso:country":"AU",
    "wof:name":"Killarney Yards",
    "wof:placetype":"locality"
},
  "geometry": {"coordinates":[141.74768999999995,-15.92151],"type":"Point"}
}