{
  "type": "Feature",
  "properties": {
    "gn:admin1_code":"4.0",
    "gn:admin2_code":"34710.0",
    "gn:asciiname":"The Glen",
    "gn:country_code":"AU",
    "gn:dem":230,
    "gn:feature_class":"P",
    "gn:feature_code":"PPL",
    "gn:name":"The Glen",
    "gn:population":0,
    "gn:timezone":"Australia/Brisbane",
    "iso:country":"AU",
    "name:ceb_x_preferred":[
        "The Glen"
    ],
    "name:eng_x_preferred":[
        "The Glen"
    ],
    "name:swe_x_preferred":[
        "The Glen"
    ],
    "wof:name":"The Glen",
    "wof:placetype":"locality"
},
  "geometry": {"coordinates":[144.15723,-23.8767],"type":"Point"}
}