{
  "type": "Feature",
  "properties": {
    "gn:admin1_code":"8",
    "gn:admin2_code":"51680",
    "gn:asciiname":"Chittering",
    "gn:country_code":"AU",
    "gn:dem":203,
    "gn:feature_class":"P",
    "gn:feature_code":"PPL",
    "gn:name":"Chittering",
    "gn:population":388,
    "gn:timezone":"Australia/Perth",
    "iso:country":"AU",
    "name:ceb_x_preferred":[
        "Chittering"
    ],
    "name:nld_x_preferred":[
        "Chittering"
    ],
    "name:swe_x_preferred":[
        "Chittering"
    ],
    "wof:name":"Chittering",
    "wof:placetype":"locality",
    "wof:population":921
},
  "geometry": {"coordinates":[116.0801,-31.46766],"type":"Point"}
}