{
  "type": "Feature",
  "properties": {
    "gn:admin1_code":"5",
    "gn:admin2_code":"43650",
    "gn:asciiname":"Bethel",
    "gn:country_code":"AU",
    "gn:dem":282,
    "gn:feature_class":"P",
    "gn:feature_code":"PPL",
    "gn:name":"Bethel",
    "gn:population":0,
    "gn:timezone":"Australia/Adelaide",
    "iso:country":"AU",
    "wof:name":"Bethel",
    "wof:placetype":"locality"
},
  "geometry": {"coordinates":[138.83763000000002,-34.32784],"type":"Point"}
}