{
  "type": "Feature",
  "properties": {
    "gn:admin1_code":"4.0",
    "gn:admin2_code":"30900.0",
    "gn:asciiname":"Pollygammon",
    "gn:country_code":"AU",
    "gn:dem":168,
    "gn:feature_class":"P",
    "gn:feature_code":"PPL",
    "gn:name":"Pollygammon",
    "gn:population":0,
    "gn:timezone":"Australia/Brisbane",
    "iso:country":"AU",
    "name:eng_x_preferred":[
        "Pollygammon"
    ],
    "wof:name":"Pollygammon",
    "wof:placetype":"locality"
},
  "geometry": {"coordinates":[140.58351999999999,-22.74217],"type":"Point"}
}