{
  "type": "Feature",
  "properties": {
    "gn:country":"AU",
    "gn:fcode":"PPL",
    "gn:population":0,
    "iso:country":"AU",
    "name:eng_x_preferred":[
        "Little Burleigh"
    ],
    "qs:gn_adm0_cc":"AU",
    "qs:gn_fcode":"PPL",
    "qs:gn_local":2165087,
    "qs:gn_namadm1":"04",
    "qs:gn_name":"Little Burleigh",
    "qs:local_max":10372,
    "qs:local_sum":57138,
    "qs:localhoods":62,
    "qs:name":"Little Burleigh",
    "qs:name_adm0":"Australia",
    "qs:name_adm1":"Queensland",
    "qs:name_adm2":"Gold Coast City",
    "qs:name_local":"City of Gold Coast",
    "qs:photo_max":234,
    "qs:photo_sum":1244,
    "qs:placetype":"Suburb",
    "qs:quad_count":19,
    "qs:woe_adm0":23424748,
    "qs:woe_adm1":2344702,
    "qs:woe_adm2":55864296,
    "qs:woe_lau":0,
    "qs:woe_local":7226269,
    "qs:woe_ver":"7.10.0",
    "qs_pg:aaroncc":"AU",
    "qs_pg:gn_country":"AU",
    "qs_pg:gn_fcode":"PPL",
    "qs_pg:gn_pop":0,
    "qs_pg:name":"Little Burleigh",
    "qs_pg:name_adm0":"Australia",
    "qs_pg:name_adm1":"Queensland",
    "qs_pg:photos":1306,
    "qs_pg:photos_1k":265,
    "qs_pg:photos_9k":6,
    "qs_pg:photos_9r":7,
    "qs_pg:photos_all":1306,
    "qs_pg:photos_sr":12,
    "qs_pg:pop_sr":0,
    "qs_pg:qs_pg_placetype":"neighbourhood",
    "qs_pg:qs_pg_placetype_gp":"Suburb",
    "qs_pg:woe_adm0":23424748,
    "wof:lang":[
        "eng"
    ],
    "wof:name":"Little Burleigh",
    "wof:placetype":"neighbourhood"
},
  "geometry": {"coordinates":[153.44843299999999,-28.067439],"type":"Point"}
}