{
  "type": "Feature",
  "properties": {
    "gn:gn_country":"AU",
    "gn:gn_fcode":"PPLX",
    "gn:gn_pop":0,
    "gn:population":47,
    "iso:country":"AU",
    "name:eng_x_preferred":[
        "Peron"
    ],
    "name:unk_x_variant":[
        "Peron"
    ],
    "qs:gn_adm0_cc":"AU",
    "qs:gn_fcode":"PPLX",
    "qs:gn_local":2062338,
    "qs:gn_nam_loc":"rockingham",
    "qs:gn_namadm1":"08",
    "qs:gn_name":"Peron",
    "qs:local_max":485,
    "qs:local_sum":1915,
    "qs:localhoods":7,
    "qs:name":"Peron",
    "qs:name_adm0":"Australia",
    "qs:name_adm1":"Western Australia",
    "qs:name_adm2":"Rockingham",
    "qs:name_local":"Rockingham",
    "qs:photo_max":58,
    "qs:photo_sum":323,
    "qs:placetype":"Suburb",
    "qs:quad_count":20,
    "qs:woe_adm0":23424748,
    "qs:woe_adm1":2344706,
    "qs:woe_adm2":55864390,
    "qs:woe_lau":0,
    "qs:woe_local":1105355,
    "qs:woe_ver":"7.10.0",
    "qs_pg:aaroncc":"AU",
    "qs_pg:gn_country":"AU",
    "qs_pg:gn_fcode":"PPLX",
    "qs_pg:gn_pop":0,
    "qs_pg:name":"Peron",
    "qs_pg:name_adm0":"Australia",
    "qs_pg:name_adm1":"Western Australia",
    "qs_pg:photos":316,
    "qs_pg:photos_1k":64,
    "qs_pg:photos_9k":1,
    "qs_pg:photos_9r":5,
    "qs_pg:photos_all":316,
    "qs_pg:photos_sr":5,
    "qs_pg:pop_sr":0,
    "qs_pg:qs_pg_placetype":"neighbourhood",
    "qs_pg:qs_pg_placetype_gp":"Suburb",
    "qs_pg:woe_adm0":23424748,
    "wof:name":"Peron",
    "wof:placetype":"neighbourhood",
    "wof:population":47
},
  "geometry": {"coordinates":[115.693208,-32.267287],"type":"Point"}
}