{
  "type": "Feature",
  "properties": {
    "gn:admin1_code":"4.0",
    "gn:admin2_code":"32500.0",
    "gn:asciiname":"Kintore Satellite Station",
    "gn:country_code":"AU",
    "gn:dem":279,
    "gn:feature_class":"P",
    "gn:feature_code":"PPL",
    "gn:name":"Kintore Satellite Station",
    "gn:population":0,
    "gn:timezone":"Australia/Brisbane",
    "iso:country":"AU",
    "wof:name":"Kintore Satellite Station",
    "wof:placetype":"locality"
},
  "geometry": {"coordinates":[143.34572,-14.29747],"type":"Point"}
}