{
  "type": "Feature",
  "properties": {
    "gn:admin1_code":"5.0",
    "gn:asciiname":"Samson Well",
    "gn:country_code":"AU",
    "gn:dem":68,
    "gn:feature_class":"P",
    "gn:feature_code":"PPL",
    "gn:name":"Samson Well",
    "gn:population":0,
    "gn:timezone":"Australia/Adelaide",
    "iso:country":"AU",
    "name:eng_x_preferred":[
        "Samson Well"
    ],
    "wof:name":"Samson Well",
    "wof:placetype":"locality"
},
  "geometry": {"coordinates":[139.62053999999998,-33.79086],"type":"Point"}
}