{
  "type": "Feature",
  "properties": {
    "gn:admin1_code":"5.0",
    "gn:admin2_code":"43790.0",
    "gn:asciiname":"Tennyson",
    "gn:country_code":"AU",
    "gn:dem":40,
    "gn:feature_class":"P",
    "gn:feature_code":"PPL",
    "gn:name":"Tennyson",
    "gn:population":0,
    "gn:timezone":"Australia/Adelaide",
    "iso:country":"AU",
    "name:eng_x_preferred":[
        "Tennyson"
    ],
    "wof:name":"Tennyson",
    "wof:placetype":"locality"
},
  "geometry": {"coordinates":[140.78072,-34.55572],"type":"Point"}
}