{
  "type": "Feature",
  "properties": {
    "gn:admin1_code":"2",
    "gn:admin2_code":"16200",
    "gn:asciiname":"Wallanbillan",
    "gn:country_code":"AU",
    "gn:dem":217,
    "gn:feature_class":"P",
    "gn:feature_code":"PPL",
    "gn:name":"Wallanbillan",
    "gn:population":0,
    "gn:timezone":"Australia/Sydney",
    "iso:country":"AU",
    "wof:name":"Wallanbillan",
    "wof:placetype":"locality"
},
  "geometry": {"coordinates":[147.83333000000005,-32.43333],"type":"Point"}
}