{
  "type": "Feature",
  "properties": {
    "gn:admin1_code":"6.0",
    "gn:admin2_code":"62010.0",
    "gn:asciiname":"Killiecrankie",
    "gn:country_code":"AU",
    "gn:dem":30,
    "gn:feature_class":"P",
    "gn:feature_code":"PPL",
    "gn:name":"Killiecrankie",
    "gn:population":0,
    "gn:timezone":"Australia/Hobart",
    "iso:country":"AU",
    "name:eng_x_preferred":[
        "Killiecrankie"
    ],
    "wof:name":"Killiecrankie",
    "wof:placetype":"locality"
},
  "geometry": {"coordinates":[147.83396999999999,-39.83914],"type":"Point"}
}