{
  "type": "Feature",
  "properties": {
    "gn:gn_country":"AU",
    "gn:gn_fcode":"PPL",
    "gn:gn_pop":0,
    "iso:country":"AU",
    "name:ceb_x_preferred":[
        "Rydal"
    ],
    "name:deu_x_preferred":[
        "Rydal"
    ],
    "name:eng_x_preferred":[
        "Rydal"
    ],
    "name:fra_x_preferred":[
        "Rydal"
    ],
    "name:nld_x_preferred":[
        "Rydal"
    ],
    "name:sco_x_preferred":[
        "Rydal"
    ],
    "qs_pg:aaroncc":"AU",
    "qs_pg:gn_country":"AU",
    "qs_pg:gn_fcode":"PPL",
    "qs_pg:gn_pop":0,
    "qs_pg:name":"Rydal",
    "qs_pg:name_adm0":"Australia",
    "qs_pg:name_adm1":"New South Wales",
    "qs_pg:photos":204,
    "qs_pg:photos_1k":41,
    "qs_pg:photos_9k":1,
    "qs_pg:photos_9r":4,
    "qs_pg:photos_all":204,
    "qs_pg:photos_sr":4,
    "qs_pg:pop_sr":0,
    "qs_pg:qs_pg_placetype":"locality",
    "qs_pg:qs_pg_placetype_gp":"Town",
    "qs_pg:woe_adm0":23424748,
    "woe:adm0_id":23424748,
    "woe:name_adm0":"Australia",
    "woe:name_adm1":"New South Wales",
    "woe:placetype":"Town",
    "wof:name":"Rydal",
    "wof:placetype":"locality",
    "wof:population":213
},
  "geometry": {"coordinates":[150.03333000000001,-33.48333],"type":"Point"}
}