{
  "type": "Feature",
  "properties": {
    "gn:admin1_code":"8",
    "gn:admin2_code":"58680",
    "gn:asciiname":"Dwarda",
    "gn:country_code":"AU",
    "gn:dem":258,
    "gn:feature_class":"P",
    "gn:feature_code":"PPL",
    "gn:name":"Dwarda",
    "gn:population":0,
    "gn:timezone":"Australia/Perth",
    "iso:country":"AU",
    "wof:name":"Dwarda",
    "wof:placetype":"locality"
},
  "geometry": {"coordinates":[116.66667,-32.76667],"type":"Point"}
}