{
  "type": "Feature",
  "properties": {
    "gn:admin1_code":"2.0",
    "gn:admin2_code":"12050.0",
    "gn:asciiname":"Murrulula",
    "gn:country_code":"AU",
    "gn:dem":954,
    "gn:feature_class":"P",
    "gn:feature_code":"PPL",
    "gn:name":"Murrulula",
    "gn:population":0,
    "gn:timezone":"Australia/Sydney",
    "iso:country":"AU",
    "name:eng_x_preferred":[
        "Murrulula"
    ],
    "wof:name":"Murrulula",
    "wof:placetype":"locality"
},
  "geometry": {"coordinates":[149.30097000000001,-36.44711],"type":"Point"}
}