{
  "type": "Feature",
  "properties": {
    "iso:country":"AU",
    "name:eng_x_preferred":[
        "Lindfield West"
    ],
    "name:eng_x_variant":[
        "W Lindfield",
        "West Lindfield"
    ],
    "qs:gn_adm0_cc":"AU",
    "qs:gn_local":2147714,
    "qs:local_max":35533,
    "qs:local_sum":687549,
    "qs:localhoods":516,
    "qs:name":"Lindfield West",
    "qs:name_adm0":"Australia",
    "qs:name_adm1":"New South Wales",
    "qs:name_adm2":"Ku-ring-gai",
    "qs:name_local":"Sydney",
    "qs:photo_max":89,
    "qs:photo_sum":717,
    "qs:placetype":"Suburb",
    "qs:quad_count":42,
    "qs:woe_adm0":23424748,
    "qs:woe_adm1":2344700,
    "qs:woe_adm2":55864181,
    "qs:woe_lau":0,
    "qs:woe_local":1105779,
    "qs:woe_ver":"7.10.0",
    "wof:lang":[
        "eng"
    ],
    "wof:name":"Lindfield West",
    "wof:placetype":"neighbourhood"
},
  "geometry": {"coordinates":[151.148337,-33.78578],"type":"Point"}
}