{
  "type": "Feature",
  "properties": {
    "gn:admin1_code":"7",
    "gn:admin2_code":"26610",
    "gn:asciiname":"Vinifera",
    "gn:country_code":"AU",
    "gn:dem":85,
    "gn:feature_class":"P",
    "gn:feature_code":"PPL",
    "gn:name":"Vinifera",
    "gn:population":0,
    "gn:timezone":"Australia/Melbourne",
    "iso:country":"AU",
    "wof:name":"Vinifera",
    "wof:placetype":"locality"
},
  "geometry": {"coordinates":[143.37836999999999,-35.20309],"type":"Point"}
}