{
  "type": "Feature",
  "properties": {
    "iso:country":"AU",
    "name:ceb_x_preferred":[
        "Pooncarie Airport"
    ],
    "name:eng_x_preferred":[
        "Pooncarie Airport"
    ],
    "name:eng_x_variant":[
        "YPCE"
    ],
    "name:msa_x_preferred":[
        "Lapangan Terbang Pooncarie"
    ],
    "name:ron_x_preferred":[
        "Aeroportul Pooncarie"
    ],
    "name:spa_x_preferred":[
        "Ponncarie"
    ],
    "name:swe_x_preferred":[
        "Pooncarie Airport"
    ],
    "oa:elevation_ft":"50",
    "oa:type":"small_airport",
    "woe:hierarchy":{
        "country_id":23424748,
        "county_id":55863770,
        "planet_id":1,
        "state_id":2344700
    },
    "wof:name":"Pooncarie Aerodrome",
    "wof:placetype":"campus"
},
  "geometry": {"coordinates":[142.583,-33.3733],"type":"Point"}
}