{
  "type": "Feature",
  "properties": {
    "gn:admin1_code":"3.0",
    "gn:admin2_code":"71300.0",
    "gn:asciiname":"Gaiawdjapin",
    "gn:country_code":"AU",
    "gn:dem":28,
    "gn:feature_class":"P",
    "gn:feature_code":"PPL",
    "gn:name":"Gaiawdjapin",
    "gn:population":0,
    "gn:timezone":"Australia/Darwin",
    "iso:country":"AU",
    "wof:name":"Gaiawdjapin",
    "wof:placetype":"locality"
},
  "geometry": {"coordinates":[134.82323,-12.28821],"type":"Point"}
}