{
  "type": "Feature",
  "properties": {
    "gn:admin1_code":"5",
    "gn:admin2_code":"45040",
    "gn:asciiname":"Warla",
    "gn:country_code":"AU",
    "gn:dem":140,
    "gn:feature_class":"P",
    "gn:feature_code":"PPL",
    "gn:name":"Warla",
    "gn:population":0,
    "gn:timezone":"Australia/Adelaide",
    "iso:country":"AU",
    "wof:name":"Warla",
    "wof:placetype":"locality"
},
  "geometry": {"coordinates":[139.06666999999999,-35.13333],"type":"Point"}
}