{
  "type": "Feature",
  "properties": {
    "gn:admin1_code":"8",
    "gn:admin2_code":"55460",
    "gn:asciiname":"Koonadgin",
    "gn:country_code":"AU",
    "gn:dem":405,
    "gn:feature_class":"P",
    "gn:feature_code":"PPL",
    "gn:name":"Koonadgin",
    "gn:population":0,
    "gn:timezone":"Australia/Perth",
    "iso:country":"AU",
    "name:eng_x_preferred":[
        "Koonadgin"
    ],
    "wof:name":"Koonadgin",
    "wof:placetype":"locality"
},
  "geometry": {"coordinates":[118.51079,-31.60875],"type":"Point"}
}