{
  "type": "Feature",
  "properties": {
    "gn:admin1_code":"2.0",
    "gn:admin2_code":"14920.0",
    "gn:asciiname":"Castle Mountain",
    "gn:country_code":"AU",
    "gn:dem":418,
    "gn:feature_class":"P",
    "gn:feature_code":"PPL",
    "gn:name":"Castle Mountain",
    "gn:population":0,
    "gn:timezone":"Australia/Sydney",
    "iso:country":"AU",
    "wof:name":"Castle Mountain",
    "wof:placetype":"locality"
},
  "geometry": {"coordinates":[150.75,-31.51667],"type":"Point"}
}