{
  "type": "Feature",
  "properties": {
    "iso:country":"AU",
    "name:deu_x_preferred":[
        "Gillen"
    ],
    "name:eng_x_preferred":[
        "Gillen"
    ],
    "name:fra_x_preferred":[
        "Gillen"
    ],
    "name:ltz_x_preferred":[
        "Gillen"
    ],
    "name:rus_x_preferred":[
        "\u0413\u0438\u043b\u043b\u0435\u043d"
    ],
    "name:ukr_x_preferred":[
        "\u0413\u0456\u043b\u043b\u0435\u043d"
    ],
    "qs:gn_adm0_cc":"AU",
    "qs:gn_fcode":"PPLX",
    "qs:gn_local":2077895,
    "qs:gn_nam_loc":"Alice Springs, Alice Springs, Northern Territory, AU",
    "qs:gn_namadm1":"03",
    "qs:gn_name":"Gillen",
    "qs:local_max":1807,
    "qs:local_sum":4749,
    "qs:localhoods":13,
    "qs:name":"Gillen",
    "qs:name_adm0":"Australia",
    "qs:name_adm1":"Northern Territory",
    "qs:name_adm2":"Alice Springs",
    "qs:name_local":"Alice Springs",
    "qs:photo_max":62,
    "qs:photo_sum":160,
    "qs:placetype":"Suburb",
    "qs:quad_count":10,
    "qs:woe_adm0":23424748,
    "qs:woe_adm1":2344701,
    "qs:woe_adm2":55864163,
    "qs:woe_lau":0,
    "qs:woe_local":1099853,
    "qs:woe_ver":"7.10.0",
    "wof:name":"Gillen",
    "wof:placetype":"neighbourhood"
},
  "geometry": {"coordinates":[133.85709900000001,-23.711656],"type":"Point"}
}