{
  "type": "Feature",
  "properties": {
    "gn:admin1_code":"02",
    "gn:asciiname":"Cooleman Caves",
    "gn:country_code":"AU",
    "gn:dem":1266,
    "gn:feature_class":"P",
    "gn:feature_code":"PPL",
    "gn:name":"Cooleman Caves",
    "gn:population":0,
    "gn:timezone":"Australia/Sydney",
    "iso:country":"AU",
    "name:und_x_variant":[
        "Cooleman"
    ],
    "wof:name":"Cooleman Caves",
    "wof:placetype":"locality"
},
  "geometry": {"coordinates":[148.67410000000001,-35.62987000000001],"type":"Point"}
}