{
  "type": "Feature",
  "properties": {
    "gn:admin1_code":"7",
    "gn:admin2_code":"22250",
    "gn:asciiname":"Wee-wee-rup",
    "gn:country_code":"AU",
    "gn:dem":83,
    "gn:feature_class":"P",
    "gn:feature_code":"PPL",
    "gn:name":"Wee-wee-rup",
    "gn:population":0,
    "gn:timezone":"Australia/Melbourne",
    "iso:country":"AU",
    "wof:name":"Wee-wee-rup",
    "wof:placetype":"locality"
},
  "geometry": {"coordinates":[144.30000000000001,-35.86667],"type":"Point"}
}