{
  "type": "Feature",
  "properties": {
    "gn:admin1_code":"5",
    "gn:admin2_code":"47490",
    "gn:asciiname":"Yantanabie",
    "gn:country_code":"AU",
    "gn:dem":97,
    "gn:feature_class":"P",
    "gn:feature_code":"PPL",
    "gn:name":"Yantanabie",
    "gn:population":0,
    "gn:timezone":"Australia/Adelaide",
    "iso:country":"AU",
    "wof:name":"Yantanabie",
    "wof:placetype":"locality"
},
  "geometry": {"coordinates":[134.63626000000002,-32.48327],"type":"Point"}
}