{
  "type": "Feature",
  "properties": {
    "gn:admin1_code":"6.0",
    "gn:admin2_code":"60210.0",
    "gn:asciiname":"Lagoons",
    "gn:country_code":"AU",
    "gn:dem":11,
    "gn:feature_class":"P",
    "gn:feature_code":"PPL",
    "gn:name":"Lagoons",
    "gn:population":0,
    "gn:timezone":"Australia/Hobart",
    "iso:country":"AU",
    "name:eng_x_preferred":[
        "Lagoons"
    ],
    "wof:name":"Lagoons",
    "wof:placetype":"locality"
},
  "geometry": {"coordinates":[148.28586000000001,-41.67035],"type":"Point"}
}