{
  "type": "Feature",
  "properties": {
    "gn:admin1_code":"5",
    "gn:admin2_code":"44210",
    "gn:asciiname":"Towitta",
    "gn:country_code":"AU",
    "gn:dem":153,
    "gn:feature_class":"P",
    "gn:feature_code":"PPL",
    "gn:name":"Towitta",
    "gn:population":0,
    "gn:timezone":"Australia/Adelaide",
    "iso:country":"AU",
    "wof:name":"Towitta",
    "wof:placetype":"locality"
},
  "geometry": {"coordinates":[139.25,-34.53333],"type":"Point"}
}