{
  "type": "Feature",
  "properties": {
    "gn:admin1_code":"5.0",
    "gn:admin2_code":"40250.0",
    "gn:asciiname":"Officer Creek",
    "gn:country_code":"AU",
    "gn:dem":579,
    "gn:feature_class":"P",
    "gn:feature_code":"PPL",
    "gn:name":"Officer Creek",
    "gn:population":0,
    "gn:timezone":"Australia/Adelaide",
    "iso:country":"AU",
    "name:ceb_x_preferred":[
        "Officer Creek"
    ],
    "name:eng_x_preferred":[
        "Officer Creek"
    ],
    "name:und_x_variant":[
        "Wantinuna"
    ],
    "wof:name":"Officer Creek",
    "wof:placetype":"locality"
},
  "geometry": {"coordinates":[131.89543,-26.51068],"type":"Point"}
}