{
  "type": "Feature",
  "properties": {
    "gn:admin1_code":"2.0",
    "gn:admin2_code":"16380.0",
    "gn:asciiname":"Ballengarra",
    "gn:country_code":"AU",
    "gn:dem":72,
    "gn:feature_class":"P",
    "gn:feature_code":"PPL",
    "gn:name":"Ballengarra",
    "gn:population":0,
    "gn:timezone":"Australia/Sydney",
    "iso:country":"AU",
    "wof:name":"Ballengarra",
    "wof:placetype":"locality"
},
  "geometry": {"coordinates":[152.75,-31.31667],"type":"Point"}
}