{
  "type": "Feature",
  "properties": {
    "gn:admin1_code":"2.0",
    "gn:admin2_code":"15700.0",
    "gn:asciiname":"Burrapine",
    "gn:country_code":"AU",
    "gn:dem":102,
    "gn:feature_class":"P",
    "gn:feature_code":"PPL",
    "gn:name":"Burrapine",
    "gn:population":0,
    "gn:timezone":"Australia/Sydney",
    "iso:country":"AU",
    "name:eng_x_preferred":[
        "Burrapine"
    ],
    "wof:name":"Burrapine",
    "wof:placetype":"locality"
},
  "geometry": {"coordinates":[152.63706999999999,-30.71759],"type":"Point"}
}