{
  "type": "Feature",
  "properties": {
    "gn:admin1_code":"5",
    "gn:admin2_code":"44210",
    "gn:asciiname":"Purnong Landing",
    "gn:country_code":"AU",
    "gn:dem":69,
    "gn:feature_class":"P",
    "gn:feature_code":"PPL",
    "gn:name":"Purnong Landing",
    "gn:population":0,
    "gn:timezone":"Australia/Adelaide",
    "iso:country":"AU",
    "name:und_x_variant":[
        "Purnong"
    ],
    "wof:name":"Purnong Landing",
    "wof:placetype":"locality"
},
  "geometry": {"coordinates":[139.61667,-34.86667],"type":"Point"}
}