{
  "type": "Feature",
  "properties": {
    "gn:admin1_code":"2.0",
    "gn:admin2_code":"10550.0",
    "gn:asciiname":"Rosebank",
    "gn:country_code":"AU",
    "gn:dem":208,
    "gn:feature_class":"P",
    "gn:feature_code":"PPL",
    "gn:name":"Rosebank",
    "gn:population":0,
    "gn:timezone":"Australia/Sydney",
    "iso:country":"AU",
    "name:ceb_x_preferred":[
        "Rosebank"
    ],
    "name:eng_x_preferred":[
        "Rosebank"
    ],
    "wof:name":"Rosebank",
    "wof:placetype":"locality"
},
  "geometry": {"coordinates":[149.87326999999999,-36.30399],"type":"Point"}
}