{
  "type": "Feature",
  "properties": {
    "gn:admin1_code":"6",
    "gn:admin2_code":"60810",
    "gn:asciiname":"Sprent",
    "gn:country_code":"AU",
    "gn:dem":256,
    "gn:feature_class":"P",
    "gn:feature_code":"PPL",
    "gn:name":"Sprent",
    "gn:population":0,
    "gn:timezone":"Australia/Hobart",
    "iso:country":"AU",
    "name:eng_x_preferred":[
        "Sprent"
    ],
    "wof:name":"Sprent",
    "wof:placetype":"locality"
},
  "geometry": {"coordinates":[146.15913999999995,-41.27656],"type":"Point"}
}