{
  "type": "Feature",
  "properties": {
    "gn:admin1_code":"7.0",
    "gn:admin2_code":"21450.0",
    "gn:asciiname":"Gembrook South",
    "gn:country_code":"AU",
    "gn:dem":116,
    "gn:feature_class":"P",
    "gn:feature_code":"PPL",
    "gn:name":"Gembrook South",
    "gn:population":0,
    "gn:timezone":"Australia/Melbourne",
    "iso:country":"AU",
    "wof:name":"Gembrook South",
    "wof:placetype":"locality"
},
  "geometry": {"coordinates":[145.53333000000001,-38.01667],"type":"Point"}
}