{
  "type": "Feature",
  "properties": {
    "gn:admin1_code":"4.0",
    "gn:admin2_code":"30410.0",
    "gn:asciiname":"Ivy Leaf",
    "gn:country_code":"AU",
    "gn:dem":357,
    "gn:feature_class":"P",
    "gn:feature_code":"PPL",
    "gn:name":"Ivy Leaf",
    "gn:population":0,
    "gn:timezone":"Australia/Brisbane",
    "iso:country":"AU",
    "name:eng_x_preferred":[
        "Ivy Leaf"
    ],
    "wof:name":"Ivy Leaf",
    "wof:placetype":"locality"
},
  "geometry": {"coordinates":[145.58526000000001,-23.05595],"type":"Point"}
}