{
  "type": "Feature",
  "properties": {
    "gn:admin1_code":"4.0",
    "gn:admin2_code":"32270.0",
    "gn:asciiname":"Royles",
    "gn:country_code":"AU",
    "gn:dem":91,
    "gn:feature_class":"P",
    "gn:feature_code":"PPL",
    "gn:name":"Royles",
    "gn:population":0,
    "gn:timezone":"Australia/Brisbane",
    "iso:country":"AU",
    "name:eng_x_preferred":[
        "Royles"
    ],
    "wof:name":"Royles",
    "wof:placetype":"locality"
},
  "geometry": {"coordinates":[149.37881999999999,-23.04128],"type":"Point"}
}