{
  "type": "Feature",
  "properties": {
    "gn:country":"AU",
    "gn:fcode":"PPL",
    "gn:population":0,
    "iso:country":"AU",
    "name:ast_x_preferred":[
        "Torrumbarry"
    ],
    "name:eng_x_preferred":[
        "Torrumbarry"
    ],
    "name:fra_x_preferred":[
        "Torrumbarry"
    ],
    "name:nld_x_preferred":[
        "Torrumbarry"
    ],
    "name:por_x_preferred":[
        "Torrumbarry"
    ],
    "qs_pg:aaroncc":"AU",
    "qs_pg:gn_country":"AU",
    "qs_pg:gn_fcode":"PPL",
    "qs_pg:gn_pop":0,
    "qs_pg:name":"Torrumbarry",
    "qs_pg:name_adm0":"Australia",
    "qs_pg:name_adm1":"Victoria",
    "qs_pg:photos_9k":1,
    "qs_pg:photos_9r":1,
    "qs_pg:photos_all":2,
    "qs_pg:photos_sr":0,
    "qs_pg:pop_sr":4,
    "qs_pg:qs_pg_placetype":"locality",
    "qs_pg:qs_pg_placetype_gp":"Town",
    "qs_pg:woe_adm0":23424748,
    "woe:adm0_id":23424748,
    "woe:name_adm0":"Australia",
    "woe:name_adm1":"Victoria",
    "woe:placetype":"Town",
    "wof:name":"Torrumbarry",
    "wof:placetype":"locality"
},
  "geometry": {"coordinates":[144.55000000000001,-36.03333],"type":"Point"}
}