{
  "type": "Feature",
  "properties": {
    "gn:admin1_code":"6",
    "gn:admin2_code":"62210",
    "gn:asciiname":"The Glen",
    "gn:country_code":"AU",
    "gn:dem":127,
    "gn:feature_class":"P",
    "gn:feature_code":"PPL",
    "gn:name":"The Glen",
    "gn:population":0,
    "gn:timezone":"Australia/Hobart",
    "iso:country":"AU",
    "name:ceb_x_preferred":[
        "The Glen"
    ],
    "name:eng_x_preferred":[
        "The Glen"
    ],
    "name:swe_x_preferred":[
        "The Glen"
    ],
    "wof:name":"The Glen",
    "wof:placetype":"locality"
},
  "geometry": {"coordinates":[147.06521000000001,-41.17186],"type":"Point"}
}