{
  "type": "Feature",
  "properties": {
    "gn:admin1_code":"5.0",
    "gn:admin2_code":"41750.0",
    "gn:asciiname":"Gum Park",
    "gn:country_code":"AU",
    "gn:dem":41,
    "gn:feature_class":"P",
    "gn:feature_code":"PPL",
    "gn:name":"Gum Park",
    "gn:population":0,
    "gn:timezone":"Australia/Adelaide",
    "iso:country":"AU",
    "name:eng_x_preferred":[
        "Gum Park"
    ],
    "wof:name":"Gum Park",
    "wof:placetype":"locality"
},
  "geometry": {"coordinates":[135.29777000000001,-33.51365],"type":"Point"}
}