{
  "type": "Feature",
  "properties": {
    "gn:admin1_code":"4.0",
    "gn:admin2_code":"30300.0",
    "gn:asciiname":"Hawkston",
    "gn:country_code":"AU",
    "gn:dem":191,
    "gn:feature_class":"P",
    "gn:feature_code":"PPL",
    "gn:name":"Hawkston",
    "gn:population":0,
    "gn:timezone":"Australia/Brisbane",
    "iso:country":"AU",
    "name:eng_x_preferred":[
        "Hawkston"
    ],
    "wof:name":"Hawkston",
    "wof:placetype":"locality"
},
  "geometry": {"coordinates":[148.53322,-28.62092],"type":"Point"}
}