{
  "type": "Feature",
  "properties": {
    "gn:gn_country":"AU",
    "gn:gn_fcode":"PPL",
    "gn:gn_pop":690,
    "gn:population":690,
    "iso:country":"AU",
    "name:chi_x_preferred":[
        "\u8cbb\u8332\u7f85\u4f0a\u7011\u5e03"
    ],
    "name:eng_x_preferred":[
        "Fitzroy Falls"
    ],
    "name:geo_x_preferred":[
        "\u10e4\u10d8\u10e2\u10e1\u10e0\u10dd\u10d8"
    ],
    "name:per_x_preferred":[
        "\u0622\u0628\u0634\u0627\u0631 \u0641\u06cc\u062a\u0632\u0648\u0631\u06cc"
    ],
    "name:pol_x_preferred":[
        "Fitzroy Falls"
    ],
    "name:swe_x_preferred":[
        "Fitzroy Falls"
    ],
    "qs_pg:aaroncc":"AU",
    "qs_pg:gn_country":"AU",
    "qs_pg:gn_fcode":"PPL",
    "qs_pg:gn_pop":690,
    "qs_pg:name":"Fitzroy Falls",
    "qs_pg:name_adm0":"Australia",
    "qs_pg:name_adm1":"New South Wales",
    "qs_pg:photos":620,
    "qs_pg:photos_1k":126,
    "qs_pg:photos_9k":3,
    "qs_pg:photos_9r":5,
    "qs_pg:photos_all":620,
    "qs_pg:photos_sr":8,
    "qs_pg:pop_sr":2,
    "qs_pg:qs_pg_placetype":"locality",
    "qs_pg:qs_pg_placetype_gp":"Town",
    "qs_pg:woe_adm0":23424748,
    "woe:adm0_id":23424748,
    "woe:name_adm0":"Australia",
    "woe:name_adm1":"New South Wales",
    "woe:placetype":"Town",
    "wof:name":"Fitzroy Falls",
    "wof:placetype":"locality",
    "wof:population":690
},
  "geometry": {"coordinates":[150.48333,-34.65],"type":"Point"}
}