{
  "type": "Feature",
  "properties": {
    "gn:admin1_code":"4.0",
    "gn:admin2_code":"32500.0",
    "gn:asciiname":"Endeavour",
    "gn:country_code":"AU",
    "gn:dem":28,
    "gn:feature_class":"P",
    "gn:feature_code":"PPL",
    "gn:name":"Endeavour",
    "gn:population":0,
    "gn:timezone":"Australia/Brisbane",
    "iso:country":"AU",
    "name:ces_x_preferred":[
        "Endeavour"
    ],
    "name:deu_x_preferred":[
        "Endeavour"
    ],
    "name:fin_x_preferred":[
        "Endeavour"
    ],
    "name:fra_x_preferred":[
        "Endeavour"
    ],
    "name:glg_x_preferred":[
        "Endeavour"
    ],
    "name:heb_x_preferred":[
        "\u05d0\u05e0\u05d3\u05d5\u05d5\u05e8"
    ],
    "name:isl_x_preferred":[
        "Endeavour"
    ],
    "name:ita_x_preferred":[
        "Endeavour"
    ],
    "name:jpn_x_preferred":[
        "\u30a8\u30f3\u30c7\u30d0\u30fc"
    ],
    "name:kor_x_preferred":[
        "\uc778\ub370\ubc84"
    ],
    "name:ltz_x_preferred":[
        "Endeavour"
    ],
    "name:nld_x_preferred":[
        "Endeavour"
    ],
    "name:pol_x_preferred":[
        "Endeavour"
    ],
    "name:por_x_preferred":[
        "Endeavour"
    ],
    "name:rus_x_preferred":[
        "\u0418\u043d\u0434\u0435\u0432\u043e\u0440"
    ],
    "name:slk_x_preferred":[
        "Endeavour"
    ],
    "name:slv_x_preferred":[
        "Endeavour"
    ],
    "name:spa_x_preferred":[
        "Endeavour"
    ],
    "name:swe_x_preferred":[
        "Endeavour"
    ],
    "name:tgl_x_preferred":[
        "Endeavour"
    ],
    "name:ukr_x_preferred":[
        "\u0406\u043d\u0434\u0435\u0432\u043e\u0440"
    ],
    "wof:name":"Endeavour",
    "wof:placetype":"locality"
},
  "geometry": {"coordinates":[145.08333000000005,-15.41667],"type":"Point"}
}