{
  "type": "Feature",
  "properties": {
    "iso:country":"AU",
    "name:eng_x_preferred":[
        "Bald Knob"
    ],
    "name:fra_x_preferred":[
        "Bald Knob"
    ],
    "name:nld_x_preferred":[
        "Bald Knob"
    ],
    "qs_pg:aaroncc":"AU",
    "qs_pg:name":"Bald Knob",
    "qs_pg:name_adm0":"Australia",
    "qs_pg:name_adm1":"Queensland",
    "qs_pg:photos":36,
    "qs_pg:photos_1k":7,
    "qs_pg:photos_9k":1,
    "qs_pg:photos_9r":2,
    "qs_pg:photos_all":36,
    "qs_pg:photos_sr":2,
    "qs_pg:pop_sr":0,
    "qs_pg:qs_pg_placetype":"locality",
    "qs_pg:qs_pg_placetype_gp":"Town",
    "qs_pg:woe_adm0":23424748,
    "woe:adm0_id":23424748,
    "woe:name_adm0":"Australia",
    "woe:name_adm1":"Queensland",
    "woe:placetype":"Town",
    "wof:name":"Bald Knob",
    "wof:placetype":"locality",
    "wof:population":253
},
  "geometry": {"coordinates":[152.91282100000001,-26.788985],"type":"Point"}
}