{
  "type": "Feature",
  "properties": {
    "iso:country":"AU",
    "name:bre_x_preferred":[
        "One Tree Hill"
    ],
    "name:ceb_x_preferred":[
        "One Tree Hill"
    ],
    "name:dan_x_preferred":[
        "One Tree Hill"
    ],
    "name:deu_x_preferred":[
        "One Tree Hill"
    ],
    "name:eng_x_preferred":[
        "One Tree Hill"
    ],
    "name:fra_x_preferred":[
        "One Tree Hill"
    ],
    "name:glg_x_preferred":[
        "One Tree Hill"
    ],
    "name:kat_x_preferred":[
        "\u10d5\u10d0\u10dc \u10d7\u10e0\u10d8 \u10f0\u10d8\u10da\u10d8"
    ],
    "name:nld_x_preferred":[
        "One Tree Hill"
    ],
    "name:nor_x_preferred":[
        "One Tree Hill"
    ],
    "name:pol_x_preferred":[
        "One Tree Hill"
    ],
    "name:rus_x_preferred":[
        "One Tree Hill"
    ],
    "name:spa_x_preferred":[
        "One Tree Hill"
    ],
    "name:swe_x_preferred":[
        "One Tree Hill"
    ],
    "name:tur_x_preferred":[
        "One Tree Hill"
    ],
    "name:unk_x_variant":[
        "One Tree Hill"
    ],
    "qs:gn_adm0_cc":"AU",
    "qs:gn_local":2158177,
    "qs:local_max":22745,
    "qs:local_sum":338594,
    "qs:localhoods":407,
    "qs:name":"One Tree Hill",
    "qs:name_adm0":"Australia",
    "qs:name_adm1":"Victoria",
    "qs:name_adm2":"Yarra Ranges",
    "qs:name_local":"Melbourne",
    "qs:photo_max":17,
    "qs:photo_sum":41,
    "qs:placetype":"Suburb",
    "qs:quad_count":8,
    "qs:woe_adm0":23424748,
    "qs:woe_adm1":2344705,
    "qs:woe_adm2":55863960,
    "qs:woe_lau":0,
    "qs:woe_local":1103816,
    "qs:woe_ver":"7.10.0",
    "wd:wordcount":192,
    "wof:lang":[
        "eng"
    ],
    "wof:name":"One Tree Hill",
    "wof:placetype":"neighbourhood"
},
  "geometry": {"coordinates":[145.32218800000001,-37.872165],"type":"Point"}
}