{
  "type": "Feature",
  "properties": {
    "iso:country":"AU",
    "qs_pg:aaroncc":"AU",
    "qs_pg:name":"Cameron Corner",
    "qs_pg:name_adm0":"Australia",
    "qs_pg:name_adm1":"Queensland",
    "qs_pg:photos":59,
    "qs_pg:photos_1k":12,
    "qs_pg:photos_9k":1,
    "qs_pg:photos_9r":2,
    "qs_pg:photos_all":59,
    "qs_pg:photos_sr":2,
    "qs_pg:pop_sr":0,
    "qs_pg:qs_pg_placetype":"locality",
    "qs_pg:qs_pg_placetype_gp":"Town",
    "qs_pg:woe_adm0":23424748,
    "woe:adm0_id":23424748,
    "woe:name_adm0":"Australia",
    "woe:name_adm1":"Queensland",
    "woe:placetype":"Town",
    "wof:name":"Cameron Corner",
    "wof:placetype":"locality"
},
  "geometry": {"coordinates":[140.99943300000001,-28.998264],"type":"Point"}
}