{
  "type": "Feature",
  "properties": {
    "gn:admin1_code":"5",
    "gn:admin2_code":"43920",
    "gn:asciiname":"Barabba",
    "gn:country_code":"AU",
    "gn:dem":102,
    "gn:feature_class":"P",
    "gn:feature_code":"PPL",
    "gn:name":"Barabba",
    "gn:population":0,
    "gn:timezone":"Australia/Adelaide",
    "iso:country":"AU",
    "wof:name":"Barabba",
    "wof:placetype":"locality"
},
  "geometry": {"coordinates":[138.58993000000001,-34.34498],"type":"Point"}
}