{
  "type": "Feature",
  "properties": {
    "iso:country":"AU",
    "name:ceb_x_preferred":[
        "Caloundra Airport"
    ],
    "name:eng_x_preferred":[
        "Caloundra Airport"
    ],
    "name:eng_x_variant":[
        "CUD",
        "YCDR"
    ],
    "name:jpn_x_preferred":[
        "\u30ab\u30e9\u30a6\u30f3\u30c9\u30e9\u7a7a\u6e2f"
    ],
    "name:msa_x_preferred":[
        "Lapangan Terbang Caloundra"
    ],
    "name:ron_x_preferred":[
        "Aeroportul Caloundra"
    ],
    "name:swe_x_preferred":[
        "Caloundra Airport"
    ],
    "name:zho_x_preferred":[
        "\u5361\u62c9\u5fb7\u62c9\u6a5f\u5834"
    ],
    "oa:elevation_ft":"12",
    "oa:type":"small_airport",
    "woe:hierarchy":{
        "country_id":23424748,
        "county_id":56072960,
        "planet_id":1,
        "state_id":2344702
    },
    "wof:name":"Caloundra Aerodrome",
    "wof:placetype":"campus"
},
  "geometry": {"coordinates":[153.10499999999999,-26.8017],"type":"Point"}
}