{
  "type": "Feature",
  "properties": {
    "iso:country":"AU",
    "oa:elevation_ft":"12",
    "oa:type":"small_airport",
    "woe:hierarchy":{
        "country_id":23424748,
        "county_id":56072960,
        "planet_id":1,
        "state_id":2344702
    },
    "wof:name":"Caloundra Aerodrome",
    "wof:placetype":"campus"
},
  "geometry": {"coordinates":[153.10499999999999,-26.8017],"type":"Point"}
}