{
  "type": "Feature",
  "properties": {
    "gn:admin1_code":"7.0",
    "gn:admin2_code":"22910.0",
    "gn:asciiname":"Rocklyn",
    "gn:country_code":"AU",
    "gn:dem":607,
    "gn:feature_class":"P",
    "gn:feature_code":"PPL",
    "gn:name":"Rocklyn",
    "gn:population":0,
    "gn:timezone":"Australia/Melbourne",
    "iso:country":"AU",
    "wof:name":"Rocklyn",
    "wof:placetype":"locality"
},
  "geometry": {"coordinates":[144.05000000000001,-37.43333],"type":"Point"}
}