{
  "type": "Feature",
  "properties": {
    "gn:admin1_code":"3",
    "gn:admin2_code":"72330",
    "gn:asciiname":"Curtin Springs",
    "gn:country_code":"AU",
    "gn:dem":495,
    "gn:elevation":"484.0",
    "gn:feature_class":"P",
    "gn:feature_code":"PPLL",
    "gn:name":"Curtin Springs",
    "gn:population":0,
    "gn:timezone":"Australia/Darwin",
    "iso:country":"AU",
    "name:deu_x_preferred":[
        "Curtin Springs"
    ],
    "wof:name":"Curtin Springs",
    "wof:placetype":"locality"
},
  "geometry": {"coordinates":[131.75,-25.33333],"type":"Point"}
}