{
  "type": "Feature",
  "properties": {
    "gn:country":"AU",
    "gn:fcode":"PPL",
    "gn:population":125,
    "iso:country":"AU",
    "name:ceb_x_preferred":[
        "Fowlers Bay"
    ],
    "name:eng_x_preferred":[
        "Fowlers Bay"
    ],
    "name:fas_x_preferred":[
        "\u0641\u0644\u0627\u0648\u0631\u0632 \u0628\u06cc"
    ],
    "name:fra_x_preferred":[
        "Fowlers Bay"
    ],
    "name:nld_x_preferred":[
        "Fowlers Bay"
    ],
    "name:rus_x_preferred":[
        "\u0424\u0430\u0443\u043b\u0435\u0440\u0441-\u0411\u0435\u0439"
    ],
    "name:swe_x_preferred":[
        "Fowlers Bay"
    ],
    "qs_pg:aaroncc":"AU",
    "qs_pg:gn_country":"AU",
    "qs_pg:gn_fcode":"PPL",
    "qs_pg:gn_pop":125,
    "qs_pg:name":"Fowlers Bay",
    "qs_pg:photos_9r":0,
    "qs_pg:photos_sr":0,
    "qs_pg:pop_sr":1,
    "qs_pg:qs_pg_placetype":"locality",
    "wof:name":"Fowlers Bay",
    "wof:placetype":"locality",
    "wof:population":125
},
  "geometry": {"coordinates":[132.44999999999999,-31.98333],"type":"Point"}
}