{
  "type": "Feature",
  "properties": {
    "gn:admin1_code":"2.0",
    "gn:admin2_code":"14600.0",
    "gn:asciiname":"Boona West",
    "gn:country_code":"AU",
    "gn:dem":271,
    "gn:feature_class":"P",
    "gn:feature_code":"PPL",
    "gn:name":"Boona West",
    "gn:population":0,
    "gn:timezone":"Australia/Sydney",
    "iso:country":"AU",
    "name:eng_x_preferred":[
        "Boona West"
    ],
    "wof:name":"Boona West",
    "wof:placetype":"locality"
},
  "geometry": {"coordinates":[147.13983999999999,-32.77658],"type":"Point"}
}