{
  "type": "Feature",
  "properties": {
    "gn:country":"AU",
    "gn:fcode":"PPL",
    "gn:population":0,
    "iso:country":"AU",
    "name:bar_x_preferred":[
        "Nandi"
    ],
    "name:ceb_x_preferred":[
        "Nandi"
    ],
    "name:deu_x_preferred":[
        "Nandi"
    ],
    "name:eng_x_preferred":[
        "Nandi"
    ],
    "name:fra_x_preferred":[
        "Nandi"
    ],
    "name:hrv_x_preferred":[
        "Nandi"
    ],
    "name:nld_x_preferred":[
        "Nandi"
    ],
    "name:pol_x_preferred":[
        "Nandi"
    ],
    "name:rus_x_preferred":[
        "\u041d\u0430\u043d\u0434\u0438"
    ],
    "name:swe_x_preferred":[
        "Nandi"
    ],
    "name:ukr_x_preferred":[
        "\u041d\u0430\u043d\u0434\u0456"
    ],
    "qs_pg:aaroncc":"AU",
    "qs_pg:gn_country":"AU",
    "qs_pg:gn_fcode":"PPL",
    "qs_pg:gn_pop":0,
    "qs_pg:name":"Nandi",
    "qs_pg:name_adm0":"Australia",
    "qs_pg:name_adm1":"Queensland",
    "qs_pg:photos":48,
    "qs_pg:photos_1k":10,
    "qs_pg:photos_9k":1,
    "qs_pg:photos_9r":2,
    "qs_pg:photos_all":48,
    "qs_pg:photos_sr":2,
    "qs_pg:pop_sr":4,
    "qs_pg:qs_pg_placetype":"locality",
    "qs_pg:qs_pg_placetype_gp":"Town",
    "qs_pg:woe_adm0":23424748,
    "woe:adm0_id":23424748,
    "woe:name_adm0":"Australia",
    "woe:name_adm1":"Queensland",
    "woe:placetype":"Town",
    "wof:name":"Nandi",
    "wof:placetype":"locality",
    "wof:population":108
},
  "geometry": {"coordinates":[151.16667000000001,-27.21667],"type":"Point"}
}