{
  "type": "Feature",
  "properties": {
    "gn:admin1_code":"2.0",
    "gn:admin2_code":"18020.0",
    "gn:asciiname":"Abington",
    "gn:country_code":"AU",
    "gn:dem":469,
    "gn:feature_class":"P",
    "gn:feature_code":"PPL",
    "gn:name":"Abington",
    "gn:population":0,
    "gn:timezone":"Australia/Sydney",
    "iso:country":"AU",
    "name:ceb_x_preferred":[
        "Abington"
    ],
    "name:deu_x_preferred":[
        "Abington"
    ],
    "name:eng_x_preferred":[
        "Abington"
    ],
    "name:fra_x_preferred":[
        "Abington"
    ],
    "name:ido_x_preferred":[
        "Abington"
    ],
    "name:ita_x_preferred":[
        "Abington"
    ],
    "name:kor_x_preferred":[
        "\uc560\ube59\ud134"
    ],
    "name:nld_x_preferred":[
        "Abington"
    ],
    "name:pol_x_preferred":[
        "Abington"
    ],
    "name:rus_x_preferred":[
        "\u0410\u0431\u0438\u043d\u0433\u0442\u043e\u043d"
    ],
    "name:swe_x_preferred":[
        "Abington"
    ],
    "name:ukr_x_preferred":[
        "\u0410\u0431\u0456\u043d\u0433\u0442\u043e\u043d"
    ],
    "name:vol_x_preferred":[
        "Abington"
    ],
    "wof:name":"Abington",
    "wof:placetype":"locality"
},
  "geometry": {"coordinates":[149.81169,-31.50863],"type":"Point"}
}