{
  "type": "Feature",
  "properties": {
    "gn:admin1_code":"2.0",
    "gn:admin2_code":"14950.0",
    "gn:asciiname":"French Park",
    "gn:country_code":"AU",
    "gn:dem":186,
    "gn:feature_class":"P",
    "gn:feature_code":"PPL",
    "gn:name":"French Park",
    "gn:population":0,
    "gn:timezone":"Australia/Sydney",
    "iso:country":"AU",
    "wof:name":"French Park",
    "wof:placetype":"locality"
},
  "geometry": {"coordinates":[146.92703999999995,-35.26229],"type":"Point"}
}