{
  "type": "Feature",
  "properties": {
    "iso:country":"AU",
    "name:eng_x_preferred":[
        "Driver"
    ],
    "name:fra_x_preferred":[
        "Driver"
    ],
    "qs:gn_adm0_cc":"AU",
    "qs:gn_fcode":"PPLX",
    "qs:gn_local":6301965,
    "qs:gn_nam_loc":"Palmerston, Palmerston, Northern Territory, AU",
    "qs:gn_namadm1":"03",
    "qs:gn_name":"Driver",
    "qs:local_max":307,
    "qs:local_sum":891,
    "qs:localhoods":5,
    "qs:name":"Driver",
    "qs:name_adm0":"Australia",
    "qs:name_adm1":"Northern Territory",
    "qs:name_adm2":"Palmerston",
    "qs:name_local":"Palmerston",
    "qs:photo_max":42,
    "qs:photo_sum":104,
    "qs:placetype":"Suburb",
    "qs:quad_count":10,
    "qs:woe_adm0":23424748,
    "qs:woe_adm1":2344701,
    "qs:woe_adm2":55864356,
    "qs:woe_lau":0,
    "qs:woe_local":1104879,
    "qs:woe_ver":"7.10.0",
    "wof:name":"Driver",
    "wof:placetype":"neighbourhood"
},
  "geometry": {"coordinates":[130.96986999999999,-12.49537],"type":"Point"}
}