{
  "type": "Feature",
  "properties": {
    "iso:country":"AU",
    "name:eng_x_preferred":[
        "Albury Central"
    ],
    "qs:gn_adm0_cc":"AU",
    "qs:gn_local":2178174,
    "qs:gn_nam_loc":"Albury, Albury, New South Wales, AU",
    "qs:gn_namadm1":"02",
    "qs:local_max":1057,
    "qs:local_sum":3629,
    "qs:localhoods":8,
    "qs:name":"Albury Central",
    "qs:name_adm0":"Australia",
    "qs:name_adm1":"New South Wales",
    "qs:name_adm2":"Albury",
    "qs:name_local":"Albury",
    "qs:photo_max":120,
    "qs:photo_sum":1057,
    "qs:placetype":"Suburb",
    "qs:quad_count":35,
    "qs:woe_adm0":23424748,
    "qs:woe_adm1":2344700,
    "qs:woe_adm2":55863864,
    "qs:woe_lau":0,
    "qs:woe_local":1099836,
    "qs:woe_ver":"7.10.0",
    "wof:lang":[
        "eng"
    ],
    "wof:name":"Albury Central",
    "wof:placetype":"neighbourhood"
},
  "geometry": {"coordinates":[146.91825299999999,-36.080316],"type":"Point"}
}