{
  "type": "Feature",
  "properties": {
    "gn:admin1_code":"4.0",
    "gn:admin2_code":"32500.0",
    "gn:asciiname":"Lilly Vale",
    "gn:country_code":"AU",
    "gn:dem":31,
    "gn:feature_class":"P",
    "gn:feature_code":"PPL",
    "gn:name":"Lilly Vale",
    "gn:population":0,
    "gn:timezone":"Australia/Brisbane",
    "iso:country":"AU",
    "wof:name":"Lilly Vale",
    "wof:placetype":"locality"
},
  "geometry": {"coordinates":[143.67743999999999,-14.48794],"type":"Point"}
}