{
  "type": "Feature",
  "properties": {
    "gn:admin1_code":"7",
    "gn:admin2_code":"24780",
    "gn:asciiname":"Timberoo",
    "gn:country_code":"AU",
    "gn:dem":66,
    "gn:feature_class":"P",
    "gn:feature_code":"PPL",
    "gn:name":"Timberoo",
    "gn:population":0,
    "gn:timezone":"Australia/Melbourne",
    "iso:country":"AU",
    "wof:name":"Timberoo",
    "wof:placetype":"locality"
},
  "geometry": {"coordinates":[142.18333000000001,-35.15],"type":"Point"}
}