{
  "type": "Feature",
  "properties": {
    "gn:admin1_code":"4.0",
    "gn:admin2_code":"30250.0",
    "gn:asciiname":"Kenchering Camp",
    "gn:country_code":"AU",
    "gn:dem":6,
    "gn:feature_class":"P",
    "gn:feature_code":"PPL",
    "gn:name":"Kenchering Camp",
    "gn:population":0,
    "gn:timezone":"Australia/Brisbane",
    "iso:country":"AU",
    "wof:name":"Kenchering Camp",
    "wof:placetype":"locality"
},
  "geometry": {"coordinates":[141.60543999999999,-13.84459],"type":"Point"}
}