{
  "type": "Feature",
  "properties": {
    "gn:admin1_code":"2.0",
    "gn:admin2_code":"14920.0",
    "gn:asciiname":"Fairview",
    "gn:country_code":"AU",
    "gn:dem":561,
    "gn:feature_class":"P",
    "gn:feature_code":"PPL",
    "gn:name":"Fairview",
    "gn:population":0,
    "gn:timezone":"Australia/Sydney",
    "iso:country":"AU",
    "wof:name":"Fairview",
    "wof:placetype":"locality"
},
  "geometry": {"coordinates":[150.80000000000001,-31.58333],"type":"Point"}
}