{
  "type": "Feature",
  "properties": {
    "gn:gn_country":"AU",
    "gn:gn_fcode":"PPL",
    "gn:gn_pop":249,
    "gn:population":249,
    "iso:country":"AU",
    "name:ceb_x_preferred":[
        "Red Range"
    ],
    "name:eng_x_preferred":[
        "Red Range"
    ],
    "name:fra_x_preferred":[
        "Red Range"
    ],
    "name:nld_x_preferred":[
        "Red Range"
    ],
    "name:swe_x_preferred":[
        "Red Range"
    ],
    "qs_pg:aaroncc":"AU",
    "qs_pg:gn_country":"AU",
    "qs_pg:gn_fcode":"PPL",
    "qs_pg:gn_pop":249,
    "qs_pg:name":"Red Range",
    "qs_pg:name_adm0":"Australia",
    "qs_pg:name_adm1":"New South Wales",
    "qs_pg:photos_9k":1,
    "qs_pg:photos_9r":1,
    "qs_pg:photos_all":1,
    "qs_pg:photos_sr":0,
    "qs_pg:pop_sr":2,
    "qs_pg:qs_pg_placetype":"locality",
    "qs_pg:qs_pg_placetype_gp":"Town",
    "qs_pg:woe_adm0":23424748,
    "woe:adm0_id":23424748,
    "woe:name_adm0":"Australia",
    "woe:name_adm1":"New South Wales",
    "woe:placetype":"Town",
    "wof:name":"Red Range",
    "wof:placetype":"locality",
    "wof:population":187
},
  "geometry": {"coordinates":[151.90000000000001,-29.78333],"type":"Point"}
}