{
  "type": "Feature",
  "properties": {
    "gn:admin1_code":"5",
    "gn:admin2_code":"44210",
    "gn:asciiname":"Dutton",
    "gn:country_code":"AU",
    "gn:dem":370,
    "gn:feature_class":"P",
    "gn:feature_code":"PPL",
    "gn:name":"Dutton",
    "gn:population":0,
    "gn:timezone":"Australia/Adelaide",
    "iso:country":"AU",
    "wof:name":"Dutton",
    "wof:placetype":"locality"
},
  "geometry": {"coordinates":[139.13333,-34.36667],"type":"Point"}
}