{
  "type": "Feature",
  "properties": {
    "gn:admin1_code":"06",
    "gn:asciiname":"Pipe Clay Lagoon",
    "gn:country_code":"AU",
    "gn:dem":1,
    "gn:feature_class":"P",
    "gn:feature_code":"PPL",
    "gn:name":"Pipe Clay Lagoon",
    "gn:population":0,
    "gn:timezone":"Australia/Hobart",
    "iso:country":"AU",
    "name:eng_x_preferred":[
        "Pipe Clay"
    ],
    "wof:name":"Pipe Clay Lagoon",
    "wof:placetype":"locality"
},
  "geometry": {"coordinates":[147.52746000000005,-42.98154],"type":"Point"}
}