{
  "type": "Feature",
  "properties": {
    "iso:country":"AU",
    "name:deu_x_preferred":[
        "Tallai"
    ],
    "name:eng_x_preferred":[
        "Tallai"
    ],
    "qs:gn_adm0_cc":"AU",
    "qs:gn_fcode":"PPLX",
    "qs:gn_local":2165087,
    "qs:gn_namadm1":"04",
    "qs:gn_name":"Tallai",
    "qs:local_max":10372,
    "qs:local_sum":57138,
    "qs:localhoods":62,
    "qs:name":"Tallai",
    "qs:name_adm0":"Australia",
    "qs:name_adm1":"Queensland",
    "qs:name_adm2":"Gold Coast City",
    "qs:name_local":"City of Gold Coast",
    "qs:photo_max":8,
    "qs:photo_sum":50,
    "qs:placetype":"Suburb",
    "qs:quad_count":17,
    "qs:woe_adm0":23424748,
    "qs:woe_adm1":2344702,
    "qs:woe_adm2":55864296,
    "qs:woe_lau":0,
    "qs:woe_local":7226269,
    "qs:woe_ver":"7.10.0",
    "wof:name":"Tallai",
    "wof:placetype":"neighbourhood"
},
  "geometry": {"coordinates":[153.31709532564901,-28.06359962732654],"type":"Point"}
}