{
  "type": "Feature",
  "properties": {
    "gn:admin1_code":"4.0",
    "gn:admin2_code":"35760.0",
    "gn:asciiname":"Dimbir",
    "gn:country_code":"AU",
    "gn:dem":111,
    "gn:feature_class":"P",
    "gn:feature_code":"PPL",
    "gn:name":"Dimbir",
    "gn:population":0,
    "gn:timezone":"Australia/Brisbane",
    "iso:country":"AU",
    "name:eng_x_preferred":[
        "Dimbir"
    ],
    "name:und_x_variant":[
        "Dirnbir"
    ],
    "wof:name":"Dimbir",
    "wof:placetype":"locality"
},
  "geometry": {"coordinates":[151.56031999999999,-25.60762],"type":"Point"}
}