{
  "type": "Feature",
  "properties": {
    "gn:gn_country":"AU",
    "gn:gn_fcode":"PPL",
    "gn:gn_pop":278,
    "gn:population":278,
    "iso:country":"AU",
    "name:eng_x_preferred":[
        "Gravesend"
    ],
    "name:fra_x_preferred":[
        "Gravesend"
    ],
    "name:nld_x_preferred":[
        "Gravesend"
    ],
    "name:swe_x_preferred":[
        "Gravesend"
    ],
    "qs_pg:aaroncc":"AU",
    "qs_pg:gn_country":"AU",
    "qs_pg:gn_fcode":"PPL",
    "qs_pg:gn_pop":278,
    "qs_pg:name":"Gravesend",
    "qs_pg:name_adm0":"Australia",
    "qs_pg:name_adm1":"New South Wales",
    "qs_pg:photos_9k":1,
    "qs_pg:photos_9r":1,
    "qs_pg:photos_all":3,
    "qs_pg:photos_sr":0,
    "qs_pg:pop_sr":2,
    "qs_pg:qs_pg_placetype":"locality",
    "qs_pg:qs_pg_placetype_gp":"Town",
    "qs_pg:woe_adm0":23424748,
    "woe:adm0_id":23424748,
    "woe:name_adm0":"Australia",
    "woe:name_adm1":"New South Wales",
    "woe:placetype":"Town",
    "wof:name":"Gravesend",
    "wof:placetype":"locality",
    "wof:population":278
},
  "geometry": {"coordinates":[150.31666999999999,-29.58333],"type":"Point"}
}