{
  "type": "Feature",
  "properties": {
    "gn:admin1_code":"7.0",
    "gn:admin2_code":"26890.0",
    "gn:asciiname":"Apsley",
    "gn:country_code":"AU",
    "gn:dem":113,
    "gn:feature_class":"P",
    "gn:feature_code":"PPL",
    "gn:name":"Apsley",
    "gn:population":0,
    "gn:timezone":"Australia/Melbourne",
    "iso:country":"AU",
    "wof:name":"Apsley",
    "wof:placetype":"locality"
},
  "geometry": {"coordinates":[141.08333000000005,-36.96667],"type":"Point"}
}