{
  "type": "Feature",
  "properties": {
    "gn:admin1_code":"3.0",
    "gn:admin2_code":"71300.0",
    "gn:asciiname":"Galawarra",
    "gn:country_code":"AU",
    "gn:dem":19,
    "gn:feature_class":"P",
    "gn:feature_code":"PPL",
    "gn:name":"Galawarra",
    "gn:population":0,
    "gn:timezone":"Australia/Darwin",
    "iso:country":"AU",
    "wof:name":"Galawarra",
    "wof:placetype":"locality"
},
  "geometry": {"coordinates":[135.59631999999999,-12.03793],"type":"Point"}
}