{
  "type": "Feature",
  "properties": {
    "iso:country":"AU",
    "name:bar_x_preferred":[
        "Mount Pleasant"
    ],
    "name:cat_x_preferred":[
        "Mount Pleasant"
    ],
    "name:ceb_x_preferred":[
        "Mount Pleasant"
    ],
    "name:ces_x_preferred":[
        "Mount Pleasant"
    ],
    "name:deu_x_preferred":[
        "Mount Pleasant"
    ],
    "name:eng_x_preferred":[
        "Mount Pleasant"
    ],
    "name:eng_x_variant":[
        "Mt Pleasant"
    ],
    "name:fra_x_preferred":[
        "Mount Pleasant"
    ],
    "name:ita_x_preferred":[
        "Mount Pleasant"
    ],
    "name:jpn_x_preferred":[
        "\u30de\u30a6\u30f3\u30c8\u30fb\u30d7\u30ec\u30b6\u30f3\u30c8"
    ],
    "name:kor_x_preferred":[
        "\ub9c8\uc6b4\ud2b8\ud50c\ub808\uc804\ud2b8"
    ],
    "name:mlg_x_preferred":[
        "Mount Pleasant"
    ],
    "name:nld_x_preferred":[
        "Mount Pleasant"
    ],
    "name:nor_x_preferred":[
        "Mount Pleasant"
    ],
    "name:pol_x_preferred":[
        "Mount Pleasant"
    ],
    "name:por_x_preferred":[
        "Mount Pleasant"
    ],
    "name:rus_x_preferred":[
        "\u041c\u0430\u0443\u043d\u0442-\u041f\u043b\u0435\u0437\u0430\u043d\u0442"
    ],
    "name:spa_x_preferred":[
        "Mount Pleasant"
    ],
    "name:srp_x_preferred":[
        "\u041c\u0430\u0443\u043d\u0442 \u041f\u043b\u0435\u0437\u0430\u043d\u0442"
    ],
    "name:swe_x_preferred":[
        "Mount Pleasant"
    ],
    "name:ukr_x_preferred":[
        "\u041c\u0430\u0443\u043d\u0442-\u041f\u043b\u0435\u0437\u0430\u043d\u0442"
    ],
    "name:unk_x_variant":[
        "Mount Pleasant"
    ],
    "name:vol_x_preferred":[
        "Mount Pleasant"
    ],
    "qs:gn_adm0_cc":"AU",
    "qs:gn_local":2177091,
    "qs:gn_nam_loc":"ballarat",
    "qs:gn_namadm1":"07",
    "qs:local_max":2722,
    "qs:local_sum":9720,
    "qs:localhoods":15,
    "qs:name":"Mount Pleasant",
    "qs:name_adm0":"Australia",
    "qs:name_adm1":"Victoria",
    "qs:name_adm2":"City of Ballarat",
    "qs:name_local":"Ballarat",
    "qs:photo_max":67,
    "qs:photo_sum":75,
    "qs:placetype":"Suburb",
    "qs:quad_count":5,
    "qs:woe_adm0":23424748,
    "qs:woe_adm1":2344705,
    "qs:woe_adm2":55864013,
    "qs:woe_lau":0,
    "qs:woe_local":1100071,
    "qs:woe_ver":"7.10.0",
    "wof:lang":[
        "eng"
    ],
    "wof:name":"Mount Pleasant",
    "wof:placetype":"neighbourhood"
},
  "geometry": {"coordinates":[143.84037900000001,-37.585081],"type":"Point"}
}