{
  "type": "Feature",
  "properties": {
    "iso:country":"AU",
    "name:ceb_x_preferred":[
        "Cedar Valley"
    ],
    "name:deu_x_preferred":[
        "Cedar Valley"
    ],
    "name:pol_x_preferred":[
        "Cedar Valley"
    ],
    "qs_pg:aaroncc":"AU",
    "qs_pg:name":"Cedar Valley",
    "qs_pg:name_adm0":"Australia",
    "qs_pg:name_adm1":"New South Wales",
    "qs_pg:photos":121,
    "qs_pg:photos_1k":25,
    "qs_pg:photos_9k":1,
    "qs_pg:photos_9r":3,
    "qs_pg:photos_all":121,
    "qs_pg:photos_sr":3,
    "qs_pg:pop_sr":0,
    "qs_pg:qs_pg_placetype":"locality",
    "qs_pg:qs_pg_placetype_gp":"Town",
    "qs_pg:woe_adm0":23424748,
    "woe:adm0_id":23424748,
    "woe:name_adm0":"Australia",
    "woe:name_adm1":"New South Wales",
    "woe:placetype":"Town",
    "wof:name":"Cedar Valley",
    "wof:placetype":"locality"
},
  "geometry": {"coordinates":[150.31777299999999,-33.7841],"type":"Point"}
}