{
  "type": "Feature",
  "properties": {
    "iso:country":"AU",
    "name:ceb_x_preferred":[
        "Bulwer Island"
    ],
    "name:eng_x_preferred":[
        "Bulwer Island"
    ],
    "name:nld_x_preferred":[
        "Bulwer Island"
    ],
    "name:swe_x_preferred":[
        "Bulwer Island"
    ],
    "qs:gn_adm0_cc":"AU",
    "qs:gn_local":2174003,
    "qs:gn_nam_loc":"Brisbane, Brisbane, Queensland, AU",
    "qs:gn_namadm1":"04",
    "qs:local_max":15217,
    "qs:local_sum":137917,
    "qs:localhoods":252,
    "qs:name":"Bulwer Island",
    "qs:name_adm0":"Australia",
    "qs:name_adm1":"Queensland",
    "qs:name_adm2":"Brisbane",
    "qs:name_local":"Brisbane",
    "qs:photo_max":286,
    "qs:photo_sum":377,
    "qs:placetype":"Suburb",
    "qs:quad_count":14,
    "qs:woe_adm0":23424748,
    "qs:woe_adm1":2344702,
    "qs:woe_adm2":55864298,
    "qs:woe_lau":0,
    "qs:woe_local":1100661,
    "qs:woe_ver":"7.10.0",
    "wd:wordcount":280,
    "wof:lang":[
        "eng"
    ],
    "wof:name":"Bulwer Island",
    "wof:placetype":"neighbourhood"
},
  "geometry": {"coordinates":[153.14110962961641,-27.40743673895923],"type":"Point"}
}