{
  "type": "Feature",
  "properties": {
    "gn:admin1_code":"2.0",
    "gn:admin2_code":"10300.0",
    "gn:asciiname":"Condoulpe",
    "gn:country_code":"AU",
    "gn:dem":66,
    "gn:feature_class":"P",
    "gn:feature_code":"PPL",
    "gn:name":"Condoulpe",
    "gn:population":0,
    "gn:timezone":"Australia/Sydney",
    "iso:country":"AU",
    "wof:name":"Condoulpe",
    "wof:placetype":"locality"
},
  "geometry": {"coordinates":[143.55828,-34.77172],"type":"Point"}
}