{
  "type": "Feature",
  "properties": {
    "gn:admin1_code":"7.0",
    "gn:admin2_code":"23350.0",
    "gn:asciiname":"Chiltern Valley",
    "gn:country_code":"AU",
    "gn:dem":186,
    "gn:feature_class":"P",
    "gn:feature_code":"PPL",
    "gn:name":"Chiltern Valley",
    "gn:population":0,
    "gn:timezone":"Australia/Melbourne",
    "iso:country":"AU",
    "wof:name":"Chiltern Valley",
    "wof:placetype":"locality"
},
  "geometry": {"coordinates":[146.54075,-36.13994],"type":"Point"}
}