{
  "type": "Feature",
  "properties": {
    "gn:admin1_code":"4.0",
    "gn:admin2_code":"34570.0",
    "gn:asciiname":"Pascoe River",
    "gn:country_code":"AU",
    "gn:dem":68,
    "gn:feature_class":"P",
    "gn:feature_code":"PPL",
    "gn:name":"Pascoe River",
    "gn:population":0,
    "gn:timezone":"Australia/Brisbane",
    "iso:country":"AU",
    "name:ceb_x_preferred":[
        "Pascoe River"
    ],
    "name:swe_x_preferred":[
        "Pascoe River"
    ],
    "wof:name":"Pascoe River",
    "wof:placetype":"locality"
},
  "geometry": {"coordinates":[142.92301,-12.81822],"type":"Point"}
}