{
  "type": "Feature",
  "properties": {
    "gn:admin1_code":"7",
    "gn:admin2_code":"22410",
    "gn:asciiname":"Tahara",
    "gn:country_code":"AU",
    "gn:dem":150,
    "gn:feature_class":"P",
    "gn:feature_code":"PPL",
    "gn:name":"Tahara",
    "gn:population":0,
    "gn:timezone":"Australia/Melbourne",
    "iso:country":"AU",
    "name:bar_x_preferred":[
        "Tahara"
    ],
    "name:ceb_x_preferred":[
        "Tahara"
    ],
    "name:deu_x_preferred":[
        "Tahara"
    ],
    "name:fra_x_preferred":[
        "Tahara"
    ],
    "name:ita_x_preferred":[
        "Tahara"
    ],
    "name:jpn_x_preferred":[
        "\u7530\u539f"
    ],
    "name:mlg_x_preferred":[
        "Tahara"
    ],
    "name:swe_x_preferred":[
        "Tahara"
    ],
    "name:ukr_x_preferred":[
        "\u0422\u0430\u0445\u0430\u0440\u0430"
    ],
    "wof:name":"Tahara",
    "wof:placetype":"locality"
},
  "geometry": {"coordinates":[141.69999999999999,-37.73333],"type":"Point"}
}