{
  "type": "Feature",
  "properties": {
    "iso:country":"AU",
    "name:deu_x_preferred":[
        "Manahan"
    ],
    "name:eng_x_preferred":[
        "Manahan"
    ],
    "name:jpn_x_preferred":[
        "\u30de\u30ca\u30cf\u30f3"
    ],
    "qs:gn_adm0_cc":"AU",
    "qs:gn_local":2147714,
    "qs:local_max":35533,
    "qs:local_sum":687549,
    "qs:localhoods":516,
    "qs:name":"Manahan",
    "qs:name_adm0":"Australia",
    "qs:name_adm1":"New South Wales",
    "qs:name_adm2":"City of Bankstown",
    "qs:name_local":"Sydney",
    "qs:photo_max":119,
    "qs:photo_sum":505,
    "qs:placetype":"Suburb",
    "qs:quad_count":27,
    "qs:woe_adm0":23424748,
    "qs:woe_adm1":2344700,
    "qs:woe_adm2":55864193,
    "qs:woe_lau":0,
    "qs:woe_local":1105779,
    "qs:woe_ver":"7.10.0",
    "wd:wordcount":219,
    "wof:lang":[
        "eng"
    ],
    "wof:name":"Manahan",
    "wof:placetype":"neighbourhood"
},
  "geometry": {"coordinates":[150.99922599999999,-33.920807],"type":"Point"}
}