{
  "type": "Feature",
  "properties": {
    "iso:country":"AU",
    "name:eng_x_preferred":[
        "St Kilda South"
    ],
    "name:unk_x_variant":[
        "St Kilda South"
    ],
    "qs:gn_adm0_cc":"AU",
    "qs:gn_fcode":"PPL",
    "qs:gn_local":2158177,
    "qs:gn_namadm1":"07",
    "qs:gn_name":"St Kilda West",
    "qs:local_max":22745,
    "qs:local_sum":338594,
    "qs:localhoods":407,
    "qs:name":"St Kilda South",
    "qs:name_adm0":"Australia",
    "qs:name_adm1":"Victoria",
    "qs:name_adm2":"Port Phillip",
    "qs:name_local":"Melbourne",
    "qs:photo_max":754,
    "qs:photo_sum":6102,
    "qs:placetype":"Suburb",
    "qs:quad_count":56,
    "qs:woe_adm0":23424748,
    "qs:woe_adm1":2344705,
    "qs:woe_adm2":55864241,
    "qs:woe_lau":0,
    "qs:woe_local":1103816,
    "qs:woe_ver":"7.10.0",
    "wd:wordcount":2530,
    "wof:lang":[
        "eng"
    ],
    "wof:name":"St Kilda South",
    "wof:placetype":"neighbourhood"
},
  "geometry": {"coordinates":[144.977667,-37.868174],"type":"Point"}
}