{
  "type": "Feature",
  "properties": {
    "gn:admin1_code":"8",
    "gn:admin2_code":"55040",
    "gn:asciiname":"Linden",
    "gn:country_code":"AU",
    "gn:dem":426,
    "gn:feature_class":"P",
    "gn:feature_code":"PPL",
    "gn:name":"Linden",
    "gn:population":0,
    "gn:timezone":"Australia/Perth",
    "iso:country":"AU",
    "name:eng_x_preferred":[
        "Linden"
    ],
    "wof:name":"Linden",
    "wof:placetype":"locality"
},
  "geometry": {"coordinates":[122.4258,-29.30658],"type":"Point"}
}