{
  "type": "Feature",
  "properties": {
    "gn:admin1_code":"8",
    "gn:admin2_code":"55040",
    "gn:asciiname":"Linden",
    "gn:country_code":"AU",
    "gn:dem":426,
    "gn:feature_class":"P",
    "gn:feature_code":"PPL",
    "gn:name":"Linden",
    "gn:population":0,
    "gn:timezone":"Australia/Perth",
    "iso:country":"AU",
    "name:cat_x_preferred":[
        "Linden"
    ],
    "name:ceb_x_preferred":[
        "Linden"
    ],
    "name:ces_x_preferred":[
        "Linden"
    ],
    "name:deu_x_preferred":[
        "Linden"
    ],
    "name:eng_x_preferred":[
        "Linden"
    ],
    "name:epo_x_preferred":[
        "Linden"
    ],
    "name:est_x_preferred":[
        "Linden"
    ],
    "name:eus_x_preferred":[
        "Linden"
    ],
    "name:fas_x_preferred":[
        "\u0644\u06cc\u0646\u062f\u0646"
    ],
    "name:fin_x_preferred":[
        "Lind\u00e9n"
    ],
    "name:fra_x_preferred":[
        "Linden"
    ],
    "name:heb_x_preferred":[
        "\u05dc\u05d9\u05e0\u05d3\u05df"
    ],
    "name:ita_x_preferred":[
        "Linden"
    ],
    "name:jpn_x_preferred":[
        "\u30ea\u30f3\u30c7\u30f3"
    ],
    "name:kor_x_preferred":[
        "\ub9b0\ub4e0"
    ],
    "name:mkd_x_preferred":[
        "\u041b\u0438\u043d\u0434\u0435\u043d"
    ],
    "name:nld_x_preferred":[
        "Linden"
    ],
    "name:nor_x_preferred":[
        "Linden"
    ],
    "name:pol_x_preferred":[
        "Linden"
    ],
    "name:por_x_preferred":[
        "Linden"
    ],
    "name:rus_x_preferred":[
        "\u041b\u0438\u043d\u0434\u0435\u043d"
    ],
    "name:slk_x_preferred":[
        "Linden"
    ],
    "name:spa_x_preferred":[
        "Linden"
    ],
    "name:srp_x_preferred":[
        "\u041b\u0438\u043d\u0434\u0435\u043d"
    ],
    "name:swe_x_preferred":[
        "Linden"
    ],
    "name:tgl_x_preferred":[
        "Linden"
    ],
    "name:ukr_x_preferred":[
        "\u041b\u0456\u043d\u0434\u0435\u043d"
    ],
    "name:vol_x_preferred":[
        "Linden"
    ],
    "name:zho_x_preferred":[
        "\u6797\u767b"
    ],
    "wof:name":"Linden",
    "wof:placetype":"locality"
},
  "geometry": {"coordinates":[122.4258,-29.30658],"type":"Point"}
}