{
  "type": "Feature",
  "properties": {
    "gn:admin1_code":"8",
    "gn:admin2_code":"55810",
    "gn:asciiname":"Lennonville",
    "gn:country_code":"AU",
    "gn:dem":472,
    "gn:feature_class":"P",
    "gn:feature_code":"PPL",
    "gn:name":"Lennonville",
    "gn:population":0,
    "gn:timezone":"Australia/Perth",
    "iso:country":"AU",
    "wof:name":"Lennonville",
    "wof:placetype":"locality"
},
  "geometry": {"coordinates":[117.8348,-27.97094],"type":"Point"}
}