{
  "type": "Feature",
  "properties": {
    "gn:admin1_code":"7",
    "gn:admin2_code":"25810",
    "gn:asciiname":"Stuart Mill",
    "gn:country_code":"AU",
    "gn:dem":270,
    "gn:feature_class":"P",
    "gn:feature_code":"PPL",
    "gn:name":"Stuart Mill",
    "gn:population":0,
    "gn:timezone":"Australia/Melbourne",
    "iso:country":"AU",
    "wof:name":"Stuart Mill",
    "wof:placetype":"locality"
},
  "geometry": {"coordinates":[143.28621999999999,-36.8053],"type":"Point"}
}