{
  "type": "Feature",
  "properties": {
    "gn:admin1_code":"2.0",
    "gn:admin2_code":"18020.0",
    "gn:asciiname":"Dapper",
    "gn:country_code":"AU",
    "gn:dem":403,
    "gn:feature_class":"P",
    "gn:feature_code":"PPL",
    "gn:name":"Dapper",
    "gn:population":0,
    "gn:timezone":"Australia/Sydney",
    "iso:country":"AU",
    "wof:name":"Dapper",
    "wof:placetype":"locality"
},
  "geometry": {"coordinates":[149.23333,-32.21667],"type":"Point"}
}