{
  "type": "Feature",
  "properties": {
    "gn:admin1_code":"8.0",
    "gn:admin2_code":"55600.0",
    "gn:asciiname":"Cairn Hill",
    "gn:country_code":"AU",
    "gn:dem":231,
    "gn:feature_class":"P",
    "gn:feature_code":"PPL",
    "gn:name":"Cairn Hill",
    "gn:population":0,
    "gn:timezone":"Australia/Perth",
    "iso:country":"AU",
    "name:ceb_x_preferred":[
        "Cairn Hill"
    ],
    "name:eng_x_preferred":[
        "Cairn Hill"
    ],
    "wof:name":"Cairn Hill",
    "wof:placetype":"locality"
},
  "geometry": {"coordinates":[116.03166,-30.54282000000001],"type":"Point"}
}