{
  "type": "Feature",
  "properties": {
    "gn:admin1_code":"7.0",
    "gn:admin2_code":"20830.0",
    "gn:asciiname":"Knotts Siding",
    "gn:cc2":"AU",
    "gn:country_code":"AU",
    "gn:dem":462,
    "gn:feature_class":"P",
    "gn:feature_code":"PPL",
    "gn:name":"Knotts Siding",
    "gn:population":0,
    "gn:timezone":"Australia/Melbourne",
    "iso:country":"AU",
    "name:und_x_variant":[
        "Knotts",
        "Knotts Siding"
    ],
    "wof:name":"Knotts Siding",
    "wof:placetype":"locality"
},
  "geometry": {"coordinates":[146.38333,-37.96667],"type":"Point"}
}