{
  "type": "Feature",
  "properties": {
    "gn:admin1_code":"4.0",
    "gn:admin2_code":"34860.0",
    "gn:asciiname":"Boondarra",
    "gn:country_code":"AU",
    "gn:dem":254,
    "gn:feature_class":"P",
    "gn:feature_code":"PPL",
    "gn:name":"Boondarra",
    "gn:population":0,
    "gn:timezone":"Australia/Brisbane",
    "iso:country":"AU",
    "wof:name":"Boondarra",
    "wof:placetype":"locality"
},
  "geometry": {"coordinates":[148.40000000000001,-27.33333],"type":"Point"}
}