{
  "type": "Feature",
  "properties": {
    "gn:admin1_code":"4.0",
    "gn:admin2_code":"32500.0",
    "gn:asciiname":"Clayhole Yards",
    "gn:country_code":"AU",
    "gn:dem":9,
    "gn:feature_class":"P",
    "gn:feature_code":"PPL",
    "gn:name":"Clayhole Yards",
    "gn:population":0,
    "gn:timezone":"Australia/Brisbane",
    "iso:country":"AU",
    "wof:name":"Clayhole Yards",
    "wof:placetype":"locality"
},
  "geometry": {"coordinates":[144.22776999999999,-14.45903],"type":"Point"}
}