{
  "type": "Feature",
  "properties": {
    "iso:country":"AU",
    "name:eng_x_preferred":[
        "Charman"
    ],
    "name:fra_x_preferred":[
        "Roy Charman"
    ],
    "name:unk_x_variant":[
        "Charman"
    ],
    "qs:gn_adm0_cc":"AU",
    "qs:gn_local":2158177,
    "qs:local_max":22745,
    "qs:local_sum":338594,
    "qs:localhoods":407,
    "qs:name":"Charman",
    "qs:name_adm0":"Australia",
    "qs:name_adm1":"Victoria",
    "qs:name_adm2":"Bayside",
    "qs:name_local":"Melbourne",
    "qs:photo_max":46,
    "qs:photo_sum":166,
    "qs:placetype":"Suburb",
    "qs:quad_count":7,
    "qs:woe_adm0":23424748,
    "qs:woe_adm1":2344705,
    "qs:woe_adm2":55864256,
    "qs:woe_lau":0,
    "qs:woe_local":1103816,
    "qs:woe_ver":"7.10.0",
    "wd:wordcount":123,
    "wof:lang":[
        "eng"
    ],
    "wof:name":"Charman",
    "wof:placetype":"neighbourhood"
},
  "geometry": {"coordinates":[145.05188799999999,-37.985317],"type":"Point"}
}