{
  "type": "Feature",
  "properties": {
    "gn:gn_country":"AU",
    "gn:gn_fcode":"PPL",
    "gn:gn_pop":535,
    "gn:population":535,
    "iso:country":"AU",
    "name:dut_x_preferred":[
        "Moorook"
    ],
    "name:eng_x_preferred":[
        "Moorook"
    ],
    "name:fre_x_preferred":[
        "Moorook"
    ],
    "name:swe_x_preferred":[
        "Moorook"
    ],
    "qs_pg:aaroncc":"AU",
    "qs_pg:gn_country":"AU",
    "qs_pg:gn_fcode":"PPL",
    "qs_pg:gn_pop":535,
    "qs_pg:name":"Moorook",
    "qs_pg:name_adm0":"Australia",
    "qs_pg:name_adm1":"South Australia",
    "qs_pg:photos_9k":1,
    "qs_pg:photos_9r":1,
    "qs_pg:photos_all":1,
    "qs_pg:photos_sr":0,
    "qs_pg:pop_sr":2,
    "qs_pg:qs_pg_placetype":"locality",
    "qs_pg:qs_pg_placetype_gp":"Town",
    "qs_pg:woe_adm0":23424748,
    "woe:adm0_id":23424748,
    "woe:name_adm0":"Australia",
    "woe:name_adm1":"South Australia",
    "woe:placetype":"Town",
    "wof:name":"Moorook",
    "wof:placetype":"locality",
    "wof:population":535
},
  "geometry": {"coordinates":[140.35657,-34.26627],"type":"Point"}
}