{
  "type": "Feature",
  "properties": {
    "gn:admin1_code":"7.0",
    "gn:admin2_code":"20110.0",
    "gn:asciiname":"Running Creek",
    "gn:country_code":"AU",
    "gn:dem":461,
    "gn:feature_class":"P",
    "gn:feature_code":"PPL",
    "gn:name":"Running Creek",
    "gn:population":0,
    "gn:timezone":"Australia/Melbourne",
    "iso:country":"AU",
    "wof:name":"Running Creek",
    "wof:placetype":"locality"
},
  "geometry": {"coordinates":[146.91666999999995,-36.61667],"type":"Point"}
}