{
  "type": "Feature",
  "properties": {
    "iso:country":"AU",
    "oa:elevation_ft":"334",
    "oa:type":"small_airport",
    "woe:hierarchy":{
        "country_id":23424748,
        "county_id":55863947,
        "planet_id":1,
        "state_id":2344702
    },
    "wof:name":"Arrabury Aerodrome",
    "wof:placetype":"campus"
},
  "geometry": {"coordinates":[141.04722222000001,-26.69055556],"type":"Point"}
}