{
  "type": "Feature",
  "properties": {
    "iso:country":"AU",
    "name:ceb_x_preferred":[
        "Arrabury Airport"
    ],
    "name:deu_x_preferred":[
        "Flugplatz Arrabury"
    ],
    "name:eng_x_preferred":[
        "Arrabury Airport"
    ],
    "name:fas_x_preferred":[
        "\u0641\u0631\u0648\u062f\u06af\u0627\u0647 \u0622\u0631\u0627\u0628\u0631\u06cc"
    ],
    "name:fra_x_preferred":[
        "a\u00e9roport d'Arrabury"
    ],
    "name:ind_x_preferred":[
        "Bandar Udara Arrabury"
    ],
    "name:nld_x_preferred":[
        "Arrabury Airport"
    ],
    "name:nob_x_preferred":[
        "Arrabury lufthavn"
    ],
    "name:ron_x_preferred":[
        "Aeroportul Arrabury"
    ],
    "name:swe_x_preferred":[
        "Arrabury Airport"
    ],
    "name:tgk_x_preferred":[
        "\u0424\u0443\u0440\u0443\u0434\u0433\u043e\u04b3\u0438 \u043e\u0440\u043e\u0431\u0440\u0438"
    ],
    "name:zho_x_preferred":[
        "\u963f\u62c9\u8c9d\u91cc\u6a5f\u5834"
    ],
    "oa:elevation_ft":"334",
    "oa:type":"small_airport",
    "woe:hierarchy":{
        "country_id":23424748,
        "county_id":55863947,
        "planet_id":1,
        "state_id":2344702
    },
    "wof:name":"Arrabury Aerodrome",
    "wof:placetype":"campus"
},
  "geometry": {"coordinates":[141.04722222000001,-26.69055556],"type":"Point"}
}