{
  "type": "Feature",
  "properties": {
    "gn:admin1_code":"4.0",
    "gn:admin2_code":"36360.0",
    "gn:asciiname":"Barmoya East",
    "gn:country_code":"AU",
    "gn:dem":28,
    "gn:feature_class":"P",
    "gn:feature_code":"PPL",
    "gn:name":"Barmoya East",
    "gn:population":0,
    "gn:timezone":"Australia/Brisbane",
    "iso:country":"AU",
    "name:eng_x_preferred":[
        "Barmoya East"
    ],
    "wof:name":"Barmoya East",
    "wof:placetype":"locality"
},
  "geometry": {"coordinates":[150.54667000000001,-23.14646],"type":"Point"}
}