{
  "type": "Feature",
  "properties": {
    "gn:admin1_code":"7.0",
    "gn:admin2_code":"22980.0",
    "gn:asciiname":"Ellam",
    "gn:country_code":"AU",
    "gn:dem":116,
    "gn:feature_class":"P",
    "gn:feature_code":"PPL",
    "gn:name":"Ellam",
    "gn:population":0,
    "gn:timezone":"Australia/Melbourne",
    "iso:country":"AU",
    "wof:name":"Ellam",
    "wof:placetype":"locality"
},
  "geometry": {"coordinates":[142.05000000000001,-36.05],"type":"Point"}
}