{
  "type": "Feature",
  "properties": {
    "gn:admin1_code":"7.0",
    "gn:admin2_code":"21270.0",
    "gn:asciiname":"Barrakee",
    "gn:country_code":"AU",
    "gn:dem":135,
    "gn:feature_class":"P",
    "gn:feature_code":"PPL",
    "gn:name":"Barrakee",
    "gn:population":0,
    "gn:timezone":"Australia/Melbourne",
    "iso:country":"AU",
    "wof:name":"Barrakee",
    "wof:placetype":"locality"
},
  "geometry": {"coordinates":[143.44999999999999,-36.26667],"type":"Point"}
}