{
  "type": "Feature",
  "properties": {
    "gn:admin1_code":"7.0",
    "gn:admin2_code":"20830.0",
    "gn:asciiname":"Gould",
    "gn:country_code":"AU",
    "gn:dem":207,
    "gn:feature_class":"P",
    "gn:feature_code":"PPL",
    "gn:name":"Gould",
    "gn:population":0,
    "gn:timezone":"Australia/Melbourne",
    "iso:country":"AU",
    "name:cat_x_preferred":[
        "Gould"
    ],
    "name:ceb_x_preferred":[
        "Gould"
    ],
    "name:ces_x_preferred":[
        "Gould"
    ],
    "name:deu_x_preferred":[
        "Gould"
    ],
    "name:epo_x_preferred":[
        "Gould"
    ],
    "name:fin_x_preferred":[
        "Gould"
    ],
    "name:fra_x_preferred":[
        "Gould"
    ],
    "name:ita_x_preferred":[
        "Gould"
    ],
    "name:jpn_x_preferred":[
        "\u30b0\u30fc\u30eb\u30c9"
    ],
    "name:kor_x_preferred":[
        "\uad74\ub4dc"
    ],
    "name:lat_x_preferred":[
        "Gould"
    ],
    "name:lav_x_preferred":[
        "Gould"
    ],
    "name:nld_x_preferred":[
        "Gould"
    ],
    "name:pol_x_preferred":[
        "Gould"
    ],
    "name:por_x_preferred":[
        "Gould"
    ],
    "name:rus_x_preferred":[
        "\u0413\u0443\u043b\u0434"
    ],
    "name:spa_x_preferred":[
        "Gould"
    ],
    "name:srp_x_preferred":[
        "\u0413\u0443\u043b\u0434"
    ],
    "name:swe_x_preferred":[
        "Gould"
    ],
    "name:ukr_x_preferred":[
        "\u0413\u0443\u043b\u0434"
    ],
    "wof:name":"Gould",
    "wof:placetype":"locality"
},
  "geometry": {"coordinates":[146.34999999999999,-38.06667],"type":"Point"}
}