{
  "type": "Feature",
  "properties": {
    "gn:admin1_code":"4.0",
    "gn:admin2_code":"33980.0",
    "gn:asciiname":"McDonald Flat",
    "gn:country_code":"AU",
    "gn:dem":251,
    "gn:feature_class":"P",
    "gn:feature_code":"PPL",
    "gn:name":"McDonald Flat",
    "gn:population":0,
    "gn:timezone":"Australia/Brisbane",
    "iso:country":"AU",
    "wof:name":"McDonald Flat",
    "wof:placetype":"locality"
},
  "geometry": {"coordinates":[147.66666999999995,-22.88333],"type":"Point"}
}