{
  "type": "Feature",
  "properties": {
    "gn:country":"AU",
    "gn:fcode":"PPL",
    "gn:population":201,
    "iso:country":"AU",
    "qs_pg:aaroncc":"AU",
    "qs_pg:gn_country":"AU",
    "qs_pg:gn_fcode":"PPL",
    "qs_pg:gn_pop":201,
    "qs_pg:name":"Gowang",
    "qs_pg:photos_9r":0,
    "qs_pg:photos_sr":0,
    "qs_pg:pop_sr":2,
    "qs_pg:qs_pg_placetype":"locality",
    "wof:name":"Gowang",
    "wof:placetype":"locality",
    "wof:population":201
},
  "geometry": {"coordinates":[149.09999999999999,-31.41667],"type":"Point"}
}