{
  "type": "Feature",
  "properties": {
    "iso:country":"AU",
    "name:bar_x_preferred":[
        "Burnside"
    ],
    "name:cat_x_preferred":[
        "Burnside"
    ],
    "name:ceb_x_preferred":[
        "Burnside"
    ],
    "name:deu_x_preferred":[
        "Burnside"
    ],
    "name:eng_x_preferred":[
        "Burnside"
    ],
    "name:fra_x_preferred":[
        "Burnside"
    ],
    "name:ita_x_preferred":[
        "Burnside"
    ],
    "name:jpn_x_preferred":[
        "\u30d0\u30fc\u30f3\u30b5\u30a4\u30c9"
    ],
    "name:nld_x_preferred":[
        "Burnside"
    ],
    "name:pol_x_preferred":[
        "Burnside"
    ],
    "name:por_x_preferred":[
        "Burnside"
    ],
    "name:rus_x_preferred":[
        "\u0411\u0451\u0440\u043d\u0441\u0430\u0439\u0434"
    ],
    "name:spa_x_preferred":[
        "Burnside"
    ],
    "name:srp_x_preferred":[
        "\u0411\u0435\u0440\u043d\u0441\u0430\u0458\u0434"
    ],
    "name:swe_x_preferred":[
        "Burnside"
    ],
    "name:ukr_x_preferred":[
        "\u0411\u0435\u0440\u043d\u0441\u0430\u0439\u0434"
    ],
    "name:vol_x_preferred":[
        "Burnside"
    ],
    "qs:gn_adm0_cc":"AU",
    "qs:gn_local":2078025,
    "qs:local_max":18505,
    "qs:local_sum":99726,
    "qs:localhoods":191,
    "qs:name":"Burnside",
    "qs:name_adm0":"Australia",
    "qs:name_adm1":"South Australia",
    "qs:name_adm2":"City of Burnside",
    "qs:name_local":"Adelaide",
    "qs:photo_max":34,
    "qs:photo_sum":105,
    "qs:placetype":"Suburb",
    "qs:quad_count":10,
    "qs:woe_adm0":23424748,
    "qs:woe_adm1":2344703,
    "qs:woe_adm2":55864130,
    "qs:woe_lau":0,
    "qs:woe_local":1099805,
    "qs:woe_ver":"7.10.0",
    "wof:lang":[
        "eng"
    ],
    "wof:name":"Burnside",
    "wof:placetype":"neighbourhood"
},
  "geometry": {"coordinates":[138.65903900000001,-34.93952],"type":"Point"}
}