{
  "type": "Feature",
  "properties": {
    "gn:admin1_code":"05",
    "gn:asciiname":"The Sill",
    "gn:country_code":"AU",
    "gn:dem":67,
    "gn:feature_class":"P",
    "gn:feature_code":"PPLL",
    "gn:name":"The Sill",
    "gn:population":0,
    "gn:timezone":"Australia/Adelaide",
    "iso:country":"AU",
    "wof:name":"The Sill",
    "wof:placetype":"locality"
},
  "geometry": {"coordinates":[138.6754,-28.16048],"type":"Point"}
}