{
  "type": "Feature",
  "properties": {
    "gn:admin1_code":"5",
    "gn:admin2_code":"41750",
    "gn:asciiname":"Warrachie",
    "gn:country_code":"AU",
    "gn:dem":76,
    "gn:feature_class":"P",
    "gn:feature_code":"PPL",
    "gn:name":"Warrachie",
    "gn:population":0,
    "gn:timezone":"Australia/Adelaide",
    "iso:country":"AU",
    "wof:name":"Warrachie",
    "wof:placetype":"locality"
},
  "geometry": {"coordinates":[135.71666999999999,-33.65],"type":"Point"}
}