{
  "type": "Feature",
  "properties": {
    "gn:admin1_code":"4",
    "gn:admin2_code":"30450",
    "gn:asciiname":"Welford",
    "gn:country_code":"AU",
    "gn:dem":172,
    "gn:feature_class":"P",
    "gn:feature_code":"PPL",
    "gn:name":"Welford",
    "gn:population":0,
    "gn:timezone":"Australia/Brisbane",
    "iso:country":"AU",
    "name:ceb_x_preferred":[
        "Welford"
    ],
    "name:deu_x_preferred":[
        "Welford"
    ],
    "name:nld_x_preferred":[
        "Welford"
    ],
    "name:pol_x_preferred":[
        "Welford"
    ],
    "name:swe_x_preferred":[
        "Welford"
    ],
    "wof:name":"Welford",
    "wof:placetype":"locality"
},
  "geometry": {"coordinates":[143.71666999999999,-25.11667000000001],"type":"Point"}
}