{
  "type": "Feature",
  "properties": {
    "gn:admin1_code":"2.0",
    "gn:admin2_code":"16180.0",
    "gn:asciiname":"Caloola",
    "gn:country_code":"AU",
    "gn:dem":666,
    "gn:feature_class":"P",
    "gn:feature_code":"PPL",
    "gn:name":"Caloola",
    "gn:population":0,
    "gn:timezone":"Australia/Sydney",
    "iso:country":"AU",
    "name:eng_x_preferred":[
        "Caloola"
    ],
    "wof:name":"Caloola",
    "wof:placetype":"locality"
},
  "geometry": {"coordinates":[149.77101000000005,-35.52361],"type":"Point"}
}