{
  "type": "Feature",
  "properties": {
    "iso:country":"AU",
    "name:eng_x_preferred":[
        "Bexley South"
    ],
    "qs:gn_adm0_cc":"AU",
    "qs:gn_local":2147714,
    "qs:local_max":35533,
    "qs:local_sum":687549,
    "qs:localhoods":516,
    "qs:name":"Bexley South",
    "qs:name_adm0":"Australia",
    "qs:name_adm1":"New South Wales",
    "qs:name_adm2":"City of Rockdale",
    "qs:name_local":"Sydney",
    "qs:photo_max":86,
    "qs:photo_sum":152,
    "qs:placetype":"Suburb",
    "qs:quad_count":11,
    "qs:woe_adm0":23424748,
    "qs:woe_adm1":2344700,
    "qs:woe_adm2":55864197,
    "qs:woe_lau":0,
    "qs:woe_local":1105779,
    "qs:woe_ver":"7.10.0",
    "wof:lang":[
        "eng"
    ],
    "wof:name":"Bexley South",
    "wof:placetype":"neighbourhood"
},
  "geometry": {"coordinates":[151.12114800000001,-33.958981],"type":"Point"}
}