{
  "type": "Feature",
  "properties": {
    "iso:country":"AU",
    "name:ceb_x_preferred":[
        "Chillagoe Airport"
    ],
    "name:swe_x_preferred":[
        "Chillagoe Airport"
    ],
    "oa:elevation_ft":"1110",
    "oa:type":"small_airport",
    "wd:wordcount":46,
    "woe:hierarchy":{
        "country_id":23424748,
        "county_id":56072998,
        "planet_id":1,
        "state_id":2344702
    },
    "wof:name":"Chillagoe Aerodrome",
    "wof:placetype":"campus"
},
  "geometry": {"coordinates":[144.529,-17.1428],"type":"Point"}
}