{
  "type": "Feature",
  "properties": {
    "gn:admin1_code":"2.0",
    "gn:admin2_code":"11400.0",
    "gn:asciiname":"Towan",
    "gn:country_code":"AU",
    "gn:dem":527,
    "gn:feature_class":"P",
    "gn:feature_code":"PPL",
    "gn:name":"Towan",
    "gn:population":0,
    "gn:timezone":"Australia/Sydney",
    "iso:country":"AU",
    "name:eng_x_preferred":[
        "Towan"
    ],
    "wof:name":"Towan",
    "wof:placetype":"locality"
},
  "geometry": {"coordinates":[148.67381,-32.96278],"type":"Point"}
}