{
  "type": "Feature",
  "properties": {
    "gn:gn_country":"AU",
    "gn:gn_fcode":"PPL",
    "gn:gn_pop":1692,
    "gn:population":1692,
    "iso:country":"AU",
    "name:ceb_x_preferred":[
        "Kingscote"
    ],
    "name:deu_x_preferred":[
        "Kingscote"
    ],
    "name:eng_x_preferred":[
        "Kingscote"
    ],
    "name:fas_x_preferred":[
        "\u06a9\u06cc\u0646\u06af\u0632\u06a9\u0627\u062a"
    ],
    "name:fra_x_preferred":[
        "Kingscote"
    ],
    "name:ita_x_preferred":[
        "Kingscote"
    ],
    "name:jpn_x_preferred":[
        "\u30ad\u30f3\u30b0\u30b9\u30b3\u30fc\u30c8"
    ],
    "name:kor_x_preferred":[
        "\ud0b9\uc2a4\ucf67"
    ],
    "name:nld_x_preferred":[
        "Kingscote"
    ],
    "name:nno_x_preferred":[
        "Kingscote"
    ],
    "name:nob_x_preferred":[
        "Kingscote"
    ],
    "name:pol_x_preferred":[
        "Kingscote"
    ],
    "name:por_x_preferred":[
        "Kingscote"
    ],
    "name:rus_x_preferred":[
        "\u041a\u0438\u043d\u0433\u0441\u043a\u043e\u0442"
    ],
    "name:spa_x_preferred":[
        "Kingscote"
    ],
    "name:swe_x_preferred":[
        "Kingscote"
    ],
    "name:ukr_x_preferred":[
        "\u041a\u0456\u043d\u0433\u0441\u043a\u043e\u0442"
    ],
    "name:zho_x_preferred":[
        "\u91d1\u65af\u79d1\u7279"
    ],
    "qs_pg:aaroncc":"AU",
    "qs_pg:gn_country":"AU",
    "qs_pg:gn_fcode":"PPL",
    "qs_pg:gn_pop":1692,
    "qs_pg:name":"Kingscote",
    "qs_pg:name_adm0":"Australia",
    "qs_pg:name_adm1":"South Australia",
    "qs_pg:photos":757,
    "qs_pg:photos_1k":153,
    "qs_pg:photos_9k":3,
    "qs_pg:photos_9r":6,
    "qs_pg:photos_all":757,
    "qs_pg:photos_sr":9,
    "qs_pg:pop_sr":3,
    "qs_pg:qs_pg_placetype":"locality",
    "qs_pg:qs_pg_placetype_gp":"Town",
    "qs_pg:woe_adm0":23424748,
    "woe:adm0_id":23424748,
    "woe:name_adm0":"Australia",
    "woe:name_adm1":"South Australia",
    "woe:placetype":"Town",
    "wof:name":"Kingscote",
    "wof:placetype":"locality",
    "wof:population":1826
},
  "geometry": {"coordinates":[137.63929999999999,-35.6559],"type":"Point"}
}