{
  "type": "Feature",
  "properties": {
    "gn:admin1_code":"2.0",
    "gn:admin2_code":"10850.0",
    "gn:asciiname":"Garland",
    "gn:country_code":"AU",
    "gn:dem":694,
    "gn:feature_class":"P",
    "gn:feature_code":"PPL",
    "gn:name":"Garland",
    "gn:population":0,
    "gn:timezone":"Australia/Sydney",
    "iso:country":"AU",
    "wof:name":"Garland",
    "wof:placetype":"locality"
},
  "geometry": {"coordinates":[149.03333000000001,-33.71667],"type":"Point"}
}