{
  "type": "Feature",
  "properties": {
    "gn:admin1_code":"2.0",
    "gn:admin2_code":"16180.0",
    "gn:asciiname":"Coolavin",
    "gn:country_code":"AU",
    "gn:dem":672,
    "gn:feature_class":"P",
    "gn:feature_code":"PPL",
    "gn:name":"Coolavin",
    "gn:population":0,
    "gn:timezone":"Australia/Sydney",
    "iso:country":"AU",
    "name:eng_x_preferred":[
        "Coolavin"
    ],
    "wof:name":"Coolavin",
    "wof:placetype":"locality"
},
  "geometry": {"coordinates":[149.78339,-35.36807],"type":"Point"}
}