{
  "type": "Feature",
  "properties": {
    "gn:admin1_code":"4.0",
    "gn:admin2_code":"33220.0",
    "gn:asciiname":"Kooringa",
    "gn:country_code":"AU",
    "gn:dem":33,
    "gn:feature_class":"P",
    "gn:feature_code":"PPL",
    "gn:name":"Kooringa",
    "gn:population":0,
    "gn:timezone":"Australia/Brisbane",
    "iso:country":"AU",
    "name:eng_x_preferred":[
        "Kooringa"
    ],
    "wof:name":"Kooringa",
    "wof:placetype":"locality"
},
  "geometry": {"coordinates":[152.56505000000001,-25.73519],"type":"Point"}
}