{
  "type": "Feature",
  "properties": {
    "gn:admin1_code":"7.0",
    "gn:admin2_code":"20740.0",
    "gn:asciiname":"Powlett River",
    "gn:country_code":"AU",
    "gn:dem":20,
    "gn:feature_class":"P",
    "gn:feature_code":"PPL",
    "gn:name":"Powlett River",
    "gn:population":0,
    "gn:timezone":"Australia/Melbourne",
    "iso:country":"AU",
    "wof:name":"Powlett River",
    "wof:placetype":"locality"
},
  "geometry": {"coordinates":[145.58333000000005,-38.56667],"type":"Point"}
}