{
  "type": "Feature",
  "properties": {
    "gn:admin1_code":"8.0",
    "gn:admin2_code":"52800.0",
    "gn:asciiname":"Cone Bay Community",
    "gn:country_code":"AU",
    "gn:dem":78,
    "gn:feature_class":"P",
    "gn:feature_code":"PPL",
    "gn:name":"Cone Bay Community",
    "gn:population":0,
    "gn:timezone":"Australia/Perth",
    "iso:country":"AU",
    "wof:name":"Cone Bay Community",
    "wof:placetype":"locality"
},
  "geometry": {"coordinates":[123.66905,-16.49018],"type":"Point"}
}