{
  "type": "Feature",
  "properties": {
    "gn:admin1_code":"7",
    "gn:admin2_code":"20260",
    "gn:asciiname":"Yalla-Y-Poora",
    "gn:country_code":"AU",
    "gn:dem":311,
    "gn:feature_class":"P",
    "gn:feature_code":"PPL",
    "gn:name":"Yalla-Y-Poora",
    "gn:population":0,
    "gn:timezone":"Australia/Melbourne",
    "iso:country":"AU",
    "wof:name":"Yalla-Y-Poora",
    "wof:placetype":"locality"
},
  "geometry": {"coordinates":[143.06666999999999,-37.53333],"type":"Point"}
}