{
  "type": "Feature",
  "properties": {
    "gn:admin1_code":"8",
    "gn:admin2_code":"57210",
    "gn:asciiname":"Carbarup",
    "gn:country_code":"AU",
    "gn:dem":196,
    "gn:feature_class":"P",
    "gn:feature_code":"PPL",
    "gn:name":"Carbarup",
    "gn:population":0,
    "gn:timezone":"Australia/Perth",
    "iso:country":"AU",
    "name:eng_x_preferred":[
        "Carbarup"
    ],
    "wof:name":"Carbarup",
    "wof:placetype":"locality"
},
  "geometry": {"coordinates":[117.6859,-34.53816],"type":"Point"}
}