{
  "type": "Feature",
  "properties": {
    "gn:admin1_code":"4.0",
    "gn:admin2_code":"36660.0",
    "gn:asciiname":"Cherry Gully",
    "gn:country_code":"AU",
    "gn:dem":751,
    "gn:feature_class":"P",
    "gn:feature_code":"PPL",
    "gn:name":"Cherry Gully",
    "gn:population":0,
    "gn:timezone":"Australia/Brisbane",
    "iso:country":"AU",
    "name:eng_x_preferred":[
        "Cherry Gully"
    ],
    "wof:name":"Cherry Gully",
    "wof:placetype":"locality"
},
  "geometry": {"coordinates":[152.03213,-28.43305],"type":"Point"}
}