{
  "type": "Feature",
  "properties": {
    "gn:admin1_code":"4.0",
    "gn:admin2_code":"36810.0",
    "gn:asciiname":"Koorboora",
    "gn:country_code":"AU",
    "gn:dem":575,
    "gn:feature_class":"P",
    "gn:feature_code":"PPL",
    "gn:name":"Koorboora",
    "gn:population":0,
    "gn:timezone":"Australia/Brisbane",
    "iso:country":"AU",
    "wof:name":"Koorboora",
    "wof:placetype":"locality"
},
  "geometry": {"coordinates":[144.81666999999999,-17.38332999999999],"type":"Point"}
}