{
  "type": "Feature",
  "properties": {
    "gn:admin1_code":"4.0",
    "gn:admin2_code":"32070.0",
    "gn:asciiname":"Charringa",
    "gn:country_code":"AU",
    "gn:dem":15,
    "gn:feature_class":"P",
    "gn:feature_code":"PPL",
    "gn:name":"Charringa",
    "gn:population":0,
    "gn:timezone":"Australia/Brisbane",
    "iso:country":"AU",
    "wof:name":"Charringa",
    "wof:placetype":"locality"
},
  "geometry": {"coordinates":[145.83333000000005,-17.13332999999999],"type":"Point"}
}