{
  "type": "Feature",
  "properties": {
    "gn:admin1_code":"4.0",
    "gn:admin2_code":"30370.0",
    "gn:asciiname":"Don River",
    "gn:country_code":"AU",
    "gn:dem":116,
    "gn:feature_class":"P",
    "gn:feature_code":"PPL",
    "gn:name":"Don River",
    "gn:population":0,
    "gn:timezone":"Australia/Brisbane",
    "iso:country":"AU",
    "wof:name":"Don River",
    "wof:placetype":"locality"
},
  "geometry": {"coordinates":[150.30000000000001,-23.98333],"type":"Point"}
}