{
  "type": "Feature",
  "properties": {
    "gn:admin1_code":"4.0",
    "gn:admin2_code":"32500.0",
    "gn:asciiname":"Bobs Yard",
    "gn:country_code":"AU",
    "gn:dem":183,
    "gn:feature_class":"P",
    "gn:feature_code":"PPL",
    "gn:name":"Bobs Yard",
    "gn:population":0,
    "gn:timezone":"Australia/Brisbane",
    "iso:country":"AU",
    "wof:name":"Bobs Yard",
    "wof:placetype":"locality"
},
  "geometry": {"coordinates":[143.25441000000001,-14.9122],"type":"Point"}
}