{
  "type": "Feature",
  "properties": {
    "gn:population":5693,
    "iso:country":"AU",
    "name:ceb_x_preferred":[
        "Torquay"
    ],
    "name:eng_x_preferred":[
        "Torquay"
    ],
    "name:fas_x_preferred":[
        "\u062a\u0648\u0631\u06a9\u0648\u0627\u06cc"
    ],
    "name:swe_x_preferred":[
        "Torquay"
    ],
    "qs:gn_adm0_cc":"AU",
    "qs:gn_fcode":"PPL",
    "qs:gn_local":6354957,
    "qs:gn_nam_loc":"hervey bay",
    "qs:gn_namadm1":"04",
    "qs:gn_name":"Torquay",
    "qs:local_max":795,
    "qs:local_sum":1774,
    "qs:localhoods":5,
    "qs:name":"Torquay",
    "qs:name_adm0":"Australia",
    "qs:name_adm1":"Queensland",
    "qs:name_adm2":"Fraser Coast Regional",
    "qs:name_local":"Hervey Bay",
    "qs:photo_max":50,
    "qs:photo_sum":231,
    "qs:placetype":"Suburb",
    "qs:quad_count":18,
    "qs:woe_adm0":23424748,
    "qs:woe_adm1":2344702,
    "qs:woe_adm2":56072986,
    "qs:woe_lau":0,
    "qs:woe_local":1102631,
    "qs:woe_ver":"7.10.0",
    "wof:lang":[
        "eng"
    ],
    "wof:name":"Torquay",
    "wof:placetype":"neighbourhood",
    "wof:population":5693
},
  "geometry": {"coordinates":[152.87405200000001,-25.282841],"type":"Point"}
}