{
  "type": "Feature",
  "properties": {
    "gn:admin1_code":"4.0",
    "gn:admin2_code":"37340.0",
    "gn:asciiname":"Delta",
    "gn:country_code":"AU",
    "gn:dem":10,
    "gn:feature_class":"P",
    "gn:feature_code":"PPL",
    "gn:name":"Delta",
    "gn:population":0,
    "gn:timezone":"Australia/Brisbane",
    "iso:country":"AU",
    "wof:name":"Delta",
    "wof:placetype":"locality"
},
  "geometry": {"coordinates":[148.18333000000001,-20.01667],"type":"Point"}
}