{
  "type": "Feature",
  "properties": {
    "gn:admin1_code":"06",
    "gn:admin2_code":"64610.0",
    "gn:asciiname":"Delmont",
    "gn:country_code":"AU",
    "gn:dem":147,
    "gn:feature_class":"P",
    "gn:feature_code":"PPL",
    "gn:name":"Delmont",
    "gn:population":0,
    "gn:timezone":"Australia/Hobart",
    "iso:country":"AU",
    "name:eng_x_preferred":[
        "Delmont"
    ],
    "wof:name":"Delmont",
    "wof:placetype":"locality"
},
  "geometry": {"coordinates":[147.16723000000005,-41.75636],"type":"Point"}
}