{
  "type": "Feature",
  "properties": {
    "gn:admin1_code":"8",
    "gn:admin2_code":"59030",
    "gn:asciiname":"West Westonia",
    "gn:country_code":"AU",
    "gn:dem":347,
    "gn:feature_class":"P",
    "gn:feature_code":"PPL",
    "gn:name":"West Westonia",
    "gn:population":0,
    "gn:timezone":"Australia/Perth",
    "iso:country":"AU",
    "name:eng_x_preferred":[
        "West Westonia"
    ],
    "wof:name":"West Westonia",
    "wof:placetype":"locality"
},
  "geometry": {"coordinates":[118.64646999999999,-31.28698],"type":"Point"}
}