{
  "type": "Feature",
  "properties": {
    "gn:admin1_code":"2.0",
    "gn:admin2_code":"17620.0",
    "gn:asciiname":"Grenell Park",
    "gn:country_code":"AU",
    "gn:dem":330,
    "gn:feature_class":"P",
    "gn:feature_code":"PPL",
    "gn:name":"Grenell Park",
    "gn:population":0,
    "gn:timezone":"Australia/Sydney",
    "iso:country":"AU",
    "name:eng_x_preferred":[
        "Grenell Park"
    ],
    "wof:name":"Grenell Park",
    "wof:placetype":"locality"
},
  "geometry": {"coordinates":[151.08772999999999,-32.15509],"type":"Point"}
}