{
  "type": "Feature",
  "properties": {
    "gn:admin1_code":"4.0",
    "gn:admin2_code":"36910.0",
    "gn:asciiname":"Cuppine",
    "gn:country_code":"AU",
    "gn:dem":417,
    "gn:feature_class":"P",
    "gn:feature_code":"PPL",
    "gn:name":"Cuppine",
    "gn:population":0,
    "gn:timezone":"Australia/Brisbane",
    "iso:country":"AU",
    "name:eng_x_preferred":[
        "Cuppine"
    ],
    "wof:name":"Cuppine",
    "wof:placetype":"locality"
},
  "geometry": {"coordinates":[151.12826000000001,-27.87615],"type":"Point"}
}