{
  "type": "Feature",
  "properties": {
    "gn:admin1_code":"2.0",
    "gn:admin2_code":"14600.0",
    "gn:asciiname":"The Bluff",
    "gn:country_code":"AU",
    "gn:dem":291,
    "gn:feature_class":"P",
    "gn:feature_code":"PPL",
    "gn:name":"The Bluff",
    "gn:population":0,
    "gn:timezone":"Australia/Sydney",
    "iso:country":"AU",
    "name:ceb_x_preferred":[
        "The Bluff"
    ],
    "name:eng_x_preferred":[
        "The Bluff"
    ],
    "name:swe_x_preferred":[
        "The Bluff"
    ],
    "wof:name":"The Bluff",
    "wof:placetype":"locality"
},
  "geometry": {"coordinates":[146.86340000000001,-32.47032],"type":"Point"}
}