{
  "type": "Feature",
  "properties": {
    "gn:admin1_code":"2.0",
    "gn:admin2_code":"14600.0",
    "gn:asciiname":"The Bluff",
    "gn:country_code":"AU",
    "gn:dem":291,
    "gn:feature_class":"P",
    "gn:feature_code":"PPL",
    "gn:name":"The Bluff",
    "gn:population":0,
    "gn:timezone":"Australia/Sydney",
    "iso:country":"AU",
    "name:ara_x_preferred":[
        "\u0630\u0627 \u0628\u0644\u0627\u0641"
    ],
    "name:ben_x_preferred":[
        "\u09ac\u09cd\u09b2\u09be\u09ab"
    ],
    "name:ceb_x_preferred":[
        "The Bluff"
    ],
    "name:deu_x_preferred":[
        "Bluff Mountain"
    ],
    "name:ell_x_preferred":[
        "\u0394\u03b5 \u039c\u03c0\u03bb\u03b1\u03c6"
    ],
    "name:eng_x_preferred":[
        "The Bluff"
    ],
    "name:fas_x_preferred":[
        "\u0628\u0644\u0627\u0641"
    ],
    "name:heb_x_preferred":[
        "\u05d3\u05d4 \u05d1\u05dc\u05d0\u05e3"
    ],
    "name:hin_x_preferred":[
        "\u0926 \u092c\u094d\u0932\u095e"
    ],
    "name:hun_x_preferred":[
        "The Bluff-hegy"
    ],
    "name:ind_x_preferred":[
        "Bluff"
    ],
    "name:ita_x_preferred":[
        "The Bluff"
    ],
    "name:kor_x_preferred":[
        "\ub354 \ube14\ub7ec\ud504"
    ],
    "name:por_x_preferred":[
        "The Bluff"
    ],
    "name:rus_x_preferred":[
        "\u0433\u043e\u0440\u0430 \u0411\u043b\u0430\u0444\u0444"
    ],
    "name:spa_x_preferred":[
        "Bluff"
    ],
    "name:swe_x_preferred":[
        "The Bluff"
    ],
    "name:tur_x_preferred":[
        "The Bluff"
    ],
    "name:ukr_x_preferred":[
        "\u0411\u043b\u0430\u0444\u0444"
    ],
    "name:urd_x_preferred":[
        "\u062f\u06cc \u0628\u0644\u0641"
    ],
    "name:vie_x_preferred":[
        "N\u00fai Bluff"
    ],
    "name:zho_cn_x_preferred":[
        "\u5e03\u62c9\u592b\u5c71"
    ],
    "name:zho_tw_x_preferred":[
        "\u5e03\u62c9\u592b\u5c71"
    ],
    "wof:name":"The Bluff",
    "wof:placetype":"locality"
},
  "geometry": {"coordinates":[146.86340000000001,-32.47032],"type":"Point"}
}