{
  "type": "Feature",
  "properties": {
    "gn:country":"AU",
    "gn:fcode":"PPL",
    "gn:population":4368,
    "iso:country":"AU",
    "name:ceb_x_preferred":[
        "Port Kembla"
    ],
    "name:deu_x_preferred":[
        "Port Kembla"
    ],
    "name:eng_x_preferred":[
        "Port Kembla"
    ],
    "name:eng_x_variant":[
        "Pt. Kembla",
        "Pt Kembla"
    ],
    "name:fas_x_preferred":[
        "\u067e\u0648\u0631\u062a \u06a9\u0645\u0628\u0644\u0627"
    ],
    "name:fra_x_preferred":[
        "Port Kembla"
    ],
    "name:nld_x_preferred":[
        "Eagle Junction"
    ],
    "name:pol_x_preferred":[
        "Port Kembla"
    ],
    "name:rus_x_preferred":[
        "\u041f\u043e\u0440\u0442-\u041a\u0435\u043c\u0431\u043b\u0430"
    ],
    "name:swe_x_preferred":[
        "Port Kembla"
    ],
    "qs_pg:aaroncc":"AU",
    "qs_pg:gn_country":"AU",
    "qs_pg:gn_fcode":"PPL",
    "qs_pg:gn_pop":4368,
    "qs_pg:name":"Port Kembla",
    "qs_pg:name_adm0":"Australia",
    "qs_pg:name_adm1":"New South Wales",
    "qs_pg:photos":436,
    "qs_pg:photos_1k":88,
    "qs_pg:photos_9k":2,
    "qs_pg:photos_9r":5,
    "qs_pg:photos_all":436,
    "qs_pg:photos_sr":6,
    "qs_pg:pop_sr":4,
    "qs_pg:qs_pg_placetype":"neighbourhood",
    "qs_pg:qs_pg_placetype_gp":"Suburb",
    "qs_pg:woe_adm0":23424748,
    "woe:adm0_id":23424748,
    "woe:name_adm0":"Australia",
    "woe:name_adm1":"New South Wales",
    "woe:placetype":"Suburb",
    "wof:name":"Port Kembla",
    "wof:placetype":"neighbourhood",
    "wof:population":4368
},
  "geometry": {"coordinates":[150.90000000000001,-34.46667],"type":"Point"}
}