{
  "type": "Feature",
  "properties": {
    "gn:admin1_code":"3",
    "gn:admin2_code":"70420",
    "gn:asciiname":"Elkedra",
    "gn:country_code":"AU",
    "gn:dem":358,
    "gn:feature_class":"P",
    "gn:feature_code":"PPLL",
    "gn:name":"Elkedra",
    "gn:population":0,
    "gn:timezone":"Australia/Darwin",
    "iso:country":"AU",
    "name:eng_x_preferred":[
        "Elkedra"
    ],
    "wof:name":"Elkedra",
    "wof:placetype":"locality"
},
  "geometry": {"coordinates":[135.44640999999999,-21.16636],"type":"Point"}
}