{
  "type": "Feature",
  "properties": {
    "gn:admin1_code":"7.0",
    "gn:admin2_code":"26890.0",
    "gn:asciiname":"Bringalbert South",
    "gn:cc2":"AU",
    "gn:country_code":"AU",
    "gn:dem":126,
    "gn:feature_class":"P",
    "gn:feature_code":"PPL",
    "gn:name":"Bringalbert South",
    "gn:population":0,
    "gn:timezone":"Australia/Melbourne",
    "iso:country":"AU",
    "name:und_x_variant":[
        "Bringalbert",
        "Bringalbert South"
    ],
    "wof:name":"Bringalbert South",
    "wof:placetype":"locality"
},
  "geometry": {"coordinates":[141.16666999999995,-36.85],"type":"Point"}
}