{
  "type": "Feature",
  "properties": {
    "gn:admin1_code":"4.0",
    "gn:admin2_code":"32270.0",
    "gn:asciiname":"Retro",
    "gn:country_code":"AU",
    "gn:dem":259,
    "gn:feature_class":"P",
    "gn:feature_code":"PPL",
    "gn:name":"Retro",
    "gn:population":0,
    "gn:timezone":"Australia/Brisbane",
    "iso:country":"AU",
    "wof:name":"Retro",
    "wof:placetype":"locality"
},
  "geometry": {"coordinates":[147.90000000000001,-23.01667],"type":"Point"}
}