{
  "type": "Feature",
  "properties": {
    "gn:admin1_code":"4",
    "gn:admin2_code":"33360",
    "gn:asciiname":"Taunton",
    "gn:country_code":"AU",
    "gn:dem":15,
    "gn:feature_class":"P",
    "gn:feature_code":"PPL",
    "gn:name":"Taunton",
    "gn:population":0,
    "gn:timezone":"Australia/Brisbane",
    "iso:country":"AU",
    "name:ara_x_preferred":[
        "\u062a\u0648\u0646\u062a\u0648\u0646"
    ],
    "name:ast_x_preferred":[
        "Taunton"
    ],
    "name:azb_x_preferred":[
        "\u062a\u0627\u0648\u0646\u062a\u0648\u0646"
    ],
    "name:bul_x_preferred":[
        "\u0422\u043e\u0443\u043d\u0442\u044a\u043d"
    ],
    "name:cat_x_preferred":[
        "Taunton"
    ],
    "name:ceb_x_preferred":[
        "Taunton"
    ],
    "name:cym_x_preferred":[
        "Taunton"
    ],
    "name:dan_x_preferred":[
        "Taunton"
    ],
    "name:deu_x_preferred":[
        "Taunton"
    ],
    "name:eng_x_preferred":[
        "Taunton"
    ],
    "name:epo_x_preferred":[
        "Taunton"
    ],
    "name:eus_x_preferred":[
        "Taunton"
    ],
    "name:fas_x_preferred":[
        "\u062a\u0627\u0648\u0646\u062a\u0648\u0646"
    ],
    "name:fra_x_preferred":[
        "Taunton"
    ],
    "name:gle_x_preferred":[
        "Taunton"
    ],
    "name:hin_x_preferred":[
        "\u091f\u093e\u0909\u0902\u091f\u0928"
    ],
    "name:ile_x_preferred":[
        "Taunton"
    ],
    "name:ind_x_preferred":[
        "Taunton"
    ],
    "name:ita_x_preferred":[
        "Taunton"
    ],
    "name:jpn_x_preferred":[
        "\u30c8\u30fc\u30f3\u30c8\u30f3"
    ],
    "name:kor_x_preferred":[
        "\ud1a4\ud134"
    ],
    "name:lat_x_preferred":[
        "Tantonia"
    ],
    "name:mal_x_preferred":[
        "\u0d1f\u0d57\u0d28\u0d4d\u0d31\u0d7a"
    ],
    "name:mar_x_preferred":[
        "\u091f\u093e\u0901\u091f\u0928"
    ],
    "name:nld_x_preferred":[
        "Taunton"
    ],
    "name:nno_x_preferred":[
        "Taunton"
    ],
    "name:nor_x_preferred":[
        "Taunton"
    ],
    "name:pan_x_preferred":[
        "\u0a1f\u0a3e\u0a0a\u0a02\u0a1f\u0a28"
    ],
    "name:pol_x_preferred":[
        "Taunton"
    ],
    "name:por_x_preferred":[
        "Taunton"
    ],
    "name:ron_x_preferred":[
        "Taunton"
    ],
    "name:rus_x_preferred":[
        "\u0422\u043e\u043d\u0442\u043e\u043d"
    ],
    "name:spa_x_preferred":[
        "Taunton"
    ],
    "name:srp_x_preferred":[
        "\u0422\u043e\u043d\u0442\u043e\u043d"
    ],
    "name:swe_x_preferred":[
        "Taunton"
    ],
    "name:szl_x_preferred":[
        "Taunton"
    ],
    "name:tat_x_preferred":[
        "\u0422\u043e\u043d\u0442\u043e\u043d"
    ],
    "name:urd_x_preferred":[
        "\u0679\u0627\u0646\u0679\u0646"
    ],
    "name:vol_x_preferred":[
        "Taunton"
    ],
    "name:zho_x_preferred":[
        "\u6e6f\u9813"
    ],
    "wof:name":"Taunton",
    "wof:placetype":"locality"
},
  "geometry": {"coordinates":[151.82176999999999,-24.42054],"type":"Point"}
}