{
  "type": "Feature",
  "properties": {
    "gn:admin1_code":"4",
    "gn:admin2_code":"33360",
    "gn:asciiname":"Taunton",
    "gn:country_code":"AU",
    "gn:dem":15,
    "gn:feature_class":"P",
    "gn:feature_code":"PPL",
    "gn:name":"Taunton",
    "gn:population":0,
    "gn:timezone":"Australia/Brisbane",
    "iso:country":"AU",
    "name:eng_x_preferred":[
        "Taunton"
    ],
    "wof:name":"Taunton",
    "wof:placetype":"locality"
},
  "geometry": {"coordinates":[151.82176999999999,-24.42054],"type":"Point"}
}