{
  "type": "Feature",
  "properties": {
    "iso:country":"AU",
    "name:bar_x_preferred":[
        "Flaxton"
    ],
    "name:ceb_x_preferred":[
        "Flaxton"
    ],
    "name:deu_x_preferred":[
        "Flaxton"
    ],
    "name:eng_x_preferred":[
        "Flaxton"
    ],
    "name:fra_x_preferred":[
        "Flaxton"
    ],
    "name:nld_x_preferred":[
        "Flaxton"
    ],
    "name:pol_x_preferred":[
        "Flaxton"
    ],
    "name:swe_x_preferred":[
        "Flaxton"
    ],
    "qs_pg:aaroncc":"AU",
    "qs_pg:name":"Flaxton",
    "qs_pg:name_adm0":"Australia",
    "qs_pg:name_adm1":"Queensland",
    "qs_pg:photos":310,
    "qs_pg:photos_1k":63,
    "qs_pg:photos_9k":1,
    "qs_pg:photos_9r":5,
    "qs_pg:photos_all":310,
    "qs_pg:photos_sr":5,
    "qs_pg:pop_sr":0,
    "qs_pg:qs_pg_placetype":"locality",
    "qs_pg:qs_pg_placetype_gp":"Town",
    "qs_pg:woe_adm0":23424748,
    "woe:adm0_id":23424748,
    "woe:name_adm0":"Australia",
    "woe:name_adm1":"Queensland",
    "woe:placetype":"Town",
    "wof:name":"Flaxton",
    "wof:placetype":"locality"
},
  "geometry": {"coordinates":[152.86566350000001,-26.671084],"type":"Point"}
}