{
  "type": "Feature",
  "properties": {
    "iso:country":"AU",
    "name:deu_x_preferred":[
        "Alkimos"
    ],
    "name:eng_x_preferred":[
        "Alkimos"
    ],
    "name:ita_x_preferred":[
        "Alkimos"
    ],
    "name:rus_x_preferred":[
        "\u0410\u043b\u043a\u0438\u043c"
    ],
    "name:slk_x_preferred":[
        "Alkimos"
    ],
    "qs_pg:aaroncc":"AU",
    "qs_pg:name":"Alkimos",
    "qs_pg:name_adm0":"Australia",
    "qs_pg:name_adm1":"Western Australia",
    "qs_pg:photos":91,
    "qs_pg:photos_1k":18,
    "qs_pg:photos_9k":1,
    "qs_pg:photos_9r":3,
    "qs_pg:photos_all":91,
    "qs_pg:photos_sr":3,
    "qs_pg:pop_sr":0,
    "qs_pg:qs_pg_placetype":"locality",
    "qs_pg:qs_pg_placetype_gp":"Town",
    "qs_pg:woe_adm0":23424748,
    "woe:adm0_id":23424748,
    "woe:name_adm0":"Australia",
    "woe:name_adm1":"Western Australia",
    "woe:placetype":"Town",
    "wof:name":"Alkimos",
    "wof:placetype":"locality",
    "wof:population":6269
},
  "geometry": {"coordinates":[115.713157,-31.619035],"type":"Point"}
}