{
  "type": "Feature",
  "properties": {
    "gn:gn_country":"AU",
    "gn:gn_fcode":"PPL",
    "gn:gn_pop":195,
    "gn:population":195,
    "iso:country":"AU",
    "qs_pg:aaroncc":"AU",
    "qs_pg:gn_country":"AU",
    "qs_pg:gn_fcode":"PPL",
    "qs_pg:gn_pop":195,
    "qs_pg:name":"Fairholme",
    "qs_pg:photos_9r":0,
    "qs_pg:photos_sr":0,
    "qs_pg:pop_sr":1,
    "qs_pg:qs_pg_placetype":"locality",
    "wof:name":"Fairholme",
    "wof:placetype":"locality",
    "wof:population":195
},
  "geometry": {"coordinates":[147.38333,-33.28333],"type":"Point"}
}