{
  "type": "Feature",
  "properties": {
    "gn:admin1_code":"7",
    "gn:admin2_code":"23350",
    "gn:asciiname":"Wooragee North",
    "gn:cc2":"AU",
    "gn:country_code":"AU",
    "gn:dem":213,
    "gn:feature_class":"P",
    "gn:feature_code":"PPL",
    "gn:name":"Wooragee North",
    "gn:population":0,
    "gn:timezone":"Australia/Melbourne",
    "iso:country":"AU",
    "name:und_x_variant":[
        "Middle Indigo",
        "Wooragee North"
    ],
    "wof:name":"Wooragee North",
    "wof:placetype":"locality"
},
  "geometry": {"coordinates":[146.73333,-36.15],"type":"Point"}
}