{
  "type": "Feature",
  "properties": {
    "iso:country":"AU",
    "name:eng_x_preferred":[
        "Moonta Bay"
    ],
    "name:eng_x_variant":[
        "Port Moonta",
        "Pt Moonta",
        "Pt. Moonta"
    ],
    "qs:gn_local":0,
    "qs:local_max":75,
    "qs:local_sum":148,
    "qs:localhoods":3,
    "qs:name":"Moonta Bay",
    "qs:name_adm0":"Australia",
    "qs:name_adm1":"South Australia",
    "qs:name_adm2":"Copper Coast",
    "qs:name_local":"Moonta",
    "qs:photo_max":33,
    "qs:photo_sum":75,
    "qs:placetype":"Suburb",
    "qs:quad_count":11,
    "qs:woe_adm0":23424748,
    "qs:woe_adm1":2344703,
    "qs:woe_adm2":55864215,
    "qs:woe_lau":0,
    "qs:woe_local":1104064,
    "qs:woe_ver":"7.10.0",
    "wof:lang":[
        "eng"
    ],
    "wof:name":"Moonta Bay",
    "wof:placetype":"neighbourhood"
},
  "geometry": {"coordinates":[137.56049400000001,-34.055952],"type":"Point"}
}