{
  "type": "Feature",
  "properties": {
    "iso:country":"AU",
    "name:eng_x_preferred":[
        "Moonta Bay"
    ],
    "name:eng_x_variant":[
        "Port Moonta",
        "Pt Moonta",
        "Pt. Moonta"
    ],
    "qs:gn_local":0,
    "qs:local_max":75,
    "qs:local_sum":148,
    "qs:localhoods":3,
    "qs:name":"Moonta Bay",
    "qs:name_adm0":"Australia",
    "qs:name_adm1":"South Australia",
    "qs:name_adm2":"Copper Coast",
    "qs:name_local":"Moonta",
    "qs:photo_max":33,
    "qs:photo_sum":75,
    "qs:placetype":"Suburb",
    "qs:quad_count":11,
    "qs:woe_adm0":23424748,
    "qs:woe_adm1":2344703,
    "qs:woe_adm2":55864215,
    "qs:woe_lau":0,
    "qs:woe_local":1104064,
    "qs:woe_ver":"7.10.0",
    "qs_pg:name":"Moonta Bay",
    "qs_pg:name_adm0":"Australia",
    "qs_pg:name_adm1":"South Australia",
    "qs_pg:photos":74,
    "qs_pg:photos_1k":15,
    "qs_pg:photos_9k":1,
    "qs_pg:photos_9r":2,
    "qs_pg:photos_all":74,
    "qs_pg:photos_sr":2,
    "qs_pg:pop_sr":0,
    "qs_pg:qs_pg_placetype":"neighbourhood",
    "qs_pg:qs_pg_placetype_gp":"Suburb",
    "qs_pg:woe_adm0":23424748,
    "woe:adm0_id":23424748,
    "woe:name_adm0":"Australia",
    "woe:name_adm1":"South Australia",
    "woe:placetype":"Suburb",
    "wof:lang":[
        "eng"
    ],
    "wof:name":"Moonta Bay",
    "wof:placetype":"neighbourhood"
},
  "geometry": {"coordinates":[137.56049400000001,-34.055952],"type":"Point"}
}