{
  "type": "Feature",
  "properties": {
    "gn:admin1_code":"2.0",
    "gn:admin2_code":"15270.0",
    "gn:asciiname":"Bundarrah",
    "gn:country_code":"AU",
    "gn:dem":566,
    "gn:feature_class":"P",
    "gn:feature_code":"PPL",
    "gn:name":"Bundarrah",
    "gn:population":0,
    "gn:timezone":"Australia/Sydney",
    "iso:country":"AU",
    "name:eng_x_preferred":[
        "Bundarrah"
    ],
    "wof:name":"Bundarrah",
    "wof:placetype":"locality"
},
  "geometry": {"coordinates":[149.82029,-32.44698],"type":"Point"}
}