{
  "type": "Feature",
  "properties": {
    "gn:admin1_code":"2",
    "gn:admin2_code":"10550",
    "gn:asciiname":"Wyndham",
    "gn:country_code":"AU",
    "gn:dem":282,
    "gn:feature_class":"P",
    "gn:feature_code":"PPL",
    "gn:name":"Wyndham",
    "gn:population":0,
    "gn:timezone":"Australia/Sydney",
    "iso:country":"AU",
    "name:ceb_x_preferred":[
        "Wyndham"
    ],
    "name:deu_x_preferred":[
        "Wyndham"
    ],
    "name:fra_x_preferred":[
        "Wyndham"
    ],
    "name:ita_x_preferred":[
        "Wyndham"
    ],
    "name:kor_x_preferred":[
        "\uc708\ub364"
    ],
    "name:nld_x_preferred":[
        "Wyndham"
    ],
    "name:pol_x_preferred":[
        "Wyndham"
    ],
    "name:ron_x_preferred":[
        "Wyndham"
    ],
    "name:rus_x_preferred":[
        "\u0423\u0438\u043d\u0434\u0435\u043c"
    ],
    "name:srp_x_preferred":[
        "\u0412\u0438\u043d\u0434\u0430\u043c"
    ],
    "name:swe_x_preferred":[
        "Wyndham"
    ],
    "wof:name":"Wyndham",
    "wof:placetype":"locality",
    "wof:population":386
},
  "geometry": {"coordinates":[149.65119999999999,-36.9318],"type":"Point"}
}