{
  "type": "Feature",
  "properties": {
    "gn:admin1_code":"2",
    "gn:admin2_code":"10550",
    "gn:asciiname":"Wyndham",
    "gn:country_code":"AU",
    "gn:dem":282,
    "gn:feature_class":"P",
    "gn:feature_code":"PPL",
    "gn:name":"Wyndham",
    "gn:population":0,
    "gn:timezone":"Australia/Sydney",
    "iso:country":"AU",
    "name:ara_x_preferred":[
        "\u0648\u064a\u0646\u062f\u0647\u0627\u0645"
    ],
    "name:ben_x_preferred":[
        "\u0993\u09df\u09c7\u09a8\u09a7\u09cd\u09af\u09be\u09ae"
    ],
    "name:ceb_x_preferred":[
        "Wyndham"
    ],
    "name:deu_x_preferred":[
        "Wyndham"
    ],
    "name:ell_x_preferred":[
        "\u0393\u03bf\u03c5\u03af\u03bd\u03c4\u03b1\u03bc"
    ],
    "name:fra_x_preferred":[
        "Wyndham"
    ],
    "name:heb_x_preferred":[
        "\u05d5\u05d9\u05e0\u05d3\u05d4\u05d0\u05dd"
    ],
    "name:hin_x_preferred":[
        "\u0935\u093f\u0902\u0921\u0948\u092e"
    ],
    "name:hun_x_preferred":[
        "Wyndham"
    ],
    "name:ind_x_preferred":[
        "Wyndham"
    ],
    "name:ita_x_preferred":[
        "Wyndham"
    ],
    "name:kor_x_preferred":[
        "\uc708\ub364"
    ],
    "name:nld_x_preferred":[
        "Wyndham"
    ],
    "name:pol_x_preferred":[
        "Wyndham"
    ],
    "name:por_x_preferred":[
        "Wyndham"
    ],
    "name:ron_x_preferred":[
        "Wyndham"
    ],
    "name:rus_x_preferred":[
        "\u0423\u0438\u043d\u0434\u0435\u043c"
    ],
    "name:spa_x_preferred":[
        "Wyndham"
    ],
    "name:srp_x_preferred":[
        "\u0412\u0438\u043d\u0434\u0430\u043c"
    ],
    "name:swe_x_preferred":[
        "Wyndham"
    ],
    "name:tur_x_preferred":[
        "Wyndham"
    ],
    "name:ukr_x_preferred":[
        "\u0412\u0456\u043d\u0434\u0435\u043c"
    ],
    "name:vie_x_preferred":[
        "Wyndham"
    ],
    "wof:name":"Wyndham",
    "wof:placetype":"locality"
},
  "geometry": {"coordinates":[149.65119999999999,-36.9318],"type":"Point"}
}