{
  "type": "Feature",
  "properties": {
    "gn:gn_country":"AU",
    "gn:gn_fcode":"PPL",
    "gn:gn_pop":387,
    "gn:population":387,
    "iso:country":"AU",
    "name:dut_x_preferred":[
        "Coolac"
    ],
    "name:eng_x_preferred":[
        "Coolac"
    ],
    "name:fre_x_preferred":[
        "Coolac"
    ],
    "name:swe_x_preferred":[
        "Coolac"
    ],
    "qs_pg:aaroncc":"AU",
    "qs_pg:gn_country":"AU",
    "qs_pg:gn_fcode":"PPL",
    "qs_pg:gn_pop":387,
    "qs_pg:name":"Coolac",
    "qs_pg:photos_9r":0,
    "qs_pg:photos_sr":0,
    "qs_pg:pop_sr":2,
    "qs_pg:qs_pg_placetype":"locality",
    "wof:name":"Coolac",
    "wof:placetype":"locality",
    "wof:population":387
},
  "geometry": {"coordinates":[148.16667000000001,-34.95],"type":"Point"}
}