{
  "type": "Feature",
  "properties": {
    "gn:admin1_code":"4.0",
    "gn:admin2_code":"36910.0",
    "gn:asciiname":"Formartin",
    "gn:country_code":"AU",
    "gn:dem":359,
    "gn:feature_class":"P",
    "gn:feature_code":"PPL",
    "gn:name":"Formartin",
    "gn:population":0,
    "gn:timezone":"Australia/Brisbane",
    "iso:country":"AU",
    "name:eng_x_preferred":[
        "Formartin"
    ],
    "wof:name":"Formartin",
    "wof:placetype":"locality"
},
  "geometry": {"coordinates":[151.4118,-27.39587],"type":"Point"}
}