{
  "type": "Feature",
  "properties": {
    "iso:country":"AU",
    "name:eng_x_preferred":[
        "Nyannia"
    ],
    "qs:gn_adm0_cc":"AU",
    "qs:gn_local":2063523,
    "qs:local_max":26312,
    "qs:local_sum":139041,
    "qs:localhoods":187,
    "qs:name":"Nyannia",
    "qs:name_adm0":"Australia",
    "qs:name_adm1":"Western Australia",
    "qs:name_adm2":"Mundaring",
    "qs:name_local":"Perth",
    "qs:photo_max":8,
    "qs:photo_sum":17,
    "qs:placetype":"Suburb",
    "qs:quad_count":3,
    "qs:woe_adm0":23424748,
    "qs:woe_adm1":2344706,
    "qs:woe_adm2":55864050,
    "qs:woe_lau":0,
    "qs:woe_local":1098081,
    "qs:woe_ver":"7.10.0",
    "wof:lang":[
        "eng"
    ],
    "wof:name":"Nyannia",
    "wof:placetype":"neighbourhood"
},
  "geometry": {"coordinates":[116.13663699999999,-31.915827],"type":"Point"}
}