{
  "type": "Feature",
  "properties": {
    "gn:country":"AU",
    "gn:fcode":"PPL",
    "gn:population":0,
    "iso:country":"AU",
    "name:ceb_x_preferred":[
        "Alberton"
    ],
    "name:deu_x_preferred":[
        "Alberton"
    ],
    "name:eng_x_preferred":[
        "Alberton"
    ],
    "name:fra_x_preferred":[
        "Alberton"
    ],
    "name:ita_x_preferred":[
        "Alberton"
    ],
    "name:nld_x_preferred":[
        "Alberton"
    ],
    "name:pol_x_preferred":[
        "Alberton"
    ],
    "name:por_x_preferred":[
        "Alberton"
    ],
    "name:swe_x_preferred":[
        "Alberton"
    ],
    "qs_pg:aaroncc":"AU",
    "qs_pg:gn_country":"AU",
    "qs_pg:gn_fcode":"PPL",
    "qs_pg:gn_pop":0,
    "qs_pg:name":"Alberton",
    "qs_pg:name_adm0":"Australia",
    "qs_pg:name_adm1":"Victoria",
    "qs_pg:photos":5,
    "qs_pg:photos_1k":1,
    "qs_pg:photos_9k":1,
    "qs_pg:photos_9r":1,
    "qs_pg:photos_all":5,
    "qs_pg:photos_sr":1,
    "qs_pg:pop_sr":4,
    "qs_pg:qs_pg_placetype":"locality",
    "qs_pg:qs_pg_placetype_gp":"Town",
    "qs_pg:woe_adm0":23424748,
    "woe:adm0_id":23424748,
    "woe:name_adm0":"Australia",
    "woe:name_adm1":"Victoria",
    "woe:placetype":"Town",
    "wof:name":"Alberton",
    "wof:placetype":"locality",
    "wof:population":262
},
  "geometry": {"coordinates":[146.66667000000001,-38.61667],"type":"Point"}
}