{
  "type": "Feature",
  "properties": {
    "iso:country":"AU",
    "name:ceb_x_preferred":[
        "Willoughby"
    ],
    "name:deu_x_preferred":[
        "Willoughby"
    ],
    "name:eng_x_preferred":[
        "Willoughby"
    ],
    "name:fra_x_preferred":[
        "Willoughby"
    ],
    "name:ita_x_preferred":[
        "Willoughby"
    ],
    "name:nld_x_preferred":[
        "Willoughby"
    ],
    "name:pol_x_preferred":[
        "Willoughby"
    ],
    "name:por_x_preferred":[
        "Willoughby"
    ],
    "name:rus_x_preferred":[
        "\u0423\u0438\u043b\u043b\u043e\u0443\u0431\u0438"
    ],
    "name:swe_x_preferred":[
        "Willoughby"
    ],
    "qs_pg:aaroncc":"AU",
    "qs_pg:name":"Willoughby",
    "qs_pg:name_adm0":"Australia",
    "qs_pg:name_adm1":"South Australia",
    "qs_pg:photos":106,
    "qs_pg:photos_1k":21,
    "qs_pg:photos_9k":1,
    "qs_pg:photos_9r":3,
    "qs_pg:photos_all":106,
    "qs_pg:photos_sr":3,
    "qs_pg:pop_sr":0,
    "qs_pg:qs_pg_placetype":"locality",
    "qs_pg:qs_pg_placetype_gp":"Town",
    "qs_pg:woe_adm0":23424748,
    "woe:adm0_id":23424748,
    "woe:name_adm0":"Australia",
    "woe:name_adm1":"South Australia",
    "woe:placetype":"Town",
    "wof:name":"Willoughby",
    "wof:placetype":"locality"
},
  "geometry": {"coordinates":[138.13101700000001,-35.842029],"type":"Point"}
}