{
  "type": "Feature",
  "properties": {
    "iso:country":"AU",
    "qs_pg:aaroncc":"AU",
    "qs_pg:name":"Hester Brook",
    "qs_pg:name_adm0":"Australia",
    "qs_pg:name_adm1":"Western Australia",
    "qs_pg:photos":3,
    "qs_pg:photos_1k":1,
    "qs_pg:photos_9k":1,
    "qs_pg:photos_9r":1,
    "qs_pg:photos_all":3,
    "qs_pg:photos_sr":1,
    "qs_pg:pop_sr":0,
    "qs_pg:qs_pg_placetype":"locality",
    "qs_pg:qs_pg_placetype_gp":"Town",
    "qs_pg:woe_adm0":23424748,
    "woe:adm0_id":23424748,
    "woe:name_adm0":"Australia",
    "woe:name_adm1":"Western Australia",
    "woe:placetype":"Town",
    "wof:name":"Hester Brook",
    "wof:placetype":"locality"
},
  "geometry": {"coordinates":[116.10905099999999,-33.911719],"type":"Point"}
}