{
  "type": "Feature",
  "properties": {
    "gn:admin1_code":"4.0",
    "gn:admin2_code":"34710.0",
    "gn:asciiname":"Tulga",
    "gn:country_code":"AU",
    "gn:dem":196,
    "gn:feature_class":"P",
    "gn:feature_code":"PPL",
    "gn:name":"Tulga",
    "gn:population":0,
    "gn:timezone":"Australia/Brisbane",
    "iso:country":"AU",
    "name:eng_x_preferred":[
        "Tulga"
    ],
    "wof:name":"Tulga",
    "wof:placetype":"locality"
},
  "geometry": {"coordinates":[143.29116000000005,-23.80431],"type":"Point"}
}