{
  "type": "Feature",
  "properties": {
    "gn:admin1_code":"4.0",
    "gn:admin2_code":"34710.0",
    "gn:asciiname":"Tulga",
    "gn:country_code":"AU",
    "gn:dem":196,
    "gn:feature_class":"P",
    "gn:feature_code":"PPL",
    "gn:name":"Tulga",
    "gn:population":0,
    "gn:timezone":"Australia/Brisbane",
    "iso:country":"AU",
    "name:arg_x_preferred":[
        "Tulga"
    ],
    "name:bul_x_preferred":[
        "\u0422\u0443\u043b\u0433\u0430"
    ],
    "name:cat_x_preferred":[
        "Tulga"
    ],
    "name:ces_x_preferred":[
        "Tulga"
    ],
    "name:deu_x_preferred":[
        "Tulga"
    ],
    "name:eng_x_preferred":[
        "Tulga"
    ],
    "name:eus_x_preferred":[
        "Tulga"
    ],
    "name:fra_x_preferred":[
        "Tulga"
    ],
    "name:glg_x_preferred":[
        "Tulga"
    ],
    "name:got_x_preferred":[
        "\ud800\udf44\ud800\udf3f\ud800\udf3b\ud800\udf32\ud800\udf30"
    ],
    "name:ita_x_preferred":[
        "Tulga"
    ],
    "name:nld_x_preferred":[
        "Tulga"
    ],
    "name:nor_x_preferred":[
        "Tulga"
    ],
    "name:pol_x_preferred":[
        "Tulga"
    ],
    "name:por_x_preferred":[
        "Tulga"
    ],
    "name:rus_x_preferred":[
        "\u0422\u0443\u043b\u044c\u0433\u0430"
    ],
    "name:spa_x_preferred":[
        "Tulga"
    ],
    "name:srp_x_preferred":[
        "\u0422\u0443\u043b\u0433\u0430"
    ],
    "name:ukr_x_preferred":[
        "\u0422\u0443\u043b\u044c\u0491\u0430"
    ],
    "wof:name":"Tulga",
    "wof:placetype":"locality"
},
  "geometry": {"coordinates":[143.29116000000005,-23.80431],"type":"Point"}
}