{
  "type": "Feature",
  "properties": {
    "iso:country":"AU",
    "name:eng_x_preferred":[
        "Bayview"
    ],
    "name:fra_x_preferred":[
        "Bayview"
    ],
    "qs:gn_adm0_cc":"AU",
    "qs:gn_fcode":"PPLX",
    "qs:gn_local":2073124,
    "qs:gn_nam_loc":"Darwin, Northern Territory, AU",
    "qs:gn_namadm1":"03",
    "qs:gn_name":"Bayview",
    "qs:local_max":8241,
    "qs:local_sum":25191,
    "qs:localhoods":25,
    "qs:name":"Bayview",
    "qs:name_adm0":"Australia",
    "qs:name_adm1":"Northern Territory",
    "qs:name_adm2":"Darwin",
    "qs:name_local":"Darwin",
    "qs:photo_max":83,
    "qs:photo_sum":120,
    "qs:placetype":"Suburb",
    "qs:quad_count":7,
    "qs:woe_adm0":23424748,
    "qs:woe_adm1":2344701,
    "qs:woe_adm2":55864364,
    "qs:woe_lau":0,
    "qs:woe_local":1101597,
    "qs:woe_ver":"7.10.0",
    "wof:name":"Bayview",
    "wof:placetype":"neighbourhood"
},
  "geometry": {"coordinates":[130.860375,-12.446435],"type":"Point"}
}