{
  "type": "Feature",
  "properties": {
    "gn:admin1_code":"5.0",
    "gn:admin2_code":"41010.0",
    "gn:asciiname":"Marnview Stud",
    "gn:country_code":"AU",
    "gn:dem":29,
    "gn:feature_class":"P",
    "gn:feature_code":"PPL",
    "gn:name":"Marnview Stud",
    "gn:population":0,
    "gn:timezone":"Australia/Adelaide",
    "iso:country":"AU",
    "name:eng_x_preferred":[
        "Marnview Stud"
    ],
    "wof:name":"Marnview Stud",
    "wof:placetype":"locality"
},
  "geometry": {"coordinates":[133.58914999999999,-32.05878],"type":"Point"}
}