{
  "type": "Feature",
  "properties": {
    "gn:admin1_code":"4.0",
    "gn:admin2_code":"36510.0",
    "gn:asciiname":"Maroon",
    "gn:country_code":"AU",
    "gn:dem":197,
    "gn:feature_class":"P",
    "gn:feature_code":"PPL",
    "gn:name":"Maroon",
    "gn:population":0,
    "gn:timezone":"Australia/Brisbane",
    "iso:country":"AU",
    "name:eng_x_preferred":[
        "Maroon"
    ],
    "wof:name":"Maroon",
    "wof:placetype":"locality"
},
  "geometry": {"coordinates":[152.71778999999995,-28.1773],"type":"Point"}
}