{
  "type": "Feature",
  "properties": {
    "gn:admin1_code":"5.0",
    "gn:admin2_code":"43790.0",
    "gn:asciiname":"Mootatunga",
    "gn:country_code":"AU",
    "gn:dem":75,
    "gn:feature_class":"P",
    "gn:feature_code":"PPL",
    "gn:name":"Mootatunga",
    "gn:population":0,
    "gn:timezone":"Australia/Adelaide",
    "iso:country":"AU",
    "name:eng_x_preferred":[
        "Mootatunga"
    ],
    "wof:name":"Mootatunga",
    "wof:placetype":"locality"
},
  "geometry": {"coordinates":[140.84163000000001,-34.96137],"type":"Point"}
}