{
  "type": "Feature",
  "properties": {
    "gn:country":"AU",
    "gn:fcode":"PPL",
    "gn:population":377,
    "iso:country":"AU",
    "name:bel_x_preferred":[
        "\u0424\u0430\u043b\u043c\u0443\u0442"
    ],
    "name:cat_x_preferred":[
        "Falmouth"
    ],
    "name:ceb_x_preferred":[
        "Falmouth"
    ],
    "name:deu_x_preferred":[
        "Falmouth"
    ],
    "name:ell_x_preferred":[
        "\u03a6\u03ac\u03bb\u03bc\u03bf\u03c5\u03b8"
    ],
    "name:fin_x_preferred":[
        "Falmouth"
    ],
    "name:fra_x_preferred":[
        "Falmouth"
    ],
    "name:glg_x_preferred":[
        "Falmouth"
    ],
    "name:ita_x_preferred":[
        "Falmouth"
    ],
    "name:jpn_x_preferred":[
        "\u30d5\u30a1\u30eb\u30de\u30b9"
    ],
    "name:kor_x_preferred":[
        "\ud330\uba38\uc2a4"
    ],
    "name:nld_x_preferred":[
        "Falmouth"
    ],
    "name:nor_x_preferred":[
        "Falmouth"
    ],
    "name:pol_x_preferred":[
        "Falmouth"
    ],
    "name:por_x_preferred":[
        "Falmouth"
    ],
    "name:rus_x_preferred":[
        "\u0424\u0430\u043b\u043c\u0443\u0442"
    ],
    "name:spa_x_preferred":[
        "Falmouth"
    ],
    "name:srp_x_preferred":[
        "\u0424\u0430\u043b\u043c\u0443\u0442"
    ],
    "name:swa_x_preferred":[
        "Falmouth"
    ],
    "name:swe_x_preferred":[
        "Falmouth"
    ],
    "name:ukr_x_preferred":[
        "\u0424\u0430\u043b\u043c\u0443\u0442"
    ],
    "name:vol_x_preferred":[
        "Falmouth"
    ],
    "name:zho_x_preferred":[
        "\u6cd5\u5c14\u8305\u65af"
    ],
    "qs_pg:aaroncc":"AU",
    "qs_pg:gn_country":"AU",
    "qs_pg:gn_fcode":"PPL",
    "qs_pg:gn_pop":377,
    "qs_pg:name":"Falmouth",
    "qs_pg:name_adm0":"Australia",
    "qs_pg:name_adm1":"Tasmania",
    "qs_pg:photos":44,
    "qs_pg:photos_1k":9,
    "qs_pg:photos_9k":1,
    "qs_pg:photos_9r":2,
    "qs_pg:photos_all":44,
    "qs_pg:photos_sr":2,
    "qs_pg:pop_sr":2,
    "qs_pg:qs_pg_placetype":"locality",
    "qs_pg:qs_pg_placetype_gp":"Town",
    "qs_pg:woe_adm0":23424748,
    "woe:adm0_id":23424748,
    "woe:name_adm0":"Australia",
    "woe:name_adm1":"Tasmania",
    "woe:placetype":"Town",
    "wof:name":"Falmouth",
    "wof:placetype":"locality",
    "wof:population":377
},
  "geometry": {"coordinates":[148.26333,-41.50611],"type":"Point"}
}