{
  "type": "Feature",
  "properties": {
    "gn:admin1_code":"4.0",
    "gn:admin2_code":"36660.0",
    "gn:asciiname":"Bapaume",
    "gn:country_code":"AU",
    "gn:dem":897,
    "gn:feature_class":"P",
    "gn:feature_code":"PPL",
    "gn:name":"Bapaume",
    "gn:population":0,
    "gn:timezone":"Australia/Brisbane",
    "iso:country":"AU",
    "name:ara_x_preferred":[
        "\u0628\u0627\u0628\u0648\u0645"
    ],
    "name:bre_x_preferred":[
        "Bapaume"
    ],
    "name:bul_x_preferred":[
        "\u0411\u0430\u043f\u043e\u043c"
    ],
    "name:cat_x_preferred":[
        "Bapaume"
    ],
    "name:ceb_x_preferred":[
        "Bapaume"
    ],
    "name:deu_x_preferred":[
        "Bapaume"
    ],
    "name:eng_x_preferred":[
        "Bapaume"
    ],
    "name:eus_x_preferred":[
        "Bapaume"
    ],
    "name:fas_x_preferred":[
        "\u0628\u0627\u067e\u0648\u0645"
    ],
    "name:fin_x_preferred":[
        "Bapaume"
    ],
    "name:fra_x_preferred":[
        "Bapaume"
    ],
    "name:hun_x_preferred":[
        "Bapaume"
    ],
    "name:ind_x_preferred":[
        "Bapaume"
    ],
    "name:ita_x_preferred":[
        "Bapaume"
    ],
    "name:kaz_x_preferred":[
        "\u0411\u0430\u043f\u043e\u043c"
    ],
    "name:lat_x_preferred":[
        "Bapalma"
    ],
    "name:ltz_x_preferred":[
        "Bapaume"
    ],
    "name:mlg_x_preferred":[
        "Bapaume"
    ],
    "name:msa_x_preferred":[
        "Bapaume"
    ],
    "name:nld_x_preferred":[
        "Bapaume"
    ],
    "name:nor_x_preferred":[
        "Bapaume"
    ],
    "name:oci_x_preferred":[
        "Bapaume"
    ],
    "name:pcd_x_preferred":[
        "Bapaume"
    ],
    "name:pms_x_preferred":[
        "Bapaume"
    ],
    "name:pol_x_preferred":[
        "Bapaume"
    ],
    "name:por_x_preferred":[
        "Bapaume"
    ],
    "name:ron_x_preferred":[
        "Bapaume"
    ],
    "name:rus_x_preferred":[
        "\u0411\u0430\u043f\u043e\u043c"
    ],
    "name:slk_x_preferred":[
        "Bapaume"
    ],
    "name:spa_x_preferred":[
        "Bapaume"
    ],
    "name:sqi_x_preferred":[
        "Bapaume"
    ],
    "name:srp_x_preferred":[
        "\u0411\u0430\u043f\u043e\u043c"
    ],
    "name:swe_x_preferred":[
        "Bapaume"
    ],
    "name:tur_x_preferred":[
        "Bapaume"
    ],
    "name:ukr_x_preferred":[
        "\u0411\u0430\u043f\u043e\u043c"
    ],
    "name:vie_x_preferred":[
        "Bapaume"
    ],
    "name:vol_x_preferred":[
        "Bapaume"
    ],
    "name:war_x_preferred":[
        "Bapaume"
    ],
    "name:zho_x_preferred":[
        "\u5df4\u6ce2\u59c6"
    ],
    "wof:name":"Bapaume",
    "wof:placetype":"locality"
},
  "geometry": {"coordinates":[151.84384,-28.5699],"type":"Point"}
}