{
  "type": "Feature",
  "properties": {
    "gn:admin1_code":"4.0",
    "gn:admin2_code":"33620.0",
    "gn:asciiname":"Kanyan",
    "gn:country_code":"AU",
    "gn:dem":62,
    "gn:feature_class":"P",
    "gn:feature_code":"PPL",
    "gn:name":"Kanyan",
    "gn:population":0,
    "gn:timezone":"Australia/Brisbane",
    "iso:country":"AU",
    "name:eng_x_preferred":[
        "Kanyan"
    ],
    "wof:name":"Kanyan",
    "wof:placetype":"locality"
},
  "geometry": {"coordinates":[152.54638,-25.93058],"type":"Point"}
}