{
  "type": "Feature",
  "properties": {
    "gn:country":"AU",
    "gn:fcode":"PPLX",
    "gn:population":0,
    "iso:country":"AU",
    "qs_pg:aaroncc":"AU",
    "qs_pg:gn_country":"AU",
    "qs_pg:gn_fcode":"PPLX",
    "qs_pg:gn_pop":0,
    "qs_pg:name":"Armadale North",
    "qs_pg:name_adm0":"Australia",
    "qs_pg:name_adm1":"Victoria",
    "qs_pg:photos":91,
    "qs_pg:photos_1k":18,
    "qs_pg:photos_9k":1,
    "qs_pg:photos_9r":3,
    "qs_pg:photos_all":91,
    "qs_pg:photos_sr":3,
    "qs_pg:pop_sr":0,
    "qs_pg:qs_pg_placetype":"neighbourhood",
    "qs_pg:qs_pg_placetype_gp":"Suburb",
    "qs_pg:woe_adm0":23424748,
    "woe:adm0_id":23424748,
    "woe:name_adm0":"Australia",
    "woe:name_adm1":"Victoria",
    "woe:placetype":"Suburb",
    "wof:name":"Armadale North",
    "wof:placetype":"neighbourhood"
},
  "geometry": {"coordinates":[145.03333000000001,-37.85],"type":"Point"}
}