{
  "type": "Feature",
  "properties": {
    "gn:admin1_code":"2.0",
    "gn:admin2_code":"10300.0",
    "gn:asciiname":"Lette",
    "gn:country_code":"AU",
    "gn:dem":65,
    "gn:feature_class":"P",
    "gn:feature_code":"PPL",
    "gn:name":"Lette",
    "gn:population":0,
    "gn:timezone":"Australia/Sydney",
    "iso:country":"AU",
    "wof:name":"Lette",
    "wof:placetype":"locality"
},
  "geometry": {"coordinates":[143.16666999999995,-34.36667],"type":"Point"}
}