{
  "type": "Feature",
  "properties": {
    "gn:admin1_code":"2.0",
    "gn:admin2_code":"13700.0",
    "gn:asciiname":"Bramshott",
    "gn:country_code":"AU",
    "gn:dem":519,
    "gn:feature_class":"P",
    "gn:feature_code":"PPL",
    "gn:name":"Bramshott",
    "gn:population":0,
    "gn:timezone":"Australia/Sydney",
    "iso:country":"AU",
    "name:cym_x_preferred":[
        "Bramshott"
    ],
    "name:eng_x_preferred":[
        "Bramshott"
    ],
    "name:pol_x_preferred":[
        "Bramshott"
    ],
    "wof:name":"Bramshott",
    "wof:placetype":"locality"
},
  "geometry": {"coordinates":[148.18589,-34.48387],"type":"Point"}
}