{
  "type": "Feature",
  "properties": {
    "gn:admin1_code":"2.0",
    "gn:admin2_code":"12750.0",
    "gn:asciiname":"Coila",
    "gn:country_code":"AU",
    "gn:dem":6,
    "gn:feature_class":"P",
    "gn:feature_code":"PPL",
    "gn:name":"Coila",
    "gn:population":0,
    "gn:timezone":"Australia/Sydney",
    "iso:country":"AU",
    "wof:name":"Coila",
    "wof:placetype":"locality"
},
  "geometry": {"coordinates":[150.09649999999999,-36.0068],"type":"Point"}
}