{
  "type": "Feature",
  "properties": {
    "gn:admin1_code":"2.0",
    "gn:admin2_code":"14750.0",
    "gn:asciiname":"Fivebough",
    "gn:country_code":"AU",
    "gn:dem":135,
    "gn:feature_class":"P",
    "gn:feature_code":"PPL",
    "gn:name":"Fivebough",
    "gn:population":0,
    "gn:timezone":"Australia/Sydney",
    "iso:country":"AU",
    "name:und_x_variant":[
        "Five Bough"
    ],
    "wof:name":"Fivebough",
    "wof:placetype":"locality"
},
  "geometry": {"coordinates":[146.44631000000001,-34.52802],"type":"Point"}
}