{
  "type": "Feature",
  "properties": {
    "gn:asciiname":"Queensland Islands",
    "gn:country_code":"AU",
    "gn:dem":-9999,
    "gn:feature_class":"P",
    "gn:feature_code":"PPL",
    "gn:name":"Queensland Islands",
    "gn:population":0,
    "gn:timezone":"Australia/Brisbane",
    "iso:country":"AU",
    "wof:name":"Queensland Islands",
    "wof:placetype":"locality"
},
  "geometry": {"coordinates":[149.9333,-21.48333],"type":"Point"}
}