{
  "type": "Feature",
  "properties": {
    "gn:admin1_code":"8.0",
    "gn:admin2_code":"55250.0",
    "gn:asciiname":"Duffers Yard",
    "gn:country_code":"AU",
    "gn:dem":313,
    "gn:feature_class":"P",
    "gn:feature_code":"PPL",
    "gn:name":"Duffers Yard",
    "gn:population":0,
    "gn:timezone":"Australia/Perth",
    "iso:country":"AU",
    "wof:name":"Duffers Yard",
    "wof:placetype":"locality"
},
  "geometry": {"coordinates":[117.81054,-23.78497],"type":"Point"}
}