{
  "type": "Feature",
  "properties": {
    "gn:admin1_code":"2.0",
    "gn:admin2_code":"14600.0",
    "gn:asciiname":"Berrilee",
    "gn:country_code":"AU",
    "gn:dem":300,
    "gn:feature_class":"P",
    "gn:feature_code":"PPL",
    "gn:name":"Berrilee",
    "gn:population":0,
    "gn:timezone":"Australia/Sydney",
    "iso:country":"AU",
    "name:eng_x_preferred":[
        "Berrilee"
    ],
    "wof:name":"Berrilee",
    "wof:placetype":"locality"
},
  "geometry": {"coordinates":[147.33435,-32.73397],"type":"Point"}
}