{
  "type": "Feature",
  "properties": {
    "gn:gn_country":"AU",
    "gn:gn_fcode":"PPL",
    "gn:gn_pop":622,
    "gn:population":622,
    "iso:country":"AU",
    "name:eng_x_preferred":[
        "Doubtful Creek"
    ],
    "qs_pg:aaroncc":"AU",
    "qs_pg:gn_country":"AU",
    "qs_pg:gn_fcode":"PPL",
    "qs_pg:gn_pop":622,
    "qs_pg:name":"Doubtful Creek",
    "qs_pg:name_adm0":"Australia",
    "qs_pg:name_adm1":"New South Wales",
    "qs_pg:photos_9k":1,
    "qs_pg:photos_9r":1,
    "qs_pg:photos_all":1,
    "qs_pg:photos_sr":0,
    "qs_pg:pop_sr":2,
    "qs_pg:qs_pg_placetype":"locality",
    "qs_pg:qs_pg_placetype_gp":"Town",
    "qs_pg:woe_adm0":23424748,
    "woe:adm0_id":23424748,
    "woe:name_adm0":"Australia",
    "woe:name_adm1":"New South Wales",
    "woe:placetype":"Town",
    "wof:name":"Doubtful Creek",
    "wof:placetype":"locality",
    "wof:population":622
},
  "geometry": {"coordinates":[152.91667000000001,-28.76667],"type":"Point"}
}