{
  "type": "Feature",
  "properties": {
    "gn:admin1_code":"6.0",
    "gn:admin2_code":"60210.0",
    "gn:asciiname":"Douglas River",
    "gn:country_code":"AU",
    "gn:dem":86,
    "gn:feature_class":"P",
    "gn:feature_code":"PPL",
    "gn:name":"Douglas River",
    "gn:population":0,
    "gn:timezone":"Australia/Hobart",
    "iso:country":"AU",
    "name:ceb_x_preferred":[
        "Douglas River"
    ],
    "name:eng_x_preferred":[
        "Douglas River"
    ],
    "name:fra_x_preferred":[
        "Douglas"
    ],
    "wof:name":"Douglas River",
    "wof:placetype":"locality"
},
  "geometry": {"coordinates":[148.25028,-41.78556],"type":"Point"}
}