{
  "type": "Feature",
  "properties": {
    "gn:admin1_code":"2.0",
    "gn:admin2_code":"10600.0",
    "gn:asciiname":"Darwood",
    "gn:country_code":"AU",
    "gn:dem":100,
    "gn:feature_class":"P",
    "gn:feature_code":"PPL",
    "gn:name":"Darwood",
    "gn:population":0,
    "gn:timezone":"Australia/Sydney",
    "iso:country":"AU",
    "name:eng_x_preferred":[
        "Darwood"
    ],
    "wof:name":"Darwood",
    "wof:placetype":"locality"
},
  "geometry": {"coordinates":[152.64046999999999,-30.4462],"type":"Point"}
}