{
  "type": "Feature",
  "properties": {
    "gn:admin1_code":"2.0",
    "gn:admin2_code":"14950.0",
    "gn:asciiname":"Ashburton",
    "gn:country_code":"AU",
    "gn:dem":157,
    "gn:feature_class":"P",
    "gn:feature_code":"PPL",
    "gn:name":"Ashburton",
    "gn:population":0,
    "gn:timezone":"Australia/Sydney",
    "iso:country":"AU",
    "name:ceb_x_preferred":[
        "Ashburton"
    ],
    "name:chv_x_preferred":[
        "\u0410\u0448\u0431\u0435\u0440\u0442\u043e\u043d"
    ],
    "name:deu_x_preferred":[
        "Ashburton"
    ],
    "name:eng_x_preferred":[
        "Ashburton"
    ],
    "name:fra_x_preferred":[
        "Ashburton"
    ],
    "name:hrv_x_preferred":[
        "Ashburton"
    ],
    "name:ita_x_preferred":[
        "Ashburton"
    ],
    "name:jpn_x_preferred":[
        "\u30a2\u30b7\u30e5\u30d0\u30fc\u30c8\u30f3"
    ],
    "name:kor_x_preferred":[
        "\uc560\uc288\ubc84\ud134"
    ],
    "name:mlg_x_preferred":[
        "Ashburton"
    ],
    "name:nld_x_preferred":[
        "Ashburton"
    ],
    "name:nor_x_preferred":[
        "Ashburton"
    ],
    "name:pol_x_preferred":[
        "Ashburton"
    ],
    "name:rus_x_preferred":[
        "\u0410\u0448\u0431\u0435\u0440\u0442\u043e\u043d"
    ],
    "name:swe_x_preferred":[
        "Ashburton"
    ],
    "wof:name":"Ashburton",
    "wof:placetype":"locality"
},
  "geometry": {"coordinates":[146.53564,-35.48486],"type":"Point"}
}