{
  "type": "Feature",
  "properties": {
    "gn:admin1_code":"4.0",
    "gn:admin2_code":"36660.0",
    "gn:asciiname":"Silverwood",
    "gn:country_code":"AU",
    "gn:dem":516,
    "gn:feature_class":"P",
    "gn:feature_code":"PPL",
    "gn:name":"Silverwood",
    "gn:population":0,
    "gn:timezone":"Australia/Brisbane",
    "iso:country":"AU",
    "name:eng_x_preferred":[
        "Silverwood"
    ],
    "wof:name":"Silverwood",
    "wof:placetype":"locality"
},
  "geometry": {"coordinates":[152.00507999999999,-28.32388],"type":"Point"}
}