{
  "type": "Feature",
  "properties": {
    "gn:admin1_code":"4.0",
    "gn:admin2_code":"35760.0",
    "gn:asciiname":"Ceratodus",
    "gn:country_code":"AU",
    "gn:dem":176,
    "gn:feature_class":"P",
    "gn:feature_code":"PPL",
    "gn:name":"Ceratodus",
    "gn:population":0,
    "gn:timezone":"Australia/Brisbane",
    "iso:country":"AU",
    "wof:name":"Ceratodus",
    "wof:placetype":"locality"
},
  "geometry": {"coordinates":[151.13945000000001,-25.29162],"type":"Point"}
}