{
  "type": "Feature",
  "properties": {
    "gn:admin1_code":"2.0",
    "gn:admin2_code":"17850.0",
    "gn:asciiname":"Kangaroo Flat",
    "gn:country_code":"AU",
    "gn:dem":969,
    "gn:feature_class":"P",
    "gn:feature_code":"PPL",
    "gn:name":"Kangaroo Flat",
    "gn:population":0,
    "gn:timezone":"Australia/Sydney",
    "iso:country":"AU",
    "name:eng_x_preferred":[
        "Kangaroo Flat"
    ],
    "wof:name":"Kangaroo Flat",
    "wof:placetype":"locality"
},
  "geometry": {"coordinates":[152.13355000000001,-31.13121],"type":"Point"}
}