{
  "type": "Feature",
  "properties": {
    "gn:admin1_code":"2",
    "gn:admin2_code":"16950",
    "gn:asciiname":"Wogamia",
    "gn:country_code":"AU",
    "gn:dem":14,
    "gn:feature_class":"P",
    "gn:feature_code":"PPL",
    "gn:name":"Wogamia",
    "gn:population":0,
    "gn:timezone":"Australia/Sydney",
    "iso:country":"AU",
    "wof:name":"Wogamia",
    "wof:placetype":"locality"
},
  "geometry": {"coordinates":[150.51667,-34.88333],"type":"Point"}
}