{
  "type": "Feature",
  "properties": {
    "gn:admin1_code":"4.0",
    "gn:admin2_code":"30900.0",
    "gn:asciiname":"Canary",
    "gn:country_code":"AU",
    "gn:dem":151,
    "gn:feature_class":"P",
    "gn:feature_code":"PPL",
    "gn:name":"Canary",
    "gn:population":0,
    "gn:timezone":"Australia/Brisbane",
    "iso:country":"AU",
    "name:eng_x_preferred":[
        "Canary"
    ],
    "wof:name":"Canary",
    "wof:placetype":"locality"
},
  "geometry": {"coordinates":[140.35708,-23.24174],"type":"Point"}
}