{
  "type": "Feature",
  "properties": {
    "gn:admin1_code":"2.0",
    "gn:admin2_code":"10250.0",
    "gn:asciiname":"Bagotville",
    "gn:country_code":"AU",
    "gn:dem":8,
    "gn:feature_class":"P",
    "gn:feature_code":"PPL",
    "gn:name":"Bagotville",
    "gn:population":0,
    "gn:timezone":"Australia/Sydney",
    "iso:country":"AU",
    "name:eng_x_preferred":[
        "Bagotville"
    ],
    "name:fra_x_preferred":[
        "Bagotville"
    ],
    "wof:name":"Bagotville",
    "wof:placetype":"locality"
},
  "geometry": {"coordinates":[153.42117999999999,-28.98276],"type":"Point"}
}