{
  "type": "Feature",
  "properties": {
    "iso:country":"AU",
    "name:ace_x_preferred":[
        "Cam Cleeland"
    ],
    "name:ast_x_preferred":[
        "Cam Cleeland"
    ],
    "name:bjn_x_preferred":[
        "Cam Cleeland"
    ],
    "name:bug_x_preferred":[
        "Cam Cleeland"
    ],
    "name:cat_x_preferred":[
        "Cam Cleeland"
    ],
    "name:deu_x_preferred":[
        "Cam Cleeland"
    ],
    "name:eng_x_preferred":[
        "Cleeland"
    ],
    "name:eng_x_variant":[
        "Cam Cleeland"
    ],
    "name:fra_x_preferred":[
        "Cam Cleeland"
    ],
    "name:ind_x_preferred":[
        "Cam Cleeland"
    ],
    "name:ita_x_preferred":[
        "Cam Cleeland"
    ],
    "name:jav_x_preferred":[
        "Cam Cleeland"
    ],
    "name:min_x_preferred":[
        "Cam Cleeland"
    ],
    "name:nld_x_preferred":[
        "Cam Cleeland"
    ],
    "name:slv_x_preferred":[
        "Cam Cleeland"
    ],
    "name:spa_x_preferred":[
        "Cam Cleeland"
    ],
    "name:sun_x_preferred":[
        "Cam Cleeland"
    ],
    "qs:gn_adm0_cc":"AU",
    "qs:gn_local":2158177,
    "qs:local_max":22745,
    "qs:local_sum":338594,
    "qs:localhoods":407,
    "qs:name":"Cleeland",
    "qs:name_adm0":"Australia",
    "qs:name_adm1":"Victoria",
    "qs:name_adm2":"Greater Dandenong",
    "qs:name_local":"Melbourne",
    "qs:photo_max":34,
    "qs:photo_sum":96,
    "qs:placetype":"Suburb",
    "qs:quad_count":7,
    "qs:woe_adm0":23424748,
    "qs:woe_adm1":2344705,
    "qs:woe_adm2":55863999,
    "qs:woe_lau":0,
    "qs:woe_local":1103816,
    "qs:woe_ver":"7.10.0",
    "wd:wordcount":80,
    "wof:lang":[
        "eng"
    ],
    "wof:name":"Cleeland",
    "wof:placetype":"neighbourhood"
},
  "geometry": {"coordinates":[145.21091999999999,-37.972543],"type":"Point"}
}