{
  "type": "Feature",
  "properties": {
    "gn:admin1_code":"4.0",
    "gn:admin2_code":"33610.0",
    "gn:asciiname":"Kurumbul",
    "gn:country_code":"AU",
    "gn:dem":237,
    "gn:feature_class":"P",
    "gn:feature_code":"PPL",
    "gn:name":"Kurumbul",
    "gn:population":0,
    "gn:timezone":"Australia/Brisbane",
    "iso:country":"AU",
    "name:eng_x_preferred":[
        "Kurumbul"
    ],
    "wof:name":"Kurumbul",
    "wof:placetype":"locality"
},
  "geometry": {"coordinates":[150.55000000000001,-28.61667000000001],"type":"Point"}
}