{
  "type": "Feature",
  "properties": {
    "gn:admin1_code":"2.0",
    "gn:admin2_code":"15800.0",
    "gn:asciiname":"The Chace",
    "gn:country_code":"AU",
    "gn:dem":147,
    "gn:feature_class":"P",
    "gn:feature_code":"PPL",
    "gn:name":"The Chace",
    "gn:population":0,
    "gn:timezone":"Australia/Sydney",
    "iso:country":"AU",
    "name:eng_x_preferred":[
        "The Chace"
    ],
    "wof:name":"The Chace",
    "wof:placetype":"locality"
},
  "geometry": {"coordinates":[146.39834999999999,-34.88815],"type":"Point"}
}