{
  "type": "Feature",
  "properties": {
    "gn:admin1_code":"4.0",
    "gn:admin2_code":"32250.0",
    "gn:asciiname":"Duck Hole Yard",
    "gn:country_code":"AU",
    "gn:dem":50,
    "gn:feature_class":"P",
    "gn:feature_code":"PPL",
    "gn:name":"Duck Hole Yard",
    "gn:population":0,
    "gn:timezone":"Australia/Brisbane",
    "iso:country":"AU",
    "wof:name":"Duck Hole Yard",
    "wof:placetype":"locality"
},
  "geometry": {"coordinates":[142.34826000000001,-15.90013],"type":"Point"}
}