{
  "type": "Feature",
  "properties": {
    "gn:admin1_code":"2.0",
    "gn:admin2_code":"11050.0",
    "gn:asciiname":"Numby",
    "gn:country_code":"AU",
    "gn:dem":391,
    "gn:feature_class":"P",
    "gn:feature_code":"PPL",
    "gn:name":"Numby",
    "gn:population":0,
    "gn:timezone":"Australia/Sydney",
    "iso:country":"AU",
    "wof:name":"Numby",
    "wof:placetype":"locality"
},
  "geometry": {"coordinates":[149.01667,-34.13333],"type":"Point"}
}