{
  "type": "Feature",
  "properties": {
    "gn:admin1_code":"4.0",
    "gn:admin2_code":"31820.0",
    "gn:asciiname":"Kowbi",
    "gn:country_code":"AU",
    "gn:dem":109,
    "gn:feature_class":"P",
    "gn:feature_code":"PPL",
    "gn:name":"Kowbi",
    "gn:population":0,
    "gn:timezone":"Australia/Brisbane",
    "iso:country":"AU",
    "wof:name":"Kowbi",
    "wof:placetype":"locality"
},
  "geometry": {"coordinates":[152.23333,-25.18333],"type":"Point"}
}