{
  "type": "Feature",
  "properties": {
    "gn:admin1_code":"7",
    "gn:admin2_code":"26810",
    "gn:asciiname":"Woodside",
    "gn:country_code":"AU",
    "gn:dem":40,
    "gn:feature_class":"P",
    "gn:feature_code":"PPL",
    "gn:name":"Woodside",
    "gn:population":0,
    "gn:timezone":"Australia/Melbourne",
    "iso:country":"AU",
    "name:rus_x_preferred":[
        "\u0412\u0443\u0434\u0441\u0430\u0439\u0434"
    ],
    "wof:name":"Woodside",
    "wof:placetype":"locality"
},
  "geometry": {"coordinates":[146.87513999999999,-38.52377],"type":"Point"}
}