{
  "type": "Feature",
  "properties": {
    "gn:admin1_code":"7.0",
    "gn:admin2_code":"27170.0",
    "gn:asciiname":"Mitta Junction",
    "gn:country_code":"AU",
    "gn:dem":182,
    "gn:feature_class":"P",
    "gn:feature_code":"PPL",
    "gn:name":"Mitta Junction",
    "gn:population":0,
    "gn:timezone":"Australia/Melbourne",
    "iso:country":"AU",
    "wof:name":"Mitta Junction",
    "wof:placetype":"locality"
},
  "geometry": {"coordinates":[147.01609999999999,-36.10988],"type":"Point"}
}