{
  "type": "Feature",
  "properties": {
    "gn:country":"AU",
    "gn:fcode":"PPL",
    "gn:population":240,
    "iso:country":"AU",
    "name:ceb_x_preferred":[
        "Gwabegar"
    ],
    "name:deu_x_preferred":[
        "Gwabegar"
    ],
    "name:eng_x_preferred":[
        "Gwabegar"
    ],
    "name:fas_x_preferred":[
        "\u06af\u0648\u0627\u0628\u06cc\u06af\u0631"
    ],
    "name:fra_x_preferred":[
        "Gwabegar"
    ],
    "name:nld_x_preferred":[
        "Gwabegar"
    ],
    "name:swe_x_preferred":[
        "Gwabegar"
    ],
    "qs_pg:aaroncc":"AU",
    "qs_pg:gn_country":"AU",
    "qs_pg:gn_fcode":"PPL",
    "qs_pg:gn_pop":240,
    "qs_pg:name":"Gwabegar",
    "qs_pg:name_adm0":"Australia",
    "qs_pg:name_adm1":"New South Wales",
    "qs_pg:photos_9k":1,
    "qs_pg:photos_9r":1,
    "qs_pg:photos_all":3,
    "qs_pg:photos_sr":0,
    "qs_pg:pop_sr":2,
    "qs_pg:qs_pg_placetype":"locality",
    "qs_pg:qs_pg_placetype_gp":"Town",
    "qs_pg:woe_adm0":23424748,
    "woe:adm0_id":23424748,
    "woe:name_adm0":"Australia",
    "woe:name_adm1":"New South Wales",
    "woe:placetype":"Town",
    "wof:name":"Gwabegar",
    "wof:placetype":"locality",
    "wof:population":240
},
  "geometry": {"coordinates":[148.98333,-30.61667],"type":"Point"}
}