{
  "type": "Feature",
  "properties": {
    "gn:admin1_code":"7.0",
    "gn:admin2_code":"26430.0",
    "gn:asciiname":"Bailieston East",
    "gn:country_code":"AU",
    "gn:dem":129,
    "gn:feature_class":"P",
    "gn:feature_code":"PPL",
    "gn:name":"Bailieston East",
    "gn:population":0,
    "gn:timezone":"Australia/Melbourne",
    "iso:country":"AU",
    "wof:name":"Bailieston East",
    "wof:placetype":"locality"
},
  "geometry": {"coordinates":[145.11667,-36.75],"type":"Point"}
}