{
  "type": "Feature",
  "properties": {
    "gn:admin1_code":"4.0",
    "gn:admin2_code":"36810.0",
    "gn:asciiname":"Kulara",
    "gn:country_code":"AU",
    "gn:dem":692,
    "gn:feature_class":"P",
    "gn:feature_code":"PPL",
    "gn:name":"Kulara",
    "gn:population":0,
    "gn:timezone":"Australia/Brisbane",
    "iso:country":"AU",
    "wof:name":"Kulara",
    "wof:placetype":"locality"
},
  "geometry": {"coordinates":[145.56666999999999,-17.25],"type":"Point"}
}