{
  "type": "Feature",
  "properties": {
    "gn:admin1_code":"06",
    "gn:admin2_code":"61210.0",
    "gn:asciiname":"Three Hummock Island",
    "gn:country_code":"AU",
    "gn:dem":43,
    "gn:feature_class":"P",
    "gn:feature_code":"PPL",
    "gn:name":"Three Hummock Island",
    "gn:population":0,
    "gn:timezone":"Australia/Hobart",
    "iso:country":"AU",
    "name:ceb_x_preferred":[
        "Three Hummock Island"
    ],
    "name:deu_x_preferred":[
        "Three Hummock Island"
    ],
    "name:ita_x_preferred":[
        "Three Hummock Island"
    ],
    "name:por_x_preferred":[
        "Ilha Three Hummock"
    ],
    "name:rus_x_preferred":[
        "\u0422\u0440\u0438-\u0425\u0430\u043c\u043c\u043e\u043a"
    ],
    "name:swe_x_preferred":[
        "Three Hummock Island"
    ],
    "wof:name":"Three Hummock Island",
    "wof:placetype":"locality"
},
  "geometry": {"coordinates":[144.90648999999999,-40.4361],"type":"Point"}
}