{
  "type": "Feature",
  "properties": {
    "gn:admin1_code":"5.0",
    "gn:admin2_code":"43080.0",
    "gn:asciiname":"Pankina",
    "gn:country_code":"AU",
    "gn:dem":80,
    "gn:feature_class":"P",
    "gn:feature_code":"PPL",
    "gn:name":"Pankina",
    "gn:population":0,
    "gn:timezone":"Australia/Adelaide",
    "iso:country":"AU",
    "name:eng_x_preferred":[
        "Pankina"
    ],
    "wof:name":"Pankina",
    "wof:placetype":"locality"
},
  "geometry": {"coordinates":[140.42183,-34.93228],"type":"Point"}
}