{
  "type": "Feature",
  "properties": {
    "gn:admin1_code":"8",
    "gn:admin2_code":"54900",
    "gn:asciiname":"Burngup",
    "gn:country_code":"AU",
    "gn:dem":318,
    "gn:feature_class":"P",
    "gn:feature_code":"PPL",
    "gn:name":"Burngup",
    "gn:population":0,
    "gn:timezone":"Australia/Perth",
    "iso:country":"AU",
    "name:eng_x_preferred":[
        "Burngup"
    ],
    "wof:name":"Burngup",
    "wof:placetype":"locality"
},
  "geometry": {"coordinates":[118.69158,-33.0171],"type":"Point"}
}