{
  "type": "Feature",
  "properties": {
    "gn:admin1_code":"2.0",
    "gn:admin2_code":"18100.0",
    "gn:asciiname":"Marsden",
    "gn:country_code":"AU",
    "gn:dem":209,
    "gn:feature_class":"P",
    "gn:feature_code":"PPL",
    "gn:name":"Marsden",
    "gn:population":0,
    "gn:timezone":"Australia/Sydney",
    "iso:country":"AU",
    "wof:name":"Marsden",
    "wof:placetype":"locality"
},
  "geometry": {"coordinates":[147.53333000000001,-33.75],"type":"Point"}
}