{
  "type": "Feature",
  "properties": {
    "gn:admin1_code":"2.0",
    "gn:admin2_code":"18100.0",
    "gn:asciiname":"Marsden",
    "gn:country_code":"AU",
    "gn:dem":209,
    "gn:feature_class":"P",
    "gn:feature_code":"PPL",
    "gn:name":"Marsden",
    "gn:population":0,
    "gn:timezone":"Australia/Sydney",
    "iso:country":"AU",
    "name:ceb_x_preferred":[
        "Marsden"
    ],
    "name:deu_x_preferred":[
        "Marsden"
    ],
    "name:epo_x_preferred":[
        "Marsden"
    ],
    "name:fra_x_preferred":[
        "Marsden"
    ],
    "name:heb_x_preferred":[
        "\u05de\u05e8\u05e1\u05d3\u05df"
    ],
    "name:ita_x_preferred":[
        "Marsden"
    ],
    "name:nds_x_preferred":[
        "Marsden"
    ],
    "name:nld_x_preferred":[
        "Marsden"
    ],
    "name:pol_x_preferred":[
        "Marsden"
    ],
    "name:rus_x_preferred":[
        "\u041c\u0430\u0440\u0441\u0434\u0435\u043d"
    ],
    "name:swe_x_preferred":[
        "Marsden"
    ],
    "name:ukr_x_preferred":[
        "\u041c\u0430\u0440\u0441\u0434\u0435\u043d"
    ],
    "wof:name":"Marsden",
    "wof:placetype":"locality"
},
  "geometry": {"coordinates":[147.53333000000001,-33.75],"type":"Point"}
}