{
  "type": "Feature",
  "properties": {
    "gn:admin1_code":"2",
    "gn:admin2_code":"11050",
    "gn:asciiname":"Spring Vale",
    "gn:country_code":"AU",
    "gn:dem":352,
    "gn:feature_class":"P",
    "gn:feature_code":"PPL",
    "gn:name":"Spring Vale",
    "gn:population":0,
    "gn:timezone":"Australia/Sydney",
    "iso:country":"AU",
    "wof:name":"Spring Vale",
    "wof:placetype":"locality"
},
  "geometry": {"coordinates":[148.80000000000001,-34.15],"type":"Point"}
}