{
  "type": "Feature",
  "properties": {
    "gn:admin1_code":"2.0",
    "gn:admin2_code":"12750.0",
    "gn:asciiname":"Merricumbene",
    "gn:country_code":"AU",
    "gn:dem":72,
    "gn:feature_class":"P",
    "gn:feature_code":"PPL",
    "gn:name":"Merricumbene",
    "gn:population":0,
    "gn:timezone":"Australia/Sydney",
    "iso:country":"AU",
    "name:eng_x_preferred":[
        "Merricumbene"
    ],
    "wof:name":"Merricumbene",
    "wof:placetype":"locality"
},
  "geometry": {"coordinates":[149.89600000000004,-35.7335],"type":"Point"}
}