{
  "type": "Feature",
  "properties": {
    "gn:admin1_code":"8.0",
    "gn:admin2_code":"56230.0",
    "gn:asciiname":"Calcine",
    "gn:country_code":"AU",
    "gn:dem":39,
    "gn:feature_class":"P",
    "gn:feature_code":"PPL",
    "gn:name":"Calcine",
    "gn:population":0,
    "gn:timezone":"Australia/Perth",
    "iso:country":"AU",
    "name:eng_x_preferred":[
        "Calcine"
    ],
    "wof:name":"Calcine",
    "wof:placetype":"locality"
},
  "geometry": {"coordinates":[115.94277,-32.65106],"type":"Point"}
}