{
  "type": "Feature",
  "properties": {
    "iso:country":"AU",
    "name:ara_x_preferred":[
        "\u063a\u0631\u0627\u0645"
    ],
    "name:cat_x_preferred":[
        "Amor"
    ],
    "name:ceb_x_preferred":[
        "Amor"
    ],
    "name:deu_x_preferred":[
        "Amor"
    ],
    "name:epo_x_preferred":[
        "Amoro"
    ],
    "name:est_x_preferred":[
        "Amor"
    ],
    "name:eus_x_preferred":[
        "Amor"
    ],
    "name:fra_x_preferred":[
        "Amor"
    ],
    "name:ita_x_preferred":[
        "Amor"
    ],
    "name:jpn_x_preferred":[
        "\u30a2\u30e2\u30eb"
    ],
    "name:kor_x_preferred":[
        "\uc544\ubaa8\ub974"
    ],
    "name:lat_x_preferred":[
        "Amor"
    ],
    "name:nld_x_preferred":[
        "Amor"
    ],
    "name:pol_x_preferred":[
        "Amor"
    ],
    "name:por_x_preferred":[
        "Amor"
    ],
    "name:ron_x_preferred":[
        "Amor"
    ],
    "name:rus_x_preferred":[
        "\u0410\u043c\u043e\u0440"
    ],
    "name:slk_x_preferred":[
        "Amor"
    ],
    "name:slv_x_preferred":[
        "Amor"
    ],
    "name:spa_x_preferred":[
        "Amor"
    ],
    "name:swe_x_preferred":[
        "Amor"
    ],
    "qs_pg:aaroncc":"AU",
    "qs_pg:name":"Amor",
    "qs_pg:name_adm0":"Australia",
    "qs_pg:name_adm1":"Victoria",
    "qs_pg:photos":6,
    "qs_pg:photos_1k":1,
    "qs_pg:photos_9k":1,
    "qs_pg:photos_9r":1,
    "qs_pg:photos_all":6,
    "qs_pg:photos_sr":1,
    "qs_pg:pop_sr":0,
    "qs_pg:qs_pg_placetype":"locality",
    "qs_pg:qs_pg_placetype_gp":"Town",
    "qs_pg:woe_adm0":23424748,
    "woe:adm0_id":23424748,
    "woe:name_adm0":"Australia",
    "woe:name_adm1":"Victoria",
    "woe:placetype":"Town",
    "wof:name":"Amor",
    "wof:placetype":"locality"
},
  "geometry": {"coordinates":[146.402725,-37.93721],"type":"Point"}
}