{
  "type": "Feature",
  "properties": {
    "gn:admin1_code":"4.0",
    "gn:admin2_code":"32500.0",
    "gn:asciiname":"Billymango Yard",
    "gn:country_code":"AU",
    "gn:dem":128,
    "gn:feature_class":"P",
    "gn:feature_code":"PPL",
    "gn:name":"Billymango Yard",
    "gn:population":0,
    "gn:timezone":"Australia/Brisbane",
    "iso:country":"AU",
    "wof:name":"Billymango Yard",
    "wof:placetype":"locality"
},
  "geometry": {"coordinates":[143.40934999999999,-15.179],"type":"Point"}
}