{
  "type": "Feature",
  "properties": {
    "gn:gn_country":"AU",
    "gn:gn_fcode":"PPL",
    "gn:gn_pop":6298,
    "gn:population":6298,
    "iso:country":"AU",
    "name:ceb_x_preferred":[
        "Kelso"
    ],
    "name:eng_x_preferred":[
        "Kelso"
    ],
    "name:fra_x_preferred":[
        "Kelso"
    ],
    "name:swe_x_preferred":[
        "Kelso"
    ],
    "name:unk_x_variant":[
        "Kelso"
    ],
    "qs:gn_adm0_cc":"AU",
    "qs:gn_fcode":"PPL",
    "qs:gn_local":2176632,
    "qs:gn_nam_loc":"Bathurst, Bathurst Regional, New South Wales, AU",
    "qs:gn_namadm1":"02",
    "qs:gn_name":"Kelso",
    "qs:local_max":2983,
    "qs:local_sum":5777,
    "qs:localhoods":7,
    "qs:name":"Kelso",
    "qs:name_adm0":"Australia",
    "qs:name_adm1":"New South Wales",
    "qs:name_adm2":"Bathurst Regional",
    "qs:name_local":"Bathurst",
    "qs:photo_max":11,
    "qs:photo_sum":45,
    "qs:placetype":"Suburb",
    "qs:quad_count":12,
    "qs:woe_adm0":23424748,
    "qs:woe_adm1":2344700,
    "qs:woe_adm2":55863861,
    "qs:woe_lau":0,
    "qs:woe_local":1100182,
    "qs:woe_ver":"7.10.0",
    "qs_pg:aaroncc":"AU",
    "qs_pg:gn_country":"AU",
    "qs_pg:gn_fcode":"PPL",
    "qs_pg:gn_pop":6298,
    "qs_pg:name":"Kelso",
    "qs_pg:name_adm0":"Australia",
    "qs_pg:name_adm1":"New South Wales",
    "qs_pg:photos":50,
    "qs_pg:photos_1k":10,
    "qs_pg:photos_9k":1,
    "qs_pg:photos_9r":2,
    "qs_pg:photos_all":50,
    "qs_pg:photos_sr":2,
    "qs_pg:pop_sr":5,
    "qs_pg:qs_pg_placetype":"neighbourhood",
    "qs_pg:qs_pg_placetype_gp":"Suburb",
    "qs_pg:woe_adm0":23424748,
    "wd:wordcount":232,
    "wof:lang":[
        "eng"
    ],
    "wof:name":"Kelso",
    "wof:placetype":"neighbourhood",
    "wof:population":6298
},
  "geometry": {"coordinates":[149.60955799999999,-33.415801],"type":"Point"}
}