{
  "type": "Feature",
  "properties": {
    "gn:admin1_code":"2.0",
    "gn:admin2_code":"15270.0",
    "gn:asciiname":"Hillview",
    "gn:country_code":"AU",
    "gn:dem":431,
    "gn:feature_class":"P",
    "gn:feature_code":"PPL",
    "gn:name":"Hillview",
    "gn:population":0,
    "gn:timezone":"Australia/Sydney",
    "iso:country":"AU",
    "name:ceb_x_preferred":[
        "Hillview"
    ],
    "name:deu_x_preferred":[
        "Hillview"
    ],
    "name:eng_x_preferred":[
        "Hillview"
    ],
    "name:fra_x_preferred":[
        "Hillview"
    ],
    "name:ita_x_preferred":[
        "Hillview"
    ],
    "name:nld_x_preferred":[
        "Hillview"
    ],
    "name:pol_x_preferred":[
        "Hillview"
    ],
    "name:por_x_preferred":[
        "Hillview"
    ],
    "name:srp_x_preferred":[
        "\u0425\u0438\u043b\u0432\u0458\u0443"
    ],
    "name:swe_x_preferred":[
        "Hillview"
    ],
    "name:ukr_x_preferred":[
        "\u0413\u0456\u043b\u043b\u0432'\u044e"
    ],
    "name:vol_x_preferred":[
        "Hillview"
    ],
    "wof:name":"Hillview",
    "wof:placetype":"locality"
},
  "geometry": {"coordinates":[149.86591999999999,-32.36999],"type":"Point"}
}