{
  "type": "Feature",
  "properties": {
    "gn:admin1_code":"4.0",
    "gn:admin2_code":"32500.0",
    "gn:asciiname":"Blackfellow Yard",
    "gn:country_code":"AU",
    "gn:dem":112,
    "gn:feature_class":"P",
    "gn:feature_code":"PPL",
    "gn:name":"Blackfellow Yard",
    "gn:population":0,
    "gn:timezone":"Australia/Brisbane",
    "iso:country":"AU",
    "wof:name":"Blackfellow Yard",
    "wof:placetype":"locality"
},
  "geometry": {"coordinates":[142.78625,-13.72513],"type":"Point"}
}