{
  "type": "Feature",
  "properties": {
    "gn:admin1_code":"4.0",
    "gn:admin2_code":"35600.0",
    "gn:asciiname":"Angellala",
    "gn:country_code":"AU",
    "gn:dem":369,
    "gn:feature_class":"P",
    "gn:feature_code":"PPL",
    "gn:name":"Angellala",
    "gn:population":0,
    "gn:timezone":"Australia/Brisbane",
    "iso:country":"AU",
    "name:eng_x_preferred":[
        "Angellala"
    ],
    "wof:name":"Angellala",
    "wof:placetype":"locality"
},
  "geometry": {"coordinates":[146.88949,-26.41451],"type":"Point"}
}