{
  "type": "Feature",
  "properties": {
    "gn:admin1_code":"6.0",
    "gn:admin2_code":"63010.0",
    "gn:asciiname":"Glendevie",
    "gn:country_code":"AU",
    "gn:dem":87,
    "gn:feature_class":"P",
    "gn:feature_code":"PPL",
    "gn:name":"Glendevie",
    "gn:population":0,
    "gn:timezone":"Australia/Hobart",
    "iso:country":"AU",
    "name:eng_x_preferred":[
        "Glendevie"
    ],
    "wof:name":"Glendevie",
    "wof:placetype":"locality"
},
  "geometry": {"coordinates":[146.99525,-43.23915],"type":"Point"}
}