{
  "type": "Feature",
  "properties": {
    "gn:admin1_code":"2.0",
    "gn:admin2_code":"11350.0",
    "gn:asciiname":"Coorabell Creek",
    "gn:country_code":"AU",
    "gn:dem":136,
    "gn:feature_class":"P",
    "gn:feature_code":"PPL",
    "gn:name":"Coorabell Creek",
    "gn:population":0,
    "gn:timezone":"Australia/Sydney",
    "iso:country":"AU",
    "wof:name":"Coorabell Creek",
    "wof:placetype":"locality"
},
  "geometry": {"coordinates":[153.48333,-28.63333],"type":"Point"}
}