{
  "type": "Feature",
  "properties": {
    "iso:country":"AU",
    "name:eng_x_preferred":[
        "Gore Hill"
    ],
    "name:ron_x_preferred":[
        "Gore Hill"
    ],
    "qs:gn_adm0_cc":"AU",
    "qs:gn_fcode":"PPLX",
    "qs:gn_local":2147714,
    "qs:gn_namadm1":"02",
    "qs:gn_name":"Gore Hill",
    "qs:local_max":35533,
    "qs:local_sum":687549,
    "qs:localhoods":516,
    "qs:name":"Gore Hill",
    "qs:name_adm0":"Australia",
    "qs:name_adm1":"New South Wales",
    "qs:name_adm2":"Municipality of Lane Cove",
    "qs:name_local":"Sydney",
    "qs:photo_max":136,
    "qs:photo_sum":575,
    "qs:placetype":"Suburb",
    "qs:quad_count":15,
    "qs:woe_adm0":23424748,
    "qs:woe_adm1":2344700,
    "qs:woe_adm2":55864175,
    "qs:woe_lau":0,
    "qs:woe_local":1105779,
    "qs:woe_ver":"7.10.0",
    "wd:wordcount":352,
    "wof:lang":[
        "eng"
    ],
    "wof:name":"Gore Hill",
    "wof:placetype":"neighbourhood"
},
  "geometry": {"coordinates":[151.18789899999999,-33.820708],"type":"Point"}
}