{
  "type": "Feature",
  "properties": {
    "gn:admin1_code":"7",
    "gn:admin2_code":"26260",
    "gn:asciiname":"Victory Valley",
    "gn:cc2":"AU",
    "gn:country_code":"AU",
    "gn:dem":229,
    "gn:feature_class":"P",
    "gn:feature_code":"PPL",
    "gn:name":"Victory Valley",
    "gn:population":0,
    "gn:timezone":"Australia/Melbourne",
    "iso:country":"AU",
    "name:und_x_variant":[
        "Victoria Valley",
        "Victory Valley"
    ],
    "wof:name":"Victory Valley",
    "wof:placetype":"locality"
},
  "geometry": {"coordinates":[142.33333000000005,-37.55],"type":"Point"}
}