{
  "type": "Feature",
  "properties": {
    "gn:gn_country":"AU",
    "gn:gn_fcode":"PPL",
    "gn:gn_pop":224,
    "gn:population":224,
    "iso:country":"AU",
    "name:ceb_x_preferred":[
        "Booligal"
    ],
    "name:eng_x_preferred":[
        "Booligal"
    ],
    "name:fas_x_preferred":[
        "\u0628\u0648\u0644\u06cc\u06af\u0627\u0644"
    ],
    "name:fra_x_preferred":[
        "Booligal"
    ],
    "name:msa_x_preferred":[
        "Booligal"
    ],
    "name:nld_x_preferred":[
        "Booligal"
    ],
    "name:rus_x_preferred":[
        "\u0411\u0443\u043b\u0438\u0433\u0430\u043b"
    ],
    "name:swe_x_preferred":[
        "Booligal"
    ],
    "name:unk_x_variant":[
        "Village of Booligal"
    ],
    "qs_pg:aaroncc":"AU",
    "qs_pg:gn_country":"AU",
    "qs_pg:gn_fcode":"PPL",
    "qs_pg:gn_pop":224,
    "qs_pg:name":"Booligal",
    "qs_pg:name_adm0":"Australia",
    "qs_pg:name_adm1":"New South Wales",
    "qs_pg:photos_9k":1,
    "qs_pg:photos_9r":1,
    "qs_pg:photos_all":5,
    "qs_pg:photos_sr":0,
    "qs_pg:pop_sr":2,
    "qs_pg:qs_pg_placetype":"locality",
    "qs_pg:qs_pg_placetype_gp":"Town",
    "qs_pg:woe_adm0":23424748,
    "woe:adm0_id":23424748,
    "woe:name_adm0":"Australia",
    "woe:name_adm1":"New South Wales",
    "woe:placetype":"Town",
    "wof:name":"Booligal",
    "wof:placetype":"locality",
    "wof:population":95
},
  "geometry": {"coordinates":[144.88333,-33.86667],"type":"Point"}
}