{
  "type": "Feature",
  "properties": {
    "gn:gn_country":"AU",
    "gn:gn_fcode":"PPL",
    "gn:gn_pop":239,
    "gn:population":239,
    "iso:country":"AU",
    "name:ceb_x_preferred":[
        "Mount Russell"
    ],
    "name:deu_x_preferred":[
        "Mount Russell"
    ],
    "name:eng_x_preferred":[
        "Mount Russell"
    ],
    "name:heb_x_preferred":[
        "\u05d4\u05e8 \u05e8\u05d0\u05e1\u05dc"
    ],
    "name:nds_x_preferred":[
        "Mount Russell"
    ],
    "name:swe_x_preferred":[
        "Mount Russell"
    ],
    "qs_pg:aaroncc":"AU",
    "qs_pg:gn_country":"AU",
    "qs_pg:gn_fcode":"PPL",
    "qs_pg:gn_pop":239,
    "qs_pg:name":"Mount Russell",
    "qs_pg:name_adm0":"Australia",
    "qs_pg:name_adm1":"New South Wales",
    "qs_pg:photos_9r":0,
    "qs_pg:photos_sr":0,
    "qs_pg:pop_sr":2,
    "qs_pg:qs_pg_placetype":"locality",
    "qs_pg:qs_pg_placetype_gp":"Town",
    "qs_pg:woe_adm0":23424748,
    "woe:adm0_id":23424748,
    "woe:name_adm0":"Australia",
    "woe:name_adm1":"New South Wales",
    "woe:placetype":"Town",
    "wof:name":"Mount Russell",
    "wof:placetype":"locality",
    "wof:population":111
},
  "geometry": {"coordinates":[150.93333000000001,-29.68333],"type":"Point"}
}