{
  "type": "Feature",
  "properties": {
    "gn:admin1_code":"4.0",
    "gn:admin2_code":"31820.0",
    "gn:asciiname":"Huxley",
    "gn:country_code":"AU",
    "gn:dem":86,
    "gn:feature_class":"P",
    "gn:feature_code":"PPL",
    "gn:name":"Huxley",
    "gn:population":0,
    "gn:timezone":"Australia/Brisbane",
    "iso:country":"AU",
    "name:bel_x_preferred":[
        "\u0425\u0430\u043a\u0441\u043b\u0456"
    ],
    "name:cat_x_preferred":[
        "Huxley"
    ],
    "name:ceb_x_preferred":[
        "Huxley"
    ],
    "name:ces_x_preferred":[
        "Huxley"
    ],
    "name:deu_x_preferred":[
        "Huxley"
    ],
    "name:fas_x_preferred":[
        "\u0647\u0627\u06a9\u0633\u0644\u06cc"
    ],
    "name:fra_x_preferred":[
        "Huxley"
    ],
    "name:heb_x_preferred":[
        "\u05d4\u05d0\u05e7\u05e1\u05dc\u05d9"
    ],
    "name:hun_x_preferred":[
        "Huxley"
    ],
    "name:ita_x_preferred":[
        "Huxley"
    ],
    "name:jpn_x_preferred":[
        "\u30cf\u30af\u30b9\u30ea\u30fc"
    ],
    "name:kor_x_preferred":[
        "\ud5c9\uc2ac\ub9ac"
    ],
    "name:lat_x_preferred":[
        "Huxley"
    ],
    "name:lav_x_preferred":[
        "Hakslijs"
    ],
    "name:nds_x_preferred":[
        "Huxley"
    ],
    "name:nld_x_preferred":[
        "Huxley"
    ],
    "name:nor_x_preferred":[
        "Huxley"
    ],
    "name:pol_x_preferred":[
        "Huxley"
    ],
    "name:por_x_preferred":[
        "Huxley"
    ],
    "name:rus_x_preferred":[
        "\u0425\u0430\u043a\u0441\u043b\u0438"
    ],
    "name:slv_x_preferred":[
        "Huxley"
    ],
    "name:spa_x_preferred":[
        "Huxley"
    ],
    "name:srp_x_preferred":[
        "\u0425\u0430\u043a\u0441\u043b\u0438"
    ],
    "name:swe_x_preferred":[
        "Huxley"
    ],
    "name:ukr_x_preferred":[
        "\u0413\u0430\u043a\u0441\u043b\u0456"
    ],
    "name:zho_x_preferred":[
        "\u8d6b\u80e5\u9ece"
    ],
    "wof:name":"Huxley",
    "wof:placetype":"locality"
},
  "geometry": {"coordinates":[152.26667,-25.21667],"type":"Point"}
}