{
  "type": "Feature",
  "properties": {
    "gn:admin1_code":"4.0",
    "gn:admin2_code":"35760.0",
    "gn:asciiname":"Dundarrah",
    "gn:country_code":"AU",
    "gn:dem":220,
    "gn:feature_class":"P",
    "gn:feature_code":"PPL",
    "gn:name":"Dundarrah",
    "gn:population":0,
    "gn:timezone":"Australia/Brisbane",
    "iso:country":"AU",
    "wof:name":"Dundarrah",
    "wof:placetype":"locality"
},
  "geometry": {"coordinates":[151.88333,-25.65],"type":"Point"}
}