{
  "type": "Feature",
  "properties": {
    "gn:admin1_code":"2.0",
    "gn:admin2_code":"13700.0",
    "gn:asciiname":"Nurung",
    "gn:country_code":"AU",
    "gn:dem":473,
    "gn:feature_class":"P",
    "gn:feature_code":"PPL",
    "gn:name":"Nurung",
    "gn:population":0,
    "gn:timezone":"Australia/Sydney",
    "iso:country":"AU",
    "name:eng_x_preferred":[
        "Nurung"
    ],
    "wof:name":"Nurung",
    "wof:placetype":"locality"
},
  "geometry": {"coordinates":[148.54338999999999,-34.46356],"type":"Point"}
}