{
  "type": "Feature",
  "properties": {
    "gn:admin1_code":"7.0",
    "gn:admin2_code":"26700.0",
    "gn:asciiname":"Docker",
    "gn:country_code":"AU",
    "gn:dem":159,
    "gn:feature_class":"P",
    "gn:feature_code":"PPL",
    "gn:name":"Docker",
    "gn:population":0,
    "gn:timezone":"Australia/Melbourne",
    "iso:country":"AU",
    "wof:name":"Docker",
    "wof:placetype":"locality"
},
  "geometry": {"coordinates":[146.38333,-36.51667],"type":"Point"}
}