{
  "type": "Feature",
  "properties": {
    "gn:admin1_code":"7.0",
    "gn:admin2_code":"24900.0",
    "gn:asciiname":"Drumanure",
    "gn:country_code":"AU",
    "gn:dem":111,
    "gn:feature_class":"P",
    "gn:feature_code":"PPL",
    "gn:name":"Drumanure",
    "gn:population":0,
    "gn:timezone":"Australia/Melbourne",
    "iso:country":"AU",
    "wof:name":"Drumanure",
    "wof:placetype":"locality"
},
  "geometry": {"coordinates":[145.50573,-36.13125],"type":"Point"}
}