{
  "type": "Feature",
  "properties": {
    "iso:country":"AU",
    "name:ceb_x_preferred":[
        "Golden Grove"
    ],
    "name:deu_x_preferred":[
        "Golden Grove"
    ],
    "name:eng_x_preferred":[
        "Golden Grove"
    ],
    "name:ita_x_preferred":[
        "Golden Grove"
    ],
    "name:mlg_x_preferred":[
        "Golden Grove"
    ],
    "name:nld_x_preferred":[
        "Golden Grove"
    ],
    "name:spa_x_preferred":[
        "Golden Grove"
    ],
    "name:swe_x_preferred":[
        "Golden Grove"
    ],
    "name:unk_x_variant":[
        "Golden Grove"
    ],
    "qs:gn_adm0_cc":"AU",
    "qs:gn_local":2147714,
    "qs:local_max":35533,
    "qs:local_sum":687549,
    "qs:localhoods":516,
    "qs:name":"Golden Grove",
    "qs:name_adm0":"Australia",
    "qs:name_adm1":"New South Wales",
    "qs:name_adm2":"Sydney",
    "qs:name_local":"Sydney",
    "qs:photo_max":6747,
    "qs:photo_sum":8364,
    "qs:placetype":"Suburb",
    "qs:quad_count":38,
    "qs:woe_adm0":23424748,
    "qs:woe_adm1":2344700,
    "qs:woe_adm2":55864169,
    "qs:woe_lau":0,
    "qs:woe_local":1105779,
    "qs:woe_ver":"7.10.0",
    "wof:lang":[
        "eng"
    ],
    "wof:name":"Golden Grove",
    "wof:placetype":"neighbourhood"
},
  "geometry": {"coordinates":[151.189063,-33.888604],"type":"Point"}
}