{
  "type": "Feature",
  "properties": {
    "gn:admin1_code":"8",
    "gn:admin2_code":"54900",
    "gn:asciiname":"North Lake Grace",
    "gn:country_code":"AU",
    "gn:dem":304,
    "gn:feature_class":"P",
    "gn:feature_code":"PPL",
    "gn:name":"North Lake Grace",
    "gn:population":0,
    "gn:timezone":"Australia/Perth",
    "iso:country":"AU",
    "wof:name":"North Lake Grace",
    "wof:placetype":"locality"
},
  "geometry": {"coordinates":[118.46666999999999,-32.95],"type":"Point"}
}