{
  "type": "Feature",
  "properties": {
    "gn:country":"AU",
    "gn:fcode":"PPL",
    "gn:population":559,
    "iso:country":"AU",
    "name:ceb_x_preferred":[
        "Roadvale"
    ],
    "name:eng_x_preferred":[
        "Roadvale"
    ],
    "name:fra_x_preferred":[
        "Roadvale"
    ],
    "name:nld_x_preferred":[
        "Roadvale"
    ],
    "name:swe_x_preferred":[
        "Roadvale"
    ],
    "qs_pg:aaroncc":"AU",
    "qs_pg:gn_country":"AU",
    "qs_pg:gn_fcode":"PPL",
    "qs_pg:gn_pop":559,
    "qs_pg:name":"Roadvale",
    "qs_pg:photos_9r":0,
    "qs_pg:photos_sr":0,
    "qs_pg:pop_sr":2,
    "qs_pg:qs_pg_placetype":"locality",
    "wof:name":"Roadvale",
    "wof:placetype":"locality",
    "wof:population":286
},
  "geometry": {"coordinates":[152.68333000000001,-27.91667],"type":"Point"}
}