{
  "type": "Feature",
  "properties": {
    "gn:admin1_code":"4.0",
    "gn:admin2_code":"30410.0",
    "gn:asciiname":"Pine Hill",
    "gn:country_code":"AU",
    "gn:dem":364,
    "gn:feature_class":"P",
    "gn:feature_code":"PPL",
    "gn:name":"Pine Hill",
    "gn:population":0,
    "gn:timezone":"Australia/Brisbane",
    "iso:country":"AU",
    "name:ceb_x_preferred":[
        "Pine Hill"
    ],
    "name:deu_x_preferred":[
        "Pine Hill"
    ],
    "name:ita_x_preferred":[
        "Pine Hill"
    ],
    "name:nds_x_preferred":[
        "Pine Hill"
    ],
    "name:nld_x_preferred":[
        "Pine Hill"
    ],
    "name:pol_x_preferred":[
        "Pine Hill"
    ],
    "name:por_x_preferred":[
        "Pine Hill"
    ],
    "name:srp_x_preferred":[
        "\u041f\u0430\u0458\u043d \u0425\u0438\u043b"
    ],
    "name:swe_x_preferred":[
        "Pine Hill"
    ],
    "name:vol_x_preferred":[
        "Pine Hill"
    ],
    "wof:name":"Pine Hill",
    "wof:placetype":"locality"
},
  "geometry": {"coordinates":[146.96666999999999,-23.65],"type":"Point"}
}