{
  "type": "Feature",
  "properties": {
    "gn:admin1_code":"4.0",
    "gn:admin2_code":"37340.0",
    "gn:asciiname":"Hayman Island",
    "gn:country_code":"AU",
    "gn:dem":160,
    "gn:feature_class":"P",
    "gn:feature_code":"PPL",
    "gn:name":"Hayman Island",
    "gn:population":0,
    "gn:timezone":"Australia/Lindeman",
    "iso:country":"AU",
    "name:ceb_x_preferred":[
        "Hayman Island"
    ],
    "name:deu_x_preferred":[
        "Hayman Island"
    ],
    "name:ita_x_preferred":[
        "Hayman Island"
    ],
    "name:nld_x_preferred":[
        "Haymaneiland"
    ],
    "name:swe_x_preferred":[
        "Hayman Island"
    ],
    "name:zho_x_preferred":[
        "\u6d77\u66fc\u5cf6"
    ],
    "wof:name":"Hayman Island",
    "wof:placetype":"locality"
},
  "geometry": {"coordinates":[148.88487000000001,-20.05105],"type":"Point"}
}