{
  "type": "Feature",
  "properties": {
    "gn:admin1_code":"2.0",
    "gn:admin2_code":"17640.0",
    "gn:asciiname":"Gullen",
    "gn:country_code":"AU",
    "gn:dem":891,
    "gn:feature_class":"P",
    "gn:feature_code":"PPL",
    "gn:name":"Gullen",
    "gn:population":0,
    "gn:timezone":"Australia/Sydney",
    "iso:country":"AU",
    "wof:name":"Gullen",
    "wof:placetype":"locality"
},
  "geometry": {"coordinates":[149.36667,-34.56667],"type":"Point"}
}