{
  "type": "Feature",
  "properties": {
    "gn:gn_country":"AU",
    "iso:country":"AU",
    "name:eng_x_preferred":[
        "American Beach"
    ],
    "name:nld_x_preferred":[
        "American Beach"
    ],
    "qs_pg:aaroncc":"AU",
    "qs_pg:gn_country":"AU",
    "qs_pg:name":"American Beach",
    "qs_pg:name_adm0":"Australia",
    "qs_pg:name_adm1":"South Australia",
    "qs_pg:photos":22,
    "qs_pg:photos_1k":4,
    "qs_pg:photos_9k":1,
    "qs_pg:photos_9r":1,
    "qs_pg:photos_all":22,
    "qs_pg:photos_sr":1,
    "qs_pg:pop_sr":0,
    "qs_pg:qs_pg_placetype":"locality",
    "qs_pg:qs_pg_placetype_gp":"Town",
    "qs_pg:woe_adm0":23424748,
    "woe:adm0_id":23424748,
    "woe:name_adm0":"Australia",
    "woe:name_adm1":"South Australia",
    "woe:placetype":"Town",
    "wof:name":"American Beach",
    "wof:placetype":"locality"
},
  "geometry": {"coordinates":[137.890691,-35.759607],"type":"Point"}
}