{
  "type": "Feature",
  "properties": {
    "gn:admin1_code":"4.0",
    "gn:admin2_code":"32500.0",
    "gn:asciiname":"Captain Billy Landing",
    "gn:country_code":"AU",
    "gn:dem":36,
    "gn:feature_class":"P",
    "gn:feature_code":"PPL",
    "gn:name":"Captain Billy Landing",
    "gn:population":0,
    "gn:timezone":"Australia/Brisbane",
    "iso:country":"AU",
    "name:eng_x_preferred":[
        "Captain Billy Landing"
    ],
    "wof:name":"Captain Billy Landing",
    "wof:placetype":"locality"
},
  "geometry": {"coordinates":[142.85445000000001,-11.63057],"type":"Point"}
}