{
  "type": "Feature",
  "properties": {
    "gn:admin1_code":"2.0",
    "gn:admin2_code":"17900.0",
    "gn:asciiname":"Old Burren",
    "gn:country_code":"AU",
    "gn:dem":156,
    "gn:feature_class":"P",
    "gn:feature_code":"PPL",
    "gn:name":"Old Burren",
    "gn:population":0,
    "gn:timezone":"Australia/Sydney",
    "iso:country":"AU",
    "name:eng_x_preferred":[
        "Old Burren"
    ],
    "wof:name":"Old Burren",
    "wof:placetype":"locality"
},
  "geometry": {"coordinates":[148.90451000000004,-29.9536],"type":"Point"}
}