{
  "type": "Feature",
  "properties": {
    "gn:admin1_code":"2",
    "gn:admin2_code":"13350",
    "gn:asciiname":"Stewarts River",
    "gn:country_code":"AU",
    "gn:dem":30,
    "gn:feature_class":"P",
    "gn:feature_code":"PPL",
    "gn:name":"Stewarts River",
    "gn:population":0,
    "gn:timezone":"Australia/Sydney",
    "iso:country":"AU",
    "wof:name":"Stewarts River",
    "wof:placetype":"locality"
},
  "geometry": {"coordinates":[152.65000000000001,-31.73333],"type":"Point"}
}