{
  "type": "Feature",
  "properties": {
    "gn:admin1_code":"3.0",
    "gn:admin2_code":"70620.0",
    "gn:asciiname":"Tariton Downs",
    "gn:country_code":"AU",
    "gn:dem":280,
    "gn:feature_class":"P",
    "gn:feature_code":"PPL",
    "gn:name":"Tariton Downs",
    "gn:population":0,
    "gn:timezone":"Australia/Darwin",
    "iso:country":"AU",
    "name:eng_x_preferred":[
        "Tariton Downs"
    ],
    "wof:name":"Tariton Downs",
    "wof:placetype":"locality"
},
  "geometry": {"coordinates":[136.79781,-22.65819],"type":"Point"}
}