{
  "type": "Feature",
  "properties": {
    "gn:admin1_code":"5.0",
    "gn:admin2_code":"44210.0",
    "gn:asciiname":"Moorundie",
    "gn:country_code":"AU",
    "gn:dem":39,
    "gn:feature_class":"P",
    "gn:feature_code":"PPL",
    "gn:name":"Moorundie",
    "gn:population":0,
    "gn:timezone":"Australia/Adelaide",
    "iso:country":"AU",
    "name:eng_x_preferred":[
        "Moorundie"
    ],
    "wof:name":"Moorundie",
    "wof:placetype":"locality"
},
  "geometry": {"coordinates":[139.59058000000002,-34.40051],"type":"Point"}
}