{
  "type": "Feature",
  "properties": {
    "gn:admin1_code":"4.0",
    "gn:admin2_code":"37310.0",
    "gn:asciiname":"Inverai",
    "gn:country_code":"AU",
    "gn:dem":327,
    "gn:feature_class":"P",
    "gn:feature_code":"PPL",
    "gn:name":"Inverai",
    "gn:population":0,
    "gn:timezone":"Australia/Brisbane",
    "iso:country":"AU",
    "wof:name":"Inverai",
    "wof:placetype":"locality"
},
  "geometry": {"coordinates":[150.94999999999999,-26.78333],"type":"Point"}
}