{
  "type": "Feature",
  "properties": {
    "gn:admin1_code":"4.0",
    "gn:admin2_code":"32260.0",
    "gn:asciiname":"Berner Creek",
    "gn:country_code":"AU",
    "gn:dem":110,
    "gn:feature_class":"P",
    "gn:feature_code":"PPL",
    "gn:name":"Berner Creek",
    "gn:population":0,
    "gn:timezone":"Australia/Brisbane",
    "iso:country":"AU",
    "wof:name":"Berner Creek",
    "wof:placetype":"locality"
},
  "geometry": {"coordinates":[145.90000000000001,-17.56667],"type":"Point"}
}