{
  "type": "Feature",
  "properties": {
    "gn:admin1_code":"7",
    "gn:admin2_code":"21370",
    "gn:asciiname":"Tongala East",
    "gn:country_code":"AU",
    "gn:dem":103,
    "gn:feature_class":"P",
    "gn:feature_code":"PPL",
    "gn:name":"Tongala East",
    "gn:population":0,
    "gn:timezone":"Australia/Melbourne",
    "iso:country":"AU",
    "wof:name":"Tongala East",
    "wof:placetype":"locality"
},
  "geometry": {"coordinates":[144.98333,-36.25],"type":"Point"}
}