{
  "type": "Feature",
  "properties": {
    "gn:admin1_code":"2.0",
    "gn:admin2_code":"15300.0",
    "gn:asciiname":"Marambir",
    "gn:country_code":"AU",
    "gn:dem":241,
    "gn:feature_class":"P",
    "gn:feature_code":"PPL",
    "gn:name":"Marambir",
    "gn:population":0,
    "gn:timezone":"Australia/Sydney",
    "iso:country":"AU",
    "name:eng_x_preferred":[
        "Marambir"
    ],
    "wof:name":"Marambir",
    "wof:placetype":"locality"
},
  "geometry": {"coordinates":[150.06604999999999,-29.52708],"type":"Point"}
}