{
  "type": "Feature",
  "properties": {
    "gn:admin1_code":"4.0",
    "gn:admin2_code":"32270.0",
    "gn:asciiname":"Bonnie Doon",
    "gn:country_code":"AU",
    "gn:dem":197,
    "gn:feature_class":"P",
    "gn:feature_code":"PPL",
    "gn:name":"Bonnie Doon",
    "gn:population":0,
    "gn:timezone":"Australia/Brisbane",
    "iso:country":"AU",
    "name:ceb_x_preferred":[
        "Bonnie Doon"
    ],
    "name:eng_x_preferred":[
        "Bonnie Doon"
    ],
    "name:fra_x_preferred":[
        "Bonnie Doon"
    ],
    "name:swe_x_preferred":[
        "Bonnie Doon"
    ],
    "wof:name":"Bonnie Doon",
    "wof:placetype":"locality"
},
  "geometry": {"coordinates":[148.33322999999999,-23.70904],"type":"Point"}
}