{
  "type": "Feature",
  "properties": {
    "gn:admin1_code":"4.0",
    "gn:admin2_code":"33200.0",
    "gn:asciiname":"Watten",
    "gn:country_code":"AU",
    "gn:dem":286,
    "gn:feature_class":"P",
    "gn:feature_code":"PPL",
    "gn:name":"Watten",
    "gn:population":0,
    "gn:timezone":"Australia/Brisbane",
    "iso:country":"AU",
    "name:deu_x_preferred":[
        "Watten"
    ],
    "name:eng_x_preferred":[
        "Watten"
    ],
    "name:ita_x_preferred":[
        "Watten"
    ],
    "name:nld_x_preferred":[
        "Watten"
    ],
    "name:scn_x_preferred":[
        "Watten"
    ],
    "wof:name":"Watten",
    "wof:placetype":"locality"
},
  "geometry": {"coordinates":[144.05443,-21.01284],"type":"Point"}
}