{
  "type": "Feature",
  "properties": {
    "gn:admin1_code":"4.0",
    "gn:admin2_code":"32250.0",
    "gn:asciiname":"Daroo Pocket",
    "gn:country_code":"AU",
    "gn:dem":11,
    "gn:feature_class":"P",
    "gn:feature_code":"PPL",
    "gn:name":"Daroo Pocket",
    "gn:population":0,
    "gn:timezone":"Australia/Brisbane",
    "iso:country":"AU",
    "name:eng_x_preferred":[
        "Daroo Pocket"
    ],
    "wof:name":"Daroo Pocket",
    "wof:placetype":"locality"
},
  "geometry": {"coordinates":[140.83593999999999,-17.81795],"type":"Point"}
}