{
  "type": "Feature",
  "properties": {
    "gn:admin1_code":"4.0",
    "gn:admin2_code":"32310.0",
    "gn:asciiname":"Nosnillor",
    "gn:country_code":"AU",
    "gn:dem":217,
    "gn:feature_class":"P",
    "gn:feature_code":"PPL",
    "gn:name":"Nosnillor",
    "gn:population":0,
    "gn:timezone":"Australia/Brisbane",
    "iso:country":"AU",
    "name:eng_x_preferred":[
        "Nosnillor"
    ],
    "wof:name":"Nosnillor",
    "wof:placetype":"locality"
},
  "geometry": {"coordinates":[146.33552,-20.94862],"type":"Point"}
}