{
  "type": "Feature",
  "properties": {
    "gn:admin1_code":"06",
    "gn:admin2_code":"64210.0",
    "gn:asciiname":"Glenore",
    "gn:country_code":"AU",
    "gn:dem":185,
    "gn:feature_class":"P",
    "gn:feature_code":"PPL",
    "gn:name":"Glenore",
    "gn:population":0,
    "gn:timezone":"Australia/Hobart",
    "iso:country":"AU",
    "name:eng_x_preferred":[
        "Glenore"
    ],
    "wof:name":"Glenore",
    "wof:placetype":"locality"
},
  "geometry": {"coordinates":[146.93459999999999,-41.60458],"type":"Point"}
}