{
  "type": "Feature",
  "properties": {
    "gn:admin1_code":"8",
    "gn:admin2_code":"51610",
    "gn:asciiname":"Whelarra",
    "gn:country_code":"AU",
    "gn:dem":271,
    "gn:feature_class":"P",
    "gn:feature_code":"PPL",
    "gn:name":"Whelarra",
    "gn:population":0,
    "gn:timezone":"Australia/Perth",
    "iso:country":"AU",
    "wof:name":"Whelarra",
    "wof:placetype":"locality"
},
  "geometry": {"coordinates":[114.95,-28.33333],"type":"Point"}
}