{
  "type": "Feature",
  "properties": {
    "iso:country":"AU",
    "oa:elevation_ft":"1492",
    "oa:type":"medium_airport",
    "woe:hierarchy":{
        "country_id":23424748,
        "county_id":56072979,
        "planet_id":1,
        "state_id":2344702
    },
    "wof:name":"Kingaroy Aerodrome",
    "wof:placetype":"campus"
},
  "geometry": {"coordinates":[151.84200000000001,-26.58],"type":"Point"}
}