{
  "type": "Feature",
  "properties": {
    "gn:admin1_code":"08",
    "gn:admin2_code":"51260.0",
    "gn:asciiname":"Anniebrook",
    "gn:country_code":"AU",
    "gn:dem":2,
    "gn:feature_class":"P",
    "gn:feature_code":"PPL",
    "gn:name":"Anniebrook",
    "gn:population":0,
    "gn:timezone":"Australia/Perth",
    "iso:country":"AU",
    "wof:name":"Anniebrook",
    "wof:placetype":"locality"
},
  "geometry": {"coordinates":[115.17255,-33.65914],"type":"Point"}
}