{
  "type": "Feature",
  "properties": {
    "iso:country":"AU",
    "name:ceb_x_preferred":[
        "Eggs and Bacon Bay"
    ],
    "name:swe_x_preferred":[
        "Eggs and Bacon Bay"
    ],
    "qs_pg:aaroncc":"AU",
    "qs_pg:name":"Eggs and Bacon Bay",
    "qs_pg:name_adm0":"Australia",
    "qs_pg:name_adm1":"Tasmania",
    "qs_pg:photos":17,
    "qs_pg:photos_1k":3,
    "qs_pg:photos_9k":1,
    "qs_pg:photos_9r":1,
    "qs_pg:photos_all":17,
    "qs_pg:photos_sr":1,
    "qs_pg:pop_sr":0,
    "qs_pg:qs_pg_placetype":"locality",
    "qs_pg:qs_pg_placetype_gp":"Town",
    "qs_pg:woe_adm0":23424748,
    "woe:adm0_id":23424748,
    "woe:name_adm0":"Australia",
    "woe:name_adm1":"Tasmania",
    "woe:placetype":"Town",
    "wof:name":"Eggs and Bacon Bay",
    "wof:placetype":"locality"
},
  "geometry": {"coordinates":[147.102127,-43.245577],"type":"Point"}
}