{
  "type": "Feature",
  "properties": {
    "gn:country":"AU",
    "gn:fcode":"PPL",
    "gn:population":297,
    "iso:country":"AU",
    "name:ceb_x_preferred":[
        "Nyabing"
    ],
    "name:eng_x_preferred":[
        "Nyabing"
    ],
    "name:ita_x_preferred":[
        "Nyabing"
    ],
    "name:jpn_x_preferred":[
        "\u30ca\u30a4\u30a2\u30d3\u30f3"
    ],
    "name:nld_x_preferred":[
        "Nyabing"
    ],
    "name:sgs_x_preferred":[
        "Nyabing"
    ],
    "name:swe_x_preferred":[
        "Nyabing"
    ],
    "qs_pg:aaroncc":"AU",
    "qs_pg:gn_country":"AU",
    "qs_pg:gn_fcode":"PPL",
    "qs_pg:gn_pop":297,
    "qs_pg:name":"Nyabing",
    "qs_pg:photos_9r":0,
    "qs_pg:photos_sr":0,
    "qs_pg:pop_sr":2,
    "qs_pg:qs_pg_placetype":"locality",
    "wof:name":"Nyabing",
    "wof:placetype":"locality",
    "wof:population":296
},
  "geometry": {"coordinates":[118.15000000000001,-33.53333],"type":"Point"}
}