{
  "type": "Feature",
  "properties": {
    "gn:admin1_code":"06",
    "gn:admin2_code":"62410.0",
    "gn:asciiname":"Apslawn",
    "gn:country_code":"AU",
    "gn:dem":51,
    "gn:feature_class":"P",
    "gn:feature_code":"PPL",
    "gn:name":"Apslawn",
    "gn:population":0,
    "gn:timezone":"Australia/Hobart",
    "iso:country":"AU",
    "name:eng_x_preferred":[
        "Apslawn"
    ],
    "wof:name":"Apslawn",
    "wof:placetype":"locality"
},
  "geometry": {"coordinates":[148.18648999999999,-41.97376],"type":"Point"}
}