{
  "type": "Feature",
  "properties": {
    "gn:admin1_code":"4.0",
    "gn:admin2_code":"34860.0",
    "gn:asciiname":"Dargal",
    "gn:country_code":"AU",
    "gn:dem":334,
    "gn:feature_class":"P",
    "gn:feature_code":"PPL",
    "gn:name":"Dargal",
    "gn:population":0,
    "gn:timezone":"Australia/Brisbane",
    "iso:country":"AU",
    "name:eng_x_preferred":[
        "Dargal"
    ],
    "wof:name":"Dargal",
    "wof:placetype":"locality"
},
  "geometry": {"coordinates":[148.57592,-26.48044],"type":"Point"}
}