{
  "type": "Feature",
  "properties": {
    "iso:country":"AU",
    "name:ceb_x_preferred":[
        "Shelly Beach"
    ],
    "name:deu_x_preferred":[
        "Shelly Beach"
    ],
    "name:swe_x_preferred":[
        "Shelly Beach"
    ],
    "qs_pg:aaroncc":"AU",
    "qs_pg:name":"Shelly Beach",
    "qs_pg:name_adm0":"Australia",
    "qs_pg:name_adm1":"Tasmania",
    "qs_pg:photos":8,
    "qs_pg:photos_1k":2,
    "qs_pg:photos_9k":1,
    "qs_pg:photos_9r":1,
    "qs_pg:photos_all":8,
    "qs_pg:photos_sr":1,
    "qs_pg:pop_sr":0,
    "qs_pg:qs_pg_placetype":"locality",
    "qs_pg:qs_pg_placetype_gp":"Town",
    "qs_pg:woe_adm0":23424748,
    "woe:adm0_id":23424748,
    "woe:name_adm0":"Australia",
    "woe:name_adm1":"Tasmania",
    "woe:placetype":"Town",
    "wof:name":"Shelly Beach",
    "wof:placetype":"locality"
},
  "geometry": {"coordinates":[147.87762499999999,-42.5735935],"type":"Point"}
}