{
  "type": "Feature",
  "properties": {
    "gn:admin1_code":"8.0",
    "gn:admin2_code":"53220.0",
    "gn:asciiname":"Redmont",
    "gn:country_code":"AU",
    "gn:dem":386,
    "gn:feature_class":"P",
    "gn:feature_code":"PPL",
    "gn:name":"Redmont",
    "gn:population":0,
    "gn:timezone":"Australia/Perth",
    "iso:country":"AU",
    "wof:name":"Redmont",
    "wof:placetype":"locality"
},
  "geometry": {"coordinates":[119.01617,-21.99359],"type":"Point"}
}