{
  "type": "Feature",
  "properties": {
    "gn:admin1_code":"5",
    "gn:admin2_code":"44210",
    "gn:asciiname":"Netherleigh",
    "gn:country_code":"AU",
    "gn:dem":56,
    "gn:feature_class":"P",
    "gn:feature_code":"PPL",
    "gn:name":"Netherleigh",
    "gn:population":0,
    "gn:timezone":"Australia/Adelaide",
    "iso:country":"AU",
    "wof:name":"Netherleigh",
    "wof:placetype":"locality"
},
  "geometry": {"coordinates":[139.75,-34.58333],"type":"Point"}
}