{
  "type": "Feature",
  "properties": {
    "gn:admin1_code":"2.0",
    "gn:admin2_code":"14600.0",
    "gn:asciiname":"Brotherony",
    "gn:country_code":"AU",
    "gn:dem":168,
    "gn:feature_class":"P",
    "gn:feature_code":"PPL",
    "gn:name":"Brotherony",
    "gn:population":0,
    "gn:timezone":"Australia/Sydney",
    "iso:country":"AU",
    "name:eng_x_preferred":[
        "Brotherony"
    ],
    "wof:name":"Brotherony",
    "wof:placetype":"locality"
},
  "geometry": {"coordinates":[146.65413000000001,-33.10317],"type":"Point"}
}