{
  "type": "Feature",
  "properties": {
    "gn:admin1_code":"8",
    "gn:admin2_code":"57210",
    "gn:asciiname":"Mortigallup",
    "gn:country_code":"AU",
    "gn:dem":270,
    "gn:feature_class":"P",
    "gn:feature_code":"PPL",
    "gn:name":"Mortigallup",
    "gn:population":0,
    "gn:timezone":"Australia/Perth",
    "iso:country":"AU",
    "wof:name":"Mortigallup",
    "wof:placetype":"locality"
},
  "geometry": {"coordinates":[117.51667,-34.46667],"type":"Point"}
}