{
  "type": "Feature",
  "properties": {
    "gn:admin1_code":"2",
    "gn:admin2_code":"16200",
    "gn:asciiname":"Warge Rock",
    "gn:country_code":"AU",
    "gn:dem":229,
    "gn:feature_class":"P",
    "gn:feature_code":"PPL",
    "gn:name":"Warge Rock",
    "gn:population":0,
    "gn:timezone":"Australia/Sydney",
    "iso:country":"AU",
    "wof:name":"Warge Rock",
    "wof:placetype":"locality"
},
  "geometry": {"coordinates":[147.80000000000001,-32.55],"type":"Point"}
}