{
  "type": "Feature",
  "properties": {
    "gn:admin1_code":"8",
    "gn:admin2_code":"50080",
    "gn:asciiname":"Marbellup",
    "gn:cc2":"AU",
    "gn:country_code":"AU",
    "gn:dem":19,
    "gn:feature_class":"P",
    "gn:feature_code":"PPL",
    "gn:name":"Marbellup",
    "gn:population":0,
    "gn:timezone":"Australia/Perth",
    "iso:country":"AU",
    "name:und_x_variant":[
        "Marbelup",
        "Marbellup"
    ],
    "wof:name":"Marbellup",
    "wof:placetype":"locality"
},
  "geometry": {"coordinates":[117.73333,-34.9675],"type":"Point"}
}