{
  "type": "Feature",
  "properties": {
    "gn:admin1_code":"2.0",
    "gn:admin2_code":"18150.0",
    "gn:asciiname":"Klondyke",
    "gn:country_code":"AU",
    "gn:dem":445,
    "gn:feature_class":"P",
    "gn:feature_code":"PPL",
    "gn:name":"Klondyke",
    "gn:population":0,
    "gn:timezone":"Australia/Sydney",
    "iso:country":"AU",
    "name:ceb_x_preferred":[
        "Klondyke"
    ],
    "name:eng_x_preferred":[
        "Klondyke"
    ],
    "wof:name":"Klondyke",
    "wof:placetype":"locality"
},
  "geometry": {"coordinates":[149.16281000000001,-32.26978],"type":"Point"}
}