{
  "type": "Feature",
  "properties": {
    "gn:admin1_code":"8",
    "gn:admin2_code":"59660",
    "gn:asciiname":"Baladjie",
    "gn:country_code":"AU",
    "gn:dem":348,
    "gn:feature_class":"P",
    "gn:feature_code":"PPL",
    "gn:name":"Baladjie",
    "gn:population":0,
    "gn:timezone":"Australia/Perth",
    "iso:country":"AU",
    "wof:name":"Baladjie",
    "wof:placetype":"locality"
},
  "geometry": {"coordinates":[118.9387,-30.98429],"type":"Point"}
}