{
  "type": "Feature",
  "properties": {
    "gn:admin1_code":"4.0",
    "gn:admin2_code":"32500.0",
    "gn:asciiname":"Melon Yard",
    "gn:country_code":"AU",
    "gn:dem":59,
    "gn:feature_class":"P",
    "gn:feature_code":"PPL",
    "gn:name":"Melon Yard",
    "gn:population":0,
    "gn:timezone":"Australia/Brisbane",
    "iso:country":"AU",
    "wof:name":"Melon Yard",
    "wof:placetype":"locality"
},
  "geometry": {"coordinates":[142.29546999999999,-14.69275],"type":"Point"}
}