{
  "type": "Feature",
  "properties": {
    "gn:admin1_code":"2.0",
    "gn:admin2_code":"15270.0",
    "gn:asciiname":"Meruthera",
    "gn:country_code":"AU",
    "gn:dem":416,
    "gn:feature_class":"P",
    "gn:feature_code":"PPL",
    "gn:name":"Meruthera",
    "gn:population":0,
    "gn:timezone":"Australia/Sydney",
    "iso:country":"AU",
    "wof:name":"Meruthera",
    "wof:placetype":"locality"
},
  "geometry": {"coordinates":[149.58333000000005,-32.11667],"type":"Point"}
}