{
  "type": "Feature",
  "properties": {
    "gn:admin1_code":"4.0",
    "gn:admin2_code":"35600.0",
    "gn:asciiname":"Cooladdi",
    "gn:country_code":"AU",
    "gn:dem":269,
    "gn:feature_class":"P",
    "gn:feature_code":"PPL",
    "gn:name":"Cooladdi",
    "gn:population":0,
    "gn:timezone":"Australia/Brisbane",
    "iso:country":"AU",
    "name:eng_x_preferred":[
        "Cooladdi"
    ],
    "wof:name":"Cooladdi",
    "wof:placetype":"locality"
},
  "geometry": {"coordinates":[145.46444,-26.64264],"type":"Point"}
}