{
  "type": "Feature",
  "properties": {
    "gn:admin1_code":"2.0",
    "gn:admin2_code":"11400.0",
    "gn:asciiname":"Burdett",
    "gn:country_code":"AU",
    "gn:dem":409,
    "gn:feature_class":"P",
    "gn:feature_code":"PPL",
    "gn:name":"Burdett",
    "gn:population":0,
    "gn:timezone":"Australia/Sydney",
    "iso:country":"AU",
    "name:cat_x_preferred":[
        "Burdett"
    ],
    "name:ceb_x_preferred":[
        "Burdett"
    ],
    "name:deu_x_preferred":[
        "Burdett"
    ],
    "name:fra_x_preferred":[
        "Burdett"
    ],
    "name:ita_x_preferred":[
        "Burdett"
    ],
    "name:nld_x_preferred":[
        "Burdett"
    ],
    "name:pol_x_preferred":[
        "Burdett"
    ],
    "name:por_x_preferred":[
        "Burdett"
    ],
    "name:srp_x_preferred":[
        "\u0411\u0435\u0440\u0434\u0435\u0442"
    ],
    "name:ukr_x_preferred":[
        "\u0411\u0435\u0440\u0434\u0435\u0442\u0442"
    ],
    "name:vol_x_preferred":[
        "Burdett"
    ],
    "name:zho_x_preferred":[
        "\u4f2f\u5fb7\u7279"
    ],
    "wof:name":"Burdett",
    "wof:placetype":"locality"
},
  "geometry": {"coordinates":[148.59999999999999,-33.41667],"type":"Point"}
}