{
  "type": "Feature",
  "properties": {
    "gn:admin1_code":"3.0",
    "gn:admin2_code":"70620.0",
    "gn:asciiname":"Manners Creek",
    "gn:country_code":"AU",
    "gn:dem":184,
    "gn:feature_class":"P",
    "gn:feature_code":"PPL",
    "gn:name":"Manners Creek",
    "gn:population":0,
    "gn:timezone":"Australia/Darwin",
    "iso:country":"AU",
    "name:eng_x_preferred":[
        "Manners Creek"
    ],
    "wof:name":"Manners Creek",
    "wof:placetype":"locality"
},
  "geometry": {"coordinates":[137.98150000000001,-22.11272],"type":"Point"}
}