{
  "type": "Feature",
  "properties": {
    "gn:admin1_code":"4.0",
    "gn:admin2_code":"31900.0",
    "gn:asciiname":"Mirrigan",
    "gn:country_code":"AU",
    "gn:dem":15,
    "gn:feature_class":"P",
    "gn:feature_code":"PPL",
    "gn:name":"Mirrigan",
    "gn:population":0,
    "gn:timezone":"Australia/Brisbane",
    "iso:country":"AU",
    "wof:name":"Mirrigan",
    "wof:placetype":"locality"
},
  "geometry": {"coordinates":[147.38333,-19.58333],"type":"Point"}
}