{
  "type": "Feature",
  "properties": {
    "gn:admin1_code":"7.0",
    "gn:admin2_code":"26170.0",
    "gn:asciiname":"Darby River",
    "gn:country_code":"AU",
    "gn:dem":20,
    "gn:feature_class":"P",
    "gn:feature_code":"PPL",
    "gn:name":"Darby River",
    "gn:population":0,
    "gn:timezone":"Australia/Melbourne",
    "iso:country":"AU",
    "name:ceb_x_preferred":[
        "Darby River"
    ],
    "name:swe_x_preferred":[
        "Darby River"
    ],
    "wof:name":"Darby River",
    "wof:placetype":"locality"
},
  "geometry": {"coordinates":[146.28333000000001,-38.98333],"type":"Point"}
}