{
  "type": "Feature",
  "properties": {
    "gn:admin1_code":"4.0",
    "gn:admin2_code":"32070.0",
    "gn:asciiname":"Mopo",
    "gn:country_code":"AU",
    "gn:dem":16,
    "gn:feature_class":"P",
    "gn:feature_code":"PPL",
    "gn:name":"Mopo",
    "gn:population":0,
    "gn:timezone":"Australia/Brisbane",
    "iso:country":"AU",
    "wof:name":"Mopo",
    "wof:placetype":"locality"
},
  "geometry": {"coordinates":[145.91666999999995,-17.36667000000001],"type":"Point"}
}