{
  "type": "Feature",
  "properties": {
    "gn:admin1_code":"4.0",
    "gn:admin2_code":"30370.0",
    "gn:asciiname":"Rannes",
    "gn:country_code":"AU",
    "gn:dem":106,
    "gn:feature_class":"P",
    "gn:feature_code":"PPL",
    "gn:name":"Rannes",
    "gn:population":0,
    "gn:timezone":"Australia/Brisbane",
    "iso:country":"AU",
    "wof:name":"Rannes",
    "wof:placetype":"locality"
},
  "geometry": {"coordinates":[150.11667,-24.11667000000001],"type":"Point"}
}