{
  "type": "Feature",
  "properties": {
    "gn:admin1_code":"4.0",
    "gn:admin2_code":"32270.0",
    "gn:asciiname":"Mayden Parks",
    "gn:country_code":"AU",
    "gn:dem":226,
    "gn:feature_class":"P",
    "gn:feature_code":"PPL",
    "gn:name":"Mayden Parks",
    "gn:population":0,
    "gn:timezone":"Australia/Brisbane",
    "iso:country":"AU",
    "name:eng_x_preferred":[
        "Mayden Parks"
    ],
    "wof:name":"Mayden Parks",
    "wof:placetype":"locality"
},
  "geometry": {"coordinates":[147.75963999999999,-23.01388],"type":"Point"}
}