{
  "type": "Feature",
  "properties": {
    "gn:admin1_code":"4.0",
    "gn:admin2_code":"32250.0",
    "gn:asciiname":"Flying Fox Yard",
    "gn:country_code":"AU",
    "gn:dem":58,
    "gn:feature_class":"P",
    "gn:feature_code":"PPL",
    "gn:name":"Flying Fox Yard",
    "gn:population":0,
    "gn:timezone":"Australia/Brisbane",
    "iso:country":"AU",
    "wof:name":"Flying Fox Yard",
    "wof:placetype":"locality"
},
  "geometry": {"coordinates":[142.56331,-15.98559],"type":"Point"}
}