{
  "type": "Feature",
  "properties": {
    "gn:admin1_code":"2.0",
    "gn:admin2_code":"11050.0",
    "gn:asciiname":"Vandeville",
    "gn:country_code":"AU",
    "gn:dem":617,
    "gn:feature_class":"P",
    "gn:feature_code":"PPL",
    "gn:name":"Vandeville",
    "gn:population":0,
    "gn:timezone":"Australia/Sydney",
    "iso:country":"AU",
    "name:eng_x_preferred":[
        "Vandeville"
    ],
    "wof:name":"Vandeville",
    "wof:placetype":"locality"
},
  "geometry": {"coordinates":[148.94137000000001,-34.56113],"type":"Point"}
}