{
  "type": "Feature",
  "properties": {
    "gn:admin1_code":"4.0",
    "gn:admin2_code":"33980.0",
    "gn:asciiname":"Telerah",
    "gn:country_code":"AU",
    "gn:dem":315,
    "gn:feature_class":"P",
    "gn:feature_code":"PPL",
    "gn:name":"Telerah",
    "gn:population":0,
    "gn:timezone":"Australia/Brisbane",
    "iso:country":"AU",
    "name:eng_x_preferred":[
        "Telerah"
    ],
    "wof:name":"Telerah",
    "wof:placetype":"locality"
},
  "geometry": {"coordinates":[147.10983000000004,-22.94992],"type":"Point"}
}