{
  "type": "Feature",
  "properties": {
    "gn:admin1_code":"06",
    "gn:admin2_code":"63610.0",
    "gn:asciiname":"Summerleas",
    "gn:country_code":"AU",
    "gn:dem":159,
    "gn:feature_class":"P",
    "gn:feature_code":"PPL",
    "gn:name":"Summerleas",
    "gn:population":0,
    "gn:timezone":"Australia/Hobart",
    "iso:country":"AU",
    "name:eng_x_preferred":[
        "Summerleas"
    ],
    "wof:name":"Summerleas",
    "wof:placetype":"locality"
},
  "geometry": {"coordinates":[147.27287999999999,-42.95402],"type":"Point"}
}