{
  "type": "Feature",
  "properties": {
    "gn:gn_country":"AU",
    "gn:gn_fcode":"PPL",
    "gn:gn_pop":501,
    "gn:population":501,
    "iso:country":"AU",
    "name:eng_x_preferred":[
        "Elizabeth Town"
    ],
    "name:fra_x_preferred":[
        "Elizabeth Town"
    ],
    "name:nld_x_preferred":[
        "Elizabeth Town"
    ],
    "name:swe_x_preferred":[
        "Elizabeth Town"
    ],
    "qs_pg:aaroncc":"AU",
    "qs_pg:gn_country":"AU",
    "qs_pg:gn_fcode":"PPL",
    "qs_pg:gn_pop":501,
    "qs_pg:name":"Elizabeth Town",
    "qs_pg:name_adm0":"Australia",
    "qs_pg:name_adm1":"Tasmania",
    "qs_pg:photos":137,
    "qs_pg:photos_1k":28,
    "qs_pg:photos_9k":1,
    "qs_pg:photos_9r":3,
    "qs_pg:photos_all":137,
    "qs_pg:photos_sr":3,
    "qs_pg:pop_sr":2,
    "qs_pg:qs_pg_placetype":"locality",
    "qs_pg:qs_pg_placetype_gp":"Town",
    "qs_pg:woe_adm0":23424748,
    "woe:adm0_id":23424748,
    "woe:name_adm0":"Australia",
    "woe:name_adm1":"Tasmania",
    "woe:placetype":"Town",
    "wof:name":"Elizabeth Town",
    "wof:placetype":"locality",
    "wof:population":501
},
  "geometry": {"coordinates":[146.56666999999999,-41.45],"type":"Point"}
}