{
  "type": "Feature",
  "properties": {
    "gn:admin1_code":"7",
    "gn:admin2_code":"22110",
    "gn:asciiname":"The Walnuts",
    "gn:country_code":"AU",
    "gn:dem":311,
    "gn:feature_class":"P",
    "gn:feature_code":"PPL",
    "gn:name":"The Walnuts",
    "gn:population":0,
    "gn:timezone":"Australia/Melbourne",
    "iso:country":"AU",
    "wof:name":"The Walnuts",
    "wof:placetype":"locality"
},
  "geometry": {"coordinates":[147.69999999999999,-37.26667],"type":"Point"}
}