{
  "type": "Feature",
  "properties": {
    "iso:country":"AU",
    "name:ara_x_preferred":[
        "\u062b\u064a\u0648\u062f\u0648\u0631"
    ],
    "name:ben_x_preferred":[
        "\u09a5\u09c7\u0993\u09a1\u09b0"
    ],
    "name:deu_x_preferred":[
        "Theodore"
    ],
    "name:ell_x_preferred":[
        "\u0398\u03af\u03bf\u03bd\u03c4\u03bf\u03c1"
    ],
    "name:eng_x_preferred":[
        "Theodore"
    ],
    "name:epo_x_preferred":[
        "Teodoro"
    ],
    "name:fra_x_preferred":[
        "Theodore"
    ],
    "name:heb_x_preferred":[
        "\u05d8\u05d0\u05d5\u05d3\u05d5\u05e8"
    ],
    "name:hin_x_preferred":[
        "\u0925\u093f\u092f\u094b\u0921\u094b\u0930"
    ],
    "name:hun_x_preferred":[
        "Theodore"
    ],
    "name:ind_x_preferred":[
        "Theodore"
    ],
    "name:ita_x_preferred":[
        "Theodore"
    ],
    "name:jpn_x_preferred":[
        "\u30bb\u30aa\u30c9\u30a2"
    ],
    "name:kor_x_preferred":[
        "\ud14c\uc624\ub3c4\ub974"
    ],
    "name:nld_x_preferred":[
        "Theodore"
    ],
    "name:por_x_preferred":[
        "Theodore"
    ],
    "name:rus_x_preferred":[
        "\u0422\u0435\u043e\u0434\u043e\u0440"
    ],
    "name:spa_x_preferred":[
        "Theodore"
    ],
    "name:tur_x_preferred":[
        "Theodore"
    ],
    "name:ukr_x_preferred":[
        "\u0422\u0435\u043e\u0434\u043e\u0440"
    ],
    "name:urd_x_preferred":[
        "\u062a\u06be\u06cc\u0648\u0688\u0631"
    ],
    "name:vie_x_preferred":[
        "Theodore"
    ],
    "name:zho_cn_x_preferred":[
        "\u897f\u5965\u591a"
    ],
    "name:zho_tw_x_preferred":[
        "\u897f\u5967\u591a"
    ],
    "qs:gn_adm0_cc":"AU",
    "qs:gn_fcode":"PPLX",
    "qs:gn_local":2172517,
    "qs:gn_namadm1":"01",
    "qs:gn_name":"Theodore",
    "qs:local_max":10266,
    "qs:local_sum":72297,
    "qs:localhoods":96,
    "qs:name":"Theodore",
    "qs:name_adm0":"Australia",
    "qs:name_adm1":"Australian Capital Territory",
    "qs:name_adm2":"Canberra",
    "qs:name_local":"Canberra",
    "qs:photo_max":25,
    "qs:photo_sum":44,
    "qs:placetype":"Suburb",
    "qs:quad_count":10,
    "qs:woe_adm0":23424748,
    "qs:woe_adm1":2344699,
    "qs:woe_adm2":55863865,
    "qs:woe_lau":0,
    "qs:woe_local":1100968,
    "qs:woe_ver":"7.10.0",
    "wof:name":"Theodore",
    "wof:placetype":"neighbourhood"
},
  "geometry": {"coordinates":[149.130101,-35.45173],"type":"Point"}
}