{
  "type": "Feature",
  "properties": {
    "iso:country":"AU",
    "name:deu_x_preferred":[
        "Theodore"
    ],
    "name:eng_x_preferred":[
        "Theodore"
    ],
    "name:epo_x_preferred":[
        "Teodoro"
    ],
    "name:fra_x_preferred":[
        "Theodore"
    ],
    "name:nld_x_preferred":[
        "Theodore"
    ],
    "qs:gn_adm0_cc":"AU",
    "qs:gn_fcode":"PPLX",
    "qs:gn_local":2172517,
    "qs:gn_namadm1":"01",
    "qs:gn_name":"Theodore",
    "qs:local_max":10266,
    "qs:local_sum":72297,
    "qs:localhoods":96,
    "qs:name":"Theodore",
    "qs:name_adm0":"Australia",
    "qs:name_adm1":"Australian Capital Territory",
    "qs:name_adm2":"Canberra",
    "qs:name_local":"Canberra",
    "qs:photo_max":25,
    "qs:photo_sum":44,
    "qs:placetype":"Suburb",
    "qs:quad_count":10,
    "qs:woe_adm0":23424748,
    "qs:woe_adm1":2344699,
    "qs:woe_adm2":55863865,
    "qs:woe_lau":0,
    "qs:woe_local":1100968,
    "qs:woe_ver":"7.10.0",
    "wof:name":"Theodore",
    "wof:placetype":"neighbourhood"
},
  "geometry": {"coordinates":[149.13010079479625,-35.45173023488067],"type":"Point"}
}