{
  "type": "Feature",
  "properties": {
    "gn:admin1_code":"4.0",
    "gn:admin2_code":"33360.0",
    "gn:asciiname":"Bindawalla",
    "gn:country_code":"AU",
    "gn:dem":221,
    "gn:feature_class":"P",
    "gn:feature_code":"PPL",
    "gn:name":"Bindawalla",
    "gn:population":0,
    "gn:timezone":"Australia/Brisbane",
    "iso:country":"AU",
    "name:eng_x_preferred":[
        "Bindawalla"
    ],
    "wof:name":"Bindawalla",
    "wof:placetype":"locality"
},
  "geometry": {"coordinates":[150.99376999999996,-24.22022],"type":"Point"}
}