{
  "type": "Feature",
  "properties": {
    "gn:admin1_code":"4",
    "gn:admin2_code":"37340",
    "gn:asciiname":"Wakala",
    "gn:country_code":"AU",
    "gn:dem":16,
    "gn:feature_class":"P",
    "gn:feature_code":"PPL",
    "gn:name":"Wakala",
    "gn:population":0,
    "gn:timezone":"Australia/Brisbane",
    "iso:country":"AU",
    "wof:name":"Wakala",
    "wof:placetype":"locality"
},
  "geometry": {"coordinates":[147.63333,-19.86667000000001],"type":"Point"}
}