{
  "type": "Feature",
  "properties": {
    "gn:admin1_code":"2.0",
    "gn:admin2_code":"17700.0",
    "gn:asciiname":"Boonongo",
    "gn:country_code":"AU",
    "gn:dem":130,
    "gn:feature_class":"P",
    "gn:feature_code":"PPL",
    "gn:name":"Boonongo",
    "gn:population":0,
    "gn:timezone":"Australia/Sydney",
    "iso:country":"AU",
    "name:eng_x_preferred":[
        "Boonongo"
    ],
    "wof:name":"Boonongo",
    "wof:placetype":"locality"
},
  "geometry": {"coordinates":[146.27038999999999,-35.08562],"type":"Point"}
}