{
  "type": "Feature",
  "properties": {
    "gn:admin1_code":"7.0",
    "gn:admin2_code":"24780.0",
    "gn:asciiname":"Linga",
    "gn:country_code":"AU",
    "gn:dem":61,
    "gn:feature_class":"P",
    "gn:feature_code":"PPL",
    "gn:name":"Linga",
    "gn:population":0,
    "gn:timezone":"Australia/Melbourne",
    "iso:country":"AU",
    "wof:name":"Linga",
    "wof:placetype":"locality"
},
  "geometry": {"coordinates":[141.69899999999996,-35.171],"type":"Point"}
}