{
  "type": "Feature",
  "properties": {
    "gn:admin1_code":"4.0",
    "gn:admin2_code":"37310.0",
    "gn:asciiname":"Mannhurst",
    "gn:country_code":"AU",
    "gn:dem":335,
    "gn:feature_class":"P",
    "gn:feature_code":"PPL",
    "gn:name":"Mannhurst",
    "gn:population":0,
    "gn:timezone":"Australia/Brisbane",
    "iso:country":"AU",
    "wof:name":"Mannhurst",
    "wof:placetype":"locality"
},
  "geometry": {"coordinates":[150.40000000000001,-26.76667],"type":"Point"}
}