{
  "type": "Feature",
  "properties": {
    "gn:population":1121,
    "iso:country":"AU",
    "name:ceb_x_preferred":[
        "Goodwood"
    ],
    "name:eng_x_preferred":[
        "Goodwood"
    ],
    "name:swe_x_preferred":[
        "Goodwood"
    ],
    "name:unk_x_variant":[
        "Goodwood"
    ],
    "qs:gn_fcode":"PPL",
    "qs:gn_local":0,
    "qs:gn_namadm1":"06",
    "qs:gn_name":"Goodwood",
    "qs:local_max":6320,
    "qs:local_sum":24464,
    "qs:localhoods":40,
    "qs:name":"Goodwood",
    "qs:name_adm0":"Australia",
    "qs:name_adm1":"Tasmania",
    "qs:name_adm2":"City of Glenorchy",
    "qs:name_local":"Hobart",
    "qs:photo_max":24,
    "qs:photo_sum":103,
    "qs:placetype":"Suburb",
    "qs:quad_count":12,
    "qs:woe_adm0":23424748,
    "qs:woe_adm1":2344704,
    "qs:woe_adm2":55864283,
    "qs:woe_lau":0,
    "qs:woe_local":1102670,
    "qs:woe_ver":"7.10.0",
    "wof:lang":[
        "eng"
    ],
    "wof:name":"Goodwood",
    "wof:placetype":"neighbourhood",
    "wof:population":1121
},
  "geometry": {"coordinates":[147.297954,-42.832155],"type":"Point"}
}