{
  "type": "Feature",
  "properties": {
    "gn:country":"AU",
    "gn:fcode":"PPL",
    "gn:population":0,
    "iso:country":"AU",
    "name:cat_x_preferred":[
        "Dartmouth"
    ],
    "name:ceb_x_preferred":[
        "Dartmouth"
    ],
    "name:ces_x_preferred":[
        "Dartmouth"
    ],
    "name:cym_x_preferred":[
        "Dartmouth"
    ],
    "name:deu_x_preferred":[
        "Dartmouth"
    ],
    "name:fin_x_preferred":[
        "Dartmouth"
    ],
    "name:fra_x_preferred":[
        "Dartmouth"
    ],
    "name:ita_x_preferred":[
        "Dartmouth"
    ],
    "name:jpn_x_preferred":[
        "\u30c0\u30fc\u30c8\u30de\u30b9"
    ],
    "name:kor_x_preferred":[
        "\ub2e4\ud2b8\uba38\uc2a4"
    ],
    "name:mal_x_preferred":[
        "\u0d21\u0d3e\u0d7c\u0d1f\u0d4d\u0d2e\u0d57\u0d24\u0d4d"
    ],
    "name:nld_x_preferred":[
        "Dartmouth"
    ],
    "name:nno_x_preferred":[
        "Dartmouth"
    ],
    "name:pol_x_preferred":[
        "Dartmouth"
    ],
    "name:por_x_preferred":[
        "Dartmouth"
    ],
    "name:spa_x_preferred":[
        "Dartmouth"
    ],
    "name:swe_x_preferred":[
        "Dartmouth"
    ],
    "name:und_x_variant":[
        "Dartmouth Siding"
    ],
    "name:vol_x_preferred":[
        "Dartmouth"
    ],
    "qs_pg:aaroncc":"AU",
    "qs_pg:gn_country":"AU",
    "qs_pg:gn_fcode":"PPL",
    "qs_pg:gn_pop":0,
    "qs_pg:name":"Dartmouth",
    "qs_pg:name_adm0":"Australia",
    "qs_pg:name_adm1":"Queensland",
    "qs_pg:photos":15,
    "qs_pg:photos_1k":3,
    "qs_pg:photos_9k":1,
    "qs_pg:photos_9r":1,
    "qs_pg:photos_all":15,
    "qs_pg:photos_sr":1,
    "qs_pg:pop_sr":0,
    "qs_pg:qs_pg_placetype":"locality",
    "qs_pg:qs_pg_placetype_gp":"Town",
    "qs_pg:woe_adm0":23424748,
    "woe:adm0_id":23424748,
    "woe:name_adm0":"Australia",
    "woe:name_adm1":"Queensland",
    "woe:placetype":"Town",
    "wof:name":"Dartmouth",
    "wof:placetype":"locality"
},
  "geometry": {"coordinates":[144.69999999999999,-23.51667],"type":"Point"}
}