{
  "type": "Feature",
  "properties": {
    "gn:admin1_code":"4",
    "gn:admin2_code":"31820",
    "gn:asciiname":"The Grange",
    "gn:country_code":"AU",
    "gn:dem":23,
    "gn:feature_class":"P",
    "gn:feature_code":"PPL",
    "gn:name":"The Grange",
    "gn:population":0,
    "gn:timezone":"Australia/Brisbane",
    "iso:country":"AU",
    "name:bar_x_preferred":[
        "The Grange"
    ],
    "name:deu_x_preferred":[
        "The Grange"
    ],
    "name:hun_x_preferred":[
        "Grange"
    ],
    "wof:name":"The Grange",
    "wof:placetype":"locality"
},
  "geometry": {"coordinates":[152.41666999999995,-24.81667],"type":"Point"}
}