{
  "type": "Feature",
  "properties": {
    "gn:admin1_code":"4.0",
    "gn:admin2_code":"33980.0",
    "gn:asciiname":"Solferino",
    "gn:country_code":"AU",
    "gn:dem":265,
    "gn:feature_class":"P",
    "gn:feature_code":"PPL",
    "gn:name":"Solferino",
    "gn:population":0,
    "gn:timezone":"Australia/Brisbane",
    "iso:country":"AU",
    "name:eng_x_preferred":[
        "Solferino"
    ],
    "wof:name":"Solferino",
    "wof:placetype":"locality"
},
  "geometry": {"coordinates":[147.58455000000001,-22.21163],"type":"Point"}
}