{
  "type": "Feature",
  "properties": {
    "gn:admin1_code":"4.0",
    "gn:admin2_code":"33980.0",
    "gn:asciiname":"Solferino",
    "gn:country_code":"AU",
    "gn:dem":265,
    "gn:feature_class":"P",
    "gn:feature_code":"PPL",
    "gn:name":"Solferino",
    "gn:population":0,
    "gn:timezone":"Australia/Brisbane",
    "iso:country":"AU",
    "name:azb_x_preferred":[
        "\u0633\u0648\u0644\u0641\u0631\u06cc\u0646\u0648"
    ],
    "name:bul_x_preferred":[
        "\u0421\u043e\u043b\u0444\u0435\u0440\u0438\u043d\u043e"
    ],
    "name:cat_x_preferred":[
        "Solferino"
    ],
    "name:ceb_x_preferred":[
        "Solferino"
    ],
    "name:dan_x_preferred":[
        "Solferino"
    ],
    "name:deu_x_preferred":[
        "Solferino"
    ],
    "name:ell_x_preferred":[
        "\u03a3\u03bf\u03bb\u03c6\u03b5\u03c1\u03af\u03bd\u03bf"
    ],
    "name:eng_x_preferred":[
        "Solferino"
    ],
    "name:epo_x_preferred":[
        "Solferino"
    ],
    "name:eus_x_preferred":[
        "Solferino"
    ],
    "name:fas_x_preferred":[
        "\u0633\u0648\u0644\u0641\u0631\u06cc\u0646\u0648"
    ],
    "name:fra_x_preferred":[
        "Solf\u00e9rino"
    ],
    "name:hun_x_preferred":[
        "Solferino"
    ],
    "name:hye_x_preferred":[
        "\u054d\u0578\u056c\u0586\u0565\u0580\u056b\u0576\u0578"
    ],
    "name:ind_x_preferred":[
        "Solferino"
    ],
    "name:ita_x_preferred":[
        "Solferino"
    ],
    "name:jpn_x_preferred":[
        "\u30bd\u30eb\u30d5\u30a7\u30ea\u30fc\u30ce"
    ],
    "name:kaz_x_preferred":[
        "\u0421\u043e\u043b\u044c\u0444\u0435\u0440\u0438\u043d\u043e"
    ],
    "name:kor_x_preferred":[
        "\uc194\ud398\ub9ac\ub178"
    ],
    "name:lat_x_preferred":[
        "Sulferinum"
    ],
    "name:lmo_x_preferred":[
        "Sulfr\u00ec"
    ],
    "name:mkd_x_preferred":[
        "\u0421\u043e\u043b\u0444\u0435\u0440\u0438\u043d\u043e"
    ],
    "name:msa_x_preferred":[
        "Solferino"
    ],
    "name:nap_x_preferred":[
        "Solferino"
    ],
    "name:nld_x_preferred":[
        "Solferino"
    ],
    "name:nor_x_preferred":[
        "Solferino"
    ],
    "name:oci_x_preferred":[
        "Solferino"
    ],
    "name:pms_x_preferred":[
        "Solferino"
    ],
    "name:pol_x_preferred":[
        "Solferino"
    ],
    "name:por_x_preferred":[
        "Solferino"
    ],
    "name:ron_x_preferred":[
        "Solferino"
    ],
    "name:rus_x_preferred":[
        "\u0421\u043e\u043b\u044c\u0444\u0435\u0440\u0438\u043d\u043e"
    ],
    "name:scn_x_preferred":[
        "Solferino"
    ],
    "name:spa_x_preferred":[
        "Solferino"
    ],
    "name:srp_x_preferred":[
        "\u0421\u043e\u043b\u0444\u0435\u0440\u0438\u043d\u043e"
    ],
    "name:swe_x_preferred":[
        "Solferino"
    ],
    "name:tgl_x_preferred":[
        "Solferino"
    ],
    "name:ukr_x_preferred":[
        "\u0421\u043e\u043b\u044c\u0444\u0435\u0440\u0438\u043d\u043e"
    ],
    "name:uzb_x_preferred":[
        "Solferino"
    ],
    "name:vec_x_preferred":[
        "Solferino"
    ],
    "name:vol_x_preferred":[
        "Solferino"
    ],
    "name:war_x_preferred":[
        "Solferino"
    ],
    "name:zho_x_preferred":[
        "\u8607\u6cd5\u5229\u8afe"
    ],
    "wof:name":"Solferino",
    "wof:placetype":"locality"
},
  "geometry": {"coordinates":[147.58455000000001,-22.21163],"type":"Point"}
}