{
  "type": "Feature",
  "properties": {
    "gn:admin1_code":"4.0",
    "gn:admin2_code":"34710.0",
    "gn:asciiname":"Montrose",
    "gn:country_code":"AU",
    "gn:dem":239,
    "gn:feature_class":"P",
    "gn:feature_code":"PPL",
    "gn:name":"Montrose",
    "gn:population":0,
    "gn:timezone":"Australia/Brisbane",
    "iso:country":"AU",
    "name:eng_x_preferred":[
        "Montrose"
    ],
    "wof:name":"Montrose",
    "wof:placetype":"locality"
},
  "geometry": {"coordinates":[144.29002,-23.7739],"type":"Point"}
}