{
  "type": "Feature",
  "properties": {
    "gn:admin1_code":"7.0",
    "gn:admin2_code":"21750.0",
    "gn:asciiname":"Cressy",
    "gn:country_code":"AU",
    "gn:dem":128,
    "gn:feature_class":"P",
    "gn:feature_code":"PPL",
    "gn:name":"Cressy",
    "gn:population":0,
    "gn:timezone":"Australia/Melbourne",
    "iso:country":"AU",
    "wof:name":"Cressy",
    "wof:placetype":"locality"
},
  "geometry": {"coordinates":[143.63333,-38.03333],"type":"Point"}
}