{
  "type": "Feature",
  "properties": {
    "gn:admin1_code":"5.0",
    "gn:admin2_code":"47800.0",
    "gn:asciiname":"Sunwood Park",
    "gn:country_code":"AU",
    "gn:dem":17,
    "gn:feature_class":"P",
    "gn:feature_code":"PPL",
    "gn:name":"Sunwood Park",
    "gn:population":0,
    "gn:timezone":"Australia/Adelaide",
    "iso:country":"AU",
    "name:eng_x_preferred":[
        "Sunwood Park"
    ],
    "wof:name":"Sunwood Park",
    "wof:placetype":"locality"
},
  "geometry": {"coordinates":[139.66508000000002,-35.96773],"type":"Point"}
}