{
  "type": "Feature",
  "properties": {
    "gn:admin1_code":"7.0",
    "gn:admin2_code":"23350.0",
    "gn:asciiname":"Reids Creek",
    "gn:country_code":"AU",
    "gn:dem":334,
    "gn:feature_class":"P",
    "gn:feature_code":"PPL",
    "gn:name":"Reids Creek",
    "gn:population":0,
    "gn:timezone":"Australia/Melbourne",
    "iso:country":"AU",
    "wof:name":"Reids Creek",
    "wof:placetype":"locality"
},
  "geometry": {"coordinates":[146.68333000000001,-36.31667],"type":"Point"}
}