{
  "type": "Feature",
  "properties": {
    "gn:admin1_code":"4.0",
    "gn:admin2_code":"34770.0",
    "gn:asciiname":"Mowo",
    "gn:country_code":"AU",
    "gn:dem":39,
    "gn:feature_class":"P",
    "gn:feature_code":"PPL",
    "gn:name":"Mowo",
    "gn:population":0,
    "gn:timezone":"Australia/Brisbane",
    "iso:country":"AU",
    "name:eng_x_preferred":[
        "Mowo"
    ],
    "wof:name":"Mowo",
    "wof:placetype":"locality"
},
  "geometry": {"coordinates":[148.58581000000001,-20.6774],"type":"Point"}
}