{
  "type": "Feature",
  "properties": {
    "gn:country":"AU",
    "gn:fcode":"PPL",
    "gn:population":0,
    "iso:country":"AU",
    "name:bre_x_preferred":[
        "Windermere"
    ],
    "name:cat_x_preferred":[
        "Windermere"
    ],
    "name:ceb_x_preferred":[
        "Windermere"
    ],
    "name:ces_x_preferred":[
        "Windermere"
    ],
    "name:chv_x_preferred":[
        "\u0423\u0438\u043d\u0434\u0435\u0440\u043c\u0438\u0440"
    ],
    "name:cym_x_preferred":[
        "Windermere"
    ],
    "name:dan_x_preferred":[
        "Windermere"
    ],
    "name:deu_x_preferred":[
        "Windermere"
    ],
    "name:eng_x_preferred":[
        "Windermere"
    ],
    "name:eus_x_preferred":[
        "Windermere"
    ],
    "name:fin_x_preferred":[
        "Windermere"
    ],
    "name:fra_x_preferred":[
        "Lac Windermere"
    ],
    "name:gle_x_preferred":[
        "Windermere"
    ],
    "name:heb_x_preferred":[
        "\u05d0\u05d2\u05dd \u05d5\u05d9\u05e0\u05d3\u05de\u05d9\u05d9\u05e8"
    ],
    "name:hrv_x_preferred":[
        "Windermere"
    ],
    "name:ita_x_preferred":[
        "Windermere"
    ],
    "name:mkd_x_preferred":[
        "\u0412\u0438\u043d\u0434\u0435\u0440\u043c\u0438\u0440"
    ],
    "name:nld_x_preferred":[
        "Windermere"
    ],
    "name:nno_x_preferred":[
        "Windermere"
    ],
    "name:nor_x_preferred":[
        "Windermere"
    ],
    "name:pnb_x_preferred":[
        "\u0648\u0646\u0688\u0631\u0645\u06cc\u0626\u0631"
    ],
    "name:pol_x_preferred":[
        "Windermere"
    ],
    "name:rus_x_preferred":[
        "\u0423\u0438\u043d\u0434\u0435\u0440\u043c\u0438\u0440"
    ],
    "name:spa_x_preferred":[
        "Windermere"
    ],
    "name:swe_x_preferred":[
        "Windermere"
    ],
    "name:zho_x_preferred":[
        "\u6eab\u5fb7\u7c73\u723e\u6e56"
    ],
    "qs_pg:aaroncc":"AU",
    "qs_pg:gn_country":"AU",
    "qs_pg:gn_fcode":"PPL",
    "qs_pg:gn_pop":0,
    "qs_pg:name":"Windermere",
    "qs_pg:name_adm0":"Australia",
    "qs_pg:name_adm1":"Victoria",
    "qs_pg:photos":5,
    "qs_pg:photos_1k":1,
    "qs_pg:photos_9k":1,
    "qs_pg:photos_9r":1,
    "qs_pg:photos_all":5,
    "qs_pg:photos_sr":1,
    "qs_pg:pop_sr":0,
    "qs_pg:qs_pg_placetype":"locality",
    "qs_pg:qs_pg_placetype_gp":"Town",
    "qs_pg:woe_adm0":23424748,
    "woe:adm0_id":23424748,
    "woe:name_adm0":"Australia",
    "woe:name_adm1":"Victoria",
    "woe:placetype":"Town",
    "wof:name":"Windermere",
    "wof:placetype":"locality",
    "wof:population":97
},
  "geometry": {"coordinates":[143.71666999999999,-37.48333],"type":"Point"}
}