{
  "type": "Feature",
  "properties": {
    "gn:admin1_code":"2.0",
    "gn:admin2_code":"12200.0",
    "gn:asciiname":"Kilrush",
    "gn:country_code":"AU",
    "gn:dem":390,
    "gn:feature_class":"P",
    "gn:feature_code":"PPL",
    "gn:name":"Kilrush",
    "gn:population":0,
    "gn:timezone":"Australia/Sydney",
    "iso:country":"AU",
    "wof:name":"Kilrush",
    "wof:placetype":"locality"
},
  "geometry": {"coordinates":[148.11667,-34.65],"type":"Point"}
}