{
  "type": "Feature",
  "properties": {
    "iso:country":"AU",
    "name:eng_x_preferred":[
        "Glebe Point"
    ],
    "name:ron_x_preferred":[
        "Glebe Point"
    ],
    "name:unk_x_variant":[
        "Glebe Point"
    ],
    "qs:gn_adm0_cc":"AU",
    "qs:gn_local":2147714,
    "qs:local_max":35533,
    "qs:local_sum":687549,
    "qs:localhoods":516,
    "qs:name":"Glebe Point",
    "qs:name_adm0":"Australia",
    "qs:name_adm1":"New South Wales",
    "qs:name_adm2":"Sydney",
    "qs:name_local":"Sydney",
    "qs:photo_max":389,
    "qs:photo_sum":1476,
    "qs:placetype":"Suburb",
    "qs:quad_count":29,
    "qs:woe_adm0":23424748,
    "qs:woe_adm1":2344700,
    "qs:woe_adm2":55864169,
    "qs:woe_lau":0,
    "qs:woe_local":1105779,
    "qs:woe_ver":"7.10.0",
    "wd:wordcount":89,
    "wof:lang":[
        "eng"
    ],
    "wof:name":"Glebe Point",
    "wof:placetype":"neighbourhood"
},
  "geometry": {"coordinates":[151.187511,-33.88221],"type":"Point"}
}