{
  "type": "Feature",
  "properties": {
    "iso:country":"AU",
    "oa:elevation_ft":"532",
    "oa:type":"medium_airport",
    "woe:hierarchy":{
        "country_id":23424748,
        "county_id":55864348,
        "planet_id":1,
        "state_id":2344702
    },
    "wof:name":"Coen Aerodrome",
    "wof:placetype":"campus"
},
  "geometry": {"coordinates":[143.11666666667,-13.761944444444],"type":"Point"}
}