{
  "type": "Feature",
  "properties": {
    "iso:country":"AU",
    "name:ceb_x_preferred":[
        "Coen Airport"
    ],
    "name:eng_x_preferred":[
        "Coen Airport"
    ],
    "name:eng_x_variant":[
        "CUQ",
        "YCOE"
    ],
    "name:jpn_x_preferred":[
        "\u30b3\u30fc\u30a8\u30f3\u7a7a\u6e2f"
    ],
    "name:msa_x_preferred":[
        "Lapangan Terbang Coen"
    ],
    "name:pol_x_preferred":[
        "Port lotniczy Coen"
    ],
    "name:ron_x_preferred":[
        "Aeroportul Coen"
    ],
    "name:swe_x_preferred":[
        "Coen Airport"
    ],
    "name:zho_x_preferred":[
        "\u79d1\u6069\u6a5f\u5834"
    ],
    "oa:elevation_ft":"532",
    "oa:type":"medium_airport",
    "woe:hierarchy":{
        "country_id":23424748,
        "county_id":55864348,
        "planet_id":1,
        "state_id":2344702
    },
    "wof:name":"Coen Aerodrome",
    "wof:placetype":"campus"
},
  "geometry": {"coordinates":[143.11666700000001,-13.761944],"type":"Point"}
}