{
  "type": "Feature",
  "properties": {
    "gn:admin1_code":"4.0",
    "gn:admin2_code":"34770.0",
    "gn:asciiname":"Okuloo",
    "gn:country_code":"AU",
    "gn:dem":162,
    "gn:feature_class":"P",
    "gn:feature_code":"PPL",
    "gn:name":"Okuloo",
    "gn:population":0,
    "gn:timezone":"Australia/Brisbane",
    "iso:country":"AU",
    "wof:name":"Okuloo",
    "wof:placetype":"locality"
},
  "geometry": {"coordinates":[148.56666999999999,-21.13333],"type":"Point"}
}