{
  "type": "Feature",
  "properties": {
    "gn:gn_country":"AU",
    "gn:gn_fcode":"PPL",
    "gn:gn_pop":135,
    "gn:population":135,
    "iso:country":"AU",
    "name:eng_x_preferred":[
        "Ouse"
    ],
    "name:fra_x_preferred":[
        "Ouse"
    ],
    "name:nld_x_preferred":[
        "Ouse"
    ],
    "name:rus_x_preferred":[
        "\u0423\u0437"
    ],
    "name:swe_x_preferred":[
        "Ouse"
    ],
    "qs_pg:aaroncc":"AU",
    "qs_pg:gn_country":"AU",
    "qs_pg:gn_fcode":"PPL",
    "qs_pg:gn_pop":135,
    "qs_pg:name":"Ouse",
    "qs_pg:name_adm0":"Australia",
    "qs_pg:name_adm1":"Tasmania",
    "qs_pg:photos_9k":1,
    "qs_pg:photos_9r":1,
    "qs_pg:photos_all":24,
    "qs_pg:photos_sr":0,
    "qs_pg:pop_sr":1,
    "qs_pg:qs_pg_placetype":"locality",
    "qs_pg:qs_pg_placetype_gp":"Town",
    "qs_pg:woe_adm0":23424748,
    "woe:adm0_id":23424748,
    "woe:name_adm0":"Australia",
    "woe:name_adm1":"Tasmania",
    "woe:placetype":"Town",
    "wof:name":"Ouse",
    "wof:placetype":"locality",
    "wof:population":135
},
  "geometry": {"coordinates":[146.71666999999999,-42.46667],"type":"Point"}
}