{
  "type": "Feature",
  "properties": {
    "gn:gn_country":"AU",
    "gn:gn_fcode":"PPL",
    "gn:gn_pop":264,
    "gn:population":264,
    "iso:country":"AU",
    "name:ceb_x_preferred":[
        "Eumungerie"
    ],
    "name:eng_x_preferred":[
        "Eumungerie"
    ],
    "name:fas_x_preferred":[
        "\u06cc\u0648\u0645\u0627\u0646\u062c\u0631\u06cc"
    ],
    "name:swe_x_preferred":[
        "Eumungerie"
    ],
    "qs_pg:aaroncc":"AU",
    "qs_pg:gn_country":"AU",
    "qs_pg:gn_fcode":"PPL",
    "qs_pg:gn_pop":264,
    "qs_pg:name":"Eumungerie",
    "qs_pg:photos_9r":0,
    "qs_pg:photos_sr":0,
    "qs_pg:pop_sr":2,
    "qs_pg:qs_pg_placetype":"locality",
    "wof:name":"Eumungerie",
    "wof:placetype":"locality",
    "wof:population":264
},
  "geometry": {"coordinates":[148.61667,-31.95],"type":"Point"}
}