{
  "type": "Feature",
  "properties": {
    "gn:admin1_code":"4",
    "gn:admin2_code":"35600",
    "gn:asciiname":"Sommariva",
    "gn:country_code":"AU",
    "gn:dem":391,
    "gn:feature_class":"P",
    "gn:feature_code":"PPL",
    "gn:name":"Sommariva",
    "gn:population":0,
    "gn:timezone":"Australia/Brisbane",
    "iso:country":"AU",
    "name:eng_x_preferred":[
        "Sommariva"
    ],
    "wof:name":"Sommariva",
    "wof:placetype":"locality"
},
  "geometry": {"coordinates":[146.60306,-26.41914],"type":"Point"}
}