{
  "type": "Feature",
  "properties": {
    "iso:country":"AU",
    "name:eng_x_preferred":[
        "Wheeler Heights"
    ],
    "name:fra_x_preferred":[
        "Wheeler Heights"
    ],
    "name:por_x_preferred":[
        "Wheeler Heights"
    ],
    "qs:gn_adm0_cc":"AU",
    "qs:gn_local":2147714,
    "qs:local_max":35533,
    "qs:local_sum":687549,
    "qs:localhoods":516,
    "qs:name":"Wheeler Heights",
    "qs:name_adm0":"Australia",
    "qs:name_adm1":"New South Wales",
    "qs:name_adm2":"Warringah",
    "qs:name_local":"Sydney",
    "qs:photo_max":118,
    "qs:photo_sum":195,
    "qs:placetype":"Suburb",
    "qs:quad_count":11,
    "qs:woe_adm0":23424748,
    "qs:woe_adm1":2344700,
    "qs:woe_adm2":55864177,
    "qs:woe_lau":0,
    "qs:woe_local":1105779,
    "qs:woe_ver":"7.10.0",
    "wd:wordcount":1185,
    "wof:lang":[
        "eng"
    ],
    "wof:name":"Wheeler Heights",
    "wof:placetype":"neighbourhood"
},
  "geometry": {"coordinates":[151.272199,-33.730138],"type":"Point"}
}