{
  "type": "Feature",
  "properties": {
    "gn:admin1_code":"6.0",
    "gn:admin2_code":"63410.0",
    "gn:asciiname":"Egg Lagoon",
    "gn:country_code":"AU",
    "gn:dem":30,
    "gn:feature_class":"P",
    "gn:feature_code":"PPL",
    "gn:name":"Egg Lagoon",
    "gn:population":0,
    "gn:timezone":"Australia/Currie",
    "iso:country":"AU",
    "name:eng_x_preferred":[
        "Egg Lagoon"
    ],
    "wof:name":"Egg Lagoon",
    "wof:placetype":"locality"
},
  "geometry": {"coordinates":[143.97638999999995,-39.66111],"type":"Point"}
}