{
  "type": "Feature",
  "properties": {
    "gn:admin1_code":"4.0",
    "gn:admin2_code":"30410.0",
    "gn:asciiname":"Mafeking",
    "gn:country_code":"AU",
    "gn:dem":321,
    "gn:feature_class":"P",
    "gn:feature_code":"PPL",
    "gn:name":"Mafeking",
    "gn:population":0,
    "gn:timezone":"Australia/Brisbane",
    "iso:country":"AU",
    "name:eng_x_preferred":[
        "Mafeking"
    ],
    "wof:name":"Mafeking",
    "wof:placetype":"locality"
},
  "geometry": {"coordinates":[145.76101,-23.74443],"type":"Point"}
}