{
  "type": "Feature",
  "properties": {
    "gn:gn_country":"AU",
    "gn:gn_fcode":"PPL",
    "gn:gn_pop":928,
    "gn:population":928,
    "iso:country":"AU",
    "name:dut_x_preferred":[
        "Kangarilla"
    ],
    "name:eng_x_preferred":[
        "Kangarilla"
    ],
    "name:fre_x_preferred":[
        "Kangarilla"
    ],
    "name:swe_x_preferred":[
        "Kangarilla"
    ],
    "qs_pg:aaroncc":"AU",
    "qs_pg:gn_country":"AU",
    "qs_pg:gn_fcode":"PPL",
    "qs_pg:gn_pop":928,
    "qs_pg:name":"Kangarilla",
    "qs_pg:name_adm0":"Australia",
    "qs_pg:name_adm1":"South Australia",
    "qs_pg:photos":91,
    "qs_pg:photos_1k":18,
    "qs_pg:photos_9k":1,
    "qs_pg:photos_9r":3,
    "qs_pg:photos_all":91,
    "qs_pg:photos_sr":3,
    "qs_pg:pop_sr":2,
    "qs_pg:qs_pg_placetype":"locality",
    "qs_pg:qs_pg_placetype_gp":"Town",
    "qs_pg:woe_adm0":23424748,
    "woe:adm0_id":23424748,
    "woe:name_adm0":"Australia",
    "woe:name_adm1":"South Australia",
    "woe:placetype":"Town",
    "wof:name":"Kangarilla",
    "wof:placetype":"locality",
    "wof:population":928
},
  "geometry": {"coordinates":[138.65000000000001,-35.15],"type":"Point"}
}