{
  "type": "Feature",
  "properties": {
    "gn:admin1_code":"4.0",
    "gn:admin2_code":"36510.0",
    "gn:asciiname":"Cannon Creek",
    "gn:country_code":"AU",
    "gn:dem":221,
    "gn:feature_class":"P",
    "gn:feature_code":"PPL",
    "gn:name":"Cannon Creek",
    "gn:population":0,
    "gn:timezone":"Australia/Brisbane",
    "iso:country":"AU",
    "wof:name":"Cannon Creek",
    "wof:placetype":"locality"
},
  "geometry": {"coordinates":[152.72412,-28.06274],"type":"Point"}
}