{
  "type": "Feature",
  "properties": {
    "gn:admin1_code":"7",
    "gn:admin2_code":"27450",
    "gn:asciiname":"Slaty Creek",
    "gn:country_code":"AU",
    "gn:dem":330,
    "gn:feature_class":"P",
    "gn:feature_code":"PPL",
    "gn:name":"Slaty Creek",
    "gn:population":0,
    "gn:timezone":"Australia/Melbourne",
    "iso:country":"AU",
    "wof:name":"Slaty Creek",
    "wof:placetype":"locality"
},
  "geometry": {"coordinates":[145.66666999999995,-37.85],"type":"Point"}
}