{
  "type": "Feature",
  "properties": {
    "gn:admin1_code":"8",
    "gn:admin2_code":"53220",
    "gn:asciiname":"Dalton",
    "gn:cc2":"AU",
    "gn:country_code":"AU",
    "gn:dem":300,
    "gn:feature_class":"P",
    "gn:feature_code":"PPL",
    "gn:name":"Dalton",
    "gn:population":0,
    "gn:timezone":"Australia/Perth",
    "iso:country":"AU",
    "name:ara_x_preferred":[
        "\u062f\u0627\u0644\u062a\u0648\u0646"
    ],
    "name:cat_x_preferred":[
        "Dalton"
    ],
    "name:ceb_x_preferred":[
        "Dalton"
    ],
    "name:ces_x_preferred":[
        "Dalton"
    ],
    "name:dan_x_preferred":[
        "Dalton"
    ],
    "name:deu_x_preferred":[
        "Dalton"
    ],
    "name:est_x_preferred":[
        "Dalton"
    ],
    "name:fas_x_preferred":[
        "\u062f\u0627\u0644\u062a\u0648\u0646"
    ],
    "name:fin_x_preferred":[
        "Dalton"
    ],
    "name:fra_x_preferred":[
        "Dalton"
    ],
    "name:glg_x_preferred":[
        "Dalton"
    ],
    "name:heb_x_preferred":[
        "\u05d3\u05dc\u05d8\u05d5\u05df"
    ],
    "name:hun_x_preferred":[
        "Dalton"
    ],
    "name:ind_x_preferred":[
        "Dalton"
    ],
    "name:ita_x_preferred":[
        "Dalton"
    ],
    "name:jav_x_preferred":[
        "Dalton"
    ],
    "name:jpn_x_preferred":[
        "\u30c9\u30eb\u30c8\u30f3"
    ],
    "name:kor_x_preferred":[
        "\ub3cc\ud134"
    ],
    "name:nld_x_preferred":[
        "Dalton"
    ],
    "name:pol_x_preferred":[
        "Dalton"
    ],
    "name:por_x_preferred":[
        "Dalton"
    ],
    "name:rus_x_preferred":[
        "\u0414\u0430\u043b\u044c\u0442\u043e\u043d"
    ],
    "name:slv_x_preferred":[
        "Dalton"
    ],
    "name:snd_x_preferred":[
        "\u068a\u0627\u0644\u067d\u0646"
    ],
    "name:spa_x_preferred":[
        "Dalton"
    ],
    "name:srp_x_preferred":[
        "\u0414\u0430\u043b\u0442\u043e\u043d"
    ],
    "name:swe_x_preferred":[
        "Dalton"
    ],
    "name:tur_x_preferred":[
        "Dalton"
    ],
    "name:ukr_x_preferred":[
        "\u0414\u0430\u043b\u044c\u0442\u043e\u043d"
    ],
    "name:und_x_variant":[
        "Dalton Mining Centre"
    ],
    "name:urd_x_preferred":[
        "\u0688\u0627\u0644\u0679\u0646"
    ],
    "name:vol_x_preferred":[
        "Dalton"
    ],
    "name:zho_x_preferred":[
        "\u9053\u5c14\u987f"
    ],
    "wof:name":"Dalton",
    "wof:placetype":"locality"
},
  "geometry": {"coordinates":[119.23333,-21.48333],"type":"Point"}
}