{
  "type": "Feature",
  "properties": {
    "gn:admin1_code":"8",
    "gn:admin2_code":"53220",
    "gn:asciiname":"Dalton",
    "gn:cc2":"AU",
    "gn:country_code":"AU",
    "gn:dem":300,
    "gn:feature_class":"P",
    "gn:feature_code":"PPL",
    "gn:name":"Dalton",
    "gn:population":0,
    "gn:timezone":"Australia/Perth",
    "iso:country":"AU",
    "name:und_x_variant":[
        "Dalton Mining Centre",
        "Dalton"
    ],
    "wof:name":"Dalton",
    "wof:placetype":"locality"
},
  "geometry": {"coordinates":[119.23333,-21.48333],"type":"Point"}
}