{
  "type": "Feature",
  "properties": {
    "gn:admin1_code":"4.0",
    "gn:admin2_code":"36810.0",
    "gn:asciiname":"Batcha",
    "gn:country_code":"AU",
    "gn:dem":604,
    "gn:feature_class":"P",
    "gn:feature_code":"PPL",
    "gn:name":"Batcha",
    "gn:population":0,
    "gn:timezone":"Australia/Brisbane",
    "iso:country":"AU",
    "wof:name":"Batcha",
    "wof:placetype":"locality"
},
  "geometry": {"coordinates":[144.91666999999995,-17.46667],"type":"Point"}
}