{
  "type": "Feature",
  "properties": {
    "gn:admin1_code":"2.0",
    "gn:admin2_code":"15300.0",
    "gn:asciiname":"Willow Park",
    "gn:country_code":"AU",
    "gn:dem":228,
    "gn:feature_class":"P",
    "gn:feature_code":"PPL",
    "gn:name":"Willow Park",
    "gn:population":0,
    "gn:timezone":"Australia/Sydney",
    "iso:country":"AU",
    "name:ceb_x_preferred":[
        "Willow Park"
    ],
    "name:eng_x_preferred":[
        "Willow Park"
    ],
    "name:swe_x_preferred":[
        "Willow Park"
    ],
    "wof:name":"Willow Park",
    "wof:placetype":"locality"
},
  "geometry": {"coordinates":[149.91244,-29.58125],"type":"Point"}
}