{
  "type": "Feature",
  "properties": {
    "gn:admin1_code":"3.0",
    "gn:admin2_code":"74050.0",
    "gn:asciiname":"North Ridge",
    "gn:country_code":"AU",
    "gn:dem":69,
    "gn:feature_class":"P",
    "gn:feature_code":"PPL",
    "gn:name":"North Ridge",
    "gn:population":0,
    "gn:timezone":"Australia/Darwin",
    "iso:country":"AU",
    "name:ceb_x_preferred":[
        "North Ridge"
    ],
    "name:swe_x_preferred":[
        "North Ridge"
    ],
    "wof:name":"North Ridge",
    "wof:placetype":"locality"
},
  "geometry": {"coordinates":[131.27076,-11.68766],"type":"Point"}
}