{
  "type": "Feature",
  "properties": {
    "gn:admin1_code":"2.0",
    "gn:admin2_code":"15270.0",
    "gn:asciiname":"Apple Tree Flat",
    "gn:country_code":"AU",
    "gn:dem":494,
    "gn:feature_class":"P",
    "gn:feature_code":"PPL",
    "gn:name":"Apple Tree Flat",
    "gn:population":0,
    "gn:timezone":"Australia/Sydney",
    "iso:country":"AU",
    "wof:name":"Apple Tree Flat",
    "wof:placetype":"locality"
},
  "geometry": {"coordinates":[149.7012,-32.6818],"type":"Point"}
}