{
  "type": "Feature",
  "properties": {
    "gn:admin1_code":"8",
    "gn:admin2_code":"55460",
    "gn:asciiname":"Booraan",
    "gn:country_code":"AU",
    "gn:dem":372,
    "gn:feature_class":"P",
    "gn:feature_code":"PPL",
    "gn:name":"Booraan",
    "gn:population":0,
    "gn:timezone":"Australia/Perth",
    "iso:country":"AU",
    "wof:name":"Booraan",
    "wof:placetype":"locality"
},
  "geometry": {"coordinates":[118.36893000000001,-31.46729],"type":"Point"}
}