{
  "type": "Feature",
  "properties": {
    "iso:country":"AU",
    "name:eng_x_preferred":[
        "Nowra Central"
    ],
    "qs:gn_adm0_cc":"AU",
    "qs:gn_local":2154787,
    "qs:gn_nam_loc":"nowra",
    "qs:gn_namadm1":"02",
    "qs:local_max":356,
    "qs:local_sum":869,
    "qs:localhoods":6,
    "qs:name":"Nowra Central",
    "qs:name_adm0":"Australia",
    "qs:name_adm1":"New South Wales",
    "qs:name_adm2":"Shoalhaven",
    "qs:name_local":"Nowra",
    "qs:photo_max":29,
    "qs:photo_sum":159,
    "qs:placetype":"Suburb",
    "qs:quad_count":14,
    "qs:woe_adm0":23424748,
    "qs:woe_adm1":2344700,
    "qs:woe_adm2":55864285,
    "qs:woe_lau":0,
    "qs:woe_local":1104694,
    "qs:woe_ver":"7.10.0",
    "wof:lang":[
        "eng"
    ],
    "wof:name":"Nowra Central",
    "wof:placetype":"neighbourhood"
},
  "geometry": {"coordinates":[150.59780499999999,-34.873883],"type":"Point"}
}