{
  "type": "Feature",
  "properties": {
    "iso:country":"AU",
    "name:ara_x_preferred":[
        "\u0646\u0647\u0631 \u0631\u0648\u0633"
    ],
    "name:cym_x_preferred":[
        "Afon Ross"
    ],
    "name:eng_x_preferred":[
        "Ross River"
    ],
    "name:fas_x_preferred":[
        "\u0631\u0622\u0633 \u0631\u06cc\u0648\u0631"
    ],
    "name:fra_x_preferred":[
        "Ross River"
    ],
    "name:ita_x_preferred":[
        "Ross"
    ],
    "name:nld_x_preferred":[
        "Ross River"
    ],
    "name:pol_x_preferred":[
        "Ross"
    ],
    "qs:gn_adm0_cc":"AU",
    "qs:gn_fcode":"PPL",
    "qs:gn_local":2146142,
    "qs:gn_nam_loc":"Townsville, Townsville, Queensland, AU",
    "qs:gn_namadm1":"04",
    "qs:gn_name":"Ross River",
    "qs:local_max":1893,
    "qs:local_sum":7234,
    "qs:localhoods":21,
    "qs:name":"Ross River",
    "qs:name_adm0":"Australia",
    "qs:name_adm1":"Queensland",
    "qs:name_adm2":"Townsville City",
    "qs:name_local":"Townsville",
    "qs:photo_max":263,
    "qs:photo_sum":371,
    "qs:placetype":"Suburb",
    "qs:quad_count":7,
    "qs:woe_adm0":23424748,
    "qs:woe_adm1":2344702,
    "qs:woe_adm2":56072971,
    "qs:woe_lau":0,
    "qs:woe_local":1106143,
    "qs:woe_ver":"7.10.0",
    "wd:wordcount":1247,
    "wof:lang":[
        "eng"
    ],
    "wof:name":"Ross River",
    "wof:placetype":"neighbourhood"
},
  "geometry": {"coordinates":[146.73917599999999,-19.312664],"type":"Point"}
}