{
  "type": "Feature",
  "properties": {
    "gn:admin1_code":"4.0",
    "gn:admin2_code":"35760.0",
    "gn:asciiname":"Cronulla",
    "gn:country_code":"AU",
    "gn:dem":212,
    "gn:feature_class":"P",
    "gn:feature_code":"PPL",
    "gn:name":"Cronulla",
    "gn:population":0,
    "gn:timezone":"Australia/Brisbane",
    "iso:country":"AU",
    "name:eng_x_preferred":[
        "Cronulla"
    ],
    "wof:name":"Cronulla",
    "wof:placetype":"locality"
},
  "geometry": {"coordinates":[151.37796,-25.38228],"type":"Point"}
}