{
  "type": "Feature",
  "properties": {
    "iso:country":"AU",
    "name:eng_x_preferred":[
        "Regent"
    ],
    "name:unk_x_variant":[
        "Regent"
    ],
    "qs:gn_adm0_cc":"AU",
    "qs:gn_fcode":"PPL",
    "qs:gn_local":2158177,
    "qs:gn_namadm1":"07",
    "qs:gn_name":"Regent",
    "qs:local_max":22745,
    "qs:local_sum":338594,
    "qs:localhoods":407,
    "qs:name":"Regent",
    "qs:name_adm0":"Australia",
    "qs:name_adm1":"Victoria",
    "qs:name_adm2":"City of Darebin",
    "qs:name_local":"Melbourne",
    "qs:photo_max":25,
    "qs:photo_sum":61,
    "qs:placetype":"Suburb",
    "qs:quad_count":11,
    "qs:woe_adm0":23424748,
    "qs:woe_adm1":2344705,
    "qs:woe_adm2":55864005,
    "qs:woe_lau":0,
    "qs:woe_local":1103816,
    "qs:woe_ver":"7.10.0",
    "wd:wordcount":857,
    "wof:lang":[
        "eng"
    ],
    "wof:name":"Regent",
    "wof:placetype":"neighbourhood"
},
  "geometry": {"coordinates":[145.002916,-37.729104],"type":"Point"}
}