{
  "type": "Feature",
  "properties": {
    "gn:country":"AU",
    "gn:fcode":"PPL",
    "gn:population":168,
    "iso:country":"AU",
    "name:ceb_x_preferred":[
        "Kelso"
    ],
    "name:cym_x_preferred":[
        "Kelso"
    ],
    "name:deu_x_preferred":[
        "Kelso"
    ],
    "name:ell_x_preferred":[
        "\u039a\u03ad\u03bb\u03c3\u03bf"
    ],
    "name:eng_x_preferred":[
        "Kelso"
    ],
    "name:fra_x_preferred":[
        "Kelso"
    ],
    "name:ita_x_preferred":[
        "Kelso"
    ],
    "name:kor_x_preferred":[
        "\ucf08\uc18c"
    ],
    "name:mlg_x_preferred":[
        "Kelso"
    ],
    "name:nld_x_preferred":[
        "Kelso"
    ],
    "name:pol_x_preferred":[
        "Kelso"
    ],
    "name:por_x_preferred":[
        "Kelso"
    ],
    "name:rus_x_preferred":[
        "\u041a\u0435\u043b\u0441\u043e"
    ],
    "name:sco_x_preferred":[
        "Kelso"
    ],
    "name:srp_x_preferred":[
        "\u041a\u0435\u043b\u0441\u043e"
    ],
    "name:swe_x_preferred":[
        "Kelso"
    ],
    "name:ukr_x_preferred":[
        "\u041a\u0435\u043b\u0441\u043e"
    ],
    "name:vol_x_preferred":[
        "Kelso"
    ],
    "qs_pg:aaroncc":"AU",
    "qs_pg:gn_country":"AU",
    "qs_pg:gn_fcode":"PPL",
    "qs_pg:gn_pop":168,
    "qs_pg:name":"Kelso",
    "qs_pg:name_adm0":"Australia",
    "qs_pg:name_adm1":"Tasmania",
    "qs_pg:photos_9k":1,
    "qs_pg:photos_9r":1,
    "qs_pg:photos_all":4,
    "qs_pg:photos_sr":0,
    "qs_pg:pop_sr":1,
    "qs_pg:qs_pg_placetype":"locality",
    "qs_pg:qs_pg_placetype_gp":"Town",
    "qs_pg:woe_adm0":23424748,
    "woe:adm0_id":23424748,
    "woe:name_adm0":"Australia",
    "woe:name_adm1":"Tasmania",
    "woe:placetype":"Town",
    "wof:name":"Kelso",
    "wof:placetype":"locality",
    "wof:population":168
},
  "geometry": {"coordinates":[146.80000000000001,-41.11667],"type":"Point"}
}