{
  "type": "Feature",
  "properties": {
    "gn:admin1_code":"7.0",
    "gn:admin2_code":"26610.0",
    "gn:asciiname":"Kooloonong",
    "gn:country_code":"AU",
    "gn:dem":63,
    "gn:feature_class":"P",
    "gn:feature_code":"PPL",
    "gn:name":"Kooloonong",
    "gn:population":0,
    "gn:timezone":"Australia/Melbourne",
    "iso:country":"AU",
    "wof:name":"Kooloonong",
    "wof:placetype":"locality"
},
  "geometry": {"coordinates":[143.14588999999995,-34.87738],"type":"Point"}
}