{
  "type": "Feature",
  "properties": {
    "gn:admin1_code":"8.0",
    "gn:admin2_code":"57420.0",
    "gn:asciiname":"Maydon",
    "gn:country_code":"AU",
    "gn:dem":124,
    "gn:feature_class":"P",
    "gn:feature_code":"PPL",
    "gn:name":"Maydon",
    "gn:population":0,
    "gn:timezone":"Australia/Perth",
    "iso:country":"AU",
    "name:eng_x_preferred":[
        "Maydon"
    ],
    "wof:name":"Maydon",
    "wof:placetype":"locality"
},
  "geometry": {"coordinates":[120.22387999999999,-33.61901],"type":"Point"}
}