{
  "type": "Feature",
  "properties": {
    "gn:admin1_code":"4.0",
    "gn:admin2_code":"32270.0",
    "gn:asciiname":"Tryphinia",
    "gn:country_code":"AU",
    "gn:dem":123,
    "gn:feature_class":"P",
    "gn:feature_code":"PPL",
    "gn:name":"Tryphinia",
    "gn:population":0,
    "gn:timezone":"Australia/Brisbane",
    "iso:country":"AU",
    "name:eng_x_preferred":[
        "Tryphinia"
    ],
    "wof:name":"Tryphinia",
    "wof:placetype":"locality"
},
  "geometry": {"coordinates":[149.51786999999999,-23.67671],"type":"Point"}
}