{
  "type": "Feature",
  "properties": {
    "gn:admin1_code":"04",
    "gn:admin2_code":"31820.0",
    "gn:asciiname":"Electra",
    "gn:country_code":"AU",
    "gn:dem":33,
    "gn:feature_class":"P",
    "gn:feature_code":"PPL",
    "gn:name":"Electra",
    "gn:population":0,
    "gn:timezone":"Australia/Brisbane",
    "iso:country":"AU",
    "wof:name":"Electra",
    "wof:placetype":"locality"
},
  "geometry": {"coordinates":[152.11626999999999,-24.97528],"type":"Point"}
}