{
  "type": "Feature",
  "properties": {
    "gn:admin1_code":"2.0",
    "gn:admin2_code":"10550.0",
    "gn:asciiname":"Mogilla",
    "gn:country_code":"AU",
    "gn:dem":205,
    "gn:feature_class":"P",
    "gn:feature_code":"PPL",
    "gn:name":"Mogilla",
    "gn:population":0,
    "gn:timezone":"Australia/Sydney",
    "iso:country":"AU",
    "wof:name":"Mogilla",
    "wof:placetype":"locality"
},
  "geometry": {"coordinates":[149.58459999999999,-36.6985],"type":"Point"}
}