{
  "type": "Feature",
  "properties": {
    "gn:admin1_code":"4.0",
    "gn:admin2_code":"37400.0",
    "gn:asciiname":"Black Rock Yard",
    "gn:country_code":"AU",
    "gn:dem":142,
    "gn:feature_class":"P",
    "gn:feature_code":"PPL",
    "gn:name":"Black Rock Yard",
    "gn:population":0,
    "gn:timezone":"Australia/Brisbane",
    "iso:country":"AU",
    "name:eng_x_preferred":[
        "Black Rock Yard"
    ],
    "wof:name":"Black Rock Yard",
    "wof:placetype":"locality"
},
  "geometry": {"coordinates":[141.94498999999999,-23.64616],"type":"Point"}
}