{
  "type": "Feature",
  "properties": {
    "gn:admin1_code":"2.0",
    "gn:admin2_code":"13400.0",
    "gn:asciiname":"Bunyah",
    "gn:country_code":"AU",
    "gn:dem":72,
    "gn:feature_class":"P",
    "gn:feature_code":"PPL",
    "gn:name":"Bunyah",
    "gn:population":0,
    "gn:timezone":"Australia/Sydney",
    "iso:country":"AU",
    "wof:name":"Bunyah",
    "wof:placetype":"locality"
},
  "geometry": {"coordinates":[152.21666999999999,-32.16667],"type":"Point"}
}