{
  "type": "Feature",
  "properties": {
    "gn:admin1_code":"2.0",
    "gn:admin2_code":"13800.0",
    "gn:asciiname":"Comleroy",
    "gn:cc2":"AU",
    "gn:country_code":"AU",
    "gn:dem":148,
    "gn:feature_class":"P",
    "gn:feature_code":"PPL",
    "gn:name":"Comleroy",
    "gn:population":0,
    "gn:timezone":"Australia/Sydney",
    "iso:country":"AU",
    "name:und_x_variant":[
        "Comleroy Road",
        "Comleroy"
    ],
    "wof:name":"Comleroy",
    "wof:placetype":"locality"
},
  "geometry": {"coordinates":[150.68333000000001,-33.53333],"type":"Point"}
}