{
  "type": "Feature",
  "properties": {
    "gn:admin1_code":"2.0",
    "gn:admin2_code":"11600.0",
    "gn:asciiname":"Boorga",
    "gn:country_code":"AU",
    "gn:dem":142,
    "gn:feature_class":"P",
    "gn:feature_code":"PPL",
    "gn:name":"Boorga",
    "gn:population":0,
    "gn:timezone":"Australia/Sydney",
    "iso:country":"AU",
    "wof:name":"Boorga",
    "wof:placetype":"locality"
},
  "geometry": {"coordinates":[146.02101000000005,-34.03262],"type":"Point"}
}