{
  "type": "Feature",
  "properties": {
    "gn:admin1_code":"7",
    "gn:admin2_code":"23940",
    "gn:asciiname":"Serpentine",
    "gn:country_code":"AU",
    "gn:dem":118,
    "gn:feature_class":"P",
    "gn:feature_code":"PPL",
    "gn:name":"Serpentine",
    "gn:population":0,
    "gn:timezone":"Australia/Melbourne",
    "iso:country":"AU",
    "name:nld_x_preferred":[
        "Serpentine"
    ],
    "wof:name":"Serpentine",
    "wof:placetype":"locality"
},
  "geometry": {"coordinates":[143.98333,-36.43333],"type":"Point"}
}