{
  "type": "Feature",
  "properties": {
    "gn:admin1_code":"3.0",
    "gn:admin2_code":"74660.0",
    "gn:asciiname":"Nabbarla Kunindabba",
    "gn:country_code":"AU",
    "gn:dem":18,
    "gn:feature_class":"P",
    "gn:feature_code":"PPL",
    "gn:name":"Nabbarla Kunindabba",
    "gn:population":0,
    "gn:timezone":"Australia/Darwin",
    "iso:country":"AU",
    "wof:name":"Nabbarla Kunindabba",
    "wof:placetype":"locality"
},
  "geometry": {"coordinates":[134.40312,-12.06356],"type":"Point"}
}