{
  "type": "Feature",
  "properties": {
    "gn:admin1_code":"2.0",
    "gn:admin2_code":"17450.0",
    "gn:asciiname":"Glenbrook",
    "gn:country_code":"AU",
    "gn:dem":523,
    "gn:feature_class":"P",
    "gn:feature_code":"PPL",
    "gn:name":"Glenbrook",
    "gn:population":0,
    "gn:timezone":"Australia/Sydney",
    "iso:country":"AU",
    "name:ceb_x_preferred":[
        "Glenbrook"
    ],
    "name:deu_x_preferred":[
        "Glenbrook"
    ],
    "name:eng_x_preferred":[
        "Glenbrook"
    ],
    "name:swe_x_preferred":[
        "Glenbrook"
    ],
    "wof:name":"Glenbrook",
    "wof:placetype":"locality"
},
  "geometry": {"coordinates":[148.0864,-35.9174],"type":"Point"}
}