{
  "type": "Feature",
  "properties": {
    "gn:admin1_code":"7",
    "gn:admin2_code":"21370",
    "gn:asciiname":"Tennyson",
    "gn:country_code":"AU",
    "gn:dem":106,
    "gn:feature_class":"P",
    "gn:feature_code":"PPL",
    "gn:name":"Tennyson",
    "gn:population":0,
    "gn:timezone":"Australia/Melbourne",
    "iso:country":"AU",
    "wof:name":"Tennyson",
    "wof:placetype":"locality"
},
  "geometry": {"coordinates":[144.43333000000001,-36.28333],"type":"Point"}
}