{
  "type": "Feature",
  "properties": {
    "gn:admin1_code":"2.0",
    "gn:admin2_code":"10550.0",
    "gn:asciiname":"Gourlay",
    "gn:country_code":"AU",
    "gn:dem":163,
    "gn:feature_class":"P",
    "gn:feature_code":"PPL",
    "gn:name":"Gourlay",
    "gn:population":0,
    "gn:timezone":"Australia/Sydney",
    "iso:country":"AU",
    "wof:name":"Gourlay",
    "wof:placetype":"locality"
},
  "geometry": {"coordinates":[149.65000000000001,-36.68333],"type":"Point"}
}