{
  "type": "Feature",
  "properties": {
    "gn:admin1_code":"8",
    "gn:admin2_code":"54900",
    "gn:asciiname":"Beenong",
    "gn:country_code":"AU",
    "gn:dem":280,
    "gn:feature_class":"P",
    "gn:feature_code":"PPL",
    "gn:name":"Beenong",
    "gn:population":0,
    "gn:timezone":"Australia/Perth",
    "iso:country":"AU",
    "name:eng_x_preferred":[
        "Beenong"
    ],
    "wof:name":"Beenong",
    "wof:placetype":"locality"
},
  "geometry": {"coordinates":[118.58526000000001,-33.04496],"type":"Point"}
}