{
  "type": "Feature",
  "properties": {
    "gn:admin1_code":"7.0",
    "gn:admin2_code":"26170.0",
    "gn:asciiname":"Korumburra South",
    "gn:country_code":"AU",
    "gn:dem":193,
    "gn:feature_class":"P",
    "gn:feature_code":"PPL",
    "gn:name":"Korumburra South",
    "gn:population":0,
    "gn:timezone":"Australia/Melbourne",
    "iso:country":"AU",
    "wof:name":"Korumburra South",
    "wof:placetype":"locality"
},
  "geometry": {"coordinates":[145.84999999999999,-38.46667],"type":"Point"}
}