{
  "type": "Feature",
  "properties": {
    "iso:country":"AU",
    "name:eng_x_preferred":[
        "Estella"
    ],
    "name:spa_x_preferred":[
        "Estella"
    ],
    "name:unk_x_variant":[
        "Estella"
    ],
    "qs:gn_adm0_cc":"AU",
    "qs:gn_fcode":"PPL",
    "qs:gn_local":2145110,
    "qs:gn_nam_loc":"Wagga Wagga, Wagga Wagga, New South Wales, AU",
    "qs:gn_namadm1":"02",
    "qs:gn_name":"Estella",
    "qs:local_max":1073,
    "qs:local_sum":2457,
    "qs:localhoods":8,
    "qs:name":"Estella",
    "qs:name_adm0":"Australia",
    "qs:name_adm1":"New South Wales",
    "qs:name_adm2":"Wagga Wagga",
    "qs:name_local":"Wagga Wagga",
    "qs:photo_max":83,
    "qs:photo_sum":119,
    "qs:placetype":"Suburb",
    "qs:quad_count":13,
    "qs:woe_adm0":23424748,
    "qs:woe_adm1":2344700,
    "qs:woe_adm2":55863778,
    "qs:woe_lau":0,
    "qs:woe_local":1106324,
    "qs:woe_ver":"7.10.0",
    "wof:lang":[
        "eng"
    ],
    "wof:name":"Estella",
    "wof:placetype":"neighbourhood"
},
  "geometry": {"coordinates":[147.34892600000001,-35.06158],"type":"Point"}
}