{
  "type": "Feature",
  "properties": {
    "iso:country":"AU",
    "name:ceb_x_preferred":[
        "Kingswood"
    ],
    "name:cym_x_preferred":[
        "Kingswood"
    ],
    "name:deu_x_preferred":[
        "Kingswood"
    ],
    "name:eng_x_preferred":[
        "Kingswood"
    ],
    "name:fra_x_preferred":[
        "Kingswood"
    ],
    "name:ita_x_preferred":[
        "Kingswood"
    ],
    "name:kor_x_preferred":[
        "\ud0b9\uc2a4\uc6b0\ub4dc"
    ],
    "name:nld_x_preferred":[
        "Kingswood"
    ],
    "name:pol_x_preferred":[
        "Kingswood"
    ],
    "name:spa_x_preferred":[
        "Kingswood"
    ],
    "name:swe_x_preferred":[
        "Kingswood"
    ],
    "qs:gn_adm0_cc":"AU",
    "qs:gn_local":2078025,
    "qs:local_max":18505,
    "qs:local_sum":99726,
    "qs:localhoods":191,
    "qs:name":"Kingswood",
    "qs:name_adm0":"Australia",
    "qs:name_adm1":"South Australia",
    "qs:name_adm2":"City of Mitcham",
    "qs:name_local":"Adelaide",
    "qs:photo_max":158,
    "qs:photo_sum":353,
    "qs:placetype":"Suburb",
    "qs:quad_count":4,
    "qs:woe_adm0":23424748,
    "qs:woe_adm1":2344703,
    "qs:woe_adm2":55864116,
    "qs:woe_lau":0,
    "qs:woe_local":1099805,
    "qs:woe_ver":"7.10.0",
    "wof:lang":[
        "eng"
    ],
    "wof:name":"Kingswood",
    "wof:placetype":"neighbourhood"
},
  "geometry": {"coordinates":[138.61786000000001,-34.97171],"type":"Point"}
}