{
  "type": "Feature",
  "properties": {
    "gn:admin1_code":"5",
    "gn:admin2_code":"42750",
    "gn:asciiname":"Wisanger",
    "gn:country_code":"AU",
    "gn:dem":108,
    "gn:feature_class":"P",
    "gn:feature_code":"PPL",
    "gn:name":"Wisanger",
    "gn:population":0,
    "gn:timezone":"Australia/Adelaide",
    "iso:country":"AU",
    "wof:name":"Wisanger",
    "wof:placetype":"locality"
},
  "geometry": {"coordinates":[137.45596,-35.61551],"type":"Point"}
}