{
  "type": "Feature",
  "properties": {
    "gn:country":"AU",
    "gn:fcode":"PPL",
    "gn:population":449,
    "iso:country":"AU",
    "name:ast_x_preferred":[
        "Mumbil"
    ],
    "name:ceb_x_preferred":[
        "Mumbil"
    ],
    "name:eng_x_preferred":[
        "Mumbil"
    ],
    "name:fas_x_preferred":[
        "\u0645\u0648\u0645\u0628\u06cc\u0644"
    ],
    "name:fra_x_preferred":[
        "Mumbil"
    ],
    "name:nld_x_preferred":[
        "Mumbil"
    ],
    "name:swe_x_preferred":[
        "Mumbil"
    ],
    "qs_pg:aaroncc":"AU",
    "qs_pg:gn_country":"AU",
    "qs_pg:gn_fcode":"PPL",
    "qs_pg:gn_pop":449,
    "qs_pg:name":"Mumbil",
    "qs_pg:name_adm0":"Australia",
    "qs_pg:name_adm1":"New South Wales",
    "qs_pg:photos_9k":1,
    "qs_pg:photos_9r":1,
    "qs_pg:photos_all":16,
    "qs_pg:photos_sr":0,
    "qs_pg:pop_sr":2,
    "qs_pg:qs_pg_placetype":"locality",
    "qs_pg:qs_pg_placetype_gp":"Town",
    "qs_pg:woe_adm0":23424748,
    "woe:adm0_id":23424748,
    "woe:name_adm0":"Australia",
    "woe:name_adm1":"New South Wales",
    "woe:placetype":"Town",
    "wof:name":"Mumbil",
    "wof:placetype":"locality",
    "wof:population":449
},
  "geometry": {"coordinates":[149.05000000000001,-32.71667],"type":"Point"}
}