{
  "type": "Feature",
  "properties": {
    "iso:country":"AU",
    "name:eng_x_preferred":[
        "Regent West"
    ],
    "qs:gn_adm0_cc":"AU",
    "qs:gn_local":2158177,
    "qs:local_max":22745,
    "qs:local_sum":338594,
    "qs:localhoods":407,
    "qs:name":"Regent West",
    "qs:name_adm0":"Australia",
    "qs:name_adm1":"Victoria",
    "qs:name_adm2":"City of Darebin",
    "qs:name_local":"Melbourne",
    "qs:photo_max":159,
    "qs:photo_sum":477,
    "qs:placetype":"Suburb",
    "qs:quad_count":22,
    "qs:woe_adm0":23424748,
    "qs:woe_adm1":2344705,
    "qs:woe_adm2":55864005,
    "qs:woe_lau":0,
    "qs:woe_local":1103816,
    "qs:woe_ver":"7.10.0",
    "wof:lang":[
        "eng"
    ],
    "wof:name":"Regent West",
    "wof:placetype":"neighbourhood"
},
  "geometry": {"coordinates":[145.01965300000001,-37.750178],"type":"Point"}
}