{
  "type": "Feature",
  "properties": {
    "gn:admin1_code":"4.0",
    "gn:admin2_code":"33360.0",
    "gn:asciiname":"Amos Quarries",
    "gn:country_code":"AU",
    "gn:dem":26,
    "gn:feature_class":"P",
    "gn:feature_code":"PPL",
    "gn:name":"Amos Quarries",
    "gn:population":0,
    "gn:timezone":"Australia/Brisbane",
    "iso:country":"AU",
    "wof:name":"Amos Quarries",
    "wof:placetype":"locality"
},
  "geometry": {"coordinates":[150.83333000000005,-23.75],"type":"Point"}
}