{
  "type": "Feature",
  "properties": {
    "gn:admin1_code":"3.0",
    "gn:admin2_code":"71300.0",
    "gn:asciiname":"Gurjangan",
    "gn:country_code":"AU",
    "gn:dem":9,
    "gn:feature_class":"P",
    "gn:feature_code":"PPL",
    "gn:name":"Gurjangan",
    "gn:population":0,
    "gn:timezone":"Australia/Darwin",
    "iso:country":"AU",
    "wof:name":"Gurjangan",
    "wof:placetype":"locality"
},
  "geometry": {"coordinates":[136.81002000000001,-12.08475],"type":"Point"}
}