{
  "type": "Feature",
  "properties": {
    "gn:admin1_code":"7",
    "gn:admin2_code":"26610",
    "gn:asciiname":"Turoar",
    "gn:country_code":"AU",
    "gn:dem":61,
    "gn:feature_class":"P",
    "gn:feature_code":"PPL",
    "gn:name":"Turoar",
    "gn:population":0,
    "gn:timezone":"Australia/Melbourne",
    "iso:country":"AU",
    "wof:name":"Turoar",
    "wof:placetype":"locality"
},
  "geometry": {"coordinates":[143.05000000000001,-35.16667],"type":"Point"}
}