{
  "type": "Feature",
  "properties": {
    "gn:admin1_code":"4.0",
    "gn:admin2_code":"30410.0",
    "gn:asciiname":"Minnamorra",
    "gn:country_code":"AU",
    "gn:dem":337,
    "gn:feature_class":"P",
    "gn:feature_code":"PPL",
    "gn:name":"Minnamorra",
    "gn:population":0,
    "gn:timezone":"Australia/Brisbane",
    "iso:country":"AU",
    "name:eng_x_preferred":[
        "Minnamorra"
    ],
    "wof:name":"Minnamorra",
    "wof:placetype":"locality"
},
  "geometry": {"coordinates":[145.85120000000001,-23.4064],"type":"Point"}
}