{
  "type": "Feature",
  "properties": {
    "gn:admin1_code":"8",
    "gn:admin2_code":"59030",
    "gn:asciiname":"North Walgoolan",
    "gn:country_code":"AU",
    "gn:dem":303,
    "gn:feature_class":"P",
    "gn:feature_code":"PPL",
    "gn:name":"North Walgoolan",
    "gn:population":0,
    "gn:timezone":"Australia/Perth",
    "iso:country":"AU",
    "name:eng_x_preferred":[
        "North Walgoolan"
    ],
    "wof:name":"North Walgoolan",
    "wof:placetype":"locality"
},
  "geometry": {"coordinates":[118.59713000000001,-31.18468],"type":"Point"}
}