{
  "type": "Feature",
  "properties": {
    "gn:admin1_code":"4.0",
    "gn:admin2_code":"35760.0",
    "gn:asciiname":"Benvenue",
    "gn:country_code":"AU",
    "gn:dem":180,
    "gn:feature_class":"P",
    "gn:feature_code":"PPL",
    "gn:name":"Benvenue",
    "gn:population":0,
    "gn:timezone":"Australia/Brisbane",
    "iso:country":"AU",
    "name:eng_x_preferred":[
        "Benvenue"
    ],
    "wof:name":"Benvenue",
    "wof:placetype":"locality"
},
  "geometry": {"coordinates":[151.37321,-25.85371],"type":"Point"}
}