{
  "type": "Feature",
  "properties": {
    "gn:admin1_code":"8",
    "gn:admin2_code":"55250",
    "gn:asciiname":"Mundiwindi",
    "gn:country_code":"AU",
    "gn:dem":573,
    "gn:feature_class":"P",
    "gn:feature_code":"PPL",
    "gn:name":"Mundiwindi",
    "gn:population":0,
    "gn:timezone":"Australia/Perth",
    "iso:country":"AU",
    "name:und_x_variant":[
        "Mundawindi",
        "Mundiwindi"
    ],
    "wof:name":"Mundiwindi",
    "wof:placetype":"locality"
},
  "geometry": {"coordinates":[120.24370999999999,-23.79498],"type":"Point"}
}