{
  "type": "Feature",
  "properties": {
    "gn:admin1_code":"8",
    "gn:admin2_code":"51540",
    "gn:asciiname":"Gladstone",
    "gn:country_code":"AU",
    "gn:dem":9,
    "gn:feature_class":"P",
    "gn:feature_code":"PPL",
    "gn:name":"Gladstone",
    "gn:population":0,
    "gn:timezone":"Australia/Perth",
    "iso:country":"AU",
    "name:hun_x_preferred":[
        "Gladstone"
    ],
    "wof:name":"Gladstone",
    "wof:placetype":"locality"
},
  "geometry": {"coordinates":[114.25373999999999,-25.95607],"type":"Point"}
}