{
  "type": "Feature",
  "properties": {
    "gn:admin1_code":"4.0",
    "gn:admin2_code":"37400.0",
    "gn:asciiname":"Cathedral Hill",
    "gn:country_code":"AU",
    "gn:dem":212,
    "gn:feature_class":"P",
    "gn:feature_code":"PPL",
    "gn:name":"Cathedral Hill",
    "gn:population":0,
    "gn:timezone":"Australia/Brisbane",
    "iso:country":"AU",
    "name:eng_x_preferred":[
        "Cathedral Hill"
    ],
    "wof:name":"Cathedral Hill",
    "wof:placetype":"locality"
},
  "geometry": {"coordinates":[142.19658000000001,-22.00411],"type":"Point"}
}