{
  "type": "Feature",
  "properties": {
    "iso:country":"AU",
    "name:deu_x_preferred":[
        "Dendy"
    ],
    "name:rus_x_preferred":[
        "\u0414\u0435\u043d\u0434\u0438"
    ],
    "name:spa_x_preferred":[
        "Dendy"
    ],
    "name:vie_x_preferred":[
        "Dendy"
    ],
    "qs_pg:aaroncc":"AU",
    "qs_pg:name":"Dendy",
    "qs_pg:name_adm0":"Australia",
    "qs_pg:name_adm1":"Victoria",
    "qs_pg:photos":119,
    "qs_pg:photos_1k":24,
    "qs_pg:photos_9k":1,
    "qs_pg:photos_9r":3,
    "qs_pg:photos_all":119,
    "qs_pg:photos_sr":3,
    "qs_pg:pop_sr":0,
    "qs_pg:qs_pg_placetype":"neighbourhood",
    "qs_pg:qs_pg_placetype_gp":"Suburb",
    "qs_pg:woe_adm0":23424748,
    "woe:adm0_id":23424748,
    "woe:name_adm0":"Australia",
    "woe:name_adm1":"Victoria",
    "woe:placetype":"Suburb",
    "wof:name":"Dendy",
    "wof:placetype":"neighbourhood"
},
  "geometry": {"coordinates":[145.011291,-37.920393],"type":"Point"}
}