{
  "type": "Feature",
  "properties": {
    "gn:admin1_code":"3.0",
    "gn:admin2_code":"72330.0",
    "gn:asciiname":"Fifteen Mile Yard",
    "gn:country_code":"AU",
    "gn:dem":603,
    "gn:feature_class":"P",
    "gn:feature_code":"PPL",
    "gn:name":"Fifteen Mile Yard",
    "gn:population":0,
    "gn:timezone":"Australia/Darwin",
    "iso:country":"AU",
    "wof:name":"Fifteen Mile Yard",
    "wof:placetype":"locality"
},
  "geometry": {"coordinates":[132.64916000000002,-23.81642],"type":"Point"}
}