{
  "type": "Feature",
  "properties": {
    "gn:gn_country":"AU",
    "gn:gn_fcode":"PPL",
    "gn:gn_pop":185,
    "gn:population":185,
    "iso:country":"AU",
    "name:ceb_x_preferred":[
        "Moonan Flat"
    ],
    "name:eng_x_preferred":[
        "Moonan Flat"
    ],
    "name:swe_x_preferred":[
        "Moonan Flat"
    ],
    "name:unk_x_variant":[
        "Macqueen"
    ],
    "qs_pg:aaroncc":"AU",
    "qs_pg:gn_country":"AU",
    "qs_pg:gn_fcode":"PPL",
    "qs_pg:gn_pop":185,
    "qs_pg:name":"Moonan Flat",
    "qs_pg:name_adm0":"Australia",
    "qs_pg:name_adm1":"New South Wales",
    "qs_pg:photos":21,
    "qs_pg:photos_1k":4,
    "qs_pg:photos_9k":1,
    "qs_pg:photos_9r":1,
    "qs_pg:photos_all":21,
    "qs_pg:photos_sr":1,
    "qs_pg:pop_sr":1,
    "qs_pg:qs_pg_placetype":"locality",
    "qs_pg:qs_pg_placetype_gp":"Town",
    "qs_pg:woe_adm0":23424748,
    "woe:adm0_id":23424748,
    "woe:name_adm0":"Australia",
    "woe:name_adm1":"New South Wales",
    "woe:placetype":"Town",
    "wof:name":"Moonan Flat",
    "wof:placetype":"locality",
    "wof:population":128
},
  "geometry": {"coordinates":[151.25,-31.91667],"type":"Point"}
}