{
  "type": "Feature",
  "properties": {
    "gn:admin1_code":"4.0",
    "gn:admin2_code":"33200.0",
    "gn:asciiname":"Tamworth",
    "gn:country_code":"AU",
    "gn:dem":267,
    "gn:feature_class":"P",
    "gn:feature_code":"PPL",
    "gn:name":"Tamworth",
    "gn:population":0,
    "gn:timezone":"Australia/Brisbane",
    "iso:country":"AU",
    "name:eng_x_preferred":[
        "Tamworth"
    ],
    "wof:name":"Tamworth",
    "wof:placetype":"locality"
},
  "geometry": {"coordinates":[143.66852,-21.04574],"type":"Point"}
}