{
  "type": "Feature",
  "properties": {
    "gn:admin1_code":"4.0",
    "gn:admin2_code":"33200.0",
    "gn:asciiname":"Tamworth",
    "gn:country_code":"AU",
    "gn:dem":267,
    "gn:feature_class":"P",
    "gn:feature_code":"PPL",
    "gn:name":"Tamworth",
    "gn:population":0,
    "gn:timezone":"Australia/Brisbane",
    "iso:country":"AU",
    "name:ceb_x_preferred":[
        "Tamworth"
    ],
    "name:cym_x_preferred":[
        "Tamworth"
    ],
    "name:dan_x_preferred":[
        "Tamworth"
    ],
    "name:deu_x_preferred":[
        "Tamworth"
    ],
    "name:eng_x_preferred":[
        "Tamworth"
    ],
    "name:fra_x_preferred":[
        "Tamworth"
    ],
    "name:ita_x_preferred":[
        "Tamworth"
    ],
    "name:jpn_x_preferred":[
        "\u30bf\u30e0\u30ef\u30fc\u30b9"
    ],
    "name:mlg_x_preferred":[
        "Tamworth"
    ],
    "name:nld_x_preferred":[
        "Tamworth"
    ],
    "name:pol_x_preferred":[
        "Tamworth"
    ],
    "name:rus_x_preferred":[
        "\u0422\u0430\u043c\u0443\u043e\u0440\u0442"
    ],
    "name:san_x_preferred":[
        "\u091f\u093e\u092e\u0935\u094b\u0930\u094d\u0925"
    ],
    "name:spa_x_preferred":[
        "Tamworth"
    ],
    "name:swe_x_preferred":[
        "Tamworth"
    ],
    "name:vol_x_preferred":[
        "Tamworth"
    ],
    "wof:name":"Tamworth",
    "wof:placetype":"locality"
},
  "geometry": {"coordinates":[143.66852,-21.04574],"type":"Point"}
}