{
  "type": "Feature",
  "properties": {
    "gn:admin1_code":"4.0",
    "gn:admin2_code":"30410.0",
    "gn:asciiname":"Nebea",
    "gn:country_code":"AU",
    "gn:dem":374,
    "gn:feature_class":"P",
    "gn:feature_code":"PPL",
    "gn:name":"Nebea",
    "gn:population":0,
    "gn:timezone":"Australia/Brisbane",
    "iso:country":"AU",
    "name:eng_x_preferred":[
        "Nebea"
    ],
    "wof:name":"Nebea",
    "wof:placetype":"locality"
},
  "geometry": {"coordinates":[147.0299,-23.44237],"type":"Point"}
}