{
  "type": "Feature",
  "properties": {
    "gn:admin1_code":"2",
    "gn:admin2_code":"16610",
    "gn:asciiname":"Wyan",
    "gn:country_code":"AU",
    "gn:dem":77,
    "gn:feature_class":"P",
    "gn:feature_code":"PPL",
    "gn:name":"Wyan",
    "gn:population":0,
    "gn:timezone":"Australia/Sydney",
    "iso:country":"AU",
    "wof:name":"Wyan",
    "wof:placetype":"locality"
},
  "geometry": {"coordinates":[152.86667,-29.06667],"type":"Point"}
}