{
  "type": "Feature",
  "properties": {
    "gn:gn_country":"AU",
    "gn:gn_fcode":"PPL",
    "gn:gn_pop":0,
    "iso:country":"AU",
    "name:cat_x_preferred":[
        "Somerton"
    ],
    "name:ceb_x_preferred":[
        "Somerton"
    ],
    "name:dan_x_preferred":[
        "Somerton"
    ],
    "name:deu_x_preferred":[
        "Somerton"
    ],
    "name:eng_x_preferred":[
        "Somerton"
    ],
    "name:fra_x_preferred":[
        "Somerton"
    ],
    "name:ita_x_preferred":[
        "Somerton"
    ],
    "name:nld_x_preferred":[
        "Somerton"
    ],
    "name:pol_x_preferred":[
        "Somerton"
    ],
    "name:por_x_preferred":[
        "Somerton"
    ],
    "name:spa_x_preferred":[
        "Somerton"
    ],
    "name:srp_x_preferred":[
        "\u0421\u0430\u043c\u0435\u0440\u0442\u043e\u043d"
    ],
    "name:swe_x_preferred":[
        "Somerton"
    ],
    "name:vol_x_preferred":[
        "Somerton"
    ],
    "qs_pg:aaroncc":"AU",
    "qs_pg:gn_country":"AU",
    "qs_pg:gn_fcode":"PPL",
    "qs_pg:gn_pop":0,
    "qs_pg:name":"Somerton",
    "qs_pg:name_adm0":"Australia",
    "qs_pg:name_adm1":"New South Wales",
    "qs_pg:photos_9k":1,
    "qs_pg:photos_9r":4,
    "qs_pg:photos_all":190,
    "qs_pg:photos_sr":0,
    "qs_pg:pop_sr":4,
    "qs_pg:qs_pg_placetype":"locality",
    "qs_pg:qs_pg_placetype_gp":"Town",
    "qs_pg:woe_adm0":23424748,
    "woe:adm0_id":23424748,
    "woe:name_adm0":"Australia",
    "woe:name_adm1":"New South Wales",
    "woe:placetype":"Town",
    "wof:name":"Somerton",
    "wof:placetype":"locality",
    "wof:population":277
},
  "geometry": {"coordinates":[150.63333,-30.95],"type":"Point"}
}