{
  "type": "Feature",
  "properties": {
    "gn:admin1_code":"2.0",
    "gn:admin2_code":"15850.0",
    "gn:asciiname":"Gin Gin",
    "gn:country_code":"AU",
    "gn:dem":211,
    "gn:feature_class":"P",
    "gn:feature_code":"PPL",
    "gn:name":"Gin Gin",
    "gn:population":0,
    "gn:timezone":"Australia/Sydney",
    "iso:country":"AU",
    "name:eng_x_preferred":[
        "Gin Gin"
    ],
    "wof:name":"Gin Gin",
    "wof:placetype":"locality"
},
  "geometry": {"coordinates":[148.0898,-31.9116],"type":"Point"}
}