{
  "type": "Feature",
  "properties": {
    "gn:admin1_code":"3.0",
    "gn:admin2_code":"73600.0",
    "gn:asciiname":"Wumajbarr",
    "gn:country_code":"AU",
    "gn:dem":9,
    "gn:feature_class":"P",
    "gn:feature_code":"PPL",
    "gn:name":"Wumajbarr",
    "gn:population":0,
    "gn:timezone":"Australia/Darwin",
    "iso:country":"AU",
    "wof:name":"Wumajbarr",
    "wof:placetype":"locality"
},
  "geometry": {"coordinates":[135.69154,-14.16577],"type":"Point"}
}