{
  "type": "Feature",
  "properties": {
    "gn:admin1_code":"6",
    "gn:admin2_code":"61810",
    "gn:asciiname":"South Springfield",
    "gn:country_code":"AU",
    "gn:dem":237,
    "gn:feature_class":"P",
    "gn:feature_code":"PPL",
    "gn:name":"South Springfield",
    "gn:population":0,
    "gn:timezone":"Australia/Hobart",
    "iso:country":"AU",
    "name:eng_x_preferred":[
        "South Springfield"
    ],
    "wof:name":"South Springfield",
    "wof:placetype":"locality"
},
  "geometry": {"coordinates":[147.50811000000004,-41.25155],"type":"Point"}
}