{
  "type": "Feature",
  "properties": {
    "gn:admin1_code":"5",
    "gn:admin2_code":"43080",
    "gn:asciiname":"Galga",
    "gn:country_code":"AU",
    "gn:dem":73,
    "gn:feature_class":"P",
    "gn:feature_code":"PPL",
    "gn:name":"Galga",
    "gn:population":0,
    "gn:timezone":"Australia/Adelaide",
    "iso:country":"AU",
    "name:eng_x_preferred":[
        "Galga"
    ],
    "wof:name":"Galga",
    "wof:placetype":"locality"
},
  "geometry": {"coordinates":[139.96459999999999,-34.69937],"type":"Point"}
}