{
  "type": "Feature",
  "properties": {
    "gn:gn_country":"AU",
    "gn:gn_fcode":"PPL",
    "gn:gn_pop":0,
    "iso:country":"AU",
    "name:eng_x_preferred":[
        "Swifts Creek"
    ],
    "name:fra_x_preferred":[
        "Swifts Creek"
    ],
    "name:jpn_x_preferred":[
        "\u30b9\u30a6\u30a3\u30d5\u30c4\u30fb\u30af\u30ea\u30fc\u30af"
    ],
    "name:nld_x_preferred":[
        "Swifts Creek"
    ],
    "name:swe_x_preferred":[
        "Swifts Creek"
    ],
    "name:unk_x_variant":[
        "Swifts Creek Junction"
    ],
    "name:zho_x_preferred":[
        "\u96e8\u71d5\u6eaa"
    ],
    "qs_pg:aaroncc":"AU",
    "qs_pg:gn_country":"AU",
    "qs_pg:gn_fcode":"PPL",
    "qs_pg:gn_pop":0,
    "qs_pg:name":"Swifts Creek",
    "qs_pg:name_adm0":"Australia",
    "qs_pg:name_adm1":"Victoria",
    "qs_pg:photos":21,
    "qs_pg:photos_1k":4,
    "qs_pg:photos_9k":1,
    "qs_pg:photos_9r":1,
    "qs_pg:photos_all":21,
    "qs_pg:photos_sr":1,
    "qs_pg:pop_sr":0,
    "qs_pg:qs_pg_placetype":"locality",
    "qs_pg:qs_pg_placetype_gp":"Town",
    "qs_pg:woe_adm0":23424748,
    "woe:adm0_id":23424748,
    "woe:name_adm0":"Australia",
    "woe:name_adm1":"Victoria",
    "woe:placetype":"Town",
    "wof:name":"Swifts Creek",
    "wof:placetype":"locality"
},
  "geometry": {"coordinates":[147.71666999999999,-37.25],"type":"Point"}
}