{
  "type": "Feature",
  "properties": {
    "gn:admin1_code":"2.0",
    "gn:admin2_code":"14350.0",
    "gn:asciiname":"Beranghi",
    "gn:country_code":"AU",
    "gn:dem":3,
    "gn:feature_class":"P",
    "gn:feature_code":"PPL",
    "gn:name":"Beranghi",
    "gn:population":0,
    "gn:timezone":"Australia/Sydney",
    "iso:country":"AU",
    "wof:name":"Beranghi",
    "wof:placetype":"locality"
},
  "geometry": {"coordinates":[152.91666999999995,-31.21667],"type":"Point"}
}