{
  "type": "Feature",
  "properties": {
    "gn:admin1_code":"2",
    "gn:admin2_code":"17400",
    "gn:asciiname":"Tarban",
    "gn:country_code":"AU",
    "gn:dem":769,
    "gn:feature_class":"P",
    "gn:feature_code":"PPL",
    "gn:name":"Tarban",
    "gn:population":0,
    "gn:timezone":"Australia/Sydney",
    "iso:country":"AU",
    "wof:name":"Tarban",
    "wof:placetype":"locality"
},
  "geometry": {"coordinates":[151.90119999999999,-28.9818],"type":"Point"}
}