{
  "type": "Feature",
  "properties": {
    "gn:gn_country":"AU",
    "gn:gn_fcode":"PPL",
    "gn:gn_pop":261,
    "gn:population":261,
    "iso:country":"AU",
    "name:ceb_x_preferred":[
        "Carey Gully"
    ],
    "name:eng_x_preferred":[
        "Carey Gully"
    ],
    "name:fas_x_preferred":[
        "\u06a9\u0631\u06cc \u06af\u0627\u0644\u06cc"
    ],
    "name:fra_x_preferred":[
        "Carey Gully"
    ],
    "name:nld_x_preferred":[
        "Carey Gully"
    ],
    "name:swe_x_preferred":[
        "Carey Gully"
    ],
    "name:unk_x_variant":[
        "Carey's Gully"
    ],
    "qs_pg:aaroncc":"AU",
    "qs_pg:gn_country":"AU",
    "qs_pg:gn_fcode":"PPL",
    "qs_pg:gn_pop":261,
    "qs_pg:name":"Carey Gully",
    "qs_pg:name_adm0":"Australia",
    "qs_pg:name_adm1":"South Australia",
    "qs_pg:photos_9k":1,
    "qs_pg:photos_9r":1,
    "qs_pg:photos_all":15,
    "qs_pg:photos_sr":0,
    "qs_pg:pop_sr":2,
    "qs_pg:qs_pg_placetype":"locality",
    "qs_pg:qs_pg_placetype_gp":"Town",
    "qs_pg:woe_adm0":23424748,
    "woe:adm0_id":23424748,
    "woe:name_adm0":"Australia",
    "woe:name_adm1":"South Australia",
    "woe:placetype":"Town",
    "wof:name":"Carey Gully",
    "wof:placetype":"locality",
    "wof:population":414
},
  "geometry": {"coordinates":[138.76178999999999,-34.96468],"type":"Point"}
}