{
  "type": "Feature",
  "properties": {
    "gn:admin1_code":"7.0",
    "gn:admin2_code":"22110.0",
    "gn:asciiname":"Holstons",
    "gn:country_code":"AU",
    "gn:dem":441,
    "gn:feature_class":"P",
    "gn:feature_code":"PPL",
    "gn:name":"Holstons",
    "gn:population":0,
    "gn:timezone":"Australia/Melbourne",
    "iso:country":"AU",
    "name:eng_x_preferred":[
        "Holstons"
    ],
    "wof:name":"Holstons",
    "wof:placetype":"locality"
},
  "geometry": {"coordinates":[147.95498999999995,-37.42247],"type":"Point"}
}