{
  "type": "Feature",
  "properties": {
    "gn:admin1_code":"2",
    "gn:admin2_code":"11730",
    "gn:asciiname":"Whiteman Creek",
    "gn:country_code":"AU",
    "gn:dem":25,
    "gn:feature_class":"P",
    "gn:feature_code":"PPL",
    "gn:name":"Whiteman Creek",
    "gn:population":0,
    "gn:timezone":"Australia/Sydney",
    "iso:country":"AU",
    "wof:name":"Whiteman Creek",
    "wof:placetype":"locality"
},
  "geometry": {"coordinates":[152.88333,-29.58333],"type":"Point"}
}