{
  "type": "Feature",
  "properties": {
    "gn:admin1_code":"7.0",
    "gn:admin2_code":"26430.0",
    "gn:asciiname":"Locksley",
    "gn:country_code":"AU",
    "gn:dem":170,
    "gn:feature_class":"P",
    "gn:feature_code":"PPL",
    "gn:name":"Locksley",
    "gn:population":0,
    "gn:timezone":"Australia/Melbourne",
    "iso:country":"AU",
    "wof:name":"Locksley",
    "wof:placetype":"locality"
},
  "geometry": {"coordinates":[145.33333000000005,-36.83333],"type":"Point"}
}