{
  "type": "Feature",
  "properties": {
    "gn:admin1_code":"7",
    "gn:admin2_code":"22620",
    "gn:asciiname":"Woodvale",
    "gn:country_code":"AU",
    "gn:dem":158,
    "gn:feature_class":"P",
    "gn:feature_code":"PPL",
    "gn:name":"Woodvale",
    "gn:population":0,
    "gn:timezone":"Australia/Melbourne",
    "iso:country":"AU",
    "wof:name":"Woodvale",
    "wof:placetype":"locality"
},
  "geometry": {"coordinates":[144.21666999999999,-36.65],"type":"Point"}
}