{
  "type": "Feature",
  "properties": {
    "gn:admin1_code":"2",
    "gn:admin2_code":"15270",
    "gn:asciiname":"Spring Ridge",
    "gn:country_code":"AU",
    "gn:dem":571,
    "gn:feature_class":"P",
    "gn:feature_code":"PPL",
    "gn:name":"Spring Ridge",
    "gn:population":0,
    "gn:timezone":"Australia/Sydney",
    "iso:country":"AU",
    "name:ceb_x_preferred":[
        "Spring Ridge"
    ],
    "name:deu_x_preferred":[
        "Spring Ridge"
    ],
    "name:srp_x_preferred":[
        "\u0421\u043f\u0440\u0438\u043d\u0433 \u0420\u0438\u045f"
    ],
    "wof:name":"Spring Ridge",
    "wof:placetype":"locality"
},
  "geometry": {"coordinates":[149.34999999999999,-32.26667],"type":"Point"}
}