{
  "type": "Feature",
  "properties": {
    "gn:gn_country":"AU",
    "gn:gn_fcode":"PPL",
    "gn:gn_pop":0,
    "iso:country":"AU",
    "name:ara_x_preferred":[
        "\u0647\u064a\u0628\u0644"
    ],
    "name:dut_x_preferred":[
        "Hebel"
    ],
    "name:eng_x_preferred":[
        "Hebel"
    ],
    "name:fre_x_preferred":[
        "Hebel"
    ],
    "name:rus_x_preferred":[
        "\u0425\u0435\u0431\u0435\u043b"
    ],
    "qs_pg:aaroncc":"AU",
    "qs_pg:gn_country":"AU",
    "qs_pg:gn_fcode":"PPL",
    "qs_pg:gn_pop":0,
    "qs_pg:name":"Hebel",
    "qs_pg:name_adm0":"Australia",
    "qs_pg:name_adm1":"Queensland",
    "qs_pg:photos":28,
    "qs_pg:photos_1k":6,
    "qs_pg:photos_9k":1,
    "qs_pg:photos_9r":2,
    "qs_pg:photos_all":28,
    "qs_pg:photos_sr":2,
    "qs_pg:pop_sr":3,
    "qs_pg:qs_pg_placetype":"locality",
    "qs_pg:qs_pg_placetype_gp":"Town",
    "qs_pg:woe_adm0":23424748,
    "woe:adm0_id":23424748,
    "woe:name_adm0":"Australia",
    "woe:name_adm1":"Queensland",
    "woe:placetype":"Town",
    "wof:name":"Hebel",
    "wof:placetype":"locality"
},
  "geometry": {"coordinates":[147.78333000000001,-28.96667],"type":"Point"}
}