{
  "type": "Feature",
  "properties": {
    "gn:admin1_code":"4.0",
    "gn:admin2_code":"33800.0",
    "gn:asciiname":"Michael Creek",
    "gn:country_code":"AU",
    "gn:dem":681,
    "gn:feature_class":"P",
    "gn:feature_code":"PPL",
    "gn:name":"Michael Creek",
    "gn:population":0,
    "gn:timezone":"Australia/Brisbane",
    "iso:country":"AU",
    "wof:name":"Michael Creek",
    "wof:placetype":"locality"
},
  "geometry": {"coordinates":[145.88333,-18.83333],"type":"Point"}
}