{
  "type": "Feature",
  "properties": {
    "gn:admin1_code":"5.0",
    "gn:admin2_code":"43790.0",
    "gn:asciiname":"Wintrena",
    "gn:country_code":"AU",
    "gn:dem":57,
    "gn:feature_class":"P",
    "gn:feature_code":"PPL",
    "gn:name":"Wintrena",
    "gn:population":0,
    "gn:timezone":"Australia/Adelaide",
    "iso:country":"AU",
    "name:eng_x_preferred":[
        "Wintrena"
    ],
    "wof:name":"Wintrena",
    "wof:placetype":"locality"
},
  "geometry": {"coordinates":[140.5275,-34.69763],"type":"Point"}
}