{
  "type": "Feature",
  "properties": {
    "gn:admin1_code":"2.0",
    "gn:admin2_code":"13700.0",
    "gn:asciiname":"Woburn",
    "gn:country_code":"AU",
    "gn:dem":371,
    "gn:feature_class":"P",
    "gn:feature_code":"PPL",
    "gn:name":"Woburn",
    "gn:population":0,
    "gn:timezone":"Australia/Sydney",
    "iso:country":"AU",
    "name:ceb_x_preferred":[
        "Woburn"
    ],
    "name:deu_x_preferred":[
        "Woburn"
    ],
    "name:eng_x_preferred":[
        "Woburn"
    ],
    "name:fra_x_preferred":[
        "Woburn"
    ],
    "name:ita_x_preferred":[
        "Woburn"
    ],
    "name:nld_x_preferred":[
        "Woburn"
    ],
    "name:pol_x_preferred":[
        "Woburn"
    ],
    "wof:name":"Woburn",
    "wof:placetype":"locality"
},
  "geometry": {"coordinates":[148.38893999999999,-34.64585],"type":"Point"}
}