{
  "type": "Feature",
  "properties": {
    "iso:country":"AU",
    "name:ceb_x_preferred":[
        "Mount Archer"
    ],
    "name:deu_x_preferred":[
        "Mount Archer"
    ],
    "name:eng_x_preferred":[
        "Mount Archer"
    ],
    "name:fas_x_preferred":[
        "\u0645\u0627\u0648\u0646\u062a \u0622\u0631\u0686\u0631"
    ],
    "name:fra_x_preferred":[
        "Mount Archer"
    ],
    "name:nld_x_preferred":[
        "Mount Archer"
    ],
    "name:swe_x_preferred":[
        "Mount Archer"
    ],
    "qs_pg:aaroncc":"AU",
    "qs_pg:name":"Mount Archer",
    "qs_pg:name_adm0":"Australia",
    "qs_pg:name_adm1":"Queensland",
    "qs_pg:photos":50,
    "qs_pg:photos_1k":10,
    "qs_pg:photos_9k":1,
    "qs_pg:photos_9r":2,
    "qs_pg:photos_all":50,
    "qs_pg:photos_sr":2,
    "qs_pg:pop_sr":0,
    "qs_pg:qs_pg_placetype":"locality",
    "qs_pg:qs_pg_placetype_gp":"Town",
    "qs_pg:woe_adm0":23424748,
    "woe:adm0_id":23424748,
    "woe:name_adm0":"Australia",
    "woe:name_adm1":"Queensland",
    "woe:placetype":"Town",
    "wof:name":"Mount Archer",
    "wof:placetype":"locality"
},
  "geometry": {"coordinates":[150.57715400000001,-23.339418],"type":"Point"}
}