{
  "type": "Feature",
  "properties": {
    "gn:admin1_code":"2.0",
    "gn:admin2_code":"16200.0",
    "gn:asciiname":"Yarrimbah",
    "gn:country_code":"AU",
    "gn:dem":282,
    "gn:feature_class":"P",
    "gn:feature_code":"PPL",
    "gn:name":"Yarrimbah",
    "gn:population":0,
    "gn:timezone":"Australia/Sydney",
    "iso:country":"AU",
    "name:eng_x_preferred":[
        "Yarrimbah"
    ],
    "wof:name":"Yarrimbah",
    "wof:placetype":"locality"
},
  "geometry": {"coordinates":[148.07406,-33.06932],"type":"Point"}
}