{
  "type": "Feature",
  "properties": {
    "gn:admin1_code":"4.0",
    "gn:admin2_code":"33980.0",
    "gn:asciiname":"Wynyard",
    "gn:country_code":"AU",
    "gn:dem":336,
    "gn:feature_class":"P",
    "gn:feature_code":"PPL",
    "gn:name":"Wynyard",
    "gn:population":0,
    "gn:timezone":"Australia/Brisbane",
    "iso:country":"AU",
    "name:ceb_x_preferred":[
        "Wynyard"
    ],
    "name:eng_x_preferred":[
        "Wynyard"
    ],
    "name:ita_x_preferred":[
        "Wynyard"
    ],
    "name:nld_x_preferred":[
        "Wynyard"
    ],
    "name:swe_x_preferred":[
        "Wynyard"
    ],
    "wof:name":"Wynyard",
    "wof:placetype":"locality"
},
  "geometry": {"coordinates":[147.17934,-23.06679],"type":"Point"}
}