{
  "type": "Feature",
  "properties": {
    "gn:country":"AU",
    "iso:country":"AU",
    "name:ceb_x_preferred":[
        "Inskip Point"
    ],
    "name:swe_x_preferred":[
        "Inskip Point"
    ],
    "qs_pg:aaroncc":"AU",
    "qs_pg:gn_country":"AU",
    "qs_pg:name":"Inskip Point",
    "qs_pg:name_adm0":"Australia",
    "qs_pg:name_adm1":"Queensland",
    "qs_pg:photos":456,
    "qs_pg:photos_1k":92,
    "qs_pg:photos_9k":2,
    "qs_pg:photos_9r":5,
    "qs_pg:photos_all":456,
    "qs_pg:photos_sr":7,
    "qs_pg:pop_sr":0,
    "qs_pg:qs_pg_placetype":"locality",
    "qs_pg:qs_pg_placetype_gp":"Town",
    "qs_pg:woe_adm0":23424748,
    "woe:adm0_id":23424748,
    "woe:name_adm0":"Australia",
    "woe:name_adm1":"Queensland",
    "woe:placetype":"Town",
    "wof:name":"Inskip Point",
    "wof:placetype":"locality"
},
  "geometry": {"coordinates":[153.07491300000001,-25.82883],"type":"Point"}
}