{
  "type": "Feature",
  "properties": {
    "gn:admin1_code":"8",
    "gn:admin2_code":"55460",
    "gn:asciiname":"South Burracoppin",
    "gn:country_code":"AU",
    "gn:dem":293,
    "gn:feature_class":"P",
    "gn:feature_code":"PPL",
    "gn:name":"South Burracoppin",
    "gn:population":0,
    "gn:timezone":"Australia/Perth",
    "iso:country":"AU",
    "wof:name":"South Burracoppin",
    "wof:placetype":"locality"
},
  "geometry": {"coordinates":[118.11667,-31.56667],"type":"Point"}
}