{
  "type": "Feature",
  "properties": {
    "gn:admin1_code":"2.0",
    "gn:admin2_code":"10600.0",
    "gn:asciiname":"Kooroowi",
    "gn:country_code":"AU",
    "gn:dem":62,
    "gn:feature_class":"P",
    "gn:feature_code":"PPL",
    "gn:name":"Kooroowi",
    "gn:population":0,
    "gn:timezone":"Australia/Sydney",
    "iso:country":"AU",
    "name:eng_x_preferred":[
        "Kooroowi"
    ],
    "wof:name":"Kooroowi",
    "wof:placetype":"locality"
},
  "geometry": {"coordinates":[152.80288999999999,-30.479],"type":"Point"}
}