{
  "type": "Feature",
  "properties": {
    "gn:admin1_code":"8.0",
    "gn:admin2_code":"53290.0",
    "gn:asciiname":"Cowerup",
    "gn:country_code":"AU",
    "gn:dem":18,
    "gn:feature_class":"P",
    "gn:feature_code":"PPL",
    "gn:name":"Cowerup",
    "gn:population":0,
    "gn:timezone":"Australia/Perth",
    "iso:country":"AU",
    "name:eng_x_preferred":[
        "Cowerup"
    ],
    "wof:name":"Cowerup",
    "wof:placetype":"locality"
},
  "geometry": {"coordinates":[120.80257,-33.83691],"type":"Point"}
}