{
  "type": "Feature",
  "properties": {
    "iso:country":"AU",
    "name:amh_x_preferred":[
        "\u12a0\u120d\u1260\u122a"
    ],
    "name:ara_x_preferred":[
        "\u0623\u0644\u0628\u0648\u0631\u064a"
    ],
    "name:azb_x_preferred":[
        "\u0622\u0644\u0628\u0631\u06cc"
    ],
    "name:cat_x_preferred":[
        "Albury"
    ],
    "name:ceb_x_preferred":[
        "Albury"
    ],
    "name:ckb_x_preferred":[
        "\u0626\u06d5\u06b5\u0628\u0648\u0631\u06cc"
    ],
    "name:cym_x_preferred":[
        "Albury"
    ],
    "name:dan_x_preferred":[
        "Albury"
    ],
    "name:deu_x_preferred":[
        "Albury"
    ],
    "name:eng_x_preferred":[
        "Albury"
    ],
    "name:fas_x_preferred":[
        "\u0622\u0644\u0628\u0631\u06cc"
    ],
    "name:fra_x_preferred":[
        "Albury"
    ],
    "name:gle_x_preferred":[
        "Albury"
    ],
    "name:glv_x_preferred":[
        "Albury"
    ],
    "name:heb_x_preferred":[
        "\u05d0\u05d5\u05dc\u05d1\u05d5\u05e8\u05d9"
    ],
    "name:hun_x_preferred":[
        "Albury"
    ],
    "name:ind_x_preferred":[
        "Albury"
    ],
    "name:ita_x_preferred":[
        "Albury"
    ],
    "name:jav_x_preferred":[
        "Albury"
    ],
    "name:jpn_x_preferred":[
        "\u30aa\u30eb\u30d9\u30ea\u30fc"
    ],
    "name:kat_x_preferred":[
        "\u10dd\u10da\u10d1\u10d4\u10e0\u10d8"
    ],
    "name:kor_x_preferred":[
        "\uc62c\ubc84\ub9ac"
    ],
    "name:lit_x_preferred":[
        "Olberis"
    ],
    "name:mlg_x_preferred":[
        "Albury"
    ],
    "name:nld_x_preferred":[
        "Albury"
    ],
    "name:nor_x_preferred":[
        "Albury"
    ],
    "name:pnb_x_preferred":[
        "\u0627\u0644\u0628\u0631\u06cc"
    ],
    "name:pol_x_preferred":[
        "Albury"
    ],
    "name:por_x_preferred":[
        "Albury"
    ],
    "name:rus_x_preferred":[
        "\u041e\u043b\u0431\u0435\u0440\u0438"
    ],
    "name:spa_x_preferred":[
        "Albury"
    ],
    "name:srp_x_preferred":[
        "\u041e\u043b\u0431\u0435\u0440\u0438"
    ],
    "name:swe_x_preferred":[
        "Albury"
    ],
    "name:tur_x_preferred":[
        "Albury"
    ],
    "name:ukr_x_preferred":[
        "\u041e\u043b\u0431\u0435\u0440\u0456"
    ],
    "name:urd_x_preferred":[
        "\u0627\u06cc\u0644\u0628\u0631\u06cc"
    ],
    "name:vie_x_preferred":[
        "Albury"
    ],
    "name:war_x_preferred":[
        "Albury"
    ],
    "name:zho_x_preferred":[
        "\u5965\u5c14\u4f2f\u91cc"
    ],
    "wof:coterminous":[
        1376953287
    ],
    "wof:lang_x_official":[
        "eng"
    ],
    "wof:lang_x_spoken":[
        "eng"
    ],
    "wof:name":"Albury",
    "wof:placetype":"locality"
},
  "geometry": {"coordinates":[146.91450399999999,-36.074771],"type":"Point"}
}