{
  "type": "Feature",
  "properties": {
    "iso:country":"AU",
    "name:eng_x_preferred":[
        "Albury"
    ],
    "wof:coterminous":[
        1376953287
    ],
    "wof:lang_x_official":[
        "eng"
    ],
    "wof:lang_x_spoken":[
        "eng"
    ],
    "wof:name":"Albury",
    "wof:placetype":"locality"
},
  "geometry": {"coordinates":[146.91450399999999,-36.074771],"type":"Point"}
}