{
  "type": "Feature",
  "properties": {
    "gn:admin1_code":"5.0",
    "gn:asciiname":"Broadview",
    "gn:country_code":"AU",
    "gn:dem":126,
    "gn:feature_class":"P",
    "gn:feature_code":"PPL",
    "gn:name":"Broadview",
    "gn:population":0,
    "gn:timezone":"Australia/Adelaide",
    "iso:country":"AU",
    "name:ceb_x_preferred":[
        "Broadview"
    ],
    "name:deu_x_preferred":[
        "Broadview"
    ],
    "name:eng_x_preferred":[
        "Broadview"
    ],
    "name:fra_x_preferred":[
        "Broadview"
    ],
    "name:ita_x_preferred":[
        "Broadview"
    ],
    "name:nld_x_preferred":[
        "Broadview"
    ],
    "name:pol_x_preferred":[
        "Broadview"
    ],
    "name:por_x_preferred":[
        "Broadview"
    ],
    "name:srp_x_preferred":[
        "\u0411\u0440\u043e\u0434\u0432\u0458\u0443"
    ],
    "name:swe_x_preferred":[
        "Broadview"
    ],
    "name:vol_x_preferred":[
        "Broadview"
    ],
    "wof:name":"Broadview",
    "wof:placetype":"locality"
},
  "geometry": {"coordinates":[137.23078000000001,-33.1224],"type":"Point"}
}