{
  "type": "Feature",
  "properties": {
    "iso:country":"AU",
    "name:ceb_x_preferred":[
        "West Beach"
    ],
    "name:eng_x_preferred":[
        "West Beach"
    ],
    "name:eng_x_variant":[
        "W Beach"
    ],
    "name:swe_x_preferred":[
        "West Beach"
    ],
    "qs:gn_adm0_cc":"AU",
    "qs:gn_local":2071860,
    "qs:local_max":364,
    "qs:local_sum":606,
    "qs:localhoods":5,
    "qs:name":"West Beach",
    "qs:name_adm0":"Australia",
    "qs:name_adm1":"Western Australia",
    "qs:name_adm2":"Esperance",
    "qs:name_local":"Esperance",
    "qs:photo_max":22,
    "qs:photo_sum":139,
    "qs:placetype":"Suburb",
    "qs:quad_count":23,
    "qs:woe_adm0":23424748,
    "qs:woe_adm1":2344706,
    "qs:woe_adm2":55864164,
    "qs:woe_lau":0,
    "qs:woe_local":1101955,
    "qs:woe_ver":"7.10.0",
    "wof:lang":[
        "eng"
    ],
    "wof:name":"West Beach",
    "wof:placetype":"neighbourhood"
},
  "geometry": {"coordinates":[121.872463,-33.880795],"type":"Point"}
}