{
  "type": "Feature",
  "properties": {
    "gn:admin1_code":"7",
    "gn:admin2_code":"27630",
    "gn:asciiname":"Yellangip",
    "gn:country_code":"AU",
    "gn:dem":107,
    "gn:feature_class":"P",
    "gn:feature_code":"PPL",
    "gn:name":"Yellangip",
    "gn:population":0,
    "gn:timezone":"Australia/Melbourne",
    "iso:country":"AU",
    "wof:name":"Yellangip",
    "wof:placetype":"locality"
},
  "geometry": {"coordinates":[142.28333000000001,-36.13333],"type":"Point"}
}