{
  "type": "Feature",
  "properties": {
    "gn:admin1_code":"5",
    "gn:admin2_code":"43080",
    "gn:asciiname":"Kulde",
    "gn:country_code":"AU",
    "gn:dem":98,
    "gn:feature_class":"P",
    "gn:feature_code":"PPL",
    "gn:name":"Kulde",
    "gn:population":0,
    "gn:timezone":"Australia/Adelaide",
    "iso:country":"AU",
    "wof:name":"Kulde",
    "wof:placetype":"locality"
},
  "geometry": {"coordinates":[139.66666999999998,-35.16667],"type":"Point"}
}