{
  "type": "Feature",
  "properties": {
    "gn:admin1_code":"3.0",
    "gn:admin2_code":"71300.0",
    "gn:asciiname":"Rurrangala",
    "gn:country_code":"AU",
    "gn:dem":39,
    "gn:feature_class":"P",
    "gn:feature_code":"PPL",
    "gn:name":"Rurrangala",
    "gn:population":0,
    "gn:timezone":"Australia/Darwin",
    "iso:country":"AU",
    "wof:name":"Rurrangala",
    "wof:placetype":"locality"
},
  "geometry": {"coordinates":[136.25533999999999,-12.905],"type":"Point"}
}