{
  "type": "Feature",
  "properties": {
    "gn:admin1_code":"2.0",
    "gn:admin2_code":"11600.0",
    "gn:asciiname":"Ballandry",
    "gn:country_code":"AU",
    "gn:dem":192,
    "gn:feature_class":"P",
    "gn:feature_code":"PPL",
    "gn:name":"Ballandry",
    "gn:population":0,
    "gn:timezone":"Australia/Sydney",
    "iso:country":"AU",
    "name:eng_x_preferred":[
        "Ballandry"
    ],
    "wof:name":"Ballandry",
    "wof:placetype":"locality"
},
  "geometry": {"coordinates":[146.18323000000001,-34.07846],"type":"Point"}
}