{
  "type": "Feature",
  "properties": {
    "gn:admin1_code":"7.0",
    "gn:admin2_code":"24900.0",
    "gn:asciiname":"Lower Moira",
    "gn:country_code":"AU",
    "gn:dem":97,
    "gn:feature_class":"P",
    "gn:feature_code":"PPL",
    "gn:name":"Lower Moira",
    "gn:population":0,
    "gn:timezone":"Australia/Melbourne",
    "iso:country":"AU",
    "wof:name":"Lower Moira",
    "wof:placetype":"locality"
},
  "geometry": {"coordinates":[144.97627,-36.08546],"type":"Point"}
}