{
  "type": "Feature",
  "properties": {
    "gn:admin1_code":"4.0",
    "gn:admin2_code":"37340.0",
    "gn:asciiname":"Banana Pocket",
    "gn:country_code":"AU",
    "gn:dem":5,
    "gn:feature_class":"P",
    "gn:feature_code":"PPL",
    "gn:name":"Banana Pocket",
    "gn:population":0,
    "gn:timezone":"Australia/Brisbane",
    "iso:country":"AU",
    "wof:name":"Banana Pocket",
    "wof:placetype":"locality"
},
  "geometry": {"coordinates":[148.65000000000001,-20.53333],"type":"Point"}
}