{
  "type": "Feature",
  "properties": {
    "gn:admin1_code":"5.0",
    "gn:admin2_code":"47290.0",
    "gn:asciiname":"Garraside",
    "gn:country_code":"AU",
    "gn:dem":88,
    "gn:feature_class":"P",
    "gn:feature_code":"PPL",
    "gn:name":"Garraside",
    "gn:population":0,
    "gn:timezone":"Australia/Adelaide",
    "iso:country":"AU",
    "name:eng_x_preferred":[
        "Garraside"
    ],
    "wof:name":"Garraside",
    "wof:placetype":"locality"
},
  "geometry": {"coordinates":[140.31365,-35.44726],"type":"Point"}
}