{
  "type": "Feature",
  "properties": {
    "gn:admin1_code":"8",
    "gn:admin2_code":"51120",
    "gn:asciiname":"Eujinyn",
    "gn:country_code":"AU",
    "gn:dem":252,
    "gn:feature_class":"P",
    "gn:feature_code":"PPL",
    "gn:name":"Eujinyn",
    "gn:population":0,
    "gn:timezone":"Australia/Perth",
    "iso:country":"AU",
    "name:eng_x_preferred":[
        "Eujinyn"
    ],
    "wof:name":"Eujinyn",
    "wof:placetype":"locality"
},
  "geometry": {"coordinates":[118.04061000000002,-31.90753],"type":"Point"}
}