{
  "type": "Feature",
  "properties": {
    "gn:admin1_code":"5",
    "gn:admin2_code":"42110",
    "gn:asciiname":"Worlds End Creek",
    "gn:country_code":"AU",
    "gn:dem":307,
    "gn:feature_class":"P",
    "gn:feature_code":"PPL",
    "gn:name":"Worlds End Creek",
    "gn:population":0,
    "gn:timezone":"Australia/Adelaide",
    "iso:country":"AU",
    "wof:name":"Worlds End Creek",
    "wof:placetype":"locality"
},
  "geometry": {"coordinates":[139.05670000000001,-33.83266],"type":"Point"}
}