{
  "type": "Feature",
  "properties": {
    "gn:admin1_code":"4.0",
    "gn:admin2_code":"33360.0",
    "gn:asciiname":"Spadely",
    "gn:country_code":"AU",
    "gn:dem":23,
    "gn:feature_class":"P",
    "gn:feature_code":"PPL",
    "gn:name":"Spadely",
    "gn:population":0,
    "gn:timezone":"Australia/Brisbane",
    "iso:country":"AU",
    "name:eng_x_preferred":[
        "Spadely"
    ],
    "wof:name":"Spadely",
    "wof:placetype":"locality"
},
  "geometry": {"coordinates":[151.02388999999999,-23.46185],"type":"Point"}
}