{
  "type": "Feature",
  "properties": {
    "gn:admin1_code":"2.0",
    "gn:admin2_code":"17400.0",
    "gn:asciiname":"Billyrimba",
    "gn:country_code":"AU",
    "gn:dem":384,
    "gn:feature_class":"P",
    "gn:feature_code":"PPL",
    "gn:name":"Billyrimba",
    "gn:population":0,
    "gn:timezone":"Australia/Sydney",
    "iso:country":"AU",
    "name:eng_x_preferred":[
        "Billyrimba"
    ],
    "wof:name":"Billyrimba",
    "wof:placetype":"locality"
},
  "geometry": {"coordinates":[152.22871000000001,-29.17098],"type":"Point"}
}