{
  "type": "Feature",
  "properties": {
    "gn:admin1_code":"2.0",
    "gn:admin2_code":"18020.0",
    "gn:asciiname":"Girragulang",
    "gn:country_code":"AU",
    "gn:dem":462,
    "gn:feature_class":"P",
    "gn:feature_code":"PPL",
    "gn:name":"Girragulang",
    "gn:population":0,
    "gn:timezone":"Australia/Sydney",
    "iso:country":"AU",
    "name:eng_x_preferred":[
        "Girragulang"
    ],
    "wof:name":"Girragulang",
    "wof:placetype":"locality"
},
  "geometry": {"coordinates":[149.68608,-31.92315],"type":"Point"}
}