{
  "type": "Feature",
  "properties": {
    "gn:admin1_code":"2.0",
    "gn:admin2_code":"16180.0",
    "gn:asciiname":"Kain",
    "gn:country_code":"AU",
    "gn:dem":846,
    "gn:feature_class":"P",
    "gn:feature_code":"PPL",
    "gn:name":"Kain",
    "gn:population":0,
    "gn:timezone":"Australia/Sydney",
    "iso:country":"AU",
    "name:ces_x_preferred":[
        "Kain"
    ],
    "name:deu_x_preferred":[
        "Kain"
    ],
    "name:fra_x_preferred":[
        "Kain"
    ],
    "name:hun_x_preferred":[
        "K\u00e1in"
    ],
    "name:hye_x_preferred":[
        "\u053f\u0561\u0575\u0565\u0576"
    ],
    "name:ind_x_preferred":[
        "Kain"
    ],
    "name:ita_x_preferred":[
        "Kain"
    ],
    "name:jav_x_preferred":[
        "Kain"
    ],
    "name:jpn_x_preferred":[
        "\u30ab\u30a4\u30f3"
    ],
    "name:nld_x_preferred":[
        "Kain"
    ],
    "name:pol_x_preferred":[
        "Kain"
    ],
    "name:rus_x_preferred":[
        "\u041a\u0430\u0438\u043d"
    ],
    "wof:name":"Kain",
    "wof:placetype":"locality"
},
  "geometry": {"coordinates":[149.56666999999999,-35.71667],"type":"Point"}
}