{
  "type": "Feature",
  "properties": {
    "gn:admin1_code":"7.0",
    "gn:admin2_code":"26810.0",
    "gn:asciiname":"Cobbannah",
    "gn:cc2":"AU",
    "gn:country_code":"AU",
    "gn:dem":616,
    "gn:feature_class":"P",
    "gn:feature_code":"PPL",
    "gn:name":"Cobbannah",
    "gn:population":0,
    "gn:timezone":"Australia/Melbourne",
    "iso:country":"AU",
    "name:und_x_variant":[
        "Cobbanah",
        "Cobannah",
        "Cobbannah"
    ],
    "wof:name":"Cobbannah",
    "wof:placetype":"locality"
},
  "geometry": {"coordinates":[147.18333000000001,-37.63333],"type":"Point"}
}