{
  "type": "Feature",
  "properties": {
    "iso:country":"AU",
    "name:ceb_x_preferred":[
        "Spreyton"
    ],
    "name:cym_x_preferred":[
        "Spreyton"
    ],
    "name:fas_x_preferred":[
        "\u0627\u0633\u067e\u0631\u06cc\u062a\u0648\u0646"
    ],
    "name:nld_x_preferred":[
        "Spreyton"
    ],
    "name:pol_x_preferred":[
        "Spreyton"
    ],
    "name:swe_x_preferred":[
        "Spreyton"
    ],
    "qs_pg:aaroncc":"AU",
    "qs_pg:name":"Spreyton",
    "qs_pg:name_adm0":"Australia",
    "qs_pg:name_adm1":"Tasmania",
    "qs_pg:photos":5,
    "qs_pg:photos_1k":1,
    "qs_pg:photos_9k":1,
    "qs_pg:photos_9r":1,
    "qs_pg:photos_all":5,
    "qs_pg:photos_sr":1,
    "qs_pg:pop_sr":0,
    "qs_pg:qs_pg_placetype":"neighbourhood",
    "qs_pg:qs_pg_placetype_gp":"Suburb",
    "qs_pg:woe_adm0":23424748,
    "woe:adm0_id":23424748,
    "woe:name_adm0":"Australia",
    "woe:name_adm1":"Tasmania",
    "woe:placetype":"Suburb",
    "wof:name":"Spreyton",
    "wof:placetype":"neighbourhood"
},
  "geometry": {"coordinates":[146.35436999999999,-41.180204],"type":"Point"}
}