{
  "type": "Feature",
  "properties": {
    "iso:country":"AU",
    "qs_pg:aaroncc":"AU",
    "qs_pg:name":"Freycinet",
    "qs_pg:name_adm0":"Australia",
    "qs_pg:name_adm1":"Tasmania",
    "qs_pg:photos":2701,
    "qs_pg:photos_1k":547,
    "qs_pg:photos_9k":12,
    "qs_pg:photos_9r":10,
    "qs_pg:photos_all":2701,
    "qs_pg:photos_sr":18,
    "qs_pg:pop_sr":0,
    "qs_pg:qs_pg_placetype":"locality",
    "qs_pg:qs_pg_placetype_gp":"Town",
    "qs_pg:woe_adm0":23424748,
    "woe:adm0_id":23424748,
    "woe:name_adm0":"Australia",
    "woe:name_adm1":"Tasmania",
    "woe:placetype":"Town",
    "wof:name":"Freycinet",
    "wof:placetype":"locality"
},
  "geometry": {"coordinates":[148.29912100000001,-42.153223],"type":"Point"}
}