{
  "type": "Feature",
  "properties": {
    "gn:admin1_code":"8",
    "gn:admin2_code":"50630",
    "gn:asciiname":"Pindalup",
    "gn:country_code":"AU",
    "gn:dem":345,
    "gn:feature_class":"P",
    "gn:feature_code":"PPL",
    "gn:name":"Pindalup",
    "gn:population":0,
    "gn:timezone":"Australia/Perth",
    "iso:country":"AU",
    "wof:name":"Pindalup",
    "wof:placetype":"locality"
},
  "geometry": {"coordinates":[116.25,-32.78333],"type":"Point"}
}