{
  "type": "Feature",
  "properties": {
    "gn:admin1_code":"3.0",
    "gn:admin2_code":"71300.0",
    "gn:asciiname":"Mata Mata",
    "gn:country_code":"AU",
    "gn:dem":14,
    "gn:feature_class":"P",
    "gn:feature_code":"PPL",
    "gn:name":"Mata Mata",
    "gn:population":0,
    "gn:timezone":"Australia/Darwin",
    "iso:country":"AU",
    "wof:name":"Mata Mata",
    "wof:placetype":"locality"
},
  "geometry": {"coordinates":[136.26991999999998,-12.07666],"type":"Point"}
}