{
  "type": "Feature",
  "properties": {
    "gn:admin1_code":"4.0",
    "gn:admin2_code":"32270.0",
    "gn:asciiname":"Amah",
    "gn:country_code":"AU",
    "gn:dem":217,
    "gn:feature_class":"P",
    "gn:feature_code":"PPL",
    "gn:name":"Amah",
    "gn:population":0,
    "gn:timezone":"Australia/Brisbane",
    "iso:country":"AU",
    "name:eng_x_preferred":[
        "Amah"
    ],
    "wof:name":"Amah",
    "wof:placetype":"locality"
},
  "geometry": {"coordinates":[148.06825000000001,-23.24508],"type":"Point"}
}