{
  "type": "Feature",
  "properties": {
    "gn:admin1_code":"4",
    "gn:admin2_code":"36510",
    "gn:asciiname":"Teviotville",
    "gn:country_code":"AU",
    "gn:dem":196,
    "gn:feature_class":"P",
    "gn:feature_code":"PPL",
    "gn:name":"Teviotville",
    "gn:population":0,
    "gn:timezone":"Australia/Brisbane",
    "iso:country":"AU",
    "wof:name":"Teviotville",
    "wof:placetype":"locality"
},
  "geometry": {"coordinates":[152.68333000000001,-27.95],"type":"Point"}
}