{
  "type": "Feature",
  "properties": {
    "gn:admin1_code":"8",
    "gn:admin2_code":"51960",
    "gn:asciiname":"Bulla Bulling",
    "gn:country_code":"AU",
    "gn:dem":445,
    "gn:feature_class":"P",
    "gn:feature_code":"PPL",
    "gn:name":"Bulla Bulling",
    "gn:population":0,
    "gn:timezone":"Australia/Perth",
    "iso:country":"AU",
    "name:eng_x_preferred":[
        "Bulla Bulling"
    ],
    "name:und_x_variant":[
        "Bullabulling"
    ],
    "wof:name":"Bulla Bulling",
    "wof:placetype":"locality"
},
  "geometry": {"coordinates":[120.87103999999999,-31.01347],"type":"Point"}
}