{
  "type": "Feature",
  "properties": {
    "gn:admin1_code":"02",
    "gn:admin2_code":"16370.0",
    "gn:asciiname":"Ku Ring Gai Chase",
    "gn:country_code":"AU",
    "gn:dem":87,
    "gn:feature_class":"P",
    "gn:feature_code":"PPL",
    "gn:name":"Ku Ring Gai Chase",
    "gn:population":0,
    "gn:timezone":"Australia/Sydney",
    "iso:country":"AU",
    "wof:name":"Ku Ring Gai Chase",
    "wof:placetype":"locality"
},
  "geometry": {"coordinates":[151.23401999999999,-33.63724000000001],"type":"Point"}
}