{
  "type": "Feature",
  "properties": {
    "gn:admin1_code":"2.0",
    "gn:admin2_code":"15270.0",
    "gn:asciiname":"Glenella",
    "gn:country_code":"AU",
    "gn:dem":792,
    "gn:feature_class":"P",
    "gn:feature_code":"PPL",
    "gn:name":"Glenella",
    "gn:population":0,
    "gn:timezone":"Australia/Sydney",
    "iso:country":"AU",
    "name:eng_x_preferred":[
        "Glenella"
    ],
    "wof:name":"Glenella",
    "wof:placetype":"locality"
},
  "geometry": {"coordinates":[149.60650999999999,-32.84525],"type":"Point"}
}