{
  "type": "Feature",
  "properties": {
    "iso:country":"AU",
    "name:eng_x_preferred":[
        "Cornelian Bay"
    ],
    "name:unk_x_variant":[
        "Cornelian Bay"
    ],
    "qs:gn_local":0,
    "qs:local_max":6320,
    "qs:local_sum":24464,
    "qs:localhoods":40,
    "qs:name":"Cornelian Bay",
    "qs:name_adm0":"Australia",
    "qs:name_adm1":"Tasmania",
    "qs:name_adm2":"Hobart",
    "qs:name_local":"Hobart",
    "qs:photo_max":101,
    "qs:photo_sum":349,
    "qs:placetype":"Suburb",
    "qs:quad_count":18,
    "qs:woe_adm0":23424748,
    "qs:woe_adm1":2344704,
    "qs:woe_adm2":55864281,
    "qs:woe_lau":0,
    "qs:woe_local":1102670,
    "qs:woe_ver":"7.10.0",
    "wd:wordcount":29,
    "wof:lang":[
        "eng"
    ],
    "wof:name":"Cornelian Bay",
    "wof:placetype":"neighbourhood"
},
  "geometry": {"coordinates":[147.31923499999999,-42.852744],"type":"Point"}
}