{
  "type": "Feature",
  "properties": {
    "gn:admin1_code":"2",
    "gn:admin2_code":"15850",
    "gn:asciiname":"Timbrebongie",
    "gn:country_code":"AU",
    "gn:dem":233,
    "gn:feature_class":"P",
    "gn:feature_code":"PPL",
    "gn:name":"Timbrebongie",
    "gn:population":0,
    "gn:timezone":"Australia/Sydney",
    "iso:country":"AU",
    "wof:name":"Timbrebongie",
    "wof:placetype":"locality"
},
  "geometry": {"coordinates":[148.25,-32.11667],"type":"Point"}
}