{
  "type": "Feature",
  "properties": {
    "gn:admin1_code":"4.0",
    "gn:admin2_code":"31820.0",
    "gn:asciiname":"Kolan",
    "gn:country_code":"AU",
    "gn:dem":58,
    "gn:feature_class":"P",
    "gn:feature_code":"PPL",
    "gn:name":"Kolan",
    "gn:population":0,
    "gn:timezone":"Australia/Brisbane",
    "iso:country":"AU",
    "wof:name":"Kolan",
    "wof:placetype":"locality"
},
  "geometry": {"coordinates":[152.16631000000001,-24.93073],"type":"Point"}
}