{
  "type": "Feature",
  "properties": {
    "gn:admin1_code":"4.0",
    "gn:admin2_code":"31820.0",
    "gn:asciiname":"Kolan",
    "gn:country_code":"AU",
    "gn:dem":58,
    "gn:feature_class":"P",
    "gn:feature_code":"PPL",
    "gn:name":"Kolan",
    "gn:population":0,
    "gn:timezone":"Australia/Brisbane",
    "iso:country":"AU",
    "name:bos_x_preferred":[
        "Kolan"
    ],
    "name:deu_x_preferred":[
        "Kolan"
    ],
    "name:hrv_x_preferred":[
        "Kolan"
    ],
    "name:hun_x_preferred":[
        "Kolan"
    ],
    "name:ita_x_preferred":[
        "Colane"
    ],
    "name:nld_x_preferred":[
        "Kolan"
    ],
    "name:pol_x_preferred":[
        "Gmina Kolan"
    ],
    "name:ron_x_preferred":[
        "Comuna Kolan"
    ],
    "name:slv_x_preferred":[
        "Kolan"
    ],
    "name:srp_x_preferred":[
        "\u041a\u043e\u043b\u0430\u043d"
    ],
    "name:ukr_x_preferred":[
        "\u041a\u043e\u043b\u0430\u043d"
    ],
    "wof:name":"Kolan",
    "wof:placetype":"locality"
},
  "geometry": {"coordinates":[152.16631000000001,-24.93073],"type":"Point"}
}