{
  "type": "Feature",
  "properties": {
    "gn:admin1_code":"2.0",
    "gn:admin2_code":"11800.0",
    "gn:asciiname":"Brooklana",
    "gn:country_code":"AU",
    "gn:dem":558,
    "gn:feature_class":"P",
    "gn:feature_code":"PPL",
    "gn:name":"Brooklana",
    "gn:population":0,
    "gn:timezone":"Australia/Sydney",
    "iso:country":"AU",
    "name:eng_x_preferred":[
        "Brooklana"
    ],
    "wof:name":"Brooklana",
    "wof:placetype":"locality"
},
  "geometry": {"coordinates":[152.84316999999999,-30.24881],"type":"Point"}
}