{
  "type": "Feature",
  "properties": {
    "iso:country":"AU",
    "name:eng_x_preferred":[
        "Corney Town"
    ],
    "name:unk_x_variant":[
        "Corney Town"
    ],
    "qs:gn_local":0,
    "qs:local_max":568,
    "qs:local_sum":1728,
    "qs:localhoods":7,
    "qs:name":"Corney Town",
    "qs:name_adm0":"Australia",
    "qs:name_adm1":"New South Wales",
    "qs:name_adm2":"Lithgow",
    "qs:name_local":"Lithgow",
    "qs:photo_max":72,
    "qs:photo_sum":235,
    "qs:placetype":"Suburb",
    "qs:quad_count":14,
    "qs:woe_adm0":23424748,
    "qs:woe_adm1":2344700,
    "qs:woe_adm2":55863806,
    "qs:woe_lau":0,
    "qs:woe_local":1103465,
    "qs:woe_ver":"7.10.0",
    "wof:lang":[
        "eng"
    ],
    "wof:name":"Corney Town",
    "wof:placetype":"neighbourhood"
},
  "geometry": {"coordinates":[150.17702399999999,-33.473446],"type":"Point"}
}