{
  "type": "Feature",
  "properties": {
    "gn:admin1_code":"8.0",
    "gn:admin2_code":"51960.0",
    "gn:asciiname":"Mandilla",
    "gn:country_code":"AU",
    "gn:dem":319,
    "gn:feature_class":"P",
    "gn:feature_code":"PPL",
    "gn:name":"Mandilla",
    "gn:population":0,
    "gn:timezone":"Australia/Perth",
    "iso:country":"AU",
    "name:eng_x_preferred":[
        "Mandilla"
    ],
    "wof:name":"Mandilla",
    "wof:placetype":"locality"
},
  "geometry": {"coordinates":[121.53034,-31.37956],"type":"Point"}
}