{
  "type": "Feature",
  "properties": {
    "gn:admin1_code":"2.0",
    "gn:admin2_code":"17400.0",
    "gn:asciiname":"Cottonvale",
    "gn:country_code":"AU",
    "gn:dem":921,
    "gn:feature_class":"P",
    "gn:feature_code":"PPL",
    "gn:name":"Cottonvale",
    "gn:population":0,
    "gn:timezone":"Australia/Brisbane",
    "iso:country":"AU",
    "name:eng_x_preferred":[
        "Cottonvale"
    ],
    "name:und_x_variant":[
        "Cotton Vale"
    ],
    "wof:name":"Cottonvale",
    "wof:placetype":"locality",
    "wof:population":148
},
  "geometry": {"coordinates":[151.95203000000001,-28.52123],"type":"Point"}
}