{
  "type": "Feature",
  "properties": {
    "gn:gn_country":"AU",
    "gn:gn_fcode":"PPL",
    "gn:gn_pop":263,
    "gn:population":263,
    "iso:country":"AU",
    "name:eng_x_preferred":[
        "Laughtondale"
    ],
    "name:fre_x_preferred":[
        "Laughtondale"
    ],
    "name:jpn_x_preferred":[
        "\u30ed\u30fc\u30c8\u30f3\u30c7\u30fc\u30eb"
    ],
    "name:swe_x_preferred":[
        "Laughtondale"
    ],
    "qs_pg:aaroncc":"AU",
    "qs_pg:gn_country":"AU",
    "qs_pg:gn_fcode":"PPL",
    "qs_pg:gn_pop":263,
    "qs_pg:name":"Laughtondale",
    "qs_pg:name_adm0":"Australia",
    "qs_pg:name_adm1":"New South Wales",
    "qs_pg:photos":10,
    "qs_pg:photos_1k":2,
    "qs_pg:photos_9k":1,
    "qs_pg:photos_9r":1,
    "qs_pg:photos_all":10,
    "qs_pg:photos_sr":1,
    "qs_pg:pop_sr":2,
    "qs_pg:qs_pg_placetype":"locality",
    "qs_pg:qs_pg_placetype_gp":"Town",
    "qs_pg:woe_adm0":23424748,
    "woe:adm0_id":23424748,
    "woe:name_adm0":"Australia",
    "woe:name_adm1":"New South Wales",
    "woe:placetype":"Town",
    "wof:name":"Laughtondale",
    "wof:placetype":"locality",
    "wof:population":263
},
  "geometry": {"coordinates":[151.03333000000001,-33.41667],"type":"Point"}
}