{
  "type": "Feature",
  "properties": {
    "gn:admin1_code":"8.0",
    "gn:admin2_code":"50980.0",
    "gn:asciiname":"Yardoogarra Community",
    "gn:country_code":"AU",
    "gn:dem":16,
    "gn:feature_class":"P",
    "gn:feature_code":"PPL",
    "gn:name":"Yardoogarra Community",
    "gn:population":0,
    "gn:timezone":"Australia/Perth",
    "iso:country":"AU",
    "wof:name":"Yardoogarra Community",
    "wof:placetype":"locality"
},
  "geometry": {"coordinates":[121.9211,-18.46222],"type":"Point"}
}