{
  "type": "Feature",
  "properties": {
    "gn:admin1_code":"5.0",
    "gn:admin2_code":"41830.0",
    "gn:asciiname":"Arden Vale",
    "gn:country_code":"AU",
    "gn:dem":388,
    "gn:feature_class":"P",
    "gn:feature_code":"PPL",
    "gn:name":"Arden Vale",
    "gn:population":0,
    "gn:timezone":"Australia/Adelaide",
    "iso:country":"AU",
    "name:eng_x_preferred":[
        "Arden Vale"
    ],
    "wof:name":"Arden Vale",
    "wof:placetype":"locality"
},
  "geometry": {"coordinates":[138.04701,-32.22574],"type":"Point"}
}