{
  "type": "Feature",
  "properties": {
    "gn:admin1_code":"2.0",
    "gn:admin2_code":"15650.0",
    "gn:asciiname":"Hungerford Creek",
    "gn:country_code":"AU",
    "gn:dem":174,
    "gn:feature_class":"P",
    "gn:feature_code":"PPL",
    "gn:name":"Hungerford Creek",
    "gn:population":0,
    "gn:timezone":"Australia/Sydney",
    "iso:country":"AU",
    "name:eng_x_preferred":[
        "Hungerford Creek"
    ],
    "wof:name":"Hungerford Creek",
    "wof:placetype":"locality"
},
  "geometry": {"coordinates":[150.48712,-32.48201],"type":"Point"}
}