{
  "type": "Feature",
  "properties": {
    "gn:admin1_code":"8",
    "gn:admin2_code":"57420",
    "gn:asciiname":"Wooganup",
    "gn:country_code":"AU",
    "gn:dem":245,
    "gn:feature_class":"P",
    "gn:feature_code":"PPL",
    "gn:name":"Wooganup",
    "gn:population":0,
    "gn:timezone":"Australia/Perth",
    "iso:country":"AU",
    "wof:name":"Wooganup",
    "wof:placetype":"locality"
},
  "geometry": {"coordinates":[119.58333,-33.76667],"type":"Point"}
}