{
  "type": "Feature",
  "properties": {
    "iso:country":"AU",
    "name:eng_x_preferred":[
        "Kawana"
    ],
    "name:fra_x_preferred":[
        "Kawana"
    ],
    "name:ita_x_preferred":[
        "Kawana"
    ],
    "name:jpn_x_preferred":[
        "\u30ab\u30ef\u30ca"
    ],
    "qs:gn_adm0_cc":"AU",
    "qs:gn_fcode":"PPLX",
    "qs:gn_local":2151437,
    "qs:gn_nam_loc":"rockhampton",
    "qs:gn_namadm1":"04",
    "qs:gn_name":"Kawana",
    "qs:local_max":488,
    "qs:local_sum":1297,
    "qs:localhoods":11,
    "qs:name":"Kawana",
    "qs:name_adm0":"Australia",
    "qs:name_adm1":"Queensland",
    "qs:name_adm2":"Rockhampton Regional",
    "qs:name_local":"Rockhampton",
    "qs:photo_max":56,
    "qs:photo_sum":99,
    "qs:placetype":"Suburb",
    "qs:quad_count":12,
    "qs:woe_adm0":23424748,
    "qs:woe_adm1":2344702,
    "qs:woe_adm2":56072972,
    "qs:woe_lau":0,
    "qs:woe_local":1105353,
    "qs:woe_ver":"7.10.0",
    "wof:lang":[
        "eng"
    ],
    "wof:name":"Kawana",
    "wof:placetype":"neighbourhood"
},
  "geometry": {"coordinates":[150.521085,-23.326704],"type":"Point"}
}