{
  "type": "Feature",
  "properties": {
    "gn:admin1_code":"4.0",
    "gn:admin2_code":"30370.0",
    "gn:asciiname":"Jooro",
    "gn:country_code":"AU",
    "gn:dem":150,
    "gn:feature_class":"P",
    "gn:feature_code":"PPL",
    "gn:name":"Jooro",
    "gn:population":0,
    "gn:timezone":"Australia/Brisbane",
    "iso:country":"AU",
    "name:eng_x_preferred":[
        "Jooro"
    ],
    "wof:name":"Jooro",
    "wof:placetype":"locality"
},
  "geometry": {"coordinates":[150.21098999999995,-24.11499],"type":"Point"}
}