{
  "type": "Feature",
  "properties": {
    "gn:country":"AU",
    "iso:country":"AU",
    "qs_pg:aaroncc":"AU",
    "qs_pg:gn_country":"AU",
    "qs_pg:name":"Collendina",
    "qs_pg:name_adm0":"Australia",
    "qs_pg:name_adm1":"Victoria",
    "qs_pg:photos":98,
    "qs_pg:photos_1k":20,
    "qs_pg:photos_9k":1,
    "qs_pg:photos_9r":3,
    "qs_pg:photos_all":98,
    "qs_pg:photos_sr":3,
    "qs_pg:pop_sr":0,
    "qs_pg:qs_pg_placetype":"locality",
    "qs_pg:qs_pg_placetype_gp":"Town",
    "qs_pg:woe_adm0":23424748,
    "woe:adm0_id":23424748,
    "woe:name_adm0":"Australia",
    "woe:name_adm1":"Victoria",
    "woe:placetype":"Town",
    "wof:name":"Collendina",
    "wof:placetype":"locality"
},
  "geometry": {"coordinates":[144.606889,-38.292227],"type":"Point"}
}