{
  "type": "Feature",
  "properties": {
    "gn:admin1_code":"4.0",
    "gn:admin2_code":"37340.0",
    "gn:asciiname":"Crystal Brook",
    "gn:country_code":"AU",
    "gn:dem":33,
    "gn:feature_class":"P",
    "gn:feature_code":"PPL",
    "gn:name":"Crystal Brook",
    "gn:population":0,
    "gn:timezone":"Australia/Brisbane",
    "iso:country":"AU",
    "name:eng_x_preferred":[
        "Crystal Brook"
    ],
    "wof:name":"Crystal Brook",
    "wof:placetype":"locality"
},
  "geometry": {"coordinates":[148.48498000000001,-20.34844],"type":"Point"}
}