{
  "type": "Feature",
  "properties": {
    "gn:admin1_code":"5.0",
    "gn:admin2_code":"44000.0",
    "gn:asciiname":"Emu",
    "gn:country_code":"AU",
    "gn:dem":265,
    "gn:feature_class":"P",
    "gn:feature_code":"PPL",
    "gn:name":"Emu",
    "gn:population":0,
    "gn:timezone":"Australia/Adelaide",
    "iso:country":"AU",
    "name:eng_x_preferred":[
        "Emu"
    ],
    "wof:name":"Emu",
    "wof:placetype":"locality"
},
  "geometry": {"coordinates":[132.19911999999999,-28.64488],"type":"Point"}
}