{
  "type": "Feature",
  "properties": {
    "gn:admin1_code":"2",
    "gn:admin2_code":"11600",
    "gn:asciiname":"Thoomee",
    "gn:country_code":"AU",
    "gn:dem":140,
    "gn:feature_class":"P",
    "gn:feature_code":"PPL",
    "gn:name":"Thoomee",
    "gn:population":0,
    "gn:timezone":"Australia/Sydney",
    "iso:country":"AU",
    "wof:name":"Thoomee",
    "wof:placetype":"locality"
},
  "geometry": {"coordinates":[146.01667,-33.53333],"type":"Point"}
}