{
  "type": "Feature",
  "properties": {
    "iso:country":"AU",
    "name:eng_x_preferred":[
        "East Bunbury"
    ],
    "name:eng_x_variant":[
        "E Bunbury"
    ],
    "qs:gn_adm0_cc":"AU",
    "qs:gn_local":2075432,
    "qs:gn_nam_loc":"Bunbury, Bunbury, Western Australia, AU",
    "qs:gn_namadm1":"08",
    "qs:local_max":848,
    "qs:local_sum":1463,
    "qs:localhoods":9,
    "qs:name":"East Bunbury",
    "qs:name_adm0":"Australia",
    "qs:name_adm1":"Western Australia",
    "qs:name_adm2":"Bunbury",
    "qs:name_local":"Bunbury",
    "qs:photo_max":14,
    "qs:photo_sum":39,
    "qs:placetype":"Suburb",
    "qs:quad_count":11,
    "qs:woe_adm0":23424748,
    "qs:woe_adm1":2344706,
    "qs:woe_adm2":55864424,
    "qs:woe_lau":0,
    "qs:woe_local":1100778,
    "qs:woe_ver":"7.10.0",
    "wof:lang":[
        "eng"
    ],
    "wof:name":"East Bunbury",
    "wof:placetype":"neighbourhood"
},
  "geometry": {"coordinates":[115.651268,-33.342675],"type":"Point"}
}