{
  "type": "Feature",
  "properties": {
    "gn:admin1_code":"5.0",
    "gn:admin2_code":"47800.0",
    "gn:asciiname":"Huon Downs",
    "gn:country_code":"AU",
    "gn:dem":63,
    "gn:feature_class":"P",
    "gn:feature_code":"PPL",
    "gn:name":"Huon Downs",
    "gn:population":0,
    "gn:timezone":"Australia/Adelaide",
    "iso:country":"AU",
    "name:eng_x_preferred":[
        "Huon Downs"
    ],
    "wof:name":"Huon Downs",
    "wof:placetype":"locality"
},
  "geometry": {"coordinates":[140.09153000000001,-35.79490999999999],"type":"Point"}
}