{
  "type": "Feature",
  "properties": {
    "gn:gn_country":"AU",
    "gn:gn_fcode":"PPL",
    "gn:gn_pop":0,
    "iso:country":"AU",
    "name:dut_x_preferred":[
        "Island Beach"
    ],
    "name:eng_x_preferred":[
        "Island Beach"
    ],
    "name:per_x_preferred":[
        "\u062c\u0632\u06cc\u0631\u0647 \u0628\u06cc\u0686"
    ],
    "qs_pg:aaroncc":"AU",
    "qs_pg:gn_country":"AU",
    "qs_pg:gn_fcode":"PPL",
    "qs_pg:gn_pop":0,
    "qs_pg:name":"Island Beach",
    "qs_pg:name_adm0":"Australia",
    "qs_pg:name_adm1":"South Australia",
    "qs_pg:photos":62,
    "qs_pg:photos_1k":13,
    "qs_pg:photos_9k":1,
    "qs_pg:photos_9r":2,
    "qs_pg:photos_all":62,
    "qs_pg:photos_sr":2,
    "qs_pg:pop_sr":0,
    "qs_pg:qs_pg_placetype":"locality",
    "qs_pg:qs_pg_placetype_gp":"Town",
    "qs_pg:woe_adm0":23424748,
    "woe:adm0_id":23424748,
    "woe:name_adm0":"Australia",
    "woe:name_adm1":"South Australia",
    "woe:placetype":"Town",
    "wof:name":"Island Beach",
    "wof:placetype":"locality"
},
  "geometry": {"coordinates":[137.80279999999999,-35.79888],"type":"Point"}
}