{
  "type": "Feature",
  "properties": {
    "iso:country":"AU",
    "name:eng_x_preferred":[
        "Gaythorne"
    ],
    "name:zho_x_preferred":[
        "\u7d66\u7d22\u6069"
    ],
    "qs:gn_adm0_cc":"AU",
    "qs:gn_local":2174003,
    "qs:gn_nam_loc":"Brisbane, Brisbane, Queensland, AU",
    "qs:gn_namadm1":"04",
    "qs:local_max":15217,
    "qs:local_sum":137917,
    "qs:localhoods":252,
    "qs:name":"Gaythorne",
    "qs:name_adm0":"Australia",
    "qs:name_adm1":"Queensland",
    "qs:name_adm2":"Brisbane",
    "qs:name_local":"Brisbane",
    "qs:photo_max":38,
    "qs:photo_sum":197,
    "qs:placetype":"Suburb",
    "qs:quad_count":15,
    "qs:woe_adm0":23424748,
    "qs:woe_adm1":2344702,
    "qs:woe_adm2":55864298,
    "qs:woe_lau":0,
    "qs:woe_local":1100661,
    "qs:woe_ver":"7.10.0",
    "wof:lang":[
        "eng"
    ],
    "wof:name":"Gaythorne",
    "wof:placetype":"neighbourhood"
},
  "geometry": {"coordinates":[152.975977,-27.416954],"type":"Point"}
}