{
  "type": "Feature",
  "properties": {
    "gn:admin1_code":"2.0",
    "gn:admin2_code":"13660.0",
    "gn:asciiname":"Baroma",
    "gn:country_code":"AU",
    "gn:dem":281,
    "gn:feature_class":"P",
    "gn:feature_code":"PPL",
    "gn:name":"Baroma",
    "gn:population":0,
    "gn:timezone":"Australia/Sydney",
    "iso:country":"AU",
    "wof:name":"Baroma",
    "wof:placetype":"locality"
},
  "geometry": {"coordinates":[150.31666999999999,-29.13333],"type":"Point"}
}