{
  "type": "Feature",
  "properties": {
    "gn:admin1_code":"4.0",
    "gn:admin2_code":"34420.0",
    "gn:asciiname":"Whiteys Corner Hut",
    "gn:country_code":"AU",
    "gn:dem":19,
    "gn:feature_class":"P",
    "gn:feature_code":"PPL",
    "gn:name":"Whiteys Corner Hut",
    "gn:population":0,
    "gn:timezone":"Australia/Brisbane",
    "iso:country":"AU",
    "wof:name":"Whiteys Corner Hut",
    "wof:placetype":"locality"
},
  "geometry": {"coordinates":[141.88172,-15.5617],"type":"Point"}
}