{
  "type": "Feature",
  "properties": {
    "iso:country":"AU",
    "name:ceb_x_preferred":[
        "Garden Island"
    ],
    "name:deu_x_preferred":[
        "Garden Island"
    ],
    "name:eng_x_preferred":[
        "Garden Island"
    ],
    "name:eng_x_variant":[
        "Gardenisland"
    ],
    "name:fra_x_preferred":[
        "Garden Island"
    ],
    "name:swe_x_preferred":[
        "Garden Island"
    ],
    "qs:gn_adm0_cc":"AU",
    "qs:gn_local":2147714,
    "qs:local_max":35533,
    "qs:local_sum":687549,
    "qs:localhoods":516,
    "qs:name":"Garden Island",
    "qs:name_adm0":"Australia",
    "qs:name_adm1":"New South Wales",
    "qs:name_adm2":"Sydney",
    "qs:name_local":"Sydney",
    "qs:photo_max":909,
    "qs:photo_sum":5354,
    "qs:placetype":"Suburb",
    "qs:quad_count":73,
    "qs:woe_adm0":23424748,
    "qs:woe_adm1":2344700,
    "qs:woe_adm2":55864169,
    "qs:woe_lau":0,
    "qs:woe_local":1105779,
    "qs:woe_ver":"7.10.0",
    "wof:lang":[
        "eng"
    ],
    "wof:name":"Garden Island",
    "wof:placetype":"neighbourhood"
},
  "geometry": {"coordinates":[151.23148800000001,-33.858111],"type":"Point"}
}