{
  "type": "Feature",
  "properties": {
    "gn:admin1_code":"2.0",
    "gn:admin2_code":"17150.0",
    "gn:asciiname":"Deer Park",
    "gn:country_code":"AU",
    "gn:dem":64,
    "gn:feature_class":"P",
    "gn:feature_code":"PPL",
    "gn:name":"Deer Park",
    "gn:population":0,
    "gn:timezone":"Australia/Sydney",
    "iso:country":"AU",
    "name:bul_x_preferred":[
        "\u0414\u0438\u044a\u0440 \u041f\u0430\u0440\u043a"
    ],
    "name:cat_x_preferred":[
        "Deer Park"
    ],
    "name:ceb_x_preferred":[
        "Deer Park"
    ],
    "name:deu_x_preferred":[
        "Deer Park"
    ],
    "name:fas_x_preferred":[
        "\u062f\u06cc\u0631 \u067e\u0627\u0631\u06a9"
    ],
    "name:ita_x_preferred":[
        "Deer Park"
    ],
    "name:mlg_x_preferred":[
        "Deer Park"
    ],
    "name:nld_x_preferred":[
        "Deer Park"
    ],
    "name:pol_x_preferred":[
        "Deer Park"
    ],
    "name:por_x_preferred":[
        "Deer Park"
    ],
    "name:rus_x_preferred":[
        "\u0414\u0438\u0440-\u041f\u0430\u0440\u043a"
    ],
    "name:spa_x_preferred":[
        "Deer Park"
    ],
    "name:srp_x_preferred":[
        "\u0414\u0438\u0440 \u041f\u0430\u0440\u043a"
    ],
    "name:swe_x_preferred":[
        "Deer Park"
    ],
    "name:ukr_x_preferred":[
        "\u0414\u0456\u0435\u0440-\u041f\u0430\u0440\u043a"
    ],
    "name:vol_x_preferred":[
        "Deer Park"
    ],
    "wof:name":"Deer Park",
    "wof:placetype":"locality"
},
  "geometry": {"coordinates":[151.09517,-34.06265],"type":"Point"}
}