{
  "type": "Feature",
  "properties": {
    "gn:admin1_code":"2.0",
    "gn:admin2_code":"11700.0",
    "gn:asciiname":"Sunset Strip",
    "gn:country_code":"AU",
    "gn:dem":71,
    "gn:feature_class":"P",
    "gn:feature_code":"PPL",
    "gn:name":"Sunset Strip",
    "gn:population":0,
    "gn:timezone":"Australia/Sydney",
    "iso:country":"AU",
    "name:deu_x_preferred":[
        "Sunset Strip"
    ],
    "name:eng_x_preferred":[
        "Sunset Strip"
    ],
    "name:fra_x_preferred":[
        "Sunset Strip"
    ],
    "name:ind_x_preferred":[
        "Sunset Strip"
    ],
    "name:ita_x_preferred":[
        "Sunset Strip"
    ],
    "name:mkd_x_preferred":[
        "Sunset Strip"
    ],
    "name:nld_x_preferred":[
        "Sunset Strip"
    ],
    "name:spa_x_preferred":[
        "Sunset Strip"
    ],
    "name:swe_x_preferred":[
        "Sunset Strip"
    ],
    "wof:name":"Sunset Strip",
    "wof:placetype":"locality"
},
  "geometry": {"coordinates":[142.30119999999999,-32.2652],"type":"Point"}
}