{
  "type": "Feature",
  "properties": {
    "gn:admin1_code":"4.0",
    "gn:admin2_code":"34800.0",
    "gn:asciiname":"Redland Park",
    "gn:country_code":"AU",
    "gn:dem":182,
    "gn:feature_class":"P",
    "gn:feature_code":"PPL",
    "gn:name":"Redland Park",
    "gn:population":0,
    "gn:timezone":"Australia/Brisbane",
    "iso:country":"AU",
    "name:eng_x_preferred":[
        "Redland Park"
    ],
    "wof:name":"Redland Park",
    "wof:placetype":"locality"
},
  "geometry": {"coordinates":[141.52282,-21.34064],"type":"Point"}
}