{
  "type": "Feature",
  "properties": {
    "gn:admin1_code":"2.0",
    "gn:admin2_code":"18020.0",
    "gn:asciiname":"Mooren",
    "gn:country_code":"AU",
    "gn:dem":391,
    "gn:feature_class":"P",
    "gn:feature_code":"PPL",
    "gn:name":"Mooren",
    "gn:population":0,
    "gn:timezone":"Australia/Sydney",
    "iso:country":"AU",
    "name:eng_x_preferred":[
        "Mooren"
    ],
    "wof:name":"Mooren",
    "wof:placetype":"locality"
},
  "geometry": {"coordinates":[149.34017,-31.68793],"type":"Point"}
}