{
  "type": "Feature",
  "properties": {
    "gn:admin1_code":"2.0",
    "gn:admin2_code":"17400.0",
    "gn:asciiname":"Springfield",
    "gn:country_code":"AU",
    "gn:dem":655,
    "gn:feature_class":"P",
    "gn:feature_code":"PPL",
    "gn:name":"Springfield",
    "gn:population":0,
    "gn:timezone":"Australia/Sydney",
    "iso:country":"AU",
    "name:eng_x_preferred":[
        "Springfield"
    ],
    "wof:name":"Springfield",
    "wof:placetype":"locality"
},
  "geometry": {"coordinates":[151.69682,-29.11258],"type":"Point"}
}