{
  "type": "Feature",
  "properties": {
    "gn:admin1_code":"8",
    "gn:admin2_code":"57630",
    "gn:asciiname":"Barrambie",
    "gn:country_code":"AU",
    "gn:dem":545,
    "gn:feature_class":"P",
    "gn:feature_code":"PPL",
    "gn:name":"Barrambie",
    "gn:population":0,
    "gn:timezone":"Australia/Perth",
    "iso:country":"AU",
    "name:eng_x_preferred":[
        "Barrambie"
    ],
    "wof:name":"Barrambie",
    "wof:placetype":"locality"
},
  "geometry": {"coordinates":[119.18781,-27.52481],"type":"Point"}
}