{
  "type": "Feature",
  "properties": {
    "iso:country":"AU",
    "name:eng_x_preferred":[
        "Hawksburn"
    ],
    "name:unk_x_variant":[
        "Hawksburn"
    ],
    "qs:gn_adm0_cc":"AU",
    "qs:gn_local":2158177,
    "qs:local_max":22745,
    "qs:local_sum":338594,
    "qs:localhoods":407,
    "qs:name":"Hawksburn",
    "qs:name_adm0":"Australia",
    "qs:name_adm1":"Victoria",
    "qs:name_adm2":"Stonnington",
    "qs:name_local":"Melbourne",
    "qs:photo_max":40,
    "qs:photo_sum":275,
    "qs:placetype":"Suburb",
    "qs:quad_count":14,
    "qs:woe_adm0":23424748,
    "qs:woe_adm1":2344705,
    "qs:woe_adm2":55863969,
    "qs:woe_lau":0,
    "qs:woe_local":1103816,
    "qs:woe_ver":"7.10.0",
    "wof:lang":[
        "eng"
    ],
    "wof:name":"Hawksburn",
    "wof:placetype":"neighbourhood"
},
  "geometry": {"coordinates":[145.00555600000001,-37.847441],"type":"Point"}
}