{
  "type": "Feature",
  "properties": {
    "iso:country":"AU",
    "name:ceb_x_preferred":[
        "Sovereign Hill"
    ],
    "name:eng_x_preferred":[
        "Sovereign Hill"
    ],
    "name:nor_x_preferred":[
        "Sovereign Hill"
    ],
    "name:swe_x_preferred":[
        "Sovereign Hill"
    ],
    "qs:gn_adm0_cc":"AU",
    "qs:gn_local":2177091,
    "qs:gn_nam_loc":"ballarat",
    "qs:gn_namadm1":"07",
    "qs:local_max":2722,
    "qs:local_sum":9720,
    "qs:localhoods":15,
    "qs:name":"Sovereign Hill",
    "qs:name_adm0":"Australia",
    "qs:name_adm1":"Victoria",
    "qs:name_adm2":"City of Ballarat",
    "qs:name_local":"Ballarat",
    "qs:photo_max":606,
    "qs:photo_sum":1392,
    "qs:placetype":"Suburb",
    "qs:quad_count":14,
    "qs:woe_adm0":23424748,
    "qs:woe_adm1":2344705,
    "qs:woe_adm2":55864013,
    "qs:woe_lau":0,
    "qs:woe_local":1100071,
    "qs:woe_ver":"7.10.0",
    "wof:lang":[
        "eng"
    ],
    "wof:name":"Sovereign Hill",
    "wof:placetype":"neighbourhood"
},
  "geometry": {"coordinates":[143.865196,-37.57735],"type":"Point"}
}