{
  "type": "Feature",
  "properties": {
    "gn:admin1_code":"4.0",
    "gn:admin2_code":"34860.0",
    "gn:asciiname":"Pickanjinnie",
    "gn:country_code":"AU",
    "gn:dem":316,
    "gn:feature_class":"P",
    "gn:feature_code":"PPL",
    "gn:name":"Pickanjinnie",
    "gn:population":0,
    "gn:timezone":"Australia/Brisbane",
    "iso:country":"AU",
    "name:eng_x_preferred":[
        "Pickanjinnie"
    ],
    "wof:name":"Pickanjinnie",
    "wof:placetype":"locality"
},
  "geometry": {"coordinates":[149.11328999999995,-26.58315],"type":"Point"}
}