{
  "type": "Feature",
  "properties": {
    "gn:admin1_code":"8",
    "gn:admin2_code":"51960",
    "gn:asciiname":"Spargoville",
    "gn:country_code":"AU",
    "gn:dem":436,
    "gn:feature_class":"P",
    "gn:feature_code":"PPL",
    "gn:name":"Spargoville",
    "gn:population":0,
    "gn:timezone":"Australia/Perth",
    "iso:country":"AU",
    "wof:name":"Spargoville",
    "wof:placetype":"locality"
},
  "geometry": {"coordinates":[121.46666999999999,-31.23333],"type":"Point"}
}