{
  "type": "Feature",
  "properties": {
    "gn:admin1_code":"8",
    "gn:admin2_code":"54280",
    "gn:asciiname":"Broad Arrow",
    "gn:country_code":"AU",
    "gn:dem":399,
    "gn:feature_class":"P",
    "gn:feature_code":"PPL",
    "gn:name":"Broad Arrow",
    "gn:population":0,
    "gn:timezone":"Australia/Perth",
    "iso:country":"AU",
    "wof:name":"Broad Arrow",
    "wof:placetype":"locality"
},
  "geometry": {"coordinates":[121.45,-30.33333],"type":"Point"}
}