{
  "type": "Feature",
  "properties": {
    "iso:country":"AU",
    "name:eng_x_preferred":[
        "Grafton Central"
    ],
    "name:unk_x_variant":[
        "Grafton Central"
    ],
    "qs:gn_adm0_cc":"AU",
    "qs:gn_local":2164771,
    "qs:gn_nam_loc":"grafton",
    "qs:gn_namadm1":"02",
    "qs:local_max":359,
    "qs:local_sum":715,
    "qs:localhoods":2,
    "qs:name":"Grafton Central",
    "qs:name_adm0":"Australia",
    "qs:name_adm1":"New South Wales",
    "qs:name_adm2":"Clarence Valley",
    "qs:name_local":"Grafton",
    "qs:photo_max":50,
    "qs:photo_sum":359,
    "qs:placetype":"Suburb",
    "qs:quad_count":26,
    "qs:woe_adm0":23424748,
    "qs:woe_adm1":2344700,
    "qs:woe_adm2":55864305,
    "qs:woe_lau":0,
    "qs:woe_local":1102409,
    "qs:woe_ver":"7.10.0",
    "wof:lang":[
        "eng"
    ],
    "wof:name":"Grafton Central",
    "wof:placetype":"neighbourhood"
},
  "geometry": {"coordinates":[152.93666999999999,-29.685162],"type":"Point"}
}