{
  "type": "Feature",
  "properties": {
    "gn:admin1_code":"7.0",
    "gn:admin2_code":"26610.0",
    "gn:asciiname":"Nowie North",
    "gn:country_code":"AU",
    "gn:dem":78,
    "gn:feature_class":"P",
    "gn:feature_code":"PPL",
    "gn:name":"Nowie North",
    "gn:population":0,
    "gn:timezone":"Australia/Melbourne",
    "iso:country":"AU",
    "wof:name":"Nowie North",
    "wof:placetype":"locality"
},
  "geometry": {"coordinates":[143.35543000000001,-35.24352000000001],"type":"Point"}
}