{
  "type": "Feature",
  "properties": {
    "gn:admin1_code":"5.0",
    "gn:admin2_code":"43570.0",
    "gn:asciiname":"Karinga",
    "gn:country_code":"AU",
    "gn:dem":81,
    "gn:feature_class":"P",
    "gn:feature_code":"PPL",
    "gn:name":"Karinga",
    "gn:population":0,
    "gn:timezone":"Australia/Adelaide",
    "iso:country":"AU",
    "name:eng_x_preferred":[
        "Karinga"
    ],
    "wof:name":"Karinga",
    "wof:placetype":"locality"
},
  "geometry": {"coordinates":[135.5692,-33.32348],"type":"Point"}
}