{
  "type": "Feature",
  "properties": {
    "gn:admin1_code":"5",
    "gn:admin2_code":"47490",
    "gn:asciiname":"Karcultaby",
    "gn:country_code":"AU",
    "gn:dem":111,
    "gn:feature_class":"P",
    "gn:feature_code":"PPL",
    "gn:name":"Karcultaby",
    "gn:population":0,
    "gn:timezone":"Australia/Adelaide",
    "iso:country":"AU",
    "wof:name":"Karcultaby",
    "wof:placetype":"locality"
},
  "geometry": {"coordinates":[134.96666999999999,-32.76667],"type":"Point"}
}