{
  "type": "Feature",
  "properties": {
    "iso:country":"AU",
    "name:ceb_x_preferred":[
        "Church Point"
    ],
    "name:eng_x_preferred":[
        "Church Point"
    ],
    "name:ita_x_preferred":[
        "Church Point"
    ],
    "name:swe_x_preferred":[
        "Church Point"
    ],
    "qs:gn_adm0_cc":"AU",
    "qs:gn_local":2147714,
    "qs:local_max":35533,
    "qs:local_sum":687549,
    "qs:localhoods":516,
    "qs:name":"Church Point",
    "qs:name_adm0":"Australia",
    "qs:name_adm1":"New South Wales",
    "qs:name_adm2":"Pittwater",
    "qs:name_local":"Sydney",
    "qs:photo_max":72,
    "qs:photo_sum":487,
    "qs:placetype":"Suburb",
    "qs:quad_count":33,
    "qs:woe_adm0":23424748,
    "qs:woe_adm1":2344700,
    "qs:woe_adm2":55864176,
    "qs:woe_lau":0,
    "qs:woe_local":1105779,
    "qs:woe_ver":"7.10.0",
    "wof:lang":[
        "eng"
    ],
    "wof:name":"Church Point",
    "wof:placetype":"neighbourhood"
},
  "geometry": {"coordinates":[151.26929166227771,-33.64941488476287],"type":"Point"}
}