{
  "type": "Feature",
  "properties": {
    "gn:admin1_code":"4.0",
    "gn:admin2_code":"33220.0",
    "gn:asciiname":"Orchid Beach Island Village",
    "gn:country_code":"AU",
    "gn:dem":65,
    "gn:feature_class":"P",
    "gn:feature_code":"PPL",
    "gn:name":"Orchid Beach Island Village",
    "gn:population":0,
    "gn:timezone":"Australia/Brisbane",
    "iso:country":"AU",
    "name:eng_x_preferred":[
        "Orchid Beach Island Village"
    ],
    "wof:name":"Orchid Beach Island Village",
    "wof:placetype":"locality"
},
  "geometry": {"coordinates":[153.31441000000001,-24.96735],"type":"Point"}
}