{
  "type": "Feature",
  "properties": {
    "gn:admin1_code":"2.0",
    "gn:admin2_code":"13700.0",
    "gn:asciiname":"Beaulambil",
    "gn:country_code":"AU",
    "gn:dem":489,
    "gn:feature_class":"P",
    "gn:feature_code":"PPL",
    "gn:name":"Beaulambil",
    "gn:population":0,
    "gn:timezone":"Australia/Sydney",
    "iso:country":"AU",
    "name:eng_x_preferred":[
        "Beaulambil"
    ],
    "wof:name":"Beaulambil",
    "wof:placetype":"locality"
},
  "geometry": {"coordinates":[148.58156,-34.55149],"type":"Point"}
}