{
  "type": "Feature",
  "properties": {
    "gn:country":"AU",
    "gn:fcode":"PPL",
    "gn:population":4363,
    "iso:country":"AU",
    "name:azb_x_preferred":[
        "\u0647\u0648\u0644\u0633\u0648\u0648\u0631\u062a\u06cc"
    ],
    "name:ceb_x_preferred":[
        "Holsworthy"
    ],
    "name:cym_x_preferred":[
        "Holsworthy"
    ],
    "name:deu_x_preferred":[
        "Holsworthy"
    ],
    "name:eng_x_preferred":[
        "Holsworthy"
    ],
    "name:fas_x_preferred":[
        "\u0647\u0648\u0644\u0633\u200c\u0648\u0631\u062a\u06cc"
    ],
    "name:fas_x_variant":[
        "\u0647\u0648\u0644\u0633\u0648\u0648\u0631\u062a\u06cc"
    ],
    "name:fra_x_preferred":[
        "Holsworthy"
    ],
    "name:gle_x_preferred":[
        "Holsworthy"
    ],
    "name:ita_x_preferred":[
        "Holsworthy"
    ],
    "name:jpn_x_preferred":[
        "\u30db\u30eb\u30b9\u30ef\u30fc\u30ba\u30a3\u30fc"
    ],
    "name:lat_x_preferred":[
        "Holsworthy"
    ],
    "name:mlg_x_preferred":[
        "Holsworthy"
    ],
    "name:nld_x_preferred":[
        "Holsworthy"
    ],
    "name:pol_x_preferred":[
        "Holsworthy"
    ],
    "name:ron_x_preferred":[
        "Holsworthy"
    ],
    "name:spa_x_preferred":[
        "Holsworthy"
    ],
    "name:swe_x_preferred":[
        "Holsworthy"
    ],
    "qs_pg:aaroncc":"AU",
    "qs_pg:gn_country":"AU",
    "qs_pg:gn_fcode":"PPL",
    "qs_pg:gn_pop":4363,
    "qs_pg:name":"Holsworthy",
    "qs_pg:name_adm0":"Australia",
    "qs_pg:name_adm1":"New South Wales",
    "qs_pg:photos":188,
    "qs_pg:photos_1k":38,
    "qs_pg:photos_9k":1,
    "qs_pg:photos_9r":4,
    "qs_pg:photos_all":188,
    "qs_pg:photos_sr":4,
    "qs_pg:pop_sr":4,
    "qs_pg:qs_pg_placetype":"locality",
    "qs_pg:qs_pg_placetype_gp":"Town",
    "qs_pg:woe_adm0":23424748,
    "woe:adm0_id":23424748,
    "woe:name_adm0":"Australia",
    "woe:name_adm1":"New South Wales",
    "woe:placetype":"Town",
    "wof:name":"Holsworthy",
    "wof:placetype":"locality",
    "wof:population":5476
},
  "geometry": {"coordinates":[150.96666999999999,-33.98333],"type":"Point"}
}