{
  "type": "Feature",
  "properties": {
    "gn:admin1_code":"4.0",
    "gn:admin2_code":"32260.0",
    "gn:asciiname":"Bombeeta",
    "gn:country_code":"AU",
    "gn:dem":84,
    "gn:feature_class":"P",
    "gn:feature_code":"PPL",
    "gn:name":"Bombeeta",
    "gn:population":0,
    "gn:timezone":"Australia/Brisbane",
    "iso:country":"AU",
    "wof:name":"Bombeeta",
    "wof:placetype":"locality"
},
  "geometry": {"coordinates":[145.96666999999999,-17.68332999999999],"type":"Point"}
}