{
  "type": "Feature",
  "properties": {
    "gn:admin1_code":"2",
    "gn:admin2_code":"16400",
    "gn:asciiname":"Swan Reach",
    "gn:country_code":"AU",
    "gn:dem":3,
    "gn:feature_class":"P",
    "gn:feature_code":"PPL",
    "gn:name":"Swan Reach",
    "gn:population":0,
    "gn:timezone":"Australia/Sydney",
    "iso:country":"AU",
    "wof:name":"Swan Reach",
    "wof:placetype":"locality"
},
  "geometry": {"coordinates":[151.66666999999995,-32.73333],"type":"Point"}
}