{
  "type": "Feature",
  "properties": {
    "gn:admin1_code":"2",
    "gn:admin2_code":"12600",
    "gn:asciiname":"Yerribah",
    "gn:country_code":"AU",
    "gn:dem":346,
    "gn:feature_class":"P",
    "gn:feature_code":"PPL",
    "gn:name":"Yerribah",
    "gn:population":0,
    "gn:timezone":"Australia/Sydney",
    "iso:country":"AU",
    "wof:name":"Yerribah",
    "wof:placetype":"locality"
},
  "geometry": {"coordinates":[148.46666999999999,-32.36667],"type":"Point"}
}