{
  "type": "Feature",
  "properties": {
    "gn:admin1_code":"7",
    "gn:admin2_code":"21670",
    "gn:asciiname":"Timor",
    "gn:country_code":"AU",
    "gn:dem":195,
    "gn:feature_class":"P",
    "gn:feature_code":"PPL",
    "gn:name":"Timor",
    "gn:population":0,
    "gn:timezone":"Australia/Melbourne",
    "iso:country":"AU",
    "wof:name":"Timor",
    "wof:placetype":"locality"
},
  "geometry": {"coordinates":[143.71393999999995,-36.9859],"type":"Point"}
}