{
  "type": "Feature",
  "properties": {
    "gn:admin1_code":"4.0",
    "gn:admin2_code":"33980.0",
    "gn:asciiname":"Turrawalla",
    "gn:country_code":"AU",
    "gn:dem":255,
    "gn:feature_class":"P",
    "gn:feature_code":"PPL",
    "gn:name":"Turrawalla",
    "gn:population":0,
    "gn:timezone":"Australia/Brisbane",
    "iso:country":"AU",
    "name:eng_x_preferred":[
        "Turrawalla"
    ],
    "wof:name":"Turrawalla",
    "wof:placetype":"locality"
},
  "geometry": {"coordinates":[148.23675,-21.16782000000001],"type":"Point"}
}