{
  "type": "Feature",
  "properties": {
    "gn:admin1_code":"2",
    "gn:admin2_code":"13400",
    "gn:asciiname":"The Branch",
    "gn:country_code":"AU",
    "gn:dem":35,
    "gn:feature_class":"P",
    "gn:feature_code":"PPL",
    "gn:name":"The Branch",
    "gn:population":0,
    "gn:timezone":"Australia/Sydney",
    "iso:country":"AU",
    "wof:name":"The Branch",
    "wof:placetype":"locality"
},
  "geometry": {"coordinates":[152.01667,-32.53333],"type":"Point"}
}