{
  "type": "Feature",
  "properties": {
    "gn:admin1_code":"6.0",
    "gn:admin2_code":"60810.0",
    "gn:asciiname":"Abbotsham",
    "gn:country_code":"AU",
    "gn:dem":168,
    "gn:feature_class":"P",
    "gn:feature_code":"PPL",
    "gn:name":"Abbotsham",
    "gn:population":0,
    "gn:timezone":"Australia/Hobart",
    "iso:country":"AU",
    "name:ceb_x_preferred":[
        "Abbotsham"
    ],
    "name:cym_x_preferred":[
        "Abbotsham"
    ],
    "name:eng_x_preferred":[
        "Abbotsham"
    ],
    "name:fas_x_preferred":[
        "\u0627\u0628\u0628\u062a\u0634\u0645"
    ],
    "name:ita_x_preferred":[
        "Abbotsham"
    ],
    "name:nld_x_preferred":[
        "Abbotsham"
    ],
    "name:pol_x_preferred":[
        "Abbotsham"
    ],
    "name:swe_x_preferred":[
        "Abbotsham"
    ],
    "wof:name":"Abbotsham",
    "wof:placetype":"locality"
},
  "geometry": {"coordinates":[146.17316,-41.22649000000001],"type":"Point"}
}