{
  "type": "Feature",
  "properties": {
    "gn:admin1_code":"7.0",
    "gn:admin2_code":"26430.0",
    "gn:asciiname":"Graytown",
    "gn:country_code":"AU",
    "gn:dem":162,
    "gn:feature_class":"P",
    "gn:feature_code":"PPL",
    "gn:name":"Graytown",
    "gn:population":0,
    "gn:timezone":"Australia/Melbourne",
    "iso:country":"AU",
    "name:deu_x_preferred":[
        "Graytown"
    ],
    "wof:name":"Graytown",
    "wof:placetype":"locality"
},
  "geometry": {"coordinates":[144.94999999999999,-36.81667],"type":"Point"}
}