{
  "type": "Feature",
  "properties": {
    "gn:admin1_code":"4.0",
    "gn:admin2_code":"30900.0",
    "gn:asciiname":"Saint Lucia",
    "gn:country_code":"AU",
    "gn:dem":188,
    "gn:feature_class":"P",
    "gn:feature_code":"PPL",
    "gn:name":"Saint Lucia",
    "gn:population":0,
    "gn:timezone":"Australia/Brisbane",
    "iso:country":"AU",
    "name:eng_x_preferred":[
        "Saint Lucia"
    ],
    "wof:name":"Saint Lucia",
    "wof:placetype":"locality"
},
  "geometry": {"coordinates":[140.50382999999999,-22.59683],"type":"Point"}
}