{
  "type": "Feature",
  "properties": {
    "gn:admin1_code":"7.0",
    "gn:admin2_code":"27630.0",
    "gn:asciiname":"Mellis",
    "gn:country_code":"AU",
    "gn:dem":119,
    "gn:feature_class":"P",
    "gn:feature_code":"PPL",
    "gn:name":"Mellis",
    "gn:population":0,
    "gn:timezone":"Australia/Melbourne",
    "iso:country":"AU",
    "name:ceb_x_preferred":[
        "Mellis"
    ],
    "name:nld_x_preferred":[
        "Mellis"
    ],
    "name:pol_x_preferred":[
        "Mellis"
    ],
    "name:spa_x_preferred":[
        "Mellis"
    ],
    "name:swe_x_preferred":[
        "Mellis"
    ],
    "wof:name":"Mellis",
    "wof:placetype":"locality"
},
  "geometry": {"coordinates":[142.44999999999999,-36.28333],"type":"Point"}
}