{
  "type": "Feature",
  "properties": {
    "gn:population":5486,
    "iso:country":"AU",
    "name:eng_x_preferred":[
        "Wooloowin"
    ],
    "name:unk_x_variant":[
        "Wooloowin"
    ],
    "qs:gn_adm0_cc":"AU",
    "qs:gn_fcode":"PPL",
    "qs:gn_local":2174003,
    "qs:gn_nam_loc":"Brisbane, Brisbane, Queensland, AU",
    "qs:gn_namadm1":"04",
    "qs:gn_name":"Wooloowin",
    "qs:local_max":15217,
    "qs:local_sum":137917,
    "qs:localhoods":252,
    "qs:name":"Wooloowin",
    "qs:name_adm0":"Australia",
    "qs:name_adm1":"Queensland",
    "qs:name_adm2":"Brisbane",
    "qs:name_local":"Brisbane",
    "qs:photo_max":401,
    "qs:photo_sum":547,
    "qs:placetype":"Suburb",
    "qs:quad_count":14,
    "qs:woe_adm0":23424748,
    "qs:woe_adm1":2344702,
    "qs:woe_adm2":55864298,
    "qs:woe_lau":0,
    "qs:woe_local":1100661,
    "qs:woe_ver":"7.10.0",
    "wof:name":"Wooloowin",
    "wof:placetype":"neighbourhood",
    "wof:population":5486
},
  "geometry": {"coordinates":[153.04836499999999,-27.419598],"type":"Point"}
}