{
  "type": "Feature",
  "properties": {
    "gn:admin1_code":"04",
    "gn:admin2_code":"32070.0",
    "gn:asciiname":"Rocky Point",
    "gn:country_code":"AU",
    "gn:dem":52,
    "gn:feature_class":"P",
    "gn:feature_code":"PPL",
    "gn:name":"Rocky Point",
    "gn:population":0,
    "gn:timezone":"Australia/Brisbane",
    "iso:country":"AU",
    "wof:name":"Rocky Point",
    "wof:placetype":"locality"
},
  "geometry": {"coordinates":[145.40559999999999,-16.39072],"type":"Point"}
}