{
  "type": "Feature",
  "properties": {
    "gn:admin1_code":"2.0",
    "gn:admin2_code":"14600.0",
    "gn:asciiname":"Micabil",
    "gn:country_code":"AU",
    "gn:dem":184,
    "gn:feature_class":"P",
    "gn:feature_code":"PPL",
    "gn:name":"Micabil",
    "gn:population":0,
    "gn:timezone":"Australia/Sydney",
    "iso:country":"AU",
    "name:eng_x_preferred":[
        "Micabil"
    ],
    "wof:name":"Micabil",
    "wof:placetype":"locality"
},
  "geometry": {"coordinates":[146.97132999999999,-33.0897],"type":"Point"}
}