{
  "type": "Feature",
  "properties": {
    "gn:admin1_code":"2.0",
    "gn:admin2_code":"14950.0",
    "gn:asciiname":"Lallahrook",
    "gn:country_code":"AU",
    "gn:dem":223,
    "gn:feature_class":"P",
    "gn:feature_code":"PPL",
    "gn:name":"Lallahrook",
    "gn:population":0,
    "gn:timezone":"Australia/Sydney",
    "iso:country":"AU",
    "wof:name":"Lallahrook",
    "wof:placetype":"locality"
},
  "geometry": {"coordinates":[146.82675,-35.37237000000001],"type":"Point"}
}