{
  "type": "Feature",
  "properties": {
    "iso:country":"AU",
    "name:jpn_x_preferred":[
        "\u30c7\u30a3\u30fc\u30d7\u30c7\u30a3\u30fc\u30f3"
    ],
    "qs_pg:aaroncc":"AU",
    "qs_pg:name":"Deepdene",
    "qs_pg:name_adm0":"Australia",
    "qs_pg:name_adm1":"Western Australia",
    "qs_pg:photos":148,
    "qs_pg:photos_1k":30,
    "qs_pg:photos_9k":1,
    "qs_pg:photos_9r":3,
    "qs_pg:photos_all":148,
    "qs_pg:photos_sr":3,
    "qs_pg:pop_sr":0,
    "qs_pg:qs_pg_placetype":"locality",
    "qs_pg:qs_pg_placetype_gp":"Town",
    "qs_pg:woe_adm0":23424748,
    "woe:adm0_id":23424748,
    "woe:name_adm0":"Australia",
    "woe:name_adm1":"Western Australia",
    "woe:placetype":"Town",
    "wof:name":"Deepdene",
    "wof:placetype":"locality"
},
  "geometry": {"coordinates":[115.08110000000001,-34.265445],"type":"Point"}
}