{
  "type": "Feature",
  "properties": {
    "gn:admin1_code":"5.0",
    "gn:admin2_code":"47490.0",
    "gn:asciiname":"Aldergrove",
    "gn:country_code":"AU",
    "gn:dem":31,
    "gn:feature_class":"P",
    "gn:feature_code":"PPL",
    "gn:name":"Aldergrove",
    "gn:population":0,
    "gn:timezone":"Australia/Adelaide",
    "iso:country":"AU",
    "name:eng_x_preferred":[
        "Aldergrove"
    ],
    "wof:name":"Aldergrove",
    "wof:placetype":"locality"
},
  "geometry": {"coordinates":[134.29948999999999,-32.58996],"type":"Point"}
}