{
  "type": "Feature",
  "properties": {
    "gn:admin1_code":"2.0",
    "gn:admin2_code":"14600.0",
    "gn:asciiname":"Ellerslie",
    "gn:country_code":"AU",
    "gn:dem":199,
    "gn:feature_class":"P",
    "gn:feature_code":"PPL",
    "gn:name":"Ellerslie",
    "gn:population":0,
    "gn:timezone":"Australia/Sydney",
    "iso:country":"AU",
    "name:ceb_x_preferred":[
        "Ellerslie"
    ],
    "name:deu_x_preferred":[
        "Ellerslie"
    ],
    "name:eng_x_preferred":[
        "Ellerslie"
    ],
    "name:swe_x_preferred":[
        "Ellerslie"
    ],
    "wof:name":"Ellerslie",
    "wof:placetype":"locality"
},
  "geometry": {"coordinates":[147.24617000000001,-33.31032],"type":"Point"}
}