{
  "type": "Feature",
  "properties": {
    "gn:admin1_code":"5",
    "gn:admin2_code":"48830",
    "gn:asciiname":"Yongala Cowie",
    "gn:country_code":"AU",
    "gn:dem":33,
    "gn:feature_class":"P",
    "gn:feature_code":"PPL",
    "gn:name":"Yongala Cowie",
    "gn:population":0,
    "gn:timezone":"Australia/Adelaide",
    "iso:country":"AU",
    "name:und_x_variant":[
        "Roger Corner",
        "Yongala",
        "Yongala Cowie"
    ],
    "wof:name":"Yongala Cowie",
    "wof:placetype":"locality"
},
  "geometry": {"coordinates":[137.55000000000001,-34.91667],"type":"Point"}
}