{
  "type": "Feature",
  "properties": {
    "gn:admin1_code":"2",
    "gn:admin2_code":"16950",
    "gn:asciiname":"Tianjara",
    "gn:country_code":"AU",
    "gn:dem":501,
    "gn:feature_class":"P",
    "gn:feature_code":"PPL",
    "gn:name":"Tianjara",
    "gn:population":0,
    "gn:timezone":"Australia/Sydney",
    "iso:country":"AU",
    "wof:name":"Tianjara",
    "wof:placetype":"locality"
},
  "geometry": {"coordinates":[150.33333000000005,-35.11667],"type":"Point"}
}