{
  "type": "Feature",
  "properties": {
    "gn:admin1_code":"4.0",
    "gn:admin2_code":"36580.0",
    "gn:asciiname":"Caboonbah",
    "gn:country_code":"AU",
    "gn:dem":65,
    "gn:feature_class":"P",
    "gn:feature_code":"PPL",
    "gn:name":"Caboonbah",
    "gn:population":0,
    "gn:timezone":"Australia/Brisbane",
    "iso:country":"AU",
    "wof:name":"Caboonbah",
    "wof:placetype":"locality"
},
  "geometry": {"coordinates":[152.48333,-27.15],"type":"Point"}
}