{
  "type": "Feature",
  "properties": {
    "gn:admin1_code":"2.0",
    "gn:admin2_code":"14950.0",
    "gn:asciiname":"Brookong",
    "gn:country_code":"AU",
    "gn:dem":147,
    "gn:feature_class":"P",
    "gn:feature_code":"PPL",
    "gn:name":"Brookong",
    "gn:population":0,
    "gn:timezone":"Australia/Sydney",
    "iso:country":"AU",
    "wof:name":"Brookong",
    "wof:placetype":"locality"
},
  "geometry": {"coordinates":[146.63636,-35.18436],"type":"Point"}
}