{
  "type": "Feature",
  "properties": {
    "gn:admin1_code":"7.0",
    "gn:admin2_code":"21750.0",
    "gn:asciiname":"Forrest",
    "gn:country_code":"AU",
    "gn:dem":184,
    "gn:feature_class":"P",
    "gn:feature_code":"PPL",
    "gn:name":"Forrest",
    "gn:population":0,
    "gn:timezone":"Australia/Melbourne",
    "iso:country":"AU",
    "wof:name":"Forrest",
    "wof:placetype":"locality"
},
  "geometry": {"coordinates":[143.71666999999999,-38.51667],"type":"Point"}
}