{
  "type": "Feature",
  "properties": {
    "gn:country":"AU",
    "gn:fcode":"PPL",
    "gn:population":382,
    "iso:country":"AU",
    "name:ast_x_preferred":[
        "Oura"
    ],
    "name:ceb_x_preferred":[
        "Oura"
    ],
    "name:eng_x_preferred":[
        "Oura"
    ],
    "name:fas_x_preferred":[
        "\u0627\u0648\u0631\u0627"
    ],
    "name:fra_x_preferred":[
        "Oura"
    ],
    "name:nld_x_preferred":[
        "Oura"
    ],
    "name:swe_x_preferred":[
        "Oura"
    ],
    "qs_pg:aaroncc":"AU",
    "qs_pg:gn_country":"AU",
    "qs_pg:gn_fcode":"PPL",
    "qs_pg:gn_pop":382,
    "qs_pg:name":"Oura",
    "qs_pg:name_adm0":"Australia",
    "qs_pg:name_adm1":"New South Wales",
    "qs_pg:photos_9k":1,
    "qs_pg:photos_9r":1,
    "qs_pg:photos_all":3,
    "qs_pg:photos_sr":0,
    "qs_pg:pop_sr":2,
    "qs_pg:qs_pg_placetype":"locality",
    "qs_pg:qs_pg_placetype_gp":"Town",
    "qs_pg:woe_adm0":23424748,
    "woe:adm0_id":23424748,
    "woe:name_adm0":"Australia",
    "woe:name_adm1":"New South Wales",
    "woe:placetype":"Town",
    "wof:name":"Oura",
    "wof:placetype":"locality",
    "wof:population":382
},
  "geometry": {"coordinates":[147.53333000000001,-35.11667],"type":"Point"}
}