{
  "type": "Feature",
  "properties": {
    "gn:admin1_code":"7.0",
    "gn:admin2_code":"21370.0",
    "gn:asciiname":"Mologa",
    "gn:country_code":"AU",
    "gn:dem":96,
    "gn:feature_class":"P",
    "gn:feature_code":"PPL",
    "gn:name":"Mologa",
    "gn:population":0,
    "gn:timezone":"Australia/Melbourne",
    "iso:country":"AU",
    "name:fin_x_preferred":[
        "Mologa"
    ],
    "name:fra_x_preferred":[
        "Mologa"
    ],
    "name:heb_x_preferred":[
        "\u05de\u05d5\u05dc\u05d5\u05d2\u05d4"
    ],
    "name:ita_x_preferred":[
        "Mologa"
    ],
    "name:nld_x_preferred":[
        "Mologa"
    ],
    "name:pol_x_preferred":[
        "Mo\u0142oga"
    ],
    "name:rus_x_preferred":[
        "\u041c\u043e\u043b\u043e\u0433\u0430"
    ],
    "name:swe_x_preferred":[
        "Mologa"
    ],
    "name:ukr_x_preferred":[
        "\u041c\u043e\u043b\u043e\u0433\u0430"
    ],
    "wof:name":"Mologa",
    "wof:placetype":"locality"
},
  "geometry": {"coordinates":[144.17908,-36.1437],"type":"Point"}
}