{
  "type": "Feature",
  "properties": {
    "iso:country":"AU",
    "name:deu_x_preferred":[
        "Newcastle Waters"
    ],
    "name:eng_x_preferred":[
        "Newcastle Waters"
    ],
    "name:fas_x_preferred":[
        "\u0646\u06cc\u0648\u06a9\u0627\u0633\u0644 \u0648\u0627\u062a\u0631\u0632"
    ],
    "name:fra_x_preferred":[
        "Newcastle Waters"
    ],
    "name:nld_x_preferred":[
        "Newcastle Waters"
    ],
    "name:nld_x_variant":[
        "Central Coast"
    ],
    "name:por_x_preferred":[
        "Newcastle Waters"
    ],
    "name:spa_x_preferred":[
        "Newcastle Waters"
    ],
    "name:zho_x_preferred":[
        "\u7d10\u5361\u7d20\u6c83\u5854\u65af"
    ],
    "ne:ADM0CAP":0.0,
    "ne:ADM0NAME":"Australia",
    "ne:ADM0_A3":"AUS",
    "ne:ADM1NAME":"Northern Territory",
    "ne:ADMIN1_COD":0,
    "ne:CAPALT":0,
    "ne:CHANGED":0,
    "ne:CHECKME":0,
    "ne:COMPARE":0,
    "ne:DIFFASCII":0,
    "ne:ELEVATION":0.0,
    "ne:FEATURECLA":"Populated place",
    "ne:GEONAMEID":-1,
    "ne:GEONAMESNO":"No GeoNames match due to small population, not in GeoNames, or poor NEV placement.",
    "ne:GN_POP":0,
    "ne:GTOPO30":0.0,
    "ne:ISO_A2":"AU",
    "ne:LABELRANK":3,
    "ne:LATITUDE":-17.552793,
    "ne:LONGITUDE":133.467243,
    "ne:LS_MATCH":0,
    "ne:LS_NAME":"Newcastle Waters",
    "ne:MAX_AREAKM":0.0,
    "ne:MAX_AREAMI":0.0,
    "ne:MAX_BBXMAX":0.0,
    "ne:MAX_BBXMIN":0.0,
    "ne:MAX_BBYMAX":0.0,
    "ne:MAX_BBYMIN":0.0,
    "ne:MAX_NATSCA":0.0,
    "ne:MAX_PERKM":0.0,
    "ne:MAX_PERMI":0.0,
    "ne:MAX_POP10":0,
    "ne:MAX_POP20":0,
    "ne:MAX_POP300":0,
    "ne:MAX_POP310":0,
    "ne:MAX_POP50":0,
    "ne:MEAN_BBXC":0.0,
    "ne:MEAN_BBYC":0.0,
    "ne:MEGACITY":0,
    "ne:MIN_AREAKM":0.0,
    "ne:MIN_AREAMI":0.0,
    "ne:MIN_BBXMAX":0.0,
    "ne:MIN_BBXMIN":0.0,
    "ne:MIN_BBYMAX":0.0,
    "ne:MIN_BBYMIN":0.0,
    "ne:MIN_PERKM":0.0,
    "ne:MIN_PERMI":0.0,
    "ne:NAME":"Newcastle Waters",
    "ne:NAMEASCII":"Newcastle Waters",
    "ne:NAMEDIFF":0,
    "ne:NATSCALE":20,
    "ne:POP1950":0,
    "ne:POP1955":0,
    "ne:POP1960":0,
    "ne:POP1965":0,
    "ne:POP1970":0,
    "ne:POP1975":0,
    "ne:POP1980":0,
    "ne:POP1985":0,
    "ne:POP1990":0,
    "ne:POP1995":0,
    "ne:POP2000":0,
    "ne:POP2005":0,
    "ne:POP2010":0,
    "ne:POP2015":0,
    "ne:POP2020":0,
    "ne:POP2025":0,
    "ne:POP2050":0,
    "ne:POP_MAX":10,
    "ne:POP_MIN":10,
    "ne:POP_OTHER":0,
    "ne:RANK_MAX":1,
    "ne:RANK_MIN":1,
    "ne:SCALERANK":7,
    "ne:SOV0NAME":"Australia",
    "ne:SOV_A3":"AUS",
    "ne:UN_FID":0,
    "ne:UN_LAT":0.0,
    "ne:UN_LONG":0.0,
    "ne:WORLDCITY":0,
    "ne:min_zoom":6.7,
    "wof:name":"Newcastle Waters",
    "wof:placetype":"locality"
},
  "geometry": {"coordinates":[133.46724320387182,-17.55279294959803],"type":"Point"}
}