{
  "type": "Feature",
  "properties": {
    "iso:country":"AU",
    "name:eng_x_preferred":[
        "Dobroyd Point"
    ],
    "name:ron_x_preferred":[
        "Dobroyd Point"
    ],
    "name:unk_x_variant":[
        "Dobroyd Point"
    ],
    "qs:gn_adm0_cc":"AU",
    "qs:gn_local":2147714,
    "qs:local_max":35533,
    "qs:local_sum":687549,
    "qs:localhoods":516,
    "qs:name":"Dobroyd Point",
    "qs:name_adm0":"Australia",
    "qs:name_adm1":"New South Wales",
    "qs:name_adm2":"Municipality of Ashfield",
    "qs:name_local":"Sydney",
    "qs:photo_max":269,
    "qs:photo_sum":1621,
    "qs:placetype":"Suburb",
    "qs:quad_count":48,
    "qs:woe_adm0":23424748,
    "qs:woe_adm1":2344700,
    "qs:woe_adm2":55864186,
    "qs:woe_lau":0,
    "qs:woe_local":1105779,
    "qs:woe_ver":"7.10.0",
    "wd:wordcount":141,
    "wof:lang":[
        "eng"
    ],
    "wof:name":"Dobroyd Point",
    "wof:placetype":"neighbourhood"
},
  "geometry": {"coordinates":[151.144712,-33.873331],"type":"Point"}
}