{
  "type": "Feature",
  "properties": {
    "gn:admin1_code":"4.0",
    "gn:admin2_code":"33980.0",
    "gn:asciiname":"Clydevale",
    "gn:country_code":"AU",
    "gn:dem":332,
    "gn:feature_class":"P",
    "gn:feature_code":"PPL",
    "gn:name":"Clydevale",
    "gn:population":0,
    "gn:timezone":"Australia/Brisbane",
    "iso:country":"AU",
    "name:eng_x_preferred":[
        "Clydevale"
    ],
    "wof:name":"Clydevale",
    "wof:placetype":"locality"
},
  "geometry": {"coordinates":[147.23328000000001,-22.8607],"type":"Point"}
}