{
  "type": "Feature",
  "properties": {
    "iso:country":"AU",
    "name:eng_x_preferred":[
        "Hawker"
    ],
    "name:hun_x_preferred":[
        "Hawker"
    ],
    "name:unk_x_variant":[
        "Hawker"
    ],
    "qs:gn_adm0_cc":"AU",
    "qs:gn_fcode":"PPLX",
    "qs:gn_local":2172517,
    "qs:gn_namadm1":"01",
    "qs:gn_name":"Hawker",
    "qs:local_max":10266,
    "qs:local_sum":72297,
    "qs:localhoods":96,
    "qs:name":"Hawker",
    "qs:name_adm0":"Australia",
    "qs:name_adm1":"Australian Capital Territory",
    "qs:name_adm2":"Canberra",
    "qs:name_local":"Canberra",
    "qs:photo_max":23,
    "qs:photo_sum":156,
    "qs:placetype":"Suburb",
    "qs:quad_count":25,
    "qs:woe_adm0":23424748,
    "qs:woe_adm1":2344699,
    "qs:woe_adm2":55863865,
    "qs:woe_lau":0,
    "qs:woe_local":1100968,
    "qs:woe_ver":"7.10.0",
    "wof:name":"Hawker",
    "wof:placetype":"neighbourhood"
},
  "geometry": {"coordinates":[149.02786338488039,-35.25540667738323],"type":"Point"}
}