{
  "type": "Feature",
  "properties": {
    "iso:country":"AU",
    "name:eng_x_preferred":[
        "Norwood South"
    ],
    "name:unk_x_variant":[
        "Norwood South"
    ],
    "qs:gn_adm0_cc":"AU",
    "qs:gn_local":2078025,
    "qs:local_max":18505,
    "qs:local_sum":99726,
    "qs:localhoods":191,
    "qs:name":"Norwood South",
    "qs:name_adm0":"Australia",
    "qs:name_adm1":"South Australia",
    "qs:name_adm2":"Adelaide",
    "qs:name_local":"Adelaide",
    "qs:photo_max":937,
    "qs:photo_sum":1681,
    "qs:placetype":"Suburb",
    "qs:quad_count":11,
    "qs:woe_adm0":23424748,
    "qs:woe_adm1":2344703,
    "qs:woe_adm2":55864133,
    "qs:woe_lau":0,
    "qs:woe_local":1099805,
    "qs:woe_ver":"7.10.0",
    "wd:wordcount":721,
    "wof:lang":[
        "eng"
    ],
    "wof:name":"Norwood South",
    "wof:placetype":"neighbourhood"
},
  "geometry": {"coordinates":[138.62459899999999,-34.928898],"type":"Point"}
}