{
  "type": "Feature",
  "properties": {
    "gn:admin1_code":"4",
    "gn:admin2_code":"36910",
    "gn:asciiname":"Woodleighton",
    "gn:country_code":"AU",
    "gn:dem":492,
    "gn:feature_class":"P",
    "gn:feature_code":"PPL",
    "gn:name":"Woodleighton",
    "gn:population":0,
    "gn:timezone":"Australia/Brisbane",
    "iso:country":"AU",
    "wof:name":"Woodleighton",
    "wof:placetype":"locality"
},
  "geometry": {"coordinates":[151.68333000000001,-27.08333],"type":"Point"}
}