{
  "type": "Feature",
  "properties": {
    "gn:admin1_code":"2.0",
    "gn:admin2_code":"13550.0",
    "gn:asciiname":"Milroy",
    "gn:country_code":"AU",
    "gn:dem":354,
    "gn:feature_class":"P",
    "gn:feature_code":"PPL",
    "gn:name":"Milroy",
    "gn:population":0,
    "gn:timezone":"Australia/Sydney",
    "iso:country":"AU",
    "name:ceb_x_preferred":[
        "Milroy"
    ],
    "name:deu_x_preferred":[
        "Milroy"
    ],
    "name:ita_x_preferred":[
        "Milroy"
    ],
    "name:nld_x_preferred":[
        "Milroy"
    ],
    "name:pol_x_preferred":[
        "Milroy"
    ],
    "name:por_x_preferred":[
        "Milroy"
    ],
    "name:srp_x_preferred":[
        "\u041c\u0438\u043b\u0440\u043e\u0458"
    ],
    "name:ukr_x_preferred":[
        "\u041c\u0456\u043b\u0440\u043e\u0439"
    ],
    "name:vol_x_preferred":[
        "Milroy"
    ],
    "wof:name":"Milroy",
    "wof:placetype":"locality"
},
  "geometry": {"coordinates":[150.05000000000001,-31.15],"type":"Point"}
}