{
  "type": "Feature",
  "properties": {
    "gn:admin1_code":"2.0",
    "gn:admin2_code":"13550.0",
    "gn:asciiname":"Milroy",
    "gn:country_code":"AU",
    "gn:dem":354,
    "gn:feature_class":"P",
    "gn:feature_code":"PPL",
    "gn:name":"Milroy",
    "gn:population":0,
    "gn:timezone":"Australia/Sydney",
    "iso:country":"AU",
    "wof:name":"Milroy",
    "wof:placetype":"locality"
},
  "geometry": {"coordinates":[150.05000000000001,-31.15],"type":"Point"}
}