{
  "type": "Feature",
  "properties": {
    "gn:admin1_code":"2.0",
    "gn:admin2_code":"11000.0",
    "gn:asciiname":"Bindaree",
    "gn:country_code":"AU",
    "gn:dem":848,
    "gn:feature_class":"P",
    "gn:feature_code":"PPL",
    "gn:name":"Bindaree",
    "gn:population":0,
    "gn:timezone":"Australia/Sydney",
    "iso:country":"AU",
    "name:eng_x_preferred":[
        "Bindaree"
    ],
    "name:jpn_x_preferred":[
        "\u30d3\u30f3\u30c0\u30ea\u30fc"
    ],
    "wof:name":"Bindaree",
    "wof:placetype":"locality"
},
  "geometry": {"coordinates":[149.27739,-36.94331],"type":"Point"}
}