{
  "type": "Feature",
  "properties": {
    "iso:country":"AU",
    "name:eng_x_preferred":[
        "Ballarat"
    ],
    "wof:coterminous":[
        1376953323
    ],
    "wof:lang_x_official":[
        "eng"
    ],
    "wof:lang_x_spoken":[
        "eng"
    ],
    "wof:name":"Ballarat",
    "wof:placetype":"locality"
},
  "geometry": {"coordinates":[143.852395,-37.563892],"type":"Point"}
}