{
  "type": "Feature",
  "properties": {
    "iso:country":"AU",
    "name:ara_x_preferred":[
        "\u0628\u0627\u0644\u0627\u0631\u0627\u062a"
    ],
    "name:bel_x_preferred":[
        "\u0411\u0430\u043b\u0430\u0440\u0430\u0442"
    ],
    "name:bul_x_preferred":[
        "\u0411\u0430\u043b\u0430\u0440\u0430\u0442"
    ],
    "name:ceb_x_preferred":[
        "Ballarat"
    ],
    "name:ces_x_preferred":[
        "Ballarat"
    ],
    "name:ckb_x_preferred":[
        "\u0628\u06d5\u0644\u06ce\u0631\u0627\u062a"
    ],
    "name:cym_x_preferred":[
        "Ballarat"
    ],
    "name:dan_x_preferred":[
        "Ballarat"
    ],
    "name:deu_x_preferred":[
        "Ballarat"
    ],
    "name:ell_x_preferred":[
        "\u039c\u03c0\u03b1\u03bb\u03b1\u03c1\u03ac\u03c4"
    ],
    "name:eng_x_preferred":[
        "Ballarat"
    ],
    "name:fas_x_preferred":[
        "\u0628\u0644\u0631\u062a"
    ],
    "name:fin_x_preferred":[
        "Ballarat"
    ],
    "name:fra_x_preferred":[
        "Ballarat"
    ],
    "name:gle_x_preferred":[
        "Ballarat"
    ],
    "name:glg_x_preferred":[
        "Ballarat"
    ],
    "name:heb_x_preferred":[
        "\u05d1\u05dc\u05d0\u05e8\u05d0\u05d8"
    ],
    "name:ind_x_preferred":[
        "Ballarat"
    ],
    "name:ita_x_preferred":[
        "Ballarat"
    ],
    "name:jav_x_preferred":[
        "Ballarat"
    ],
    "name:jpn_x_preferred":[
        "\u30d0\u30e9\u30e9\u30c3\u30c8"
    ],
    "name:kat_x_preferred":[
        "\u10d1\u10d0\u10da\u10d0\u10e0\u10d0\u10e2\u10d8"
    ],
    "name:kor_x_preferred":[
        "\ubc38\ub7ec\ub7ab"
    ],
    "name:lit_x_preferred":[
        "Balaratas"
    ],
    "name:mlg_x_preferred":[
        "Ballarat"
    ],
    "name:mon_x_preferred":[
        "\u0411\u0430\u043b\u043b\u0430\u0440\u0430\u0442"
    ],
    "name:msa_x_preferred":[
        "Ballarat"
    ],
    "name:nld_x_preferred":[
        "Ballarat"
    ],
    "name:nor_x_preferred":[
        "Ballarat"
    ],
    "name:pnb_x_preferred":[
        "\u0628\u0627\u0644\u0627\u0631\u062a"
    ],
    "name:pol_x_preferred":[
        "Ballarat"
    ],
    "name:por_x_preferred":[
        "Ballarat"
    ],
    "name:ron_x_preferred":[
        "Ballarat"
    ],
    "name:rus_x_preferred":[
        "\u0411\u0430\u043b\u043b\u0430\u0440\u0430\u0442"
    ],
    "name:san_x_preferred":[
        "\u092c\u0932\u094d\u0932\u093e\u0930\u0924"
    ],
    "name:spa_x_preferred":[
        "Ballarat"
    ],
    "name:srp_x_preferred":[
        "\u0411\u0430\u043b\u0430\u0440\u0430\u0442"
    ],
    "name:swe_x_preferred":[
        "Ballarat"
    ],
    "name:tat_x_preferred":[
        "\u0411\u04d9\u043b\u0435\u0440\u04d9\u0442"
    ],
    "name:tur_x_preferred":[
        "Ballarat"
    ],
    "name:ukr_x_preferred":[
        "\u0411\u0430\u043b\u043b\u0430\u0440\u0430\u0442"
    ],
    "name:urd_x_preferred":[
        "\u0628\u0627\u0644\u0627\u0631\u0627\u0679"
    ],
    "name:vie_x_preferred":[
        "Ballarat"
    ],
    "name:zho_x_preferred":[
        "\u5df4\u62c9\u745e\u7279"
    ],
    "wof:coterminous":[
        1376953323
    ],
    "wof:lang_x_official":[
        "eng"
    ],
    "wof:lang_x_spoken":[
        "eng"
    ],
    "wof:name":"Ballarat",
    "wof:placetype":"locality"
},
  "geometry": {"coordinates":[143.852395,-37.563892],"type":"Point"}
}