{
  "type": "Feature",
  "properties": {
    "gn:admin1_code":"2",
    "gn:admin2_code":"14750",
    "gn:asciiname":"Wamoon",
    "gn:country_code":"AU",
    "gn:dem":136,
    "gn:feature_class":"P",
    "gn:feature_code":"PPL",
    "gn:name":"Wamoon",
    "gn:population":0,
    "gn:timezone":"Australia/Sydney",
    "iso:country":"AU",
    "wof:name":"Wamoon",
    "wof:placetype":"locality"
},
  "geometry": {"coordinates":[146.33663999999999,-34.53584],"type":"Point"}
}