{
  "type": "Feature",
  "properties": {
    "gn:admin1_code":"2.0",
    "gn:admin2_code":"14350.0",
    "gn:asciiname":"Pelican Island",
    "gn:country_code":"AU",
    "gn:dem":-1,
    "gn:feature_class":"P",
    "gn:feature_code":"PPL",
    "gn:name":"Pelican Island",
    "gn:population":0,
    "gn:timezone":"Australia/Sydney",
    "iso:country":"AU",
    "name:ceb_x_preferred":[
        "Pelican Island"
    ],
    "name:deu_x_preferred":[
        "Pelican Island"
    ],
    "name:fra_x_preferred":[
        "Pelican Island"
    ],
    "name:swe_x_preferred":[
        "Pelican Island"
    ],
    "wof:name":"Pelican Island",
    "wof:placetype":"locality"
},
  "geometry": {"coordinates":[153.01667,-30.95],"type":"Point"}
}