{
  "type": "Feature",
  "properties": {
    "gn:admin1_code":"6.0",
    "gn:admin2_code":"60410.0",
    "gn:asciiname":"Dromedary Upper",
    "gn:cc2":"AU",
    "gn:country_code":"AU",
    "gn:dem":237,
    "gn:feature_class":"P",
    "gn:feature_code":"PPL",
    "gn:name":"Dromedary Upper",
    "gn:population":0,
    "gn:timezone":"Australia/Hobart",
    "iso:country":"AU",
    "name:und_x_variant":[
        "Upper Dromedary",
        "Dromedary Upper"
    ],
    "wof:name":"Dromedary Upper",
    "wof:placetype":"locality"
},
  "geometry": {"coordinates":[147.15000000000001,-42.71667],"type":"Point"}
}