{
  "type": "Feature",
  "properties": {
    "gn:admin1_code":"5.0",
    "gn:admin2_code":"43790.0",
    "gn:asciiname":"Overland Corner",
    "gn:country_code":"AU",
    "gn:dem":59,
    "gn:feature_class":"P",
    "gn:feature_code":"PPL",
    "gn:name":"Overland Corner",
    "gn:population":0,
    "gn:timezone":"Australia/Adelaide",
    "iso:country":"AU",
    "name:eng_x_preferred":[
        "Overland Corner"
    ],
    "wof:name":"Overland Corner",
    "wof:placetype":"locality"
},
  "geometry": {"coordinates":[140.33427,-34.14579000000001],"type":"Point"}
}