{
  "type": "Feature",
  "properties": {
    "gn:admin1_code":"7.0",
    "gn:admin2_code":"23940.0",
    "gn:asciiname":"Mysia",
    "gn:country_code":"AU",
    "gn:dem":115,
    "gn:feature_class":"P",
    "gn:feature_code":"PPL",
    "gn:name":"Mysia",
    "gn:population":0,
    "gn:timezone":"Australia/Melbourne",
    "iso:country":"AU",
    "name:amh_x_preferred":[
        "\u121a\u1235\u12eb"
    ],
    "name:ara_x_preferred":[
        "\u0645\u064a\u0633\u064a\u0627"
    ],
    "name:bel_x_preferred":[
        "\u041c\u0456\u0437\u0456\u044f"
    ],
    "name:bre_x_preferred":[
        "Misia"
    ],
    "name:bul_x_preferred":[
        "\u041c\u0438\u0437\u0438\u044f"
    ],
    "name:cat_x_preferred":[
        "M\u00edsia"
    ],
    "name:deu_x_preferred":[
        "Mysien"
    ],
    "name:ell_x_preferred":[
        "\u039c\u03c5\u03c3\u03af\u03b1"
    ],
    "name:est_x_preferred":[
        "M\u00fc\u00fcsia"
    ],
    "name:eus_x_preferred":[
        "Misia"
    ],
    "name:fin_x_preferred":[
        "Mysia"
    ],
    "name:fra_x_preferred":[
        "Mysie"
    ],
    "name:hrv_x_preferred":[
        "Mizija"
    ],
    "name:hye_x_preferred":[
        "\u0544\u056b\u057d\u056b\u0575\u0561"
    ],
    "name:ind_x_preferred":[
        "Mysia"
    ],
    "name:ita_x_preferred":[
        "Misia"
    ],
    "name:jpn_x_preferred":[
        "\u30df\u30e5\u30b7\u30a2"
    ],
    "name:kor_x_preferred":[
        "\ubbf8\uc2dc\uc544"
    ],
    "name:lat_x_preferred":[
        "Mysia"
    ],
    "name:lit_x_preferred":[
        "Mysija"
    ],
    "name:nor_x_preferred":[
        "Mysia"
    ],
    "name:pol_x_preferred":[
        "Myzja"
    ],
    "name:por_x_preferred":[
        "M\u00edsia"
    ],
    "name:ron_x_preferred":[
        "Misia"
    ],
    "name:rus_x_preferred":[
        "\u041c\u0438\u0441\u0438\u044f"
    ],
    "name:spa_x_preferred":[
        "Misia"
    ],
    "name:srp_x_preferred":[
        "\u041c\u0438\u0437\u0438\u0458\u0430"
    ],
    "name:swe_x_preferred":[
        "Mysien"
    ],
    "name:tur_x_preferred":[
        "Misya"
    ],
    "name:zho_x_preferred":[
        "\u5bc6\u7ec6\u4e9a"
    ],
    "wof:name":"Mysia",
    "wof:placetype":"locality"
},
  "geometry": {"coordinates":[143.76667,-36.25],"type":"Point"}
}