{
  "type": "Feature",
  "properties": {
    "gn:admin1_code":"5.0",
    "gn:admin2_code":"43790.0",
    "gn:asciiname":"Lowbank",
    "gn:country_code":"AU",
    "gn:dem":57,
    "gn:feature_class":"P",
    "gn:feature_code":"PPL",
    "gn:name":"Lowbank",
    "gn:population":0,
    "gn:timezone":"Australia/Adelaide",
    "iso:country":"AU",
    "name:eng_x_preferred":[
        "Lowbank"
    ],
    "wof:name":"Lowbank",
    "wof:placetype":"locality"
},
  "geometry": {"coordinates":[140.08524,-34.19429],"type":"Point"}
}