{
  "type": "Feature",
  "properties": {
    "gn:admin1_code":"2.0",
    "gn:admin2_code":"18200.0",
    "gn:asciiname":"Moorna",
    "gn:country_code":"AU",
    "gn:dem":45,
    "gn:feature_class":"P",
    "gn:feature_code":"PPL",
    "gn:name":"Moorna",
    "gn:population":0,
    "gn:timezone":"Australia/Sydney",
    "iso:country":"AU",
    "wof:name":"Moorna",
    "wof:placetype":"locality"
},
  "geometry": {"coordinates":[141.61271000000005,-34.14501],"type":"Point"}
}