{
  "type": "Feature",
  "properties": {
    "gn:admin1_code":"5.0",
    "gn:admin2_code":"47800.0",
    "gn:asciiname":"Field",
    "gn:country_code":"AU",
    "gn:dem":16,
    "gn:feature_class":"P",
    "gn:feature_code":"PPL",
    "gn:name":"Field",
    "gn:population":0,
    "gn:timezone":"Australia/Adelaide",
    "iso:country":"AU",
    "name:eng_x_preferred":[
        "Field"
    ],
    "wof:name":"Field",
    "wof:placetype":"locality"
},
  "geometry": {"coordinates":[139.66523999999998,-35.82237],"type":"Point"}
}