{
  "type": "Feature",
  "properties": {
    "gn:admin1_code":"3.0",
    "gn:admin2_code":"74660.0",
    "gn:asciiname":"Damdam",
    "gn:country_code":"AU",
    "gn:dem":13,
    "gn:feature_class":"P",
    "gn:feature_code":"PPL",
    "gn:name":"Damdam",
    "gn:population":0,
    "gn:timezone":"Australia/Darwin",
    "iso:country":"AU",
    "wof:name":"Damdam",
    "wof:placetype":"locality"
},
  "geometry": {"coordinates":[134.64615000000001,-12.1662],"type":"Point"}
}