{
  "type": "Feature",
  "properties": {
    "gn:admin1_code":"2.0",
    "gn:admin2_code":"11730.0",
    "gn:asciiname":"Marengo",
    "gn:country_code":"AU",
    "gn:dem":1134,
    "gn:feature_class":"P",
    "gn:feature_code":"PPL",
    "gn:name":"Marengo",
    "gn:population":0,
    "gn:timezone":"Australia/Sydney",
    "iso:country":"AU",
    "name:eng_x_preferred":[
        "Marengo"
    ],
    "wof:name":"Marengo",
    "wof:placetype":"locality"
},
  "geometry": {"coordinates":[152.36148,-30.17252],"type":"Point"}
}