{
  "type": "Feature",
  "properties": {
    "iso:country":"AU",
    "name:ara_x_preferred":[
        "\u0643\u0648\u064a\u0646\u0628\u064a\u0627\u0646"
    ],
    "name:azb_x_preferred":[
        "\u06a9\u0648\u0626\u06cc\u0646\u200c\u0628\u06cc\u0646"
    ],
    "name:ceb_x_preferred":[
        "Queanbeyan"
    ],
    "name:ces_x_preferred":[
        "Queanbeyan"
    ],
    "name:ckb_x_preferred":[
        "\u06a9\u0648\u06cc\u0646 \u0628\u06cc\u06ce\u0646"
    ],
    "name:cym_x_preferred":[
        "Queanbeyan"
    ],
    "name:dan_x_preferred":[
        "Queanbeyan"
    ],
    "name:deu_x_preferred":[
        "Queanbeyan"
    ],
    "name:eng_x_preferred":[
        "Queanbeyan"
    ],
    "name:est_x_preferred":[
        "Queanbeyan"
    ],
    "name:fas_x_preferred":[
        "\u06a9\u0648\u0626\u06cc\u0646\u0628\u06cc\u0627\u0646"
    ],
    "name:fra_x_preferred":[
        "Queanbeyan"
    ],
    "name:gle_x_preferred":[
        "Queanbeyan"
    ],
    "name:hun_x_preferred":[
        "Queanbeyan"
    ],
    "name:ita_x_preferred":[
        "Queanbeyan"
    ],
    "name:kat_x_preferred":[
        "\u10d9\u10e3\u10dc\u10d8\u10d1\u10d4\u10d8"
    ],
    "name:kor_x_preferred":[
        "\ud038\ube44\uc5b8"
    ],
    "name:mlg_x_preferred":[
        "Queanbeyan"
    ],
    "name:nor_x_preferred":[
        "Queanbeyan"
    ],
    "name:pnb_x_preferred":[
        "\u06a9\u0648\u06cc\u0646\u0628\u06cc\u0627\u0646"
    ],
    "name:pol_x_preferred":[
        "Queanbeyan"
    ],
    "name:por_x_preferred":[
        "Queanbeyan"
    ],
    "name:rus_x_preferred":[
        "\u041a\u0443\u0438\u043d\u0431\u0438\u0430\u043d"
    ],
    "name:sco_x_preferred":[
        "Queanbeyan"
    ],
    "name:srp_x_preferred":[
        "\u041a\u0432\u0438\u043d\u0431\u0438\u0458\u0430\u043d"
    ],
    "name:swe_x_preferred":[
        "Queanbeyan"
    ],
    "name:urd_x_preferred":[
        "\u06a9\u0648\u06cc\u0646\u0628\u06cc\u0627\u0646"
    ],
    "name:vie_x_preferred":[
        "Queanbeyan"
    ],
    "name:zho_x_preferred":[
        "\u6606\u6bd4\u6069"
    ],
    "wof:coterminous":[
        1376968045
    ],
    "wof:lang_x_official":[
        "eng"
    ],
    "wof:lang_x_spoken":[
        "eng"
    ],
    "wof:name":"Queanbeyan",
    "wof:placetype":"locality"
},
  "geometry": {"coordinates":[149.23010400000001,-35.353399],"type":"Point"}
}