{
  "type": "Feature",
  "properties": {
    "iso:country":"AU",
    "name:eng_x_preferred":[
        "Queanbeyan"
    ],
    "wof:coterminous":[
        1376968045
    ],
    "wof:lang_x_official":[
        "eng"
    ],
    "wof:lang_x_spoken":[
        "eng"
    ],
    "wof:name":"Queanbeyan",
    "wof:placetype":"locality"
},
  "geometry": {"coordinates":[149.23010400000001,-35.353399],"type":"Point"}
}