{
  "type": "Feature",
  "properties": {
    "gn:admin1_code":"7.0",
    "gn:admin2_code":"25150.0",
    "gn:asciiname":"Newbury",
    "gn:country_code":"AU",
    "gn:dem":731,
    "gn:feature_class":"P",
    "gn:feature_code":"PPL",
    "gn:name":"Newbury",
    "gn:population":0,
    "gn:timezone":"Australia/Melbourne",
    "iso:country":"AU",
    "name:cat_x_preferred":[
        "Newbury"
    ],
    "name:ceb_x_preferred":[
        "Newbury"
    ],
    "name:deu_x_preferred":[
        "Newbury"
    ],
    "name:fas_x_preferred":[
        "\u0646\u06cc\u0648\u0628\u0631\u06cc"
    ],
    "name:fra_x_preferred":[
        "Newbury"
    ],
    "name:ita_x_preferred":[
        "Newbury"
    ],
    "name:pol_x_preferred":[
        "Newbury"
    ],
    "name:por_x_preferred":[
        "Newbury"
    ],
    "name:spa_x_preferred":[
        "Newbury"
    ],
    "name:swe_x_preferred":[
        "Newbury"
    ],
    "name:vol_x_preferred":[
        "Newbury"
    ],
    "wof:name":"Newbury",
    "wof:placetype":"locality"
},
  "geometry": {"coordinates":[144.31666999999999,-37.41667],"type":"Point"}
}