{
  "type": "Feature",
  "properties": {
    "gn:admin1_code":"4",
    "gn:admin2_code":"36810",
    "gn:asciiname":"Tabacum",
    "gn:country_code":"AU",
    "gn:dem":505,
    "gn:feature_class":"P",
    "gn:feature_code":"PPL",
    "gn:name":"Tabacum",
    "gn:population":0,
    "gn:timezone":"Australia/Brisbane",
    "iso:country":"AU",
    "wof:name":"Tabacum",
    "wof:placetype":"locality"
},
  "geometry": {"coordinates":[145.30000000000001,-17.11667000000001],"type":"Point"}
}