{
  "type": "Feature",
  "properties": {
    "gn:admin1_code":"2.0",
    "gn:admin2_code":"16610.0",
    "gn:asciiname":"Naughtons Gap",
    "gn:country_code":"AU",
    "gn:dem":146,
    "gn:feature_class":"P",
    "gn:feature_code":"PPL",
    "gn:name":"Naughtons Gap",
    "gn:population":0,
    "gn:timezone":"Australia/Sydney",
    "iso:country":"AU",
    "name:eng_x_preferred":[
        "Naughtons Gap"
    ],
    "wof:name":"Naughtons Gap",
    "wof:placetype":"locality"
},
  "geometry": {"coordinates":[153.10837000000001,-28.80049],"type":"Point"}
}