{
  "type": "Feature",
  "properties": {
    "gn:admin1_code":"2.0",
    "gn:asciiname":"Myramount",
    "gn:country_code":"AU",
    "gn:dem":-9999,
    "gn:feature_class":"P",
    "gn:feature_code":"PPL",
    "gn:name":"Myramount",
    "gn:population":0,
    "gn:timezone":"Australia/Sydney",
    "iso:country":"AU",
    "wof:name":"Myramount",
    "wof:placetype":"locality"
},
  "geometry": {"coordinates":[150.83333000000005,-34.76667],"type":"Point"}
}