{
  "type": "Feature",
  "properties": {
    "gn:admin1_code":"8.0",
    "gn:admin2_code":"53920.0",
    "gn:asciiname":"Kurinyjiyan",
    "gn:country_code":"AU",
    "gn:dem":311,
    "gn:feature_class":"P",
    "gn:feature_code":"PPL",
    "gn:name":"Kurinyjiyan",
    "gn:population":0,
    "gn:timezone":"Australia/Perth",
    "iso:country":"AU",
    "wof:name":"Kurinyjiyan",
    "wof:placetype":"locality"
},
  "geometry": {"coordinates":[126.95195,-18.64713],"type":"Point"}
}