{
  "type": "Feature",
  "properties": {
    "gn:admin1_code":"7.0",
    "gn:admin2_code":"24250.0",
    "gn:asciiname":"Ancona",
    "gn:country_code":"AU",
    "gn:dem":372,
    "gn:feature_class":"P",
    "gn:feature_code":"PPL",
    "gn:name":"Ancona",
    "gn:population":0,
    "gn:timezone":"Australia/Melbourne",
    "iso:country":"AU",
    "name:ita_x_preferred":[
        "Ancona"
    ],
    "wof:name":"Ancona",
    "wof:placetype":"locality"
},
  "geometry": {"coordinates":[145.81666999999999,-36.98333],"type":"Point"}
}