{
  "type": "Feature",
  "properties": {
    "gn:admin1_code":"2.0",
    "gn:admin2_code":"17650.0",
    "gn:asciiname":"Laura",
    "gn:country_code":"AU",
    "gn:dem":689,
    "gn:feature_class":"P",
    "gn:feature_code":"PPL",
    "gn:name":"Laura",
    "gn:population":0,
    "gn:timezone":"Australia/Sydney",
    "iso:country":"AU",
    "wof:name":"Laura",
    "wof:placetype":"locality"
},
  "geometry": {"coordinates":[151.13333,-30.21667],"type":"Point"}
}