{
  "type": "Feature",
  "properties": {
    "gn:admin1_code":"2.0",
    "gn:admin2_code":"16200.0",
    "gn:asciiname":"Monomie",
    "gn:country_code":"AU",
    "gn:dem":215,
    "gn:feature_class":"P",
    "gn:feature_code":"PPL",
    "gn:name":"Monomie",
    "gn:population":0,
    "gn:timezone":"Australia/Sydney",
    "iso:country":"AU",
    "wof:name":"Monomie",
    "wof:placetype":"locality"
},
  "geometry": {"coordinates":[147.68333000000001,-33.13333],"type":"Point"}
}