{
  "type": "Feature",
  "properties": {
    "iso:country":"AU",
    "name:eng_x_preferred":[
        "North Dubbo"
    ],
    "name:eng_x_variant":[
        "N Dubbo"
    ],
    "name:unk_x_variant":[
        "North Dubbo"
    ],
    "qs:gn_adm0_cc":"AU",
    "qs:gn_local":2168305,
    "qs:local_max":2205,
    "qs:local_sum":2818,
    "qs:localhoods":6,
    "qs:name":"North Dubbo",
    "qs:name_adm0":"Australia",
    "qs:name_adm1":"New South Wales",
    "qs:name_adm2":"Dubbo",
    "qs:name_local":"Dubbo",
    "qs:photo_max":21,
    "qs:photo_sum":33,
    "qs:placetype":"Suburb",
    "qs:quad_count":9,
    "qs:woe_adm0":23424748,
    "qs:woe_adm1":2344700,
    "qs:woe_adm2":55863833,
    "qs:woe_lau":0,
    "qs:woe_local":1101749,
    "qs:woe_ver":"7.10.0",
    "wof:lang":[
        "eng"
    ],
    "wof:name":"North Dubbo",
    "wof:placetype":"neighbourhood"
},
  "geometry": {"coordinates":[148.57302899999999,-32.217378],"type":"Point"}
}