{
  "type": "Feature",
  "properties": {
    "iso:country":"AU",
    "name:ceb_x_preferred":[
        "Black River Falls Area Airport"
    ],
    "name:eng_x_preferred":[
        "Black River Falls Area Airport"
    ],
    "name:eng_x_variant":[
        "BCK",
        "YBWR"
    ],
    "name:fas_x_preferred":[
        "\u0641\u0631\u0648\u062f\u06af\u0627\u0647 \u0628\u0644\u06a9 \u0631\u06cc\u0648\u0631 \u0641\u0644\u0632 \u0627\u06cc\u0631\u06cc\u0627"
    ],
    "name:tgk_x_preferred":[
        "\u0424\u0443\u0440\u0443\u0434\u0433\u043e\u04b3\u0438 \u0411\u043b\u0435\u043a \u0420\u0438\u0432\u0435\u0440 \u0424\u043e\u043b\u0437 \u042d\u0440\u0438\u0430"
    ],
    "name:urd_x_preferred":[
        "\u0628\u0644\u06cc\u06a9 \u0631\u06cc\u0648\u0631 \u0641\u0627\u0644\u0632 \u0639\u0644\u0627\u0642\u06c1 \u06c1\u0648\u0627\u0626\u06cc \u0627\u0688\u0627"
    ],
    "oa:type":"small_airport",
    "wd:wordcount":277,
    "woe:hierarchy":{
        "country_id":23424977,
        "county_id":12590560,
        "planet_id":1,
        "state_id":2347608
    },
    "wof:name":"Black River Falls Area Airport",
    "wof:placetype":"campus"
},
  "geometry": {"coordinates":[144.169006,-17.3883],"type":"Point"}
}