{
  "type": "Feature",
  "properties": {
    "gn:country":"AU",
    "iso:country":"AU",
    "name:deu_x_preferred":[
        "Wooyung"
    ],
    "name:eng_x_preferred":[
        "Wooyung"
    ],
    "name:fra_x_preferred":[
        "Wooyung"
    ],
    "name:por_x_preferred":[
        "Wooyung"
    ],
    "name:sco_x_preferred":[
        "Wooyung"
    ],
    "name:spa_x_preferred":[
        "Wooyung"
    ],
    "name:swe_x_preferred":[
        "Wooyung"
    ],
    "name:swe_x_variant":[
        "Rocksberg"
    ],
    "qs_pg:aaroncc":"AU",
    "qs_pg:gn_country":"AU",
    "qs_pg:name":"Wooyung",
    "qs_pg:name_adm0":"Australia",
    "qs_pg:name_adm1":"New South Wales",
    "qs_pg:photos":15,
    "qs_pg:photos_1k":3,
    "qs_pg:photos_9k":1,
    "qs_pg:photos_9r":1,
    "qs_pg:photos_all":15,
    "qs_pg:photos_sr":1,
    "qs_pg:pop_sr":0,
    "qs_pg:qs_pg_placetype":"locality",
    "qs_pg:qs_pg_placetype_gp":"Town",
    "qs_pg:woe_adm0":23424748,
    "woe:adm0_id":23424748,
    "woe:name_adm0":"Australia",
    "woe:name_adm1":"New South Wales",
    "woe:placetype":"Town",
    "wof:name":"Wooyung",
    "wof:placetype":"locality"
},
  "geometry": {"coordinates":[153.55492100000001,-28.455769],"type":"Point"}
}