{
  "type": "Feature",
  "properties": {
    "gn:admin1_code":"8.0",
    "gn:admin2_code":"50980.0",
    "gn:asciiname":"Roebuck Roadhouse",
    "gn:country_code":"AU",
    "gn:dem":38,
    "gn:feature_class":"P",
    "gn:feature_code":"PPL",
    "gn:name":"Roebuck Roadhouse",
    "gn:population":0,
    "gn:timezone":"Australia/Perth",
    "iso:country":"AU",
    "wof:name":"Roebuck Roadhouse",
    "wof:placetype":"locality"
},
  "geometry": {"coordinates":[122.50047000000001,-17.84658],"type":"Point"}
}