{
  "type": "Feature",
  "properties": {
    "gn:admin1_code":"7.0",
    "gn:admin2_code":"26170.0",
    "gn:asciiname":"Berrys Creek",
    "gn:country_code":"AU",
    "gn:dem":173,
    "gn:feature_class":"P",
    "gn:feature_code":"PPL",
    "gn:name":"Berrys Creek",
    "gn:population":0,
    "gn:timezone":"Australia/Melbourne",
    "iso:country":"AU",
    "wof:name":"Berrys Creek",
    "wof:placetype":"locality"
},
  "geometry": {"coordinates":[146.06666999999999,-38.41667],"type":"Point"}
}