{
  "type": "Feature",
  "properties": {
    "gn:admin1_code":"7.0",
    "gn:admin2_code":"22750.0",
    "gn:asciiname":"Pettavel",
    "gn:country_code":"AU",
    "gn:dem":89,
    "gn:feature_class":"P",
    "gn:feature_code":"PPL",
    "gn:name":"Pettavel",
    "gn:population":0,
    "gn:timezone":"Australia/Melbourne",
    "iso:country":"AU",
    "wof:name":"Pettavel",
    "wof:placetype":"locality"
},
  "geometry": {"coordinates":[144.25,-38.23333],"type":"Point"}
}