{
  "type": "Feature",
  "properties": {
    "gn:admin1_code":"5.0",
    "gn:admin2_code":"41830.0",
    "gn:asciiname":"Commodore",
    "gn:country_code":"AU",
    "gn:dem":117,
    "gn:feature_class":"P",
    "gn:feature_code":"PPL",
    "gn:name":"Commodore",
    "gn:population":0,
    "gn:timezone":"Australia/Adelaide",
    "iso:country":"AU",
    "name:eng_x_preferred":[
        "Commodore"
    ],
    "wof:name":"Commodore",
    "wof:placetype":"locality"
},
  "geometry": {"coordinates":[138.40479999999999,-31.24169],"type":"Point"}
}