{
  "type": "Feature",
  "properties": {
    "gn:admin1_code":"5.0",
    "gn:admin2_code":"41830.0",
    "gn:asciiname":"Commodore",
    "gn:country_code":"AU",
    "gn:dem":117,
    "gn:feature_class":"P",
    "gn:feature_code":"PPL",
    "gn:name":"Commodore",
    "gn:population":0,
    "gn:timezone":"Australia/Adelaide",
    "iso:country":"AU",
    "name:bul_x_preferred":[
        "\u041a\u043e\u043c\u043e\u0434\u043e\u0440"
    ],
    "name:cat_x_preferred":[
        "Comodor"
    ],
    "name:ces_x_preferred":[
        "Commodore"
    ],
    "name:dan_x_preferred":[
        "Commodore"
    ],
    "name:deu_x_preferred":[
        "Commodore"
    ],
    "name:eng_x_preferred":[
        "Commodore"
    ],
    "name:fas_x_preferred":[
        "\u06a9\u0645\u0648\u062f\u0648\u0631"
    ],
    "name:fin_x_preferred":[
        "Commodore"
    ],
    "name:fra_x_preferred":[
        "Commodore"
    ],
    "name:fry_x_preferred":[
        "Commodore"
    ],
    "name:heb_x_preferred":[
        "\u05e7\u05d5\u05de\u05d5\u05d3\u05d5\u05e8"
    ],
    "name:kor_x_preferred":[
        "\ucf54\ubaa8\ub3c4\uc5b4"
    ],
    "name:lit_x_preferred":[
        "Commodore"
    ],
    "name:nld_x_preferred":[
        "Commodore"
    ],
    "name:nno_x_preferred":[
        "Commodore"
    ],
    "name:nor_x_preferred":[
        "Commodore"
    ],
    "name:por_x_preferred":[
        "Commodore"
    ],
    "name:rus_x_preferred":[
        "\u041a\u043e\u043c\u043c\u043e\u0434\u043e\u0440"
    ],
    "name:spa_x_preferred":[
        "Commodore"
    ],
    "name:srp_x_preferred":[
        "\u041a\u043e\u043c\u043e\u0434\u043e\u0440"
    ],
    "name:swe_x_preferred":[
        "Commodore"
    ],
    "name:tur_x_preferred":[
        "Commodore"
    ],
    "name:ukr_x_preferred":[
        "\u041a\u043e\u043c\u043c\u043e\u0434\u043e\u0440"
    ],
    "wof:name":"Commodore",
    "wof:placetype":"locality"
},
  "geometry": {"coordinates":[138.40479999999999,-31.24169],"type":"Point"}
}