{
  "type": "Feature",
  "properties": {
    "gn:admin1_code":"7.0",
    "gn:admin2_code":"22110.0",
    "gn:asciiname":"Burtons",
    "gn:country_code":"AU",
    "gn:dem":182,
    "gn:feature_class":"P",
    "gn:feature_code":"PPL",
    "gn:name":"Burtons",
    "gn:population":0,
    "gn:timezone":"Australia/Melbourne",
    "iso:country":"AU",
    "name:eng_x_preferred":[
        "Burtons"
    ],
    "wof:name":"Burtons",
    "wof:placetype":"locality"
},
  "geometry": {"coordinates":[148.91037,-37.45951],"type":"Point"}
}