{
  "type": "Feature",
  "properties": {
    "gn:admin1_code":"7.0",
    "gn:admin2_code":"24780.0",
    "gn:asciiname":"Nowingi",
    "gn:country_code":"AU",
    "gn:dem":46,
    "gn:feature_class":"P",
    "gn:feature_code":"PPL",
    "gn:name":"Nowingi",
    "gn:population":0,
    "gn:timezone":"Australia/Melbourne",
    "iso:country":"AU",
    "wof:name":"Nowingi",
    "wof:placetype":"locality"
},
  "geometry": {"coordinates":[142.22522000000001,-34.59634],"type":"Point"}
}