{
  "type": "Feature",
  "properties": {
    "gn:admin1_code":"7.0",
    "gn:admin2_code":"22830.0",
    "gn:asciiname":"Pine Lodge South",
    "gn:country_code":"AU",
    "gn:dem":126,
    "gn:feature_class":"P",
    "gn:feature_code":"PPL",
    "gn:name":"Pine Lodge South",
    "gn:population":0,
    "gn:timezone":"Australia/Melbourne",
    "iso:country":"AU",
    "wof:name":"Pine Lodge South",
    "wof:placetype":"locality"
},
  "geometry": {"coordinates":[145.56666999999999,-36.41667],"type":"Point"}
}