{
  "type": "Feature",
  "properties": {
    "gn:admin1_code":"2.0",
    "gn:admin2_code":"17310.0",
    "gn:asciiname":"Crow Mountain",
    "gn:country_code":"AU",
    "gn:dem":682,
    "gn:feature_class":"P",
    "gn:feature_code":"PPL",
    "gn:name":"Crow Mountain",
    "gn:population":0,
    "gn:timezone":"Australia/Sydney",
    "iso:country":"AU",
    "wof:name":"Crow Mountain",
    "wof:placetype":"locality"
},
  "geometry": {"coordinates":[150.76667,-30.46667],"type":"Point"}
}