{
  "type": "Feature",
  "properties": {
    "gn:admin1_code":"3.0",
    "gn:admin2_code":"71300.0",
    "gn:asciiname":"Wurrumenbumanja",
    "gn:country_code":"AU",
    "gn:dem":36,
    "gn:feature_class":"P",
    "gn:feature_code":"PPL",
    "gn:name":"Wurrumenbumanja",
    "gn:population":0,
    "gn:timezone":"Australia/Darwin",
    "iso:country":"AU",
    "wof:name":"Wurrumenbumanja",
    "wof:placetype":"locality"
},
  "geometry": {"coordinates":[136.53656999999998,-14.12617],"type":"Point"}
}