{
  "type": "Feature",
  "properties": {
    "gn:admin1_code":"7.0",
    "gn:admin2_code":"22110.0",
    "gn:asciiname":"Gillinggall",
    "gn:country_code":"AU",
    "gn:dem":311,
    "gn:feature_class":"P",
    "gn:feature_code":"PPL",
    "gn:name":"Gillinggall",
    "gn:population":0,
    "gn:timezone":"Australia/Melbourne",
    "iso:country":"AU",
    "wof:name":"Gillinggall",
    "wof:placetype":"locality"
},
  "geometry": {"coordinates":[148.15000000000001,-37.31667],"type":"Point"}
}