{
  "type": "Feature",
  "properties": {
    "gn:admin1_code":"3.0",
    "gn:admin2_code":"72330.0",
    "gn:asciiname":"Warren Creek Bore",
    "gn:country_code":"AU",
    "gn:dem":622,
    "gn:feature_class":"P",
    "gn:feature_code":"PPL",
    "gn:name":"Warren Creek Bore",
    "gn:population":0,
    "gn:timezone":"Australia/Darwin",
    "iso:country":"AU",
    "wof:name":"Warren Creek Bore",
    "wof:placetype":"locality"
},
  "geometry": {"coordinates":[131.17838999999998,-23.26763],"type":"Point"}
}