{
  "type": "Feature",
  "properties": {
    "iso:country":"AU",
    "name:eng_x_preferred":[
        "Newcastle - Maitland"
    ],
    "wof:coterminous":[
        1376953349
    ],
    "wof:lang_x_official":[
        "eng"
    ],
    "wof:lang_x_spoken":[
        "eng"
    ],
    "wof:name":"Newcastle - Maitland",
    "wof:placetype":"locality"
},
  "geometry": {"coordinates":[151.78260700000001,-32.9278],"type":"Point"}
}