{
  "type": "Feature",
  "properties": {
    "gn:population":2420,
    "iso:country":"AU",
    "name:ceb_x_preferred":[
        "Granton"
    ],
    "name:eng_x_preferred":[
        "Granton"
    ],
    "name:fas_x_preferred":[
        "\u06af\u0631\u0646\u062a\u0646"
    ],
    "name:fra_x_preferred":[
        "Granton"
    ],
    "name:nld_x_preferred":[
        "Granton"
    ],
    "name:swe_x_preferred":[
        "Granton"
    ],
    "name:unk_x_variant":[
        "Granton"
    ],
    "qs:gn_fcode":"PPL",
    "qs:gn_local":0,
    "qs:gn_namadm1":"06",
    "qs:gn_name":"Granton",
    "qs:local_max":6320,
    "qs:local_sum":24464,
    "qs:localhoods":40,
    "qs:name":"Granton",
    "qs:name_adm0":"Australia",
    "qs:name_adm1":"Tasmania",
    "qs:name_adm2":"Derwent Valley",
    "qs:name_local":"Hobart",
    "qs:photo_max":50,
    "qs:photo_sum":136,
    "qs:placetype":"Suburb",
    "qs:quad_count":21,
    "qs:woe_adm0":23424748,
    "qs:woe_adm1":2344704,
    "qs:woe_adm2":55864284,
    "qs:woe_lau":0,
    "qs:woe_local":1102670,
    "qs:woe_ver":"7.10.0",
    "wd:wordcount":161,
    "wof:lang":[
        "eng"
    ],
    "wof:name":"Granton",
    "wof:placetype":"neighbourhood",
    "wof:population":2420
},
  "geometry": {"coordinates":[147.19472099999999,-42.751888],"type":"Point"}
}