{
  "type": "Feature",
  "properties": {
    "iso:country":"AU",
    "name:eng_x_preferred":[
        "Mount Jagged"
    ],
    "name:jpn_x_preferred":[
        "\u30de\u30a6\u30f3\u30c8 \u30b8\u30e3\u30ae\u30c3\u30c9"
    ],
    "qs_pg:aaroncc":"AU",
    "qs_pg:name":"Mount Jagged",
    "qs_pg:name_adm0":"Australia",
    "qs_pg:name_adm1":"South Australia",
    "qs_pg:photos":12,
    "qs_pg:photos_1k":2,
    "qs_pg:photos_9k":1,
    "qs_pg:photos_9r":1,
    "qs_pg:photos_all":12,
    "qs_pg:photos_sr":1,
    "qs_pg:pop_sr":0,
    "qs_pg:qs_pg_placetype":"locality",
    "qs_pg:qs_pg_placetype_gp":"Town",
    "qs_pg:woe_adm0":23424748,
    "woe:adm0_id":23424748,
    "woe:name_adm0":"Australia",
    "woe:name_adm1":"South Australia",
    "woe:placetype":"Town",
    "wof:name":"Mount Jagged",
    "wof:placetype":"locality"
},
  "geometry": {"coordinates":[138.63666699999999,-35.4068475],"type":"Point"}
}