{
  "type": "Feature",
  "properties": {
    "gn:admin1_code":"5.0",
    "gn:asciiname":"Mount Ive",
    "gn:country_code":"AU",
    "gn:dem":241,
    "gn:feature_class":"P",
    "gn:feature_code":"PPL",
    "gn:name":"Mount Ive",
    "gn:population":0,
    "gn:timezone":"Australia/Adelaide",
    "iso:country":"AU",
    "name:eng_x_preferred":[
        "Mount Ive"
    ],
    "wof:name":"Mount Ive",
    "wof:placetype":"locality"
},
  "geometry": {"coordinates":[136.0635,-32.43696],"type":"Point"}
}