{
  "type": "Feature",
  "properties": {
    "iso:country":"AU",
    "name:bel_x_preferred":[
        "\u0414\u0430\u0440\u043b\u0456\u043d\u0433"
    ],
    "name:ceb_x_preferred":[
        "Darling"
    ],
    "name:ces_x_preferred":[
        "Darling"
    ],
    "name:dan_x_preferred":[
        "Darling"
    ],
    "name:deu_x_preferred":[
        "Darling"
    ],
    "name:eng_x_preferred":[
        "Darling"
    ],
    "name:fin_x_preferred":[
        "Darling"
    ],
    "name:fra_x_preferred":[
        "Darling"
    ],
    "name:heb_x_preferred":[
        "\u05d3\u05e8\u05dc\u05d9\u05e0\u05d2"
    ],
    "name:hun_x_preferred":[
        "Darling"
    ],
    "name:ita_x_preferred":[
        "Darling"
    ],
    "name:jpn_x_preferred":[
        "\u30c0\u30fc\u30ea\u30f3\u30b0"
    ],
    "name:kor_x_preferred":[
        "\ub2ec\ub9c1"
    ],
    "name:nld_x_preferred":[
        "Darling"
    ],
    "name:nor_x_preferred":[
        "Darling"
    ],
    "name:pol_x_preferred":[
        "Darling"
    ],
    "name:ron_x_preferred":[
        "Darling"
    ],
    "name:rus_x_preferred":[
        "\u0414\u0430\u0440\u043b\u0438\u043d\u0433"
    ],
    "name:slk_x_preferred":[
        "Darling"
    ],
    "name:spa_x_preferred":[
        "Darling"
    ],
    "name:swe_x_preferred":[
        "Darling"
    ],
    "name:tel_x_preferred":[
        "\u0c21\u0c3e\u0c30\u0c4d\u0c32\u0c3f\u0c02\u0c17\u0c4d"
    ],
    "name:tgl_x_preferred":[
        "Irog"
    ],
    "name:ukr_x_preferred":[
        "\u0414\u0430\u0440\u043b\u0456\u043d\u0433"
    ],
    "qs:gn_adm0_cc":"AU",
    "qs:gn_local":2158177,
    "qs:local_max":22745,
    "qs:local_sum":338594,
    "qs:localhoods":407,
    "qs:name":"Darling",
    "qs:name_adm0":"Australia",
    "qs:name_adm1":"Victoria",
    "qs:name_adm2":"Stonnington",
    "qs:name_local":"Melbourne",
    "qs:photo_max":38,
    "qs:photo_sum":214,
    "qs:placetype":"Suburb",
    "qs:quad_count":24,
    "qs:woe_adm0":23424748,
    "qs:woe_adm1":2344705,
    "qs:woe_adm2":55863969,
    "qs:woe_lau":0,
    "qs:woe_local":1103816,
    "qs:woe_ver":"7.10.0",
    "wd:wordcount":467,
    "wof:lang":[
        "eng"
    ],
    "wof:name":"Darling",
    "wof:placetype":"neighbourhood"
},
  "geometry": {"coordinates":[145.06738200000001,-37.871003],"type":"Point"}
}