{
  "type": "Feature",
  "properties": {
    "gn:admin1_code":"7.0",
    "gn:admin2_code":"24250.0",
    "gn:asciiname":"Enochs Point",
    "gn:country_code":"AU",
    "gn:dem":424,
    "gn:feature_class":"P",
    "gn:feature_code":"PPL",
    "gn:name":"Enochs Point",
    "gn:population":0,
    "gn:timezone":"Australia/Melbourne",
    "iso:country":"AU",
    "wof:name":"Enochs Point",
    "wof:placetype":"locality"
},
  "geometry": {"coordinates":[146.09999999999999,-37.41667],"type":"Point"}
}