{
  "type": "Feature",
  "properties": {
    "gn:admin1_code":"7.0",
    "gn:admin2_code":"26890.0",
    "gn:asciiname":"Awonga",
    "gn:country_code":"AU",
    "gn:dem":170,
    "gn:feature_class":"P",
    "gn:feature_code":"PPL",
    "gn:name":"Awonga",
    "gn:population":0,
    "gn:timezone":"Australia/Melbourne",
    "iso:country":"AU",
    "wof:name":"Awonga",
    "wof:placetype":"locality"
},
  "geometry": {"coordinates":[141.38333,-36.95],"type":"Point"}
}