{
  "type": "Feature",
  "properties": {
    "gn:admin1_code":"2.0",
    "gn:admin2_code":"14600.0",
    "gn:asciiname":"Wilga Plains",
    "gn:country_code":"AU",
    "gn:dem":237,
    "gn:feature_class":"P",
    "gn:feature_code":"PPL",
    "gn:name":"Wilga Plains",
    "gn:population":0,
    "gn:timezone":"Australia/Sydney",
    "iso:country":"AU",
    "name:eng_x_preferred":[
        "Wilga Plains"
    ],
    "wof:name":"Wilga Plains",
    "wof:placetype":"locality"
},
  "geometry": {"coordinates":[146.90125,-33.38068],"type":"Point"}
}