{
  "type": "Feature",
  "properties": {
    "gn:admin1_code":"7",
    "gn:admin2_code":"24780",
    "gn:asciiname":"Wymlet",
    "gn:country_code":"AU",
    "gn:dem":56,
    "gn:feature_class":"P",
    "gn:feature_code":"PPL",
    "gn:name":"Wymlet",
    "gn:population":0,
    "gn:timezone":"Australia/Melbourne",
    "iso:country":"AU",
    "wof:name":"Wymlet",
    "wof:placetype":"locality"
},
  "geometry": {"coordinates":[142.11667,-34.93333],"type":"Point"}
}