{
  "type": "Feature",
  "properties": {
    "gn:admin1_code":"8",
    "gn:admin2_code":"52030",
    "gn:asciiname":"Waddi Forest",
    "gn:country_code":"AU",
    "gn:dem":284,
    "gn:feature_class":"P",
    "gn:feature_code":"PPL",
    "gn:name":"Waddi Forest",
    "gn:population":0,
    "gn:timezone":"Australia/Perth",
    "iso:country":"AU",
    "wof:name":"Waddi Forest",
    "wof:placetype":"locality"
},
  "geometry": {"coordinates":[116.16667,-29.86667000000001],"type":"Point"}
}