{
  "type": "Feature",
  "properties": {
    "gn:admin1_code":"8",
    "gn:admin2_code":"55460",
    "gn:asciiname":"Baandee",
    "gn:country_code":"AU",
    "gn:dem":249,
    "gn:feature_class":"P",
    "gn:feature_code":"PPL",
    "gn:name":"Baandee",
    "gn:population":0,
    "gn:timezone":"Australia/Perth",
    "iso:country":"AU",
    "name:est_x_preferred":[
        "Baandee"
    ],
    "name:fas_x_preferred":[
        "\u0628\u0627\u0646\u062f\u06cc"
    ],
    "wof:name":"Baandee",
    "wof:placetype":"locality"
},
  "geometry": {"coordinates":[117.95363,-31.58318],"type":"Point"}
}