{
  "type": "Feature",
  "properties": {
    "gn:admin1_code":"4.0",
    "gn:admin2_code":"37550.0",
    "gn:asciiname":"Foleyvale",
    "gn:country_code":"AU",
    "gn:dem":64,
    "gn:feature_class":"P",
    "gn:feature_code":"PPL",
    "gn:name":"Foleyvale",
    "gn:population":0,
    "gn:timezone":"Australia/Brisbane",
    "iso:country":"AU",
    "name:eng_x_preferred":[
        "Foleyvale"
    ],
    "wof:name":"Foleyvale",
    "wof:placetype":"locality"
},
  "geometry": {"coordinates":[149.70138,-23.50758],"type":"Point"}
}