{
  "type": "Feature",
  "properties": {
    "gn:admin1_code":"8",
    "gn:admin2_code":"54690",
    "gn:asciiname":"Jingymia",
    "gn:country_code":"AU",
    "gn:dem":328,
    "gn:feature_class":"P",
    "gn:feature_code":"PPL",
    "gn:name":"Jingymia",
    "gn:population":0,
    "gn:timezone":"Australia/Perth",
    "iso:country":"AU",
    "name:eng_x_preferred":[
        "Jingymia"
    ],
    "wof:name":"Jingymia",
    "wof:placetype":"locality"
},
  "geometry": {"coordinates":[117.41038,-30.46697],"type":"Point"}
}