{
  "type": "Feature",
  "properties": {
    "gn:admin1_code":"4.0",
    "gn:admin2_code":"32500.0",
    "gn:asciiname":"Eighteen Mile Yard",
    "gn:country_code":"AU",
    "gn:dem":39,
    "gn:feature_class":"P",
    "gn:feature_code":"PPL",
    "gn:name":"Eighteen Mile Yard",
    "gn:population":0,
    "gn:timezone":"Australia/Brisbane",
    "iso:country":"AU",
    "wof:name":"Eighteen Mile Yard",
    "wof:placetype":"locality"
},
  "geometry": {"coordinates":[143.73062999999999,-14.79738],"type":"Point"}
}