{
  "type": "Feature",
  "properties": {
    "gn:admin1_code":"4.0",
    "gn:admin2_code":"32500.0",
    "gn:asciiname":"Holroyd",
    "gn:country_code":"AU",
    "gn:dem":112,
    "gn:feature_class":"P",
    "gn:feature_code":"PPL",
    "gn:name":"Holroyd",
    "gn:population":0,
    "gn:timezone":"Australia/Brisbane",
    "iso:country":"AU",
    "wof:name":"Holroyd",
    "wof:placetype":"locality"
},
  "geometry": {"coordinates":[142.62712999999999,-14.11621],"type":"Point"}
}