{
  "type": "Feature",
  "properties": {
    "gn:admin1_code":"6",
    "gn:admin2_code":"64010",
    "gn:asciiname":"White Hills",
    "gn:country_code":"AU",
    "gn:dem":117,
    "gn:feature_class":"P",
    "gn:feature_code":"PPL",
    "gn:name":"White Hills",
    "gn:population":0,
    "gn:timezone":"Australia/Hobart",
    "iso:country":"AU",
    "name:ceb_x_preferred":[
        "White Hills"
    ],
    "name:eng_x_preferred":[
        "White Hills"
    ],
    "name:swe_x_preferred":[
        "White Hills"
    ],
    "wof:name":"White Hills",
    "wof:placetype":"locality",
    "wof:population":182
},
  "geometry": {"coordinates":[147.25434999999999,-41.50552],"type":"Point"}
}