{
  "type": "Feature",
  "properties": {
    "gn:admin1_code":"5",
    "gn:admin2_code":"42110",
    "gn:asciiname":"Geranium Plain",
    "gn:cc2":"AU",
    "gn:country_code":"AU",
    "gn:dem":281,
    "gn:feature_class":"P",
    "gn:feature_code":"PPL",
    "gn:name":"Geranium Plain",
    "gn:population":0,
    "gn:timezone":"Australia/Adelaide",
    "iso:country":"AU",
    "name:und_x_variant":[
        "Geranium Plains",
        "Geranium Plain"
    ],
    "wof:name":"Geranium Plain",
    "wof:placetype":"locality"
},
  "geometry": {"coordinates":[139.16666999999998,-33.96667],"type":"Point"}
}