{
  "type": "Feature",
  "properties": {
    "gn:admin1_code":"4.0",
    "gn:admin2_code":"37310.0",
    "gn:asciiname":"Blaxland",
    "gn:country_code":"AU",
    "gn:dem":348,
    "gn:feature_class":"P",
    "gn:feature_code":"PPL",
    "gn:name":"Blaxland",
    "gn:population":0,
    "gn:timezone":"Australia/Brisbane",
    "iso:country":"AU",
    "name:eng_x_preferred":[
        "Blaxland"
    ],
    "wof:name":"Blaxland",
    "wof:placetype":"locality"
},
  "geometry": {"coordinates":[151.32107999999999,-27.19873],"type":"Point"}
}