{
  "type": "Feature",
  "properties": {
    "gn:admin1_code":"4.0",
    "gn:admin2_code":"32500.0",
    "gn:asciiname":"Boiling Springs",
    "gn:country_code":"AU",
    "gn:dem":60,
    "gn:feature_class":"P",
    "gn:feature_code":"PPL",
    "gn:name":"Boiling Springs",
    "gn:population":0,
    "gn:timezone":"Australia/Brisbane",
    "iso:country":"AU",
    "wof:name":"Boiling Springs",
    "wof:placetype":"locality"
},
  "geometry": {"coordinates":[145.08914999999999,-15.2846],"type":"Point"}
}