{
  "type": "Feature",
  "properties": {
    "gn:admin1_code":"2.0",
    "gn:admin2_code":"16380.0",
    "gn:asciiname":"Rossglen",
    "gn:country_code":"AU",
    "gn:dem":46,
    "gn:feature_class":"P",
    "gn:feature_code":"PPL",
    "gn:name":"Rossglen",
    "gn:population":0,
    "gn:timezone":"Australia/Sydney",
    "iso:country":"AU",
    "name:eng_x_preferred":[
        "Rossglen"
    ],
    "wof:name":"Rossglen",
    "wof:placetype":"locality"
},
  "geometry": {"coordinates":[152.7251,-31.66579],"type":"Point"}
}