{
  "type": "Feature",
  "properties": {
    "gn:admin1_code":"2.0",
    "gn:admin2_code":"18100.0",
    "gn:asciiname":"Quondong",
    "gn:country_code":"AU",
    "gn:dem":401,
    "gn:feature_class":"P",
    "gn:feature_code":"PPL",
    "gn:name":"Quondong",
    "gn:population":0,
    "gn:timezone":"Australia/Sydney",
    "iso:country":"AU",
    "wof:name":"Quondong",
    "wof:placetype":"locality"
},
  "geometry": {"coordinates":[148.19999999999999,-33.91667],"type":"Point"}
}