{
  "type": "Feature",
  "properties": {
    "gn:admin1_code":"7.0",
    "gn:admin2_code":"26170.0",
    "gn:asciiname":"Jeetho",
    "gn:country_code":"AU",
    "gn:dem":171,
    "gn:feature_class":"P",
    "gn:feature_code":"PPL",
    "gn:name":"Jeetho",
    "gn:population":0,
    "gn:timezone":"Australia/Melbourne",
    "iso:country":"AU",
    "wof:name":"Jeetho",
    "wof:placetype":"locality"
},
  "geometry": {"coordinates":[145.71666999999999,-38.38333],"type":"Point"}
}