{
  "type": "Feature",
  "properties": {
    "gn:admin1_code":"5.0",
    "gn:admin2_code":"47490.0",
    "gn:asciiname":"Alinga Park",
    "gn:country_code":"AU",
    "gn:dem":74,
    "gn:feature_class":"P",
    "gn:feature_code":"PPL",
    "gn:name":"Alinga Park",
    "gn:population":0,
    "gn:timezone":"Australia/Adelaide",
    "iso:country":"AU",
    "name:eng_x_preferred":[
        "Alinga Park"
    ],
    "wof:name":"Alinga Park",
    "wof:placetype":"locality"
},
  "geometry": {"coordinates":[134.47888,-32.83133],"type":"Point"}
}