{
  "type": "Feature",
  "properties": {
    "iso:country":"AU",
    "name:ceb_x_preferred":[
        "Boolgeeda Airport"
    ],
    "name:eng_x_preferred":[
        "Boolgeeda Airport"
    ],
    "name:ron_x_preferred":[
        "Aeroportul Boolgeeda"
    ],
    "name:swe_x_preferred":[
        "Boolgeeda Airport"
    ],
    "oa:elevation_ft":"1871",
    "oa:type":"small_airport",
    "woe:hierarchy":{
        "country_id":23424748,
        "county_id":55864374,
        "planet_id":1,
        "state_id":2344706
    },
    "wof:name":"Boolgeeda Aerodrome",
    "wof:placetype":"campus"
},
  "geometry": {"coordinates":[117.27500000000001,-22.5397],"type":"Point"}
}