{
  "type": "Feature",
  "properties": {
    "gn:admin1_code":"7",
    "gn:admin2_code":"25710",
    "gn:asciiname":"Saint Andrews North",
    "gn:cc2":"AU",
    "gn:country_code":"AU",
    "gn:dem":240,
    "gn:feature_class":"P",
    "gn:feature_code":"PPL",
    "gn:name":"Saint Andrews North",
    "gn:population":0,
    "gn:timezone":"Australia/Melbourne",
    "iso:country":"AU",
    "name:und_x_variant":[
        "North Queenstown",
        "Saint Andrews North"
    ],
    "wof:name":"Saint Andrews North",
    "wof:placetype":"locality"
},
  "geometry": {"coordinates":[145.30000000000001,-37.56667],"type":"Point"}
}