{
  "type": "Feature",
  "properties": {
    "gn:admin1_code":"7.0",
    "gn:admin2_code":"22250.0",
    "gn:asciiname":"Cannie",
    "gn:country_code":"AU",
    "gn:dem":109,
    "gn:feature_class":"P",
    "gn:feature_code":"PPL",
    "gn:name":"Cannie",
    "gn:population":0,
    "gn:timezone":"Australia/Melbourne",
    "iso:country":"AU",
    "wof:name":"Cannie",
    "wof:placetype":"locality"
},
  "geometry": {"coordinates":[143.44848999999999,-35.75403],"type":"Point"}
}