{
  "type": "Feature",
  "properties": {
    "gn:admin1_code":"6.0",
    "gn:admin2_code":"60810.0",
    "gn:asciiname":"South Nietta",
    "gn:country_code":"AU",
    "gn:dem":621,
    "gn:feature_class":"P",
    "gn:feature_code":"PPL",
    "gn:name":"South Nietta",
    "gn:population":0,
    "gn:timezone":"Australia/Hobart",
    "iso:country":"AU",
    "name:eng_x_preferred":[
        "South Nietta"
    ],
    "wof:name":"South Nietta",
    "wof:placetype":"locality"
},
  "geometry": {"coordinates":[146.07364999999999,-41.41826],"type":"Point"}
}