{
  "type": "Feature",
  "properties": {
    "gn:admin1_code":"4.0",
    "gn:admin2_code":"32500.0",
    "gn:asciiname":"Looking Glass Yard",
    "gn:country_code":"AU",
    "gn:dem":84,
    "gn:feature_class":"P",
    "gn:feature_code":"PPL",
    "gn:name":"Looking Glass Yard",
    "gn:population":0,
    "gn:timezone":"Australia/Brisbane",
    "iso:country":"AU",
    "wof:name":"Looking Glass Yard",
    "wof:placetype":"locality"
},
  "geometry": {"coordinates":[142.52866,-14.85734],"type":"Point"}
}