{
  "type": "Feature",
  "properties": {
    "gn:admin1_code":"2.0",
    "gn:admin2_code":"12950.0",
    "gn:asciiname":"Bearbung",
    "gn:country_code":"AU",
    "gn:dem":382,
    "gn:feature_class":"P",
    "gn:feature_code":"PPL",
    "gn:name":"Bearbung",
    "gn:population":0,
    "gn:timezone":"Australia/Sydney",
    "iso:country":"AU",
    "wof:name":"Bearbung",
    "wof:placetype":"locality"
},
  "geometry": {"coordinates":[148.86667,-31.63333],"type":"Point"}
}