{
  "type": "Feature",
  "properties": {
    "gn:admin1_code":"5.0",
    "gn:admin2_code":"41960.0",
    "gn:asciiname":"Warrayappa",
    "gn:country_code":"AU",
    "gn:dem":106,
    "gn:feature_class":"P",
    "gn:feature_code":"PPL",
    "gn:name":"Warrayappa",
    "gn:population":0,
    "gn:timezone":"Australia/Adelaide",
    "iso:country":"AU",
    "name:eng_x_preferred":[
        "Warrayappa"
    ],
    "wof:name":"Warrayappa",
    "wof:placetype":"locality"
},
  "geometry": {"coordinates":[137.04333,-33.45293],"type":"Point"}
}