{
  "type": "Feature",
  "properties": {
    "iso:country":"AU",
    "name:ast_x_preferred":[
        "Penwortham"
    ],
    "name:azb_x_preferred":[
        "\u067e\u0646\u0648\u0648\u0631\u062a\u0647\u0627\u0645"
    ],
    "name:ceb_x_preferred":[
        "Penwortham"
    ],
    "name:cym_x_preferred":[
        "Penwortham"
    ],
    "name:eng_x_preferred":[
        "Penwortham"
    ],
    "name:fas_x_preferred":[
        "\u067e\u0646\u0648\u0648\u0631\u062a\u0647\u0627\u0645"
    ],
    "name:fra_x_preferred":[
        "Penwortham"
    ],
    "name:gle_x_preferred":[
        "Penwortham"
    ],
    "name:ita_x_preferred":[
        "Penwortham"
    ],
    "name:nld_x_preferred":[
        "Penwortham"
    ],
    "name:pol_x_preferred":[
        "Penwortham"
    ],
    "name:swe_x_preferred":[
        "Penwortham"
    ],
    "name:vol_x_preferred":[
        "Penwortham"
    ],
    "qs_pg:aaroncc":"AU",
    "qs_pg:name":"Penwortham",
    "qs_pg:name_adm0":"Australia",
    "qs_pg:name_adm1":"South Australia",
    "qs_pg:photos":33,
    "qs_pg:photos_1k":7,
    "qs_pg:photos_9k":1,
    "qs_pg:photos_9r":2,
    "qs_pg:photos_all":33,
    "qs_pg:photos_sr":2,
    "qs_pg:pop_sr":0,
    "qs_pg:qs_pg_placetype":"locality",
    "qs_pg:qs_pg_placetype_gp":"Town",
    "qs_pg:woe_adm0":23424748,
    "woe:adm0_id":23424748,
    "woe:name_adm0":"Australia",
    "woe:name_adm1":"South Australia",
    "woe:placetype":"Town",
    "wof:name":"Penwortham",
    "wof:placetype":"locality"
},
  "geometry": {"coordinates":[138.62216599999999,-33.910029],"type":"Point"}
}