{
  "type": "Feature",
  "properties": {
    "iso:country":"AU",
    "qs_pg:aaroncc":"AU",
    "qs_pg:name":"Harmers Haven",
    "qs_pg:name_adm0":"Australia",
    "qs_pg:name_adm1":"Victoria",
    "qs_pg:photos":48,
    "qs_pg:photos_1k":10,
    "qs_pg:photos_9k":1,
    "qs_pg:photos_9r":2,
    "qs_pg:photos_all":48,
    "qs_pg:photos_sr":2,
    "qs_pg:pop_sr":0,
    "qs_pg:qs_pg_placetype":"locality",
    "qs_pg:qs_pg_placetype_gp":"Town",
    "qs_pg:woe_adm0":23424748,
    "woe:adm0_id":23424748,
    "woe:name_adm0":"Australia",
    "woe:name_adm1":"Victoria",
    "woe:placetype":"Town",
    "wof:name":"Harmers Haven",
    "wof:placetype":"locality"
},
  "geometry": {"coordinates":[145.577618,-38.654531],"type":"Point"}
}