{
  "type": "Feature",
  "properties": {
    "gn:admin1_code":"7.0",
    "gn:admin2_code":"22490.0",
    "gn:asciiname":"Golden Lake",
    "gn:country_code":"AU",
    "gn:dem":447,
    "gn:feature_class":"P",
    "gn:feature_code":"PPL",
    "gn:name":"Golden Lake",
    "gn:population":0,
    "gn:timezone":"Australia/Melbourne",
    "iso:country":"AU",
    "wof:name":"Golden Lake",
    "wof:placetype":"locality"
},
  "geometry": {"coordinates":[143.71666999999999,-37.71667],"type":"Point"}
}