{
  "type": "Feature",
  "properties": {
    "gn:country":"AU",
    "gn:fcode":"PPL",
    "gn:population":258,
    "iso:country":"AU",
    "name:ast_x_preferred":[
        "Gretna"
    ],
    "name:ceb_x_preferred":[
        "Gretna"
    ],
    "name:cym_x_preferred":[
        "Gretna"
    ],
    "name:deu_x_preferred":[
        "Gretna"
    ],
    "name:eng_x_preferred":[
        "Gretna"
    ],
    "name:fas_x_preferred":[
        "\u06af\u0631\u062a\u0646\u0627"
    ],
    "name:fra_x_preferred":[
        "Gretna"
    ],
    "name:ita_x_preferred":[
        "Gretna"
    ],
    "name:nld_x_preferred":[
        "Gretna"
    ],
    "name:pol_x_preferred":[
        "Gretna"
    ],
    "name:por_x_preferred":[
        "Gretna"
    ],
    "name:rus_x_preferred":[
        "\u0413\u0440\u0435\u0442\u043d\u0430"
    ],
    "name:spa_x_preferred":[
        "Gretna"
    ],
    "name:srp_x_preferred":[
        "\u0413\u0440\u0435\u0442\u043d\u0430"
    ],
    "name:swe_x_preferred":[
        "Gretna"
    ],
    "name:ukr_x_preferred":[
        "\u0413\u0440\u0435\u0442\u043d\u0430"
    ],
    "name:vol_x_preferred":[
        "Gretna"
    ],
    "qs_pg:aaroncc":"AU",
    "qs_pg:gn_country":"AU",
    "qs_pg:gn_fcode":"PPL",
    "qs_pg:gn_pop":258,
    "qs_pg:name":"Gretna",
    "qs_pg:name_adm0":"Australia",
    "qs_pg:name_adm1":"Tasmania",
    "qs_pg:photos":19,
    "qs_pg:photos_1k":4,
    "qs_pg:photos_9k":1,
    "qs_pg:photos_9r":1,
    "qs_pg:photos_all":19,
    "qs_pg:photos_sr":1,
    "qs_pg:pop_sr":2,
    "qs_pg:qs_pg_placetype":"locality",
    "qs_pg:qs_pg_placetype_gp":"Town",
    "qs_pg:woe_adm0":23424748,
    "woe:adm0_id":23424748,
    "woe:name_adm0":"Australia",
    "woe:name_adm1":"Tasmania",
    "woe:placetype":"Town",
    "wof:name":"Gretna",
    "wof:placetype":"locality",
    "wof:population":258
},
  "geometry": {"coordinates":[146.93333000000001,-42.68333],"type":"Point"}
}