{
  "type": "Feature",
  "properties": {
    "gn:admin1_code":"2.0",
    "gn:admin2_code":"17500.0",
    "gn:asciiname":"Green Valley",
    "gn:country_code":"AU",
    "gn:dem":647,
    "gn:feature_class":"P",
    "gn:feature_code":"PPL",
    "gn:name":"Green Valley",
    "gn:population":0,
    "gn:timezone":"Australia/Sydney",
    "iso:country":"AU",
    "name:cat_x_preferred":[
        "Green Valley"
    ],
    "name:ceb_x_preferred":[
        "Green Valley"
    ],
    "name:deu_x_preferred":[
        "Green Valley"
    ],
    "name:eng_x_preferred":[
        "Green Valley"
    ],
    "name:ita_x_preferred":[
        "Green Valley"
    ],
    "name:nld_x_preferred":[
        "Green Valley"
    ],
    "name:pol_x_preferred":[
        "Green Valley"
    ],
    "name:por_x_preferred":[
        "Green Valley"
    ],
    "name:rus_x_preferred":[
        "\u0413\u0440\u0438\u043d-\u0412\u0430\u043b\u043b\u0438"
    ],
    "name:srp_x_preferred":[
        "\u0413\u0440\u0438\u043d \u0412\u0430\u043b\u0438"
    ],
    "name:swe_x_preferred":[
        "Green Valley"
    ],
    "name:ukr_x_preferred":[
        "\u0413\u0440\u0456\u043d-\u0412\u0435\u043b\u043b\u0456"
    ],
    "name:vol_x_preferred":[
        "Green Valley"
    ],
    "wof:name":"Green Valley",
    "wof:placetype":"locality"
},
  "geometry": {"coordinates":[148.11259999999999,-35.46696],"type":"Point"}
}