{
  "type": "Feature",
  "properties": {
    "gn:admin1_code":"05",
    "gn:admin2_code":"48830.0",
    "gn:asciiname":"Couch Beach",
    "gn:country_code":"AU",
    "gn:dem":7,
    "gn:feature_class":"P",
    "gn:feature_code":"PPL",
    "gn:name":"Couch Beach",
    "gn:population":0,
    "gn:timezone":"Australia/Adelaide",
    "iso:country":"AU",
    "wof:name":"Couch Beach",
    "wof:placetype":"locality"
},
  "geometry": {"coordinates":[137.17692,-34.90951],"type":"Point"}
}