{
  "type": "Feature",
  "properties": {
    "gn:admin1_code":"8.0",
    "gn:admin2_code":"53920.0",
    "gn:asciiname":"Lurreringu",
    "gn:country_code":"AU",
    "gn:dem":391,
    "gn:feature_class":"P",
    "gn:feature_code":"PPL",
    "gn:name":"Lurreringu",
    "gn:population":0,
    "gn:timezone":"Australia/Perth",
    "iso:country":"AU",
    "wof:name":"Lurreringu",
    "wof:placetype":"locality"
},
  "geometry": {"coordinates":[127.15869000000001,-19.4786],"type":"Point"}
}