{
  "type": "Feature",
  "properties": {
    "gn:admin1_code":"5.0",
    "gn:admin2_code":"43710.0",
    "gn:asciiname":"Charlton Gully",
    "gn:country_code":"AU",
    "gn:dem":119,
    "gn:feature_class":"P",
    "gn:feature_code":"PPL",
    "gn:name":"Charlton Gully",
    "gn:population":0,
    "gn:timezone":"Australia/Adelaide",
    "iso:country":"AU",
    "wof:name":"Charlton Gully",
    "wof:placetype":"locality"
},
  "geometry": {"coordinates":[135.80355,-34.55],"type":"Point"}
}