{
  "type": "Feature",
  "properties": {
    "gn:admin1_code":"4.0",
    "gn:admin2_code":"30900.0",
    "gn:asciiname":"Hamilton Hole",
    "gn:country_code":"AU",
    "gn:dem":165,
    "gn:feature_class":"P",
    "gn:feature_code":"PPL",
    "gn:name":"Hamilton Hole",
    "gn:population":0,
    "gn:timezone":"Australia/Brisbane",
    "iso:country":"AU",
    "name:eng_x_preferred":[
        "Hamilton Hole"
    ],
    "wof:name":"Hamilton Hole",
    "wof:placetype":"locality"
},
  "geometry": {"coordinates":[140.59195,-22.77377000000001],"type":"Point"}
}