{
  "type": "Feature",
  "properties": {
    "gn:admin1_code":"8",
    "gn:admin2_code":"55390",
    "gn:asciiname":"Yarri Battery",
    "gn:country_code":"AU",
    "gn:dem":414,
    "gn:feature_class":"P",
    "gn:feature_code":"PPL",
    "gn:name":"Yarri Battery",
    "gn:population":0,
    "gn:timezone":"Australia/Perth",
    "iso:country":"AU",
    "name:eng_x_preferred":[
        "Yarri Battery"
    ],
    "name:und_x_variant":[
        "Yarri"
    ],
    "wof:name":"Yarri Battery",
    "wof:placetype":"locality"
},
  "geometry": {"coordinates":[122.35887,-29.78299],"type":"Point"}
}