{
  "type": "Feature",
  "properties": {
    "gn:admin1_code":"7.0",
    "gn:admin2_code":"26810.0",
    "gn:asciiname":"Colloden",
    "gn:country_code":"AU",
    "gn:dem":102,
    "gn:feature_class":"P",
    "gn:feature_code":"PPL",
    "gn:name":"Colloden",
    "gn:population":0,
    "gn:timezone":"Australia/Melbourne",
    "iso:country":"AU",
    "name:eng_x_preferred":[
        "Colloden"
    ],
    "wof:name":"Colloden",
    "wof:placetype":"locality"
},
  "geometry": {"coordinates":[147.11309,-37.78663],"type":"Point"}
}