{
  "type": "Feature",
  "properties": {
    "gn:admin1_code":"3.0",
    "gn:admin2_code":"70420.0",
    "gn:asciiname":"Pingala",
    "gn:country_code":"AU",
    "gn:dem":315,
    "gn:feature_class":"P",
    "gn:feature_code":"PPLL",
    "gn:name":"Pingala",
    "gn:population":0,
    "gn:timezone":"Australia/Darwin",
    "iso:country":"AU",
    "name:cat_x_preferred":[
        "Pingala"
    ],
    "name:dan_x_preferred":[
        "Pingala"
    ],
    "name:deu_x_preferred":[
        "Pingala"
    ],
    "name:fra_x_preferred":[
        "Pingala"
    ],
    "name:hin_x_preferred":[
        "\u092a\u093f\u0919\u094d\u0917\u0932"
    ],
    "name:ita_x_preferred":[
        "Pingala"
    ],
    "name:kan_x_preferred":[
        "\u0caa\u0cbf\u0c82\u0c97\u0cb3"
    ],
    "name:mal_x_preferred":[
        "\u0d2a\u0d3f\u0d02\u0d17\u0d33\u0d7b"
    ],
    "name:mwl_x_preferred":[
        "Pingala"
    ],
    "name:new_x_preferred":[
        "\u092a\u093f\u0919\u094d\u0917\u0932"
    ],
    "name:nor_x_preferred":[
        "Pingala"
    ],
    "name:pan_x_preferred":[
        "\u0a2a\u0a3f\u0a70\u0a17\u0a32"
    ],
    "name:por_x_preferred":[
        "Pingala"
    ],
    "name:rus_x_preferred":[
        "\u041f\u0438\u043d\u0433\u0430\u043b\u0430"
    ],
    "name:san_x_preferred":[
        "\u092a\u093f\u0919\u094d\u0917\u0932\u0903"
    ],
    "name:spa_x_preferred":[
        "Pingala"
    ],
    "name:swe_x_preferred":[
        "Pingala"
    ],
    "name:zho_x_preferred":[
        "\u5bbe\u4f3d\u7f57"
    ],
    "wof:name":"Pingala",
    "wof:placetype":"locality"
},
  "geometry": {"coordinates":[133.88269,-19.0932],"type":"Point"}
}