{
  "type": "Feature",
  "properties": {
    "gn:admin1_code":"3.0",
    "gn:admin2_code":"70420.0",
    "gn:asciiname":"Pingala",
    "gn:country_code":"AU",
    "gn:dem":315,
    "gn:feature_class":"P",
    "gn:feature_code":"PPLL",
    "gn:name":"Pingala",
    "gn:population":0,
    "gn:timezone":"Australia/Darwin",
    "iso:country":"AU",
    "wof:name":"Pingala",
    "wof:placetype":"locality"
},
  "geometry": {"coordinates":[133.88269,-19.0932],"type":"Point"}
}