{
  "type": "Feature",
  "properties": {
    "gn:country":"AU",
    "gn:fcode":"PPL",
    "gn:population":533,
    "iso:country":"AU",
    "name:ceb_x_preferred":[
        "Basket Range"
    ],
    "name:eng_x_preferred":[
        "Basket Range"
    ],
    "name:fas_x_preferred":[
        "\u0628\u0633\u06a9\u062a \u0631\u0646\u062c"
    ],
    "name:nld_x_preferred":[
        "Basket Range"
    ],
    "name:swe_x_preferred":[
        "Basket Range"
    ],
    "qs_pg:aaroncc":"AU",
    "qs_pg:gn_country":"AU",
    "qs_pg:gn_fcode":"PPL",
    "qs_pg:gn_pop":533,
    "qs_pg:name":"Basket Range",
    "qs_pg:name_adm0":"Australia",
    "qs_pg:name_adm1":"South Australia",
    "qs_pg:photos":13,
    "qs_pg:photos_1k":3,
    "qs_pg:photos_9k":1,
    "qs_pg:photos_9r":1,
    "qs_pg:photos_all":13,
    "qs_pg:photos_sr":1,
    "qs_pg:pop_sr":2,
    "qs_pg:qs_pg_placetype":"locality",
    "qs_pg:qs_pg_placetype_gp":"Town",
    "qs_pg:woe_adm0":23424748,
    "woe:adm0_id":23424748,
    "woe:name_adm0":"Australia",
    "woe:name_adm1":"South Australia",
    "woe:placetype":"Town",
    "wof:name":"Basket Range",
    "wof:placetype":"locality",
    "wof:population":294
},
  "geometry": {"coordinates":[138.76505,-34.93977],"type":"Point"}
}