{
  "type": "Feature",
  "properties": {
    "gn:admin1_code":"2.0",
    "gn:admin2_code":"13850.0",
    "gn:asciiname":"One Tree",
    "gn:country_code":"AU",
    "gn:dem":86,
    "gn:feature_class":"P",
    "gn:feature_code":"PPL",
    "gn:name":"One Tree",
    "gn:population":0,
    "gn:timezone":"Australia/Sydney",
    "iso:country":"AU",
    "name:eng_x_preferred":[
        "One Tree"
    ],
    "name:und_x_variant":[
        "Village of One Tree"
    ],
    "wof:name":"One Tree",
    "wof:placetype":"locality"
},
  "geometry": {"coordinates":[144.71715,-34.18888],"type":"Point"}
}