{
  "type": "Feature",
  "properties": {
    "gn:admin1_code":"7",
    "gn:admin2_code":"24250",
    "gn:asciiname":"Woodfield",
    "gn:country_code":"AU",
    "gn:dem":300,
    "gn:feature_class":"P",
    "gn:feature_code":"PPL",
    "gn:name":"Woodfield",
    "gn:population":0,
    "gn:timezone":"Australia/Melbourne",
    "iso:country":"AU",
    "wof:name":"Woodfield",
    "wof:placetype":"locality"
},
  "geometry": {"coordinates":[145.80000000000001,-37.01667],"type":"Point"}
}