{
  "type": "Feature",
  "properties": {
    "gn:admin1_code":"8",
    "gn:admin2_code":"56370",
    "gn:asciiname":"Emu Hill",
    "gn:country_code":"AU",
    "gn:dem":283,
    "gn:feature_class":"P",
    "gn:feature_code":"PPL",
    "gn:name":"Emu Hill",
    "gn:population":0,
    "gn:timezone":"Australia/Perth",
    "iso:country":"AU",
    "wof:name":"Emu Hill",
    "wof:placetype":"locality"
},
  "geometry": {"coordinates":[118.367,-32.10597],"type":"Point"}
}