{
  "type": "Feature",
  "properties": {
    "gn:gn_country":"AU",
    "gn:gn_fcode":"PPL",
    "gn:gn_pop":0,
    "iso:country":"AU",
    "name:ceb_x_preferred":[
        "Wensleydale"
    ],
    "name:deu_x_preferred":[
        "Wensleydale"
    ],
    "name:eng_x_preferred":[
        "Wensleydale"
    ],
    "name:fra_x_preferred":[
        "Wensleydale"
    ],
    "name:isl_x_preferred":[
        "Wensleydale"
    ],
    "name:ita_x_preferred":[
        "Wensleydale"
    ],
    "name:nld_x_preferred":[
        "Wensleydale"
    ],
    "name:nor_x_preferred":[
        "Wensleydale"
    ],
    "name:pnb_x_preferred":[
        "\u0648\u06cc\u0646\u0632\u0644\u06d2\u0688\u06cc\u0644"
    ],
    "name:pol_x_preferred":[
        "Wensleydale"
    ],
    "name:spa_x_preferred":[
        "Wensleydale"
    ],
    "name:swe_x_preferred":[
        "Wensleydale"
    ],
    "qs_pg:aaroncc":"AU",
    "qs_pg:gn_country":"AU",
    "qs_pg:gn_fcode":"PPL",
    "qs_pg:gn_pop":0,
    "qs_pg:name":"Wensleydale",
    "qs_pg:name_adm0":"Australia",
    "qs_pg:name_adm1":"Victoria",
    "qs_pg:photos_9k":1,
    "qs_pg:photos_9r":1,
    "qs_pg:photos_all":10,
    "qs_pg:photos_sr":0,
    "qs_pg:pop_sr":0,
    "qs_pg:qs_pg_placetype":"locality",
    "qs_pg:qs_pg_placetype_gp":"Town",
    "qs_pg:woe_adm0":23424748,
    "woe:adm0_id":23424748,
    "woe:name_adm0":"Australia",
    "woe:name_adm1":"Victoria",
    "woe:placetype":"Town",
    "wof:name":"Wensleydale",
    "wof:placetype":"locality"
},
  "geometry": {"coordinates":[144.03333000000001,-38.35],"type":"Point"}
}