{
  "type": "Feature",
  "properties": {
    "gn:admin1_code":"4",
    "gn:admin2_code":"33610",
    "gn:asciiname":"Welltown",
    "gn:country_code":"AU",
    "gn:dem":191,
    "gn:feature_class":"P",
    "gn:feature_code":"PPL",
    "gn:name":"Welltown",
    "gn:population":0,
    "gn:timezone":"Australia/Brisbane",
    "iso:country":"AU",
    "name:eus_x_preferred":[
        "Welltown"
    ],
    "wof:name":"Welltown",
    "wof:placetype":"locality"
},
  "geometry": {"coordinates":[149.75,-28.45],"type":"Point"}
}