{
  "type": "Feature",
  "properties": {
    "iso:country":"AU",
    "name:ceb_x_preferred":[
        "Kings Park"
    ],
    "name:eng_x_preferred":[
        "Kings Park"
    ],
    "name:eng_x_variant":[
        "Kingspark"
    ],
    "name:hbs_x_preferred":[
        "Kings Park"
    ],
    "name:pol_x_preferred":[
        "Kings Park"
    ],
    "name:srp_x_preferred":[
        "\u041a\u0438\u043d\u0433\u0441 \u041f\u0430\u0440\u043a"
    ],
    "name:swe_x_preferred":[
        "Kings Park"
    ],
    "name:ukr_x_preferred":[
        "\u041a\u0456\u043d\u0433\u0441-\u041f\u0430\u0440\u043a"
    ],
    "qs:gn_adm0_cc":"AU",
    "qs:gn_local":2063523,
    "qs:local_max":26312,
    "qs:local_sum":139041,
    "qs:localhoods":187,
    "qs:name":"Kings Park",
    "qs:name_adm0":"Australia",
    "qs:name_adm1":"Western Australia",
    "qs:name_adm2":"Perth",
    "qs:name_local":"Perth",
    "qs:photo_max":24,
    "qs:photo_sum":24,
    "qs:placetype":"Suburb",
    "qs:quad_count":1,
    "qs:woe_adm0":23424748,
    "qs:woe_adm1":2344706,
    "qs:woe_adm2":55864398,
    "qs:woe_lau":0,
    "qs:woe_local":1098081,
    "qs:woe_ver":"7.10.0",
    "wof:lang":[
        "eng"
    ],
    "wof:name":"Kings Park",
    "wof:placetype":"neighbourhood"
},
  "geometry": {"coordinates":[115.831604,-31.963814],"type":"Point"}
}