{
  "type": "Feature",
  "properties": {
    "gn:admin1_code":"2",
    "gn:admin2_code":"14600",
    "gn:asciiname":"Vermont Hill",
    "gn:country_code":"AU",
    "gn:dem":290,
    "gn:feature_class":"P",
    "gn:feature_code":"PPL",
    "gn:name":"Vermont Hill",
    "gn:population":0,
    "gn:timezone":"Australia/Sydney",
    "iso:country":"AU",
    "name:eng_x_preferred":[
        "Vermont Hill"
    ],
    "wof:name":"Vermont Hill",
    "wof:placetype":"locality"
},
  "geometry": {"coordinates":[146.74943000000005,-32.56838],"type":"Point"}
}