{
  "type": "Feature",
  "properties": {
    "gn:admin1_code":"2.0",
    "gn:admin2_code":"12350.0",
    "gn:asciiname":"Billimari",
    "gn:country_code":"AU",
    "gn:dem":306,
    "gn:feature_class":"P",
    "gn:feature_code":"PPL",
    "gn:name":"Billimari",
    "gn:population":0,
    "gn:timezone":"Australia/Sydney",
    "iso:country":"AU",
    "wof:name":"Billimari",
    "wof:placetype":"locality"
},
  "geometry": {"coordinates":[148.61959999999999,-33.6741],"type":"Point"}
}