{
  "type": "Feature",
  "properties": {
    "gn:admin1_code":"2.0",
    "gn:admin2_code":"13800.0",
    "gn:asciiname":"Brawdy Farm",
    "gn:country_code":"AU",
    "gn:dem":23,
    "gn:feature_class":"P",
    "gn:feature_code":"PPL",
    "gn:name":"Brawdy Farm",
    "gn:population":0,
    "gn:timezone":"Australia/Sydney",
    "iso:country":"AU",
    "name:eng_x_preferred":[
        "Brawdy Farm"
    ],
    "wof:name":"Brawdy Farm",
    "wof:placetype":"locality"
},
  "geometry": {"coordinates":[150.70674,-33.41067],"type":"Point"}
}