{
  "type": "Feature",
  "properties": {
    "gn:admin1_code":"7.0",
    "gn:admin2_code":"23810.0",
    "gn:asciiname":"Mirboo East",
    "gn:country_code":"AU",
    "gn:dem":316,
    "gn:feature_class":"P",
    "gn:feature_code":"PPL",
    "gn:name":"Mirboo East",
    "gn:population":0,
    "gn:timezone":"Australia/Melbourne",
    "iso:country":"AU",
    "wof:name":"Mirboo East",
    "wof:placetype":"locality"
},
  "geometry": {"coordinates":[146.28333000000001,-38.48333],"type":"Point"}
}