{
  "type": "Feature",
  "properties": {
    "iso:country":"AU",
    "name:eng_x_preferred":[
        "St. Helena"
    ],
    "name:eng_x_variant":[
        "Saint Helena",
        "St Helena"
    ],
    "name:unk_x_variant":[
        "St. Helena"
    ],
    "qs:gn_adm0_cc":"AU",
    "qs:gn_fcode":"PPLX",
    "qs:gn_local":2158177,
    "qs:gn_namadm1":"07",
    "qs:gn_name":"St Helena",
    "qs:local_max":22745,
    "qs:local_sum":338594,
    "qs:localhoods":407,
    "qs:name":"St. Helena",
    "qs:name_adm0":"Australia",
    "qs:name_adm1":"Victoria",
    "qs:name_adm2":"City of Banyule",
    "qs:name_local":"Melbourne",
    "qs:photo_max":6,
    "qs:photo_sum":14,
    "qs:placetype":"Suburb",
    "qs:quad_count":4,
    "qs:woe_adm0":23424748,
    "qs:woe_adm1":2344705,
    "qs:woe_adm2":55864012,
    "qs:woe_lau":0,
    "qs:woe_local":1103816,
    "qs:woe_ver":"7.10.0",
    "wof:lang":[
        "eng"
    ],
    "wof:name":"St. Helena",
    "wof:placetype":"neighbourhood"
},
  "geometry": {"coordinates":[145.12725399999999,-37.687304],"type":"Point"}
}