{
  "type": "Feature",
  "properties": {
    "iso:country":"AU",
    "name:eng_x_preferred":[
        "HMAS Kuttabul"
    ],
    "name:pol_x_preferred":[
        "HMAS Kuttabul"
    ],
    "name:slv_x_preferred":[
        "HMAS Kuttabul"
    ],
    "qs:gn_adm0_cc":"AU",
    "qs:gn_local":2147714,
    "qs:local_max":35533,
    "qs:local_sum":687549,
    "qs:localhoods":516,
    "qs:name":"HMAS Kuttabul",
    "qs:name_adm0":"Australia",
    "qs:name_adm1":"New South Wales",
    "qs:name_adm2":"Sydney",
    "qs:name_local":"Sydney",
    "qs:photo_max":481,
    "qs:photo_sum":2108,
    "qs:placetype":"Suburb",
    "qs:quad_count":32,
    "qs:woe_adm0":23424748,
    "qs:woe_adm1":2344700,
    "qs:woe_adm2":55864169,
    "qs:woe_lau":0,
    "qs:woe_local":1105779,
    "qs:woe_ver":"7.10.0",
    "wd:wordcount":82,
    "wof:lang":[
        "eng"
    ],
    "wof:name":"HMAS Kuttabul",
    "wof:placetype":"neighbourhood"
},
  "geometry": {"coordinates":[151.22326465238919,-33.86589971128391],"type":"Point"}
}