{
  "type": "Feature",
  "properties": {
    "gn:admin1_code":"06",
    "gn:admin2_code":"64210.0",
    "gn:asciiname":"Cluan",
    "gn:country_code":"AU",
    "gn:dem":208,
    "gn:feature_class":"P",
    "gn:feature_code":"PPL",
    "gn:name":"Cluan",
    "gn:population":0,
    "gn:timezone":"Australia/Hobart",
    "iso:country":"AU",
    "name:eng_x_preferred":[
        "Cluan"
    ],
    "wof:name":"Cluan",
    "wof:placetype":"locality"
},
  "geometry": {"coordinates":[146.87261999999996,-41.60498],"type":"Point"}
}