{
  "type": "Feature",
  "properties": {
    "gn:admin1_code":"7",
    "gn:admin2_code":"21010",
    "gn:asciiname":"Stewarton",
    "gn:country_code":"AU",
    "gn:dem":147,
    "gn:feature_class":"P",
    "gn:feature_code":"PPL",
    "gn:name":"Stewarton",
    "gn:population":0,
    "gn:timezone":"Australia/Melbourne",
    "iso:country":"AU",
    "name:azb_x_preferred":[
        "\u0627\u0633\u062a\u0648\u0627\u0631\u062a\u0648\u0646"
    ],
    "name:ceb_x_preferred":[
        "Stewarton"
    ],
    "name:cym_x_preferred":[
        "Stewarton"
    ],
    "name:deu_x_preferred":[
        "Stewarton"
    ],
    "name:eus_x_preferred":[
        "Stewarton"
    ],
    "name:fas_x_preferred":[
        "\u0627\u0633\u062a\u0648\u0627\u0631\u062a\u0648\u0646"
    ],
    "name:ita_x_preferred":[
        "Stewarton"
    ],
    "name:pol_x_preferred":[
        "Stewarton"
    ],
    "name:sco_x_preferred":[
        "Stewartoun"
    ],
    "name:spa_x_preferred":[
        "Stewarton"
    ],
    "name:swe_x_preferred":[
        "Stewarton"
    ],
    "wof:name":"Stewarton",
    "wof:placetype":"locality"
},
  "geometry": {"coordinates":[145.80000000000001,-36.43333],"type":"Point"}
}