{
  "type": "Feature",
  "properties": {
    "gn:admin1_code":"2.0",
    "gn:admin2_code":"10850.0",
    "gn:asciiname":"Cadia",
    "gn:country_code":"AU",
    "gn:dem":837,
    "gn:feature_class":"P",
    "gn:feature_code":"PPL",
    "gn:name":"Cadia",
    "gn:population":0,
    "gn:timezone":"Australia/Sydney",
    "iso:country":"AU",
    "name:ceb_x_preferred":[
        "Cadia"
    ],
    "name:swe_x_preferred":[
        "Cadia"
    ],
    "wof:name":"Cadia",
    "wof:placetype":"locality"
},
  "geometry": {"coordinates":[148.9846,-33.4485],"type":"Point"}
}