{
  "type": "Feature",
  "properties": {
    "iso:country":"AU",
    "name:eng_x_preferred":[
        "Taree"
    ],
    "wof:coterminous":[
        1376953329
    ],
    "wof:lang_x_official":[
        "eng"
    ],
    "wof:lang_x_spoken":[
        "eng"
    ],
    "wof:name":"Taree",
    "wof:placetype":"locality"
},
  "geometry": {"coordinates":[152.438906,-31.877858],"type":"Point"}
}