{
  "type": "Feature",
  "properties": {
    "iso:country":"AU",
    "name:ara_x_preferred":[
        "\u062a\u0627\u0631\u064a"
    ],
    "name:ceb_x_preferred":[
        "Taree"
    ],
    "name:deu_x_preferred":[
        "Taree"
    ],
    "name:eng_x_preferred":[
        "Taree"
    ],
    "name:fas_x_preferred":[
        "\u062a\u0627\u0631\u06cc"
    ],
    "name:fin_x_preferred":[
        "Taree"
    ],
    "name:fra_x_preferred":[
        "Taree"
    ],
    "name:gle_x_preferred":[
        "Taree"
    ],
    "name:mlg_x_preferred":[
        "Taree"
    ],
    "name:nor_x_preferred":[
        "Taree"
    ],
    "name:pol_x_preferred":[
        "Taree"
    ],
    "name:rus_x_preferred":[
        "\u0422\u0430\u0440\u0438"
    ],
    "name:swe_x_preferred":[
        "Taree"
    ],
    "name:ukr_x_preferred":[
        "\u0422\u0430\u0440\u0456"
    ],
    "wof:coterminous":[
        1376953329
    ],
    "wof:lang_x_official":[
        "eng"
    ],
    "wof:lang_x_spoken":[
        "eng"
    ],
    "wof:name":"Taree",
    "wof:placetype":"locality"
},
  "geometry": {"coordinates":[152.438906,-31.877858],"type":"Point"}
}