{
  "type": "Feature",
  "properties": {
    "gn:admin1_code":"4.0",
    "gn:admin2_code":"36360.0",
    "gn:asciiname":"Kalapa",
    "gn:country_code":"AU",
    "gn:dem":54,
    "gn:feature_class":"P",
    "gn:feature_code":"PPL",
    "gn:name":"Kalapa",
    "gn:population":0,
    "gn:timezone":"Australia/Brisbane",
    "iso:country":"AU",
    "name:ast_x_preferred":[
        "Kal\u0101pa"
    ],
    "name:fra_x_preferred":[
        "Kalapa"
    ],
    "name:spa_x_preferred":[
        "Kalapa"
    ],
    "wof:name":"Kalapa",
    "wof:placetype":"locality"
},
  "geometry": {"coordinates":[150.26667,-23.51667],"type":"Point"}
}