{
  "type": "Feature",
  "properties": {
    "gn:admin1_code":"7.0",
    "gn:asciiname":"Lindsay",
    "gn:cc2":"AU",
    "gn:country_code":"AU",
    "gn:dem":70,
    "gn:feature_class":"P",
    "gn:feature_code":"PPL",
    "gn:name":"Lindsay",
    "gn:population":0,
    "gn:timezone":"Australia/Adelaide",
    "iso:country":"AU",
    "name:und_x_variant":[
        "Lindsay Station",
        "Lindsay"
    ],
    "wof:name":"Lindsay",
    "wof:placetype":"locality"
},
  "geometry": {"coordinates":[140.96666999999999,-37.63333],"type":"Point"}
}