{
  "type": "Feature",
  "properties": {
    "gn:admin1_code":"8.0",
    "gn:admin2_code":"59660.0",
    "gn:asciiname":"Narla",
    "gn:country_code":"AU",
    "gn:dem":347,
    "gn:feature_class":"P",
    "gn:feature_code":"PPL",
    "gn:name":"Narla",
    "gn:population":0,
    "gn:timezone":"Australia/Perth",
    "iso:country":"AU",
    "name:eng_x_preferred":[
        "Narla"
    ],
    "wof:name":"Narla",
    "wof:placetype":"locality"
},
  "geometry": {"coordinates":[119.00593000000001,-30.98701],"type":"Point"}
}