{
  "type": "Feature",
  "properties": {
    "gn:admin1_code":"2.0",
    "gn:admin2_code":"13310.0",
    "gn:asciiname":"Norwood",
    "gn:country_code":"AU",
    "gn:dem":696,
    "gn:feature_class":"P",
    "gn:feature_code":"PPL",
    "gn:name":"Norwood",
    "gn:population":0,
    "gn:timezone":"Australia/Sydney",
    "iso:country":"AU",
    "wof:name":"Norwood",
    "wof:placetype":"locality"
},
  "geometry": {"coordinates":[149.73333,-34.66667],"type":"Point"}
}