{
  "type": "Feature",
  "properties": {
    "gn:admin1_code":"2.0",
    "gn:admin2_code":"13310.0",
    "gn:asciiname":"Norwood",
    "gn:country_code":"AU",
    "gn:dem":696,
    "gn:feature_class":"P",
    "gn:feature_code":"PPL",
    "gn:name":"Norwood",
    "gn:population":0,
    "gn:timezone":"Australia/Sydney",
    "iso:country":"AU",
    "name:cat_x_preferred":[
        "Norwood"
    ],
    "name:ceb_x_preferred":[
        "Norwood"
    ],
    "name:ces_x_preferred":[
        "Norwood"
    ],
    "name:deu_x_preferred":[
        "Norwood"
    ],
    "name:fas_x_preferred":[
        "\u0646\u0648\u0631\u0648\u0648\u062f"
    ],
    "name:fra_x_preferred":[
        "Norwood"
    ],
    "name:ita_x_preferred":[
        "Norwood"
    ],
    "name:nld_x_preferred":[
        "Norwood"
    ],
    "name:pol_x_preferred":[
        "Norwood"
    ],
    "name:por_x_preferred":[
        "Norwood"
    ],
    "name:rus_x_preferred":[
        "\u041d\u043e\u0440\u0432\u0443\u0434"
    ],
    "name:srp_x_preferred":[
        "\u041d\u043e\u0440\u0432\u0443\u0434"
    ],
    "name:swa_x_preferred":[
        "Norwood"
    ],
    "name:swe_x_preferred":[
        "Norwood"
    ],
    "wof:name":"Norwood",
    "wof:placetype":"locality"
},
  "geometry": {"coordinates":[149.73333,-34.66667],"type":"Point"}
}