{
  "type": "Feature",
  "properties": {
    "gn:admin1_code":"4.0",
    "gn:admin2_code":"36360.0",
    "gn:asciiname":"Eden Garry",
    "gn:country_code":"AU",
    "gn:dem":94,
    "gn:feature_class":"P",
    "gn:feature_code":"PPL",
    "gn:name":"Eden Garry",
    "gn:population":0,
    "gn:timezone":"Australia/Brisbane",
    "iso:country":"AU",
    "name:eng_x_preferred":[
        "Eden Garry"
    ],
    "wof:name":"Eden Garry",
    "wof:placetype":"locality"
},
  "geometry": {"coordinates":[150.0669,-22.84766],"type":"Point"}
}