{
  "type": "Feature",
  "properties": {
    "gn:admin1_code":"4.0",
    "gn:admin2_code":"37340.0",
    "gn:asciiname":"Don",
    "gn:country_code":"AU",
    "gn:dem":14,
    "gn:feature_class":"P",
    "gn:feature_code":"PPL",
    "gn:name":"Don",
    "gn:population":0,
    "gn:timezone":"Australia/Brisbane",
    "iso:country":"AU",
    "wof:name":"Don",
    "wof:placetype":"locality"
},
  "geometry": {"coordinates":[148.19999999999999,-20.01667],"type":"Point"}
}