{
  "type": "Feature",
  "properties": {
    "gn:admin1_code":"5.0",
    "gn:admin2_code":"47490.0",
    "gn:asciiname":"Oak Vale",
    "gn:country_code":"AU",
    "gn:dem":23,
    "gn:feature_class":"P",
    "gn:feature_code":"PPL",
    "gn:name":"Oak Vale",
    "gn:population":0,
    "gn:timezone":"Australia/Adelaide",
    "iso:country":"AU",
    "name:eng_x_preferred":[
        "Oak Vale"
    ],
    "wof:name":"Oak Vale",
    "wof:placetype":"locality"
},
  "geometry": {"coordinates":[134.37073999999998,-32.91188],"type":"Point"}
}