{
  "type": "Feature",
  "properties": {
    "gn:admin1_code":"2.0",
    "gn:admin2_code":"14600.0",
    "gn:asciiname":"Fountain Dale",
    "gn:country_code":"AU",
    "gn:dem":239,
    "gn:feature_class":"P",
    "gn:feature_code":"PPL",
    "gn:name":"Fountain Dale",
    "gn:population":0,
    "gn:timezone":"Australia/Sydney",
    "iso:country":"AU",
    "name:eng_x_preferred":[
        "Fountain Dale"
    ],
    "wof:name":"Fountain Dale",
    "wof:placetype":"locality"
},
  "geometry": {"coordinates":[146.87124,-32.59467],"type":"Point"}
}