{
  "type": "Feature",
  "properties": {
    "gn:admin1_code":"6.0",
    "gn:admin2_code":"63010.0",
    "gn:asciiname":"Longley Lower",
    "gn:country_code":"AU",
    "gn:dem":280,
    "gn:feature_class":"P",
    "gn:feature_code":"PPL",
    "gn:name":"Longley Lower",
    "gn:population":0,
    "gn:timezone":"Australia/Hobart",
    "iso:country":"AU",
    "name:und_x_variant":[
        "Lower Longley",
        "Longley Lower"
    ],
    "wof:name":"Longley Lower",
    "wof:placetype":"locality"
},
  "geometry": {"coordinates":[147.14439999999999,-42.97905],"type":"Point"}
}