{
  "type": "Feature",
  "properties": {
    "gn:admin1_code":"4",
    "gn:admin2_code":"37310",
    "gn:asciiname":"Wallan Creek",
    "gn:country_code":"AU",
    "gn:dem":371,
    "gn:feature_class":"P",
    "gn:feature_code":"PPL",
    "gn:name":"Wallan Creek",
    "gn:population":0,
    "gn:timezone":"Australia/Brisbane",
    "iso:country":"AU",
    "wof:name":"Wallan Creek",
    "wof:placetype":"locality"
},
  "geometry": {"coordinates":[149.93333000000001,-26.51667],"type":"Point"}
}