{
  "type": "Feature",
  "properties": {
    "gn:admin1_code":"04",
    "gn:admin2_code":"37340.0",
    "gn:asciiname":"Lindeman Island",
    "gn:country_code":"AU",
    "gn:dem":64,
    "gn:feature_class":"P",
    "gn:feature_code":"PPL",
    "gn:name":"Lindeman Island",
    "gn:population":0,
    "gn:timezone":"Australia/Lindeman",
    "iso:country":"AU",
    "wof:name":"Lindeman Island",
    "wof:placetype":"locality"
},
  "geometry": {"coordinates":[149.03898000000001,-20.44825],"type":"Point"}
}