{
  "type": "Feature",
  "properties": {
    "gn:admin1_code":"2.0",
    "gn:admin2_code":"14600.0",
    "gn:asciiname":"Bimbella",
    "gn:country_code":"AU",
    "gn:dem":175,
    "gn:feature_class":"P",
    "gn:feature_code":"PPL",
    "gn:name":"Bimbella",
    "gn:population":0,
    "gn:timezone":"Australia/Sydney",
    "iso:country":"AU",
    "name:eng_x_preferred":[
        "Bimbella"
    ],
    "wof:name":"Bimbella",
    "wof:placetype":"locality"
},
  "geometry": {"coordinates":[146.82043999999999,-32.9798],"type":"Point"}
}