{
  "type": "Feature",
  "properties": {
    "gn:admin1_code":"4.0",
    "gn:admin2_code":"32450.0",
    "gn:asciiname":"Corrie Downs",
    "gn:country_code":"AU",
    "gn:dem":217,
    "gn:feature_class":"P",
    "gn:feature_code":"PPL",
    "gn:name":"Corrie Downs",
    "gn:population":0,
    "gn:timezone":"Australia/Brisbane",
    "iso:country":"AU",
    "name:eng_x_preferred":[
        "Corrie Downs"
    ],
    "wof:name":"Corrie Downs",
    "wof:placetype":"locality"
},
  "geometry": {"coordinates":[140.10747000000001,-22.30052],"type":"Point"}
}