{
  "type": "Feature",
  "properties": {
    "gn:admin1_code":"7.0",
    "gn:admin2_code":"26810.0",
    "gn:asciiname":"Glenrose",
    "gn:country_code":"AU",
    "gn:dem":153,
    "gn:feature_class":"P",
    "gn:feature_code":"PPL",
    "gn:name":"Glenrose",
    "gn:population":0,
    "gn:timezone":"Australia/Melbourne",
    "iso:country":"AU",
    "wof:name":"Glenrose",
    "wof:placetype":"locality"
},
  "geometry": {"coordinates":[146.59999999999999,-38.51667],"type":"Point"}
}