{
  "type": "Feature",
  "properties": {
    "gn:population":3099,
    "iso:country":"AU",
    "name:ceb_x_preferred":[
        "Erskine"
    ],
    "name:eng_x_preferred":[
        "Erskine"
    ],
    "name:fra_x_preferred":[
        "Erskine"
    ],
    "name:swe_x_preferred":[
        "Erskine"
    ],
    "qs:gn_adm0_cc":"AU",
    "qs:gn_fcode":"PPL",
    "qs:gn_local":2067119,
    "qs:gn_nam_loc":"Mandurah, Mandurah, Western Australia, AU",
    "qs:gn_namadm1":"08",
    "qs:gn_name":"Erskine",
    "qs:local_max":499,
    "qs:local_sum":1014,
    "qs:localhoods":7,
    "qs:name":"Erskine",
    "qs:name_adm0":"Australia",
    "qs:name_adm1":"Western Australia",
    "qs:name_adm2":"Mandurah",
    "qs:name_local":"Mandurah",
    "qs:photo_max":12,
    "qs:photo_sum":79,
    "qs:placetype":"Suburb",
    "qs:quad_count":20,
    "qs:woe_adm0":23424748,
    "qs:woe_adm1":2344706,
    "qs:woe_adm2":55864400,
    "qs:woe_lau":0,
    "qs:woe_local":1103644,
    "qs:woe_ver":"7.10.0",
    "wof:name":"Erskine",
    "wof:placetype":"neighbourhood",
    "wof:population":3099
},
  "geometry": {"coordinates":[115.688318,-32.555175],"type":"Point"}
}