{
  "type": "Feature",
  "properties": {
    "gn:admin1_code":"2.0",
    "gn:admin2_code":"14200.0",
    "gn:asciiname":"Cherry Tree Hill",
    "gn:country_code":"AU",
    "gn:dem":657,
    "gn:feature_class":"P",
    "gn:feature_code":"PPL",
    "gn:name":"Cherry Tree Hill",
    "gn:population":0,
    "gn:timezone":"Australia/Sydney",
    "iso:country":"AU",
    "name:eng_x_preferred":[
        "Cherry Tree Hill"
    ],
    "wof:name":"Cherry Tree Hill",
    "wof:placetype":"locality"
},
  "geometry": {"coordinates":[150.99463,-29.53677],"type":"Point"}
}