{
  "type": "Feature",
  "properties": {
    "gn:admin1_code":"8",
    "gn:admin2_code":"51120",
    "gn:asciiname":"Belka",
    "gn:country_code":"AU",
    "gn:dem":275,
    "gn:feature_class":"P",
    "gn:feature_code":"PPL",
    "gn:name":"Belka",
    "gn:population":0,
    "gn:timezone":"Australia/Perth",
    "iso:country":"AU",
    "name:ceb_x_preferred":[
        "Belka"
    ],
    "name:deu_x_preferred":[
        "Belka"
    ],
    "name:eng_x_preferred":[
        "Belka"
    ],
    "name:est_x_preferred":[
        "Belka"
    ],
    "name:hye_x_preferred":[
        "\u0532\u0565\u056c\u056f\u0561"
    ],
    "name:ita_x_preferred":[
        "Belka"
    ],
    "name:por_x_preferred":[
        "Belka"
    ],
    "name:rus_x_preferred":[
        "\u0411\u0435\u043b\u043a\u0430"
    ],
    "name:swe_x_preferred":[
        "Belka"
    ],
    "wof:name":"Belka",
    "wof:placetype":"locality"
},
  "geometry": {"coordinates":[118.17397,-31.73836],"type":"Point"}
}