{
  "type": "Feature",
  "properties": {
    "gn:admin1_code":"7.0",
    "gn:admin2_code":"22620.0",
    "gn:asciiname":"Diggorra",
    "gn:cc2":"AU",
    "gn:country_code":"AU",
    "gn:dem":123,
    "gn:feature_class":"P",
    "gn:feature_code":"PPL",
    "gn:name":"Diggorra",
    "gn:population":0,
    "gn:timezone":"Australia/Melbourne",
    "iso:country":"AU",
    "name:und_x_variant":[
        "Diggora West",
        "Diggora",
        "Diggorra"
    ],
    "wof:name":"Diggorra",
    "wof:placetype":"locality"
},
  "geometry": {"coordinates":[144.58333000000005,-36.41667],"type":"Point"}
}