{
  "type": "Feature",
  "properties": {
    "gn:gn_country":"AU",
    "gn:gn_fcode":"PPL",
    "gn:gn_pop":76,
    "gn:population":76,
    "iso:country":"AU",
    "name:dut_x_preferred":[
        "Morundah"
    ],
    "name:eng_x_preferred":[
        "Morundah"
    ],
    "name:fre_x_preferred":[
        "Morundah"
    ],
    "name:ger_x_preferred":[
        "Morundah"
    ],
    "qs_pg:aaroncc":"AU",
    "qs_pg:gn_country":"AU",
    "qs_pg:gn_fcode":"PPL",
    "qs_pg:gn_pop":76,
    "qs_pg:name":"Morundah",
    "qs_pg:photos_9r":0,
    "qs_pg:photos_sr":0,
    "qs_pg:pop_sr":1,
    "qs_pg:qs_pg_placetype":"locality",
    "wof:name":"Morundah",
    "wof:placetype":"locality",
    "wof:population":76
},
  "geometry": {"coordinates":[146.30000000000001,-34.93333],"type":"Point"}
}