{
  "type": "Feature",
  "properties": {
    "gn:gn_country":"AU",
    "gn:gn_fcode":"PPL",
    "gn:gn_pop":450,
    "gn:population":450,
    "iso:country":"AU",
    "name:dut_x_preferred":[
        "Yelarbon"
    ],
    "name:eng_x_preferred":[
        "Yelarbon"
    ],
    "name:fre_x_preferred":[
        "Yelarbon"
    ],
    "name:swe_x_preferred":[
        "Yelarbon"
    ],
    "qs_pg:aaroncc":"AU",
    "qs_pg:gn_country":"AU",
    "qs_pg:gn_fcode":"PPL",
    "qs_pg:gn_pop":450,
    "qs_pg:name":"Yelarbon",
    "qs_pg:name_adm0":"Australia",
    "qs_pg:name_adm1":"Queensland",
    "qs_pg:photos":4,
    "qs_pg:photos_1k":1,
    "qs_pg:photos_9k":1,
    "qs_pg:photos_9r":1,
    "qs_pg:photos_all":4,
    "qs_pg:photos_sr":1,
    "qs_pg:pop_sr":2,
    "qs_pg:qs_pg_placetype":"locality",
    "qs_pg:qs_pg_placetype_gp":"Town",
    "qs_pg:woe_adm0":23424748,
    "woe:adm0_id":23424748,
    "woe:name_adm0":"Australia",
    "woe:name_adm1":"Queensland",
    "woe:placetype":"Town",
    "wof:name":"Yelarbon",
    "wof:placetype":"locality",
    "wof:population":450
},
  "geometry": {"coordinates":[150.75134,-28.57247],"type":"Point"}
}