{
  "type": "Feature",
  "properties": {
    "gn:admin1_code":"2.0",
    "gn:admin2_code":"17050.0",
    "gn:asciiname":"Lincluden",
    "gn:country_code":"AU",
    "gn:dem":957,
    "gn:feature_class":"P",
    "gn:feature_code":"PPL",
    "gn:name":"Lincluden",
    "gn:population":0,
    "gn:timezone":"Australia/Sydney",
    "iso:country":"AU",
    "name:eng_x_preferred":[
        "Lincluden"
    ],
    "wof:name":"Lincluden",
    "wof:placetype":"locality"
},
  "geometry": {"coordinates":[149.12472,-36.45497],"type":"Point"}
}