{
  "type": "Feature",
  "properties": {
    "gn:admin1_code":"3.0",
    "gn:admin2_code":"70420.0",
    "gn:asciiname":"Namerinni",
    "gn:country_code":"AU",
    "gn:dem":260,
    "gn:feature_class":"P",
    "gn:feature_code":"PPLL",
    "gn:name":"Namerinni",
    "gn:population":0,
    "gn:timezone":"Australia/Darwin",
    "iso:country":"AU",
    "wof:name":"Namerinni",
    "wof:placetype":"locality"
},
  "geometry": {"coordinates":[133.71548999999999,-18.56818],"type":"Point"}
}