{
  "type": "Feature",
  "properties": {
    "iso:country":"AU",
    "name:deu_x_preferred":[
        "Sorlie"
    ],
    "name:eng_x_preferred":[
        "Sorlie"
    ],
    "qs:gn_adm0_cc":"AU",
    "qs:gn_local":2147714,
    "qs:local_max":35533,
    "qs:local_sum":687549,
    "qs:localhoods":516,
    "qs:name":"Sorlie",
    "qs:name_adm0":"Australia",
    "qs:name_adm1":"New South Wales",
    "qs:name_adm2":"Warringah",
    "qs:name_local":"Sydney",
    "qs:photo_max":657,
    "qs:photo_sum":834,
    "qs:placetype":"Suburb",
    "qs:quad_count":14,
    "qs:woe_adm0":23424748,
    "qs:woe_adm1":2344700,
    "qs:woe_adm2":55864177,
    "qs:woe_lau":0,
    "qs:woe_local":1105779,
    "qs:woe_ver":"7.10.0",
    "wd:wordcount":74,
    "wof:lang":[
        "eng"
    ],
    "wof:name":"Sorlie",
    "wof:placetype":"neighbourhood"
},
  "geometry": {"coordinates":[151.20631700000001,-33.744637],"type":"Point"}
}