{
  "type": "Feature",
  "properties": {
    "iso:country":"AU",
    "name:eng_x_preferred":[
        "Clonbinane"
    ],
    "qs_pg:aaroncc":"AU",
    "qs_pg:name":"Clonbinane",
    "qs_pg:name_adm0":"Australia",
    "qs_pg:name_adm1":"Victoria",
    "qs_pg:photos":18,
    "qs_pg:photos_1k":4,
    "qs_pg:photos_9k":1,
    "qs_pg:photos_9r":1,
    "qs_pg:photos_all":18,
    "qs_pg:photos_sr":1,
    "qs_pg:pop_sr":0,
    "qs_pg:qs_pg_placetype":"locality",
    "qs_pg:qs_pg_placetype_gp":"Town",
    "qs_pg:woe_adm0":23424748,
    "woe:adm0_id":23424748,
    "woe:name_adm0":"Australia",
    "woe:name_adm1":"Victoria",
    "woe:placetype":"Town",
    "wof:name":"Clonbinane",
    "wof:placetype":"locality",
    "wof:population":330
},
  "geometry": {"coordinates":[145.06278900000001,-37.289533],"type":"Point"}
}