{
  "type": "Feature",
  "properties": {
    "gn:admin1_code":"5",
    "gn:admin2_code":"41190",
    "gn:asciiname":"Wharminda",
    "gn:country_code":"AU",
    "gn:dem":65,
    "gn:feature_class":"P",
    "gn:feature_code":"PPL",
    "gn:name":"Wharminda",
    "gn:population":0,
    "gn:timezone":"Australia/Adelaide",
    "iso:country":"AU",
    "wof:name":"Wharminda",
    "wof:placetype":"locality"
},
  "geometry": {"coordinates":[136.24576000000002,-33.95379000000001],"type":"Point"}
}