{
  "type": "Feature",
  "properties": {
    "iso:country":"AU",
    "name:fra_x_preferred":[
        "Mamu"
    ],
    "qs_pg:aaroncc":"AU",
    "qs_pg:name":"Mamu",
    "qs_pg:name_adm0":"Australia",
    "qs_pg:name_adm1":"Queensland",
    "qs_pg:photos":25,
    "qs_pg:photos_1k":5,
    "qs_pg:photos_9k":1,
    "qs_pg:photos_9r":1,
    "qs_pg:photos_all":25,
    "qs_pg:photos_sr":1,
    "qs_pg:pop_sr":0,
    "qs_pg:qs_pg_placetype":"locality",
    "qs_pg:qs_pg_placetype_gp":"Town",
    "qs_pg:woe_adm0":23424748,
    "woe:adm0_id":23424748,
    "woe:name_adm0":"Australia",
    "woe:name_adm1":"Queensland",
    "woe:placetype":"Town",
    "wof:name":"Mamu",
    "wof:placetype":"locality"
},
  "geometry": {"coordinates":[145.78956099999999,-17.612],"type":"Point"}
}