{
  "type": "Feature",
  "properties": {
    "gn:admin1_code":"8",
    "gn:admin2_code":"59660",
    "gn:asciiname":"Cheritons Find",
    "gn:country_code":"AU",
    "gn:dem":393,
    "gn:feature_class":"P",
    "gn:feature_code":"PPL",
    "gn:name":"Cheritons Find",
    "gn:population":0,
    "gn:timezone":"Australia/Perth",
    "iso:country":"AU",
    "wof:name":"Cheritons Find",
    "wof:placetype":"locality"
},
  "geometry": {"coordinates":[119.63333,-31.81667],"type":"Point"}
}