{
  "type": "Feature",
  "properties": {
    "iso:country":"AU",
    "name:ceb_x_preferred":[
        "Fairy Bower Beach"
    ],
    "name:eng_x_preferred":[
        "Manly East"
    ],
    "name:eng_x_variant":[
        "Manly East"
    ],
    "name:swe_x_preferred":[
        "Fairy Bower Beach"
    ],
    "qs:gn_adm0_cc":"AU",
    "qs:gn_local":2147714,
    "qs:local_max":35533,
    "qs:local_sum":687549,
    "qs:localhoods":516,
    "qs:name":"Manly East",
    "qs:name_adm0":"Australia",
    "qs:name_adm1":"New South Wales",
    "qs:name_adm2":"Manly Council",
    "qs:name_local":"Sydney",
    "qs:photo_max":799,
    "qs:photo_sum":5112,
    "qs:placetype":"Suburb",
    "qs:quad_count":91,
    "qs:woe_adm0":23424748,
    "qs:woe_adm1":2344700,
    "qs:woe_adm2":55864172,
    "qs:woe_lau":0,
    "qs:woe_local":1105779,
    "qs:woe_ver":"7.10.0",
    "wd:wordcount":128,
    "wof:lang":[
        "eng"
    ],
    "wof:name":"Fairy Bower",
    "wof:placetype":"neighbourhood"
},
  "geometry": {"coordinates":[151.304598,-33.797805],"type":"Point"}
}