{
  "type": "Feature",
  "properties": {
    "iso:country":"AU",
    "name:eng_x_preferred":[
        "Black Springs"
    ],
    "qs:gn_adm0_cc":"AU",
    "qs:gn_fcode":"PPL",
    "qs:gn_local":2158177,
    "qs:gn_namadm1":"07",
    "qs:gn_name":"Black Springs",
    "qs:local_max":22745,
    "qs:local_sum":338594,
    "qs:localhoods":407,
    "qs:name":"Black Springs",
    "qs:name_adm0":"Australia",
    "qs:name_adm1":"Victoria",
    "qs:name_adm2":"Yarra Ranges",
    "qs:name_local":"Melbourne",
    "qs:photo_max":70,
    "qs:photo_sum":110,
    "qs:placetype":"Suburb",
    "qs:quad_count":11,
    "qs:woe_adm0":23424748,
    "qs:woe_adm1":2344705,
    "qs:woe_adm2":55863960,
    "qs:woe_lau":0,
    "qs:woe_local":1103816,
    "qs:woe_ver":"7.10.0",
    "wof:lang":[
        "eng"
    ],
    "wof:name":"Black Springs",
    "wof:placetype":"neighbourhood"
},
  "geometry": {"coordinates":[145.31801424610788,-37.76014801219468],"type":"Point"}
}