{
  "type": "Feature",
  "properties": {
    "gn:gn_country":"AU",
    "gn:gn_fcode":"PPL",
    "gn:gn_pop":0,
    "iso:country":"AU",
    "name:eng_x_preferred":[
        "Clareville"
    ],
    "name:fas_x_preferred":[
        "\u06a9\u0644\u0631\u0648\u06cc\u0644"
    ],
    "name:fra_x_preferred":[
        "Clareville"
    ],
    "name:jpn_x_preferred":[
        "\u30af\u30ec\u30a2\u30f4\u30a3\u30eb"
    ],
    "name:por_x_preferred":[
        "Clareville"
    ],
    "name:ron_x_preferred":[
        "Clareville Beach"
    ],
    "name:ron_x_variant":[
        "Clareville"
    ],
    "name:unk_x_variant":[
        "Clareville"
    ],
    "qs:gn_adm0_cc":"AU",
    "qs:gn_fcode":"PPL",
    "qs:gn_local":2147714,
    "qs:gn_namadm1":"02",
    "qs:gn_name":"Clareville",
    "qs:local_max":35533,
    "qs:local_sum":687549,
    "qs:localhoods":516,
    "qs:name":"Clareville",
    "qs:name_adm0":"Australia",
    "qs:name_adm1":"New South Wales",
    "qs:name_adm2":"Pittwater",
    "qs:name_local":"Sydney",
    "qs:photo_max":24,
    "qs:photo_sum":49,
    "qs:placetype":"Suburb",
    "qs:quad_count":4,
    "qs:woe_adm0":23424748,
    "qs:woe_adm1":2344700,
    "qs:woe_adm2":55864176,
    "qs:woe_lau":0,
    "qs:woe_local":1105779,
    "qs:woe_ver":"7.10.0",
    "qs_pg:aaroncc":"AU",
    "qs_pg:gn_country":"AU",
    "qs_pg:gn_fcode":"PPL",
    "qs_pg:gn_pop":0,
    "qs_pg:name":"Clareville",
    "qs_pg:name_adm0":"Australia",
    "qs_pg:name_adm1":"New South Wales",
    "qs_pg:photos":103,
    "qs_pg:photos_1k":21,
    "qs_pg:photos_9k":1,
    "qs_pg:photos_9r":3,
    "qs_pg:photos_all":103,
    "qs_pg:photos_sr":3,
    "qs_pg:pop_sr":0,
    "qs_pg:qs_pg_placetype":"neighbourhood",
    "qs_pg:qs_pg_placetype_gp":"Suburb",
    "qs_pg:woe_adm0":23424748,
    "wof:lang":[
        "eng"
    ],
    "wof:name":"Clareville",
    "wof:placetype":"neighbourhood"
},
  "geometry": {"coordinates":[151.31469799999999,-33.628341],"type":"Point"}
}