{
  "type": "Feature",
  "properties": {
    "gn:admin1_code":"8",
    "gn:admin2_code":"59660",
    "gn:asciiname":"Corinthia",
    "gn:country_code":"AU",
    "gn:dem":403,
    "gn:feature_class":"P",
    "gn:feature_code":"PPL",
    "gn:name":"Corinthia",
    "gn:population":0,
    "gn:timezone":"Australia/Perth",
    "iso:country":"AU",
    "name:ara_x_preferred":[
        "\u0643\u0648\u0631\u064a\u0646\u062b\u064a\u0627"
    ],
    "name:bul_x_preferred":[
        "\u041a\u043e\u0440\u0438\u043d\u0442\u0438\u044f"
    ],
    "name:ceb_x_preferred":[
        "Nom\u00f3s Korinth\u00edas"
    ],
    "name:deu_x_preferred":[
        "Korinthia"
    ],
    "name:epo_x_preferred":[
        "Korintio"
    ],
    "name:est_x_preferred":[
        "Korinth\u00eda piirkonna\u00fcksus"
    ],
    "name:eus_x_preferred":[
        "Korintia"
    ],
    "name:fin_x_preferred":[
        "Korinthia"
    ],
    "name:fra_x_preferred":[
        "Corinthie"
    ],
    "name:heb_x_preferred":[
        "\u05e7\u05d5\u05e8\u05d9\u05e0\u05ea\u05d5\u05e1"
    ],
    "name:hrv_x_preferred":[
        "Prefektura Korint"
    ],
    "name:ita_x_preferred":[
        "Corinzia"
    ],
    "name:jpn_x_preferred":[
        "\u30b3\u30ea\u30f3\u30c6\u30a3\u30a2\u770c"
    ],
    "name:kat_x_preferred":[
        "\u10d9\u10dd\u10e0\u10d8\u10dc\u10d7\u10d8\u10d0"
    ],
    "name:kor_x_preferred":[
        "\ucf54\ub9b0\ud2f0\uc544\ud604"
    ],
    "name:lav_x_preferred":[
        "Korintija"
    ],
    "name:lit_x_preferred":[
        "Korintija"
    ],
    "name:nno_x_preferred":[
        "Korinth\u00eda"
    ],
    "name:nor_x_preferred":[
        "Korinthia"
    ],
    "name:por_x_preferred":[
        "Cor\u00edntia"
    ],
    "name:ron_x_preferred":[
        "Corintia"
    ],
    "name:spa_x_preferred":[
        "Corintia"
    ],
    "name:srp_x_preferred":[
        "\u041a\u043e\u0440\u0438\u043d\u0442\u0438\u0458\u0430"
    ],
    "name:swe_x_preferred":[
        "Korinth"
    ],
    "name:tur_x_preferred":[
        "Korint"
    ],
    "name:ukr_x_preferred":[
        "\u041a\u043e\u0440\u0438\u043d\u0444\u0456\u044f"
    ],
    "name:urd_x_preferred":[
        "\u06a9\u0648\u0631\u0646\u062a\u06be\u06cc\u0627"
    ],
    "name:war_x_preferred":[
        "Korinthia"
    ],
    "name:zho_x_preferred":[
        "\u79d1\u6797\u897f\u4e9e\u5dde"
    ],
    "wof:name":"Corinthia",
    "wof:placetype":"locality"
},
  "geometry": {"coordinates":[119.23399999999999,-31.11706],"type":"Point"}
}