{
  "type": "Feature",
  "properties": {
    "gn:admin1_code":"8",
    "gn:admin2_code":"59660",
    "gn:asciiname":"Corinthia",
    "gn:country_code":"AU",
    "gn:dem":403,
    "gn:feature_class":"P",
    "gn:feature_code":"PPL",
    "gn:name":"Corinthia",
    "gn:population":0,
    "gn:timezone":"Australia/Perth",
    "iso:country":"AU",
    "wof:name":"Corinthia",
    "wof:placetype":"locality"
},
  "geometry": {"coordinates":[119.23399999999999,-31.11706],"type":"Point"}
}