{
  "type": "Feature",
  "properties": {
    "gn:admin1_code":"2.0",
    "gn:admin2_code":"17900.0",
    "gn:asciiname":"Come-by-Chance",
    "gn:country_code":"AU",
    "gn:dem":143,
    "gn:feature_class":"P",
    "gn:feature_code":"PPL",
    "gn:name":"Come-by-Chance",
    "gn:population":0,
    "gn:timezone":"Australia/Sydney",
    "iso:country":"AU",
    "wof:name":"Come-by-Chance",
    "wof:placetype":"locality"
},
  "geometry": {"coordinates":[148.48737,-30.37257],"type":"Point"}
}