{
  "type": "Feature",
  "properties": {
    "gn:admin1_code":"5",
    "gn:admin2_code":"43710",
    "gn:asciiname":"Brimpton Lake",
    "gn:country_code":"AU",
    "gn:dem":49,
    "gn:feature_class":"P",
    "gn:feature_code":"PPL",
    "gn:name":"Brimpton Lake",
    "gn:population":0,
    "gn:timezone":"Australia/Adelaide",
    "iso:country":"AU",
    "wof:name":"Brimpton Lake",
    "wof:placetype":"locality"
},
  "geometry": {"coordinates":[135.51667,-34.06667],"type":"Point"}
}