{
  "type": "Feature",
  "properties": {
    "gn:admin1_code":"8",
    "gn:admin2_code":"52100",
    "gn:asciiname":"Nornakin",
    "gn:country_code":"AU",
    "gn:dem":323,
    "gn:feature_class":"P",
    "gn:feature_code":"PPL",
    "gn:name":"Nornakin",
    "gn:population":0,
    "gn:timezone":"Australia/Perth",
    "iso:country":"AU",
    "name:eng_x_preferred":[
        "Nornakin"
    ],
    "wof:name":"Nornakin",
    "wof:placetype":"locality"
},
  "geometry": {"coordinates":[117.90687,-32.24876],"type":"Point"}
}