{
  "type": "Feature",
  "properties": {
    "gn:country":"AU",
    "gn:fcode":"PPLX",
    "gn:population":0,
    "iso:country":"AU",
    "name:ceb_x_preferred":[
        "Royal Park"
    ],
    "name:eng_x_preferred":[
        "Royal Park"
    ],
    "name:swe_x_preferred":[
        "Royal Park"
    ],
    "qs_pg:aaroncc":"AU",
    "qs_pg:gn_country":"AU",
    "qs_pg:gn_fcode":"PPLX",
    "qs_pg:gn_pop":0,
    "qs_pg:name":"Royal Park",
    "qs_pg:name_adm0":"Australia",
    "qs_pg:name_adm1":"Tasmania",
    "qs_pg:photos_9r":0,
    "qs_pg:photos_sr":0,
    "qs_pg:pop_sr":0,
    "qs_pg:qs_pg_placetype":"neighbourhood",
    "qs_pg:qs_pg_placetype_gp":"Suburb",
    "qs_pg:woe_adm0":23424748,
    "woe:adm0_id":23424748,
    "woe:name_adm0":"Australia",
    "woe:name_adm1":"Tasmania",
    "woe:placetype":"Suburb",
    "wof:name":"Royal Park",
    "wof:placetype":"neighbourhood"
},
  "geometry": {"coordinates":[147.12916999999999,-41.43611],"type":"Point"}
}