{
  "type": "Feature",
  "properties": {
    "gn:admin1_code":"2.0",
    "gn:admin2_code":"18020.0",
    "gn:asciiname":"Liamena",
    "gn:country_code":"AU",
    "gn:dem":403,
    "gn:feature_class":"P",
    "gn:feature_code":"PPL",
    "gn:name":"Liamena",
    "gn:population":0,
    "gn:timezone":"Australia/Sydney",
    "iso:country":"AU",
    "name:eng_x_preferred":[
        "Liamena"
    ],
    "wof:name":"Liamena",
    "wof:placetype":"locality"
},
  "geometry": {"coordinates":[149.33514,-31.97193],"type":"Point"}
}