{
  "type": "Feature",
  "properties": {
    "gn:admin1_code":"2.0",
    "gn:admin2_code":"11050.0",
    "gn:asciiname":"Narrallen",
    "gn:country_code":"AU",
    "gn:dem":498,
    "gn:feature_class":"P",
    "gn:feature_code":"PPL",
    "gn:name":"Narrallen",
    "gn:population":0,
    "gn:timezone":"Australia/Sydney",
    "iso:country":"AU",
    "wof:name":"Narrallen",
    "wof:placetype":"locality"
},
  "geometry": {"coordinates":[148.66666999999995,-34.26667],"type":"Point"}
}