{
  "type": "Feature",
  "properties": {
    "gn:admin1_code":"2.0",
    "gn:admin2_code":"17640.0",
    "gn:asciiname":"Avoca",
    "gn:country_code":"AU",
    "gn:dem":702,
    "gn:feature_class":"P",
    "gn:feature_code":"PPL",
    "gn:name":"Avoca",
    "gn:population":199,
    "gn:timezone":"Australia/Sydney",
    "iso:country":"AU",
    "name:bar_x_preferred":[
        "Avoca"
    ],
    "name:cat_x_preferred":[
        "Avoca"
    ],
    "name:ceb_x_preferred":[
        "Avoca"
    ],
    "name:deu_x_preferred":[
        "Avoca"
    ],
    "name:eng_x_preferred":[
        "Avoca"
    ],
    "name:fra_x_preferred":[
        "Avoca"
    ],
    "name:ido_x_preferred":[
        "Avoca"
    ],
    "name:ita_x_preferred":[
        "Avoca"
    ],
    "name:kat_x_preferred":[
        "\u10d0\u10d5\u10dd\u10d9\u10d0"
    ],
    "name:kor_x_preferred":[
        "\uc5b4\ubcf4\uce74"
    ],
    "name:nld_x_preferred":[
        "Avoca"
    ],
    "name:pol_x_preferred":[
        "Avoca"
    ],
    "name:por_x_preferred":[
        "Avoca"
    ],
    "name:rus_x_preferred":[
        "\u0410\u0432\u043e\u043a\u0430"
    ],
    "name:slk_x_preferred":[
        "Avoca"
    ],
    "name:srp_x_preferred":[
        "\u0410\u0432\u043e\u043a\u0430"
    ],
    "name:swe_x_preferred":[
        "Avoca"
    ],
    "name:ukr_x_preferred":[
        "\u0410\u0432\u043e\u043a\u0430"
    ],
    "name:vol_x_preferred":[
        "Avoca"
    ],
    "wof:name":"Avoca",
    "wof:placetype":"locality",
    "wof:population":199
},
  "geometry": {"coordinates":[149.29175000000001,-34.59534],"type":"Point"}
}