{
  "type": "Feature",
  "properties": {
    "gn:admin1_code":"2.0",
    "gn:admin2_code":"17640.0",
    "gn:asciiname":"Avoca",
    "gn:country_code":"AU",
    "gn:dem":702,
    "gn:feature_class":"P",
    "gn:feature_code":"PPL",
    "gn:name":"Avoca",
    "gn:population":199,
    "gn:timezone":"Australia/Sydney",
    "iso:country":"AU",
    "name:eng_x_preferred":[
        "Avoca"
    ],
    "wof:name":"Avoca",
    "wof:placetype":"locality",
    "wof:population":199
},
  "geometry": {"coordinates":[149.29175000000001,-34.59534],"type":"Point"}
}