{
  "type": "Feature",
  "properties": {
    "gn:admin1_code":"2",
    "gn:admin2_code":"13400",
    "gn:asciiname":"Wang Wauk",
    "gn:country_code":"AU",
    "gn:dem":21,
    "gn:feature_class":"P",
    "gn:feature_code":"PPL",
    "gn:name":"Wang Wauk",
    "gn:population":0,
    "gn:timezone":"Australia/Sydney",
    "iso:country":"AU",
    "wof:name":"Wang Wauk",
    "wof:placetype":"locality"
},
  "geometry": {"coordinates":[152.33333000000005,-32.16667],"type":"Point"}
}