{
  "type": "Feature",
  "properties": {
    "iso:country":"AU",
    "name:ceb_x_preferred":[
        "Parkwood"
    ],
    "name:deu_x_preferred":[
        "Parkwood"
    ],
    "name:eng_x_preferred":[
        "Parkwood"
    ],
    "name:fra_x_preferred":[
        "Parkwood"
    ],
    "name:ita_x_preferred":[
        "Parkwood"
    ],
    "name:nld_x_preferred":[
        "Parkwood"
    ],
    "name:srp_x_preferred":[
        "\u041f\u0430\u0440\u043a\u0432\u0443\u0434"
    ],
    "name:unk_x_variant":[
        "Parkwood"
    ],
    "name:vol_x_preferred":[
        "Parkwood"
    ],
    "qs:gn_adm0_cc":"AU",
    "qs:gn_fcode":"PPLX",
    "qs:gn_local":2165087,
    "qs:gn_namadm1":"04",
    "qs:gn_name":"Parkwood",
    "qs:local_max":10372,
    "qs:local_sum":57138,
    "qs:localhoods":62,
    "qs:name":"Parkwood",
    "qs:name_adm0":"Australia",
    "qs:name_adm1":"Queensland",
    "qs:name_adm2":"Gold Coast City",
    "qs:name_local":"City of Gold Coast",
    "qs:photo_max":18,
    "qs:photo_sum":79,
    "qs:placetype":"Suburb",
    "qs:quad_count":10,
    "qs:woe_adm0":23424748,
    "qs:woe_adm1":2344702,
    "qs:woe_adm2":55864296,
    "qs:woe_lau":0,
    "qs:woe_local":7226269,
    "qs:woe_ver":"7.10.0",
    "wof:name":"Parkwood",
    "wof:placetype":"neighbourhood"
},
  "geometry": {"coordinates":[153.36516,-27.940643],"type":"Point"}
}