{
  "type": "Feature",
  "properties": {
    "gn:admin1_code":"4.0",
    "gn:admin2_code":"34800.0",
    "gn:asciiname":"Helen Downs",
    "gn:country_code":"AU",
    "gn:dem":177,
    "gn:feature_class":"P",
    "gn:feature_code":"PPL",
    "gn:name":"Helen Downs",
    "gn:population":0,
    "gn:timezone":"Australia/Brisbane",
    "iso:country":"AU",
    "name:eng_x_preferred":[
        "Helen Downs"
    ],
    "wof:name":"Helen Downs",
    "wof:placetype":"locality"
},
  "geometry": {"coordinates":[142.2201,-21.08372],"type":"Point"}
}