{
  "type": "Feature",
  "properties": {
    "gn:admin1_code":"4.0",
    "gn:admin2_code":"30760.0",
    "gn:asciiname":"Malvernton",
    "gn:country_code":"AU",
    "gn:dem":260,
    "gn:feature_class":"P",
    "gn:feature_code":"PPL",
    "gn:name":"Malvernton",
    "gn:population":0,
    "gn:timezone":"Australia/Brisbane",
    "iso:country":"AU",
    "name:eng_x_preferred":[
        "Malvernton"
    ],
    "wof:name":"Malvernton",
    "wof:placetype":"locality"
},
  "geometry": {"coordinates":[145.11989,-24.50635],"type":"Point"}
}