{
  "type": "Feature",
  "properties": {
    "gn:admin1_code":"2.0",
    "gn:admin2_code":"17400.0",
    "gn:asciiname":"Clifton",
    "gn:country_code":"AU",
    "gn:dem":694,
    "gn:feature_class":"P",
    "gn:feature_code":"PPL",
    "gn:name":"Clifton",
    "gn:population":0,
    "gn:timezone":"Australia/Sydney",
    "iso:country":"AU",
    "wof:name":"Clifton",
    "wof:placetype":"locality"
},
  "geometry": {"coordinates":[151.71666999999999,-29.03333],"type":"Point"}
}