{
  "type": "Feature",
  "properties": {
    "gn:admin1_code":"2.0",
    "gn:admin2_code":"17400.0",
    "gn:asciiname":"Clifton",
    "gn:country_code":"AU",
    "gn:dem":694,
    "gn:feature_class":"P",
    "gn:feature_code":"PPL",
    "gn:name":"Clifton",
    "gn:population":0,
    "gn:timezone":"Australia/Sydney",
    "iso:country":"AU",
    "name:cat_x_preferred":[
        "Clifton"
    ],
    "name:ceb_x_preferred":[
        "Clifton"
    ],
    "name:ces_x_preferred":[
        "Clifton"
    ],
    "name:deu_x_preferred":[
        "Clifton"
    ],
    "name:fas_x_preferred":[
        "\u06a9\u0644\u06cc\u0641\u062a\u0648\u0646"
    ],
    "name:fin_x_preferred":[
        "Clifton"
    ],
    "name:fra_x_preferred":[
        "Clifton"
    ],
    "name:hun_x_preferred":[
        "Clifton"
    ],
    "name:ita_x_preferred":[
        "Clifton"
    ],
    "name:jpn_x_preferred":[
        "\u30af\u30ea\u30d5\u30c8\u30f3"
    ],
    "name:kor_x_preferred":[
        "\ud074\ub9ac\ud504\ud134"
    ],
    "name:nld_x_preferred":[
        "Clifton"
    ],
    "name:pol_x_preferred":[
        "Clifton"
    ],
    "name:por_x_preferred":[
        "Clifton"
    ],
    "name:slk_x_preferred":[
        "Clifton"
    ],
    "name:spa_x_preferred":[
        "Clifton"
    ],
    "name:swe_x_preferred":[
        "Clifton"
    ],
    "name:ukr_x_preferred":[
        "\u041a\u043b\u0456\u0444\u0442\u043e\u043d"
    ],
    "name:vol_x_preferred":[
        "Clifton"
    ],
    "name:zho_x_preferred":[
        "\u514b\u5229\u592b\u9813"
    ],
    "wof:name":"Clifton",
    "wof:placetype":"locality"
},
  "geometry": {"coordinates":[151.71666999999999,-29.03333],"type":"Point"}
}