{
  "type": "Feature",
  "properties": {
    "gn:admin1_code":"5.0",
    "gn:admin2_code":"47800.0",
    "gn:asciiname":"Calgara",
    "gn:country_code":"AU",
    "gn:dem":17,
    "gn:feature_class":"P",
    "gn:feature_code":"PPL",
    "gn:name":"Calgara",
    "gn:population":0,
    "gn:timezone":"Australia/Adelaide",
    "iso:country":"AU",
    "name:eng_x_preferred":[
        "Calgara"
    ],
    "wof:name":"Calgara",
    "wof:placetype":"locality"
},
  "geometry": {"coordinates":[140.06113999999999,-35.96024],"type":"Point"}
}