{
  "type": "Feature",
  "properties": {
    "gn:admin1_code":"4.0",
    "gn:admin2_code":"34710.0",
    "gn:asciiname":"Jugiong",
    "gn:country_code":"AU",
    "gn:dem":248,
    "gn:feature_class":"P",
    "gn:feature_code":"PPL",
    "gn:name":"Jugiong",
    "gn:population":0,
    "gn:timezone":"Australia/Brisbane",
    "iso:country":"AU",
    "name:eng_x_preferred":[
        "Jugiong"
    ],
    "wof:name":"Jugiong",
    "wof:placetype":"locality"
},
  "geometry": {"coordinates":[143.37861999999996,-23.2514],"type":"Point"}
}