{
  "type": "Feature",
  "properties": {
    "gn:admin1_code":"2.0",
    "gn:admin2_code":"18020.0",
    "gn:asciiname":"Pine Ridge",
    "gn:country_code":"AU",
    "gn:dem":408,
    "gn:feature_class":"P",
    "gn:feature_code":"PPL",
    "gn:name":"Pine Ridge",
    "gn:population":0,
    "gn:timezone":"Australia/Sydney",
    "iso:country":"AU",
    "wof:name":"Pine Ridge",
    "wof:placetype":"locality"
},
  "geometry": {"coordinates":[149.53333000000001,-31.98333],"type":"Point"}
}