{
  "type": "Feature",
  "properties": {
    "gn:admin1_code":"2.0",
    "gn:admin2_code":"18020.0",
    "gn:asciiname":"Pine Ridge",
    "gn:country_code":"AU",
    "gn:dem":408,
    "gn:feature_class":"P",
    "gn:feature_code":"PPL",
    "gn:name":"Pine Ridge",
    "gn:population":0,
    "gn:timezone":"Australia/Sydney",
    "iso:country":"AU",
    "name:cat_x_preferred":[
        "Pine Ridge"
    ],
    "name:ceb_x_preferred":[
        "Pine Ridge"
    ],
    "name:deu_x_preferred":[
        "Pine Ridge"
    ],
    "name:fin_x_preferred":[
        "Pine Ridge"
    ],
    "name:fra_x_preferred":[
        "Pine Ridge"
    ],
    "name:ind_x_preferred":[
        "Pine Ridge"
    ],
    "name:ita_x_preferred":[
        "Pine Ridge"
    ],
    "name:nld_x_preferred":[
        "Pine Ridge"
    ],
    "name:pol_x_preferred":[
        "Pine Ridge"
    ],
    "name:por_x_preferred":[
        "Pine Ridge"
    ],
    "name:rus_x_preferred":[
        "\u041f\u0430\u0439\u043d-\u0420\u0438\u0434\u0436"
    ],
    "name:srp_x_preferred":[
        "\u041f\u0430\u0458\u043d \u0420\u0438\u045f"
    ],
    "name:swe_x_preferred":[
        "Pine Ridge"
    ],
    "name:tur_x_preferred":[
        "Pine Ridge"
    ],
    "name:vol_x_preferred":[
        "Pine Ridge"
    ],
    "wof:name":"Pine Ridge",
    "wof:placetype":"locality"
},
  "geometry": {"coordinates":[149.53333000000001,-31.98333],"type":"Point"}
}