{
  "type": "Feature",
  "properties": {
    "iso:country":"AU",
    "name:ara_x_preferred":[
        "\u0643\u0631\u064a\u0633\u062a\u0627\u0644 \u0648\u0648\u062a\u0631\u0632"
    ],
    "name:azb_x_preferred":[
        "\u06a9\u0631\u06cc\u0633\u062a\u0627\u0644 \u0648\u0627\u062a\u0631\u0632"
    ],
    "name:dan_x_preferred":[
        "Crystal Waters"
    ],
    "name:deu_x_preferred":[
        "Crystal Waters"
    ],
    "name:eng_x_preferred":[
        "Crystal Waters"
    ],
    "name:fas_x_preferred":[
        "\u06a9\u0631\u06cc\u0633\u062a\u0627\u0644 \u0648\u0627\u062a\u0631\u0632"
    ],
    "name:fra_x_preferred":[
        "Crystal Waters"
    ],
    "name:hun_x_preferred":[
        "Crystal Waters"
    ],
    "name:ita_x_preferred":[
        "Crystal Waters"
    ],
    "name:nld_x_preferred":[
        "Crystal Waters"
    ],
    "name:pol_x_preferred":[
        "Crystal Waters"
    ],
    "name:por_x_preferred":[
        "Crystal Waters"
    ],
    "name:rus_x_preferred":[
        "\u041a\u0440\u0438\u0441\u0442\u0430\u043b \u0423\u043e\u0442\u0435\u0440\u0441"
    ],
    "name:slk_x_preferred":[
        "Crystal Waters"
    ],
    "name:spa_x_preferred":[
        "Crystal Waters"
    ],
    "name:swe_x_preferred":[
        "Crystal Waters"
    ],
    "name:tur_x_preferred":[
        "Crystal Waters"
    ],
    "qs_pg:aaroncc":"AU",
    "qs_pg:name":"Crystal Waters",
    "qs_pg:name_adm0":"Australia",
    "qs_pg:name_adm1":"Queensland",
    "qs_pg:photos":456,
    "qs_pg:photos_1k":92,
    "qs_pg:photos_9k":2,
    "qs_pg:photos_9r":5,
    "qs_pg:photos_all":456,
    "qs_pg:photos_sr":7,
    "qs_pg:pop_sr":0,
    "qs_pg:qs_pg_placetype":"locality",
    "qs_pg:qs_pg_placetype_gp":"Town",
    "qs_pg:woe_adm0":23424748,
    "woe:adm0_id":23424748,
    "woe:name_adm0":"Australia",
    "woe:name_adm1":"Queensland",
    "woe:placetype":"Town",
    "wof:name":"Crystal Waters",
    "wof:placetype":"locality"
},
  "geometry": {"coordinates":[152.70951600000001,-26.7859325],"type":"Point"}
}