{
  "type": "Feature",
  "properties": {
    "gn:admin1_code":"2.0",
    "gn:admin2_code":"11350.0",
    "gn:asciiname":"Durrumbul",
    "gn:country_code":"AU",
    "gn:dem":187,
    "gn:feature_class":"P",
    "gn:feature_code":"PPL",
    "gn:name":"Durrumbul",
    "gn:population":0,
    "gn:timezone":"Australia/Sydney",
    "iso:country":"AU",
    "name:und_x_variant":[
        "Durrumbull",
        "Durrumbul"
    ],
    "wof:name":"Durrumbul",
    "wof:placetype":"locality"
},
  "geometry": {"coordinates":[153.44588000000005,-28.51848],"type":"Point"}
}