{
  "type": "Feature",
  "properties": {
    "gn:admin1_code":"5.0",
    "gn:admin2_code":"45540.0",
    "gn:asciiname":"Old Whydown",
    "gn:country_code":"AU",
    "gn:dem":368,
    "gn:feature_class":"P",
    "gn:feature_code":"PPL",
    "gn:name":"Old Whydown",
    "gn:population":0,
    "gn:timezone":"Australia/Adelaide",
    "iso:country":"AU",
    "name:eng_x_preferred":[
        "Old Whydown"
    ],
    "wof:name":"Old Whydown",
    "wof:placetype":"locality"
},
  "geometry": {"coordinates":[139.26155,-32.70597],"type":"Point"}
}