{
  "type": "Feature",
  "properties": {
    "gn:admin1_code":"2.0",
    "gn:admin2_code":"17640.0",
    "gn:asciiname":"Rosedale",
    "gn:country_code":"AU",
    "gn:dem":807,
    "gn:feature_class":"P",
    "gn:feature_code":"PPL",
    "gn:name":"Rosedale",
    "gn:population":0,
    "gn:timezone":"Australia/Sydney",
    "iso:country":"AU",
    "name:ceb_x_preferred":[
        "Rosedale"
    ],
    "name:deu_x_preferred":[
        "Rosedale"
    ],
    "name:eng_x_preferred":[
        "Rosedale"
    ],
    "name:fra_x_preferred":[
        "Rosedale"
    ],
    "name:ita_x_preferred":[
        "Rosedale"
    ],
    "name:kor_x_preferred":[
        "\ub85c\uc988\ub370\uc77c"
    ],
    "name:nld_x_preferred":[
        "Rosedale"
    ],
    "name:pol_x_preferred":[
        "Rosedale"
    ],
    "name:por_x_preferred":[
        "Rosedale"
    ],
    "name:spa_x_preferred":[
        "Rosedale"
    ],
    "name:srp_x_preferred":[
        "\u0420\u043e\u0443\u0437\u0434\u0435\u0458\u043b"
    ],
    "name:swe_x_preferred":[
        "Rosedale"
    ],
    "name:vol_x_preferred":[
        "Rosedale"
    ],
    "wof:name":"Rosedale",
    "wof:placetype":"locality"
},
  "geometry": {"coordinates":[149.41648000000001,-34.18680999999999],"type":"Point"}
}