{
  "type": "Feature",
  "properties": {
    "gn:admin1_code":"4.0",
    "gn:admin2_code":"35760.0",
    "gn:asciiname":"Chowey",
    "gn:country_code":"AU",
    "gn:dem":154,
    "gn:feature_class":"P",
    "gn:feature_code":"PPL",
    "gn:name":"Chowey",
    "gn:population":0,
    "gn:timezone":"Australia/Brisbane",
    "iso:country":"AU",
    "wof:name":"Chowey",
    "wof:placetype":"locality"
},
  "geometry": {"coordinates":[151.93333000000001,-25.46667],"type":"Point"}
}