{
  "type": "Feature",
  "properties": {
    "gn:admin1_code":"4.0",
    "gn:admin2_code":"32310.0",
    "gn:asciiname":"Mundic Creek",
    "gn:country_code":"AU",
    "gn:dem":378,
    "gn:feature_class":"P",
    "gn:feature_code":"PPL",
    "gn:name":"Mundic Creek",
    "gn:population":0,
    "gn:timezone":"Australia/Brisbane",
    "iso:country":"AU",
    "name:eng_x_preferred":[
        "Mundic Creek"
    ],
    "wof:name":"Mundic Creek",
    "wof:placetype":"locality"
},
  "geometry": {"coordinates":[145.54939999999999,-20.42951],"type":"Point"}
}