{
  "type": "Feature",
  "properties": {
    "gn:admin1_code":"3.0",
    "gn:admin2_code":"70620.0",
    "gn:asciiname":"Wayillinypa",
    "gn:country_code":"AU",
    "gn:dem":607,
    "gn:feature_class":"P",
    "gn:feature_code":"PPL",
    "gn:name":"Wayillinypa",
    "gn:population":0,
    "gn:timezone":"Australia/Darwin",
    "iso:country":"AU",
    "wof:name":"Wayillinypa",
    "wof:placetype":"locality"
},
  "geometry": {"coordinates":[131.44851,-22.50628],"type":"Point"}
}