{
  "type": "Feature",
  "properties": {
    "gn:admin1_code":"2.0",
    "gn:admin2_code":"11400.0",
    "gn:asciiname":"Avenel",
    "gn:country_code":"AU",
    "gn:dem":568,
    "gn:feature_class":"P",
    "gn:feature_code":"PPL",
    "gn:name":"Avenel",
    "gn:population":0,
    "gn:timezone":"Australia/Sydney",
    "iso:country":"AU",
    "name:ceb_x_preferred":[
        "Avenel"
    ],
    "name:fra_x_preferred":[
        "Avenel"
    ],
    "name:ita_x_preferred":[
        "Avenel"
    ],
    "name:pol_x_preferred":[
        "Avenel"
    ],
    "name:rus_x_preferred":[
        "\u0410\u0432\u0435\u043d\u0435\u043b\u044c"
    ],
    "name:swe_x_preferred":[
        "Avenel"
    ],
    "wof:name":"Avenel",
    "wof:placetype":"locality"
},
  "geometry": {"coordinates":[148.76667,-33.41667],"type":"Point"}
}