{
  "type": "Feature",
  "properties": {
    "iso:country":"AU",
    "name:eng_x_preferred":[
        "Edwardstown"
    ],
    "name:fra_x_preferred":[
        "Edwardstown"
    ],
    "name:jpn_x_preferred":[
        "\u30a8\u30c9\u30ef\u30fc\u30ba\u30bf\u30a6\u30f3"
    ],
    "qs:gn_adm0_cc":"AU",
    "qs:gn_fcode":"PPLX",
    "qs:gn_local":2078025,
    "qs:gn_namadm1":"05",
    "qs:gn_name":"Edwardstown",
    "qs:local_max":18505,
    "qs:local_sum":99726,
    "qs:localhoods":191,
    "qs:name":"Edwardstown",
    "qs:name_adm0":"Australia",
    "qs:name_adm1":"South Australia",
    "qs:name_adm2":"City of Mitcham",
    "qs:name_local":"Adelaide",
    "qs:photo_max":23,
    "qs:photo_sum":57,
    "qs:placetype":"Suburb",
    "qs:quad_count":9,
    "qs:woe_adm0":23424748,
    "qs:woe_adm1":2344703,
    "qs:woe_adm2":55864116,
    "qs:woe_lau":0,
    "qs:woe_local":1099805,
    "qs:woe_ver":"7.10.0",
    "wof:lang":[
        "eng"
    ],
    "wof:name":"Edwardstown",
    "wof:placetype":"neighbourhood"
},
  "geometry": {"coordinates":[138.579047,-34.978143],"type":"Point"}
}