{
  "type": "Feature",
  "properties": {
    "iso:country":"AU",
    "name:ceb_x_preferred":[
        "Camooweal Airport"
    ],
    "name:eng_x_preferred":[
        "Camooweal Airport"
    ],
    "name:msa_x_preferred":[
        "Lapangan Terbang Camooweal"
    ],
    "name:ron_x_preferred":[
        "Aeroportul Camooweal"
    ],
    "name:swe_x_preferred":[
        "Camooweal Airport"
    ],
    "name:zho_x_preferred":[
        "\u5361\u7a46\u5a01\u723e\u6a5f\u5834"
    ],
    "oa:elevation_ft":"241",
    "oa:type":"small_airport",
    "wd:wordcount":178,
    "woe:hierarchy":{
        "country_id":23424748,
        "county_id":55863896,
        "planet_id":1,
        "state_id":2344702
    },
    "wof:name":"Camooweal Aerodrome",
    "wof:placetype":"campus"
},
  "geometry": {"coordinates":[138.125,-19.9117],"type":"Point"}
}