{
  "type": "Feature",
  "properties": {
    "gn:admin1_code":"3",
    "gn:asciiname":"Town of Brocks Creek",
    "gn:country_code":"AU",
    "gn:dem":106,
    "gn:feature_class":"P",
    "gn:feature_code":"PPL",
    "gn:name":"Town of Brocks Creek",
    "gn:population":0,
    "gn:timezone":"Australia/Darwin",
    "iso:country":"AU",
    "wof:name":"Town of Brocks Creek",
    "wof:placetype":"locality"
},
  "geometry": {"coordinates":[131.41828999999998,-13.46705],"type":"Point"}
}