{
  "type": "Feature",
  "properties": {
    "iso:country":"AU",
    "name:eng_x_preferred":[
        "Tumbling Waters"
    ],
    "name:nld_x_preferred":[
        "Tumbling Waters"
    ],
    "qs_pg:aaroncc":"AU",
    "qs_pg:name":"Tumbling Waters",
    "qs_pg:name_adm0":"Australia",
    "qs_pg:name_adm1":"Northern Territory",
    "qs_pg:photos":40,
    "qs_pg:photos_1k":8,
    "qs_pg:photos_9k":1,
    "qs_pg:photos_9r":2,
    "qs_pg:photos_all":40,
    "qs_pg:photos_sr":2,
    "qs_pg:pop_sr":0,
    "qs_pg:qs_pg_placetype":"locality",
    "qs_pg:qs_pg_placetype_gp":"Town",
    "qs_pg:woe_adm0":23424748,
    "woe:adm0_id":23424748,
    "woe:name_adm0":"Australia",
    "woe:name_adm1":"Northern Territory",
    "woe:placetype":"Town",
    "wof:name":"Tumbling Waters",
    "wof:placetype":"locality"
},
  "geometry": {"coordinates":[130.94735299999999,-12.771039],"type":"Point"}
}