{
  "type": "Feature",
  "properties": {
    "gn:admin1_code":"4.0",
    "gn:admin2_code":"36910.0",
    "gn:asciiname":"Neuve",
    "gn:country_code":"AU",
    "gn:dem":590,
    "gn:feature_class":"P",
    "gn:feature_code":"PPL",
    "gn:name":"Neuve",
    "gn:population":0,
    "gn:timezone":"Australia/Brisbane",
    "iso:country":"AU",
    "wof:name":"Neuve",
    "wof:placetype":"locality"
},
  "geometry": {"coordinates":[151.88333,-27.26667],"type":"Point"}
}