{
  "type": "Feature",
  "properties": {
    "gn:admin1_code":"8",
    "gn:admin2_code":"57350",
    "gn:asciiname":"Yoting",
    "gn:country_code":"AU",
    "gn:dem":288,
    "gn:feature_class":"P",
    "gn:feature_code":"PPL",
    "gn:name":"Yoting",
    "gn:population":0,
    "gn:timezone":"Australia/Perth",
    "iso:country":"AU",
    "name:eng_x_preferred":[
        "Yoting"
    ],
    "wof:name":"Yoting",
    "wof:placetype":"locality"
},
  "geometry": {"coordinates":[117.59142,-31.96017],"type":"Point"}
}