{
  "type": "Feature",
  "properties": {
    "iso:country":"AU",
    "qs_pg:aaroncc":"AU",
    "qs_pg:name":"Fisher",
    "qs_pg:name_adm0":"Australia",
    "qs_pg:name_adm1":"South Australia",
    "qs_pg:photos":20,
    "qs_pg:photos_1k":4,
    "qs_pg:photos_9k":1,
    "qs_pg:photos_9r":1,
    "qs_pg:photos_all":20,
    "qs_pg:photos_sr":1,
    "qs_pg:pop_sr":0,
    "qs_pg:qs_pg_placetype":"locality",
    "qs_pg:qs_pg_placetype_gp":"Town",
    "qs_pg:woe_adm0":23424748,
    "woe:adm0_id":23424748,
    "woe:name_adm0":"Australia",
    "woe:name_adm1":"South Australia",
    "woe:placetype":"Town",
    "wof:name":"Fisher",
    "wof:placetype":"locality"
},
  "geometry": {"coordinates":[139.58245099999999,-34.488504],"type":"Point"}
}