{
  "type": "Feature",
  "properties": {
    "gn:admin1_code":"4.0",
    "gn:admin2_code":"36070.0",
    "gn:asciiname":"Tobys Yard",
    "gn:country_code":"AU",
    "gn:dem":45,
    "gn:feature_class":"P",
    "gn:feature_code":"PPL",
    "gn:name":"Tobys Yard",
    "gn:population":0,
    "gn:timezone":"Australia/Brisbane",
    "iso:country":"AU",
    "wof:name":"Tobys Yard",
    "wof:placetype":"locality"
},
  "geometry": {"coordinates":[141.96969999999999,-14.51731],"type":"Point"}
}