{
  "type": "Feature",
  "properties": {
    "gn:admin1_code":"7",
    "gn:admin2_code":"26700",
    "gn:asciiname":"Whorouly South",
    "gn:country_code":"AU",
    "gn:dem":203,
    "gn:feature_class":"P",
    "gn:feature_code":"PPL",
    "gn:name":"Whorouly South",
    "gn:population":0,
    "gn:timezone":"Australia/Melbourne",
    "iso:country":"AU",
    "wof:name":"Whorouly South",
    "wof:placetype":"locality"
},
  "geometry": {"coordinates":[146.58333000000005,-36.55],"type":"Point"}
}