{
  "type": "Feature",
  "properties": {
    "gn:admin1_code":"4.0",
    "gn:admin2_code":"32500.0",
    "gn:asciiname":"Bullock Paddock Yards",
    "gn:country_code":"AU",
    "gn:dem":11,
    "gn:feature_class":"P",
    "gn:feature_code":"PPL",
    "gn:name":"Bullock Paddock Yards",
    "gn:population":0,
    "gn:timezone":"Australia/Brisbane",
    "iso:country":"AU",
    "wof:name":"Bullock Paddock Yards",
    "wof:placetype":"locality"
},
  "geometry": {"coordinates":[144.19776999999999,-14.56832],"type":"Point"}
}