{
  "type": "Feature",
  "properties": {
    "iso:country":"AU",
    "name:eng_x_preferred":[
        "Werai"
    ],
    "name:fra_x_preferred":[
        "Werai"
    ],
    "name:nld_x_preferred":[
        "Werai"
    ],
    "qs_pg:aaroncc":"AU",
    "qs_pg:name":"Werai",
    "qs_pg:name_adm0":"Australia",
    "qs_pg:name_adm1":"New South Wales",
    "qs_pg:photos":160,
    "qs_pg:photos_1k":32,
    "qs_pg:photos_9k":1,
    "qs_pg:photos_9r":4,
    "qs_pg:photos_all":160,
    "qs_pg:photos_sr":4,
    "qs_pg:pop_sr":0,
    "qs_pg:qs_pg_placetype":"locality",
    "qs_pg:qs_pg_placetype_gp":"Town",
    "qs_pg:woe_adm0":23424748,
    "woe:adm0_id":23424748,
    "woe:name_adm0":"Australia",
    "woe:name_adm1":"New South Wales",
    "woe:placetype":"Town",
    "wof:name":"Werai",
    "wof:placetype":"locality",
    "wof:population":90
},
  "geometry": {"coordinates":[150.344853,-34.590929],"type":"Point"}
}