{
  "type": "Feature",
  "properties": {
    "gn:country":"AU",
    "gn:fcode":"PPL",
    "gn:population":0,
    "iso:country":"AU",
    "name:ara_x_preferred":[
        "\u062c\u0628\u0644 \u0623\u0648\u0633\u0627"
    ],
    "name:ben_x_preferred":[
        "\u09ae\u09be\u0989\u09a8\u09cd\u099f \u0993\u09b8\u09be"
    ],
    "name:ceb_x_preferred":[
        "Mount Ossa"
    ],
    "name:ell_x_preferred":[
        "\u038c\u03c1\u03bf\u03c2 \u038c\u03c3\u03c3\u03b1"
    ],
    "name:fas_x_preferred":[
        "\u06a9\u0648\u0647 \u0627\u064f\u0633\u0627"
    ],
    "name:heb_x_preferred":[
        "\u05d4\u05e8 \u05e4\u05d0\u05d2'\u05d8"
    ],
    "name:hin_x_preferred":[
        "\u0913\u0938\u093e \u092a\u0930\u094d\u0935\u0924"
    ],
    "name:hun_x_preferred":[
        "Mount Ossa"
    ],
    "name:ind_x_preferred":[
        "Gunung Ossa"
    ],
    "name:kor_x_preferred":[
        "\ub9c8\uc6b4\ud2b8 \uc624\uc0ac"
    ],
    "name:swe_x_preferred":[
        "Mount Ossa"
    ],
    "name:tur_x_preferred":[
        "Ossa Da\u011f\u0131"
    ],
    "name:urd_x_preferred":[
        "\u0645\u0627\u0624\u0646\u0679 \u0627\u0648\u0633\u0627"
    ],
    "name:vie_x_preferred":[
        "N\u00fai Ossa"
    ],
    "name:zho_cn_x_preferred":[
        "\u5965\u8428\u5c71"
    ],
    "name:zho_tw_x_preferred":[
        "\u5967\u85a9\u5c71"
    ],
    "qs_pg:aaroncc":"AU",
    "qs_pg:gn_country":"AU",
    "qs_pg:gn_fcode":"PPL",
    "qs_pg:gn_pop":0,
    "qs_pg:name":"Mount Ossa",
    "qs_pg:name_adm0":"Australia",
    "qs_pg:name_adm1":"Queensland",
    "qs_pg:photos":13,
    "qs_pg:photos_1k":3,
    "qs_pg:photos_9k":1,
    "qs_pg:photos_9r":1,
    "qs_pg:photos_all":13,
    "qs_pg:photos_sr":1,
    "qs_pg:pop_sr":4,
    "qs_pg:qs_pg_placetype":"locality",
    "qs_pg:qs_pg_placetype_gp":"Town",
    "qs_pg:woe_adm0":23424748,
    "woe:adm0_id":23424748,
    "woe:name_adm0":"Australia",
    "woe:name_adm1":"Queensland",
    "woe:placetype":"Town",
    "wof:name":"Mount Ossa",
    "wof:placetype":"locality"
},
  "geometry": {"coordinates":[148.83332999999999,-20.96667],"type":"Point"}
}