{
  "type": "Feature",
  "properties": {
    "gn:admin1_code":"2.0",
    "gn:admin2_code":"12350.0",
    "gn:asciiname":"Padua",
    "gn:country_code":"AU",
    "gn:dem":508,
    "gn:feature_class":"P",
    "gn:feature_code":"PPL",
    "gn:name":"Padua",
    "gn:population":0,
    "gn:timezone":"Australia/Sydney",
    "iso:country":"AU",
    "name:eng_x_preferred":[
        "Padua"
    ],
    "wof:name":"Padua",
    "wof:placetype":"locality"
},
  "geometry": {"coordinates":[148.91813999999999,-33.84424],"type":"Point"}
}