{
  "type": "Feature",
  "properties": {
    "gn:gn_country":"AU",
    "gn:gn_fcode":"PPL",
    "gn:gn_pop":813,
    "gn:population":813,
    "iso:country":"AU",
    "name:eng_x_preferred":[
        "Lue"
    ],
    "name:fra_x_preferred":[
        "Lue"
    ],
    "name:nld_x_preferred":[
        "Lue"
    ],
    "name:swe_x_preferred":[
        "Lue"
    ],
    "qs_pg:aaroncc":"AU",
    "qs_pg:gn_country":"AU",
    "qs_pg:gn_fcode":"PPL",
    "qs_pg:gn_pop":813,
    "qs_pg:name":"Lue",
    "qs_pg:name_adm0":"Australia",
    "qs_pg:name_adm1":"New South Wales",
    "qs_pg:photos":75,
    "qs_pg:photos_1k":15,
    "qs_pg:photos_9k":1,
    "qs_pg:photos_9r":2,
    "qs_pg:photos_all":75,
    "qs_pg:photos_sr":2,
    "qs_pg:pop_sr":2,
    "qs_pg:qs_pg_placetype":"locality",
    "qs_pg:qs_pg_placetype_gp":"Town",
    "qs_pg:woe_adm0":23424748,
    "woe:adm0_id":23424748,
    "woe:name_adm0":"Australia",
    "woe:name_adm1":"New South Wales",
    "woe:placetype":"Town",
    "wof:name":"Lue",
    "wof:placetype":"locality",
    "wof:population":813
},
  "geometry": {"coordinates":[149.84999999999999,-32.66667],"type":"Point"}
}