{
  "type": "Feature",
  "properties": {
    "gn:admin1_code":"5.0",
    "gn:admin2_code":"41750.0",
    "gn:asciiname":"Fox Hill",
    "gn:country_code":"AU",
    "gn:dem":138,
    "gn:feature_class":"P",
    "gn:feature_code":"PPL",
    "gn:name":"Fox Hill",
    "gn:population":0,
    "gn:timezone":"Australia/Adelaide",
    "iso:country":"AU",
    "name:ceb_x_preferred":[
        "Fox Hill"
    ],
    "name:deu_x_preferred":[
        "Fox Hill"
    ],
    "name:eng_x_preferred":[
        "Fox Hill"
    ],
    "wof:name":"Fox Hill",
    "wof:placetype":"locality"
},
  "geometry": {"coordinates":[135.70862,-33.59639],"type":"Point"}
}