{
  "type": "Feature",
  "properties": {
    "gn:admin1_code":"02",
    "gn:admin2_code":"11600.0",
    "gn:asciiname":"Kooroongal",
    "gn:country_code":"AU",
    "gn:dem":113,
    "gn:feature_class":"P",
    "gn:feature_code":"PPL",
    "gn:name":"Kooroongal",
    "gn:population":0,
    "gn:timezone":"Australia/Sydney",
    "iso:country":"AU",
    "name:und_x_variant":[
        "Village of Kooroongal"
    ],
    "wof:name":"Kooroongal",
    "wof:placetype":"locality"
},
  "geometry": {"coordinates":[145.70226,-34.46639],"type":"Point"}
}