{
  "type": "Feature",
  "properties": {
    "iso:country":"AU",
    "name:eng_x_preferred":[
        "Ulladulla"
    ],
    "wof:coterminous":[
        1376953295
    ],
    "wof:lang_x_official":[
        "eng"
    ],
    "wof:lang_x_spoken":[
        "eng"
    ],
    "wof:name":"Ulladulla",
    "wof:placetype":"locality"
},
  "geometry": {"coordinates":[150.46159499999999,-35.35646],"type":"Point"}
}