{
  "type": "Feature",
  "properties": {
    "gn:country":"AU",
    "gn:fcode":"PPL",
    "gn:population":365,
    "iso:country":"AU",
    "name:ast_x_preferred":[
        "Rhynie"
    ],
    "name:ceb_x_preferred":[
        "Rhynie"
    ],
    "name:deu_x_preferred":[
        "Rhynie"
    ],
    "name:eng_x_preferred":[
        "Rhynie"
    ],
    "name:fas_x_preferred":[
        "\u0631\u0627\u06cc\u0646\u06cc"
    ],
    "name:fra_x_preferred":[
        "Rhynie"
    ],
    "name:nld_x_preferred":[
        "Rhynie"
    ],
    "name:swe_x_preferred":[
        "Rhynie"
    ],
    "qs_pg:aaroncc":"AU",
    "qs_pg:gn_country":"AU",
    "qs_pg:gn_fcode":"PPL",
    "qs_pg:gn_pop":365,
    "qs_pg:name":"Rhynie",
    "qs_pg:name_adm0":"Australia",
    "qs_pg:name_adm1":"South Australia",
    "qs_pg:photos_9k":1,
    "qs_pg:photos_9r":1,
    "qs_pg:photos_all":4,
    "qs_pg:photos_sr":0,
    "qs_pg:pop_sr":2,
    "qs_pg:qs_pg_placetype":"locality",
    "qs_pg:qs_pg_placetype_gp":"Town",
    "qs_pg:woe_adm0":23424748,
    "woe:adm0_id":23424748,
    "woe:name_adm0":"Australia",
    "woe:name_adm1":"South Australia",
    "woe:placetype":"Town",
    "wof:name":"Rhynie",
    "wof:placetype":"locality",
    "wof:population":365
},
  "geometry": {"coordinates":[138.69999999999999,-34.13333],"type":"Point"}
}