{
  "type": "Feature",
  "properties": {
    "gn:admin1_code":"2.0",
    "gn:admin2_code":"17620.0",
    "gn:asciiname":"Malumia",
    "gn:country_code":"AU",
    "gn:dem":479,
    "gn:feature_class":"P",
    "gn:feature_code":"PPL",
    "gn:name":"Malumia",
    "gn:population":0,
    "gn:timezone":"Australia/Sydney",
    "iso:country":"AU",
    "name:eng_x_preferred":[
        "Malumia"
    ],
    "wof:name":"Malumia",
    "wof:placetype":"locality"
},
  "geometry": {"coordinates":[151.23949999999999,-32.11009],"type":"Point"}
}