{
  "type": "Feature",
  "properties": {
    "gn:admin1_code":"8.0",
    "gn:admin2_code":"51960.0",
    "gn:asciiname":"Stewart",
    "gn:country_code":"AU",
    "gn:dem":433,
    "gn:feature_class":"P",
    "gn:feature_code":"PPL",
    "gn:name":"Stewart",
    "gn:population":0,
    "gn:timezone":"Australia/Perth",
    "iso:country":"AU",
    "name:eng_x_preferred":[
        "Stewart"
    ],
    "wof:name":"Stewart",
    "wof:placetype":"locality"
},
  "geometry": {"coordinates":[120.81672,-30.91601],"type":"Point"}
}