{
  "type": "Feature",
  "properties": {
    "iso:country":"AU",
    "name:eng_x_preferred":[
        "Brockman"
    ],
    "name:fra_x_preferred":[
        "Brockman"
    ],
    "name:rus_x_preferred":[
        "\u0411\u0440\u043e\u043a\u043c\u0435\u043d"
    ],
    "qs:gn_adm0_cc":"AU",
    "qs:gn_fcode":"PPLX",
    "qs:gn_local":2074865,
    "qs:gn_namadm1":"08",
    "qs:gn_name":"Brockman",
    "qs:local_max":104,
    "qs:local_sum":163,
    "qs:localhoods":4,
    "qs:name":"Brockman",
    "qs:name_adm0":"Australia",
    "qs:name_adm1":"Western Australia",
    "qs:name_adm2":"Carnarvon",
    "qs:name_local":"Carnarvon",
    "qs:photo_max":36,
    "qs:photo_sum":104,
    "qs:placetype":"Suburb",
    "qs:quad_count":16,
    "qs:woe_adm0":23424748,
    "qs:woe_adm1":2344706,
    "qs:woe_adm2":55864377,
    "qs:woe_lau":0,
    "qs:woe_local":1101039,
    "qs:woe_ver":"7.10.0",
    "wof:name":"Brockman",
    "wof:placetype":"neighbourhood"
},
  "geometry": {"coordinates":[113.658348,-24.885365],"type":"Point"}
}