{
  "type": "Feature",
  "properties": {
    "iso:country":"AU",
    "name:ceb_x_preferred":[
        "Queenstown Airport"
    ],
    "name:eng_x_preferred":[
        "Queenstown Airport"
    ],
    "name:eng_x_variant":[
        "UEE",
        "YQNS"
    ],
    "name:msa_x_preferred":[
        "Lapangan Terbang Queenstown"
    ],
    "name:ron_x_preferred":[
        "Aeroportul Queenstown"
    ],
    "oa:elevation_ft":"867",
    "oa:type":"small_airport",
    "woe:hierarchy":{
        "country_id":23424748,
        "county_id":55864277,
        "planet_id":1,
        "state_id":2344704
    },
    "wof:name":"Queenstown Aerodrome",
    "wof:placetype":"campus"
},
  "geometry": {"coordinates":[145.53200000000001,-42.075],"type":"Point"}
}