{
  "type": "Feature",
  "properties": {
    "gn:admin1_code":"5.0",
    "gn:admin2_code":"47910.0",
    "gn:asciiname":"Braeville",
    "gn:country_code":"AU",
    "gn:dem":106,
    "gn:feature_class":"P",
    "gn:feature_code":"PPL",
    "gn:name":"Braeville",
    "gn:population":0,
    "gn:timezone":"Australia/Adelaide",
    "iso:country":"AU",
    "name:eng_x_preferred":[
        "Braeville"
    ],
    "wof:name":"Braeville",
    "wof:placetype":"locality"
},
  "geometry": {"coordinates":[135.88829999999999,-33.94515],"type":"Point"}
}