{
  "type": "Feature",
  "properties": {
    "gn:admin1_code":"4.0",
    "gn:admin2_code":"34800.0",
    "gn:asciiname":"Taltal",
    "gn:country_code":"AU",
    "gn:dem":218,
    "gn:feature_class":"P",
    "gn:feature_code":"PPL",
    "gn:name":"Taltal",
    "gn:population":0,
    "gn:timezone":"Australia/Brisbane",
    "iso:country":"AU",
    "name:ara_x_preferred":[
        "\u062a\u0627\u0644\u062a\u0627\u0644"
    ],
    "name:ben_x_preferred":[
        "\u09a4\u09be\u09b2\u09be\u09a4\u09b2"
    ],
    "name:ceb_x_preferred":[
        "Taltal"
    ],
    "name:deu_x_preferred":[
        "Taltal"
    ],
    "name:ell_x_preferred":[
        "\u03a4\u03b1\u03bb\u03c4\u03ac\u03bb"
    ],
    "name:eng_x_preferred":[
        "Taltal"
    ],
    "name:eus_x_preferred":[
        "Taltal"
    ],
    "name:fas_x_preferred":[
        "\u062a\u0627\u0644 \u062a\u0627\u0644"
    ],
    "name:fra_x_preferred":[
        "Taltal"
    ],
    "name:heb_x_preferred":[
        "\u05d8\u05dc\u05d8\u05dc"
    ],
    "name:hin_x_preferred":[
        "\u091f\u093e\u0932\u094d\u091f\u0932"
    ],
    "name:hun_x_preferred":[
        "Taltal"
    ],
    "name:ind_x_preferred":[
        "Taltal"
    ],
    "name:ita_x_preferred":[
        "Taltal"
    ],
    "name:kor_x_preferred":[
        "\ud0c8\ud0c8"
    ],
    "name:nld_x_preferred":[
        "Taltal"
    ],
    "name:por_x_preferred":[
        "Taltal"
    ],
    "name:ron_x_preferred":[
        "Taltal"
    ],
    "name:rus_x_preferred":[
        "\u0422\u0430\u043b\u044c\u0442\u0430\u043b\u044c"
    ],
    "name:spa_x_preferred":[
        "Taltal"
    ],
    "name:tur_x_preferred":[
        "Taltal"
    ],
    "name:ukr_x_preferred":[
        "\u0422\u0430\u043b\u044c\u0442\u0430\u043b\u044c"
    ],
    "name:urd_x_preferred":[
        "\u0679\u0627\u0644\u0679\u0627\u0644"
    ],
    "name:vie_x_preferred":[
        "Taltal"
    ],
    "name:zho_x_preferred":[
        "\u5854\u723e\u5854\u723e"
    ],
    "wof:name":"Taltal",
    "wof:placetype":"locality"
},
  "geometry": {"coordinates":[140.99077,-21.37299],"type":"Point"}
}