{
  "type": "Feature",
  "properties": {
    "gn:admin1_code":"4.0",
    "gn:admin2_code":"34800.0",
    "gn:asciiname":"Taltal",
    "gn:country_code":"AU",
    "gn:dem":218,
    "gn:feature_class":"P",
    "gn:feature_code":"PPL",
    "gn:name":"Taltal",
    "gn:population":0,
    "gn:timezone":"Australia/Brisbane",
    "iso:country":"AU",
    "name:eng_x_preferred":[
        "Taltal"
    ],
    "wof:name":"Taltal",
    "wof:placetype":"locality"
},
  "geometry": {"coordinates":[140.99077,-21.37299],"type":"Point"}
}