{
  "type": "Feature",
  "properties": {
    "gn:admin1_code":"3.0",
    "gn:admin2_code":"73600.0",
    "gn:asciiname":"North Hill",
    "gn:country_code":"AU",
    "gn:dem":69,
    "gn:feature_class":"P",
    "gn:feature_code":"PPL",
    "gn:name":"North Hill",
    "gn:population":0,
    "gn:timezone":"Australia/Darwin",
    "iso:country":"AU",
    "name:ceb_x_preferred":[
        "North Hill"
    ],
    "name:pol_x_preferred":[
        "North Hill"
    ],
    "wof:name":"North Hill",
    "wof:placetype":"locality"
},
  "geometry": {"coordinates":[136.86836,-15.55558],"type":"Point"}
}