{
  "type": "Feature",
  "properties": {
    "gn:admin1_code":"3.0",
    "gn:admin2_code":"73600.0",
    "gn:asciiname":"North Hill",
    "gn:country_code":"AU",
    "gn:dem":69,
    "gn:feature_class":"P",
    "gn:feature_code":"PPL",
    "gn:name":"North Hill",
    "gn:population":0,
    "gn:timezone":"Australia/Darwin",
    "iso:country":"AU",
    "name:ara_x_preferred":[
        "\u0627\u0644\u062a\u0644 \u0627\u0644\u0634\u0645\u0627\u0644\u064a"
    ],
    "name:ben_x_preferred":[
        "\u09a8\u09b0\u09cd\u09a5 \u09b9\u09bf\u09b2"
    ],
    "name:ceb_x_preferred":[
        "North Hill"
    ],
    "name:deu_x_preferred":[
        "North Hill"
    ],
    "name:ell_x_preferred":[
        "\u039d\u03bf\u03c1\u03b8 \u03a7\u03b9\u03bb"
    ],
    "name:eng_x_preferred":[
        "North Hill"
    ],
    "name:fas_x_preferred":[
        "\u0646\u0648\u0631\u062a \u0647\u06cc\u0644"
    ],
    "name:fra_x_preferred":[
        "North Hill"
    ],
    "name:heb_x_preferred":[
        "\u05d4\u05d2\u05d1\u05e2\u05d4 \u05d4\u05e6\u05e4\u05d5\u05e0\u05d9\u05ea"
    ],
    "name:hin_x_preferred":[
        "\u0909\u0924\u094d\u0924\u0930\u0940 \u092a\u0939\u093e\u0921\u093c\u0940"
    ],
    "name:hun_x_preferred":[
        "North Hill"
    ],
    "name:ind_x_preferred":[
        "North Hill"
    ],
    "name:ita_x_preferred":[
        "North Hill"
    ],
    "name:jpn_x_preferred":[
        "\u30ce\u30fc\u30b9\u30fb\u30d2\u30eb"
    ],
    "name:kor_x_preferred":[
        "\ub178\uc2a4 \ud790"
    ],
    "name:nld_x_preferred":[
        "North Hill"
    ],
    "name:pol_x_preferred":[
        "North Hill"
    ],
    "name:por_x_preferred":[
        "North Hill"
    ],
    "name:rus_x_preferred":[
        "\u041d\u043e\u0440\u0442-\u0425\u0438\u043b\u043b"
    ],
    "name:spa_x_preferred":[
        "North Hill"
    ],
    "name:swe_x_preferred":[
        "North Hill"
    ],
    "name:tur_x_preferred":[
        "North Hill"
    ],
    "name:ukr_x_preferred":[
        "\u041d\u043e\u0440\u0442-\u0425\u0456\u043b\u043b"
    ],
    "name:urd_x_preferred":[
        "\u0646\u0627\u0631\u062a\u06be \u06c1\u0644"
    ],
    "name:vie_x_preferred":[
        "North Hill"
    ],
    "name:zho_cn_x_preferred":[
        "\u5317\u5c71"
    ],
    "name:zho_tw_x_preferred":[
        "\u5317\u4e18"
    ],
    "wof:name":"North Hill",
    "wof:placetype":"locality"
},
  "geometry": {"coordinates":[136.86836,-15.55558],"type":"Point"}
}