{
  "type": "Feature",
  "properties": {
    "iso:country":"AU",
    "wof:name":"Bedforddale",
    "wof:placetype":"neighbourhood"
},
  "geometry": {"coordinates":[116.06447997449845,-32.17749279970784],"type":"Point"}
}