{
  "type": "Feature",
  "properties": {
    "gn:admin1_code":"7.0",
    "gn:admin2_code":"24850.0",
    "gn:asciiname":"Emu Flat",
    "gn:country_code":"AU",
    "gn:dem":461,
    "gn:feature_class":"P",
    "gn:feature_code":"PPL",
    "gn:name":"Emu Flat",
    "gn:population":0,
    "gn:timezone":"Australia/Melbourne",
    "iso:country":"AU",
    "wof:name":"Emu Flat",
    "wof:placetype":"locality"
},
  "geometry": {"coordinates":[144.76667,-37.11667],"type":"Point"}
}