{
  "type": "Feature",
  "properties": {
    "gn:admin1_code":"3.0",
    "gn:admin2_code":"74050.0",
    "gn:asciiname":"Melville Island",
    "gn:country_code":"AU",
    "gn:dem":36,
    "gn:feature_class":"P",
    "gn:feature_code":"PPL",
    "gn:name":"Melville Island",
    "gn:population":0,
    "gn:timezone":"Australia/Darwin",
    "iso:country":"AU",
    "name:ben_x_preferred":[
        "\u09ae\u09c7\u09b2\u09ad\u09bf\u09b2 \u0986\u0987\u09b2\u09cd\u09af\u09be\u09a8\u09cd\u09a1"
    ],
    "name:ceb_x_preferred":[
        "Melville Island"
    ],
    "name:deu_x_preferred":[
        "Melville Island"
    ],
    "name:hin_x_preferred":[
        "\u092e\u0947\u0932\u0935\u093f\u0932 \u0926\u094d\u0935\u0940\u092a"
    ],
    "name:ind_x_preferred":[
        "Pulau Melville"
    ],
    "name:swe_x_preferred":[
        "Melville Island"
    ],
    "wof:name":"Melville Island",
    "wof:placetype":"locality"
},
  "geometry": {"coordinates":[131.12457000000001,-11.5796],"type":"Point"}
}