{
  "type": "Feature",
  "properties": {
    "gn:admin1_code":"3.0",
    "gn:admin2_code":"74050.0",
    "gn:asciiname":"Melville Island",
    "gn:country_code":"AU",
    "gn:dem":36,
    "gn:feature_class":"P",
    "gn:feature_code":"PPL",
    "gn:name":"Melville Island",
    "gn:population":0,
    "gn:timezone":"Australia/Darwin",
    "iso:country":"AU",
    "name:ceb_x_preferred":[
        "Melville Island"
    ],
    "name:deu_x_preferred":[
        "Melville Island"
    ],
    "name:swe_x_preferred":[
        "Melville Island"
    ],
    "wof:name":"Melville Island",
    "wof:placetype":"locality"
},
  "geometry": {"coordinates":[131.12457000000001,-11.5796],"type":"Point"}
}