{
  "type": "Feature",
  "properties": {
    "gn:admin1_code":"4.0",
    "gn:admin2_code":"37310.0",
    "gn:asciiname":"Apunyal",
    "gn:country_code":"AU",
    "gn:dem":330,
    "gn:feature_class":"P",
    "gn:feature_code":"PPL",
    "gn:name":"Apunyal",
    "gn:population":0,
    "gn:timezone":"Australia/Brisbane",
    "iso:country":"AU",
    "name:eng_x_preferred":[
        "Apunyal"
    ],
    "wof:name":"Apunyal",
    "wof:placetype":"locality"
},
  "geometry": {"coordinates":[151.11000000000001,-27.07246],"type":"Point"}
}