{
  "type": "Feature",
  "properties": {
    "gn:admin1_code":"4",
    "gn:admin2_code":"36630",
    "gn:asciiname":"Wengenville",
    "gn:country_code":"AU",
    "gn:dem":512,
    "gn:feature_class":"P",
    "gn:feature_code":"PPL",
    "gn:name":"Wengenville",
    "gn:population":0,
    "gn:timezone":"Australia/Brisbane",
    "iso:country":"AU",
    "wof:name":"Wengenville",
    "wof:placetype":"locality"
},
  "geometry": {"coordinates":[151.69999999999999,-26.83333],"type":"Point"}
}