{
  "type": "Feature",
  "properties": {
    "gn:admin1_code":"8",
    "gn:admin2_code":"51080",
    "gn:asciiname":"Carlecatup",
    "gn:country_code":"AU",
    "gn:dem":301,
    "gn:feature_class":"P",
    "gn:feature_code":"PPL",
    "gn:name":"Carlecatup",
    "gn:population":0,
    "gn:timezone":"Australia/Perth",
    "iso:country":"AU",
    "wof:name":"Carlecatup",
    "wof:placetype":"locality"
},
  "geometry": {"coordinates":[117.33333,-33.83333],"type":"Point"}
}