{
  "type": "Feature",
  "properties": {
    "gn:admin1_code":"7.0",
    "gn:admin2_code":"20830.0",
    "gn:asciiname":"Parkers Corner",
    "gn:country_code":"AU",
    "gn:dem":470,
    "gn:feature_class":"P",
    "gn:feature_code":"PPL",
    "gn:name":"Parkers Corner",
    "gn:population":0,
    "gn:timezone":"Australia/Melbourne",
    "iso:country":"AU",
    "name:eng_x_preferred":[
        "Parkers Corner"
    ],
    "name:fin_x_preferred":[
        "Parkers Corner"
    ],
    "name:nld_x_preferred":[
        "Parkers Corner"
    ],
    "wof:name":"Parkers Corner",
    "wof:placetype":"locality"
},
  "geometry": {"coordinates":[146.39251999999999,-37.94813],"type":"Point"}
}