{
  "type": "Feature",
  "properties": {
    "gn:country":"AU",
    "gn:fcode":"PPL",
    "gn:population":0,
    "iso:country":"AU",
    "name:arz_x_preferred":[
        "\u0645\u0627\u0631\u0649 \u0643\u0627\u062b\u0644\u064a\u0646"
    ],
    "name:deu_x_preferred":[
        "Mary Kathleen"
    ],
    "name:eng_x_preferred":[
        "Mary Kathleen"
    ],
    "name:fra_x_preferred":[
        "Mary Kathleen"
    ],
    "name:nld_x_preferred":[
        "Mary Kathleen"
    ],
    "name:zho_x_preferred":[
        "\u746a\u9e97\u00b7\u51f1\u85a9\u7433"
    ],
    "qs_pg:aaroncc":"AU",
    "qs_pg:gn_country":"AU",
    "qs_pg:gn_fcode":"PPL",
    "qs_pg:gn_pop":0,
    "qs_pg:name":"Mary Kathleen",
    "qs_pg:name_adm0":"Australia",
    "qs_pg:name_adm1":"Queensland",
    "qs_pg:photos":15,
    "qs_pg:photos_1k":3,
    "qs_pg:photos_9k":1,
    "qs_pg:photos_9r":1,
    "qs_pg:photos_all":15,
    "qs_pg:photos_sr":1,
    "qs_pg:pop_sr":4,
    "qs_pg:qs_pg_placetype":"locality",
    "qs_pg:qs_pg_placetype_gp":"Town",
    "qs_pg:woe_adm0":23424748,
    "woe:adm0_id":23424748,
    "woe:name_adm0":"Australia",
    "woe:name_adm1":"Queensland",
    "woe:placetype":"Town",
    "wof:name":"Mary Kathleen",
    "wof:placetype":"locality"
},
  "geometry": {"coordinates":[139.94591,-20.75515],"type":"Point"}
}