{
  "type": "Feature",
  "properties": {
    "gn:admin1_code":"4.0",
    "gn:admin2_code":"36810.0",
    "gn:asciiname":"Lancelot",
    "gn:country_code":"AU",
    "gn:dem":765,
    "gn:feature_class":"P",
    "gn:feature_code":"PPL",
    "gn:name":"Lancelot",
    "gn:population":0,
    "gn:timezone":"Australia/Brisbane",
    "iso:country":"AU",
    "name:ara_x_preferred":[
        "\u0644\u0627\u0646\u0633\u0644\u0648\u062a"
    ],
    "name:bel_x_preferred":[
        "\u041b\u0430\u043d\u0441\u044d\u043b\u043e\u0442"
    ],
    "name:bre_x_preferred":[
        "Lanselod"
    ],
    "name:bul_x_preferred":[
        "\u041b\u0430\u043d\u0441\u0435\u043b\u043e\u0442"
    ],
    "name:cat_x_preferred":[
        "Lancelot"
    ],
    "name:ces_x_preferred":[
        "Lancelot"
    ],
    "name:cym_x_preferred":[
        "Lawnslot"
    ],
    "name:dan_x_preferred":[
        "Lancelot"
    ],
    "name:deu_x_preferred":[
        "Lancelot"
    ],
    "name:ell_x_preferred":[
        "\u039b\u03ac\u03bd\u03c3\u03b5\u03bb\u03bf\u03c4"
    ],
    "name:epo_x_preferred":[
        "Lanceloto"
    ],
    "name:eus_x_preferred":[
        "Lantzelot Aintzirakoa"
    ],
    "name:fas_x_preferred":[
        "\u0644\u0627\u0646\u0633\u0644\u0648\u062a"
    ],
    "name:fin_x_preferred":[
        "Lancelot"
    ],
    "name:glg_x_preferred":[
        "Lancelot"
    ],
    "name:hrv_x_preferred":[
        "Lancelot"
    ],
    "name:ind_x_preferred":[
        "Lancelot"
    ],
    "name:ita_x_preferred":[
        "Lancillotto"
    ],
    "name:jpn_x_preferred":[
        "\u30e9\u30f3\u30b9\u30ed\u30c3\u30c8"
    ],
    "name:kat_x_preferred":[
        "\u10da\u10d0\u10dc\u10e1\u10d4\u10da\u10dd\u10e2\u10d8"
    ],
    "name:kor_x_preferred":[
        "\ub780\uc2ac\ub86f"
    ],
    "name:msa_x_preferred":[
        "Lancelot"
    ],
    "name:nld_x_preferred":[
        "Lancelot"
    ],
    "name:nor_x_preferred":[
        "Lancelot"
    ],
    "name:por_x_preferred":[
        "Lancelote"
    ],
    "name:ron_x_preferred":[
        "Lancelot"
    ],
    "name:rus_x_preferred":[
        "\u041b\u0430\u043d\u0441\u0435\u043b\u043e\u0442"
    ],
    "name:swe_x_preferred":[
        "Lancelot"
    ],
    "name:tgl_x_preferred":[
        "Lancelot"
    ],
    "name:tha_x_preferred":[
        "\u0e25\u0e32\u0e19\u0e40\u0e0b\u0e25\u0e2d\u0e15"
    ],
    "name:tur_x_preferred":[
        "Lancelot"
    ],
    "name:ukr_x_preferred":[
        "\u041b\u0430\u043d\u0441\u0435\u043b\u043e\u0442"
    ],
    "name:vie_x_preferred":[
        "Lancelot"
    ],
    "name:zho_x_preferred":[
        "\u5170\u65af\u6d1b\u7279"
    ],
    "wof:name":"Lancelot",
    "wof:placetype":"locality"
},
  "geometry": {"coordinates":[145.26667,-17.46667],"type":"Point"}
}