{
  "type": "Feature",
  "properties": {
    "gn:admin1_code":"4.0",
    "gn:admin2_code":"36810.0",
    "gn:asciiname":"Lancelot",
    "gn:country_code":"AU",
    "gn:dem":765,
    "gn:feature_class":"P",
    "gn:feature_code":"PPL",
    "gn:name":"Lancelot",
    "gn:population":0,
    "gn:timezone":"Australia/Brisbane",
    "iso:country":"AU",
    "wof:name":"Lancelot",
    "wof:placetype":"locality"
},
  "geometry": {"coordinates":[145.26667,-17.46667],"type":"Point"}
}