{
  "type": "Feature",
  "properties": {
    "gn:admin1_code":"2.0",
    "gn:admin2_code":"12050.0",
    "gn:asciiname":"Bobingah",
    "gn:country_code":"AU",
    "gn:dem":1090,
    "gn:feature_class":"P",
    "gn:feature_code":"PPL",
    "gn:name":"Bobingah",
    "gn:population":0,
    "gn:timezone":"Australia/Sydney",
    "iso:country":"AU",
    "name:eng_x_preferred":[
        "Bobingah"
    ],
    "wof:name":"Bobingah",
    "wof:placetype":"locality"
},
  "geometry": {"coordinates":[149.23585,-36.4647],"type":"Point"}
}