{
  "type": "Feature",
  "properties": {
    "iso:country":"AU",
    "name:ceb_x_preferred":[
        "Chapel Hill"
    ],
    "name:deu_x_preferred":[
        "Chapel Hill"
    ],
    "name:fra_x_preferred":[
        "Chapel Hill"
    ],
    "name:ita_x_preferred":[
        "Chapel Hill"
    ],
    "name:jpn_x_preferred":[
        "\u30c1\u30e3\u30da\u30eb\u30d2\u30eb"
    ],
    "name:kor_x_preferred":[
        "\ucc44\ud50c\ud790"
    ],
    "name:nld_x_preferred":[
        "Chapel Hill"
    ],
    "name:pol_x_preferred":[
        "Chapel Hill"
    ],
    "name:por_x_preferred":[
        "Chapel Hill"
    ],
    "name:srp_x_preferred":[
        "\u0427\u0430\u043f\u0435\u043b \u0425\u0438\u043b"
    ],
    "name:swe_x_preferred":[
        "Chapel Hill"
    ],
    "name:ukr_x_preferred":[
        "\u0427\u0430\u043f\u0435\u043b-\u0413\u0456\u043b\u043b"
    ],
    "name:vol_x_preferred":[
        "Chapel Hill"
    ],
    "name:wuu_x_preferred":[
        "\u6559\u5802\u5c71"
    ],
    "name:zho_x_preferred":[
        "\u6559\u5802\u5c71"
    ],
    "qs_pg:aaroncc":"AU",
    "qs_pg:name":"Chapel Hill",
    "qs_pg:name_adm0":"Australia",
    "qs_pg:name_adm1":"South Australia",
    "qs_pg:photos":23,
    "qs_pg:photos_1k":5,
    "qs_pg:photos_9k":1,
    "qs_pg:photos_9r":1,
    "qs_pg:photos_all":23,
    "qs_pg:photos_sr":1,
    "qs_pg:pop_sr":0,
    "qs_pg:qs_pg_placetype":"locality",
    "qs_pg:qs_pg_placetype_gp":"Town",
    "qs_pg:woe_adm0":23424748,
    "woe:adm0_id":23424748,
    "woe:name_adm0":"Australia",
    "woe:name_adm1":"South Australia",
    "woe:placetype":"Town",
    "wof:name":"Chapel Hill",
    "wof:placetype":"locality"
},
  "geometry": {"coordinates":[138.75558599999999,-35.104198],"type":"Point"}
}