{
  "type": "Feature",
  "properties": {
    "gn:admin1_code":"7",
    "gn:admin2_code":"21010",
    "gn:asciiname":"Toombullup",
    "gn:country_code":"AU",
    "gn:dem":865,
    "gn:feature_class":"P",
    "gn:feature_code":"PPL",
    "gn:name":"Toombullup",
    "gn:population":0,
    "gn:timezone":"Australia/Melbourne",
    "iso:country":"AU",
    "wof:name":"Toombullup",
    "wof:placetype":"locality"
},
  "geometry": {"coordinates":[146.21666999999999,-36.86667],"type":"Point"}
}