{
  "type": "Feature",
  "properties": {
    "gn:admin1_code":"5.0",
    "gn:admin2_code":"43220.0",
    "gn:asciiname":"Netherby",
    "gn:country_code":"AU",
    "gn:dem":292,
    "gn:feature_class":"P",
    "gn:feature_code":"PPL",
    "gn:name":"Netherby",
    "gn:population":0,
    "gn:timezone":"Australia/Adelaide",
    "iso:country":"AU",
    "name:deu_x_preferred":[
        "Netherby"
    ],
    "name:eng_x_preferred":[
        "Netherby"
    ],
    "name:pol_x_preferred":[
        "Netherby"
    ],
    "wof:name":"Netherby",
    "wof:placetype":"locality"
},
  "geometry": {"coordinates":[136.56618,-33.2294],"type":"Point"}
}