{
  "type": "Feature",
  "properties": {
    "gn:admin1_code":"8.0",
    "gn:admin2_code":"53920.0",
    "gn:asciiname":"New Ord River",
    "gn:country_code":"AU",
    "gn:dem":175,
    "gn:feature_class":"P",
    "gn:feature_code":"PPL",
    "gn:name":"New Ord River",
    "gn:population":0,
    "gn:timezone":"Australia/Perth",
    "iso:country":"AU",
    "wof:name":"New Ord River",
    "wof:placetype":"locality"
},
  "geometry": {"coordinates":[128.92074,-17.38567],"type":"Point"}
}