{
  "type": "Feature",
  "properties": {
    "iso:country":"AU",
    "name:cat_x_preferred":[
        "Hayes"
    ],
    "name:ceb_x_preferred":[
        "Hayes"
    ],
    "name:ces_x_preferred":[
        "Hayes"
    ],
    "name:deu_x_preferred":[
        "Hayes"
    ],
    "name:fin_x_preferred":[
        "Hayes"
    ],
    "name:fra_x_preferred":[
        "Hayes"
    ],
    "name:heb_x_preferred":[
        "\u05d4\u05d9\u05d9\u05d6"
    ],
    "name:hin_x_preferred":[
        "\u0939\u0947\u091c\u093c"
    ],
    "name:ita_x_preferred":[
        "Hayes"
    ],
    "name:jpn_x_preferred":[
        "HAYES"
    ],
    "name:nld_x_preferred":[
        "Hayes"
    ],
    "name:oci_x_preferred":[
        "Hayes"
    ],
    "name:pol_x_preferred":[
        "Hayes"
    ],
    "name:por_x_preferred":[
        "Hayes"
    ],
    "name:rus_x_preferred":[
        "\u0425\u0435\u0439\u0437"
    ],
    "name:spa_x_preferred":[
        "Hayes"
    ],
    "name:swe_x_preferred":[
        "Hayes"
    ],
    "name:ukr_x_preferred":[
        "\u0413\u0435\u0439\u0437"
    ],
    "name:zho_x_preferred":[
        "\u6d77\u8036\u65af"
    ],
    "qs_pg:aaroncc":"AU",
    "qs_pg:name":"Hayes",
    "qs_pg:name_adm0":"Australia",
    "qs_pg:name_adm1":"Tasmania",
    "qs_pg:photos":24,
    "qs_pg:photos_1k":5,
    "qs_pg:photos_9k":1,
    "qs_pg:photos_9r":1,
    "qs_pg:photos_all":24,
    "qs_pg:photos_sr":1,
    "qs_pg:pop_sr":0,
    "qs_pg:qs_pg_placetype":"locality",
    "qs_pg:qs_pg_placetype_gp":"Town",
    "qs_pg:woe_adm0":23424748,
    "woe:adm0_id":23424748,
    "woe:name_adm0":"Australia",
    "woe:name_adm1":"Tasmania",
    "woe:placetype":"Town",
    "wof:name":"Hayes",
    "wof:placetype":"locality"
},
  "geometry": {"coordinates":[146.9901175,-42.7551355],"type":"Point"}
}