{
  "type": "Feature",
  "properties": {
    "gn:gn_country":"AU",
    "gn:gn_fcode":"PPL",
    "gn:gn_pop":835,
    "gn:population":835,
    "iso:country":"AU",
    "name:eng_x_preferred":[
        "Royalla"
    ],
    "name:fra_x_preferred":[
        "Royalla"
    ],
    "name:jpn_x_preferred":[
        "\u30ed\u30e4\u30e9"
    ],
    "name:nld_x_preferred":[
        "Royalla"
    ],
    "name:swe_x_preferred":[
        "Royalla"
    ],
    "qs_pg:aaroncc":"AU",
    "qs_pg:gn_country":"AU",
    "qs_pg:gn_fcode":"PPL",
    "qs_pg:gn_pop":835,
    "qs_pg:name":"Royalla",
    "qs_pg:photos_9r":0,
    "qs_pg:photos_sr":0,
    "qs_pg:pop_sr":2,
    "qs_pg:qs_pg_placetype":"locality",
    "wof:name":"Royalla",
    "wof:placetype":"locality",
    "wof:population":835
},
  "geometry": {"coordinates":[149.15000000000001,-35.51667],"type":"Point"}
}