{
  "type": "Feature",
  "properties": {
    "gn:population":19637,
    "iso:country":"AU",
    "name:ceb_x_preferred":[
        "Camberwell"
    ],
    "name:eng_x_preferred":[
        "Camberwell West"
    ],
    "name:fra_x_preferred":[
        "Camberwell"
    ],
    "name:nor_x_preferred":[
        "Camberwell"
    ],
    "name:swe_x_preferred":[
        "Camberwell"
    ],
    "name:unk_x_variant":[
        "Camberwell",
        "Camberwell West"
    ],
    "qs:gn_adm0_cc":"AU",
    "qs:gn_fcode":"PPL",
    "qs:gn_local":2158177,
    "qs:gn_namadm1":"07",
    "qs:gn_name":"Camberwell",
    "qs:local_max":22745,
    "qs:local_sum":338594,
    "qs:localhoods":407,
    "qs:name":"Camberwell West",
    "qs:name_adm0":"Australia",
    "qs:name_adm1":"Victoria",
    "qs:name_adm2":"Boroondara",
    "qs:name_local":"Melbourne",
    "qs:photo_max":56,
    "qs:photo_sum":131,
    "qs:placetype":"Suburb",
    "qs:quad_count":11,
    "qs:woe_adm0":23424748,
    "qs:woe_adm1":2344705,
    "qs:woe_adm2":55864010,
    "qs:woe_lau":0,
    "qs:woe_local":1103816,
    "qs:woe_ver":"7.10.0",
    "wof:lang":[
        "eng"
    ],
    "wof:name":"Camberwell West",
    "wof:placetype":"neighbourhood",
    "wof:population":19637
},
  "geometry": {"coordinates":[145.07818599999999,-37.833396],"type":"Point"}
}