{
  "type": "Feature",
  "properties": {
    "gn:admin1_code":"8",
    "gn:admin2_code":"59030",
    "gn:asciiname":"Warralakin",
    "gn:country_code":"AU",
    "gn:dem":316,
    "gn:feature_class":"P",
    "gn:feature_code":"PPL",
    "gn:name":"Warralakin",
    "gn:population":0,
    "gn:timezone":"Australia/Perth",
    "iso:country":"AU",
    "name:und_x_variant":[
        "Warralackin",
        "Warralakin"
    ],
    "wof:name":"Warralakin",
    "wof:placetype":"locality"
},
  "geometry": {"coordinates":[118.60511,-31.01672],"type":"Point"}
}