{
  "type": "Feature",
  "properties": {
    "iso:country":"AU",
    "name:eng_x_preferred":[
        "Lismore Central"
    ],
    "name:unk_x_variant":[
        "Lismore Central"
    ],
    "qs:gn_adm0_cc":"AU",
    "qs:gn_local":2160063,
    "qs:gn_nam_loc":"Lismore, Lismore, New South Wales, AU",
    "qs:gn_namadm1":"02",
    "qs:local_max":665,
    "qs:local_sum":1145,
    "qs:localhoods":5,
    "qs:name":"Lismore Central",
    "qs:name_adm0":"Australia",
    "qs:name_adm1":"New South Wales",
    "qs:name_adm2":"Lismore",
    "qs:name_local":"Lismore",
    "qs:photo_max":37,
    "qs:photo_sum":214,
    "qs:placetype":"Suburb",
    "qs:quad_count":18,
    "qs:woe_adm0":23424748,
    "qs:woe_adm1":2344700,
    "qs:woe_adm2":55863807,
    "qs:woe_lau":0,
    "qs:woe_local":1103457,
    "qs:woe_ver":"7.10.0",
    "wof:lang":[
        "eng"
    ],
    "wof:name":"Lismore Central",
    "wof:placetype":"neighbourhood"
},
  "geometry": {"coordinates":[153.28549000000001,-28.809849],"type":"Point"}
}