{
  "type": "Feature",
  "properties": {
    "gn:admin1_code":"2.0",
    "gn:admin2_code":"17050.0",
    "gn:asciiname":"Ingebyra",
    "gn:country_code":"AU",
    "gn:dem":1075,
    "gn:feature_class":"P",
    "gn:feature_code":"PPL",
    "gn:name":"Ingebyra",
    "gn:population":0,
    "gn:timezone":"Australia/Sydney",
    "iso:country":"AU",
    "name:und_x_variant":[
        "Ingebyrah",
        "Ingebirah",
        "Ingebyra",
        "Iogebyra"
    ],
    "wof:name":"Ingebyra",
    "wof:placetype":"locality"
},
  "geometry": {"coordinates":[148.49136999999999,-36.65367],"type":"Point"}
}