{
  "type": "Feature",
  "properties": {
    "gn:admin1_code":"2.0",
    "gn:admin2_code":"10550.0",
    "gn:asciiname":"Woodlands",
    "gn:country_code":"AU",
    "gn:dem":427,
    "gn:feature_class":"P",
    "gn:feature_code":"PPL",
    "gn:name":"Woodlands",
    "gn:population":0,
    "gn:timezone":"Australia/Sydney",
    "iso:country":"AU",
    "name:bar_x_preferred":[
        "Woodlands"
    ],
    "name:ceb_x_preferred":[
        "Woodlands"
    ],
    "name:deu_x_preferred":[
        "Woodlands"
    ],
    "name:eng_x_preferred":[
        "Woodlands"
    ],
    "name:ita_x_preferred":[
        "Woodlands"
    ],
    "name:nld_x_preferred":[
        "Woodlands"
    ],
    "name:pol_x_preferred":[
        "Woodlands"
    ],
    "name:rus_x_preferred":[
        "\u0412\u0443\u0434\u043b\u0435\u043d\u0434\u0441"
    ],
    "name:srp_x_preferred":[
        "\u0412\u0443\u0434\u043b\u0430\u043d\u0434\u0441"
    ],
    "name:swe_x_preferred":[
        "Woodlands"
    ],
    "wof:name":"Woodlands",
    "wof:placetype":"locality"
},
  "geometry": {"coordinates":[149.46598999999995,-37.11395],"type":"Point"}
}