{
  "type": "Feature",
  "properties": {
    "iso:country":"AU",
    "oa:elevation_ft":"330",
    "oa:type":"small_airport",
    "woe:hierarchy":{
        "country_id":23424748,
        "county_id":55863844,
        "planet_id":1,
        "state_id":2344700
    },
    "wof:name":"Ivanhoe Aerodrome",
    "wof:placetype":"campus"
},
  "geometry": {"coordinates":[144.31,-32.883333],"type":"Point"}
}