{
  "type": "Feature",
  "properties": {
    "gn:admin1_code":"8",
    "gn:admin2_code":"50080",
    "gn:asciiname":"Bornholm",
    "gn:country_code":"AU",
    "gn:dem":69,
    "gn:feature_class":"P",
    "gn:feature_code":"PPL",
    "gn:name":"Bornholm",
    "gn:population":0,
    "gn:timezone":"Australia/Perth",
    "iso:country":"AU",
    "wof:name":"Bornholm",
    "wof:placetype":"locality"
},
  "geometry": {"coordinates":[117.57689999999999,-35.06056],"type":"Point"}
}