{
  "type": "Feature",
  "properties": {
    "gn:admin1_code":"7.0",
    "gn:admin2_code":"24780.0",
    "gn:asciiname":"Duddo Wells",
    "gn:country_code":"AU",
    "gn:dem":48,
    "gn:feature_class":"P",
    "gn:feature_code":"PPL",
    "gn:name":"Duddo Wells",
    "gn:population":0,
    "gn:timezone":"Australia/Melbourne",
    "iso:country":"AU",
    "wof:name":"Duddo Wells",
    "wof:placetype":"locality"
},
  "geometry": {"coordinates":[141.28333000000001,-35.18333],"type":"Point"}
}