{
  "type": "Feature",
  "properties": {
    "gn:admin1_code":"2.0",
    "gn:admin2_code":"14200.0",
    "gn:asciiname":"Little Plain",
    "gn:country_code":"AU",
    "gn:dem":700,
    "gn:feature_class":"P",
    "gn:feature_code":"PPL",
    "gn:name":"Little Plain",
    "gn:population":0,
    "gn:timezone":"Australia/Sydney",
    "iso:country":"AU",
    "name:eng_x_preferred":[
        "Little Plain"
    ],
    "wof:name":"Little Plain",
    "wof:placetype":"locality"
},
  "geometry": {"coordinates":[150.95501999999999,-29.73032000000001],"type":"Point"}
}