{
  "type": "Feature",
  "properties": {
    "gn:admin1_code":"2.0",
    "gn:asciiname":"Pembrooke",
    "gn:country_code":"AU",
    "gn:dem":-9999,
    "gn:feature_class":"P",
    "gn:feature_code":"PPL",
    "gn:name":"Pembrooke",
    "gn:population":0,
    "gn:timezone":"Australia/Sydney",
    "iso:country":"AU",
    "wof:name":"Pembrooke",
    "wof:placetype":"locality"
},
  "geometry": {"coordinates":[152.75,-32.38333],"type":"Point"}
}