{
  "type": "Feature",
  "properties": {
    "gn:admin1_code":"2.0",
    "gn:admin2_code":"12900.0",
    "gn:asciiname":"Red Bend",
    "gn:country_code":"AU",
    "gn:dem":248,
    "gn:feature_class":"P",
    "gn:feature_code":"PPL",
    "gn:name":"Red Bend",
    "gn:population":0,
    "gn:timezone":"Australia/Sydney",
    "iso:country":"AU",
    "wof:name":"Red Bend",
    "wof:placetype":"locality"
},
  "geometry": {"coordinates":[148.03333000000001,-33.41667],"type":"Point"}
}