{
  "type": "Feature",
  "properties": {
    "iso:country":"AU",
    "name:eng_x_preferred":[
        "Christies Beach North"
    ],
    "name:eng_x_variant":[
        "Christies Beach"
    ],
    "name:fra_x_preferred":[
        "Christies Beach"
    ],
    "qs:gn_adm0_cc":"AU",
    "qs:gn_local":2078025,
    "qs:local_max":18505,
    "qs:local_sum":99726,
    "qs:localhoods":191,
    "qs:name":"Christies Beach North",
    "qs:name_adm0":"Australia",
    "qs:name_adm1":"South Australia",
    "qs:name_adm2":"Onkaparinga",
    "qs:name_local":"Adelaide",
    "qs:photo_max":9,
    "qs:photo_sum":31,
    "qs:placetype":"Suburb",
    "qs:quad_count":5,
    "qs:woe_adm0":23424748,
    "qs:woe_adm1":2344703,
    "qs:woe_adm2":55864226,
    "qs:woe_lau":0,
    "qs:woe_local":1099805,
    "qs:woe_ver":"7.10.0",
    "wd:wordcount":1066,
    "wof:lang":[
        "eng"
    ],
    "wof:name":"Christies Beach North",
    "wof:placetype":"neighbourhood"
},
  "geometry": {"coordinates":[138.47350399999999,-35.125843],"type":"Point"}
}