{
  "type": "Feature",
  "properties": {
    "iso:country":"AU",
    "name:ceb_x_preferred":[
        "Ngukurr Airport"
    ],
    "name:ceb_x_variant":[
        "Wyndham Aerodrome"
    ],
    "name:deu_x_preferred":[
        "Flughafen Ngukurr"
    ],
    "name:eng_x_preferred":[
        "Ngukurr Airport"
    ],
    "name:eng_x_variant":[
        "RPM",
        "YNGU"
    ],
    "name:fas_x_preferred":[
        "\u0641\u0631\u0648\u062f\u06af\u0627\u0647 \u0627\u0646\u06af\u0648\u06a9\u0648\u0631"
    ],
    "name:fra_x_preferred":[
        "Ngukurr Airport"
    ],
    "name:msa_x_preferred":[
        "Lapangan Terbang Ngukurr"
    ],
    "name:ron_x_preferred":[
        "Aeroportul Ngukurr"
    ],
    "name:spa_x_preferred":[
        "Ngukurr"
    ],
    "name:swe_x_preferred":[
        "Ngukurr Airport"
    ],
    "oa:elevation_ft":"45",
    "oa:type":"medium_airport",
    "wd:wordcount":53,
    "woe:hierarchy":{
        "country_id":23424748,
        "county_id":56072995,
        "planet_id":1,
        "state_id":2344701
    },
    "wof:name":"Ngukurr Aerodrome",
    "wof:placetype":"campus"
},
  "geometry": {"coordinates":[134.74700000000001,-14.7228],"type":"Point"}
}