{
  "type": "Feature",
  "properties": {
    "gn:admin1_code":"4.0",
    "gn:admin2_code":"36510.0",
    "gn:asciiname":"Moorang",
    "gn:country_code":"AU",
    "gn:dem":136,
    "gn:feature_class":"P",
    "gn:feature_code":"PPL",
    "gn:name":"Moorang",
    "gn:population":0,
    "gn:timezone":"Australia/Brisbane",
    "iso:country":"AU",
    "wof:name":"Moorang",
    "wof:placetype":"locality"
},
  "geometry": {"coordinates":[152.46666999999999,-27.91667],"type":"Point"}
}