{
  "type": "Feature",
  "properties": {
    "gn:admin1_code":"5.0",
    "gn:admin2_code":"41960.0",
    "gn:asciiname":"Mount Ghearthy",
    "gn:country_code":"AU",
    "gn:dem":202,
    "gn:feature_class":"P",
    "gn:feature_code":"PPL",
    "gn:name":"Mount Ghearthy",
    "gn:population":0,
    "gn:timezone":"Australia/Adelaide",
    "iso:country":"AU",
    "name:eng_x_preferred":[
        "Mount Ghearthy"
    ],
    "wof:name":"Mount Ghearthy",
    "wof:placetype":"locality"
},
  "geometry": {"coordinates":[136.94363000000001,-33.48612],"type":"Point"}
}