{
  "type": "Feature",
  "properties": {
    "gn:admin1_code":"8",
    "gn:admin2_code":"50560",
    "gn:asciiname":"Bally Bally",
    "gn:country_code":"AU",
    "gn:dem":258,
    "gn:feature_class":"P",
    "gn:feature_code":"PPL",
    "gn:name":"Bally Bally",
    "gn:population":0,
    "gn:timezone":"Australia/Perth",
    "iso:country":"AU",
    "wof:name":"Bally Bally",
    "wof:placetype":"locality",
    "wof:population":45
},
  "geometry": {"coordinates":[117.09999999999999,-32.16667],"type":"Point"}
}