{
  "type": "Feature",
  "properties": {
    "iso:country":"AU",
    "name:eng_x_preferred":[
        "Scullin"
    ],
    "name:fas_x_preferred":[
        "\u0627\u0633\u06a9\u0627\u0644\u06cc\u0646"
    ],
    "name:fra_x_preferred":[
        "Scullin"
    ],
    "name:hun_x_preferred":[
        "Scullin"
    ],
    "qs:gn_adm0_cc":"AU",
    "qs:gn_fcode":"PPLX",
    "qs:gn_local":2172517,
    "qs:gn_namadm1":"01",
    "qs:gn_name":"Scullin",
    "qs:local_max":10266,
    "qs:local_sum":72297,
    "qs:localhoods":96,
    "qs:name":"Scullin",
    "qs:name_adm0":"Australia",
    "qs:name_adm1":"Australian Capital Territory",
    "qs:name_adm2":"Canberra",
    "qs:name_local":"Canberra",
    "qs:photo_max":24,
    "qs:photo_sum":55,
    "qs:placetype":"Suburb",
    "qs:quad_count":6,
    "qs:woe_adm0":23424748,
    "qs:woe_adm1":2344699,
    "qs:woe_adm2":55863865,
    "qs:woe_lau":0,
    "qs:woe_local":1100968,
    "qs:woe_ver":"7.10.0",
    "wof:name":"Scullin",
    "wof:placetype":"neighbourhood"
},
  "geometry": {"coordinates":[149.03164899999999,-35.232306],"type":"Point"}
}