{
  "type": "Feature",
  "properties": {
    "gn:admin1_code":"5.0",
    "gn:admin2_code":"47800.0",
    "gn:asciiname":"Menalpyn",
    "gn:country_code":"AU",
    "gn:dem":7,
    "gn:feature_class":"P",
    "gn:feature_code":"PPL",
    "gn:name":"Menalpyn",
    "gn:population":0,
    "gn:timezone":"Australia/Adelaide",
    "iso:country":"AU",
    "name:eng_x_preferred":[
        "Menalpyn"
    ],
    "wof:name":"Menalpyn",
    "wof:placetype":"locality"
},
  "geometry": {"coordinates":[139.59697,-35.71262],"type":"Point"}
}