{
  "type": "Feature",
  "properties": {
    "iso:country":"AU",
    "name:ara_x_preferred":[
        "\u0628\u0648\u0631\u062a \u0644\u064a\u0646\u0643\u0648\u0644\u0646"
    ],
    "name:azb_x_preferred":[
        "\u067e\u0648\u0631\u062a \u0644\u06cc\u0646\u06a9\u0648\u0644\u0646"
    ],
    "name:ceb_x_preferred":[
        "Port Lincoln"
    ],
    "name:ckb_x_preferred":[
        "\u067e\u06c6\u0631\u062a \u0644\u06cc\u0646\u06a9\u06c6\u06b5\u0646"
    ],
    "name:cym_x_preferred":[
        "Port Lincoln"
    ],
    "name:deu_x_preferred":[
        "Port Lincoln"
    ],
    "name:eng_x_preferred":[
        "Port Lincoln"
    ],
    "name:fas_x_preferred":[
        "\u067e\u0648\u0631\u062a \u0644\u06cc\u0646\u06a9\u0644\u0646"
    ],
    "name:fra_x_preferred":[
        "Port Lincoln"
    ],
    "name:gle_x_preferred":[
        "Port Lincoln"
    ],
    "name:heb_x_preferred":[
        "\u05e4\u05d5\u05e8\u05d8 \u05dc\u05d9\u05e0\u05e7\u05d5\u05dc\u05df"
    ],
    "name:ita_x_preferred":[
        "Port Lincoln"
    ],
    "name:jpn_x_preferred":[
        "\u30dd\u30fc\u30c8\u30ea\u30f3\u30ab\u30fc\u30f3"
    ],
    "name:kat_x_preferred":[
        "\u10de\u10dd\u10e0\u10e2-\u10da\u10d8\u10dc\u10d9\u10dd\u10da\u10dc\u10d8"
    ],
    "name:kor_x_preferred":[
        "\ud3ec\ud2b8\ub9c1\ucee8"
    ],
    "name:mlg_x_preferred":[
        "Port Lincoln"
    ],
    "name:nso_x_preferred":[
        "Port Lincoln"
    ],
    "name:pnb_x_preferred":[
        "\u067e\u0648\u0631\u0679 \u0644\u0646\u06a9\u0648\u0644\u0646"
    ],
    "name:pol_x_preferred":[
        "Port Lincoln"
    ],
    "name:rus_x_preferred":[
        "\u041f\u043e\u0440\u0442-\u041b\u0438\u043d\u043a\u043e\u043b\u044c\u043d"
    ],
    "name:spa_x_preferred":[
        "Port Lincoln"
    ],
    "name:swe_x_preferred":[
        "Port Lincoln"
    ],
    "name:tet_x_preferred":[
        "Port Lincoln"
    ],
    "name:ukr_x_preferred":[
        "\u041f\u043e\u0440\u0442-\u041b\u0456\u043d\u043a\u043e\u043b\u044c\u043d"
    ],
    "name:urd_x_preferred":[
        "\u067e\u0648\u0631\u0679 \u0644\u0646\u06a9\u0646"
    ],
    "name:vie_x_preferred":[
        "Port Lincoln"
    ],
    "name:zho_x_preferred":[
        "\u6797\u80af\u6e2f"
    ],
    "wof:coterminous":[
        1376953249
    ],
    "wof:lang_x_official":[
        "eng"
    ],
    "wof:lang_x_spoken":[
        "eng"
    ],
    "wof:name":"Port Lincoln",
    "wof:placetype":"locality"
},
  "geometry": {"coordinates":[135.84512699999999,-34.730421],"type":"Point"}
}