{
  "type": "Feature",
  "properties": {
    "iso:country":"AU",
    "name:eng_x_preferred":[
        "Port Lincoln"
    ],
    "wof:coterminous":[
        1376953249
    ],
    "wof:lang_x_official":[
        "eng"
    ],
    "wof:lang_x_spoken":[
        "eng"
    ],
    "wof:name":"Port Lincoln",
    "wof:placetype":"locality"
},
  "geometry": {"coordinates":[135.84512699999999,-34.730421],"type":"Point"}
}