{
  "type": "Feature",
  "properties": {
    "gn:admin1_code":"2.0",
    "gn:admin2_code":"13500.0",
    "gn:asciiname":"Wyoming",
    "gn:country_code":"AU",
    "gn:dem":348,
    "gn:feature_class":"P",
    "gn:feature_code":"PPL",
    "gn:name":"Wyoming",
    "gn:population":0,
    "gn:timezone":"Australia/Sydney",
    "iso:country":"AU",
    "name:eng_x_preferred":[
        "Wyoming"
    ],
    "wof:name":"Wyoming",
    "wof:placetype":"locality"
},
  "geometry": {"coordinates":[148.12792999999999,-35.15214],"type":"Point"}
}