{
  "type": "Feature",
  "properties": {
    "gn:gn_country":"AU",
    "gn:gn_fcode":"PPL",
    "gn:gn_pop":7071,
    "gn:population":7071,
    "iso:country":"AU",
    "qs_pg:aaroncc":"AU",
    "qs_pg:gn_country":"AU",
    "qs_pg:gn_fcode":"PPL",
    "qs_pg:gn_pop":7071,
    "qs_pg:name":"Phillip Island",
    "qs_pg:photos_9r":0,
    "qs_pg:photos_sr":0,
    "qs_pg:pop_sr":5,
    "qs_pg:qs_pg_placetype":"locality",
    "wof:name":"Phillip Island",
    "wof:placetype":"locality",
    "wof:population":7071
},
  "geometry": {"coordinates":[145.23102,-38.48349],"type":"Point"}
}