{
  "type": "Feature",
  "properties": {
    "gn:gn_country":"AU",
    "gn:gn_fcode":"PPL",
    "gn:gn_pop":7071,
    "gn:population":7071,
    "iso:country":"AU",
    "name:cat_x_preferred":[
        "Phillip Island"
    ],
    "name:deu_x_preferred":[
        "Phillip Island"
    ],
    "name:epo_x_preferred":[
        "Insulo Phillip"
    ],
    "name:fas_x_preferred":[
        "\u062c\u0632\u06cc\u0631\u0647 \u0641\u06cc\u0644\u06cc\u067e"
    ],
    "name:fra_x_preferred":[
        "Phillip Island"
    ],
    "name:hin_x_preferred":[
        "\u092b\u093f\u0932\u093f\u092a \u0926\u094d\u0935\u0940\u092a"
    ],
    "name:ind_x_preferred":[
        "Pulau Phillip"
    ],
    "name:ita_x_preferred":[
        "Phillip Island"
    ],
    "name:jpn_x_preferred":[
        "\u30d5\u30a3\u30ea\u30c3\u30d7\u5cf6"
    ],
    "name:kor_x_preferred":[
        "\ud544\ub9bd\uc12c"
    ],
    "name:mlg_x_preferred":[
        "Phillip Island"
    ],
    "name:nor_x_preferred":[
        "Phillip Island"
    ],
    "name:pol_x_preferred":[
        "Phillip Island"
    ],
    "name:spa_x_preferred":[
        "Isla Phillip"
    ],
    "name:swe_x_preferred":[
        "Phillip Island"
    ],
    "name:ukr_x_preferred":[
        "\u041e\u0441\u0442\u0440\u0456\u0432 \u0424\u0456\u043b\u0456\u043f\u0430"
    ],
    "name:zho_x_preferred":[
        "\u83f2\u5229\u666e\u5cf6"
    ],
    "qs_pg:aaroncc":"AU",
    "qs_pg:gn_country":"AU",
    "qs_pg:gn_fcode":"PPL",
    "qs_pg:gn_pop":7071,
    "qs_pg:name":"Phillip Island",
    "qs_pg:photos_9r":0,
    "qs_pg:photos_sr":0,
    "qs_pg:pop_sr":5,
    "qs_pg:qs_pg_placetype":"locality",
    "wof:name":"Phillip Island",
    "wof:placetype":"locality",
    "wof:population":7071
},
  "geometry": {"coordinates":[145.23102,-38.48349],"type":"Point"}
}