{
  "type": "Feature",
  "properties": {
    "gn:country":"AU",
    "gn:fcode":"PPL",
    "gn:population":0,
    "iso:country":"AU",
    "name:ceb_x_preferred":[
        "Bago"
    ],
    "name:ces_x_preferred":[
        "Bago"
    ],
    "name:fra_x_preferred":[
        "Bago"
    ],
    "name:ita_x_preferred":[
        "Bago"
    ],
    "name:jpn_x_preferred":[
        "\u30d0\u30b4"
    ],
    "name:kor_x_preferred":[
        "\ubc14\uace0"
    ],
    "name:nld_x_preferred":[
        "Bago"
    ],
    "name:rus_x_preferred":[
        "\u0411\u0430\u0433\u043e"
    ],
    "name:spa_x_preferred":[
        "Bago"
    ],
    "name:swe_x_preferred":[
        "Bago"
    ],
    "qs_pg:aaroncc":"AU",
    "qs_pg:gn_country":"AU",
    "qs_pg:gn_fcode":"PPL",
    "qs_pg:gn_pop":0,
    "qs_pg:name":"Bago",
    "qs_pg:name_adm0":"Australia",
    "qs_pg:name_adm1":"New South Wales",
    "qs_pg:photos":140,
    "qs_pg:photos_1k":28,
    "qs_pg:photos_9k":1,
    "qs_pg:photos_9r":3,
    "qs_pg:photos_all":140,
    "qs_pg:photos_sr":3,
    "qs_pg:pop_sr":0,
    "qs_pg:qs_pg_placetype":"locality",
    "qs_pg:qs_pg_placetype_gp":"Town",
    "qs_pg:woe_adm0":23424748,
    "woe:adm0_id":23424748,
    "woe:name_adm0":"Australia",
    "woe:name_adm1":"New South Wales",
    "woe:placetype":"Town",
    "wof:name":"Bago",
    "wof:placetype":"locality"
},
  "geometry": {"coordinates":[152.53333000000001,-31.46667],"type":"Point"}
}