{
  "type": "Feature",
  "properties": {
    "iso:country":"AU",
    "name:ceb_x_preferred":[
        "Doomadgee Airport"
    ],
    "name:swe_x_preferred":[
        "Doomadgee Airport"
    ],
    "oa:elevation_ft":"153",
    "oa:type":"small_airport",
    "wd:wordcount":43,
    "woe:hierarchy":{
        "country_id":23424748,
        "county_id":55864350,
        "planet_id":1,
        "state_id":2344702
    },
    "wof:name":"Doomadgee Aerodrome",
    "wof:placetype":"campus"
},
  "geometry": {"coordinates":[138.82166666667001,-17.94],"type":"Point"}
}