{
  "type": "Feature",
  "properties": {
    "gn:admin1_code":"6.0",
    "gn:admin2_code":"63010.0",
    "gn:asciiname":"Hythe",
    "gn:country_code":"AU",
    "gn:dem":52,
    "gn:feature_class":"P",
    "gn:feature_code":"PPL",
    "gn:name":"Hythe",
    "gn:population":0,
    "gn:timezone":"Australia/Hobart",
    "iso:country":"AU",
    "name:eng_x_preferred":[
        "Hythe"
    ],
    "wof:name":"Hythe",
    "wof:placetype":"locality"
},
  "geometry": {"coordinates":[146.97461999999999,-43.41792],"type":"Point"}
}