{
  "type": "Feature",
  "properties": {
    "gn:admin1_code":"2.0",
    "gn:admin2_code":"11750.0",
    "gn:asciiname":"Glenwood",
    "gn:country_code":"AU",
    "gn:dem":288,
    "gn:feature_class":"P",
    "gn:feature_code":"PPL",
    "gn:name":"Glenwood",
    "gn:population":0,
    "gn:timezone":"Australia/Sydney",
    "iso:country":"AU",
    "name:eng_x_preferred":[
        "Glenwood"
    ],
    "wof:name":"Glenwood",
    "wof:placetype":"locality"
},
  "geometry": {"coordinates":[146.15735000000001,-32.21536],"type":"Point"}
}