{
  "type": "Feature",
  "properties": {
    "gn:admin1_code":"2.0",
    "gn:admin2_code":"11750.0",
    "gn:asciiname":"Glenwood",
    "gn:country_code":"AU",
    "gn:dem":288,
    "gn:feature_class":"P",
    "gn:feature_code":"PPL",
    "gn:name":"Glenwood",
    "gn:population":0,
    "gn:timezone":"Australia/Sydney",
    "iso:country":"AU",
    "name:ara_x_preferred":[
        "\u063a\u0644\u064a\u0646\u0648\u0648\u062f"
    ],
    "name:bar_x_preferred":[
        "Glenwood"
    ],
    "name:ceb_x_preferred":[
        "Glenwood"
    ],
    "name:deu_x_preferred":[
        "Glenwood"
    ],
    "name:eng_x_preferred":[
        "Glenwood"
    ],
    "name:fas_x_preferred":[
        "\u06af\u0644\u0646\u0648\u0648\u062f"
    ],
    "name:fin_x_preferred":[
        "Glenwood"
    ],
    "name:fra_x_preferred":[
        "Glenwood"
    ],
    "name:hrv_x_preferred":[
        "Glenwood"
    ],
    "name:ita_x_preferred":[
        "Glenwood"
    ],
    "name:kor_x_preferred":[
        "\uae00\ub80c\uc6b0\ub4dc"
    ],
    "name:nld_x_preferred":[
        "Glenwood"
    ],
    "name:pol_x_preferred":[
        "Glenwood"
    ],
    "name:por_x_preferred":[
        "Glenwood"
    ],
    "name:rus_x_preferred":[
        "\u0413\u043b\u0435\u043d\u0432\u0443\u0434"
    ],
    "name:spa_x_preferred":[
        "Glenwood"
    ],
    "name:srp_x_preferred":[
        "\u0413\u043b\u0435\u043d\u0432\u0443\u0434"
    ],
    "name:swe_x_preferred":[
        "Glenwood"
    ],
    "name:ukr_x_preferred":[
        "\u0413\u043b\u0435\u043d\u0432\u0443\u0434"
    ],
    "name:vol_x_preferred":[
        "Glenwood"
    ],
    "wof:name":"Glenwood",
    "wof:placetype":"locality"
},
  "geometry": {"coordinates":[146.15735000000001,-32.21536],"type":"Point"}
}