{
  "type": "Feature",
  "properties": {
    "gn:admin1_code":"4.0",
    "gn:admin2_code":"34800.0",
    "gn:asciiname":"Lagavan",
    "gn:country_code":"AU",
    "gn:dem":157,
    "gn:feature_class":"P",
    "gn:feature_code":"PPL",
    "gn:name":"Lagavan",
    "gn:population":0,
    "gn:timezone":"Australia/Brisbane",
    "iso:country":"AU",
    "name:eng_x_preferred":[
        "Lagavan"
    ],
    "wof:name":"Lagavan",
    "wof:placetype":"locality"
},
  "geometry": {"coordinates":[141.38045,-21.10071],"type":"Point"}
}