{
  "type": "Feature",
  "properties": {
    "gn:admin1_code":"6.0",
    "gn:admin2_code":"65010.0",
    "gn:asciiname":"Baden",
    "gn:country_code":"AU",
    "gn:dem":439,
    "gn:feature_class":"P",
    "gn:feature_code":"PPL",
    "gn:name":"Baden",
    "gn:population":0,
    "gn:timezone":"Australia/Hobart",
    "iso:country":"AU",
    "name:eng_x_preferred":[
        "Baden"
    ],
    "wof:name":"Baden",
    "wof:placetype":"locality"
},
  "geometry": {"coordinates":[147.46666999999999,-42.43333],"type":"Point"}
}