{
  "type": "Feature",
  "properties": {
    "gn:admin1_code":"2.0",
    "gn:admin2_code":"17950.0",
    "gn:asciiname":"Belaringar",
    "gn:country_code":"AU",
    "gn:dem":194,
    "gn:feature_class":"P",
    "gn:feature_code":"PPL",
    "gn:name":"Belaringar",
    "gn:population":0,
    "gn:timezone":"Australia/Sydney",
    "iso:country":"AU",
    "name:eng_x_preferred":[
        "Belaringar"
    ],
    "wof:name":"Belaringar",
    "wof:placetype":"locality"
},
  "geometry": {"coordinates":[147.59421,-31.77903],"type":"Point"}
}