{
  "type": "Feature",
  "properties": {
    "gn:admin1_code":"2.0",
    "gn:admin2_code":"17000.0",
    "gn:asciiname":"Balmoral",
    "gn:country_code":"AU",
    "gn:dem":220,
    "gn:feature_class":"P",
    "gn:feature_code":"PPL",
    "gn:name":"Balmoral",
    "gn:population":0,
    "gn:timezone":"Australia/Sydney",
    "iso:country":"AU",
    "name:ceb_x_preferred":[
        "Balmoral"
    ],
    "name:deu_x_preferred":[
        "Balmoral"
    ],
    "name:eng_x_preferred":[
        "Balmoral"
    ],
    "name:fra_x_preferred":[
        "Balmoral"
    ],
    "name:ita_x_preferred":[
        "Balmoral"
    ],
    "name:mlg_x_preferred":[
        "Balmoral"
    ],
    "name:nds_x_preferred":[
        "Balmoral"
    ],
    "name:rus_x_preferred":[
        "\u0411\u0430\u043b\u043c\u043e\u0440\u0430\u043b"
    ],
    "name:swe_x_preferred":[
        "Balmoral"
    ],
    "wof:name":"Balmoral",
    "wof:placetype":"locality"
},
  "geometry": {"coordinates":[151.30813999999995,-32.28779],"type":"Point"}
}