{
  "type": "Feature",
  "properties": {
    "gn:admin1_code":"5.0",
    "gn:admin2_code":"42110.0",
    "gn:asciiname":"The Oaks",
    "gn:country_code":"AU",
    "gn:dem":276,
    "gn:feature_class":"P",
    "gn:feature_code":"PPL",
    "gn:name":"The Oaks",
    "gn:population":0,
    "gn:timezone":"Australia/Adelaide",
    "iso:country":"AU",
    "name:deu_x_preferred":[
        "The Oaks"
    ],
    "name:eng_x_preferred":[
        "The Oaks"
    ],
    "wof:name":"The Oaks",
    "wof:placetype":"locality"
},
  "geometry": {"coordinates":[139.33638999999999,-33.14451],"type":"Point"}
}