{
  "type": "Feature",
  "properties": {
    "gn:admin1_code":"4.0",
    "gn:admin2_code":"37310.0",
    "gn:asciiname":"Pelican",
    "gn:country_code":"AU",
    "gn:dem":328,
    "gn:feature_class":"P",
    "gn:feature_code":"PPL",
    "gn:name":"Pelican",
    "gn:population":0,
    "gn:timezone":"Australia/Brisbane",
    "iso:country":"AU",
    "wof:name":"Pelican",
    "wof:placetype":"locality"
},
  "geometry": {"coordinates":[150.86667,-26.58333],"type":"Point"}
}