{
  "type": "Feature",
  "properties": {
    "iso:country":"AU",
    "name:ceb_x_preferred":[
        "Cheero Point"
    ],
    "name:eng_x_preferred":[
        "Cheero Point"
    ],
    "name:fra_x_preferred":[
        "Cheero Point"
    ],
    "name:swe_x_preferred":[
        "Cheero Point"
    ],
    "qs_pg:aaroncc":"AU",
    "qs_pg:name":"Cheero Point",
    "qs_pg:name_adm0":"Australia",
    "qs_pg:name_adm1":"New South Wales",
    "qs_pg:photos":66,
    "qs_pg:photos_1k":13,
    "qs_pg:photos_9k":1,
    "qs_pg:photos_9r":2,
    "qs_pg:photos_all":66,
    "qs_pg:photos_sr":2,
    "qs_pg:pop_sr":0,
    "qs_pg:qs_pg_placetype":"locality",
    "qs_pg:qs_pg_placetype_gp":"Town",
    "qs_pg:woe_adm0":23424748,
    "woe:adm0_id":23424748,
    "woe:name_adm0":"Australia",
    "woe:name_adm1":"New South Wales",
    "woe:placetype":"Town",
    "wof:name":"Cheero Point",
    "wof:placetype":"locality"
},
  "geometry": {"coordinates":[151.19010349999999,-33.5024325],"type":"Point"}
}