{
  "type": "Feature",
  "properties": {
    "gn:admin1_code":"8.0",
    "gn:admin2_code":"55390.0",
    "gn:asciiname":"Diemel",
    "gn:country_code":"AU",
    "gn:dem":442,
    "gn:feature_class":"P",
    "gn:feature_code":"PPL",
    "gn:name":"Diemel",
    "gn:population":0,
    "gn:timezone":"Australia/Perth",
    "iso:country":"AU",
    "name:ceb_x_preferred":[
        "Diemel"
    ],
    "name:ces_x_preferred":[
        "Diemel"
    ],
    "name:chv_x_preferred":[
        "\u0414\u0438\u043c\u0435\u043b\u044c"
    ],
    "name:deu_x_preferred":[
        "Diemel"
    ],
    "name:eng_x_preferred":[
        "Diemel"
    ],
    "name:eus_x_preferred":[
        "Diemel"
    ],
    "name:fas_x_preferred":[
        "\u062f\u06cc\u0645\u0644"
    ],
    "name:fra_x_preferred":[
        "Diemel"
    ],
    "name:mkd_x_preferred":[
        "\u0414\u0438\u043c\u0435\u043b"
    ],
    "name:nld_x_preferred":[
        "Diemel"
    ],
    "name:nno_x_preferred":[
        "Diemel"
    ],
    "name:nor_x_preferred":[
        "Diemel"
    ],
    "name:pol_x_preferred":[
        "Diemel"
    ],
    "name:ron_x_preferred":[
        "Diemel"
    ],
    "name:rus_x_preferred":[
        "\u0414\u0438\u043c\u0435\u043b\u044c"
    ],
    "name:tgk_x_preferred":[
        "\u0414\u0438\u043c\u043b"
    ],
    "name:zho_x_preferred":[
        "\u8fea\u9ed8\u723e\u6cb3"
    ],
    "wof:name":"Diemel",
    "wof:placetype":"locality"
},
  "geometry": {"coordinates":[119.29606,-29.67403],"type":"Point"}
}