{
  "type": "Feature",
  "properties": {
    "gn:admin1_code":"8.0",
    "gn:admin2_code":"55390.0",
    "gn:asciiname":"Diemel",
    "gn:country_code":"AU",
    "gn:dem":442,
    "gn:feature_class":"P",
    "gn:feature_code":"PPL",
    "gn:name":"Diemel",
    "gn:population":0,
    "gn:timezone":"Australia/Perth",
    "iso:country":"AU",
    "name:eng_x_preferred":[
        "Diemel"
    ],
    "wof:name":"Diemel",
    "wof:placetype":"locality"
},
  "geometry": {"coordinates":[119.29606,-29.67403],"type":"Point"}
}