{
  "type": "Feature",
  "properties": {
    "gn:admin1_code":"5.0",
    "gn:admin2_code":"47800.0",
    "gn:asciiname":"Dayspring",
    "gn:country_code":"AU",
    "gn:dem":14,
    "gn:feature_class":"P",
    "gn:feature_code":"PPL",
    "gn:name":"Dayspring",
    "gn:population":0,
    "gn:timezone":"Australia/Adelaide",
    "iso:country":"AU",
    "name:eng_x_preferred":[
        "Dayspring"
    ],
    "wof:name":"Dayspring",
    "wof:placetype":"locality"
},
  "geometry": {"coordinates":[139.78478999999999,-35.99558],"type":"Point"}
}