{
  "type": "Feature",
  "properties": {
    "gn:admin1_code":"2",
    "gn:admin2_code":"10470",
    "gn:asciiname":"Trunkey",
    "gn:country_code":"AU",
    "gn:dem":879,
    "gn:feature_class":"P",
    "gn:feature_code":"PPL",
    "gn:name":"Trunkey",
    "gn:population":0,
    "gn:timezone":"Australia/Sydney",
    "iso:country":"AU",
    "name:eng_x_preferred":[
        "Trunkey"
    ],
    "name:und_x_variant":[
        "Arthur",
        "Trunkey Creek"
    ],
    "wof:name":"Trunkey",
    "wof:placetype":"locality"
},
  "geometry": {"coordinates":[149.33333000000005,-33.81667],"type":"Point"}
}