{
  "type": "Feature",
  "properties": {
    "iso:country":"AU",
    "name:eng_x_preferred":[
        "Stratford"
    ],
    "name:fra_x_preferred":[
        "Stratford"
    ],
    "name:unk_x_variant":[
        "Stratford"
    ],
    "qs:gn_adm0_cc":"AU",
    "qs:gn_fcode":"PPL",
    "qs:gn_local":2172797,
    "qs:gn_nam_loc":"cairns",
    "qs:gn_namadm1":"04",
    "qs:gn_name":"Stratford",
    "qs:local_max":9814,
    "qs:local_sum":17922,
    "qs:localhoods":22,
    "qs:name":"Stratford",
    "qs:name_adm0":"Australia",
    "qs:name_adm1":"Queensland",
    "qs:name_adm2":"Cairns Regional",
    "qs:name_local":"Cairns",
    "qs:photo_max":161,
    "qs:photo_sum":344,
    "qs:placetype":"Suburb",
    "qs:quad_count":16,
    "qs:woe_adm0":23424748,
    "qs:woe_adm1":2344702,
    "qs:woe_adm2":56072975,
    "qs:woe_lau":0,
    "qs:woe_local":1100908,
    "qs:woe_ver":"7.10.0",
    "wof:lang":[
        "eng"
    ],
    "wof:name":"Stratford",
    "wof:placetype":"neighbourhood"
},
  "geometry": {"coordinates":[145.735139,-16.878896],"type":"Point"}
}