{
  "type": "Feature",
  "properties": {
    "gn:admin1_code":"8",
    "gn:admin2_code":"56230",
    "gn:asciiname":"Holyoake",
    "gn:country_code":"AU",
    "gn:dem":266,
    "gn:feature_class":"P",
    "gn:feature_code":"PPL",
    "gn:name":"Holyoake",
    "gn:population":0,
    "gn:timezone":"Australia/Perth",
    "iso:country":"AU",
    "wof:name":"Holyoake",
    "wof:placetype":"locality"
},
  "geometry": {"coordinates":[116.08333,-32.71667],"type":"Point"}
}