{
  "type": "Feature",
  "properties": {
    "gn:admin1_code":"4.0",
    "gn:admin2_code":"32500.0",
    "gn:asciiname":"Home Rule",
    "gn:country_code":"AU",
    "gn:dem":196,
    "gn:feature_class":"P",
    "gn:feature_code":"PPL",
    "gn:name":"Home Rule",
    "gn:population":0,
    "gn:timezone":"Australia/Brisbane",
    "iso:country":"AU",
    "wof:name":"Home Rule",
    "wof:placetype":"locality"
},
  "geometry": {"coordinates":[145.28895,-15.7494],"type":"Point"}
}