{
  "type": "Feature",
  "properties": {
    "gn:admin1_code":"4.0",
    "gn:admin2_code":"30410.0",
    "gn:asciiname":"Beaufort",
    "gn:country_code":"AU",
    "gn:dem":357,
    "gn:feature_class":"P",
    "gn:feature_code":"PPL",
    "gn:name":"Beaufort",
    "gn:population":0,
    "gn:timezone":"Australia/Brisbane",
    "iso:country":"AU",
    "name:eng_x_preferred":[
        "Beaufort"
    ],
    "wof:name":"Beaufort",
    "wof:placetype":"locality"
},
  "geometry": {"coordinates":[146.89141000000001,-23.65111],"type":"Point"}
}