{
  "type": "Feature",
  "properties": {
    "gn:admin1_code":"4.0",
    "gn:admin2_code":"30410.0",
    "gn:asciiname":"Beaufort",
    "gn:country_code":"AU",
    "gn:dem":357,
    "gn:feature_class":"P",
    "gn:feature_code":"PPL",
    "gn:name":"Beaufort",
    "gn:population":0,
    "gn:timezone":"Australia/Brisbane",
    "iso:country":"AU",
    "name:bre_x_preferred":[
        "Beaufort"
    ],
    "name:cat_x_preferred":[
        "Beaufort"
    ],
    "name:ceb_x_preferred":[
        "Beaufort"
    ],
    "name:ces_x_preferred":[
        "Beaufort"
    ],
    "name:deu_x_preferred":[
        "Beaufort"
    ],
    "name:eng_x_preferred":[
        "Beaufort"
    ],
    "name:epo_x_preferred":[
        "Beaufort"
    ],
    "name:est_x_preferred":[
        "Beaufort"
    ],
    "name:eus_x_preferred":[
        "Beaufort"
    ],
    "name:fas_x_preferred":[
        "\u0628\u0648\u0641\u0648\u0631\u062a"
    ],
    "name:fin_x_preferred":[
        "Beaufort"
    ],
    "name:fra_x_preferred":[
        "Beaufort"
    ],
    "name:heb_x_preferred":[
        "\u05d1\u05d5\u05e4\u05d5\u05e8"
    ],
    "name:ita_x_preferred":[
        "Beaufort"
    ],
    "name:jpn_x_preferred":[
        "\u30dc\u30fc\u30d5\u30a9\u30fc\u30c8"
    ],
    "name:kor_x_preferred":[
        "\ubcf4\ud37c\ud2b8"
    ],
    "name:lav_x_preferred":[
        "Beaufort"
    ],
    "name:ltz_x_preferred":[
        "Beaufort"
    ],
    "name:nds_x_preferred":[
        "Beaufort"
    ],
    "name:nld_x_preferred":[
        "Beaufort"
    ],
    "name:nor_x_preferred":[
        "Beaufort"
    ],
    "name:pms_x_preferred":[
        "Beaufort"
    ],
    "name:pol_x_preferred":[
        "Beaufort"
    ],
    "name:por_x_preferred":[
        "Beaufort"
    ],
    "name:ron_x_preferred":[
        "Beaufort"
    ],
    "name:rus_x_preferred":[
        "\u0411\u043e\u0444\u043e\u0440"
    ],
    "name:slk_x_preferred":[
        "Beaufort"
    ],
    "name:spa_x_preferred":[
        "Beaufort"
    ],
    "name:srp_x_preferred":[
        "\u0411\u043e\u0444\u043e\u0440\u0442"
    ],
    "name:swe_x_preferred":[
        "Beaufort"
    ],
    "name:ukr_x_preferred":[
        "\u0411\u043e\u0444\u043e\u0440"
    ],
    "name:urd_x_preferred":[
        "\u0628\u06cc\u0648\u0641\u0648\u0631\u0679"
    ],
    "name:vie_x_preferred":[
        "Beaufort"
    ],
    "name:vls_x_preferred":[
        "Beaufort"
    ],
    "name:vol_x_preferred":[
        "Beaufort"
    ],
    "wof:name":"Beaufort",
    "wof:placetype":"locality"
},
  "geometry": {"coordinates":[146.89141000000001,-23.65111],"type":"Point"}
}