{
  "type": "Feature",
  "properties": {
    "gn:admin1_code":"7.0",
    "gn:admin2_code":"25990.0",
    "gn:asciiname":"Glenshee",
    "gn:country_code":"AU",
    "gn:dem":579,
    "gn:feature_class":"P",
    "gn:feature_code":"PPL",
    "gn:name":"Glenshee",
    "gn:population":0,
    "gn:timezone":"Australia/Melbourne",
    "iso:country":"AU",
    "wof:name":"Glenshee",
    "wof:placetype":"locality"
},
  "geometry": {"coordinates":[143.26667,-37.06667],"type":"Point"}
}