{
  "type": "Feature",
  "properties": {
    "gn:admin1_code":"4.0",
    "gn:admin2_code":"35760.0",
    "gn:asciiname":"Muan",
    "gn:country_code":"AU",
    "gn:dem":103,
    "gn:feature_class":"P",
    "gn:feature_code":"PPL",
    "gn:name":"Muan",
    "gn:population":0,
    "gn:timezone":"Australia/Brisbane",
    "iso:country":"AU",
    "name:eng_x_preferred":[
        "Muan"
    ],
    "wof:name":"Muan",
    "wof:placetype":"locality"
},
  "geometry": {"coordinates":[151.95977999999999,-25.47122],"type":"Point"}
}