{
  "type": "Feature",
  "properties": {
    "gn:admin1_code":"2.0",
    "gn:admin2_code":"16950.0",
    "gn:asciiname":"Burrier",
    "gn:country_code":"AU",
    "gn:dem":18,
    "gn:feature_class":"P",
    "gn:feature_code":"PPL",
    "gn:name":"Burrier",
    "gn:population":0,
    "gn:timezone":"Australia/Sydney",
    "iso:country":"AU",
    "wof:name":"Burrier",
    "wof:placetype":"locality"
},
  "geometry": {"coordinates":[150.46666999999999,-34.88333],"type":"Point"}
}