{
  "type": "Feature",
  "properties": {
    "iso:country":"AU",
    "name:eng_x_preferred":[
        "St Pauls"
    ],
    "name:eng_x_variant":[
        "Saint Pauls",
        "St. Pauls"
    ],
    "name:unk_x_variant":[
        "St Pauls"
    ],
    "qs:gn_adm0_cc":"AU",
    "qs:gn_local":2147714,
    "qs:local_max":35533,
    "qs:local_sum":687549,
    "qs:localhoods":516,
    "qs:name":"St Pauls",
    "qs:name_adm0":"Australia",
    "qs:name_adm1":"New South Wales",
    "qs:name_adm2":"City of Randwick",
    "qs:name_local":"Sydney",
    "qs:photo_max":1,
    "qs:photo_sum":1,
    "qs:placetype":"Suburb",
    "qs:quad_count":1,
    "qs:woe_adm0":23424748,
    "qs:woe_adm1":2344700,
    "qs:woe_adm2":55864196,
    "qs:woe_lau":0,
    "qs:woe_local":1105779,
    "qs:woe_ver":"7.10.0",
    "wof:lang":[
        "eng"
    ],
    "wof:name":"St Pauls",
    "wof:placetype":"neighbourhood"
},
  "geometry": {"coordinates":[150.69122300000001,-35.081708],"type":"Point"}
}