{
  "type": "Feature",
  "properties": {
    "gn:admin1_code":"3.0",
    "gn:admin2_code":"71300.0",
    "gn:asciiname":"Gurkawur",
    "gn:country_code":"AU",
    "gn:dem":10,
    "gn:feature_class":"P",
    "gn:feature_code":"PPL",
    "gn:name":"Gurkawur",
    "gn:population":0,
    "gn:timezone":"Australia/Darwin",
    "iso:country":"AU",
    "wof:name":"Gurkawur",
    "wof:placetype":"locality"
},
  "geometry": {"coordinates":[136.50801000000001,-12.97983],"type":"Point"}
}