{
  "type": "Feature",
  "properties": {
    "gn:admin1_code":"7.0",
    "gn:admin2_code":"26890.0",
    "gn:asciiname":"Chetwynd East",
    "gn:country_code":"AU",
    "gn:dem":174,
    "gn:feature_class":"P",
    "gn:feature_code":"PPL",
    "gn:name":"Chetwynd East",
    "gn:population":0,
    "gn:timezone":"Australia/Melbourne",
    "iso:country":"AU",
    "wof:name":"Chetwynd East",
    "wof:placetype":"locality"
},
  "geometry": {"coordinates":[141.43333000000001,-37.23333],"type":"Point"}
}