{
  "type": "Feature",
  "properties": {
    "gn:admin1_code":"5.0",
    "gn:admin2_code":"47290.0",
    "gn:asciiname":"Ellimatta",
    "gn:country_code":"AU",
    "gn:dem":77,
    "gn:feature_class":"P",
    "gn:feature_code":"PPL",
    "gn:name":"Ellimatta",
    "gn:population":0,
    "gn:timezone":"Australia/Adelaide",
    "iso:country":"AU",
    "name:eng_x_preferred":[
        "Ellimatta"
    ],
    "wof:name":"Ellimatta",
    "wof:placetype":"locality"
},
  "geometry": {"coordinates":[140.15159,-35.30945],"type":"Point"}
}