{
  "type": "Feature",
  "properties": {
    "gn:admin1_code":"6.0",
    "gn:admin2_code":"61810.0",
    "gn:asciiname":"Jetsonville",
    "gn:country_code":"AU",
    "gn:dem":106,
    "gn:feature_class":"P",
    "gn:feature_code":"PPL",
    "gn:name":"Jetsonville",
    "gn:population":0,
    "gn:timezone":"Australia/Hobart",
    "iso:country":"AU",
    "name:eng_x_preferred":[
        "Jetsonville"
    ],
    "wof:name":"Jetsonville",
    "wof:placetype":"locality"
},
  "geometry": {"coordinates":[147.46666999999999,-41.11667],"type":"Point"}
}