{
  "type": "Feature",
  "properties": {
    "gn:admin1_code":"2.0",
    "gn:admin2_code":"18020.0",
    "gn:asciiname":"Connemarra",
    "gn:country_code":"AU",
    "gn:dem":564,
    "gn:feature_class":"P",
    "gn:feature_code":"PPL",
    "gn:name":"Connemarra",
    "gn:population":0,
    "gn:timezone":"Australia/Sydney",
    "iso:country":"AU",
    "name:eng_x_preferred":[
        "Connemarra"
    ],
    "wof:name":"Connemarra",
    "wof:placetype":"locality"
},
  "geometry": {"coordinates":[149.76076,-31.59016],"type":"Point"}
}