{
  "type": "Feature",
  "properties": {
    "gn:admin1_code":"8.0",
    "gn:admin2_code":"52800.0",
    "gn:asciiname":"Ngurtuwarta Community",
    "gn:country_code":"AU",
    "gn:dem":120,
    "gn:feature_class":"P",
    "gn:feature_code":"PPL",
    "gn:name":"Ngurtuwarta Community",
    "gn:population":0,
    "gn:timezone":"Australia/Perth",
    "iso:country":"AU",
    "wof:name":"Ngurtuwarta Community",
    "wof:placetype":"locality"
},
  "geometry": {"coordinates":[125.52,-18.27778],"type":"Point"}
}