{
  "type": "Feature",
  "properties": {
    "gn:gn_country":"AU",
    "gn:gn_fcode":"PPLX",
    "gn:gn_pop":0,
    "iso:country":"AU",
    "qs_pg:aaroncc":"AU",
    "qs_pg:gn_country":"AU",
    "qs_pg:gn_fcode":"PPLX",
    "qs_pg:gn_pop":0,
    "qs_pg:name":"Taylors Point",
    "qs_pg:name_adm0":"Australia",
    "qs_pg:name_adm1":"New South Wales",
    "qs_pg:photos":155,
    "qs_pg:photos_1k":31,
    "qs_pg:photos_9k":1,
    "qs_pg:photos_9r":4,
    "qs_pg:photos_all":155,
    "qs_pg:photos_sr":4,
    "qs_pg:pop_sr":0,
    "qs_pg:qs_pg_placetype":"neighbourhood",
    "qs_pg:qs_pg_placetype_gp":"Suburb",
    "qs_pg:woe_adm0":23424748,
    "woe:adm0_id":23424748,
    "woe:name_adm0":"Australia",
    "woe:name_adm1":"New South Wales",
    "woe:placetype":"Suburb",
    "wof:name":"Taylors Point",
    "wof:placetype":"neighbourhood"
},
  "geometry": {"coordinates":[151.02526,-33.98744],"type":"Point"}
}