{
  "type": "Feature",
  "properties": {
    "gn:country":"AU",
    "gn:fcode":"PPL",
    "gn:population":286,
    "iso:country":"AU",
    "name:ceb_x_preferred":[
        "Kalannie"
    ],
    "name:eng_x_preferred":[
        "Kalannie"
    ],
    "name:fas_x_preferred":[
        "\u06a9\u0627\u0644\u0627\u0646\u06cc"
    ],
    "name:swe_x_preferred":[
        "Kalannie"
    ],
    "qs_pg:aaroncc":"AU",
    "qs_pg:gn_country":"AU",
    "qs_pg:gn_fcode":"PPL",
    "qs_pg:gn_pop":286,
    "qs_pg:name":"Kalannie",
    "qs_pg:name_adm0":"Australia",
    "qs_pg:name_adm1":"Western Australia",
    "qs_pg:photos_9r":0,
    "qs_pg:photos_sr":0,
    "qs_pg:pop_sr":2,
    "qs_pg:qs_pg_placetype":"locality",
    "qs_pg:qs_pg_placetype_gp":"Town",
    "qs_pg:woe_adm0":23424748,
    "woe:adm0_id":23424748,
    "woe:name_adm0":"Australia",
    "woe:name_adm1":"Western Australia",
    "woe:placetype":"Town",
    "wof:name":"Kalannie",
    "wof:placetype":"locality",
    "wof:population":286
},
  "geometry": {"coordinates":[117.11667,-30.35],"type":"Point"}
}