{
  "type": "Feature",
  "properties": {
    "gn:gn_country":"AU",
    "gn:gn_fcode":"PPL",
    "gn:gn_pop":383,
    "gn:population":383,
    "iso:country":"AU",
    "name:ceb_x_preferred":[
        "Otford"
    ],
    "name:cym_x_preferred":[
        "Otford"
    ],
    "name:fas_x_preferred":[
        "\u0622\u062a\u0641\u0648\u0631\u062f"
    ],
    "name:fra_x_preferred":[
        "Otford"
    ],
    "name:heb_x_preferred":[
        "\u05d0\u05d5\u05d8\u05e4\u05d5\u05e8\u05d3"
    ],
    "name:ita_x_preferred":[
        "Otford"
    ],
    "name:nld_x_preferred":[
        "Otford"
    ],
    "name:nor_x_preferred":[
        "Otford"
    ],
    "name:pol_x_preferred":[
        "Otford"
    ],
    "name:rus_x_preferred":[
        "\u041e\u0442\u0444\u043e\u0440\u0434"
    ],
    "name:spa_x_preferred":[
        "Otford"
    ],
    "name:swe_x_preferred":[
        "Otford"
    ],
    "qs_pg:aaroncc":"AU",
    "qs_pg:gn_country":"AU",
    "qs_pg:gn_fcode":"PPL",
    "qs_pg:gn_pop":383,
    "qs_pg:name":"Otford",
    "qs_pg:name_adm0":"Australia",
    "qs_pg:name_adm1":"New South Wales",
    "qs_pg:photos":170,
    "qs_pg:photos_1k":34,
    "qs_pg:photos_9k":1,
    "qs_pg:photos_9r":4,
    "qs_pg:photos_all":170,
    "qs_pg:photos_sr":4,
    "qs_pg:pop_sr":2,
    "qs_pg:qs_pg_placetype":"neighbourhood",
    "qs_pg:qs_pg_placetype_gp":"Suburb",
    "qs_pg:woe_adm0":23424748,
    "woe:adm0_id":23424748,
    "woe:name_adm0":"Australia",
    "woe:name_adm1":"New South Wales",
    "woe:placetype":"Suburb",
    "wof:name":"Otford",
    "wof:placetype":"neighbourhood",
    "wof:population":383
},
  "geometry": {"coordinates":[151.00710000000001,-34.21248],"type":"Point"}
}