{
  "type": "Feature",
  "properties": {
    "gn:admin1_code":"8.0",
    "gn:admin2_code":"59520.0",
    "gn:asciiname":"Ngilde",
    "gn:country_code":"AU",
    "gn:dem":72,
    "gn:feature_class":"P",
    "gn:feature_code":"PPL",
    "gn:name":"Ngilde",
    "gn:population":0,
    "gn:timezone":"Australia/Perth",
    "iso:country":"AU",
    "wof:name":"Ngilde",
    "wof:placetype":"locality"
},
  "geometry": {"coordinates":[127.65566,-15.2278],"type":"Point"}
}