{
  "type": "Feature",
  "properties": {
    "gn:admin1_code":"04",
    "gn:admin2_code":"32260.0",
    "gn:asciiname":"Upper Daradgee",
    "gn:country_code":"AU",
    "gn:dem":18,
    "gn:feature_class":"P",
    "gn:feature_code":"PPL",
    "gn:name":"Upper Daradgee",
    "gn:population":0,
    "gn:timezone":"Australia/Brisbane",
    "iso:country":"AU",
    "wof:name":"Upper Daradgee",
    "wof:placetype":"locality"
},
  "geometry": {"coordinates":[145.96066000000005,-17.51839],"type":"Point"}
}