{
  "type": "Feature",
  "properties": {
    "gn:admin1_code":"5.0",
    "gn:admin2_code":"43570.0",
    "gn:asciiname":"Careena Downs",
    "gn:country_code":"AU",
    "gn:dem":89,
    "gn:feature_class":"P",
    "gn:feature_code":"PPL",
    "gn:name":"Careena Downs",
    "gn:population":0,
    "gn:timezone":"Australia/Adelaide",
    "iso:country":"AU",
    "name:eng_x_preferred":[
        "Careena Downs"
    ],
    "wof:name":"Careena Downs",
    "wof:placetype":"locality"
},
  "geometry": {"coordinates":[135.10342,-32.92244],"type":"Point"}
}