{
  "type": "Feature",
  "properties": {
    "iso:country":"AU",
    "name:eng_x_preferred":[
        "Elanora Heights"
    ],
    "name:fra_x_preferred":[
        "Elanora Heights"
    ],
    "name:jpn_x_preferred":[
        "\u30a8\u30e9\u30ce\u30fc\u30e9\u30fb\u30cf\u30a4\u30c4"
    ],
    "name:por_x_preferred":[
        "Elanora Heights"
    ],
    "name:ron_x_preferred":[
        "Elanora Heights"
    ],
    "name:unk_x_variant":[
        "Elanora Heights"
    ],
    "qs:gn_adm0_cc":"AU",
    "qs:gn_fcode":"PPLX",
    "qs:gn_local":2147714,
    "qs:gn_namadm1":"02",
    "qs:gn_name":"Elanora Heights",
    "qs:local_max":35533,
    "qs:local_sum":687549,
    "qs:localhoods":516,
    "qs:name":"Elanora Heights",
    "qs:name_adm0":"Australia",
    "qs:name_adm1":"New South Wales",
    "qs:name_adm2":"Pittwater",
    "qs:name_local":"Sydney",
    "qs:photo_max":46,
    "qs:photo_sum":313,
    "qs:placetype":"Suburb",
    "qs:quad_count":30,
    "qs:woe_adm0":23424748,
    "qs:woe_adm1":2344700,
    "qs:woe_adm2":55864176,
    "qs:woe_lau":0,
    "qs:woe_local":1105779,
    "qs:woe_ver":"7.10.0",
    "wof:lang":[
        "eng"
    ],
    "wof:name":"Elanora Heights",
    "wof:placetype":"neighbourhood"
},
  "geometry": {"coordinates":[151.270105,-33.705162],"type":"Point"}
}