{
  "type": "Feature",
  "properties": {
    "iso:country":"AU",
    "name:ceb_x_preferred":[
        "Flinders Peak"
    ],
    "name:deu_x_preferred":[
        "Flinders Peak"
    ],
    "name:nno_x_preferred":[
        "Flinders Peak"
    ],
    "name:zho_x_preferred":[
        "\u5f17\u6797\u5fb7\u65af\u5c71"
    ],
    "qs_pg:aaroncc":"AU",
    "qs_pg:name":"Flinders Peak",
    "qs_pg:name_adm0":"Australia",
    "qs_pg:name_adm1":"Victoria",
    "qs_pg:photos":335,
    "qs_pg:photos_1k":68,
    "qs_pg:photos_9k":1,
    "qs_pg:photos_9r":5,
    "qs_pg:photos_all":335,
    "qs_pg:photos_sr":5,
    "qs_pg:pop_sr":0,
    "qs_pg:qs_pg_placetype":"locality",
    "qs_pg:qs_pg_placetype_gp":"Town",
    "qs_pg:woe_adm0":23424748,
    "woe:adm0_id":23424748,
    "woe:name_adm0":"Australia",
    "woe:name_adm1":"Victoria",
    "woe:placetype":"Town",
    "wof:name":"Flinders Peak",
    "wof:placetype":"locality"
},
  "geometry": {"coordinates":[144.41734299999999,-37.950153],"type":"Point"}
}