{
  "type": "Feature",
  "properties": {
    "iso:country":"AU",
    "oa:elevation_ft":"157",
    "oa:type":"small_airport",
    "woe:hierarchy":{
        "country_id":23424748,
        "county_id":55864200,
        "planet_id":1,
        "state_id":2344706
    },
    "wof:name":"Kalbarri Aerodrome",
    "wof:placetype":"campus"
},
  "geometry": {"coordinates":[114.26000000000001,-27.691666666667],"type":"Point"}
}