{
  "type": "Feature",
  "properties": {
    "iso:country":"AU",
    "name:ceb_x_preferred":[
        "Kalbarri Airport"
    ],
    "name:eng_x_preferred":[
        "Kalbarri Airport"
    ],
    "name:eng_x_variant":[
        "KAX",
        "YKBR"
    ],
    "name:fas_x_preferred":[
        "\u0641\u0631\u0648\u062f\u06af\u0627\u0647 \u06a9\u0627\u0644\u0628\u0627\u0631\u06cc"
    ],
    "name:ron_x_preferred":[
        "Aeroportul Kalbarri"
    ],
    "name:rus_x_preferred":[
        "\u041a\u0430\u043b\u0431\u0430\u0440\u0440\u0438"
    ],
    "name:swe_x_preferred":[
        "Kalbarri Airport"
    ],
    "name:tgk_x_preferred":[
        "\u0424\u0443\u0440\u0443\u0434\u0433\u043e\u04b3\u0438 \u043a\u043e\u043b\u0431\u043e\u0440\u0438"
    ],
    "oa:elevation_ft":"157",
    "oa:type":"small_airport",
    "woe:hierarchy":{
        "country_id":23424748,
        "county_id":55864200,
        "planet_id":1,
        "state_id":2344706
    },
    "wof:name":"Kalbarri Aerodrome",
    "wof:placetype":"campus"
},
  "geometry": {"coordinates":[114.26000000000001,-27.691667],"type":"Point"}
}