{
  "type": "Feature",
  "properties": {
    "gn:admin1_code":"4.0",
    "gn:admin2_code":"36510.0",
    "gn:asciiname":"Rockton",
    "gn:country_code":"AU",
    "gn:dem":46,
    "gn:feature_class":"P",
    "gn:feature_code":"PPL",
    "gn:name":"Rockton",
    "gn:population":0,
    "gn:timezone":"Australia/Brisbane",
    "iso:country":"AU",
    "wof:name":"Rockton",
    "wof:placetype":"locality"
},
  "geometry": {"coordinates":[152.73333,-27.76667],"type":"Point"}
}