{
  "type": "Feature",
  "properties": {
    "gn:admin1_code":"5",
    "gn:admin2_code":"48750",
    "gn:asciiname":"Bald Hills",
    "gn:country_code":"AU",
    "gn:dem":187,
    "gn:feature_class":"P",
    "gn:feature_code":"PPL",
    "gn:name":"Bald Hills",
    "gn:population":0,
    "gn:timezone":"Australia/Adelaide",
    "iso:country":"AU",
    "wof:name":"Bald Hills",
    "wof:placetype":"locality"
},
  "geometry": {"coordinates":[138.41666999999998,-35.51667],"type":"Point"}
}