{
  "type": "Feature",
  "properties": {
    "iso:country":"AU",
    "name:ceb_x_preferred":[
        "Hughenden Airport"
    ],
    "name:eng_x_preferred":[
        "Hughenden Airport"
    ],
    "name:msa_x_preferred":[
        "Lapangan Terbang Hughenden"
    ],
    "name:pol_x_preferred":[
        "Port lotniczy Hughenden"
    ],
    "name:ron_x_preferred":[
        "Aeroportul Hughenden"
    ],
    "name:swe_x_preferred":[
        "Hughenden Airport"
    ],
    "oa:elevation_ft":"1043",
    "oa:type":"small_airport",
    "wd:wordcount":58,
    "woe:hierarchy":{
        "country_id":23424748,
        "county_id":55863918,
        "planet_id":1,
        "state_id":2344702
    },
    "wof:name":"Hughenden Aerodrome",
    "wof:placetype":"campus"
},
  "geometry": {"coordinates":[144.22499999999999,-20.815],"type":"Point"}
}