{
  "type": "Feature",
  "properties": {
    "iso:country":"AU",
    "name:ceb_x_preferred":[
        "Wombeyan Caves"
    ],
    "name:deu_x_preferred":[
        "Wombeyan Caves"
    ],
    "name:rus_x_preferred":[
        "\u041f\u0435\u0449\u0435\u0440\u044b \u0412\u043e\u043c\u0431\u0435\u0439\u0430\u043d"
    ],
    "name:swe_x_preferred":[
        "Wombeyan Caves"
    ],
    "qs_pg:aaroncc":"AU",
    "qs_pg:name":"Wombeyan Caves",
    "qs_pg:name_adm0":"Australia",
    "qs_pg:name_adm1":"New South Wales",
    "qs_pg:photos":294,
    "qs_pg:photos_1k":60,
    "qs_pg:photos_9k":1,
    "qs_pg:photos_9r":4,
    "qs_pg:photos_all":294,
    "qs_pg:photos_sr":5,
    "qs_pg:pop_sr":0,
    "qs_pg:qs_pg_placetype":"locality",
    "qs_pg:qs_pg_placetype_gp":"Town",
    "qs_pg:woe_adm0":23424748,
    "woe:adm0_id":23424748,
    "woe:name_adm0":"Australia",
    "woe:name_adm1":"New South Wales",
    "woe:placetype":"Town",
    "wof:name":"Wombeyan Caves",
    "wof:placetype":"locality",
    "wof:population":57
},
  "geometry": {"coordinates":[149.948959,-34.31005],"type":"Point"}
}