{
  "type": "Feature",
  "properties": {
    "gn:admin1_code":"4.0",
    "gn:admin2_code":"33980.0",
    "gn:asciiname":"Picardy",
    "gn:country_code":"AU",
    "gn:dem":186,
    "gn:feature_class":"P",
    "gn:feature_code":"PPL",
    "gn:name":"Picardy",
    "gn:population":0,
    "gn:timezone":"Australia/Brisbane",
    "iso:country":"AU",
    "name:eng_x_preferred":[
        "Picardy"
    ],
    "wof:name":"Picardy",
    "wof:placetype":"locality"
},
  "geometry": {"coordinates":[148.45952,-22.62636],"type":"Point"}
}