{
  "type": "Feature",
  "properties": {
    "gn:admin1_code":"5.0",
    "gn:admin2_code":"47290.0",
    "gn:asciiname":"Mulpata",
    "gn:country_code":"AU",
    "gn:dem":91,
    "gn:feature_class":"P",
    "gn:feature_code":"PPL",
    "gn:name":"Mulpata",
    "gn:population":0,
    "gn:timezone":"Australia/Adelaide",
    "iso:country":"AU",
    "name:eng_x_preferred":[
        "Mulpata"
    ],
    "wof:name":"Mulpata",
    "wof:placetype":"locality"
},
  "geometry": {"coordinates":[140.40000000000001,-35.15],"type":"Point"}
}