{
  "type": "Feature",
  "properties": {
    "gn:gn_country":"AU",
    "gn:gn_fcode":"PPL",
    "gn:gn_pop":0,
    "iso:country":"AU",
    "name:deu_x_preferred":[
        "Sedgwick"
    ],
    "name:eng_x_preferred":[
        "Sedgwick"
    ],
    "name:fra_x_preferred":[
        "Sedgwick"
    ],
    "name:por_x_preferred":[
        "Sedgwick"
    ],
    "name:sco_x_preferred":[
        "Sedgwick"
    ],
    "name:spa_x_preferred":[
        "Sedgwick"
    ],
    "name:swe_x_preferred":[
        "Sedgwick"
    ],
    "qs_pg:aaroncc":"AU",
    "qs_pg:gn_country":"AU",
    "qs_pg:gn_fcode":"PPL",
    "qs_pg:gn_pop":0,
    "qs_pg:name":"Sedgwick",
    "qs_pg:name_adm0":"Australia",
    "qs_pg:name_adm1":"Victoria",
    "qs_pg:photos_9k":1,
    "qs_pg:photos_9r":1,
    "qs_pg:photos_all":14,
    "qs_pg:photos_sr":0,
    "qs_pg:pop_sr":3,
    "qs_pg:qs_pg_placetype":"locality",
    "qs_pg:qs_pg_placetype_gp":"Town",
    "qs_pg:woe_adm0":23424748,
    "woe:adm0_id":23424748,
    "woe:name_adm0":"Australia",
    "woe:name_adm1":"Victoria",
    "woe:placetype":"Town",
    "wof:name":"Sedgwick",
    "wof:placetype":"locality"
},
  "geometry": {"coordinates":[144.31666999999999,-36.88333],"type":"Point"}
}