{
  "type": "Feature",
  "properties": {
    "gn:admin1_code":"8.0",
    "gn:admin2_code":"59660.0",
    "gn:asciiname":"Quardanoolagin",
    "gn:country_code":"AU",
    "gn:dem":437,
    "gn:feature_class":"P",
    "gn:feature_code":"PPL",
    "gn:name":"Quardanoolagin",
    "gn:population":0,
    "gn:timezone":"Australia/Perth",
    "iso:country":"AU",
    "name:eng_x_preferred":[
        "Quardanoolagin"
    ],
    "wof:name":"Quardanoolagin",
    "wof:placetype":"locality"
},
  "geometry": {"coordinates":[119.97615999999999,-31.27082],"type":"Point"}
}