{
  "type": "Feature",
  "properties": {
    "gn:admin1_code":"8.0",
    "gn:admin2_code":"51960.0",
    "gn:asciiname":"Marell",
    "gn:country_code":"AU",
    "gn:dem":325,
    "gn:feature_class":"P",
    "gn:feature_code":"PPL",
    "gn:name":"Marell",
    "gn:population":0,
    "gn:timezone":"Australia/Perth",
    "iso:country":"AU",
    "name:eng_x_preferred":[
        "Marell"
    ],
    "wof:name":"Marell",
    "wof:placetype":"locality"
},
  "geometry": {"coordinates":[121.81647,-31.55458],"type":"Point"}
}