{
  "type": "Feature",
  "properties": {
    "iso:country":"AU",
    "oa:elevation_ft":"567",
    "oa:type":"medium_airport",
    "woe:hierarchy":{
        "country_id":23424748,
        "county_id":55863951,
        "planet_id":1,
        "state_id":2344702
    },
    "wof:name":"Dirranbandi Aerodrome",
    "wof:placetype":"campus"
},
  "geometry": {"coordinates":[148.21700000000001,-28.5917],"type":"Point"}
}