{
  "type": "Feature",
  "properties": {
    "iso:country":"AU",
    "name:ceb_x_preferred":[
        "Dirranbandi Airport"
    ],
    "name:eng_x_preferred":[
        "Dirranbandi Airport"
    ],
    "name:fas_x_preferred":[
        "\u0641\u0631\u0648\u062f\u06af\u0627\u0647 \u062f\u06cc\u0631\u0627\u0646\u0628\u0627\u0646\u062f\u06cc"
    ],
    "name:msa_x_preferred":[
        "Lapangan Terbang Dirranbandi"
    ],
    "name:ron_x_preferred":[
        "Aeroportul Dirranbandi"
    ],
    "name:swe_x_preferred":[
        "Dirranbandi Airport"
    ],
    "name:tgk_x_preferred":[
        "\u0424\u0443\u0440\u0443\u0434\u0433\u043e\u04b3\u0438 \u0434\u0438\u0440\u043e\u043d\u0431\u043e\u043d\u0434\u0438"
    ],
    "name:zho_x_preferred":[
        "\u8fea\u862d\u73ed\u4ee3\u6a5f\u5834"
    ],
    "oa:elevation_ft":"567",
    "oa:type":"medium_airport",
    "woe:hierarchy":{
        "country_id":23424748,
        "county_id":55863951,
        "planet_id":1,
        "state_id":2344702
    },
    "wof:name":"Dirranbandi Aerodrome",
    "wof:placetype":"campus"
},
  "geometry": {"coordinates":[148.21700000000001,-28.5917],"type":"Point"}
}