{
  "type": "Feature",
  "properties": {
    "gn:admin1_code":"2",
    "gn:admin2_code":"16100",
    "gn:asciiname":"Shooters Hill",
    "gn:country_code":"AU",
    "gn:dem":1228,
    "gn:feature_class":"P",
    "gn:feature_code":"PPL",
    "gn:name":"Shooters Hill",
    "gn:population":0,
    "gn:timezone":"Australia/Sydney",
    "iso:country":"AU",
    "wof:name":"Shooters Hill",
    "wof:placetype":"locality"
},
  "geometry": {"coordinates":[149.86667,-33.91667],"type":"Point"}
}