{
  "type": "Feature",
  "properties": {
    "gn:admin1_code":"8.0",
    "gn:admin2_code":"51610.0",
    "gn:asciiname":"Beetanener",
    "gn:country_code":"AU",
    "gn:dem":287,
    "gn:feature_class":"P",
    "gn:feature_code":"PPL",
    "gn:name":"Beetanener",
    "gn:population":0,
    "gn:timezone":"Australia/Perth",
    "iso:country":"AU",
    "name:eng_x_preferred":[
        "Beetanener"
    ],
    "wof:name":"Beetanener",
    "wof:placetype":"locality"
},
  "geometry": {"coordinates":[114.84237,-28.32673],"type":"Point"}
}