{
  "type": "Feature",
  "properties": {
    "gn:admin1_code":"5.0",
    "gn:asciiname":"East Whydown",
    "gn:country_code":"AU",
    "gn:dem":327,
    "gn:feature_class":"P",
    "gn:feature_code":"PPL",
    "gn:name":"East Whydown",
    "gn:population":0,
    "gn:timezone":"Australia/Adelaide",
    "iso:country":"AU",
    "name:eng_x_preferred":[
        "East Whydown"
    ],
    "wof:name":"East Whydown",
    "wof:placetype":"locality"
},
  "geometry": {"coordinates":[139.39237,-32.64095],"type":"Point"}
}