{
  "type": "Feature",
  "properties": {
    "iso:country":"AU",
    "name:chi_x_preferred":[
        "\u5384\u723e\u4e39\u9054"
    ],
    "name:eng_x_preferred":[
        "Erldunda"
    ],
    "name:ger_x_preferred":[
        "Erldunda"
    ],
    "name:pol_x_preferred":[
        "Erldunda"
    ],
    "ne:ADM0CAP":0.0,
    "ne:ADM0NAME":"Australia",
    "ne:ADM0_A3":"AUS",
    "ne:ADM1NAME":"Northern Territory",
    "ne:ADMIN1_COD":0,
    "ne:CAPALT":0,
    "ne:CHANGED":1,
    "ne:CHECKME":0,
    "ne:COMPARE":0,
    "ne:DIFFASCII":0,
    "ne:DIFFNOTE":"Changed scale rank.",
    "ne:ELEVATION":0.0,
    "ne:FEATURECLA":"Populated place",
    "ne:GEONAMEID":-1,
    "ne:GEONAMESNO":"No GeoNames match due to small population, not in GeoNames, or poor NEV placement.",
    "ne:GN_POP":0,
    "ne:GTOPO30":0.0,
    "ne:ISO_A2":"AU",
    "ne:LABELRANK":3,
    "ne:LATITUDE":-25.233306,
    "ne:LONGITUDE":133.199973,
    "ne:LS_MATCH":0,
    "ne:LS_NAME":"Erldunda",
    "ne:MAX_AREAKM":0.0,
    "ne:MAX_AREAMI":0.0,
    "ne:MAX_BBXMAX":0.0,
    "ne:MAX_BBXMIN":0.0,
    "ne:MAX_BBYMAX":0.0,
    "ne:MAX_BBYMIN":0.0,
    "ne:MAX_NATSCA":0.0,
    "ne:MAX_PERKM":0.0,
    "ne:MAX_PERMI":0.0,
    "ne:MAX_POP10":0,
    "ne:MAX_POP20":0,
    "ne:MAX_POP300":0,
    "ne:MAX_POP310":0,
    "ne:MAX_POP50":0,
    "ne:MEAN_BBXC":0.0,
    "ne:MEAN_BBYC":0.0,
    "ne:MEGACITY":0,
    "ne:MIN_AREAKM":0.0,
    "ne:MIN_AREAMI":0.0,
    "ne:MIN_BBXMAX":0.0,
    "ne:MIN_BBXMIN":0.0,
    "ne:MIN_BBYMAX":0.0,
    "ne:MIN_BBYMIN":0.0,
    "ne:MIN_PERKM":0.0,
    "ne:MIN_PERMI":0.0,
    "ne:NAME":"Erldunda",
    "ne:NAMEASCII":"Erldunda",
    "ne:NAMEDIFF":0,
    "ne:NATSCALE":30,
    "ne:POP1950":0,
    "ne:POP1955":0,
    "ne:POP1960":0,
    "ne:POP1965":0,
    "ne:POP1970":0,
    "ne:POP1975":0,
    "ne:POP1980":0,
    "ne:POP1985":0,
    "ne:POP1990":0,
    "ne:POP1995":0,
    "ne:POP2000":0,
    "ne:POP2005":0,
    "ne:POP2010":0,
    "ne:POP2015":0,
    "ne:POP2020":0,
    "ne:POP2025":0,
    "ne:POP2050":0,
    "ne:POP_MAX":10,
    "ne:POP_MIN":10,
    "ne:POP_OTHER":0,
    "ne:RANK_MAX":1,
    "ne:RANK_MIN":1,
    "ne:SCALERANK":6,
    "ne:SOV0NAME":"Australia",
    "ne:SOV_A3":"AUS",
    "ne:UN_FID":0,
    "ne:UN_LAT":0.0,
    "ne:UN_LONG":0.0,
    "ne:WORLDCITY":0,
    "ne:min_zoom":6.0,
    "qs_pg:aaroncc":"AU",
    "qs_pg:name":"Erldunda",
    "qs_pg:name_adm0":"Australia",
    "qs_pg:name_adm1":"Northern Territory",
    "qs_pg:photos":296,
    "qs_pg:photos_1k":60,
    "qs_pg:photos_9k":1,
    "qs_pg:photos_9r":4,
    "qs_pg:photos_all":296,
    "qs_pg:photos_sr":5,
    "qs_pg:pop_sr":0,
    "qs_pg:qs_pg_placetype":"locality",
    "qs_pg:qs_pg_placetype_gp":"Town",
    "qs_pg:woe_adm0":23424748,
    "wof:name":"Erldunda",
    "wof:placetype":"locality"
},
  "geometry": {"coordinates":[133.19997269605835,-25.23330605184231],"type":"Point"}
}