{
  "type": "Feature",
  "properties": {
    "gn:admin1_code":"2.0",
    "gn:admin2_code":"15270.0",
    "gn:asciiname":"Kerrabee",
    "gn:country_code":"AU",
    "gn:dem":309,
    "gn:feature_class":"P",
    "gn:feature_code":"PPL",
    "gn:name":"Kerrabee",
    "gn:population":0,
    "gn:timezone":"Australia/Sydney",
    "iso:country":"AU",
    "wof:name":"Kerrabee",
    "wof:placetype":"locality"
},
  "geometry": {"coordinates":[150.30000000000001,-32.41667],"type":"Point"}
}