{
  "type": "Feature",
  "properties": {
    "gn:admin1_code":"8",
    "gn:admin2_code":"57420",
    "gn:asciiname":"Quagitup",
    "gn:country_code":"AU",
    "gn:dem":162,
    "gn:feature_class":"P",
    "gn:feature_code":"PPL",
    "gn:name":"Quagitup",
    "gn:population":0,
    "gn:timezone":"Australia/Perth",
    "iso:country":"AU",
    "wof:name":"Quagitup",
    "wof:placetype":"locality"
},
  "geometry": {"coordinates":[119.96666999999999,-33.63333],"type":"Point"}
}