{
  "type": "Feature",
  "properties": {
    "gn:admin1_code":"06",
    "gn:admin2_code":"61010.0",
    "gn:asciiname":"Bronte Park",
    "gn:country_code":"AU",
    "gn:dem":679,
    "gn:feature_class":"P",
    "gn:feature_code":"PPL",
    "gn:name":"Bronte Park",
    "gn:population":0,
    "gn:timezone":"Australia/Hobart",
    "iso:country":"AU",
    "name:eng_x_preferred":[
        "Bronte Park"
    ],
    "wof:name":"Bronte Park",
    "wof:placetype":"locality"
},
  "geometry": {"coordinates":[146.4932,-42.13598],"type":"Point"}
}