{
  "type": "Feature",
  "properties": {
    "gn:admin1_code":"4.0",
    "gn:admin2_code":"32500.0",
    "gn:asciiname":"Koolburra",
    "gn:country_code":"AU",
    "gn:dem":105,
    "gn:feature_class":"P",
    "gn:feature_code":"PPL",
    "gn:name":"Koolburra",
    "gn:population":0,
    "gn:timezone":"Australia/Brisbane",
    "iso:country":"AU",
    "wof:name":"Koolburra",
    "wof:placetype":"locality"
},
  "geometry": {"coordinates":[143.95733000000001,-15.32081],"type":"Point"}
}