{
  "type": "Feature",
  "properties": {
    "gn:country":"AU",
    "gn:fcode":"PPL",
    "gn:population":29,
    "iso:country":"AU",
    "name:eng_x_preferred":[
        "Fords Bridge"
    ],
    "name:und_x_variant":[
        "Village of Fords Bridge"
    ],
    "qs_pg:aaroncc":"AU",
    "qs_pg:gn_country":"AU",
    "qs_pg:gn_fcode":"PPL",
    "qs_pg:gn_pop":29,
    "qs_pg:name":"Fords Bridge",
    "qs_pg:name_adm0":"Australia",
    "qs_pg:name_adm1":"New South Wales",
    "qs_pg:photos_9r":0,
    "qs_pg:photos_sr":0,
    "qs_pg:pop_sr":1,
    "qs_pg:qs_pg_placetype":"locality",
    "qs_pg:qs_pg_placetype_gp":"Town",
    "qs_pg:woe_adm0":23424748,
    "woe:adm0_id":23424748,
    "woe:name_adm0":"Australia",
    "woe:name_adm1":"New South Wales",
    "woe:placetype":"Town",
    "wof:name":"Fords Bridge",
    "wof:placetype":"locality",
    "wof:population":29
},
  "geometry": {"coordinates":[145.41667000000001,-29.75],"type":"Point"}
}