{
  "type": "Feature",
  "properties": {
    "gn:admin1_code":"2.0",
    "gn:admin2_code":"11730.0",
    "gn:asciiname":"Clifden",
    "gn:country_code":"AU",
    "gn:dem":28,
    "gn:feature_class":"P",
    "gn:feature_code":"PPL",
    "gn:name":"Clifden",
    "gn:population":0,
    "gn:timezone":"Australia/Sydney",
    "iso:country":"AU",
    "wof:name":"Clifden",
    "wof:placetype":"locality"
},
  "geometry": {"coordinates":[152.91666999999995,-29.56667],"type":"Point"}
}