{
  "type": "Feature",
  "properties": {
    "gn:admin1_code":"2.0",
    "gn:admin2_code":"11730.0",
    "gn:asciiname":"Clifden",
    "gn:country_code":"AU",
    "gn:dem":28,
    "gn:feature_class":"P",
    "gn:feature_code":"PPL",
    "gn:name":"Clifden",
    "gn:population":0,
    "gn:timezone":"Australia/Sydney",
    "iso:country":"AU",
    "name:bre_x_preferred":[
        "An Cloch\u00e1n"
    ],
    "name:cat_x_preferred":[
        "Clifden"
    ],
    "name:ceb_x_preferred":[
        "Clifden"
    ],
    "name:deu_x_preferred":[
        "Clifden"
    ],
    "name:eus_x_preferred":[
        "Clifden"
    ],
    "name:fra_x_preferred":[
        "Clifden"
    ],
    "name:gle_x_preferred":[
        "An Cloch\u00e1n"
    ],
    "name:glg_x_preferred":[
        "Clifden"
    ],
    "name:ile_x_preferred":[
        "Clifden"
    ],
    "name:ita_x_preferred":[
        "Clifden"
    ],
    "name:kat_x_preferred":[
        "\u10d9\u10da\u10d8\u10e4\u10d3\u10d4\u10dc\u10d8"
    ],
    "name:nld_x_preferred":[
        "Clifden"
    ],
    "name:pol_x_preferred":[
        "Clifden"
    ],
    "name:rus_x_preferred":[
        "\u041a\u043b\u0438\u0444\u0434\u0435\u043d"
    ],
    "name:spa_x_preferred":[
        "Clifden"
    ],
    "name:swe_x_preferred":[
        "Clifden"
    ],
    "wof:name":"Clifden",
    "wof:placetype":"locality"
},
  "geometry": {"coordinates":[152.91666999999995,-29.56667],"type":"Point"}
}