{
  "type": "Feature",
  "properties": {
    "gn:gn_country":"AU",
    "gn:gn_fcode":"PPL",
    "gn:gn_pop":390,
    "gn:population":390,
    "iso:country":"AU",
    "name:eng_x_preferred":[
        "Emu Bay"
    ],
    "name:nld_x_preferred":[
        "Emu Bay"
    ],
    "name:swe_x_preferred":[
        "Emu Bay"
    ],
    "name:urd_x_preferred":[
        "\u0627\u06cc\u0645\u06cc\u0648 \u0628\u06d2\u060c \u062c\u0646\u0648\u0628\u06cc \u0622\u0633\u0679\u0631\u06cc\u0644\u06cc\u0627"
    ],
    "qs_pg:aaroncc":"AU",
    "qs_pg:gn_country":"AU",
    "qs_pg:gn_fcode":"PPL",
    "qs_pg:gn_pop":390,
    "qs_pg:name":"Emu Bay",
    "qs_pg:photos_9r":0,
    "qs_pg:photos_sr":0,
    "qs_pg:pop_sr":2,
    "qs_pg:qs_pg_placetype":"locality",
    "wof:name":"Emu Bay",
    "wof:placetype":"locality",
    "wof:population":390
},
  "geometry": {"coordinates":[137.50591,-35.59841],"type":"Point"}
}