{
  "type": "Feature",
  "properties": {
    "iso:country":"AU",
    "name:eng_x_preferred":[
        "Regency Park Bc"
    ],
    "name:eng_x_variant":[
        "Regency Park"
    ],
    "name:zho_x_preferred":[
        "\u5229\u771f\u58eb\u67cf"
    ],
    "qs:gn_adm0_cc":"AU",
    "qs:gn_fcode":"PPLX",
    "qs:gn_local":2078025,
    "qs:gn_namadm1":"05",
    "qs:gn_name":"Regency Park",
    "qs:local_max":18505,
    "qs:local_sum":99726,
    "qs:localhoods":191,
    "qs:name":"Regency Park Bc",
    "qs:name_adm0":"Australia",
    "qs:name_adm1":"South Australia",
    "qs:name_adm2":"Port Adelaide Enfield",
    "qs:name_local":"Adelaide",
    "qs:photo_max":84,
    "qs:photo_sum":653,
    "qs:placetype":"Suburb",
    "qs:quad_count":34,
    "qs:woe_adm0":23424748,
    "qs:woe_adm1":2344703,
    "qs:woe_adm2":55864219,
    "qs:woe_lau":0,
    "qs:woe_local":1099805,
    "qs:woe_ver":"7.10.0",
    "wof:lang":[
        "eng"
    ],
    "wof:name":"Regency Park Bc",
    "wof:placetype":"neighbourhood"
},
  "geometry": {"coordinates":[138.57052100000001,-34.865336],"type":"Point"}
}