{
  "type": "Feature",
  "properties": {
    "gn:country":"AU",
    "gn:fcode":"PPL",
    "gn:population":0,
    "iso:country":"AU",
    "name:eng_x_preferred":[
        "Fentonbury"
    ],
    "qs_pg:aaroncc":"AU",
    "qs_pg:gn_country":"AU",
    "qs_pg:gn_fcode":"PPL",
    "qs_pg:gn_pop":0,
    "qs_pg:name":"Fentonbury",
    "qs_pg:name_adm0":"Australia",
    "qs_pg:name_adm1":"Tasmania",
    "qs_pg:photos":282,
    "qs_pg:photos_1k":57,
    "qs_pg:photos_9k":1,
    "qs_pg:photos_9r":4,
    "qs_pg:photos_all":282,
    "qs_pg:photos_sr":5,
    "qs_pg:pop_sr":0,
    "qs_pg:qs_pg_placetype":"locality",
    "qs_pg:qs_pg_placetype_gp":"Town",
    "qs_pg:woe_adm0":23424748,
    "woe:adm0_id":23424748,
    "woe:name_adm0":"Australia",
    "woe:name_adm1":"Tasmania",
    "woe:placetype":"Town",
    "wof:name":"Fentonbury",
    "wof:placetype":"locality"
},
  "geometry": {"coordinates":[146.76667,-42.65],"type":"Point"}
}