{
  "type": "Feature",
  "properties": {
    "gn:admin1_code":"2.0",
    "gn:admin2_code":"15270.0",
    "gn:asciiname":"Mamore",
    "gn:country_code":"AU",
    "gn:dem":728,
    "gn:feature_class":"P",
    "gn:feature_code":"PPL",
    "gn:name":"Mamore",
    "gn:population":0,
    "gn:timezone":"Australia/Sydney",
    "iso:country":"AU",
    "name:eng_x_preferred":[
        "Mamore"
    ],
    "wof:name":"Mamore",
    "wof:placetype":"locality"
},
  "geometry": {"coordinates":[149.52723,-32.71898],"type":"Point"}
}