{
  "type": "Feature",
  "properties": {
    "gn:admin1_code":"2.0",
    "gn:admin2_code":"11730.0",
    "gn:asciiname":"O.B.X. Creek",
    "gn:country_code":"AU",
    "gn:dem":76,
    "gn:feature_class":"P",
    "gn:feature_code":"PPL",
    "gn:name":"O.B.X. Creek",
    "gn:population":0,
    "gn:timezone":"Australia/Sydney",
    "iso:country":"AU",
    "name:eng_x_preferred":[
        "O.B.X. Creek"
    ],
    "wof:name":"O.B.X. Creek",
    "wof:placetype":"locality"
},
  "geometry": {"coordinates":[152.71921,-29.80561],"type":"Point"}
}