{
  "type": "Feature",
  "properties": {
    "gn:admin1_code":"8",
    "gn:admin2_code":"51960",
    "gn:asciiname":"Timberfield",
    "gn:cc2":"AU",
    "gn:country_code":"AU",
    "gn:dem":416,
    "gn:feature_class":"P",
    "gn:feature_code":"PPL",
    "gn:name":"Timberfield",
    "gn:population":0,
    "gn:timezone":"Australia/Perth",
    "iso:country":"AU",
    "name:und_x_variant":[
        "Jaurdi",
        "Timberfield"
    ],
    "wof:name":"Timberfield",
    "wof:placetype":"locality"
},
  "geometry": {"coordinates":[120.16667,-30.81667],"type":"Point"}
}