{
  "type": "Feature",
  "properties": {
    "gn:admin1_code":"4.0",
    "gn:admin2_code":"32270.0",
    "gn:asciiname":"Pamabal",
    "gn:country_code":"AU",
    "gn:dem":141,
    "gn:feature_class":"P",
    "gn:feature_code":"PPL",
    "gn:name":"Pamabal",
    "gn:population":0,
    "gn:timezone":"Australia/Brisbane",
    "iso:country":"AU",
    "name:eng_x_preferred":[
        "Pamabal"
    ],
    "wof:name":"Pamabal",
    "wof:placetype":"locality"
},
  "geometry": {"coordinates":[149.19397000000001,-23.60685],"type":"Point"}
}