{
  "type": "Feature",
  "properties": {
    "gn:country":"AU",
    "gn:fcode":"PPL",
    "gn:population":869,
    "iso:country":"AU",
    "name:ast_x_preferred":[
        "Marrangaroo"
    ],
    "name:ceb_x_preferred":[
        "Marrangaroo"
    ],
    "name:deu_x_preferred":[
        "Marrangaroo"
    ],
    "name:eng_x_preferred":[
        "Marrangaroo"
    ],
    "name:fra_x_preferred":[
        "Marrangaroo"
    ],
    "name:nld_x_preferred":[
        "Marrangaroo"
    ],
    "name:nld_x_variant":[
        "The Leap"
    ],
    "name:pol_x_preferred":[
        "Marrangaroo"
    ],
    "name:por_x_preferred":[
        "Marrangaroo"
    ],
    "name:sco_x_preferred":[
        "Marrangaroo"
    ],
    "name:spa_x_preferred":[
        "Marrangaroo"
    ],
    "name:swe_x_preferred":[
        "Marrangaroo"
    ],
    "qs_pg:aaroncc":"AU",
    "qs_pg:gn_country":"AU",
    "qs_pg:gn_fcode":"PPL",
    "qs_pg:gn_pop":869,
    "qs_pg:name":"Marrangaroo",
    "qs_pg:name_adm0":"Australia",
    "qs_pg:name_adm1":"New South Wales",
    "qs_pg:photos":14,
    "qs_pg:photos_1k":3,
    "qs_pg:photos_9k":1,
    "qs_pg:photos_9r":1,
    "qs_pg:photos_all":14,
    "qs_pg:photos_sr":1,
    "qs_pg:pop_sr":2,
    "qs_pg:qs_pg_placetype":"locality",
    "qs_pg:qs_pg_placetype_gp":"Town",
    "qs_pg:woe_adm0":23424748,
    "woe:adm0_id":23424748,
    "woe:name_adm0":"Australia",
    "woe:name_adm1":"New South Wales",
    "woe:placetype":"Town",
    "wof:name":"Marrangaroo",
    "wof:placetype":"locality",
    "wof:population":869
},
  "geometry": {"coordinates":[150.11667,-33.43333],"type":"Point"}
}