{
  "type": "Feature",
  "properties": {
    "gn:admin1_code":"2.0",
    "gn:admin2_code":"10950.0",
    "gn:asciiname":"Vaucluse",
    "gn:country_code":"AU",
    "gn:dem":292,
    "gn:feature_class":"P",
    "gn:feature_code":"PPL",
    "gn:name":"Vaucluse",
    "gn:population":0,
    "gn:timezone":"Australia/Sydney",
    "iso:country":"AU",
    "name:eng_x_preferred":[
        "Vaucluse"
    ],
    "wof:name":"Vaucluse",
    "wof:placetype":"locality"
},
  "geometry": {"coordinates":[146.52567999999999,-32.16265],"type":"Point"}
}