{
  "type": "Feature",
  "properties": {
    "gn:admin1_code":"4",
    "gn:admin2_code":"33360",
    "gn:asciiname":"Ubobo",
    "gn:country_code":"AU",
    "gn:dem":83,
    "gn:feature_class":"P",
    "gn:feature_code":"PPL",
    "gn:name":"Ubobo",
    "gn:population":0,
    "gn:timezone":"Australia/Brisbane",
    "iso:country":"AU",
    "wof:name":"Ubobo",
    "wof:placetype":"locality"
},
  "geometry": {"coordinates":[151.32345000000001,-24.40463],"type":"Point"}
}