{
  "type": "Feature",
  "properties": {
    "gn:admin1_code":"4.0",
    "gn:admin2_code":"33980.0",
    "gn:asciiname":"LittleDale",
    "gn:country_code":"AU",
    "gn:dem":367,
    "gn:feature_class":"P",
    "gn:feature_code":"PPL",
    "gn:name":"LittleDale",
    "gn:population":0,
    "gn:timezone":"Australia/Brisbane",
    "iso:country":"AU",
    "name:eng_x_preferred":[
        "LittleDale"
    ],
    "wof:name":"LittleDale",
    "wof:placetype":"locality"
},
  "geometry": {"coordinates":[147.85310000000001,-22.56222],"type":"Point"}
}