{
  "type": "Feature",
  "properties": {
    "gn:admin1_code":"2.0",
    "gn:admin2_code":"17700.0",
    "gn:asciiname":"Nowranie",
    "gn:country_code":"AU",
    "gn:dem":119,
    "gn:feature_class":"P",
    "gn:feature_code":"PPL",
    "gn:name":"Nowranie",
    "gn:population":0,
    "gn:timezone":"Australia/Sydney",
    "iso:country":"AU",
    "wof:name":"Nowranie",
    "wof:placetype":"locality"
},
  "geometry": {"coordinates":[146.08333000000005,-35.43333],"type":"Point"}
}