{
  "type": "Feature",
  "properties": {
    "gn:admin1_code":"7",
    "gn:admin2_code":"26260",
    "gn:asciiname":"Tabor",
    "gn:country_code":"AU",
    "gn:dem":205,
    "gn:feature_class":"P",
    "gn:feature_code":"PPL",
    "gn:name":"Tabor",
    "gn:population":0,
    "gn:timezone":"Australia/Melbourne",
    "iso:country":"AU",
    "name:ara_x_preferred":[
        "\u062a\u0627\u0628\u0648\u0631"
    ],
    "name:ben_x_preferred":[
        "\u09a4\u09be\u09ac\u09cb\u09b0"
    ],
    "name:deu_x_preferred":[
        "T\u00e1bor"
    ],
    "name:ell_x_preferred":[
        "\u03a4\u03b1\u03bc\u03c0\u03cc\u03c1"
    ],
    "name:fas_x_preferred":[
        "\u062a\u0627\u0628\u0648\u0631"
    ],
    "name:heb_x_preferred":[
        "\u05d8\u05d0\u05d1\u05d5\u05e8"
    ],
    "name:hin_x_preferred":[
        "\u091f\u0948\u092c\u094b\u0930 "
    ],
    "name:hun_x_preferred":[
        "Tabor"
    ],
    "name:ita_x_preferred":[
        "Tabor"
    ],
    "name:jpn_x_preferred":[
        "\u30bf\u30dc\u30eb"
    ],
    "name:kor_x_preferred":[
        "\ud0c0\ubcf4\ub974"
    ],
    "name:por_x_preferred":[
        "T\u00e1bor"
    ],
    "name:rus_x_preferred":[
        "\u0422\u0430\u0431\u043e\u0440"
    ],
    "name:spa_x_preferred":[
        "Tabor"
    ],
    "name:swe_x_preferred":[
        "Tabor"
    ],
    "name:tur_x_preferred":[
        "Tabor"
    ],
    "name:urd_x_preferred":[
        "\u062a\u0627\u0628\u0648\u0631"
    ],
    "name:vie_x_preferred":[
        "Tabor"
    ],
    "wof:name":"Tabor",
    "wof:placetype":"locality"
},
  "geometry": {"coordinates":[142.19999999999999,-37.83333],"type":"Point"}
}