{
  "type": "Feature",
  "properties": {
    "gn:admin1_code":"7",
    "gn:admin2_code":"26260",
    "gn:asciiname":"Tabor",
    "gn:country_code":"AU",
    "gn:dem":205,
    "gn:feature_class":"P",
    "gn:feature_code":"PPL",
    "gn:name":"Tabor",
    "gn:population":0,
    "gn:timezone":"Australia/Melbourne",
    "iso:country":"AU",
    "wof:name":"Tabor",
    "wof:placetype":"locality"
},
  "geometry": {"coordinates":[142.19999999999999,-37.83333],"type":"Point"}
}