{
  "type": "Feature",
  "properties": {
    "gn:admin1_code":"2.0",
    "gn:admin2_code":"17500.0",
    "gn:asciiname":"Kelvinglove",
    "gn:country_code":"AU",
    "gn:dem":334,
    "gn:feature_class":"P",
    "gn:feature_code":"PPL",
    "gn:name":"Kelvinglove",
    "gn:population":0,
    "gn:timezone":"Australia/Sydney",
    "iso:country":"AU",
    "name:eng_x_preferred":[
        "Kelvinglove"
    ],
    "wof:name":"Kelvinglove",
    "wof:placetype":"locality"
},
  "geometry": {"coordinates":[148.34442000000001,-35.31182000000001],"type":"Point"}
}