{
  "type": "Feature",
  "properties": {
    "gn:gn_country":"AU",
    "gn:gn_fcode":"PPL",
    "gn:gn_pop":207,
    "gn:population":207,
    "iso:country":"AU",
    "name:ceb_x_preferred":[
        "Frankford"
    ],
    "name:deu_x_preferred":[
        "Frankford"
    ],
    "name:eng_x_preferred":[
        "Frankford"
    ],
    "name:ita_x_preferred":[
        "Frankford"
    ],
    "name:nld_x_preferred":[
        "Frankford"
    ],
    "name:pol_x_preferred":[
        "Frankford"
    ],
    "name:por_x_preferred":[
        "Frankford"
    ],
    "name:spa_x_preferred":[
        "Frankford"
    ],
    "name:srp_x_preferred":[
        "\u0424\u0440\u0430\u043d\u043a\u0444\u043e\u0440\u0434"
    ],
    "name:swe_x_preferred":[
        "Frankford"
    ],
    "name:ukr_x_preferred":[
        "\u0424\u0440\u0430\u043d\u043a\u0444\u043e\u0440\u0434"
    ],
    "name:vol_x_preferred":[
        "Frankford"
    ],
    "qs_pg:aaroncc":"AU",
    "qs_pg:gn_country":"AU",
    "qs_pg:gn_fcode":"PPL",
    "qs_pg:gn_pop":207,
    "qs_pg:name":"Frankford",
    "qs_pg:name_adm0":"Australia",
    "qs_pg:name_adm1":"Tasmania",
    "qs_pg:photos_9k":1,
    "qs_pg:photos_9r":1,
    "qs_pg:photos_all":9,
    "qs_pg:photos_sr":0,
    "qs_pg:pop_sr":2,
    "qs_pg:qs_pg_placetype":"locality",
    "qs_pg:qs_pg_placetype_gp":"Town",
    "qs_pg:woe_adm0":23424748,
    "woe:adm0_id":23424748,
    "woe:name_adm0":"Australia",
    "woe:name_adm1":"Tasmania",
    "woe:placetype":"Town",
    "wof:name":"Frankford",
    "wof:placetype":"locality",
    "wof:population":176
},
  "geometry": {"coordinates":[146.76667,-41.33333],"type":"Point"}
}