{
  "type": "Feature",
  "properties": {
    "gn:admin1_code":"5",
    "gn:admin2_code":"45400",
    "gn:asciiname":"Wepowie",
    "gn:country_code":"AU",
    "gn:dem":473,
    "gn:feature_class":"P",
    "gn:feature_code":"PPL",
    "gn:name":"Wepowie",
    "gn:population":0,
    "gn:timezone":"Australia/Adelaide",
    "iso:country":"AU",
    "wof:name":"Wepowie",
    "wof:placetype":"locality"
},
  "geometry": {"coordinates":[138.48333,-32.83333],"type":"Point"}
}