{
  "type": "Feature",
  "properties": {
    "gn:admin1_code":"2.0",
    "gn:admin2_code":"11860.0",
    "gn:asciiname":"Pretty Pine",
    "gn:country_code":"AU",
    "gn:dem":89,
    "gn:feature_class":"P",
    "gn:feature_code":"PPL",
    "gn:name":"Pretty Pine",
    "gn:population":0,
    "gn:timezone":"Australia/Sydney",
    "iso:country":"AU",
    "name:und_x_variant":[
        "Dahwilly"
    ],
    "wof:name":"Pretty Pine",
    "wof:placetype":"locality"
},
  "geometry": {"coordinates":[144.88460000000001,-35.4152],"type":"Point"}
}