{
  "type": "Feature",
  "properties": {
    "gn:admin1_code":"4.0",
    "gn:asciiname":"Bindango",
    "gn:country_code":"AU",
    "gn:dem":1014,
    "gn:feature_class":"P",
    "gn:feature_code":"PPL",
    "gn:name":"Bindango",
    "gn:population":0,
    "gn:timezone":"Australia/Sydney",
    "iso:country":"AU",
    "wof:name":"Bindango",
    "wof:placetype":"locality"
},
  "geometry": {"coordinates":[148.55000000000001,-36.58333],"type":"Point"}
}