{
  "type": "Feature",
  "properties": {
    "gn:admin1_code":"5.0",
    "gn:admin2_code":"44210.0",
    "gn:asciiname":"Haylands",
    "gn:country_code":"AU",
    "gn:dem":29,
    "gn:feature_class":"P",
    "gn:feature_code":"PPL",
    "gn:name":"Haylands",
    "gn:population":0,
    "gn:timezone":"Australia/Adelaide",
    "iso:country":"AU",
    "name:eng_x_preferred":[
        "Haylands"
    ],
    "wof:name":"Haylands",
    "wof:placetype":"locality"
},
  "geometry": {"coordinates":[139.62431000000001,-34.24029],"type":"Point"}
}