{
  "type": "Feature",
  "properties": {
    "gn:admin1_code":"5",
    "gn:admin2_code":"44210",
    "gn:asciiname":"Neeta",
    "gn:country_code":"AU",
    "gn:dem":20,
    "gn:feature_class":"P",
    "gn:feature_code":"PPL",
    "gn:name":"Neeta",
    "gn:population":0,
    "gn:timezone":"Australia/Adelaide",
    "iso:country":"AU",
    "wof:name":"Neeta",
    "wof:placetype":"locality"
},
  "geometry": {"coordinates":[139.31666999999999,-34.93333],"type":"Point"}
}