{
  "type": "Feature",
  "properties": {
    "gn:admin1_code":"2.0",
    "gn:admin2_code":"10800.0",
    "gn:asciiname":"Murrabang",
    "gn:country_code":"AU",
    "gn:dem":224,
    "gn:feature_class":"P",
    "gn:feature_code":"PPL",
    "gn:name":"Murrabang",
    "gn:population":0,
    "gn:timezone":"Australia/Sydney",
    "iso:country":"AU",
    "name:eng_x_preferred":[
        "Murrybong"
    ],
    "wof:name":"Murrabang",
    "wof:placetype":"locality"
},
  "geometry": {"coordinates":[146.39622,-33.72887],"type":"Point"}
}