{
  "type": "Feature",
  "properties": {
    "gn:admin1_code":"8",
    "gn:admin2_code":"58540",
    "gn:asciiname":"Carani",
    "gn:country_code":"AU",
    "gn:dem":272,
    "gn:feature_class":"P",
    "gn:feature_code":"PPL",
    "gn:name":"Carani",
    "gn:population":0,
    "gn:timezone":"Australia/Perth",
    "iso:country":"AU",
    "name:eng_x_preferred":[
        "Carani"
    ],
    "wof:name":"Carani",
    "wof:placetype":"locality"
},
  "geometry": {"coordinates":[116.40526,-30.99254],"type":"Point"}
}