{
  "type": "Feature",
  "properties": {
    "gn:admin1_code":"4",
    "gn:admin2_code":"33610",
    "gn:asciiname":"Yuraraba",
    "gn:country_code":"AU",
    "gn:dem":386,
    "gn:feature_class":"P",
    "gn:feature_code":"PPL",
    "gn:name":"Yuraraba",
    "gn:population":0,
    "gn:timezone":"Australia/Brisbane",
    "iso:country":"AU",
    "name:eng_x_preferred":[
        "Yuraraba"
    ],
    "wof:name":"Yuraraba",
    "wof:placetype":"locality"
},
  "geometry": {"coordinates":[151.39569,-28.3425],"type":"Point"}
}