{
  "type": "Feature",
  "properties": {
    "gn:country":"AU",
    "gn:fcode":"PPL",
    "gn:population":0,
    "iso:country":"AU",
    "name:eng_x_preferred":[
        "McKinlay"
    ],
    "name:fra_x_preferred":[
        "McKinlay"
    ],
    "name:nld_x_preferred":[
        "McKinlay"
    ],
    "qs_pg:aaroncc":"AU",
    "qs_pg:gn_country":"AU",
    "qs_pg:gn_fcode":"PPL",
    "qs_pg:gn_pop":0,
    "qs_pg:name":"McKinlay",
    "qs_pg:name_adm0":"Australia",
    "qs_pg:name_adm1":"Queensland",
    "qs_pg:photos":47,
    "qs_pg:photos_1k":10,
    "qs_pg:photos_9k":1,
    "qs_pg:photos_9r":2,
    "qs_pg:photos_all":47,
    "qs_pg:photos_sr":2,
    "qs_pg:pop_sr":4,
    "qs_pg:qs_pg_placetype":"locality",
    "qs_pg:qs_pg_placetype_gp":"Town",
    "qs_pg:woe_adm0":23424748,
    "woe:adm0_id":23424748,
    "woe:name_adm0":"Australia",
    "woe:name_adm1":"Queensland",
    "woe:placetype":"Town",
    "wof:name":"McKinlay",
    "wof:placetype":"locality"
},
  "geometry": {"coordinates":[141.30000000000001,-21.26667],"type":"Point"}
}