{
  "type": "Feature",
  "properties": {
    "gn:admin1_code":"3.0",
    "gn:admin2_code":"72330.0",
    "gn:asciiname":"Kulpitjata",
    "gn:country_code":"AU",
    "gn:dem":646,
    "gn:feature_class":"P",
    "gn:feature_code":"PPL",
    "gn:name":"Kulpitjata",
    "gn:population":0,
    "gn:timezone":"Australia/Darwin",
    "iso:country":"AU",
    "name:eng_x_preferred":[
        "Kulpitjata"
    ],
    "wof:name":"Kulpitjata",
    "wof:placetype":"locality"
},
  "geometry": {"coordinates":[131.01195000000001,-25.80348],"type":"Point"}
}