{
  "type": "Feature",
  "properties": {
    "gn:admin1_code":"5",
    "gn:admin2_code":"44210",
    "gn:asciiname":"Sanderston",
    "gn:country_code":"AU",
    "gn:dem":156,
    "gn:feature_class":"P",
    "gn:feature_code":"PPL",
    "gn:name":"Sanderston",
    "gn:population":0,
    "gn:timezone":"Australia/Adelaide",
    "iso:country":"AU",
    "wof:name":"Sanderston",
    "wof:placetype":"locality"
},
  "geometry": {"coordinates":[139.22193999999999,-34.75537],"type":"Point"}
}