{
  "type": "Feature",
  "properties": {
    "gn:country":"AU",
    "gn:fcode":"PPL",
    "gn:population":744,
    "iso:country":"AU",
    "name:bre_x_preferred":[
        "Boned Glengarry"
    ],
    "name:cat_x_preferred":[
        "Glengarry"
    ],
    "name:ceb_x_preferred":[
        "Glengarry"
    ],
    "name:deu_x_preferred":[
        "Glengarry"
    ],
    "name:eng_x_preferred":[
        "Glengarry"
    ],
    "name:fas_x_preferred":[
        "\u06af\u0644\u0646\u06af\u0627\u0631\u06cc"
    ],
    "name:fra_x_preferred":[
        "Glengarry"
    ],
    "name:fry_x_preferred":[
        "Glengarry"
    ],
    "name:jpn_x_preferred":[
        "\u30b0\u30ec\u30f3\u30ac\u30ea\u30fc\u5e3d"
    ],
    "name:kor_x_preferred":[
        "\uae00\ub80c\uac1c\ub9ac"
    ],
    "name:nld_x_preferred":[
        "Glengarry"
    ],
    "name:pol_x_preferred":[
        "Glengarry"
    ],
    "name:rus_x_preferred":[
        "\u0413\u043b\u0435\u043d\u0433\u0430\u0440\u0440\u0438"
    ],
    "name:swe_x_preferred":[
        "Glengarry"
    ],
    "qs_pg:aaroncc":"AU",
    "qs_pg:gn_country":"AU",
    "qs_pg:gn_fcode":"PPL",
    "qs_pg:gn_pop":744,
    "qs_pg:name":"Glengarry",
    "qs_pg:name_adm0":"Australia",
    "qs_pg:name_adm1":"Tasmania",
    "qs_pg:photos_9k":1,
    "qs_pg:photos_9r":1,
    "qs_pg:photos_all":11,
    "qs_pg:photos_sr":0,
    "qs_pg:pop_sr":2,
    "qs_pg:qs_pg_placetype":"locality",
    "qs_pg:qs_pg_placetype_gp":"Town",
    "qs_pg:woe_adm0":23424748,
    "woe:adm0_id":23424748,
    "woe:name_adm0":"Australia",
    "woe:name_adm1":"Tasmania",
    "woe:placetype":"Town",
    "wof:name":"Glengarry",
    "wof:placetype":"locality",
    "wof:population":744
},
  "geometry": {"coordinates":[146.88333,-41.35],"type":"Point"}
}