{
  "type": "Feature",
  "properties": {
    "gn:gn_country":"AU",
    "gn:gn_fcode":"PPL",
    "gn:gn_pop":744,
    "gn:population":744,
    "iso:country":"AU",
    "name:dut_x_preferred":[
        "Glengarry"
    ],
    "name:eng_x_preferred":[
        "Glengarry"
    ],
    "name:fre_x_preferred":[
        "Glengarry"
    ],
    "name:ger_x_preferred":[
        "Glengarry"
    ],
    "name:swe_x_preferred":[
        "Glengarry"
    ],
    "qs_pg:aaroncc":"AU",
    "qs_pg:gn_country":"AU",
    "qs_pg:gn_fcode":"PPL",
    "qs_pg:gn_pop":744,
    "qs_pg:name":"Glengarry",
    "qs_pg:name_adm0":"Australia",
    "qs_pg:name_adm1":"Tasmania",
    "qs_pg:photos_9k":1,
    "qs_pg:photos_9r":1,
    "qs_pg:photos_all":11,
    "qs_pg:photos_sr":0,
    "qs_pg:pop_sr":2,
    "qs_pg:qs_pg_placetype":"locality",
    "qs_pg:qs_pg_placetype_gp":"Town",
    "qs_pg:woe_adm0":23424748,
    "woe:adm0_id":23424748,
    "woe:name_adm0":"Australia",
    "woe:name_adm1":"Tasmania",
    "woe:placetype":"Town",
    "wof:name":"Glengarry",
    "wof:placetype":"locality",
    "wof:population":744
},
  "geometry": {"coordinates":[146.88333,-41.35],"type":"Point"}
}