{
  "type": "Feature",
  "properties": {
    "gn:admin1_code":"2.0",
    "gn:admin2_code":"12900.0",
    "gn:asciiname":"Daroobalgie",
    "gn:country_code":"AU",
    "gn:dem":250,
    "gn:feature_class":"P",
    "gn:feature_code":"PPL",
    "gn:name":"Daroobalgie",
    "gn:population":0,
    "gn:timezone":"Australia/Sydney",
    "iso:country":"AU",
    "wof:name":"Daroobalgie",
    "wof:placetype":"locality"
},
  "geometry": {"coordinates":[148.06666999999999,-33.33333],"type":"Point"}
}