{
  "type": "Feature",
  "properties": {
    "gn:admin1_code":"3.0",
    "gn:admin2_code":"73600.0",
    "gn:asciiname":"Badawarka",
    "gn:country_code":"AU",
    "gn:dem":21,
    "gn:feature_class":"P",
    "gn:feature_code":"PPL",
    "gn:name":"Badawarka",
    "gn:population":0,
    "gn:timezone":"Australia/Darwin",
    "iso:country":"AU",
    "wof:name":"Badawarka",
    "wof:placetype":"locality"
},
  "geometry": {"coordinates":[134.44631000000001,-14.69729],"type":"Point"}
}