{
  "type": "Feature",
  "properties": {
    "gn:admin1_code":"07",
    "gn:admin2_code":"22830.0",
    "gn:asciiname":"Dookie College",
    "gn:country_code":"AU",
    "gn:dem":156,
    "gn:feature_class":"P",
    "gn:feature_code":"PPL",
    "gn:name":"Dookie College",
    "gn:population":0,
    "gn:timezone":"Australia/Melbourne",
    "iso:country":"AU",
    "wof:name":"Dookie College",
    "wof:placetype":"locality"
},
  "geometry": {"coordinates":[145.70466999999999,-36.39569],"type":"Point"}
}