{
  "type": "Feature",
  "properties": {
    "gn:admin1_code":"7.0",
    "gn:admin2_code":"22110.0",
    "gn:asciiname":"Malinns",
    "gn:country_code":"AU",
    "gn:dem":319,
    "gn:feature_class":"P",
    "gn:feature_code":"PPL",
    "gn:name":"Malinns",
    "gn:population":0,
    "gn:timezone":"Australia/Melbourne",
    "iso:country":"AU",
    "name:eng_x_preferred":[
        "Malinns"
    ],
    "wof:name":"Malinns",
    "wof:placetype":"locality"
},
  "geometry": {"coordinates":[148.58926,-37.39903],"type":"Point"}
}