{
  "type": "Feature",
  "properties": {
    "gn:admin1_code":"2.0",
    "gn:admin2_code":"16400.0",
    "gn:asciiname":"Iona",
    "gn:country_code":"AU",
    "gn:dem":4,
    "gn:feature_class":"P",
    "gn:feature_code":"PPL",
    "gn:name":"Iona",
    "gn:population":0,
    "gn:timezone":"Australia/Sydney",
    "iso:country":"AU",
    "name:ang_x_preferred":[
        "Ii"
    ],
    "name:ara_x_preferred":[
        "\u0625\u064a\u0648\u0646\u0627"
    ],
    "name:ast_x_preferred":[
        "Iona"
    ],
    "name:aze_x_preferred":[
        "Ayona"
    ],
    "name:cat_x_preferred":[
        "Iona"
    ],
    "name:ceb_x_preferred":[
        "Iona"
    ],
    "name:ces_x_preferred":[
        "Iona"
    ],
    "name:cym_x_preferred":[
        "Iona"
    ],
    "name:dan_x_preferred":[
        "Iona"
    ],
    "name:deu_x_preferred":[
        "Iona"
    ],
    "name:ell_x_preferred":[
        "\u0391\u03ca\u03cc\u03bd\u03b1"
    ],
    "name:est_x_preferred":[
        "Iona"
    ],
    "name:eus_x_preferred":[
        "Iona"
    ],
    "name:fin_x_preferred":[
        "Iona"
    ],
    "name:fra_x_preferred":[
        "Iona"
    ],
    "name:glg_x_preferred":[
        "Iona"
    ],
    "name:hun_x_preferred":[
        "Iona"
    ],
    "name:ita_x_preferred":[
        "Iona"
    ],
    "name:jpn_x_preferred":[
        "\u30a2\u30a4\u30aa\u30ca\u5cf6"
    ],
    "name:lat_x_preferred":[
        "Iona"
    ],
    "name:nds_x_preferred":[
        "Iona"
    ],
    "name:nld_x_preferred":[
        "Iona"
    ],
    "name:nno_x_preferred":[
        "Iona"
    ],
    "name:nor_x_preferred":[
        "Iona"
    ],
    "name:pnb_x_preferred":[
        "\u0622\u0626\u06cc\u0627\u0648\u0646\u0627"
    ],
    "name:pol_x_preferred":[
        "Iona"
    ],
    "name:por_x_preferred":[
        "Iona"
    ],
    "name:rus_x_preferred":[
        "\u0410\u0439\u043e\u043d\u0430"
    ],
    "name:sco_x_preferred":[
        "Iona"
    ],
    "name:spa_x_preferred":[
        "Iona"
    ],
    "name:swe_x_preferred":[
        "Iona"
    ],
    "name:ukr_x_preferred":[
        "\u0419\u043e\u043d\u0430"
    ],
    "name:urd_x_preferred":[
        "\u0622\u0626\u0648\u0646\u0627"
    ],
    "name:vie_x_preferred":[
        "Iona"
    ],
    "name:zho_x_preferred":[
        "\u611b\u5967\u90a3\u5cf6"
    ],
    "wof:name":"Iona",
    "wof:placetype":"locality"
},
  "geometry": {"coordinates":[151.59999999999999,-32.66667],"type":"Point"}
}