{
  "type": "Feature",
  "properties": {
    "gn:admin1_code":"2.0",
    "gn:admin2_code":"16400.0",
    "gn:asciiname":"Iona",
    "gn:country_code":"AU",
    "gn:dem":4,
    "gn:feature_class":"P",
    "gn:feature_code":"PPL",
    "gn:name":"Iona",
    "gn:population":0,
    "gn:timezone":"Australia/Sydney",
    "iso:country":"AU",
    "wof:name":"Iona",
    "wof:placetype":"locality"
},
  "geometry": {"coordinates":[151.59999999999999,-32.66667],"type":"Point"}
}