{
  "type": "Feature",
  "properties": {
    "gn:gn_country":"AU",
    "gn:gn_fcode":"PPL",
    "gn:gn_pop":1292,
    "gn:population":1292,
    "iso:country":"AU",
    "name:eng_x_preferred":[
        "Kendenup"
    ],
    "name:fra_x_preferred":[
        "Kendenup"
    ],
    "name:nld_x_preferred":[
        "Kendenup"
    ],
    "name:swe_x_preferred":[
        "Kendenup"
    ],
    "qs_pg:aaroncc":"AU",
    "qs_pg:gn_country":"AU",
    "qs_pg:gn_fcode":"PPL",
    "qs_pg:gn_pop":1292,
    "qs_pg:name":"Kendenup",
    "qs_pg:name_adm0":"Australia",
    "qs_pg:name_adm1":"Western Australia",
    "qs_pg:photos_9k":1,
    "qs_pg:photos_9r":1,
    "qs_pg:photos_all":25,
    "qs_pg:photos_sr":0,
    "qs_pg:pop_sr":3,
    "qs_pg:qs_pg_placetype":"locality",
    "qs_pg:qs_pg_placetype_gp":"Town",
    "qs_pg:woe_adm0":23424748,
    "woe:adm0_id":23424748,
    "woe:name_adm0":"Australia",
    "woe:name_adm1":"Western Australia",
    "woe:placetype":"Town",
    "wof:name":"Kendenup",
    "wof:placetype":"locality",
    "wof:population":1292
},
  "geometry": {"coordinates":[117.65000000000001,-34.48333],"type":"Point"}
}