{
  "type": "Feature",
  "properties": {
    "gn:admin1_code":"08",
    "gn:admin2_code":"53990.0",
    "gn:asciiname":"Warawarrup",
    "gn:country_code":"AU",
    "gn:dem":39,
    "gn:feature_class":"P",
    "gn:feature_code":"PPL",
    "gn:name":"Warawarrup",
    "gn:population":0,
    "gn:timezone":"Australia/Perth",
    "iso:country":"AU",
    "wof:name":"Warawarrup",
    "wof:placetype":"locality"
},
  "geometry": {"coordinates":[115.90022999999999,-33.03892],"type":"Point"}
}