{
  "type": "Feature",
  "properties": {
    "gn:country":"AU",
    "gn:fcode":"PPL",
    "gn:population":0,
    "iso:country":"AU",
    "name:ast_x_preferred":[
        "Alectown"
    ],
    "name:eng_x_preferred":[
        "Alectown"
    ],
    "name:fas_x_preferred":[
        "\u0627\u0644\u06a9 \u062a\u0627\u0648\u0646"
    ],
    "name:fra_x_preferred":[
        "Alectown"
    ],
    "name:nld_x_preferred":[
        "Alectown"
    ],
    "name:por_x_preferred":[
        "Alectown"
    ],
    "name:swe_x_preferred":[
        "Alectown"
    ],
    "qs_pg:aaroncc":"AU",
    "qs_pg:gn_country":"AU",
    "qs_pg:gn_fcode":"PPL",
    "qs_pg:gn_pop":0,
    "qs_pg:name":"Alectown",
    "qs_pg:name_adm0":"Australia",
    "qs_pg:name_adm1":"New South Wales",
    "qs_pg:photos":23,
    "qs_pg:photos_1k":5,
    "qs_pg:photos_9k":1,
    "qs_pg:photos_9r":1,
    "qs_pg:photos_all":23,
    "qs_pg:photos_sr":1,
    "qs_pg:pop_sr":4,
    "qs_pg:qs_pg_placetype":"locality",
    "qs_pg:qs_pg_placetype_gp":"Town",
    "qs_pg:woe_adm0":23424748,
    "woe:adm0_id":23424748,
    "woe:name_adm0":"Australia",
    "woe:name_adm1":"New South Wales",
    "woe:placetype":"Town",
    "wof:name":"Alectown",
    "wof:placetype":"locality"
},
  "geometry": {"coordinates":[148.25,-32.93333],"type":"Point"}
}