{
  "type": "Feature",
  "properties": {
    "gn:admin1_code":"2.0",
    "gn:admin2_code":"11750.0",
    "gn:asciiname":"Balowra",
    "gn:country_code":"AU",
    "gn:dem":335,
    "gn:feature_class":"P",
    "gn:feature_code":"PPL",
    "gn:name":"Balowra",
    "gn:population":0,
    "gn:timezone":"Australia/Sydney",
    "iso:country":"AU",
    "name:eng_x_preferred":[
        "Balowra"
    ],
    "wof:name":"Balowra",
    "wof:placetype":"locality"
},
  "geometry": {"coordinates":[146.48818,-32.25409000000001],"type":"Point"}
}