{
  "type": "Feature",
  "properties": {
    "gn:admin1_code":"2.0",
    "gn:admin2_code":"15270.0",
    "gn:asciiname":"Puggoon",
    "gn:country_code":"AU",
    "gn:dem":449,
    "gn:feature_class":"P",
    "gn:feature_code":"PPL",
    "gn:name":"Puggoon",
    "gn:population":0,
    "gn:timezone":"Australia/Sydney",
    "iso:country":"AU",
    "wof:name":"Puggoon",
    "wof:placetype":"locality"
},
  "geometry": {"coordinates":[149.48333,-32.26667],"type":"Point"}
}