{
  "type": "Feature",
  "properties": {
    "gn:admin1_code":"4.0",
    "gn:admin2_code":"32450.0",
    "gn:asciiname":"Eureka",
    "gn:country_code":"AU",
    "gn:dem":421,
    "gn:feature_class":"P",
    "gn:feature_code":"PPL",
    "gn:name":"Eureka",
    "gn:population":0,
    "gn:timezone":"Australia/Brisbane",
    "iso:country":"AU",
    "name:eng_x_preferred":[
        "Eureka"
    ],
    "wof:name":"Eureka",
    "wof:placetype":"locality"
},
  "geometry": {"coordinates":[140.63127,-21.21571],"type":"Point"}
}