{
  "type": "Feature",
  "properties": {
    "gn:admin1_code":"7.0",
    "gn:admin2_code":"22980.0",
    "gn:asciiname":"Kenmare",
    "gn:country_code":"AU",
    "gn:dem":92,
    "gn:feature_class":"P",
    "gn:feature_code":"PPL",
    "gn:name":"Kenmare",
    "gn:population":0,
    "gn:timezone":"Australia/Melbourne",
    "iso:country":"AU",
    "name:cat_x_preferred":[
        "Kenmare"
    ],
    "name:ceb_x_preferred":[
        "Kenmare"
    ],
    "name:deu_x_preferred":[
        "Kenmare"
    ],
    "name:eus_x_preferred":[
        "Kenmare"
    ],
    "name:fas_x_preferred":[
        "\u06a9\u0646\u0645\u0627\u0631"
    ],
    "name:fra_x_preferred":[
        "Kenmare"
    ],
    "name:gle_x_preferred":[
        "An Neid\u00edn"
    ],
    "name:ita_x_preferred":[
        "Kenmare"
    ],
    "name:nld_x_preferred":[
        "Kenmare"
    ],
    "name:pol_x_preferred":[
        "Kenmare"
    ],
    "name:rus_x_preferred":[
        "\u041a\u0435\u043d\u043c\u044d\u0440"
    ],
    "name:spa_x_preferred":[
        "Kenmare"
    ],
    "wof:name":"Kenmare",
    "wof:placetype":"locality"
},
  "geometry": {"coordinates":[142.16666999999995,-35.91667],"type":"Point"}
}