{
  "type": "Feature",
  "properties": {
    "gn:admin1_code":"7.0",
    "gn:admin2_code":"22980.0",
    "gn:asciiname":"Kenmare",
    "gn:country_code":"AU",
    "gn:dem":92,
    "gn:feature_class":"P",
    "gn:feature_code":"PPL",
    "gn:name":"Kenmare",
    "gn:population":0,
    "gn:timezone":"Australia/Melbourne",
    "iso:country":"AU",
    "wof:name":"Kenmare",
    "wof:placetype":"locality"
},
  "geometry": {"coordinates":[142.16666999999995,-35.91667],"type":"Point"}
}