{
  "type": "Feature",
  "properties": {
    "gn:admin1_code":"7.0",
    "gn:admin2_code":"26430.0",
    "gn:asciiname":"Earlston",
    "gn:country_code":"AU",
    "gn:dem":137,
    "gn:feature_class":"P",
    "gn:feature_code":"PPL",
    "gn:name":"Earlston",
    "gn:population":0,
    "gn:timezone":"Australia/Melbourne",
    "iso:country":"AU",
    "wof:name":"Earlston",
    "wof:placetype":"locality"
},
  "geometry": {"coordinates":[145.66666999999995,-36.55],"type":"Point"}
}