{
  "type": "Feature",
  "properties": {
    "gn:admin1_code":"7.0",
    "gn:admin2_code":"26430.0",
    "gn:asciiname":"Earlston",
    "gn:country_code":"AU",
    "gn:dem":137,
    "gn:feature_class":"P",
    "gn:feature_code":"PPL",
    "gn:name":"Earlston",
    "gn:population":0,
    "gn:timezone":"Australia/Melbourne",
    "iso:country":"AU",
    "name:ceb_x_preferred":[
        "Earlston"
    ],
    "name:cym_x_preferred":[
        "Earlston"
    ],
    "name:deu_x_preferred":[
        "Earlston"
    ],
    "name:eus_x_preferred":[
        "Earlston"
    ],
    "name:fas_x_preferred":[
        "\u0627\u06cc\u0631\u0644\u0633\u062a\u0648\u0646"
    ],
    "name:fra_x_preferred":[
        "Earlston"
    ],
    "name:gla_x_preferred":[
        "D\u00f9n Airchill"
    ],
    "name:gle_x_preferred":[
        "D\u00fan Airchill"
    ],
    "name:ita_x_preferred":[
        "Earlston"
    ],
    "name:nno_x_preferred":[
        "Earlston"
    ],
    "name:nor_x_preferred":[
        "Earlston"
    ],
    "name:sco_x_preferred":[
        "Yerlston"
    ],
    "name:spa_x_preferred":[
        "Earlston"
    ],
    "name:swe_x_preferred":[
        "Earlston"
    ],
    "name:zho_x_preferred":[
        "\u5384\u5c14\u65af\u987f"
    ],
    "wof:name":"Earlston",
    "wof:placetype":"locality"
},
  "geometry": {"coordinates":[145.66666999999995,-36.55],"type":"Point"}
}