{
  "type": "Feature",
  "properties": {
    "gn:admin1_code":"7.0",
    "gn:admin2_code":"26610.0",
    "gn:asciiname":"Piangil West",
    "gn:country_code":"AU",
    "gn:dem":58,
    "gn:feature_class":"P",
    "gn:feature_code":"PPL",
    "gn:name":"Piangil West",
    "gn:population":0,
    "gn:timezone":"Australia/Melbourne",
    "iso:country":"AU",
    "wof:name":"Piangil West",
    "wof:placetype":"locality"
},
  "geometry": {"coordinates":[143.07662999999999,-35.05881],"type":"Point"}
}