{
  "type": "Feature",
  "properties": {
    "gn:admin1_code":"8",
    "gn:admin2_code":"53080",
    "gn:asciiname":"Princess Royal",
    "gn:country_code":"AU",
    "gn:dem":243,
    "gn:feature_class":"P",
    "gn:feature_code":"PPL",
    "gn:name":"Princess Royal",
    "gn:population":0,
    "gn:timezone":"Australia/Perth",
    "iso:country":"AU",
    "wof:name":"Princess Royal",
    "wof:placetype":"locality"
},
  "geometry": {"coordinates":[121.8087,-32.12121],"type":"Point"}
}