{
  "type": "Feature",
  "properties": {
    "gn:gn_country":"AU",
    "gn:gn_fcode":"PPL",
    "gn:gn_pop":181,
    "gn:population":181,
    "iso:country":"AU",
    "name:dut_x_preferred":[
        "Beacon"
    ],
    "name:eng_x_preferred":[
        "Beacon"
    ],
    "name:est_x_preferred":[
        "Beacon"
    ],
    "name:fre_x_preferred":[
        "Beacon"
    ],
    "name:sgs_x_preferred":[
        "Beacon"
    ],
    "name:swe_x_preferred":[
        "Beacon"
    ],
    "qs_pg:aaroncc":"AU",
    "qs_pg:gn_country":"AU",
    "qs_pg:gn_fcode":"PPL",
    "qs_pg:gn_pop":181,
    "qs_pg:name":"Beacon",
    "qs_pg:name_adm0":"Australia",
    "qs_pg:name_adm1":"Western Australia",
    "qs_pg:photos_9r":0,
    "qs_pg:photos_sr":0,
    "qs_pg:pop_sr":1,
    "qs_pg:qs_pg_placetype":"locality",
    "qs_pg:qs_pg_placetype_gp":"Town",
    "qs_pg:woe_adm0":23424748,
    "woe:adm0_id":23424748,
    "woe:name_adm0":"Australia",
    "woe:name_adm1":"Western Australia",
    "woe:placetype":"Town",
    "wof:name":"Beacon",
    "wof:placetype":"locality",
    "wof:population":181
},
  "geometry": {"coordinates":[117.84999999999999,-30.43333],"type":"Point"}
}