{
  "type": "Feature",
  "properties": {
    "gn:country":"AU",
    "gn:fcode":"PPL",
    "gn:population":181,
    "iso:country":"AU",
    "name:ara_x_preferred":[
        "\u0645\u0631\u0634\u062f \u0644\u0627\u0633\u0644\u0643\u064a"
    ],
    "name:cat_x_preferred":[
        "Balisa"
    ],
    "name:ceb_x_preferred":[
        "Beacon"
    ],
    "name:eng_x_preferred":[
        "Beacon"
    ],
    "name:est_x_preferred":[
        "Beacon"
    ],
    "name:est_x_variant":[
        "Tulepaak"
    ],
    "name:eus_x_preferred":[
        "Baliza"
    ],
    "name:fas_x_preferred":[
        "\u0628\u06cc\u06a9\u0646"
    ],
    "name:fra_x_preferred":[
        "Beacon"
    ],
    "name:fra_x_variant":[
        "Balise"
    ],
    "name:hin_x_preferred":[
        "\u0927\u094d\u092f\u093e\u0928\u093e\u0915\u0930\u094d\u0937\u0915 \u092c\u0924\u094d\u0924\u0940"
    ],
    "name:hye_x_preferred":[
        "\u053d\u0578\u0582\u0569\u0561\u0576\u0577\u0561\u0576"
    ],
    "name:ind_x_preferred":[
        "Sinyal pandu"
    ],
    "name:isl_x_preferred":[
        "Vegviti"
    ],
    "name:nld_x_preferred":[
        "Beacon"
    ],
    "name:nld_x_variant":[
        "Baken"
    ],
    "name:sgs_x_preferred":[
        "Beacon"
    ],
    "name:spa_x_preferred":[
        "Baliza"
    ],
    "name:swe_x_preferred":[
        "Beacon"
    ],
    "qs_pg:aaroncc":"AU",
    "qs_pg:gn_country":"AU",
    "qs_pg:gn_fcode":"PPL",
    "qs_pg:gn_pop":181,
    "qs_pg:name":"Beacon",
    "qs_pg:name_adm0":"Australia",
    "qs_pg:name_adm1":"Western Australia",
    "qs_pg:photos_9r":0,
    "qs_pg:photos_sr":0,
    "qs_pg:pop_sr":1,
    "qs_pg:qs_pg_placetype":"locality",
    "qs_pg:qs_pg_placetype_gp":"Town",
    "qs_pg:woe_adm0":23424748,
    "woe:adm0_id":23424748,
    "woe:name_adm0":"Australia",
    "woe:name_adm1":"Western Australia",
    "woe:placetype":"Town",
    "wof:name":"Beacon",
    "wof:placetype":"locality",
    "wof:population":160
},
  "geometry": {"coordinates":[117.84999999999999,-30.43333],"type":"Point"}
}