{
  "type": "Feature",
  "properties": {
    "iso:country":"AU",
    "name:eng_x_preferred":[
        "West Armidale"
    ],
    "name:eng_x_variant":[
        "W Armidale"
    ],
    "qs:gn_adm0_cc":"AU",
    "qs:gn_local":2177671,
    "qs:local_max":1039,
    "qs:local_sum":1851,
    "qs:localhoods":7,
    "qs:name":"West Armidale",
    "qs:name_adm0":"Australia",
    "qs:name_adm1":"New South Wales",
    "qs:name_adm2":"Armidale Dumaresq",
    "qs:name_local":"Armidale",
    "qs:photo_max":107,
    "qs:photo_sum":385,
    "qs:placetype":"Suburb",
    "qs:quad_count":25,
    "qs:woe_adm0":23424748,
    "qs:woe_adm1":2344700,
    "qs:woe_adm2":55863863,
    "qs:woe_lau":0,
    "qs:woe_local":1099969,
    "qs:woe_ver":"7.10.0",
    "wof:lang":[
        "eng"
    ],
    "wof:name":"West Armidale",
    "wof:placetype":"neighbourhood"
},
  "geometry": {"coordinates":[151.656904,-30.5045],"type":"Point"}
}