{
  "type": "Feature",
  "properties": {
    "gn:country":"AU",
    "gn:fcode":"PPL",
    "gn:population":3665,
    "iso:country":"AU",
    "name:ceb_x_preferred":[
        "Encounter Bay"
    ],
    "name:deu_x_preferred":[
        "Encounter Bay"
    ],
    "name:eng_x_preferred":[
        "Encounter Bay"
    ],
    "name:fra_x_preferred":[
        "Baie de la Rencontre"
    ],
    "name:jpn_x_preferred":[
        "\u30a8\u30f3\u30ab\u30a6\u30f3\u30bf\u30fc\u6e7e"
    ],
    "name:mlg_x_preferred":[
        "Encounter Bay"
    ],
    "name:nld_x_preferred":[
        "Encounter Bay"
    ],
    "name:spa_x_preferred":[
        "Bah\u00eda del Encuentro"
    ],
    "name:swe_x_preferred":[
        "Encounter Bay"
    ],
    "name:vie_x_preferred":[
        "V\u1ecbnh Encounter"
    ],
    "qs_pg:aaroncc":"AU",
    "qs_pg:gn_country":"AU",
    "qs_pg:gn_fcode":"PPL",
    "qs_pg:gn_pop":3665,
    "qs_pg:name":"Encounter Bay",
    "qs_pg:name_adm0":"Australia",
    "qs_pg:name_adm1":"South Australia",
    "qs_pg:photos":214,
    "qs_pg:photos_1k":43,
    "qs_pg:photos_9k":1,
    "qs_pg:photos_9r":4,
    "qs_pg:photos_all":214,
    "qs_pg:photos_sr":4,
    "qs_pg:pop_sr":4,
    "qs_pg:qs_pg_placetype":"neighbourhood",
    "qs_pg:qs_pg_placetype_gp":"Suburb",
    "qs_pg:woe_adm0":23424748,
    "woe:adm0_id":23424748,
    "woe:name_adm0":"Australia",
    "woe:name_adm1":"South Australia",
    "woe:placetype":"Suburb",
    "wof:name":"Encounter Bay",
    "wof:placetype":"neighbourhood",
    "wof:population":3665
},
  "geometry": {"coordinates":[138.59999999999999,-35.58333],"type":"Point"}
}