{
  "type": "Feature",
  "properties": {
    "iso:country":"AU",
    "name:azb_x_preferred":[
        "\u0631\u0627\u06a9\u0647\u0645\u067e\u062a\u0648\u0646"
    ],
    "name:bel_x_preferred":[
        "\u0420\u0430\u043a\u0433\u0435\u043c\u043f\u0442\u0430\u043d"
    ],
    "name:ceb_x_preferred":[
        "Rockhampton"
    ],
    "name:ces_x_preferred":[
        "Rockhampton"
    ],
    "name:ckb_x_preferred":[
        "\u0695\u0627\u06a9\u06be\u06d5\u0645\u067e\u062a\u0646"
    ],
    "name:cym_x_preferred":[
        "Rockhampton"
    ],
    "name:dan_x_preferred":[
        "Rockhampton"
    ],
    "name:deu_x_preferred":[
        "Rockhampton"
    ],
    "name:eng_x_preferred":[
        "Rockhampton"
    ],
    "name:fas_x_preferred":[
        "\u0631\u0627\u06a9\u0647\u0645\u067e\u062a\u0648\u0646"
    ],
    "name:fin_x_preferred":[
        "Rockhampton"
    ],
    "name:fra_x_preferred":[
        "Rockhampton"
    ],
    "name:gle_x_preferred":[
        "Rockhampton"
    ],
    "name:heb_x_preferred":[
        "\u05e8\u05d5\u05e7\u05d4\u05d0\u05de\u05e4\u05d8\u05d5\u05df"
    ],
    "name:hun_x_preferred":[
        "Rockhampton"
    ],
    "name:ita_x_preferred":[
        "Rockhampton"
    ],
    "name:kat_x_preferred":[
        "\u10e0\u10dd\u10d9\u10f0\u10d4\u10db\u10de\u10e2\u10dd\u10dc\u10d8"
    ],
    "name:mlg_x_preferred":[
        "Rockhampton"
    ],
    "name:nld_x_preferred":[
        "Rockhampton"
    ],
    "name:nor_x_preferred":[
        "Rockhampton"
    ],
    "name:pnb_x_preferred":[
        "\u0631\u0627\u06a9\u06c1\u06cc\u0645\u067e\u0679\u0648\u0646"
    ],
    "name:pol_x_preferred":[
        "Rockhampton"
    ],
    "name:por_x_preferred":[
        "Rockhampton"
    ],
    "name:ron_x_preferred":[
        "Rockhampton"
    ],
    "name:rus_x_preferred":[
        "\u0420\u043e\u043a\u0433\u0435\u043c\u043f\u0442\u043e\u043d"
    ],
    "name:san_x_preferred":[
        "\u0930\u094b\u0915\u0939\u093e\u092e\u094d\u092a\u091f\u0928"
    ],
    "name:spa_x_preferred":[
        "Rockhampton"
    ],
    "name:srp_x_preferred":[
        "\u0420\u043e\u043a\u0445\u0435\u043c\u043f\u0442\u043e\u043d"
    ],
    "name:swe_x_preferred":[
        "Rockhampton"
    ],
    "name:szl_x_preferred":[
        "Rockhampton"
    ],
    "name:ukr_x_preferred":[
        "\u0420\u043e\u043a\u0433\u0435\u043c\u043f\u0442\u043e\u043d"
    ],
    "name:urd_x_preferred":[
        "\u0631\u0627\u06a9\u06c1\u06cc\u0645\u067e\u0679\u0646"
    ],
    "name:vie_x_preferred":[
        "Rockhampton"
    ],
    "name:wuu_x_preferred":[
        "\u6d1b\u574e\u666e\u987f"
    ],
    "name:zho_x_preferred":[
        "\u6d1b\u574e\u666e\u9813"
    ],
    "wof:coterminous":[
        1376953285
    ],
    "wof:lang_x_official":[
        "eng"
    ],
    "wof:lang_x_spoken":[
        "eng"
    ],
    "wof:name":"Rockhampton",
    "wof:placetype":"locality"
},
  "geometry": {"coordinates":[150.50975500000001,-23.379739],"type":"Point"}
}