{
  "type": "Feature",
  "properties": {
    "iso:country":"AU",
    "name:eng_x_preferred":[
        "Rockhampton"
    ],
    "wof:coterminous":[
        1376953285
    ],
    "wof:lang_x_official":[
        "eng"
    ],
    "wof:lang_x_spoken":[
        "eng"
    ],
    "wof:name":"Rockhampton",
    "wof:placetype":"locality"
},
  "geometry": {"coordinates":[150.50975500000001,-23.379739],"type":"Point"}
}