{
  "type": "Feature",
  "properties": {
    "gn:gn_country":"AU",
    "gn:gn_fcode":"PPL",
    "gn:gn_pop":0,
    "gn:population":1662,
    "iso:country":"AU",
    "name:ceb_x_preferred":[
        "Belgrave South"
    ],
    "name:eng_x_preferred":[
        "Belgrave South"
    ],
    "name:swe_x_preferred":[
        "Belgrave South"
    ],
    "name:unk_x_variant":[
        "South Belgrave"
    ],
    "qs_pg:aaroncc":"AU",
    "qs_pg:gn_country":"AU",
    "qs_pg:gn_fcode":"PPL",
    "qs_pg:gn_pop":0,
    "qs_pg:name":"Belgrave South",
    "qs_pg:name_adm0":"Australia",
    "qs_pg:name_adm1":"Victoria",
    "qs_pg:photos":74,
    "qs_pg:photos_1k":15,
    "qs_pg:photos_9k":1,
    "qs_pg:photos_9r":2,
    "qs_pg:photos_all":74,
    "qs_pg:photos_sr":2,
    "qs_pg:pop_sr":0,
    "qs_pg:qs_pg_placetype":"locality",
    "qs_pg:qs_pg_placetype_gp":"Town",
    "qs_pg:woe_adm0":23424748,
    "woe:adm0_id":23424748,
    "woe:name_adm0":"Australia",
    "woe:name_adm1":"Victoria",
    "woe:placetype":"Town",
    "wof:name":"Belgrave South",
    "wof:placetype":"locality",
    "wof:population":1662
},
  "geometry": {"coordinates":[145.33332999999999,-37.93333],"type":"Point"}
}