{
  "type": "Feature",
  "properties": {
    "gn:admin1_code":"3.0",
    "gn:admin2_code":"74660.0",
    "gn:asciiname":"Barridjowkeng",
    "gn:country_code":"AU",
    "gn:dem":25,
    "gn:feature_class":"P",
    "gn:feature_code":"PPL",
    "gn:name":"Barridjowkeng",
    "gn:population":0,
    "gn:timezone":"Australia/Darwin",
    "iso:country":"AU",
    "wof:name":"Barridjowkeng",
    "wof:placetype":"locality"
},
  "geometry": {"coordinates":[134.17451,-12.34808],"type":"Point"}
}