{
  "type": "Feature",
  "properties": {
    "gn:admin1_code":"8.0",
    "gn:admin2_code":"53570.0",
    "gn:asciiname":"Narrow Neck",
    "gn:country_code":"AU",
    "gn:dem":1,
    "gn:feature_class":"P",
    "gn:feature_code":"PPL",
    "gn:name":"Narrow Neck",
    "gn:population":0,
    "gn:timezone":"Australia/Perth",
    "iso:country":"AU",
    "name:ceb_x_preferred":[
        "Narrow Neck"
    ],
    "name:deu_x_preferred":[
        "Narrow Neck"
    ],
    "name:eng_x_preferred":[
        "Narrow Neck"
    ],
    "name:swe_x_preferred":[
        "Narrow Neck"
    ],
    "wof:name":"Narrow Neck",
    "wof:placetype":"locality"
},
  "geometry": {"coordinates":[115.27173000000001,-30.90998],"type":"Point"}
}