{
  "type": "Feature",
  "properties": {
    "gn:gn_country":"AU",
    "gn:gn_fcode":"PPL",
    "gn:gn_pop":381,
    "gn:population":381,
    "iso:country":"AU",
    "name:cat_x_preferred":[
        "Leith"
    ],
    "name:ceb_x_preferred":[
        "Leith"
    ],
    "name:dan_x_preferred":[
        "Leith"
    ],
    "name:deu_x_preferred":[
        "Leith"
    ],
    "name:eng_x_preferred":[
        "Leith"
    ],
    "name:eus_x_preferred":[
        "Leith"
    ],
    "name:fin_x_preferred":[
        "Leith"
    ],
    "name:fra_x_preferred":[
        "Leith"
    ],
    "name:gla_x_preferred":[
        "L\u00ecte"
    ],
    "name:ita_x_preferred":[
        "Leith"
    ],
    "name:kaz_x_preferred":[
        "\u041b\u0438\u0442"
    ],
    "name:kor_x_preferred":[
        "\ub9ac\uc2a4"
    ],
    "name:nor_x_preferred":[
        "Leith"
    ],
    "name:pol_x_preferred":[
        "Leith"
    ],
    "name:ron_x_preferred":[
        "Leith"
    ],
    "name:rus_x_preferred":[
        "\u041b\u0438\u0442"
    ],
    "name:sco_x_preferred":[
        "Leith"
    ],
    "name:spa_x_preferred":[
        "Leith"
    ],
    "name:swe_x_preferred":[
        "Leith"
    ],
    "name:tha_x_preferred":[
        "\u0e25\u0e35\u0e18"
    ],
    "name:zho_x_preferred":[
        "\u5229\u65af"
    ],
    "qs_pg:aaroncc":"AU",
    "qs_pg:gn_country":"AU",
    "qs_pg:gn_fcode":"PPL",
    "qs_pg:gn_pop":381,
    "qs_pg:name":"Leith",
    "qs_pg:name_adm0":"Australia",
    "qs_pg:name_adm1":"Tasmania",
    "qs_pg:photos_9k":1,
    "qs_pg:photos_9r":1,
    "qs_pg:photos_all":15,
    "qs_pg:photos_sr":0,
    "qs_pg:pop_sr":2,
    "qs_pg:qs_pg_placetype":"locality",
    "qs_pg:qs_pg_placetype_gp":"Town",
    "qs_pg:woe_adm0":23424748,
    "woe:adm0_id":23424748,
    "woe:name_adm0":"Australia",
    "woe:name_adm1":"Tasmania",
    "woe:placetype":"Town",
    "wof:name":"Leith",
    "wof:placetype":"locality",
    "wof:population":381
},
  "geometry": {"coordinates":[146.26667,-41.16667],"type":"Point"}
}