{
  "type": "Feature",
  "properties": {
    "iso:country":"AU",
    "name:eng_x_preferred":[
        "Middleton Beach"
    ],
    "name:fra_x_preferred":[
        "Middleton Beach"
    ],
    "qs:gn_adm0_cc":"AU",
    "qs:gn_fcode":"PPLX",
    "qs:gn_local":2077963,
    "qs:gn_nam_loc":"Albany, Albany, Western Australia, AU",
    "qs:gn_namadm1":"08",
    "qs:gn_name":"Middleton Beach",
    "qs:local_max":1022,
    "qs:local_sum":2469,
    "qs:localhoods":10,
    "qs:name":"Middleton Beach",
    "qs:name_adm0":"Australia",
    "qs:name_adm1":"Western Australia",
    "qs:name_adm2":"Albany",
    "qs:name_local":"Albany",
    "qs:photo_max":30,
    "qs:photo_sum":255,
    "qs:placetype":"Suburb",
    "qs:quad_count":20,
    "qs:woe_adm0":23424748,
    "qs:woe_adm1":2344706,
    "qs:woe_adm2":55864168,
    "qs:woe_lau":0,
    "qs:woe_local":1099825,
    "qs:woe_ver":"7.10.0",
    "wof:name":"Middleton Beach",
    "wof:placetype":"neighbourhood"
},
  "geometry": {"coordinates":[117.919769,-35.029866],"type":"Point"}
}