{
  "type": "Feature",
  "properties": {
    "gn:admin1_code":"7",
    "gn:admin2_code":"25150",
    "gn:asciiname":"Scotsburn",
    "gn:country_code":"AU",
    "gn:dem":490,
    "gn:feature_class":"P",
    "gn:feature_code":"PPL",
    "gn:name":"Scotsburn",
    "gn:population":0,
    "gn:timezone":"Australia/Melbourne",
    "iso:country":"AU",
    "wof:name":"Scotsburn",
    "wof:placetype":"locality"
},
  "geometry": {"coordinates":[143.93333000000001,-37.66667],"type":"Point"}
}