{
  "type": "Feature",
  "properties": {
    "gn:admin1_code":"2.0",
    "gn:admin2_code":"10300.0",
    "gn:asciiname":"Manfred",
    "gn:country_code":"AU",
    "gn:dem":79,
    "gn:feature_class":"P",
    "gn:feature_code":"PPL",
    "gn:name":"Manfred",
    "gn:population":0,
    "gn:timezone":"Australia/Sydney",
    "iso:country":"AU",
    "name:deu_x_preferred":[
        "Manfred"
    ],
    "name:eng_x_preferred":[
        "Manfred"
    ],
    "name:epo_x_preferred":[
        "Manfred"
    ],
    "name:fas_x_preferred":[
        "\u0645\u0627\u0646\u0641\u0631\u062f"
    ],
    "name:fra_x_preferred":[
        "Manfred"
    ],
    "name:ita_x_preferred":[
        "Manfred"
    ],
    "name:jpn_x_preferred":[
        "\u30de\u30f3\u30d5\u30ec\u30c3\u30c9"
    ],
    "name:por_x_preferred":[
        "Manfredo"
    ],
    "name:rus_x_preferred":[
        "\u041c\u0430\u043d\u0444\u0440\u0435\u0434"
    ],
    "name:spa_x_preferred":[
        "Manfredo"
    ],
    "name:ukr_x_preferred":[
        "\u041c\u0430\u043d\u0444\u0440\u0435\u0434"
    ],
    "wof:name":"Manfred",
    "wof:placetype":"locality"
},
  "geometry": {"coordinates":[143.78011999999995,-33.31045],"type":"Point"}
}