{
  "type": "Feature",
  "properties": {
    "gn:admin1_code":"2.0",
    "gn:admin2_code":"10300.0",
    "gn:asciiname":"Manfred",
    "gn:country_code":"AU",
    "gn:dem":79,
    "gn:feature_class":"P",
    "gn:feature_code":"PPL",
    "gn:name":"Manfred",
    "gn:population":0,
    "gn:timezone":"Australia/Sydney",
    "iso:country":"AU",
    "name:eng_x_preferred":[
        "Manfred"
    ],
    "wof:name":"Manfred",
    "wof:placetype":"locality"
},
  "geometry": {"coordinates":[143.78011999999995,-33.31045],"type":"Point"}
}