{
  "type": "Feature",
  "properties": {
    "gn:admin1_code":"2.0",
    "gn:admin2_code":"11800.0",
    "gn:asciiname":"Timmsvale",
    "gn:country_code":"AU",
    "gn:dem":544,
    "gn:feature_class":"P",
    "gn:feature_code":"PPL",
    "gn:name":"Timmsvale",
    "gn:population":0,
    "gn:timezone":"Australia/Sydney",
    "iso:country":"AU",
    "name:eng_x_preferred":[
        "Timmsvale"
    ],
    "wof:name":"Timmsvale",
    "wof:placetype":"locality"
},
  "geometry": {"coordinates":[152.86947000000001,-30.22143],"type":"Point"}
}