{
  "type": "Feature",
  "properties": {
    "gn:admin1_code":"7",
    "gn:admin2_code":"22490",
    "gn:asciiname":"Woodbourne",
    "gn:country_code":"AU",
    "gn:dem":340,
    "gn:feature_class":"P",
    "gn:feature_code":"PPL",
    "gn:name":"Woodbourne",
    "gn:population":0,
    "gn:timezone":"Australia/Melbourne",
    "iso:country":"AU",
    "name:ceb_x_preferred":[
        "Woodbourne"
    ],
    "name:deu_x_preferred":[
        "Woodbourne"
    ],
    "name:spa_x_preferred":[
        "Woodbourne"
    ],
    "wof:name":"Woodbourne",
    "wof:placetype":"locality"
},
  "geometry": {"coordinates":[143.98333,-37.85],"type":"Point"}
}