{
  "type": "Feature",
  "properties": {
    "gn:admin1_code":"4.0",
    "gn:admin2_code":"32500.0",
    "gn:asciiname":"Merapah",
    "gn:country_code":"AU",
    "gn:dem":80,
    "gn:feature_class":"P",
    "gn:feature_code":"PPL",
    "gn:name":"Merapah",
    "gn:population":0,
    "gn:timezone":"Australia/Brisbane",
    "iso:country":"AU",
    "wof:name":"Merapah",
    "wof:placetype":"locality"
},
  "geometry": {"coordinates":[142.41261,-13.71918],"type":"Point"}
}