{
  "type": "Feature",
  "properties": {
    "gn:gn_country":"AU",
    "gn:gn_fcode":"PPL",
    "gn:gn_pop":79,
    "gn:population":79,
    "iso:country":"AU",
    "name:deu_x_preferred":[
        "Peak Hill"
    ],
    "name:eng_x_preferred":[
        "Peak Hill"
    ],
    "name:nld_x_preferred":[
        "Peak Hill"
    ],
    "qs_pg:aaroncc":"AU",
    "qs_pg:gn_country":"AU",
    "qs_pg:gn_fcode":"PPL",
    "qs_pg:gn_pop":79,
    "qs_pg:name":"Peak Hill",
    "qs_pg:name_adm0":"Australia",
    "qs_pg:name_adm1":"Western Australia",
    "qs_pg:photos_9r":0,
    "qs_pg:photos_sr":0,
    "qs_pg:pop_sr":1,
    "qs_pg:qs_pg_placetype":"locality",
    "qs_pg:qs_pg_placetype_gp":"Town",
    "qs_pg:woe_adm0":23424748,
    "woe:adm0_id":23424748,
    "woe:name_adm0":"Australia",
    "woe:name_adm1":"Western Australia",
    "woe:placetype":"Town",
    "wof:name":"Peak Hill",
    "wof:placetype":"locality",
    "wof:population":79
},
  "geometry": {"coordinates":[118.71666999999999,-25.63333],"type":"Point"}
}