{
  "type": "Feature",
  "properties": {
    "gn:gn_country":"AU",
    "gn:gn_fcode":"PPL",
    "gn:gn_pop":359,
    "gn:population":359,
    "iso:country":"AU",
    "name:dut_x_preferred":[
        "Wannamal"
    ],
    "name:eng_x_preferred":[
        "Wannamal"
    ],
    "name:sgs_x_preferred":[
        "Wannamal"
    ],
    "name:swe_x_preferred":[
        "Wannamal"
    ],
    "qs_pg:aaroncc":"AU",
    "qs_pg:gn_country":"AU",
    "qs_pg:gn_fcode":"PPL",
    "qs_pg:gn_pop":359,
    "qs_pg:name":"Wannamal",
    "qs_pg:photos_9r":0,
    "qs_pg:photos_sr":0,
    "qs_pg:pop_sr":2,
    "qs_pg:qs_pg_placetype":"locality",
    "wof:name":"Wannamal",
    "wof:placetype":"locality",
    "wof:population":359
},
  "geometry": {"coordinates":[116.05,-31.16667],"type":"Point"}
}