{
  "type": "Feature",
  "properties": {
    "gn:country":"AU",
    "gn:fcode":"PPL",
    "gn:population":0,
    "iso:country":"AU",
    "name:als_x_preferred":[
        "Johanna"
    ],
    "name:ast_x_preferred":[
        "Johanna"
    ],
    "name:bre_x_preferred":[
        "Johanna"
    ],
    "name:deu_x_preferred":[
        "Johanna"
    ],
    "name:eng_x_preferred":[
        "Johanna"
    ],
    "name:est_x_preferred":[
        "Johanna"
    ],
    "name:fin_x_preferred":[
        "Johanna"
    ],
    "name:fra_x_preferred":[
        "Johanna"
    ],
    "name:hun_x_preferred":[
        "Johanna"
    ],
    "name:nld_x_preferred":[
        "Johanna"
    ],
    "name:nno_x_preferred":[
        "Johanna"
    ],
    "name:nor_x_preferred":[
        "Johanna"
    ],
    "name:rus_x_preferred":[
        "\u0418\u043e\u0430\u043d\u043d\u0430"
    ],
    "name:swe_x_preferred":[
        "Johanna"
    ],
    "name:und_x_variant":[
        "Johaana"
    ],
    "qs_pg:aaroncc":"AU",
    "qs_pg:gn_country":"AU",
    "qs_pg:gn_fcode":"PPL",
    "qs_pg:gn_pop":0,
    "qs_pg:name":"Johanna",
    "qs_pg:name_adm0":"Australia",
    "qs_pg:name_adm1":"Victoria",
    "qs_pg:photos":200,
    "qs_pg:photos_1k":41,
    "qs_pg:photos_9k":1,
    "qs_pg:photos_9r":4,
    "qs_pg:photos_all":200,
    "qs_pg:photos_sr":4,
    "qs_pg:pop_sr":0,
    "qs_pg:qs_pg_placetype":"locality",
    "qs_pg:qs_pg_placetype_gp":"Town",
    "qs_pg:woe_adm0":23424748,
    "woe:adm0_id":23424748,
    "woe:name_adm0":"Australia",
    "woe:name_adm1":"Victoria",
    "woe:placetype":"Town",
    "wof:name":"Johanna",
    "wof:placetype":"locality"
},
  "geometry": {"coordinates":[143.36667,-38.75],"type":"Point"}
}