{
  "type": "Feature",
  "properties": {
    "gn:gn_country":"AU",
    "gn:gn_fcode":"PPL",
    "gn:gn_pop":265,
    "gn:population":265,
    "iso:country":"AU",
    "name:ceb_x_preferred":[
        "Bellingham"
    ],
    "name:eng_x_preferred":[
        "Bellingham"
    ],
    "name:fas_x_preferred":[
        "\u0628\u0644\u06cc\u0646\u06af\u0627\u0645"
    ],
    "name:fra_x_preferred":[
        "Bellingham"
    ],
    "name:nld_x_preferred":[
        "Bellingham"
    ],
    "name:swe_x_preferred":[
        "Bellingham"
    ],
    "qs_pg:aaroncc":"AU",
    "qs_pg:gn_country":"AU",
    "qs_pg:gn_fcode":"PPL",
    "qs_pg:gn_pop":265,
    "qs_pg:name":"Bellingham",
    "qs_pg:name_adm0":"Australia",
    "qs_pg:name_adm1":"Tasmania",
    "qs_pg:photos_9k":1,
    "qs_pg:photos_9r":1,
    "qs_pg:photos_all":14,
    "qs_pg:photos_sr":0,
    "qs_pg:pop_sr":2,
    "qs_pg:qs_pg_placetype":"locality",
    "qs_pg:qs_pg_placetype_gp":"Town",
    "qs_pg:woe_adm0":23424748,
    "woe:adm0_id":23424748,
    "woe:name_adm0":"Australia",
    "woe:name_adm1":"Tasmania",
    "woe:placetype":"Town",
    "wof:name":"Bellingham",
    "wof:placetype":"locality",
    "wof:population":60
},
  "geometry": {"coordinates":[147.16667000000001,-41.01667],"type":"Point"}
}