{
  "type": "Feature",
  "properties": {
    "gn:admin1_code":"2.0",
    "gn:admin2_code":"13350.0",
    "gn:asciiname":"Killabakh Creek",
    "gn:cc2":"AU",
    "gn:country_code":"AU",
    "gn:dem":72,
    "gn:feature_class":"P",
    "gn:feature_code":"PPL",
    "gn:name":"Killabakh Creek",
    "gn:population":0,
    "gn:timezone":"Australia/Sydney",
    "iso:country":"AU",
    "name:und_x_variant":[
        "Killabakh",
        "Killabakh Creek"
    ],
    "wof:name":"Killabakh Creek",
    "wof:placetype":"locality"
},
  "geometry": {"coordinates":[152.40000000000001,-31.73333],"type":"Point"}
}