{
  "type": "Feature",
  "properties": {
    "gn:admin1_code":"4.0",
    "gn:admin2_code":"32500.0",
    "gn:asciiname":"Lightning Yard",
    "gn:country_code":"AU",
    "gn:dem":69,
    "gn:feature_class":"P",
    "gn:feature_code":"PPL",
    "gn:name":"Lightning Yard",
    "gn:population":0,
    "gn:timezone":"Australia/Brisbane",
    "iso:country":"AU",
    "wof:name":"Lightning Yard",
    "wof:placetype":"locality"
},
  "geometry": {"coordinates":[142.79089999999999,-15.87815],"type":"Point"}
}