{
  "type": "Feature",
  "properties": {
    "iso:country":"AU",
    "name:eng_x_preferred":[
        "Campbelltown North"
    ],
    "qs:gn_adm0_cc":"AU",
    "qs:gn_fcode":"PPL",
    "qs:gn_local":2147714,
    "qs:gn_namadm1":"02",
    "qs:gn_name":"Campbelltown South",
    "qs:local_max":35533,
    "qs:local_sum":687549,
    "qs:localhoods":516,
    "qs:name":"Campbelltown North",
    "qs:name_adm0":"Australia",
    "qs:name_adm1":"New South Wales",
    "qs:name_adm2":"City of Campbelltown",
    "qs:name_local":"Sydney",
    "qs:photo_max":10,
    "qs:photo_sum":30,
    "qs:placetype":"Suburb",
    "qs:quad_count":6,
    "qs:woe_adm0":23424748,
    "qs:woe_adm1":2344700,
    "qs:woe_adm2":55863846,
    "qs:woe_lau":0,
    "qs:woe_local":1105779,
    "qs:woe_ver":"7.10.0",
    "wof:lang":[
        "eng"
    ],
    "wof:name":"Campbelltown North",
    "wof:placetype":"neighbourhood"
},
  "geometry": {"coordinates":[150.82406599999999,-34.059623],"type":"Point"}
}