{
  "type": "Feature",
  "properties": {
    "gn:admin1_code":"5.0",
    "gn:asciiname":"Wilkatana",
    "gn:country_code":"AU",
    "gn:dem":86,
    "gn:feature_class":"P",
    "gn:feature_code":"PPL",
    "gn:name":"Wilkatana",
    "gn:population":0,
    "gn:timezone":"Australia/Adelaide",
    "iso:country":"AU",
    "name:eng_x_preferred":[
        "Wilkatana"
    ],
    "wof:name":"Wilkatana",
    "wof:placetype":"locality"
},
  "geometry": {"coordinates":[137.89245,-32.12838],"type":"Point"}
}