{
  "type": "Feature",
  "properties": {
    "gn:admin1_code":"3.0",
    "gn:admin2_code":"70620.0",
    "gn:asciiname":"Atula",
    "gn:country_code":"AU",
    "gn:dem":276,
    "gn:feature_class":"P",
    "gn:feature_code":"PPL",
    "gn:name":"Atula",
    "gn:population":0,
    "gn:timezone":"Australia/Darwin",
    "iso:country":"AU",
    "name:eng_x_preferred":[
        "Atula"
    ],
    "wof:name":"Atula",
    "wof:placetype":"locality"
},
  "geometry": {"coordinates":[136.38775000000001,-23.25897],"type":"Point"}
}