{
  "type": "Feature",
  "properties": {
    "gn:country":"AU",
    "gn:fcode":"PPLX",
    "gn:population":0,
    "iso:country":"AU",
    "name:dan_x_preferred":[
        "Kangaroo Ground"
    ],
    "name:deu_x_preferred":[
        "Kangaroo Ground"
    ],
    "name:eng_x_preferred":[
        "Kangaroo Ground"
    ],
    "name:fra_x_preferred":[
        "Kangaroo Ground"
    ],
    "name:nld_x_preferred":[
        "Kangaroo Ground"
    ],
    "qs_pg:aaroncc":"AU",
    "qs_pg:gn_country":"AU",
    "qs_pg:gn_fcode":"PPLX",
    "qs_pg:gn_pop":0,
    "qs_pg:name":"Kangaroo Ground",
    "qs_pg:name_adm0":"Australia",
    "qs_pg:name_adm1":"Victoria",
    "qs_pg:photos":119,
    "qs_pg:photos_1k":24,
    "qs_pg:photos_9k":1,
    "qs_pg:photos_9r":3,
    "qs_pg:photos_all":119,
    "qs_pg:photos_sr":3,
    "qs_pg:pop_sr":0,
    "qs_pg:qs_pg_placetype":"locality_gp_neighbourhood_gn",
    "qs_pg:qs_pg_placetype_gp":"Town",
    "qs_pg:woe_adm0":23424748,
    "woe:adm0_id":23424748,
    "woe:name_adm0":"Australia",
    "woe:name_adm1":"Victoria",
    "woe:placetype":"Town",
    "wof:name":"Kangaroo Ground",
    "wof:placetype":"locality",
    "wof:population":1095
},
  "geometry": {"coordinates":[145.23169999999999,-37.68919],"type":"Point"}
}