{
  "type": "Feature",
  "properties": {
    "gn:admin1_code":"7",
    "gn:admin2_code":"24900",
    "gn:asciiname":"Ulupna",
    "gn:country_code":"AU",
    "gn:dem":110,
    "gn:feature_class":"P",
    "gn:feature_code":"PPL",
    "gn:name":"Ulupna",
    "gn:population":0,
    "gn:timezone":"Australia/Melbourne",
    "iso:country":"AU",
    "wof:name":"Ulupna",
    "wof:placetype":"locality"
},
  "geometry": {"coordinates":[145.40000000000001,-35.88333],"type":"Point"}
}