{
  "type": "Feature",
  "properties": {
    "iso:country":"AU",
    "name:ben_x_preferred":[
        "\u09b8\u09c7\u09a8\u09cd\u099f\u09cd\u09b0\u09be\u09b2 \u0995\u09cb\u09b8\u09cd\u099f"
    ],
    "name:deu_x_preferred":[
        "Central Coast"
    ],
    "name:ell_x_preferred":[
        "\u03a3\u03ad\u03bd\u03c4\u03c1\u03b1\u03bb \u039a\u03cc\u03bf\u03c5\u03c3\u03c4"
    ],
    "name:eng_x_preferred":[
        "Central Coast"
    ],
    "name:fra_x_preferred":[
        "C\u00f4te centrale"
    ],
    "name:heb_x_preferred":[
        "\u05e1\u05e0\u05d8\u05e8\u05dc \u05e7\u05d5\u05e1\u05d8"
    ],
    "name:hin_x_preferred":[
        "\u0938\u0947\u0902\u091f\u094d\u0930\u0932 \u0915\u094b\u0938\u094d\u091f"
    ],
    "name:hun_x_preferred":[
        "Central Coast"
    ],
    "name:ita_x_preferred":[
        "Central Coast"
    ],
    "name:nld_x_preferred":[
        "Central Coast"
    ],
    "name:pol_x_preferred":[
        "Wybrze\u017ce \u015brodkowe"
    ],
    "name:rus_x_preferred":[
        "\u0421\u0435\u043d\u0442\u0440\u0430\u043b-\u041a\u043e\u0441\u0442"
    ],
    "name:spa_x_preferred":[
        "Costa Central"
    ],
    "name:swe_x_preferred":[
        "Central Coast"
    ],
    "name:tur_x_preferred":[
        "Central Coast"
    ],
    "name:ukr_x_preferred":[
        "\u0421\u0435\u043d\u0442\u0440\u0430\u043b-\u041a\u043e\u0441\u0442"
    ],
    "name:urd_x_preferred":[
        "\u0633\u06cc\u0646\u0679\u0631\u0644 \u06a9\u0648\u0633\u0679"
    ],
    "name:vie_x_preferred":[
        "Duy\u00ean h\u1ea3i mi\u1ec1n Trung"
    ],
    "wof:coterminous":[
        1376953297
    ],
    "wof:lang_x_official":[
        "eng"
    ],
    "wof:lang_x_spoken":[
        "eng"
    ],
    "wof:name":"Central Coast",
    "wof:placetype":"locality"
},
  "geometry": {"coordinates":[151.445776,-33.427354],"type":"Point"}
}