{
  "type": "Feature",
  "properties": {
    "iso:country":"AU",
    "name:eng_x_preferred":[
        "Central Coast"
    ],
    "wof:coterminous":[
        1376953297
    ],
    "wof:lang_x_official":[
        "eng"
    ],
    "wof:lang_x_spoken":[
        "eng"
    ],
    "wof:name":"Central Coast",
    "wof:placetype":"locality"
},
  "geometry": {"coordinates":[151.445776,-33.427354],"type":"Point"}
}