{
  "type": "Feature",
  "properties": {
    "gn:admin1_code":"4.0",
    "gn:admin2_code":"34710.0",
    "gn:asciiname":"Glenaras",
    "gn:country_code":"AU",
    "gn:dem":234,
    "gn:feature_class":"P",
    "gn:feature_code":"PPL",
    "gn:name":"Glenaras",
    "gn:population":0,
    "gn:timezone":"Australia/Brisbane",
    "iso:country":"AU",
    "name:eng_x_preferred":[
        "Glenaras"
    ],
    "wof:name":"Glenaras",
    "wof:placetype":"locality"
},
  "geometry": {"coordinates":[144.70155,-23.05499],"type":"Point"}
}