{
  "type": "Feature",
  "properties": {
    "iso:country":"AU",
    "name:eng_x_preferred":[
        "Goulburn North"
    ],
    "name:unk_x_variant":[
        "Goulburn North"
    ],
    "qs:gn_adm0_cc":"AU",
    "qs:gn_local":2164837,
    "qs:gn_nam_loc":"Goulburn, Goulburn Mulwaree, New South Wales, AU",
    "qs:gn_namadm1":"02",
    "qs:local_max":477,
    "qs:local_sum":662,
    "qs:localhoods":3,
    "qs:name":"Goulburn North",
    "qs:name_adm0":"Australia",
    "qs:name_adm1":"New South Wales",
    "qs:name_adm2":"Goulburn Mulwaree",
    "qs:name_local":"Goulburn",
    "qs:photo_max":20,
    "qs:photo_sum":69,
    "qs:placetype":"Suburb",
    "qs:quad_count":16,
    "qs:woe_adm0":23424748,
    "qs:woe_adm1":2344700,
    "qs:woe_adm2":55863825,
    "qs:woe_lau":0,
    "qs:woe_local":1102397,
    "qs:woe_ver":"7.10.0",
    "wof:lang":[
        "eng"
    ],
    "wof:name":"Goulburn North",
    "wof:placetype":"neighbourhood"
},
  "geometry": {"coordinates":[149.73748399999999,-34.749952],"type":"Point"}
}