{
  "type": "Feature",
  "properties": {
    "gn:admin1_code":"3.0",
    "gn:admin2_code":"70620.0",
    "gn:asciiname":"Puyurru",
    "gn:country_code":"AU",
    "gn:dem":435,
    "gn:feature_class":"P",
    "gn:feature_code":"PPL",
    "gn:name":"Puyurru",
    "gn:population":0,
    "gn:timezone":"Australia/Darwin",
    "iso:country":"AU",
    "wof:name":"Puyurru",
    "wof:placetype":"locality"
},
  "geometry": {"coordinates":[130.81288999999998,-21.33172],"type":"Point"}
}