{
  "type": "Feature",
  "properties": {
    "gn:country":"AU",
    "gn:fcode":"PPL",
    "gn:population":0,
    "iso:country":"AU",
    "name:eng_x_preferred":[
        "Uriarra"
    ],
    "name:eng_x_variant":[
        "Uriarra Village"
    ],
    "name:fra_x_preferred":[
        "Uriarra"
    ],
    "name:fra_x_variant":[
        "Uriarra Village"
    ],
    "name:jpn_x_preferred":[
        "\u30a6\u30ea\u30a2\u30e9\u30d3\u30ec\u30c3\u30b8"
    ],
    "name:nld_x_preferred":[
        "Uriarra"
    ],
    "name:nld_x_variant":[
        "Uriarra Village"
    ],
    "name:rus_x_preferred":[
        "\u0423\u0440\u0438\u0430\u0440\u0440\u0430"
    ],
    "qs_pg:aaroncc":"AU",
    "qs_pg:gn_country":"AU",
    "qs_pg:gn_fcode":"PPL",
    "qs_pg:gn_pop":0,
    "qs_pg:name":"Uriarra",
    "qs_pg:name_adm0":"Australia",
    "qs_pg:name_adm1":"New South Wales",
    "qs_pg:photos":82,
    "qs_pg:photos_1k":17,
    "qs_pg:photos_9k":1,
    "qs_pg:photos_9r":3,
    "qs_pg:photos_all":82,
    "qs_pg:photos_sr":3,
    "qs_pg:pop_sr":0,
    "qs_pg:qs_pg_placetype":"locality",
    "qs_pg:qs_pg_placetype_gp":"Town",
    "qs_pg:woe_adm0":23424748,
    "woe:adm0_id":23424748,
    "woe:name_adm0":"Australia",
    "woe:name_adm1":"New South Wales",
    "woe:placetype":"Town",
    "wof:name":"Uriarra",
    "wof:placetype":"locality"
},
  "geometry": {"coordinates":[148.93333000000001,-35.23333],"type":"Point"}
}