{
  "type": "Feature",
  "properties": {
    "gn:admin1_code":"2.0",
    "gn:admin2_code":"10550.0",
    "gn:asciiname":"Koorings",
    "gn:country_code":"AU",
    "gn:dem":240,
    "gn:feature_class":"P",
    "gn:feature_code":"PPL",
    "gn:name":"Koorings",
    "gn:population":0,
    "gn:timezone":"Australia/Sydney",
    "iso:country":"AU",
    "name:eng_x_preferred":[
        "Koorings"
    ],
    "wof:name":"Koorings",
    "wof:placetype":"locality"
},
  "geometry": {"coordinates":[149.7269,-36.31898],"type":"Point"}
}