{
  "type": "Feature",
  "properties": {
    "iso:country":"AU",
    "name:ceb_x_preferred":[
        "Wedge Island"
    ],
    "name:deu_x_preferred":[
        "Wedge Island"
    ],
    "name:pol_x_preferred":[
        "Wedge Island"
    ],
    "name:swe_x_preferred":[
        "Wedge Island"
    ],
    "qs_pg:aaroncc":"AU",
    "qs_pg:name":"Wedge Island",
    "qs_pg:name_adm0":"Australia",
    "qs_pg:name_adm1":"Western Australia",
    "qs_pg:photos":67,
    "qs_pg:photos_1k":14,
    "qs_pg:photos_9k":1,
    "qs_pg:photos_9r":2,
    "qs_pg:photos_all":67,
    "qs_pg:photos_sr":2,
    "qs_pg:pop_sr":0,
    "qs_pg:qs_pg_placetype":"locality",
    "qs_pg:qs_pg_placetype_gp":"Town",
    "qs_pg:woe_adm0":23424748,
    "woe:adm0_id":23424748,
    "woe:name_adm0":"Australia",
    "woe:name_adm1":"Western Australia",
    "woe:placetype":"Town",
    "wof:name":"Wedge Island",
    "wof:placetype":"locality",
    "wof:population":32
},
  "geometry": {"coordinates":[115.207443,-30.817346],"type":"Point"}
}